Workbook

Sheet 样例及说明
A1: 1、根据控制要求与措施逐条落实责任部门、责任岗位、岗位职责，（对应形成岗位清单）
A2: 2、根据控制措施细化线上、系统已建和系统未建，对于线下的应明确线下监督措施及频率，对于线上的应明确控制系统名称、功能模块名称、稽核规则，其中系统已有的补充操作路径及优化建议，系统未建的补充建设需求（形成系统规则清单）
A3: 3、将控制措施按照不相容岗位、分级授权等分类细化补充至具体分类中，其中不相容控制的需要明确不相容岗位名称及职责（形成不相容岗位清单），涉及多个不相容岗位的逐条列示；分级授权的需要明确分级授权流程；业务真实性校验、预算、合同、收支等控制的，明确控制措施。该关键节点的控制措施合计应与《典设》矩阵打勾保持一致。
A4: 4、H列的内控载体与该条控制措施一一对应，并与AT-AV列业务自评价的评价资料保持一致。
A5: 5、Z、AA列对具体制度进行完善补充。
A6: 6、AT-AV列需要明确业务自评价的样本抽取比例、评价资料和评价要点，其中评价资料与H列内控载体需保持一致。
A7: 附件2（样表） | D7: 营销 | E7: 83 | F7: 财务 | G7: 20
A8: 风控矩阵适用性验证模板
A9: 业务条线 | B9: 业务领域 | C9: 控制目标 | D9: 业务流程步骤 | E9: 经营风险 | F9: 对应屡查屡犯问题清单 | G9: 关键控制点 | H9: 控制要求与措施 | I9: 责任层级和主体 | R9: 控制方式 | S9: 线上控制系统 | Y9: 线下人工控制 | Z9: 制度修订建议 | AB9: 不相容岗位 | AD9: 分级授权流程 | AF9: 业务真实性校验措施 | AH9: 预算管控措施 | AJ9: 合同控制措施 | AL9: 收付控制措施 | AN9: 会计监督 | AP9: 财产保护 | AR9: 分析与评价 | AT9: 业务自评价及集团监督评价 | AW9: 备注 （对矩阵内容的修改意见）
I10: 省公司责任部门 | J10: 省公司责任处室及岗位 | K10: 省公司岗位职责 | L10: 市公司责任部门 | M10: 市公司责任岗位 | N10: 市公司岗位职责 | O10: 县公司责任部门 | P10: 县公司责任岗位 | Q10: 县公司岗位职责 | R10: 措施分类（系统已有、系统待建或线下） | S10: 控制系统名称 | T10: 模块名称 | U10: 稽核规则 | V10: 如已建，操作路径 | W10: 如已建，有何优化建议 | X10: 如未建，有何建设需求 | Y10: 线下监督措施-频次、措施 | Z10: 制度名称 | AA10: 制度修订建议 | AB10: 是否涉及 | AC10: 不相容岗位名称及职责 | AD10: 是否涉及 | AE10: 分级授权流程 | AF10: 是否涉及 | AG10: 业务真实性校验措施 | AH10: 是否涉及 | AI10: 预算管控措施 | AJ10: 是否涉及 | AK10: 合同控制措施 | AL10: 是否涉及 | AM10: 收付控制措施 | AN10: 是否涉及 | AO10: 会计监督措施 | AP10: 是否涉及 | AQ10: 财产保护措施 | AR10: 是否涉及 | AS10: 分析与评价措施 | AT10: 样本抽取比例 | AU10: 评价资料 | AV10: 评价要点
A11: 营销售电 | B11: 七、营销退费管理 | C11: 资金资产安全 | D11: 退费审批 | E11: 退费未经有效审核审批，导致公司资金流失、财务数据失真风险。 | F11: 20.营销系统权限管控不严。 | G11: 29.退费审批权限及流程设置 | H11: 控制要求：退费资金分级授权科学、合理。 控制措施： 1.财务部建立电费退费资金分级授权审批机制，确保系统流程轨迹可视、授权管理科学；（系统-已有） 内控载体： 1.资金分级授权。 | I11: 财务部 | J11: 稽核处-风险内控与稽核评价管理；电价处-输配与销售电价管理 | K11: 1.风险内控与稽核评价管理负责内控体系建设与运行；组织开展内控评价及报告编制工作；负责运用数智风控系统开展风险穿透管控。 2.输配与销售电价管理负责销售电价及售电收入、上网电价及价外资金、政策性收费；负责分用户类别和电能类型对售电业务进行记录与反映；负责售电业务报表编制，负责配合完成成本监审相关工作。 | L11: 财务部 | M11: 风险内控管理；价格管理 | N11: 1.风险内控管理负责内控体系建设与运行；负责运用数智风控系统开展风险穿透管控。 2.价格管理负责销售电价及售电收入、上网电价及价外资金、政策性收费；负责分用户类别和电能类型对售电业务进行记录与反映；负责售电业务报表编制。 | O11: 财务部 | P11: 价格管理 | Q11: 价格管理负责销售电价及售电收入、上网电价及购电费、价外资金、政策性收费等管理。 | R11: 系统已有 | S11: 智慧财务 | T11: 营销退费 | U11: 按照付款信息完整性审核规则，用于检查电费退费付款信息是否完整。 | V11: 购售电结算管理-营销退费 | W11: 检查付款申请单中资金支付流程是否满足资金分级授权，若否，则为疑点。 | X11: - | Y11: - | AB11: 否 | AD11: 是 | AE11: 5万元以下，执行归口管理负责人、业务经办负责人审批；5万元及以上，执行分管业务领导、财务部负责人、归口管理负责人、业务经办负责人审批。 | AF11: 否 | AH11: 否 | AJ11: 否 | AL11: 否 | AN11: 否 | AP11: 否 | AR11: 否 | AU11: 资金分级授权 | AV11: 检查是否建立资金分级授权标准，标准是否统一，授权额度是否设置合理。
H12: 控制要求：退费审批流程设置应科学、合理，与资金分级授权匹配。 控制措施： 2.营销部按照资金分级授权建立内部退费审批流程（系统-已有），对权限配置与岗位权限一致性进行校核。（系统-待建） 内控载体： 1.系统退费审批单； 2.资金分级授权； 3.岗位权限配置； 4.退费影像。 | I12: 营销部 | J12: 营业处-电费电价管理 | K12: 负责组织开展结算依据核对，负责采抄一体、智能核算、自动发行、智能催费、自动对账、智能交费等技术研究与推广应用，负责多元交费渠道的建设运营；负责管理本省集团户、电费充值卡等业务；负责电费回收管理，建立本省电费回收风险防控体系，指导、监督下属各单位开展电费回收及电费风险防控工作，组织本省重大电费结算问题与欠费风险处置；负责第三方代收机构和支付平台渠道管理。 | L12: 营销部 | M12: 电费及电价管理 | N12: 负责电费回收管理；电费账务管理；处理客户投诉及意见；协助省公司营销部开展售电侧市场机制适应性研究、宣贯培训及咨询答复等。 | O12: 营销部 | P12: 电价及电费管理 | Q12: 负责电费回收管理；电费账务管理；处理客户投诉及意见等。 | R12: 系统待建 | S12: 营销2.0系统 | T12: 计费结算-收费管理-退费管理 | U12: 1.电费频繁性退费（规则描述:电费频繁退费，每月筛查营销业务所有用电客户发生2次及以上电费退费情况的用电客户，并进行稽查监控。 取数时间范围：上一自然月，即上月1日0点（含0点）至本月1日0点（不含0点）。）； 2）已销户未退费（规则描述:已销户未退费，每月筛查营销业务中销户归档日期已超3个月（销户流程归档时间在山东营销2.0系统上线时间之后，即2022年11月15日后）且账户余额大于0元的用电客户，并进行稽查监控。） | V12: - | W12: - | X12: 建议与人资2.0系统进行一致性校核。 | Z12: 《国家电网有限公司电费业务管理办法（征求意见稿）》 | AA12: 建议明确分级审批要求“退费申请、审核审批履行不相容控制，确保流程权限设置科学、合规” | AB12: 是 | AC12: 营业厅综合柜收-退费申请；电费管理岗-退费审核；供电所长/营业班长、电费专工/电费管理班长、营销部分管主任、公司分管领导-退费审批 | AD12: 是 | AE12: 1.500元以下，执行电费账务人员、供电所长/营业班长两级审批； 2.500元及以上、5000元以下，执行电费账务人员、供电所长/营业班长、电费专工/电费管控班三级审批； 3.5000元及以上、5万元以下，执行电费账务人员、供电所长/营业班长、电费专工/电费管控班、营销部分管主任四级审批； 4.5万元及以上，执行电费账务人员、供电所长/营业班长、电费专工/电费管控班、营销部分管主任、公司分管领导五级审批 | AF12: 否 | AH12: 否 | AJ12: 否 | AL12: 是 | AM12: 按照资金分级授权建立内部退费审批流程，对权限配置与岗位权限一致性进行校核 | AN12: 否 | AP12: 否 | AR12: 否 | AT12: 5万元及以上抽取10%，5万元以下抽取1% | AU12: 1.系统退费审批单； 2.资金分级授权； 3.岗位权限配置； 4.退费影像 | AV12: 1.检查退费分级授权是否符合资金分级授权标准；2.检查退费分级授权流程设置是否符合人资部岗位配置。

Sheet 营销售电（省公司审定0818）
A1: 风控矩阵-营销售电业务
A2: 业务条线 | B2: 业务领域 | C2: 控制目标 | D2: 业务流程步骤 | E2: 经营风险 | F2: 典型问题 | G2: 关键控制点 | H2: 控制要求 | I2: 控制措施编号 | J2: 控制措施 | K2: 控制措施分类 | T2: 控制方式 | U2: 控制系统 | V2: 控制载体 | W2: 责任主体 | X2: 业务自评价 | AA2: 集团监督评价 | AD2: 数字化监督场景 | AH2: 现有制度及文件落实情况 | AK2: 总部审核部门 | AL2: 层级 | AM2: 专业 | AN2: 是否适用
K3: 不相容岗位 | L3: 分级授权 | M3: 业务真实性控制 | N3: 预算管控 | O3: 合同控制 | P3: 收付控制 | Q3: 会计监督 | R3: 财产保护 | S3: 分析与评价 | X3: 评价频率 | Y3: 评价范围 | Z3: 评价结论 | AA3: 评价频率 | AB3: 评价范围 | AC3: 评价结论 | AD3: 数字化监督场景 | AE3: 监督频率 | AF3: 监督范围 | AG3: 评价结论 | AH3: 是否已要求 | AI3: 是否满足要求 | AJ3: 对应制度及文件名称
A4: 营销售电业务 | B4: 一、客户信息与合同签订管理 | C4: 会计信息真实完整、资金资产安全 | D4: 业扩报装受理 | E4: 客户信息录入不准确，与现场不一致，引发虚假立户及电费收取不规范风险。 | F4: 19.两部制电价执行不正确：存在应执行未执行两部制电价、分户报装规避两部制电价、变更用电少收基本电费、需量基本电费计收不准确等问题。 | G4: 1.系统客户信息创建 | H4: 系统客户信息应与客户报装资料、现场用电情况一致。 | I4: 营销售电业务-1.系统客户信息创建-控制措施01 | J4: 营销部门业务受理人员根据客户报装资料做好系统客户信息的创建，并对报装资料完整性、有效性负责。 | M4: √ | T4: 线下管控 | V4: 1.系统业扩工单； 2.客户报装原始资料； 3.系统客户档案 | W4: 各级单位供电公司-营销部门-业务受理人员 | X4: 每年 | Y4: 抽查 | AA4: 年度 | AB4: 抽查 | AH4: 是 | AI4: 是 | AJ4: 《国家电网有限公司业扩报装管理规则（征求意见稿）》第三章 业务受理 | AK4: 国网营销部 | AL4: 地市 | AM4: 业扩
I5: 营销售电业务-1.系统客户信息创建-控制措施02 | J5: 营销部门应在客户新装、增容、变更用电等申请受理时，建立稽查主题前置业务环节等数智审核功能，提高客户基础信息创建质量。 | M5: √ | T5: 系统待建 | U5: 营销2.0系统 | V5: 1.系统客户档案； 2.客户报装原始资料； 3.数智审核相关功能资料 | W5: 各省（自治区、直辖市）电力公司供服中心-营销部门-业扩报装管理人员 | X5: 每年 | Y5: 抽查 | AA5: 年度 | AB5: 抽查 | AH5: 是 | AI5: 是 | AJ5: 《国家电网有限公司业扩报装管理规则（征求意见稿）》第三章 业务受理 | AK5: 国网营销部 | AL5: 供服 | AM5: 业扩
I6: 营销售电业务-1.系统客户信息创建-控制措施03 | J6: 营销部门业务办理人员结合现场勘查情况对客户关键信息真实性、准确性复核，业务受理与业务办理执行不相容控制。 | K6: √ | M6: √ | T6: 线下管控 | V6: 1.系统业扩工单； 2.客户报装原始资料； 3.系统客户档案； 4.系统授权审批记录 | W6: 各级单位供电公司-营销部门-业务办理人员 | X6: 每年 | Y6: 抽查 | AA6: 年度 | AB6: 抽查 | AH6: 是 | AI6: 是 | AJ6: 《国家电网有限公司业扩报装管理规则（征求意见稿）》第三章 业务受理 | AK6: 国网营销部 | AL6: 地市 | AM6: 业扩
I7: 营销售电业务-1.系统客户信息创建-控制措施04 | J7: 营销部门对分户报装规避基本电费、违规改变用电性质等开展数字化在线监督与现场检查。 | M7: √ | S7: √ | T7: 系统已建 | U7: 营销2.0系统 | V7: 数字化监督相关资料或稽查工单及处理情况 | W7: 各级单位供电公司-营销部门-业务审核人员 | X7: 每半年 | Y7: 抽查 | AA7: 年度 | AB7: 抽查 | AD7: 分户报装规避基本电费监督——对一址多户开展在线监督 | AE7: 每季度 | AF7: 全量 | AH7: 是 | AI7: 是 | AJ7: 《国家电网有限公司业扩报装管理规则（征求意见稿）》第三章 业务受理 | AK7: 国网营销部 | AL7: 地市 | AM7: 业扩
C8: 会计信息真实完整、资金资产安全 | D8: 方案答复与工程实施 | E8: 客户用电容量核定不准确、录入错误，导致基本电费执行不准确、电费少收。 | F8: 19.两部制电价执行不正确：存在应执行未执行两部制电价、分户报装规避两部制电价、变更用电少收基本电费、需量基本电费计收不准确等问题。 | G8: 2.客户用电容量的确定 | H8: 系统容量与现场用电情况保持一致。 | I8: 营销售电业务-2.客户用电容量的确定创建-控制措施01 | J8: 营销部门现场勘查人员应准确核定客户用电容量与负荷性质，确保计量、计费方案、供电方式等准确。 | M8: √ | T8: 线下管控 | V8: 1.系统业扩工单（现场勘查验收单）； 2.系统客户档案（供电方案等） | W8: 各级单位供电公司-营销部门-现场勘查人员 | X8: 每年 | Y8: 抽查 | AA8: 年度 | AB8: 抽查 | AH8: 是 | AI8: 是 | AJ8: 《国家电网有限公司业扩报装管理规则（征求意见稿）》第四章 供电方案编制及答复 | AK8: 国网营销部 | AL8: 地市 | AM8: 业扩
I9: 营销售电业务-2.客户用电容量的确定创建-控制措施02 | J9: 对于加装变压器的高压客户，需取得变压器出厂合格证明及型式试验报告等容量信息佐证材料并上传系统，确保系统录入容量与现场用电情况一致。 | M9: √ | T9: 系统已建 | U9: 营销2.0系统 | V9: 1.系统业扩工单信息（现场勘查验收单）； 2.客户报装原始资料（含用电负荷清单、变压器出厂合格证明及型式试验报告等）； 3.系统客户档案 | W9: 各级单位供电公司-营销部门-业务办理人员 | X9: 每半年 | Y9: 抽查 | AA9: 年度 | AB9: 抽查 | AH9: 是 | AI9: 是 | AJ9: 《国家电网有限公司业扩报装管理规则（征求意见稿）》第四章 供电方案编制及答复 | AK9: 国网营销部 | AL9: 地市 | AM9: 业扩
I10: 营销售电业务-2.客户用电容量的确定创建-控制措施03 | J10: 营销部门对超容用电、基本电费异常、高可靠性供电费收取不规范开展数字化在线监督与现场检查。 | M10: √ | S10: √ | T10: 系统已建 | U10: 营销2.0系统 | V10: 数字化监督相关资料或稽查结果与处理情况 | W10: 各级单位供电公司-营销部门-业务审核人员 | X10: 每半年 | Y10: 抽查 | AA10: 年度 | AB10: 抽查 | AD10: 客户容量与电量联动监测——对超容用电、基本电费异常、高可靠性供电费收取不规范开展在线监督 | AE10: 每季度 | AF10: 全量 | AH10: 是 | AI10: 是 | AJ10: 《国家电网有限公司业扩报装管理规则（征求意见稿）》第四章 供电方案编制及答复 | AK10: 国网营销部 | AL10: 地市 | AM10: 业扩
A11: 营销售电业务 | B11: 一、客户信息与合同签订管理 | C11: 会计信息真实完整、资金资产安全 | D11: 客户信息变更 | E11: 客户信息变更不合规，导致电费计收不准确，引发合规风险。 | F11: 19.两部制电价执行不正确：存在应执行未执行两部制电价、分户报装规避两部制电价、变更用电少收基本电费、需量基本电费计收不准确等问题。 | G11: 3.系统客户信息变更 | H11: 客户关键信息变更应结合业务工单联动调整，严禁无业务动因创建或修改客户信息行为。 | I11: 营销售电业务-3.系统客户信息变更-控制措施01 | J11: 营销部门对客户户名、电价、用电容量等关键信息的变更，应结合变更业务联动调整并经审批后实施。 | L11: √ | M11: √ | T11: 系统已建 | U11: 营销2.0系统 | V11: 1.系统变更工单； 2.客户变更原始资料； 3.系统客户档案； 4.系统授权审批记录 | W11: 各级单位供电公司-营销部门-业务审核及各级审批人员 | X11: 每年 | Y11: 抽查 | AA11: 年度 | AB11: 抽查 | AH11: 是 | AI11: 是 | AJ11: 《变更用电业务规则（试行）》 | AK11: 国网营销部 | AL11: 地市 | AM11: 业扩
I12: 营销售电业务-3.系统客户信息变更-控制措施02 | J12: 营销部门对影响价费关键信息的变更业务开展现场查验，确保用电信息与现场一致。 | M12: √ | T12: 线下管控 | V12: 现场核查相关记录 | W12: 各级单位供电公司-营销部门-现场勘查人员 | X12: 每年 | Y12: 抽查 | AA12: 年度 | AB12: 抽查 | AH12: 是 | AI12: 是 | AJ12: 《变更用电业务规则（试行）》 | AK12: 国网营销部 | AL12: 地市 | AM12: 业扩
C13: 会计信息真实完整、资金资产安全 | D13: 合同签订 | E13: 合同签订未使用公司统一且生效文本，导致电费计收合法权益无法得到保障。 | G13: 4.供用电合同签订 | H13: 供用电合同签订应使用公司统一且生效的文本。 | I13: 营销售电业务-4.供用电合同签订-控制措施01 | J13: 国网营销部统一管理合同文本，并明确执行要求、生效时间，及客户业务变更时不需重签合同的业务类型。各省（自治区、直辖市）电力公司参考统一文本拟定本单位合同文本、特别约定事项等，经法律合规部门审核后使用。 | O13: √ | T13: 系统已建 | U13: 营销2.0系统 | V13: 1.合同统一文本； 2.制度或通知 | W13: 国网营销部-合同管理人员；各省（自治区、直辖市）电力公司省公司-营销部门-合同管理人员 | X13: 每年 | Y13: 抽查 | AA13: 年度 | AB13: 抽查 | AH13: 是 | AI13: 是 | AJ13: 《国家电网有限公司电费业务管理办法（征求意见稿）》第四章 合同协议 《国网营销部关于印发变更用电业务规则》 《国家电网有限公司业扩报装管理规则（征求意见稿）》第六十三、六十四条 《国家电网有限公司合同管理办法》四十六条、六十四-六十六条 | AK13: 国网营销部 | AL13: 省公司 | AM13: 业扩
I14: 营销售电业务-4.供用电合同签订-控制措施02 | J14: 营销部门合同签订人员应严格使用本省统一且生效文本。 | O14: √ | T14: 系统已建 | U14: 营销2.0系统 | V14: 1.供用电合同； 2.合同统一文本 | W14: 各级单位供电公司-营销部门-合同签订人员 | X14: 每年 | Y14: 抽查 | AA14: 年度 | AB14: 抽查 | AH14: 是 | AI14: 是 | AJ14: 《国家电网有限公司电费业务管理办法（征求意见稿）》第四章 合同协议 《国家电网有限公司业扩报装管理规则（征求意见稿）》第六十三条 | AK14: 国网营销部 | AL14: 地市 | AM14: 业扩
I15: 营销售电业务-4.供用电合同签订-控制措施03 | J15: 营销部门合同审核人员对合同文本使用情况开展审核。 | M15: √ | T15: 线下管控 | V15: 1.供用电合同； 2.合同统一文本； 3.系统合同信息； 4.系统合同签订及审批记录 | W15: 各级单位供电公司-营销部门-合同审核人员 | X15: 每年 | Y15: 抽查 | AA15: 年度 | AB15: 抽查 | AH15: 是 | AI15: 是 | AJ15: 《国家电网有限公司电费业务管理办法（征求意见稿）》第四章 合同协议 《国家电网有限公司业扩报装管理规则（征求意见稿）》第六十四条 | AK15: 国网营销部 | AL15: 地市 | AM15: 业扩
C16: 会计信息真实完整、资金资产安全 | D16: 合同签订 | E16: 合同条款与客户报装信息、现场不一致，导致公司收支条款失效，合法权益无法得到保障。 | G16: 5.供用电合同审核 | H16: 合同关键信息与客户报装信息保持一致。 | I16: 营销售电业务-5.供用电合同审核-控制措施01 | J16: 营销部门合同签订人员要确保合同信息与业扩报装产生的客户信息保持一致，不得变更。 | M16: √ | O16: √ | T16: 线下管控 | V16: 1.供用电合同信息； 2.系统客户信息 | W16: 各级单位供电公司-营销部门-合同签订人员 | X16: 每年 | Y16: 抽查 | AA16: 年度 | AB16: 抽查 | AH16: 是 | AI16: 是 | AJ16: 《国家电网有限公司电费业务管理办法（征求意见稿）》第四章 合同协议第二十六条 | AK16: 国网营销部 | AL16: 地市 | AM16: 业扩
I17: 营销售电业务-5.供用电合同审核-控制措施02 | J17: 营销部门合同审核人员对合同信息与业扩报装产生的信息一致性进行复核。 | M17: √ | O17: √ | T17: 线下管控 | V17: 1.供用电合同信息； 2.系统客户信息； 3.合同审核记录 | W17: 各级单位供电公司-营销部门-合同审核人员 | X17: 每年 | Y17: 抽查 | AA17: 年度 | AB17: 抽查 | AH17: 是 | AI17: 是 | AJ17: 《国家电网有限公司电费业务管理办法（征求意见稿）》第四章 合同协议 | AK17: 国网营销部 | AL17: 地市 | AM17: 业扩
I18: 营销售电业务-5.供用电合同审核-控制措施03 | J18: 营销部门合同管理人员应落实合同签订一致性要求，加强系统上传合同与线下纸质合同一致性管控。 | O18: √ | T18: 线下管控 | U18: 营销2.0系统 | V18: 1.供用电合同（线下）； 2.系统合同信息 | W18: 各级单位供电公司-营销部门-合同管理人员 | X18: 每年 | Y18: 抽查 | AA18: 年度 | AB18: 抽查 | AH18: 是 | AI18: 是 | AJ18: 《国家电网有限公司电费业务管理办法（征求意见稿）》第四章 合同协议 《国家电网有限公司业扩报装管理规则（征求意见稿）》第六十五条 | AK18: 国网营销部 | AL18: 地市 | AM18: 业扩
I19: 营销售电业务-5.供用电合同审核-控制措施04 | J19: 营销部门对系统合同上传及生效情况开展稽查监督。 | S19: √ | T19: 系统已建 | U19: 营销2.0系统 | V19: 数字化监督相关资料或稽查工单及处理情况 | W19: 各级单位供电公司-营销部门-合同管理人员 | X19: 每 半年 | Y19: 抽查 | AA19: 年度 | AB19: 抽查 | AH19: 是 | AI19: 是 | AJ19: 《国家电网有限公司电费业务管理办法（征求意见稿）》第四章 合同协议 《国家电网有限公司业扩报装管理规则（征求意见稿）》第六十五条 | AK19: 国网营销部 | AL19: 地市 | AM19: 业扩
A20: 营销售电业务 | B20: 二、电价执行管理 | C20: 会计信息真实完整、资金资产安全 | D20: 电价码制定 | E20: 电价政策执行不到位，系统配置不准确，导致公司电费收入计量不准确、不合规。 | G20: 6.电价码制定与执行 | H20: 电价标准与政策匹配，电价码准确配置与执行 | I20: 营销售电业务-6.电价码制定与执行-控制措施01 | J20: 电价码管理实行“统一管理、分级维护”原则，按照统一标准规范执行。财务部门负责根据国家或省内价格政策，对照标准化电价码编码规则，解析形成每类客户电价执行标准，将政策解析与电价码关联结果推送营销。 | M20: √ | Q20: √ | T20: 系统已建 | U20: 智慧财务 | V20: 1.电价政策文件； 2.政策解析结果 | W20: 国网财务部-销售电价管理人员；各省（自治区、直辖市）电力公司省公司-财务部门-销售电价管理人员 | X20: 每年 | Y20: 抽查 | AA20: 年度 | AB20: 抽查 | AH20: 是 | AI20: 是 | AJ20: 《国网营销部国网财务部国网数字化部关于加快标准化电价码部署应用的通知》（营销营业〔2025〕83号） | AK20: 国网财务部 | AL20: 省公司 | AM20: 电价、财务
I21: 营销售电业务-6.电价码制定与执行-控制措施02 | J21: 营销部门基于电价标准及政策依据匹配形成电价码调整方案，审批后推送智慧财务，经财务部门审核（新增电价码需总部审批）后下发执行。电价码的维护申请、审核、审批、确认均执行线上流转。 | M21: √ | Q21: √ | T21: 系统已建 | U21: 营销2.0系统、智慧财务 | V21: 1.电价标准与电价码匹配记录； 2.电价码调整方案； 3.电价码审核审批记录 | W21: 国网财务部-销售电价管理人员；各省（自治区、直辖市）电力公司省公司-营销部门-电价管理人员；各省（自治区、直辖市）电力公司省公司-财务部门-销售电价管理人员 | X21: 每年 | Y21: 抽查 | AA21: 年度 | AB21: 抽查 | AH21: 是 | AI21: 是 | AJ21: 《国网营销部国网财务部国网数字化部关于加快标准化电价码部署应用的通知》（营销营业〔2025〕83号） | AK21: 国网营销部、国网财务部 | AL21: 省公司 | AM21: 电价
I22: 营销售电业务-6.电价码制定与执行-控制措施03 | J22: 营销部门将电价码部署系统并建立电价码与用户档案信息关联关系，确保电价码精准匹配到户。 | M22: √ | T22: 系统已建 | U22: 营销2.0系统 | V22: 1.电价码与用户档案信息关联关系； 2.电价码系统配置记录 | W22: 各省（自治区、直辖市）电力公司省公司-营销部门-电价管理人员 | X22: 每年 | Y22: 抽查 | AA22: 年度 | AB22: 抽查 | AH22: 是 | AI22: 是 | AJ22: 《国网营销部国网财务部国网数字化部关于加快标准化电价码部署应用的通知》（营销营业〔2025〕83号） | AK22: 国网营销部 | AL22: 省公司 | AM22: 电价
I23: 营销售电业务-6.电价码制定与执行-控制措施04 | J23: 营销部门协同财务部门对电价码配置与价码执行情况开展数字化校核及在线监控分析。 | S23: √ | T23: 系统待建 | U23: 营销2.0系统 | V23: 1.电价码执行情况记录； 2.电价码统计分析功能及优惠电价执行预警等功能相关记录； 3.标准化电价码智能校核规则库； 4.数字化监督相关资料或稽查工单及处理情况 | W23: 各省（自治区、直辖市）电力公司省公司-营销部门-电价管理人员；各省（自治区、直辖市）电力公司省公司-财务部门-销售电价管理人员 | X23: 每半年 | Y23: 抽查 | AA23: 年度 | AB23: 抽查 | AD23: 电价码执行监督——对电价码配置与执行情况开展在线监督 | AE23: 每季度 | AF23: 全量 | AH23: 是 | AI23: 是 | AJ23: 《国网营销部国网财务部国网数字化部关于加快标准化电价码部署应用的通知》（营销营业〔2025〕83号） | AK23: 国网营销部、国网财务部 | AL23: 省公司 | AM23: 电价
C24: 会计信息真实完整、资金资产安全 | D24: 电价执行 | E24: 电价执行与客户用电性质不匹配，造成公司或用户电费资金损失，收入不实 | F24: 19.两部制电价执行不正确：存在应执行未执行两部制电价、分户报装规避两部制电价、变更用电少收基本电费、需量基本电费计收不准确等问题。 | G24: 7.客户电价执行管控 | H24: 客户电价执行与用电性质、行业类别等精准匹配 | I24: 营销售电业务-7.客户电价执行管控-控制措施01 | J24: 营销部门业务受理人员应严格按照客户用电性质、行业类别等匹配执行标准电价码并准确录入系统，经审核后生效。 | M24: √ | T24: 系统已建 | U24: 营销2.0系统 | V24: 1.系统业务工单记录； 2.系统客户电价信息 | W24: 各级单位供电公司-营销部门-业务受理、业务审核人员 | X24: 每半年 | Y24: 抽查 | AA24: 年度 | AB24: 抽查 | AH24: 是 | AI24: 是 | AJ24: 《国家电网有限公司电费业务管理办法（征求意见稿）》第三章 电价执行 | AK24: 国网营销部 | AL24: 地市 | AM24: 业扩
I25: 营销售电业务-7.客户电价执行管控-控制措施02 | J25: 营销部门加强客户电价变更管理，对于电价政策变动导致的电价变更应结合电价码联动调整，对于客户用电性质改变导致的电价变更应严格执行与工单关联，其他类型电价变更严格执行授权审批后进行调整。 | M25: √ | T25: 系统已建 | U25: 营销2.0系统 | V25: 系统业务工单记录 | W25: 各级单位供电公司-营销部门-电价管理人员 | X25: 每半年 | Y25: 抽查 | AA25: 年度 | AB25: 抽查 | AH25: 是 | AI25: 是 | AJ25: 《国家电网有限公司电费业务管理办法（征求意见稿）》第三章 电价执行 | AK25: 国网营销部 | AL25: 地市 | AM25: 电价
I26: 营销售电业务-7.客户电价执行管控-控制措施03 | J26: 营销部门对客户电价执行及变更情况开展数字化在线监督。 | M26: √ | S26: √ | T26: 系统已建 | U26: 营销2.0系统 电价执行辅助管理模块 | V26: 数字化监督相关资料或稽查工单及处理情况 | W26: 各级单位供服中心、供电公司-营销部门-电价管理人员 | X26: 每半年 | Y26: 抽查 | AA26: 年度 | AB26: 抽查 | AD26: 客户电价执行监督——对客户电价执行及变更开展在线监督 | AE26: 每季度 | AF26: 全量 | AH26: 是 | AI26: 是 | AJ26: 《国家电网有限公司电费业务管理办法（征求意见稿）》第三章 电价执行 国网湖南电力营销部关于印发电价执行管理规范指引的通知)（营销〔2025〕5号） | AK26: 国网营销部 | AL26: 供服、地市 | AM26: 电价
A27: 营销售电业务 | B27: 三、电量采集管理 | C27: 会计信息真实完整 | D27: 电量采集 | E27: 未严格执行采集策略，导致电量计量失真。 | G27: 8.采集规则配置 | H27: 电能表示数采集策略应纳入统一管理 | I27: 营销售电业务-8.采集规则配置-控制措施01 | J27: 营销部门要建立电能表示数采集策略统一管理机制，强化规则配置与实施管理。 | M27: √ | T27: 系统已建 | U27: 新一代用电信息采集系统 | V27: 电能表采集数据 | W27: 各省（自治区、直辖市）电力公司供服中心-营销部门-计量管理人员 | X27: 每年 | Y27: 抽查 | AA27: 年度 | AB27: 抽查 | AH27: 是 | AI27: 是 | AJ27: 《国家电网有限公司电费业务管理办法（征求意见稿）》第五章 采集抄表 | AK27: 国网营销部 | AL27: 供服 | AM27: 计量
I28: 营销售电业务-8.采集规则配置-控制措施02 | J28: 营销部门对电能表示数采集策略执行情况开展复核与监督。 | M28: √ | T28: 系统已建 | U28: 新一代用电信息采集系统 | V28: 电能表参数任务 | W28: 各省（自治区、直辖市）电力公司供服中心-营销部门-计量管理复核人员 | X28: 每年 | Y28: 抽查 | AA28: 年度 | AB28: 抽查 | AH28: 是 | AI28: 是 | AJ28: 《国家电网有限公司电费业务管理办法（征求意见稿）》第五章 采集抄表 | AK28: 国网营销部 | AL28: 供服 | AM28: 计量
C29: 会计信息真实完整 | D29: 电量采集 | E29: 电量采集范围不完整、抄表周期不准确，导致电费收入未可靠计量。 | G29: 9.电能表示数采集 | H29: 电能表示数采集应规范完整、应抄尽抄 | I29: 营销售电业务-9.电能表示数采集-控制措施01 | J29: 电能表示数采集应由用电信息采集系统统一出口，采集范围应完整。 | M29: √ | T29: 系统已建 | U29: 新一代用电信息采集系统 | V29: 1.电能表采集数据； 2.电能表抄表工单 | W29: 各省（自治区、直辖市）电力公司供服中心-营销部门-计量管理人员 | X29: 每 半年 | Y29: 抽查 | AA29: 年度 | AB29: 抽查 | AH29: 是 | AI29: 是 | AJ29: 《国家电网有限公司电费业务管理办法（征求意见稿）》第五章 采集抄表 | AK29: 国网营销部 | AL29: 供服 | AM29: 计量
I30: 营销售电业务-9.电能表示数采集-控制措施02 | J30: 营销部门对全量用户抄表完整性开展在线监控。 | S30: √ | T30: 系统已建 | U30: 新一代用电信息采集系统、营销2.0系统 | V30: 1.电能表采集数据； 2.电能表抄表工单 | W30: 各级单位供服中心-营销部门-计量（抄表）管理/电费电价管理人员 | X30: 每季度 | Y30: 抽查 | AA30: 年度 | AB30: 抽查 | AD30: 应抄未抄监督——对全量用户抄表完整性开展在线监控 | AE30: 每月 | AF30: 全量 | AH30: 是 | AI30: 是 | AJ30: 《国家电网有限公司电费业务管理办法（征求意见稿）》第五章 采集抄表 | AK30: 国网营销部 | AL30: 供服 | AM30: 计量
I31: 营销售电业务-9.电能表示数采集-控制措施03 | J31: 营销部门严格抄表周期管理，以自然月为周期对全体用户进行抄表，抄表周期调整履行严格审批程序。 | M31: √ | T31: 系统已建 | U31: 营销2.0系统 | V31: 1.电能表采集数据； 2.电能表抄表工单； 3.应参与本次抄表算费全量客户抄表信息、实际参与本次抄表算费全量客户抄表信息 | W31: 各级单位省公司、供服中心、供电公司-营销部门-计量（抄表）管理/电费电价管理人员 | X31: 每 半年 | Y31: 抽查 | AA31: 年度 | AB31: 抽查 | AH31: 是 | AI31: 是 | AJ31: 《国家电网有限公司电费业务管理办法（征求意见稿）》第五章 采集抄表 | AK31: 国网营销部 | AL31: 省公司、供服、地市 | AM31: 计量、抄表、电费核算
I32: 营销售电业务-9.电能表示数采集-控制措施04 | J32: 营销部门应结合当地市场规则及电费结算相关协议确定月内抄表频次。 | M32: √ | T32: 线下管控 | V32: 市场规则及相关文件 | W32: 各省（自治区、直辖市）电力公司省公司、供服中心、供电公司-营销部门-电费电价（抄表）管理人员 | X32: 每 半年 | Y32: 抽查 | AA32: 年度 | AB32: 抽查 | AH32: 是 | AI32: 是 | AJ32: 《国家电网有限公司电费业务管理办法（征求意见稿）》第五章 采集抄表 | AK32: 国网营销部 | AL32: 省公司、供服、地市 | AM32: 计量、抄表、电费核算
C33: 会计信息真实完整 | D33: 电量采集 | E33: 抄表结果异常，导致电费计算失真。 | F33: 20.营销系统权限管控不严：存在重要业务流程权限设置不合规；电费收费、账务处理、财务审核和违约用电查处、审批等不相容岗位未分离；信息系统权限未严格落实实名制，账号权限与实际权责不符、一人存在多个账号等问题。 | G33: 10.电量采集结果确认 | H33: 电量采集结果应完整、准确 | I33: 营销售电业务-10.电量采集结果确认-控制措施01 | J33: 营销部门建立电量采集结果集中复核机制，健全复核规则，异常事项消缺纳入在线管控。 | M33: √ | T33: 系统已建 | U33: 营销2.0系统 | V33: 电能表采集数据 | W33: 各省（自治区、直辖市）电力公司省公司、供服中心、供电公司-营销部门-计量（抄表）管理人员 | X33: 每年 | Y33: 抽查 | AA33: 年度 | AB33: 抽查 | AH33: 是 | AI33: 是 | AJ33: 《国家电网有限公司电费业务管理办法（征求意见稿）》第五章 采集抄表 | AK33: 国网营销部 | AL33: 省公司、供服、地市 | AM33: 计量、营业
I34: 营销售电业务-10.电量采集结果确认-控制措施02 | J34: 营销部门对抄表异常事项消缺实行工单化管理，对不影响量费调整的异常事项消缺，执行本级确认后闭环。对影响量费调整的异常事项消缺，执行分级授权审批机制。 | L34: √ | M34: √ | T34: 系统已建 | U34: 营销2.0系统 | V34: 采集异常工单及审核审批记录 | W34: 各级单位供电公司-营销部门-计量（抄表）管理及各级审批人员 | X34: 每 半年 | Y34: 抽查 | AA34: 年度 | AB34: 抽查 | AH34: 是 | AI34: 是 | AJ34: 《国家电网有限公司电费业务管理办法（征求意见稿）》第五章 采集抄表 | AK34: 国网营销部 | AL34: 地市 | AM34: 计量、营业
A35: 营销售电业务 | B35: 四、电费核算与发行管理 | C35: 会计信息真实完整 | D35: 量费计算 | E35: 未严格执行电费计算规则，电费计算结果未经有效复核，导致电费计算结果失真。 | G35: 11.电费计算结果复核 | H35: 电费核算与复核规则应纳入统一管理 | I35: 营销售电业务-11.电费计算结果复核-控制措施01 | J35: 国网营销部对电费核算与复核规则进行集中管理、二级配置与实施，规则应及时动态更新。 | M35: √ | T35: 系统已建 | U35: 营销2.0系统 | V35: 系统电费核算与复核规则 | W35: 国网营销部-电费电价管理人员；各省（自治区、直辖市）电力公司省公司-营销部门-电费电价管理人员 | X35: 每年 | Y35: 抽查 | AA35: 年度 | AB35: 抽查 | AH35: 是 | AI35: 是 | AJ35: 《国家电网有限公司电费业务管理办法（征求意见稿）》第七章 核算出账 | AK35: 国网营销部 | AL35: 国网营销部、省公司 | AM35: 电费电价
I36: 营销售电业务-11.电费计算结果复核-控制措施02 | J36: 省公司营销部门应确保通用规则执行到位，对个性化补充规则严格履行审批程序后实施。 | M36: √ | T36: 系统已建 | U36: 营销2.0系统 | V36: 1.系统电费核算与复核规则； 2.系统个性化规则授权审批记录 | W36: 各省（自治区、直辖市）电力公司省公司-营销部门-电费电价管理人员 | X36: 每年 | Y36: 抽查 | AA36: 年度 | AB36: 抽查 | AH36: 是 | AI36: 是 | AJ36: 《国家电网有限公司电费业务管理办法（征求意见稿）》第七章 核算出账 | AK36: 国网营销部 | AL36: 省公司 | AM36: 电费电价
I37: 营销售电业务-11.电费计算结果复核-控制措施03 | J37: 营销部门建立量费核算结果集中复核机制，异常事项消缺实行工单化管理，并明确分级分类审批标准。 | L37: √ | M37: √ | T37: 系统已建 | U37: 营销2.0系统 | V37: 量费异常工单及审核审批记录 | W37: 各级单位供服中心、供电公司-营销部门-电费电价管理及各级审批人员 | X37: 每 半年 | Y37: 抽查 | AA37: 年度 | AB37: 抽查 | AH37: 是 | AI37: 是 | AJ37: 《国家电网有限公司电费业务管理办法（征求意见稿）》第七章 核算出账 | AK37: 国网营销部 | AL37: 供服、地市 | AM37: 电费电价
C38: 会计信息真实完整、资金资产安全 | D38: 电费发行 | E38: 违规减免电费，导致收入不实、资金损失。 | F38: 20.营销系统权限管控不严：存在重要业务流程权限设置不合规；电费收费、账务处理、财务审核和违约用电查处、审批等不相容岗位未分离；信息系统权限未严格落实实名制，账号权限与实际权责不符、一人存在多个账号等问题。 | G38: 12.电费发行确认 | H38: 电费发行应真实、完整、准确 | I38: 营销售电业务-12.电费发行确认-控制措施01 | J38: 营销部门统一配置电费发行规则，强化电费发行与核算一体化管控，严禁手工篡改发行数据。 | M38: √ | T38: 系统已建 | U38: 营销2.0系统 | V38: 1.系统电费发行工单流转记录； 2.岗位权限配置 | W38: 各省（自治区、直辖市）电力公司供服中心-营销部门-电费电价管理人员 | X38: 每年 | Y38: 抽查 | AA38: 年度 | AB38: 抽查 | AH38: 是 | AI38: 是 | AJ38: 《国家电网有限公司电费业务管理办法（征求意见稿）》第七章 核算出账 国网湖南电力营销部关于印发电费结算管理办法的通知（营销〔2022〕27号） 国网湖南电力营销部关于加强电量电费差错风险防控工作的通知（营销〔2024〕36号） | AK38: 国网营销部 | AL38: 供服 | AM38: 电费电价
I39: 营销售电业务-12.电费发行确认-控制措施02 | J39: 营销部门协同交易明确月末预估量价规则，预估到日，预估结果确认严格履行审批程序，防止人为调整。 | M39: √ | T39: 系统已建 | U39: 营销2.0系统 | V39: 1.系统电费发行工单流转记录； 2.系统电费退补审批记录及支撑依据； 3.岗位权限配置 | W39: 各省（自治区、直辖市）电力公司供服中心-营销部门-电费电价管理人员 | X39: 每 季度 | Y39: 抽查 | AA39: 年度 | AB39: 抽查 | AH39: 是 | AI39: 是 | AJ39: 《国家电网有限公司电费业务管理办法（征求意见稿）》第七章 核算出账 | AK39: 国网营销部 | AL39: 供服 | AM39: 电费电价
I40: 营销售电业务-12.电费发行确认-控制措施03 | J40: 各单位业务核算人员在算费前，对当月审核规则拦截的涉费工单进行逐一检查，督导处理归档。 | M40: √ | T40: 系统已建 | U40: 营销2.0系统 | V40: 系统试算工单流转记录 | W40: 各级单位供服中心、供电公司-营销部门-业务核算人员 | X40: 每半年 | Y40: 抽查 | AA40: 年度 | AB40: 抽查 | AH40: 是 | AI40: 是 | AJ40: 《国家电网有限公司电费业务管理办法（征求意见稿）》第七章 核算出账 | AK40: 国网营销部 | AL40: 供服、地市 | AM40: 电费电价
I41: 营销售电业务-12.电费发行确认-控制措施04 | J41: 营销部门对非政策性电费退补应严格履行分级审批程序。 | L41: √ | T41: 系统已建 | U41: 营销2.0系统 | V41: 1.系统电费退补审批记录及支撑依据； 2.岗位权限配置 | W41: 各级单位供服中心、供电公司-营销部门-电费电价管理及各级审批人员 | X41: 每半年 | Y41: 抽查 | AA41: 年度 | AB41: 抽查 | AH41: 是 | AI41: 是 | AJ41: 《国家电网有限公司电费业务管理办法（征求意见稿）》第七章 核算出账 国网湖南电力市场营销部关于规范电量电费退补管理的通知（营销〔2021〕15号） | AK41: 国网营销部 | AL41: 供服、地市 | AM41: 电费
I42: 营销售电业务-12.电费发行确认-控制措施05 | J42: 营销部门对非政策性电费退补开展数字化在线监督。 | M42: √ | S42: √ | T42: 系统已建 | U42: 营销2.0系统 | V42: 数字化监督相关资料或稽查工单及处理情况 | W42: 各级单位供服中心、供电公司-营销部门-电费电价管理人员 | X42: 每半年 | Y42: 抽查 | AA42: 年度 | AB42: 抽查 | AD42: 违规减免电费监督——对非政策性电费退补开展数字化在线监督 | AE42: 每季度 | AF42: 全量 | AH42: 是 | AI42: 是 | AJ42: 《国家电网有限公司电费业务管理办法（征求意见稿）》第七章 核算出账 国网湖南电力市场营销部关于规范电量电费退补管理的通知（营销〔2021〕15号） | AK42: 国网营销部 | AL42: 供服、地市 | AM42: 电费
A43: 营销售电业务 | B43: 四、电费核算与发行管理 | C43: 会计信息真实完整、资金资产安全 | D43: 业务费确认 | E43: 业务费收取不规范，造成电费资金损失。 | F43: 18.违约窃电查处不规范：存在未及时查处用户违约用电、窃电行为；违规减免、暂缓应补交的追补电费和违约使用电费等问题。 20.营销系统权限管控不严：电费收费、账务处理、财务审核和违约用电查处、审批等不相容岗位未分离；账号权限与实际权责不符、一人存在多个账号等问题。 | G43: 13.业务费确认 | H43: 业务费应足额、准确收取 | I43: 营销售电业务-13.业务费确认-控制措施01 | J43: 营销部门应严格执行价格主管部门批准的收费项目和计算标准，统一配置业务费计费规则，严禁手工修改系统计算结果。 | M43: √ | P43: √ | T43: 系统已建 | U43: 营销2.0系统 | V43: 1.业务费收费标准； 2，系统业务费计费规则； 3.业务费收费明细 | W43: 各省（自治区、直辖市）电力公司省公司-营销部门-业务费管理人员 | X43: 每年 | Y43: 抽查 | AA43: 年度 | AB43: 抽查 | AH43: 是 | AI43: 是 | AJ43: 《供电营业规则》 | AK43: 国网营销部 | AL43: 省公司 | AM43: 反窃查违、业扩
I44: 营销售电业务-13.业务费确认-控制措施02 | J44: 营销部门对业务费收取、减免（暂缓、退费等）严格履行分级审批程序并线上实施，确保足额收取。 | L44: √ | P44: √ | T44: 系统待建 | U44: 营销2.0系统 | V44: 1.系统审批单； 2.岗位权限配置； 3.退费影像 | W44: 各级单位供电公司-营销部门-业务收取、管理及各级审批人员 | X44: 每半年 | Y44: 抽查 | AA44: 年度 | AB44: 抽查 | AH44: 是 | AI44: 是 | AJ44: 《供电营业规则》 | AK44: 国网营销部 | AL44: 地市 | AM44: 反窃查违、业扩
I45: 营销售电业务-13.业务费确认-控制措施03 | J45: 营销部门对违规减免（暂缓）业务费开展数字化在线监督。 | M45: √ | S45: √ | T45: 系统已建 | U45: 营销2.0系统 | V45: 数字化在线监督结果或稽查工单及处理情况 | W45: 各级单位-营销部门-电费电价管理人员供电公司-营销部门-业务收取、管理及各级审批人员 | X45: 每半年 | Y45: 抽查 | AA45: 年度 | AB45: 抽查 | AD45: 违规减免业务费监督——对违规减免（暂缓）业务费开展数字化在线监督 | AE45: 每季度 | AF45: 全量 | AH45: 是 | AI45: 是 | AJ45: 《供电营业规则》 | AK45: 国网营销部 | AL45: 地市 | AM45: 反窃查违、业扩
C46: 会计信息真实完整、资金资产安全 | D46: 电费违约金减免 | E46: 违规减免电费违约金，掩盖其欠费事实，后期存在电费无法回收风险。 | F46: 17.违规减免电费违约金：存在电费未足额收回，通过全减另发等方式违规减免应收电费；违规减免或暂缓电费违约金等问题。 20.营销系统权限管控不严：存在重要业务流程权限设置不合规；电费收费、账务处理、财务审核和违约用电查处、审批等不相容岗位未分离；信息系统权限未严格落实实名制，账号权限与实际权责不符、一人存在多个账号等问题。 | G46: 14.电费违约金减免 | H46: 电费违约金应足额、准确收取 | I46: 营销售电业务-14.电费违约金减免-控制措施01 | J46: 营销部门明确电费违约金减免（暂缓）适用情形、支撑材料及分级授权标准。 | M46: √ | T46: 线下管控 | V46: 1.电费违约金减免（暂缓）支撑依据； 2.岗位权限配置 | W46: 各省（自治区、直辖市）电力公司省公司-营销部门-电费电价管理人员 | X46: 每年 | Y46: 抽查 | AA46: 年度 | AB46: 抽查 | AH46: 是 | AI46: 是 | AJ46: 《国家电网有限公司电费业务管理办法（征求意见稿）》第八章 电费收支 第五十条规范电费违约金管理 | AK46: 国网营销部 | AL46: 省公司 | AM46: 电费
I47: 营销售电业务-14.电费违约金减免-控制措施02 | J47: 营销部门统一配置电费违约金减免（暂缓）工单及系统审批程序。 | M47: √ | T47: 系统已建 | U47: 营销2.0系统 | V47: 1.系统电费违约金减免（暂缓）工单流转记录； 2.岗位权限配置 | W47: 各省（自治区、直辖市）电力公司省公司、供服中心-营销部门-电费电价管理人员 | X47: 每年 | Y47: 抽查 | AA47: 年度 | AB47: 抽查 | AH47: 是 | AI47: 是 | AJ47: 《国家电网有限公司电费业务管理办法（征求意见稿）》第八章 电费收支 第五十条规范电费违约金管理 | AK47: 国网营销部 | AL47: 省公司、供服 | AM47: 电费
I48: 营销售电业务-14.电费违约金减免-控制措施03 | J48: 营销部门电费管理人员对电费违约金减免（暂缓）支撑材料及工单记录进行复核。 | M48: √ | T48: 系统已建 | U48: 营销2.0系统 | V48: 1.系统电费违约金减免（暂缓）工单流转记录； 2.电费违约金减免（暂缓）支撑依据 | W48: 各级单位供电公司-营销部门-电费电价管理人员 | X48: 每半年 | Y48: 抽查 | AA48: 年度 | AB48: 抽查 | AH48: 是 | AI48: 是 | AJ48: 《国家电网有限公司电费业务管理办法（征求意见稿）》第八章 电费收支 第五十条规范电费违约金管理 | AK48: 国网营销部 | AL48: 地市 | AM48: 电费
I49: 营销售电业务-14.电费违约金减免-控制措施04 | J49: 营销部门对电费违约金减免（暂缓）开展数字化在线监督。 | M49: √ | S49: √ | T49: 系统已建 | U49: 营销2.0系统 | V49: 数字化在线监督结果或稽查工单及处理情况 | W49: 各级单位供电公司-营销部门-电费电价管理人员 | X49: 每半年 | Y49: 抽查 | AA49: 年度 | AB49: 抽查 | AD49: 电费违约金违规减免监督——对电费违约金减免（暂缓）开展在线监督 | AE49: 每季度 | AF49: 全量 | AH49: 是 | AI49: 是 | AJ49: 《国家电网有限公司电费业务管理办法（征求意见稿）》第八章 电费收支 第五十条规范电费违约金管理 | AK49: 国网营销部 | AL49: 地市 | AM49: 电费
B50: 五、电费账务及发票管理 | C50: 会计信息真实完整 | D50: 电费账务处理 | E50: 电费账务不准确，导致收入不实风险。 | F50: 20.营销系统权限管控不严：存在重要业务流程权限设置不合规；电费收费、账务处理、财务审核和违约用电查处、审批等不相容岗位未分离；信息系统权限未严格落实实名制，账号权限与实际权责不符、一人存在多个账号等问题。 | G50: 15.电费账务管控 | H50: 电费账务应纳入线上管控 | I50: 营销售电业务-15.电费账务管控-控制措施01 | J50: 电费账务应自动集成电费发行及收费结果，防止人为干预。 | M50: √ | T50: 系统已建 | U50: 营销2.0系统 | V50: 系统电费凭证生成标识 | W50: 各省（自治区、直辖市）电力公司省公司-营销部门-电费管理人员 | X50: 每年 | Y50: 抽查 | AA50: 年度 | AB50: 抽查 | AH50: 是 | AI50: 是 | AJ50: 《国家电网有限公司电费业务管理办法（征求意见稿）》第九章 电费账务 | AK50: 国网营销部 | AL50: 省公司 | AM50: 电费
I51: 营销售电业务-15.电费账务管控-控制措施02 | J51: 因核算差错等确需调整账务时由营销部门结合业务联动调整，并严格履行审批程序。 | L51: √ | M51: √ | T51: 系统已建 | U51: 营销2.0系统 | V51: 1.系统电费凭证生成标识； 2.岗位权限配置 | W51: 各级单位省公司、供服中心、供电公司-营销部门-电费电价管理及各级审批人员 | X51: 每半年 | Y51: 抽查 | AA51: 年度 | AB51: 抽查 | AH51: 是 | AI51: 是 | AJ51: 《国家电网有限公司电费业务管理办法（征求意见稿）》第九章 电费账务 | AK51: 国网营销部 | AL51: 省公司、供服、地市 | AM51: 电费
A52: 营销售电业务 | B52: 五、电费账务及发票管理 | C52: 会计信息真实完整 | D52: 电费账务处理 | E52: 会计政策执行不到位，手工调整账务，导致财务会计信息反映不真实。 | G52: 16.营财账务协同管理 | H52: 营财账务应建立协同管控机制 | I52: 营销售电业务-16.营财账务协同管理-控制措施01 | J52: 财务部门根据会计政策变化、制度调整及时变更会计科目及凭证生成规则，并及时下发执行。 | Q52: √ | T52: 系统已建 | U52: 智慧财务 | V52: 1.会计政策文件； 2.会计规则调整相关文件； 3.系统核算规则 | W52: 国网财务部-总账管理人员；各省（自治区、直辖市）电力公司省公司-财务部门-总账管理人员 | X52: 每年 | Y52: 抽查 | AA52: 年度 | AB52: 抽查 | AH52: 是 | AI52: 是 | AJ52: 《国网营销部财务部关于明确营销2.0系统与智慧共享财务平台系统集成有关问题的意见》（营销营业〔2023〕86号文 ） | AK52: 国网财务部 | AL52: 财务部 | AM52: 财务
I53: 营销售电业务-16.营财账务协同管理-控制措施02 | J53: 营销部门按照财务核算规则开展营销收入、销项税等的账务核算并按日传递凭证。 | Q53: √ | T53: 系统已建 | U53: 智慧财务、营销2.0系统 | V53: 1.系统核算规则； 2.系统电费凭证； 3.营财对账记录 | W53: 各省（自治区、直辖市）电力公司省公司-营销部门-电费管理人员 | X53: 每季度 | Y53: 抽查 | AA53: 年度 | AB53: 抽查 | AH53: 是 | AI53: 是 | AJ53: 《国家电网有限公司电费业务管理办法（征求意见稿）》第九章 电费账务 《国网营销部财务部关于明确营销2.0系统与智慧共享财务平台系统集成有关问题的意见》（营销营业〔2023〕86号文 ） | AK53: 国网营销部 | AL53: 财务部 | AM53: 财务
I54: 营销售电业务-16.营财账务协同管理-控制措施03 | J54: 财务部门对营销部门会计凭证与会计事务代码匹配性、营财账务一致性开展复核与数字化在线监督，营财差异应及时反馈营销并督导消缺。 | M54: √ | Q54: √ | S54: √ | T54: 系统已建 | U54: 智慧财务、营销2.0系统 | V54: 数字化在线监督结果及异常消缺记录 | W54: 各省（自治区、直辖市）电力公司供服中心、供电公司-财务部门-销售电价管理人员；各省（自治区、直辖市）电力公司供服中心、供电公司-营销部门-电费电价管理人员 | X54: 每季度 | Y54: 抽查 | AA54: 年度 | AB54: 抽查 | AD54: 营财记账监督——营财账务一致性开展在线监督 | AE54: 每月 | AF54: 全量 | AH54: 是 | AI54: 是 | AJ54: 《国网营销部财务部关于明确营销2.0系统与智慧共享财务平台系统集成有关问题的意见》（营销营业〔2023〕86号文 ） | AK54: 国网财务部、国网营销部 | AL54: 供服、地市 | AM54: 地市财务、账务
I55: 营销售电业务-16.营财账务协同管理-控制措施04 | J55: 营财账务调整应由营销结合业务进行调整并推送至财务，严禁单方面手工调整营财账务。 | Q55: √ | T55: 系统已建 | U55: 智慧财务、营销2.0系统 | V55: 1.财务记账单凭证明细及审批记录； 2.营销凭证生成标识 | W55: 各级单位供服中心、供电公司-财务部门-销售电价管理人员；各级单位供服中心、供电公司-营销部门-电费电价管理人员 | X55: 每季度 | Y55: 抽查 | AA55: 年度 | AB55: 抽查 | AH55: 是 | AI55: 是 | AJ55: 《国家电网有限公司电费业务管理办法（征求意见稿）》第九章 电费账务 《国网营销部财务部关于明确营销2.0系统与智慧共享财务平台系统集成有关问题的意见》（营销营业〔2023〕86号文 ） | AK55: 国网财务部、国网营销部 | AL55: 供服、地市 | AM55: 财务
C56: 会计信息真实完整、资金资产安全、税务合规 | D56: 电费发票开具 | E56: 电费发票虚开未有效管控，引发税务合规风险。 | G56: 17.电费发票开具 | H56: 电费发票应与电费账单、业务费确认结果一致，严禁篡改开票信息 | I56: 营销售电业务-17.电费发票开具-控制措施01 | J56: 营销部门对电费（业务费）开票实施线上统一管理，强控开票规则与开票权限，不得篡改开票信息，营销开票结果与财务共享。 | M56: √ | Q56: √ | T56: 系统已建 | U56: 营销2.0系统 | V56: 1.营销系统开票票面信息； 2.开票规则 | W56: 各省（自治区、直辖市）电力公司省公司-营销部门-电费管理人员、业务管理人员 | X56: 每半年 | Y56: 抽查 | AA56: 年度 | AB56: 抽查 | AH56: 是 | AI56: 是 | AJ56: 《国家电网有限公司电费业务管理办法（征求意见稿）》第十章 电费票据管理 第六十三条 《国网营销部财务部关于明确营销2.0系统与智慧共享财务平台系统集成有关问题的意见》（营销营业〔2023〕86号） 《国家电网有限公司发票管理规范（征求意见稿）》第二十四条至二十六条 | AK56: 国网营销部 | AL56: 省公司 | AM56: 反窃查违、业扩、电费
I57: 营销售电业务-17.电费发票开具-控制措施02 | J57: 营销部门对未结清开票、分割开票严格履行审批程序，开票执行与电费账务执行不相容控制。 | K57: √ | L57: √ | T57: 系统已建 | U57: 营销2.0系统 | V57: 1.未结清、分割开票申请及审批资料； 2.系统开票结果 | W57: 各级单位供电公司-营销部门-电费管理人员及各级审批人员 | X57: 每季度 | Y57: 抽查 | AA57: 年度 | AB57: 抽查 | AH57: 是 | AI57: 是 | AJ57: 《国家电网有限公司电费业务管理办法（征求意见稿）》第十章 电费票据管理 《国家电网有限公司发票管理规范（征求意见稿）》第二十四条至二十六条 | AK57: 国网营销部 | AL57: 地市 | AM57: 电费
I58: 营销售电业务-17.电费发票开具-控制措施03 | J58: 电费（业务费）发票原则上在营销系统进行开具，如客户要求无法满足需在智慧财务（电子税务）开具的，应由营销系统将开票信息推送智慧财务，并推动营销系统改造。在智慧财务开具电费类发票的，履行严格审批程序。 | Q58: √ | T58: 系统待建 | U58: 营销2.0系统、智慧财务、电子税务系统 | V58: 1.营销全量开票信息； 2.智慧财务、电子税务开票信息及营销推送记录； 3.智慧财务开票即审批记录 | W58: 各级单位、供服中心、供电公司-营销部门-电费电价管理人员；各级单位供电公司-财务部门-税务管理人员 | X58: 每季度 | Y58: 抽查 | AA58: 年度 | AB58: 抽查 | AH58: 是 | AI58: 否 | AJ58: 《国家电网有限公司电费业务管理办法（征求意见稿）》第十章 电费票据管理 第六十三条 《国网营销部财务部关于明确营销2.0系统与智慧共享财务平台系统集成有关问题的意见》（营销营业〔2023〕86号） 《国家电网有限公司发票管理规范（征求意见稿）》第二十四条至二十六条 | AK58: 国网营销部、国网财务部 | AL58: 供服、供电公司 | AM58: 电费
I59: 营销售电业务-17.电费发票开具-控制措施04 | J59: 财务部门协同营销部门对全量数电票开具情况纳入数字化在线监测。 | M59: √ | S59: √ | T59: 系统待建 | U59: 营销2.0系统、智慧财务 | V59: 数字化在线监督结果及异常消缺记录 | W59: 各级单位省公司、供电公司-财务部门-财税管理人员；各级单位省公司、供电公司-营销部门-电费管理人员 | X59: 每季度 | Y59: 抽查 | AA59: 年度 | AB59: 抽查 | AD59: 数电票开票监督——开展全量数电票在线监测 | AE59: 每月 | AF59: 全量 | AH59: 是 | AI59: 否 | AJ59: 《国家电网有限公司电费业务管理办法（征求意见稿）》第十章 电费票据管理 第六十三条 | AK59: 国网财务部、国网营销部 | AL59: 省公司、地市 | AM59: 电费
A60: 营销售电业务 | B60: 五、电费账务及发票管理 | C60: 会计信息真实完整、资金资产安全、税务合规 | D60: 价外基金上交 | E60: 价外基金列转不及时、上交不准确，引发税务合规风险。 | G60: 18.价外基金上交 | H60: 价外基金征收范围完整、上缴金额准确 | I60: 营销售电业务-18.价外基金上交-控制措施01 | J60: 营销部门强化价外基金与电费发行一体化管控，确保价外基金征收范围完整、金额准确。 | M60: √ | T60: 系统已建 | U60: 营销2.0系统 | V60: 1.电费账单； 2.系统发行数据与营销报表 | W60: 各级单位供服中心、供电公司-营销部门-电费电价管理人员 | X60: 每半年 | Y60: 抽查 | AA60: 年度 | AB60: 抽查 | AH60: 是 | AI60: 是 | AJ60: 《国家电网有限公司电费业务管理办法（征求意见稿）》第二章 电价执行 | AK60: 国网营销部 | AL60: 供服、地市 | AM60: 电费
I61: 营销售电业务-18.价外基金上交-控制措施02 | J61: 财务部门完成营销报表、账务信息核对一致性后完成上交，严禁篡改信息。 | M61: √ | T61: 系统已建 | U61: 智慧财务 | V61: 1.系统凭证； 2.系统发行数据与营销报表； | W61: 各级单位省公司-财务部门-销售电价及财税管理人员 | X61: 每半年 | Y61: 抽查 | AA61: 年度 | AB61: 抽查 | AH61: 是 | AI61: 是 | AJ61: 《国家电网有限公司电价工作管理办法》政府性基金及附加管理 《国网财务部 国网营销部关于调整代征政府性基金财务核算和营业开票规则的通知》（财税〔2025〕29号） | AK61: 国网财务部 | AL61: 省公司 | AM61: 财务
I62: 营销售电业务-18.价外基金上交-控制措施03 | J62: 财务部门对下级单位价外基金列转的及时性、准确性复核，确保按期足额上交财政部门。 | P62: √ | Q62: √ | T62: 系统已建 | U62: 智慧财务 | V62: 1.系统凭证； 2.系统上交数据 | W62: 各省（自治区、直辖市）电力公司省公司-财务部门-销售电价及财税管理人员 | X62: 每半年 | Y62: 抽查 | AA62: 年度 | AB62: 抽查 | AH62: 是 | AI62: 是 | AJ62: 《国家电网有限公司电价工作管理办法》政府性基金及附加管理 | AK62: 国网财务部 | AL62: 省公司 | AM62: 财务
I63: 营销售电业务-18.价外基金上交-控制措施04 | J63: 财务部门对价外基金上交情况开展数字化在线监测。 | M63: √ | S63: √ | T63: 系统待建 | U63: 智慧财务 | V63: 数字化在线监督结果及异常消缺记录 | W63: 各省（自治区、直辖市）电力公司省公司-财务部门-销售电价及财税管理人员 | X63: 每半年 | Y63: 抽查 | AA63: 年度 | AB63: 抽查 | AD63: 价外基金上交监测——开展价外基金上交在线监测 | AE63: 每季度 | AF63: 全量 | AH63: 是 | AI63: 是 | AJ63: 《国家电网有限公司电价工作管理办法》政府性基金及附加管理 | AK63: 国网财务部 | AL63: 省公司 | AM63: 财务
B64: 六、电费实收管理 | C64: 资金资产安全 | D64: 收费渠道管理 | E64: 代收渠道未统一管理，代收渠道协议不规范，引发资金挪用、财务账务不合规风险。 | G64: 19.代收渠道运行管理 | H64: 代收渠道应纳入省公司统一管理 | I64: 营销售电业务-19.代收渠道运行管理-控制措施01 | J64: 营销部门协同财务部门严格代收渠道新增、变更审批程序，加强地方代收渠道监控，加速清理超标、低效、扩范围违规代收渠道。 | P64: √ | T64: 线下管控 | V64: 1.新增（变更）代收渠道审批记录； 2.地方代收渠道纳入监控材料 | W64: 各省（自治区、直辖市）电力公司供服中心-营销部门-电费管理人员 | X64: 每年 | Y64: 抽查 | AA64: 年度 | AB64: 抽查 | AH64: 是 | AI64: 是 | AJ64: 《国网财务部关于规范和加强商户号管理的通知》（财金〔2025〕2号） 《国家电网有限公司司库管理办法》第二十三条、二十八条、第五章第二节收入管理 | AK64: 国网营销部 | AL64: 供服 | AM64: 账务
I65: 营销售电业务-19.代收渠道运行管理-控制措施02 | J65: 营销部门加强代收渠道协议的统一管理，明确对账与结算责任条款。 | P65: √ | T65: 线下管控 | V65: 代收渠道合作协议（线下） | W65: 各省（自治区、直辖市）电力公司供服中心-营销部门-电费管理人员 | X65: 每年 | Y65: 抽查 | AA65: 年度 | AB65: 抽查 | AH65: 是 | AI65: 是 | AJ65: 《国网财务部关于规范和加强商户号管理的通知》（财金〔2025〕2号） 《国家电网有限公司司库管理办法》第二十三条、第五章第二节收入管理 | AK65: 国网营销部 | AL65: 供服 | AM65: 账务
I66: 营销售电业务-19.代收渠道运行管理-控制措施03 | J66: 财务部门协同营销部门将各类代收渠道关联的银行账户、商户号纳入线上监控，营销部门每日开展对账，并及时将对账信息传递财务；财务部门每月对各电费账户、商户号进行资金对账复核，确保资金安全。 | P66: √ | Q66: √ | T66: 系统已建 | U66: 智慧财务、营销2.0系统 | V66: 1.营销对账记录； 2.财务复核记录 | W66: 各省（自治区、直辖市）电力公司供服中心、会计服务中心-资金管理人员；各省（自治区、直辖市）电力公司供服中心、会计服务中心-电费管理人员 | X66: 每季度 | Y66: 抽查 | AA66: 年度 | AB66: 抽查 | AD66: 代收渠道监管——将各类代收渠道关联的银行账户、商户号纳入线上监控 | AE66: 每月 | AF66: 全量 | AH66: 是 | AI66: 是 | AJ66: 《国网财务部关于规范和加强商户号管理的通知》（财金〔2025〕2号） 《国家电网有限公司司库管理办法》第五章第二节收入管理 | AK66: 国网财务部、国网营销部 | AL66: 供服、会服 | AM66: 财务、账务
A67: 营销售电业务 | B67: 六、电费实收管理 | C67: 资金资产安全 | D67: 收费渠道管理 | E67: 资金到账情况未及时监管，导致资金滞留风险。 | G67: 20.代收渠道在途资金管理 | H67: 强化代收渠道对账及结算管控，督导在途资金处理 | I67: 营销售电业务-20.代收渠道在途资金管理-控制措施01 | J67: 营销部门建立每日对账机制，并以核对一致的对账数据为标准进行电费资金清算。 | M67: √ | P67: √ | T67: 系统已建 | U67: 营销2.0系统 | V67: 1.在途资金对账记录； 2.系统资金流水； | W67: 各级单位供服中心-营销部门-电费管理人员 | X67: 每月 | Y67: 抽查 | AA67: 年度 | AB67: 抽查 | AH67: 是 | AI67: 是 | AJ67: 《国网财务部关于规范和加强商户号管理的通知》（财金〔2025〕2号） 《国家电网有限公司司库管理办法》第五章第二节收入管理 | AK67: 国网营销部 | AL67: 供服 | AM67: 账务
I68: 营销售电业务-20.代收渠道在途资金管理-控制措施02 | J68: 对于银行代收、商户号收取的尚未清分或清缴至电费账户的资金按在途资金管理与核算。 | Q68: √ | T68: 系统已建 | U68: 营销2.0系统 | V68: 1.在途资金明细； 2.电费账务凭证 | W68: 各级单位供服中心-营销部门-电费管理人员 | X68: 每月 | Y68: 抽查 | AA68: 年度 | AB68: 抽查 | AH68: 是 | AI68: 是 | AJ68: 《国网财务部关于规范和加强商户号管理的通知》（财金〔2025〕2号） 《国家电网有限公司司库管理办法》第六条 《国家电网有限公司会计核算办法》 | AK68: 国网营销部 | AL68: 供服 | AM68: 账务
I69: 营销售电业务-20.代收渠道在途资金管理-控制措施03 | J69: 营销部门加强超限未到账的在途资金跟踪处理，开展数字化在线监测并设置资金到账及时性预警。 | P69: √ | S69: √ | T69: 系统待建 | U69: 营销2.0系统 | V69: 数字化在线监督结果及异常消缺记录 | W69: 各级单位供服中心-营销部门-电费管理人员 | X69: 每月 | Y69: 抽查 | AA69: 年度 | AB69: 抽查 | AD69: 在途资金监控——对在途资金开展在线监测并设置资金到账及时性预警 | AE69: 每日 | AF69: 全量 | AH69: 是 | AI69: 是 | AJ69: 《国网财务部关于规范和加强商户号管理的通知》（财金〔2025〕2号） 《国家电网有限公司司库管理办法》第六条 | AK69: 国网营销部 | AL69: 供服 | AM69: 账务
C70: 资金资产安全 | D70: 收费渠道管理 | E70: 柜收资金安全性管控不到位，导致现金截留、账实不符、现金流失​​等风险。 | G70: 21.柜台收费在途资金管理 | H70: 柜台收费应与客户准确关联，并及时缴存银行 | I70: 营销售电业务-21.柜台收费在途资金管理-控制措施01 | J70: 营业厅（所）柜收人员收取现金要与客户及收费资金类别精准匹配，当面点清、验明真伪，收费后主动向客户提供收费票据（含电子票据）。 | M70: √ | P70: √ | T70: 线下管控 | V70: 1.系统收费解款记录； 2.银行缴存或到账记录 | W70: 各级单位供电公司-营销部门-营业厅柜台收费人员 | X70: 每月 | Y70: 抽查 | AA70: 年度 | AB70: 抽查 | AH70: 是 | AI70: 是 | AJ70: 《国家电网有限公司电费业务管理办法（征求意见稿）》第八章 电费收支 | AK70: 国网营销部 | AL70: 地市 | AM70: 电费
I71: 营销售电业务-21.柜台收费在途资金管理-控制措施02 | J71: 对于柜收现金，营业厅（所）收费人员应于日终解款并在线开展现金日记账及在途资金盘点，做到日清日结。现金日记账及现金盘点表应按照电子档案管理要求，取得电子签章或签批后归档，营业厅（所）负责人按月开展检查。 | P71: √ | Q71: √ | T71: 系统已建 | U71: 营销2.0系统 | V71: 1.营销现金日记账； 2.现金盘点表 | W71: 各级单位供电公司-营销部门-营业厅柜台收费人员 | X71: 每月 | Y71: 抽查 | AA71: 年度 | AB71: 抽查 | AH71: 是 | AI71: 否 | AJ71: 《国家电网有限公司电费业务管理办法（征求意见稿）》第八章 电费收支 《国家电网有限公司司库管理办法》第六十四条 | AK71: 国网营销部 | AL71: 地市 | AM71: 电费
I72: 营销售电业务-21.柜台收费在途资金管理-控制措施03 | J72: 柜收现金应及时缴存银行，通过解款时生成的唯一解款编码关联缴存信息等，确保银行流水与解款记录精准识别，实现自动销账、准确到账。 | M72: √ | P72: √ | T72: 系统待建 | U72: 营销2.0系统 | V72: 1.系统未自动收费记录； 2.系统自动收费记录交易标识或资金编码 | W72: 各级单位供电公司-营销部门-电费管理人员 | X72: 每月 | Y72: 抽查 | AA72: 年度 | AB72: 抽查 | AH72: 是 | AI72: 否 | AJ72: 《国家电网有限公司电费业务管理办法（征求意见稿）》第八章 电费收支 《国家电网有限公司司库管理办法》第六十四、六十七条 | AK72: 国网营销部 | AL72: 地市 | AM72: 电费
C73: 会计信息真实完整、资金资产安全 | D73: 实收销账 | E73: 电费销账不准确，引发资金流失及应收账款不实风险。 | G73: 22.电费销账标准制定 | H73: 电费销账应明确标准，与资金流水匹配，与客户准确关联 | I73: 营销售电业务-22.电费销账标准制定-控制措施01 | J73: 营销部门以资金流水、代收渠道对账文件、柜收现金等为依据收费到户，严禁在无可信缴费记录前提下完成电费收取。 | M73: √ | P73: √ | T73: 系统已建 | U73: 营销2.0系统 | V73: 1.系统电费一次销根凭证； 2.系统资金流水或代收渠道对账文件或柜收现金（票据） | W73: 各级单位省公司-营销部-电费管理人员、供电公司-营销部门-柜收人员、电费管理人员 | X73: 每月 | Y73: 抽查 | AA73: 年度 | AB73: 抽查 | AH73: 是 | AI73: 是 | AJ73: 《国家电网有限公司司库管理办法》第六十七条 | AK73: 国网营销部 | AL73: 省公司、地市 | AM73: 账务
I74: 营销售电业务-22.电费销账标准制定-控制措施02 | J74: 营销部门要采取措施促使银行流水与客户信息对应、与解款记录关联，确保自动收费、自动销账。对于无法自动收费的，应在系统中维护转账用户关系完成收费；需手工收取的原则上使用转账用户收费功能，并严格按照营销系统中银行流水进行收费。 | M74: √ | P74: √ | T74: 系统已建 | U74: 营销2.0系统 | V74: 1.系统人工收费记录； 2.转账用户管理 | W74: 各级单位供服中心、供电公司-营销部门-电费管理人员 | X74: 每月 | Y74: 抽查 | AA74: 年度 | AB74: 抽查 | AH74: 是 | AI74: 否 | AJ74: 《国家电网有限公司电费业务管理办法（征求意见稿）》第八章 电费收支 第四十八条 | AK74: 国网营销部 | AL74: 供服、地市 | AM74: 账务
I75: 营销售电业务-22.电费销账标准制定-控制措施03 | J75: 营销部门电费账务人员对收费记录与凭证开展一致性核对，电费收费与电费账务执行不相容控制。 | M75: √ | T75: 系统待建 | U75: 营销2.0系统 | V75: 1.系统电费一次销根凭证； 2.系统资金流水或代收渠道对账文件或柜收现金（票据）； 3.岗位权限配置 | W75: 各级单位供服中心、供电公司-营销部门-电费管理人员 | X75: 每月 | Y75: 抽查 | AA75: 年度 | AB75: 抽查 | AH75: 是 | AI75: 是 | AJ75: 《国家电网有限公司电费业务管理办法（征求意见稿）》第八章 电费收支 第四十八条 《国家电网有限公司司库管理办法》第六十七、六十九条 | AK75: 国网营销部 | AL75: 供服、地市 | AM75: 账务
A76: 营销售电业务 | B76: 六、电费实收管理 | C76: 会计信息真实完整 | D76: 预收互转 | E76: 电费预收结转不准确，导致账实不符风险。 | F76: 20.营销系统权限管控不严：存在重要业务流程权限设置不合规；电费收费、账务处理、财务审核和违约用电查处、审批等不相容岗位未分离；信息系统权限未严格落实实名制，账号权限与实际权责不符、一人存在多个账号等问题。 | G76: 23.预收互转规则控制 | H76: 预收电费应准确结转，关联到户 | I76: 营销售电业务-23.预收互转规则控制-控制措施01 | J76: 营销部门应明确预收互转规则并进行系统控制，确保预收结转精准到户。 | M76: √ | P76: √ | T76: 系统已建 | U76: 营销2.0系统 | V76: 1.系统预收电费互转规则； 2.系统预收电费互转明细； 3.岗位权限配置 | W76: 各省（自治区、直辖市）电力公司省公司-营销部门-电费管理人员 | X76: 每半年 | Y76: 抽查 | AA76: 年度 | AB76: 抽查 | AH76: 是 | AI76: 是 | AJ76: 《国家电网有限公司电费业务管理办法（征求意见稿）》第九章 电费账务 第六十条、第十一章 风险管控 第六十六条 《电费退费、预收互转规则业务规则（试行）》 | AK76: 国网营销部 | AL76: 省公司 | AM76: 电费
I77: 营销售电业务-23.预收互转规则控制-控制措施02 | J77: 营销部门对集团（关联）户设立与变更履行严格审批程序。 | L77: √ | M77: √ | T77: 系统已建 | U77: 营销2.0系统 | V77: 1.系统集团（关联）户申请资料； 2.岗位权限配置 | W77: 各级单位供服中心、供电公司-营销部门-电费管理及各级审批人员 | X77: 每季度 | Y77: 抽查 | AA77: 年度 | AB77: 抽查 | AH77: 是 | AI77: 是 | AJ77: 《国家电网有限公司电费业务管理办法（征求意见稿）》第九章 电费账务 第六十条、第十一章 风险管控 第六十六条 《电费退费、预收互转规则业务规则（试行）》 | AK77: 国网营销部 | AL77: 供服、地市 | AM77: 电费
I78: 营销售电业务-23.预收互转规则控制-控制措施03 | J78: 营销部门对集团（关联）户设立规范性、预收结转准确性开展数字化在线监测。 | M78: √ | S78: √ | T78: 系统待建 | U78: 营销2.0系统 | V78: 数字化在线监督结果或稽查工单及处理情况 | W78: 各级单位省公司、供电公司-营销部门-电费管理人员 | X78: 每季度 | Y78: 抽查 | AA78: 年度 | AB78: 抽查 | AD78: 预收互转监督——对集团（关联）户设立规范性、预收结转准确性开展在线监测 | AE78: 每月 | AF78: 全量 | AH78: 是 | AI78: 是 | AJ78: 《国家电网有限公司电费业务管理办法（征求意见稿）》第九章 电费账务 第六十条 《电费退费、预收互转规则业务规则（试行）》 | AK78: 国网营销部 | AL78: 省公司、地市 | AM78: 电费
C79: 会计信息真实完整、资金资产安全 | D79: 电费坏账管理 | E79: 应收电费账龄不准确，引发合规及资金风险。 | G79: 24.电费账龄与客户信用管理 | H79: 电费账龄准确，与客户准确关联 | I79: 营销售电业务-24.电费账龄与客户信用管理-控制措施01 | J79: 营销部门做好应收电费账龄管理，确保每一笔电费账龄准确，电费收取与账务执行不相容控制。 | K79: √ | M79: √ | T79: 系统已建 | U79: 营销2.0系统 | V79: 1.应收电费账龄台账； 2.岗位权限配置 | W79: 各级单位供服中心-营销部门-电费管理人员 | X79: 每年 | Y79: 抽查 | AA79: 年度 | AB79: 抽查 | AH79: 是 | AI79: 是 | AJ79: 《国家电网有限公司电费业务管理办法（征求意见稿）》第十一章 风险管控 | AK79: 国网营销部 | AL79: 供服 | AM79: 账务
I80: 营销售电业务-24.电费账龄与客户信用管理-控制措施02 | J80: 营销部门建立客户信用管理，清晰掌握重点客户经营状况，审慎评估回收风险，足额、准确提供应收电费坏账准备计提依据。 | M80: √ | Q80: √ | T80: 系统待建 | U80: 营销2.0系统 | V80: 1.应收电费账龄台账； 2.客户信用管理资料 | W80: 各级单位省公司-营销部门-电费管理人员 | X80: 每年 | Y80: 抽查 | AA80: 年度 | AB80: 抽查 | AH80: 是 | AI80: 是 | AJ80: 《国家电网有限公司电费业务管理办法（征求意见稿）》第十一章 风险管控 第六十六、六十七条 | AK80: 国网营销部 | AL80: 省公司 | AM80: 电费
C81: 会计信息真实完整 | D81: 电费坏账管理 | E81: 应收电费坏账未及时计提，计提不准确，导致利润失真风险。 | G81: 25.电费坏账计提与核销 | H81: 坏账计提足额准确 | I81: 营销售电业务-25.电费坏账计提与核销-控制措施01 | J81: 财务部门按照统一的坏账计提政策，制定准确的坏账计提方案。营销部门接收财务坏账计提方案，并根据应收电费账龄和客户信用情况生成坏账计提依据，经财务审核后完成坏账计提（转回）。 | M81: √ | Q81: √ | T81: 系统待建 | U81: 智慧财务、营销2.0系统 | V81: 1.应收电费账龄台账； 2.客户信用管理资料； 3.系统电费坏账计提规则及记录 | W81: 各级单位省公司、供电公司-财务部门-账务管理人员；各级单位省公司、供电公司-营销部门-电费管理人员 | X81: 每年 | Y81: 抽查 | AA81: 年度 | AB81: 抽查 | AH81: 是 | AI81: 是 | AJ81: 《国家电网有限公司会计核算办法》第二章债权债务、《国家电网有限公司会计基础管理办法》第六十二条 《国家电网有限公司电费业务管理办法（征求意见稿）》第十一章 风险管控 第六十六、六十七条 | AK81: 国网财务部、国网营销部 | AL81: 省公司、地市 | AM81: 电费、财务
I82: 营销售电业务-25.电费坏账计提与核销-控制措施02 | J82: 对满足条件的电费坏账，营销部门应履行决策程序，经财务审核后核销，同步做好账销案存管理。 | M82: √ | Q82: √ | T82: 系统待建 | U82: 营销2.0系统、智慧财务 | V82: 1.应收电费账龄台账； 2.客户信用等级评价及其他资料； 3.坏账核销资料 | W82: 各级单位省公司、供电公司-营销部门-电费管理人员；各级单位省公司、供电公司-财务部门-账务管理人员 | X82: 每年 | Y82: 抽查 | AA82: 年度 | AB82: 抽查 | AD82: 电费坏账计提监督--对应收电费账龄（超一年以上的欠费）、坏账计提依据及结果进行监督 | AE82: 每年 | AF82: 全量 | AH82: 是 | AI82: 是 | AJ82: 《国家电网有限公司会计核算办法》 《国家电网有限公司会计基础管理办法》第六十二条 | AK82: 国网营销部、国网财务部 | AL82: 省公司、地市 | AM82: 电费、财务
A83: 营销售电业务 | B83: 六、电费实收管理 | C83: 会计信息真实完整、资金资产安全 | D83: 资金勾对 | E83: 实收账务与资金流水不匹配，导致账实不符风险。 | G83: 26.资金勾对复核 | H83: 电费实收账务与资金流水准确关联 | I83: 营销售电业务-26.资金勾对复核-控制措施01 | J83: 营销部门按日完成资金日流水与账务核对，确保账实相符，同时将收款明细凭证与银行资金流水勾对记录按日传递至财务，电费收费与电费账务执行不相容分离。 | K83: √ | P83: √ | Q83: √ | T83: 系统已建 | U83: 营销2.0系统 | V83: 1.系统资金勾对记录； 2.系统电费实收凭证； 3.营财银线上对账记录 | W83: 各级单位供服中心、会计服务中心-电费管理人员 | X83: 每月 | Y83: 抽查 | AA83: 年度 | AB83: 抽查 | AH83: 是 | AI83: 是 | AJ83: 《国网营销部财务部关于明确营销2.0系统与智慧共享财务平台系统集成有关问题的意见》（营销营业〔2023〕86号） | AK83: 国网营销部 | AL83: 供服、会服 | AM83: 账务、账务
I84: 营销售电业务-26.资金勾对复核-控制措施02 | J84: 财务部门按日对营销的对账结果进行复核，开展线上营财银对账。 | M84: √ | Q84: √ | S84: √ | T84: 系统已建 | U84: 智慧财务 | V84: 银企对账记录 | W84: 各省（自治区、直辖市）电力公司供服中心、会计服务中心-资金管理人员 | X84: 每季度 | Y84: 抽查 | AA84: 年度 | AB84: 抽查 | AD84: 银企对账监督——营财银对账 | AE84: 每日 | AF84: 全量 | AH84: 是 | AI84: 是 | AJ84: 《国网营销部财务部关于明确营销2.0系统与智慧共享财务平台系统集成有关问题的意见》（营销营业〔2023〕86号） | AK84: 国网财务部 | AL84: 供服、会服 | AM84: 账务、账务
I85: 营销售电业务-26.资金勾对复核-控制措施03 | J85: 财务部门按月开展银行对账单与营财核对一致的收款账务明细勾对校核，编制银行存款（商户号）余额调节表，从严管控未达账项。 | K85: √ | M85: √ | Q85: √ | T85: 系统已建 | U85: 智慧财务 | V85: 1.银企对账记录； 2.银行余额调节表 | W85: 各省（自治区、直辖市）电力公司供服中心、会计服务中心-资金管理人员 | X85: 每季度 | Y85: 抽查 | AA85: 年度 | AB85: 抽查 | AH85: 是 | AI85: 是 | AJ85: 《国网营销部财务部关于明确营销2.0系统与智慧共享财务平台系统集成有关问题的意见》（营销营业〔2023〕86号） 《国家电网有限公司司库管理办法》第三十八条、三十九条 | AK85: 国网财务部 | AL85: 供服、会服 | AM85: 财务
C86: 会计信息真实完整、资金资产安全 | D86: 不明款管理 | E86: 不明款确认及销账不准确，导致资金性质混乱、账实不符风险。 | G86: 27.不明款确认与核销 | H86: 强化不明款管控，不明款销账时应确保与客户精准匹配 | I86: 营销售电业务-27.不明款确认与核销-控制措施01 | J86: 营销部门对长期未关联到户的银行流水应及时确认不明款，并加强清理。 | P86: √ | Q86: √ | T86: 系统已建 | U86: 营销2.0系统 | V86: 1.不明款确认（销账）明细表； 2.系统不明款台账或流水记录 | W86: 各级单位供服中心、供电公司-营销部门-电费管理人员 | X86: 每半年 | Y86: 抽查 | AA86: 年度 | AB86: 抽查 | AH86: 是 | AI86: 否 | AJ86: 《国家电网有限公司电费业务管理办法（征求意见稿）》第二章 职责分工 第九章电费账务 | AK86: 国网营销部 | AL86: 供服、地市 | AM86: 账务、电费
I87: 营销售电业务-27.不明款确认与核销-控制措施02 | J87: 营销部门对三年及以上或有确凿证据表明无法支付的不明款项，应及时履行决策程序，经严格审批后结转营业外收入。 | L87: √ | Q87: √ | T87: 线下管控、系统已建 | U87: 营销2.0系统 | V87: 1.不明款转营业外资料； 2.不明款转营业外记录 | W87: 各级单位供电公司-营销部门-电费管理及各级审批人员 | X87: 每年 | Y87: 抽查 | AA87: 年度 | AB87: 抽查 | AH87: 是 | AI87: 否 | AJ87: 《国家电网有限公司电费业务管理办法（征求意见稿）》第二章 职责分工 第九章电费账务 《国家电网有限公司会计基础管理办法》中第四节第六十二条 | AK87: 国网营销部 | AL87: 地市 | AM87: 电费
I88: 营销售电业务-27.不明款确认与核销-控制措施03 | J88: 财务部门对跨月的不明款项进行督导消缺，并对不明款转营业外规范性开展核查。 | Q88: √ | S88: √ | T88: 系统已建 | U88: 智慧财务 | V88: 1.不明款台账或流水记录； 2.不明款转营业外资料； 3.不明款转营业外记录 | W88: 各级单位供电公司-财务部门-资金（总账）管理人员、销售电价管理人员 | X88: 每季度 | Y88: 抽查 | AA88: 年度 | AB88: 抽查 | AD88: 不明款对账监督——对不明款进行预警与督导消缺 | AE88: 每月 | AF88: 全量 | AH88: 是 | AI88: 是 | AJ88: 《国网营销部财务部关于明确营销2.0系统与智慧共享财务平台系统集成有关问题的意见》（营销营业〔2023〕86号） 《国家电网有限公司会计基础管理办法》中第四节第六十二条 | AK88: 国网财务部 | AL88: 地市 | AM88: 财务
A89: 营销售电业务 | B89: 七、营销退费管理 | C89: 会计信息真实完整、资金资产安全 | D89: 退费申请 | E89: 退费资料不真实、系统录入错误，导致虚假退费、重复退费或资金冒领风险。 | F89: 20.营销系统权限管控不严：存在重要业务流程权限设置不合规；电费收费、账务处理、财务审核和违约用电查处、审批等不相容岗位未分离；信息系统权限未严格落实实名制，账号权限与实际权责不符、一人存在多个账号等问题。 | G89: 28.退费申请与退费资料一致性管控 | H89: 退费申请与退费资料一致，系统录入准确 | I89: 营销售电业务-28.退费申请与退费资料一致性管控-控制措施01 | J89: 营销部门明确营销退费场景，建立分类分级审批标准，优先选用原路退回和常用缴费账号退回，并探索建立直退机制。对因客户申请等其他原因非原路退回的提级审批。 | L89: √ | M89: √ | P89: √ | T89: 系统待建 | U89: 营销2.0系统 | V89: 1.退费分级分类审批标准； 2.原路退回管理及建设情况； 3.退费审批分级授权记录 | W89: 各级单位供电公司-营销部门-电费管理人员及各级审批人员 | X89: 每半年 | Y89: 抽查 | AA89: 年度 | AB89: 抽查 | AH89: 是 | AI89: 是 | AJ89: 《国家电网有限公司电费业务管理办法（征求意见稿）》第八章 电费收支 第五十一条 《电费退费、预收互转规则业务规则（试行）》 | AK89: 国网营销部 | AL89: 地市 | AM89: 电费
I90: 营销售电业务-28.退费申请与退费资料一致性管控-控制措施02 | J90: 营销部门业务受理人员对退费资料完整性、客户关键信息与资料一致性进行核对，加强系统上传影像与线下资料一致性管控，并准确录入系统。 | M90: √ | P90: √ | T90: 线下管控 | V90: 1.系统客户退费资料影像； 2.系统退费信息 | W90: 各级单位供电公司-营销部门-业务受理人员 | X90: 每季度 | Y90: 抽查 | AA90: 年度 | AB90: 抽查 | AH90: 是 | AI90: 是 | AJ90: 《国家电网有限公司电费业务管理办法（征求意见稿）》第八章 电费收支 第五十一条 《电费退费、预收互转规则业务规则（试行）》 | AK90: 国网营销部 | AL90: 地市 | AM90: 电费
I91: 营销售电业务-28.退费申请与退费资料一致性管控-控制措施03 | J91: 营销部门电费管理人员对系统退费信息与退费资料一致性进行复核。 | M91: √ | T91: 系统已建 | U91: 营销2.0系统 | V91: 系统退费信息及审核记录 | W91: 各级单位供电公司-营销部门-电费管理人员 | X91: 每季度 | Y91: 抽查 | AA91: 年度 | AB91: 抽查 | AH91: 是 | AI91: 是 | AJ91: 《国家电网有限公司电费业务管理办法（征求意见稿）》第八章 电费收支 第五十一条 《电费退费、预收互转规则业务规则（试行）》 | AK91: 国网营销部 | AL91: 地市 | AM91: 电费
I92: 营销售电业务-28.退费申请与退费资料一致性管控-控制措施04 | J92: 营销部门加强销户（过户）业务联办退费管理，对销户后无法联系客户或客户拒不办理等原因导致的确实无法支付的款项，营销部门及时履行决策程序后，经严格审批后结转营业外收入，并做好账销案存管理。 | L92: √ | Q92: √ | T92: 线下管控、系统已建 | U92: 营销2.0系统 | V92: 1.销户有预收明细； 2.销户有预收转营业外记录； 3.销户有预收转营业外资料 | W92: 各级单位供电公司-营销部门-电费管理及各级审批人员 | X92: 每半年 | Y92: 抽查 | AA92: 年度 | AB92: 抽查 | AH92: 是 | AI92: 是 | AJ92: 《国家电网有限公司电费业务管理办法（征求意见稿）》第八章 电费收支 第五十一条 《国家电网有限公司会计基础管理办法》中第四节第六十二条 《电费退费、预收互转规则业务规则（试行）》 | AK92: 国网营销部 | AL92: 地市 | AM92: 电费、业扩
I93: 营销售电业务-28.退费申请与退费资料一致性管控-控制措施05 | J93: 财务部门对客户收款信息、退费主体资格开展系统录入信息与退费影像一致性复查，对结转营业外收入规范性开展核查。 | M93: √ | Q93: √ | T93: 系统已建 | U93: 智慧财务 | V93: 1.系统退费信息及审核记录； 2.销户有预收转营业外记录； 3.销户有预收转营业外资料 | W93: 各级单位供电公司-财务部门-销售电价管理人员 | X93: 每半年 | Y93: 抽查 | AA93: 年度 | AB93: 抽查 | AH93: 是 | AI93: 是 | AJ93: 《国网营销部财务部关于明确营销2.0系统与智慧共享财务平台系统集成有关问题的意见》（营销营业〔2023〕86号） 《国家电网有限公司会计基础管理办法》中第四节第六十二条 | AK93: 国网财务部 | AL93: 地市 | AM93: 财务
C94: 资金资产安全 | D94: 退费审批 | E94: 退费未经有效审核审批，导致公司资金流失、财务数据失真风险。 | F94: 20.营销系统权限管控不严：存在重要业务流程权限设置不合规；电费收费、账务处理、财务审核和违约用电查处、审批等不相容岗位未分离；信息系统权限未严格落实实名制，账号权限与实际权责不符、一人存在多个账号等问题。 | G94: 29.退费审批权限及流程设置 | H94: 退费资金分级授权科学、合理 | I94: 营销售电业务-29.退费审批权限及流程设置-控制措施01 | J94: 财务部门建立电费退费资金分级授权审批机制，确保系统流程轨迹可视、授权管理科学。 | L94: √ | T94: 系统已建 | U94: 智慧财务 | V94: 1.资金分级授权 2.支付轨迹 | W94: 各省（自治区、直辖市）电力公司省公司-财务部门-资金分级授权管理人员 | X94: 每年 | Y94: 抽查 | AA94: 年度 | AB94: 抽查 | AH94: 是 | AI94: 是 | AJ94: 《国家电网有限公司司库管理办法》第七十四条 | AK94: 国网财务部 | AL94: 省公司 | AM94: 财务
I95: 营销售电业务-29.退费审批权限及流程设置-控制措施02 | J95: 营销部门按照资金分级授权建立内部退费审批流程，对权限配置与岗位权限一致性进行校核。 | L95: √ | M95: √ | P95: √ | T95: 系统已建 | U95: 营销2.0系统 | V95: 1.系统退费审批单； 2.资金分级授权； 3.岗位权限配置； 4.系统退费信息 | W95: 各级单位省公司、供电公司-营销部门-电费管理及各级审批人员 | X95: 每年 | Y95: 抽查 | AA95: 年度 | AB95: 抽查 | AH95: 是 | AI95: 是 | AJ95: 《国家电网有限公司电费业务管理办法（征求意见稿）》第八章 电费收支 第五十一条 | AK95: 国网营销部 | AL95: 省公司、地市 | AM95: 电费
C96: 资金资产安全 | D96: 退费支付 | E96: 退费支付管控不到位，导致资金流向失控，引发资金合规风险。 | G96: 30.退费支付监控 | H96: 严格退费支付管理，确保资金准确支付到户。 | I96: 营销售电业务-30.退费支付监控-控制措施01 | J96: 财务部门建立支付全流程线上监控机制，并配置大额对私、疑似重复等进行复核，确保退费支付安全、准确。 | K96: √ | M96: √ | P96: √ | T96: 系统已建 | U96: 智慧财务 | V96: 系统退费支付审核规则设置记录 | W96: 各省（自治区、直辖市）电力公司会计服务中心、供电公司-财务部门-资金管理人员 | X96: 每半年 | Y96: 抽查 | AA96: 年度 | AB96: 抽查 | AD96: 退费支付监控——建立支付全流程线上监控 | AE96: 每月 | AF96: 全量 | AH96: 是 | AI96: 是 | AJ96: 《国家电网有限公司司库管理办法》 | AK96: 国网财务部 | AL96: 会服、地市 | AM96: 财务
A97: 营销售电业务 | B97: 八、营销稽查管理 | C97: 会计信息真实完整 | D97: 稽核计划制定 | E97: 营销稽查未有效实施，导致稽查结果失真。 | G97: 31.稽核计划制定 | H97: 健全营销稽查规则，并定期实施 | I97: 营销售电业务-31.稽核计划制定-控制措施01 | J97: 省公司营销部门结合国网稽核规则及增补规则健全营销稽查机制并定期更新。 | M97: √ | T97: 系统已建 | U97: 营销2.0系统 | V97: 系统稽查任务及稽查规则 | W97: 各级单位省公司-营销部门-稽查监控人员 | X97: 每年 | Y97: 抽查 | AA97: 年度 | AB97: 抽查 | AH97: 是 | AI97: 是 | AJ97: 《国家电网有限公司营销稽查监控运营管理办法》 | AK97: 国网营销部 | AL97: 省公司 | AM97: 稽查
I98: 营销售电业务-31.稽核计划制定-控制措施02 | J98: 各级营销部门门结合稽核规则对业扩报装、计量采集、电费电价、收费及账务等建立日常稽查，形成营销价值闭环稽核管理。 | M98: √ | T98: 系统已建 | U98: 营销2.0系统 | V98: 1.系统稽查任务及稽查规则； 2.系统稽查工单 | W98: 各级单位供服中心、供电公司-营销部门-稽查监控人员 | X98: 每年 | Y98: 抽查 | AA98: 年度 | AB98: 抽查 | AH98: 是 | AI98: 是 | AJ98: 《国家电网有限公司营销稽查监控运营管理办法》 | AK98: 国网营销部 | AL98: 供服、地市 | AM98: 稽查
C99: 会计信息真实完整 | D99: 稽核工单回单 | E99: 异常问题未有效整改，导致稽查流于形式。 | G99: 32.异常事项闭环销号 | H99: 异常问题处理应建立业稽联动审批机制，确保整改成效 | I99: 营销售电业务-32.异常事项闭环销号-控制措施01 | J99: 营销部门对稽查结果处理明确分类管理标准，并实施业稽联动审批机制，严格履行查办分离，落实整改责任。涉及客户信息变动及量价费调整的应联动业务工单同步调整。涉及客户信息变动及量价费调整的应督办专业发起业务工单进行问题整改 | K99: √ | M99: √ | T99: 系统已建 | U99: 营销2.0系统 | V99: 1.稽查工单处理标准相关规范； 2..系统工单审批流程及岗位权限配置； 3.系统稽查工单； 4.异常问题处理审核审批记录 | W99: 各级单位供服中心、供电公司-营销部门-稽查管理人员 | X99: 每半年 | Y99: 抽查 | AA99: 年度 | AB99: 抽查 | AH99: 是 | AI99: 是 | AJ99: 《国家电网有限公司营销稽查监控运营管理办法》 | AK99: 国网营销部 | AL99: 供服、地市 | AM99: 稽查
I100: 营销售电业务-32.异常事项闭环销号-控制措施02 | J100: 营销部门稽查监控人员对稽查异常事项闭环处理情况开展检查，对涉及量价费的调整事项复核消缺。 | M100: √ | T100: 系统已建 | U100: 营销2.0系统 | V100: 1.系统稽查工单； 2.异常问题复核相关资料 | W100: 各级单位供服中心、供电公司-营销部门-稽查监控人员 | X100: 每半年 | Y100: 抽查 | AA100: 年度 | AB100: 抽查 | AH100: 是 | AI100: 是 | AJ100: 《国家电网有限公司营销稽查监控运营管理办法》 | AK100: 国网营销部 | AL100: 供服、地市 | AM100: 稽查
...

Sheet 营销售电（核对过程7.20） (2)
A1: 风控矩阵-营销售电业务
A2: 业务条线 | B2: 业务领域 | C2: 控制目标 | D2: 业务流程步骤 | E2: 经营风险 | F2: 典型问题 | G2: 关键控制点 | H2: 控制要求 | I2: 控制措施编号 | J2: 控制措施 | K2: 控制措施分类 | T2: 控制方式 | U2: 控制系统 | V2: 控制载体 | W2: 责任主体 | X2: 业务自评价 | AA2: 集团监督评价 | AD2: 数字化监督场景 | AH2: 现有制度及文件落实情况 | AK2: 总部审核部门 | AL2: 变化分类 | AM2: 矩阵变化内容说明 | AN2: 层级 | AO2: 专业 | AP2: 专业审核意见
K3: 不相容岗位 | L3: 分级授权 | M3: 业务真实性控制 | N3: 预算管控 | O3: 合同控制 | P3: 收付控制 | Q3: 会计监督 | R3: 财产保护 | S3: 分析与评价 | X3: 评价频率 | Y3: 评价范围 | Z3: 评价结论 | AA3: 评价频率 | AB3: 评价范围 | AC3: 评价结论 | AD3: 数字化监督场景 | AE3: 监督频率 | AF3: 监督范围 | AG3: 评价结论 | AH3: 是否已要求 | AI3: 是否满足要求 | AJ3: 对应制度及文件名称
A4: 营销售电业务 | B4: 一、客户信息与合同签订管理 | C4: 会计信息真实完整、资金资产安全 | D4: 业扩报装受理 | E4: 客户信息录入不准确，与现场不一致，引发虚假立户及电费收取不规范风险。 | F4: 19.两部制电价执行不正确：存在应执行未执行两部制电价、分户报装规避两部制电价、变更用电少收基本电费、需量基本电费计收不准确等问题。 | G4: 1.系统客户信息创建 | H4: 系统客户信息应与客户报装资料、现场用电情况一致。 | I4: 营销售电业务-1.系统客户信息创建-控制措施01 | J4: 营销部门业务受理人员根据客户报装资料做好系统客户信息的创建，并对报装资料完整性、有效性负责。 | M4: √ | T4: 线下管控 | V4: 1.系统业扩工单； 2.客户报装原始资料； 3.系统客户档案 | W4: 各级单位-营销部门-业务受理人员 | X4: 每年 | Y4: 抽查 | AA4: 年度 | AB4: 抽查 | AH4: 是 | AI4: 是 | AJ4: 《国家电网有限公司业扩报装管理规则（征求意见稿）》第三章 业务受理 | AK4: 国网营销部 | AL4: 无变化，直接引用 | AM4: 无变化，直接引用 | AN4: 地市 | AO4: 业扩 | AP4: 业扩专业：无变化，直接引用 | AQ4: =A4=[1]营销售电!A4 -> TRUE | AR4: =B4=[1]营销售电!B4 -> TRUE | AS4: =C4=[1]营销售电!C4 -> TRUE | AT4: =D4=[1]营销售电!D4 -> TRUE | AU4: =E4=[1]营销售电!E4 -> TRUE | AV4: =F4=[1]营销售电!F4 -> TRUE | AW4: =G4=[1]营销售电!G4 -> TRUE | AX4: =H4=[1]营销售电!H4 -> TRUE | ... CA4: =AK4=[1]营销售电!AK4 -> TRUE
I5: 营销售电业务-1.系统客户信息创建-控制措施02 | J5: 营销部门应在客户新装、增容、变更用电等申请受理时，建立稽查主题前置业务环节等数智审核功能，提高客户基础信息创建质量。 | M5: √ | T5: 系统待建 | U5: 营销2.0系统 | V5: 1.系统客户档案； 2.客户报装原始资料； 3.数智审核相关功能资料 | W5: 各省（自治区、直辖市）电力公司--营销部门-业扩报装管理人员 | X5: 每年 | Y5: 抽查 | AA5: 年度 | AB5: 抽查 | AH5: 是 | AI5: 是 | AJ5: 《国家电网有限公司业扩报装管理规则（征求意见稿）》第三章 业务受理 | AK5: 国网营销部 | AL5: 无变化，直接引用 | AM5: 无变化，直接引用 | AN5: 供服 | AO5: 业扩 | AP5: 业扩专业：无变化，直接引用 | AQ5: =A5=[1]营销售电!A5 -> TRUE | AR5: =B5=[1]营销售电!B5 -> TRUE | AS5: =C5=[1]营销售电!C5 -> TRUE | AT5: =D5=[1]营销售电!D5 -> TRUE | AU5: =E5=[1]营销售电!E5 -> TRUE | AV5: =F5=[1]营销售电!F5 -> TRUE | AW5: =G5=[1]营销售电!G5 -> TRUE | AX5: =H5=[1]营销售电!H5 -> TRUE | ... CA5: =AK5=[1]营销售电!AK5 -> TRUE
I6: 营销售电业务-1.系统客户信息创建-控制措施03 | J6: 营销部门业务办理人员结合现场勘查情况对客户关键信息真实性、准确性复核，业务受理与业务办理执行不相容控制。 | K6: √ | M6: √ | T6: 线下管控 | V6: 1.系统业扩工单； 2.客户报装原始资料； 3.系统客户档案； 4.系统授权审批记录 | W6: 各级单位-营销部门-业务办理人员 | X6: 每年 | Y6: 抽查 | AA6: 年度 | AB6: 抽查 | AH6: 是 | AI6: 是 | AJ6: 《国家电网有限公司业扩报装管理规则（征求意见稿）》第三章 业务受理 | AK6: 国网营销部 | AL6: 无变化，直接引用 | AM6: 无变化，直接引用 | AN6: 地市 | AO6: 业扩 | AP6: 业扩专业：无变化，直接引用 | AQ6: =A6=[1]营销售电!A6 -> TRUE | AR6: =B6=[1]营销售电!B6 -> TRUE | AS6: =C6=[1]营销售电!C6 -> TRUE | AT6: =D6=[1]营销售电!D6 -> TRUE | AU6: =E6=[1]营销售电!E6 -> TRUE | AV6: =F6=[1]营销售电!F6 -> TRUE | AW6: =G6=[1]营销售电!G6 -> TRUE | AX6: =H6=[1]营销售电!H6 -> TRUE | ... CA6: =AK6=[1]营销售电!AK6 -> TRUE
I7: 营销售电业务-1.系统客户信息创建-控制措施04 | J7: 营销部门对分户报装规避基本电费、违规改变用电性质等开展数字化在线监督与现场检查。 | M7: √ | S7: √ | T7: 系统已建 | U7: 营销2.0系统 | V7: 数字化监督相关资料或稽查工单及处理情况 | W7: 各级单位-营销部门-业务审核人员 | X7: 每半年 | Y7: 抽查 | AA7: 年度 | AB7: 抽查 | AD7: 分户报装规避基本电费监督——对一址多户开展在线监督 | AE7: 每季度 | AF7: 全量 | AH7: 是 | AI7: 是 | AJ7: 《国家电网有限公司业扩报装管理规则（征求意见稿）》第三章 业务受理 | AK7: 国网营销部 | AL7: 无变化，直接引用 | AM7: 无变化，直接引用 | AN7: 地市 | AO7: 业扩 | AP7: 业扩专业：无变化，直接引用 | AQ7: =A7=[1]营销售电!A7 -> TRUE | AR7: =B7=[1]营销售电!B7 -> TRUE | AS7: =C7=[1]营销售电!C7 -> TRUE | AT7: =D7=[1]营销售电!D7 -> TRUE | AU7: =E7=[1]营销售电!E7 -> TRUE | AV7: =F7=[1]营销售电!F7 -> TRUE | AW7: =G7=[1]营销售电!G7 -> TRUE | AX7: =H7=[1]营销售电!H7 -> TRUE | ... CA7: =AK7=[1]营销售电!AK7 -> TRUE
C8: 会计信息真实完整、资金资产安全 | D8: 方案答复与工程实施 | E8: 客户用电容量核定不准确、录入错误，导致基本电费执行不准确、电费少收。 | F8: 19.两部制电价执行不正确：存在应执行未执行两部制电价、分户报装规避两部制电价、变更用电少收基本电费、需量基本电费计收不准确等问题。 | G8: 2.客户用电容量的确定 | H8: 系统容量与现场用电情况保持一致。 | I8: 营销售电业务-2.客户用电容量的确定创建-控制措施01 | J8: 营销部门现场勘查人员应准确核定客户用电容量与负荷性质，确保计量、计费方案、供电方式等准确。 | M8: √ | T8: 线下管控 | V8: 1.系统业扩工单（现场勘查验收单）； 2.系统客户档案（供电方案等） | W8: 各级单位-营销部门-现场勘查人员 | X8: 每年 | Y8: 抽查 | AA8: 年度 | AB8: 抽查 | AH8: 是 | AI8: 是 | AJ8: 《国家电网有限公司业扩报装管理规则（征求意见稿）》第四章 供电方案编制及答复 | AK8: 国网营销部 | AL8: 无变化，但建议省公司优化系统。 | AM8: 建议新装增容的供电方案会审实现配电、调控、发展、营销多专业线上会审（株洲、岳阳） | AN8: 地市 | AO8: 业扩 | AP8: 业扩专业：无变化，直接引用 | AQ8: =A8=[1]营销售电!A8 -> TRUE | AR8: =B8=[1]营销售电!B8 -> TRUE | AS8: =C8=[1]营销售电!C8 -> TRUE | AT8: =D8=[1]营销售电!D8 -> TRUE | AU8: =E8=[1]营销售电!E8 -> TRUE | AV8: =F8=[1]营销售电!F8 -> TRUE | AW8: =G8=[1]营销售电!G8 -> TRUE | AX8: =H8=[1]营销售电!H8 -> TRUE | ... CA8: =AK8=[1]营销售电!AK8 -> TRUE
I9: 营销售电业务-2.客户用电容量的确定创建-控制措施02 | J9: 对于加装变压器的高压客户，需取得变压器出厂合格证明及型式试验报告等容量信息佐证材料并上传系统，确保系统录入容量与现场用电情况一致。 | M9: √ | T9: 系统已建 | U9: 营销2.0系统 | V9: 1.系统业扩工单信息（现场勘查验收单）； 2.客户报装原始资料（含用电负荷清单、变压器出厂合格证明及型式试验报告等）； 3.系统客户档案 | W9: 各级单位-营销部门-业务办理人员 | X9: 每半年 | Y9: 抽查 | AA9: 年度 | AB9: 抽查 | AH9: 是 | AI9: 是 | AJ9: 《国家电网有限公司业扩报装管理规则（征求意见稿）》第四章 供电方案编制及答复 | AK9: 国网营销部 | AL9: 无变化，直接引用 | AM9: 无变化，直接引用 | AN9: 地市 | AO9: 业扩 | AP9: 业扩专业：无变化，直接引用 | AQ9: =A9=[1]营销售电!A9 -> TRUE | AR9: =B9=[1]营销售电!B9 -> TRUE | AS9: =C9=[1]营销售电!C9 -> TRUE | AT9: =D9=[1]营销售电!D9 -> TRUE | AU9: =E9=[1]营销售电!E9 -> TRUE | AV9: =F9=[1]营销售电!F9 -> TRUE | AW9: =G9=[1]营销售电!G9 -> TRUE | AX9: =H9=[1]营销售电!H9 -> TRUE | ... CA9: =AK9=[1]营销售电!AK9 -> TRUE
I10: 营销售电业务-2.客户用电容量的确定创建-控制措施03 | J10: 营销部门对超容用电、基本电费异常、高可靠性供电费收取不规范开展数字化在线监督与现场检查。 | M10: √ | S10: √ | T10: 系统已建 | U10: 营销2.0系统 | V10: 数字化监督相关资料或稽查结果与处理情况 | W10: 各级单位-营销部门-业务审核人员 | X10: 每半年 | Y10: 抽查 | AA10: 年度 | AB10: 抽查 | AD10: 客户容量与电量联动监测——对超容用电、基本电费异常、高可靠性供电费收取不规范开展在线监督 | AE10: 每季度 | AF10: 全量 | AH10: 是 | AI10: 是 | AJ10: 《国家电网有限公司业扩报装管理规则（征求意见稿）》第四章 供电方案编制及答复 | AK10: 国网营销部 | AL10: 无变化，直接引用 | AM10: 无变化，直接引用 | AN10: 地市 | AO10: 业扩 | AP10: 业扩专业：无变化，直接引用 | AQ10: =A10=[1]营销售电!A10 -> TRUE | AR10: =B10=[1]营销售电!B10 -> TRUE | AS10: =C10=[1]营销售电!C10 -> TRUE | AT10: =D10=[1]营销售电!D10 -> TRUE | AU10: =E10=[1]营销售电!E10 -> TRUE | AV10: =F10=[1]营销售电!F10 -> TRUE | AW10: =G10=[1]营销售电!G10 -> TRUE | AX10: =H10=[1]营销售电!H10 -> TRUE | ... CA10: =AK10=[1]营销售电!AK10 -> TRUE
A11: 营销售电业务 | B11: 一、客户信息与合同签订管理 | C11: 会计信息真实完整、资金资产安全 | D11: 客户信息变更 | E11: 客户信息变更不合规，导致电费计收不准确，引发合规风险。 | F11: 19.两部制电价执行不正确：存在应执行未执行两部制电价、分户报装规避两部制电价、变更用电少收基本电费、需量基本电费计收不准确等问题。 | G11: 3.系统客户信息变更 | H11: 客户关键信息变更应结合业务工单联动调整，严禁无业务动因创建或修改客户信息行为。 | I11: 营销售电业务-3.系统客户信息变更-控制措施01 | J11: 营销部门对客户户名、电价、用电容量等关键信息的变更，应结合变更业务联动调整并经审批后实施。 | L11: √ | M11: √ | T11: 系统已建 | U11: 营销2.0系统 | V11: 1.系统变更工单； 2.客户变更原始资料； 3.系统客户档案； 4.系统授权审批记录 | W11: 各级单位-营销部门-业务审核及各级审批人员 | X11: 每年 | Y11: 抽查 | AA11: 年度 | AB11: 抽查 | AH11: 是 | AI11: 是 | AJ11: 《变更用电业务规则（试行）》 | AK11: 国网营销部 | AL11: 无变化，但建议省公司优化系统。 | AM11: 【补充需求】变更办理是规避一址多户的系统控制需求（同片区 / 临近地址）（岳阳） | AN11: 地市 | AO11: 业扩 | AP11: 业扩专业：无变化，直接引用 | AQ11: =A11=[1]营销售电!A11 -> TRUE | AR11: =B11=[1]营销售电!B11 -> TRUE | AS11: =C11=[1]营销售电!C11 -> TRUE | AT11: =D11=[1]营销售电!D11 -> TRUE | AU11: =E11=[1]营销售电!E11 -> TRUE | AV11: =F11=[1]营销售电!F11 -> TRUE | AW11: =G11=[1]营销售电!G11 -> TRUE | AX11: =H11=[1]营销售电!H11 -> TRUE | ... CA11: =AK11=[1]营销售电!AK11 -> TRUE
I12: 营销售电业务-3.系统客户信息变更-控制措施02 | J12: 营销部门对影响价费关键信息的变更业务开展现场查验，确保用电信息与现场一致。 | M12: √ | T12: 线下管控 | V12: 现场核查相关记录 | W12: 各级单位-营销部门-现场勘查人员 | X12: 每年 | Y12: 抽查 | AA12: 年度 | AB12: 抽查 | AH12: 是 | AI12: 是 | AJ12: 《变更用电业务规则（试行）》 | AK12: 国网营销部 | AL12: 无变化，直接引用 | AM12: 无变化，直接引用 | AN12: 地市 | AO12: 业扩 | AP12: 业扩专业：无变化，直接引用 | AQ12: =A12=[1]营销售电!A12 -> TRUE | AR12: =B12=[1]营销售电!B12 -> TRUE | AS12: =C12=[1]营销售电!C12 -> TRUE | AT12: =D12=[1]营销售电!D12 -> TRUE | AU12: =E12=[1]营销售电!E12 -> TRUE | AV12: =F12=[1]营销售电!F12 -> TRUE | AW12: =G12=[1]营销售电!G12 -> TRUE | AX12: =H12=[1]营销售电!H12 -> TRUE | ... CA12: =AK12=[1]营销售电!AK12 -> TRUE
C13: 会计信息真实完整、资金资产安全 | D13: 合同签订 | E13: 合同签订未使用公司统一且生效文本，导致电费计收合法权益无法得到保障。 | G13: 4.供用电合同签订 | H13: 供用电合同签订应使用公司统一且生效的文本。 | I13: 营销售电业务-4.供用电合同签订-控制措施01 | J13: 国网营销部统一管理合同文本，并明确执行要求、生效时间，及客户业务变更时不需重签合同的业务类型。各省（自治区、直辖市）电力公司参考统一文本拟定本单位合同文本、特别约定事项等，经法律合规部门审核后使用。 | O13: √ | T13: 系统已建 | U13: 营销2.0系统 | V13: 1.合同统一文本； 2.制度或通知 | W13: 国网营销部-合同管理人员；各省（自治区、直辖市）电力公司-营销部门-合同管理人员 | X13: 每年 | Y13: 抽查 | AA13: 年度 | AB13: 抽查 | AH13: 是 | AI13: 是 | AJ13: 《国家电网有限公司电费业务管理办法（征求意见稿）》第四章 合同协议 《国网营销部关于印发变更用电业务规则》 《国家电网有限公司业扩报装管理规则（征求意见稿）》第六十三、六十四条 《国家电网有限公司合同管理办法》四十六条、六十四-六十六条 | AK13: 国网营销部 | AL13: 无变化，但建议省公司优化系统。 | AM13: 从业务流程中提取相应字段，生成系统标准化合同（株洲） | AN13: 省公司 | AO13: 业扩 | AP13: 业扩专业：无变化，直接引用 | AQ13: =A13=[1]营销售电!A13 -> TRUE | AR13: =B13=[1]营销售电!B13 -> TRUE | AS13: =C13=[1]营销售电!C13 -> TRUE | AT13: =D13=[1]营销售电!D13 -> TRUE | AU13: =E13=[1]营销售电!E13 -> TRUE | AV13: =F13=[1]营销售电!F13 -> TRUE | AW13: =G13=[1]营销售电!G13 -> TRUE | AX13: =H13=[1]营销售电!H13 -> TRUE | ... CA13: =AK13=[1]营销售电!AK13 -> TRUE
I14: 营销售电业务-4.供用电合同签订-控制措施02 | J14: 营销部门合同签订人员应严格使用本省统一且生效文本。 | O14: √ | T14: 系统已建 | U14: 营销2.0系统 | V14: 1.供用电合同； 2.合同统一文本 | W14: 各级单位-营销部门-合同签订人员 | X14: 每年 | Y14: 抽查 | AA14: 年度 | AB14: 抽查 | AH14: 是 | AI14: 是 | AJ14: 《国家电网有限公司电费业务管理办法（征求意见稿）》第四章 合同协议 《国家电网有限公司业扩报装管理规则（征求意见稿）》第六十三条 | AK14: 国网营销部 | AL14: 无变化，直接引用 | AM14: 无变化，直接引用 | AN14: 地市 | AO14: 业扩 | AP14: 业扩专业：无变化，直接引用 | AQ14: =A14=[1]营销售电!A14 -> TRUE | AR14: =B14=[1]营销售电!B14 -> TRUE | AS14: =C14=[1]营销售电!C14 -> TRUE | AT14: =D14=[1]营销售电!D14 -> TRUE | AU14: =E14=[1]营销售电!E14 -> TRUE | AV14: =F14=[1]营销售电!F14 -> TRUE | AW14: =G14=[1]营销售电!G14 -> TRUE | AX14: =H14=[1]营销售电!H14 -> TRUE | ... CA14: =AK14=[1]营销售电!AK14 -> TRUE
I15: 营销售电业务-4.供用电合同签订-控制措施03 | J15: 营销部门合同审核人员对合同文本使用情况开展审核。 | M15: √ | T15: 线下管控 | V15: 1.供用电合同； 2.合同统一文本； 3.系统合同信息； 4.系统合同签订及审批记录 | W15: 各级单位-营销部门-合同审核人员 | X15: 每年 | Y15: 抽查 | AA15: 年度 | AB15: 抽查 | AH15: 是 | AI15: 是 | AJ15: 《国家电网有限公司电费业务管理办法（征求意见稿）》第四章 合同协议 《国家电网有限公司业扩报装管理规则（征求意见稿）》第六十四条 | AK15: 国网营销部 | AL15: 无变化，直接引用 | AM15: 无变化，直接引用 | AN15: 地市 | AO15: 业扩 | AP15: 业扩专业：无变化，直接引用 | AQ15: =A15=[1]营销售电!A15 -> TRUE | AR15: =B15=[1]营销售电!B15 -> TRUE | AS15: =C15=[1]营销售电!C15 -> TRUE | AT15: =D15=[1]营销售电!D15 -> TRUE | AU15: =E15=[1]营销售电!E15 -> TRUE | AV15: =F15=[1]营销售电!F15 -> TRUE | AW15: =G15=[1]营销售电!G15 -> TRUE | AX15: =H15=[1]营销售电!H15 -> TRUE | ... CA15: =AK15=[1]营销售电!AK15 -> TRUE
C16: 会计信息真实完整、资金资产安全 | D16: 合同签订 | E16: 合同条款与客户报装信息、现场不一致，导致公司收支条款失效，合法权益无法得到保障。 | G16: 5.供用电合同审核 | H16: 合同关键信息与客户报装信息保持一致。 | I16: 营销售电业务-5.供用电合同审核-控制措施01 | J16: 营销部门合同签订人员要确保合同信息与业扩报装产生的客户信息保持一致，不得变更。 | M16: √ | O16: √ | T16: 线下管控 | V16: 1.供用电合同信息； 2.系统客户信息 | W16: 各级单位-营销部门-合同签订人员 | X16: 每年 | Y16: 抽查 | AA16: 年度 | AB16: 抽查 | AH16: 是 | AI16: 是 | AJ16: 《国家电网有限公司电费业务管理办法（征求意见稿）》第四章 合同协议第二十六条 | AK16: 国网营销部 | AL16: 无变化，但建议省公司优化系统。 | AM16: 增加系统客户信息校验（株洲） | AN16: 地市 | AO16: 业扩 | AP16: 业扩专业：无变化，直接引用 | AQ16: =A16=[1]营销售电!A16 -> TRUE | AR16: =B16=[1]营销售电!B16 -> TRUE | AS16: =C16=[1]营销售电!C16 -> TRUE | AT16: =D16=[1]营销售电!D16 -> TRUE | AU16: =E16=[1]营销售电!E16 -> TRUE | AV16: =F16=[1]营销售电!F16 -> TRUE | AW16: =G16=[1]营销售电!G16 -> TRUE | AX16: =H16=[1]营销售电!H16 -> TRUE | ... CA16: =AK16=[1]营销售电!AK16 -> TRUE
I17: 营销售电业务-5.供用电合同审核-控制措施02 | J17: 营销部门合同审核人员对合同信息与业扩报装产生的信息一致性进行复核。 | M17: √ | O17: √ | T17: 线下管控 | V17: 1.供用电合同信息； 2.系统客户信息； 3.合同审核记录 | W17: 各级单位-营销部门-合同审核人员 | X17: 每年 | Y17: 抽查 | AA17: 年度 | AB17: 抽查 | AH17: 是 | AI17: 是 | AJ17: 《国家电网有限公司电费业务管理办法（征求意见稿）》第四章 合同协议 | AK17: 国网营销部 | AL17: 无变化，直接引用 | AM17: 无变化，直接引用 | AN17: 地市 | AO17: 业扩 | AP17: 业扩专业：无变化，直接引用 | AQ17: =A17=[1]营销售电!A17 -> TRUE | AR17: =B17=[1]营销售电!B17 -> TRUE | AS17: =C17=[1]营销售电!C17 -> TRUE | AT17: =D17=[1]营销售电!D17 -> TRUE | AU17: =E17=[1]营销售电!E17 -> TRUE | AV17: =F17=[1]营销售电!F17 -> TRUE | AW17: =G17=[1]营销售电!G17 -> TRUE | AX17: =H17=[1]营销售电!H17 -> TRUE | ... CA17: =AK17=[1]营销售电!AK17 -> TRUE
I18: 营销售电业务-5.供用电合同审核-控制措施03 | J18: 营销部门合同管理人员应落实合同签订一致性要求，加强系统上传合同与线下纸质合同一致性管控。 | O18: √ | T18: 线下管控 | U18: 营销2.0系统 | V18: 1.供用电合同（线下）； 2.系统合同信息 | W18: 各级单位-营销部门-合同管理人员 | X18: 每年 | Y18: 抽查 | AA18: 年度 | AB18: 抽查 | AH18: 是 | AI18: 是 | AJ18: 《国家电网有限公司电费业务管理办法（征求意见稿）》第四章 合同协议 《国家电网有限公司业扩报装管理规则（征求意见稿）》第六十五条 | AK18: 国网营销部 | AL18: 无变化，但建议省公司优化系统。 | AM18: 在营销2.0增加自动校验合同中关键信息功能，如表计倍率、电价、线损等关键信息。（岳阳） | AN18: 地市 | AO18: 业扩 | AP18: 业扩专业：无变化，直接引用 | AQ18: =A18=[1]营销售电!A18 -> TRUE | AR18: =B18=[1]营销售电!B18 -> TRUE | AS18: =C18=[1]营销售电!C18 -> TRUE | AT18: =D18=[1]营销售电!D18 -> TRUE | AU18: =E18=[1]营销售电!E18 -> TRUE | AV18: =F18=[1]营销售电!F18 -> TRUE | AW18: =G18=[1]营销售电!G18 -> TRUE | AX18: =H18=[1]营销售电!H18 -> TRUE | ... CA18: =AK18=[1]营销售电!AK18 -> TRUE
I19: 营销售电业务-5.供用电合同审核-控制措施04 | J19: 营销部门对系统合同上传及生效情况开展稽查监督。 | S19: √ | T19: 系统已建 | U19: 营销2.0系统 | V19: 数字化监督相关资料或稽查工单及处理情况 | W19: 各级单位-营销部门-合同管理人员 | X19: 每 半年 | Y19: 抽查 | AA19: 年度 | AB19: 抽查 | AH19: 是 | AI19: 是 | AJ19: 《国家电网有限公司电费业务管理办法（征求意见稿）》第四章 合同协议 《国家电网有限公司业扩报装管理规则（征求意见稿）》第六十五条 | AK19: 国网营销部 | AL19: 无变化，直接引用 | AM19: 无变化，直接引用 | AN19: 地市 | AO19: 业扩 | AP19: 业扩专业：无变化，直接引用 | AQ19: =A19=[1]营销售电!A19 -> TRUE | AR19: =B19=[1]营销售电!B19 -> TRUE | AS19: =C19=[1]营销售电!C19 -> TRUE | AT19: =D19=[1]营销售电!D19 -> TRUE | AU19: =E19=[1]营销售电!E19 -> TRUE | AV19: =F19=[1]营销售电!F19 -> TRUE | AW19: =G19=[1]营销售电!G19 -> TRUE | AX19: =H19=[1]营销售电!H19 -> TRUE | ... CA19: =AK19=[1]营销售电!AK19 -> TRUE
A20: 营销售电业务 | B20: 二、电价执行管理 | C20: 会计信息真实完整、资金资产安全 | D20: 电价码制定 | E20: 电价政策执行不到位，系统配置不准确，导致公司电费收入计量不准确、不合规。 | G20: 6.电价码制定与执行 | H20: 电价标准与政策匹配，电价码准确配置与执行 | I20: 营销售电业务-6.电价码制定与执行-控制措施01 | J20: 电价码管理实行“统一管理、分级维护”原则，按照统一标准规范执行。财务部门负责根据国家或省内价格政策，对照标准化电价码编码规则，解析形成每类客户电价执行标准，将政策解析与电价码关联结果推送营销。 | M20: √ | Q20: √ | T20: 系统已建 | U20: 智慧财务 | V20: 1.电价政策文件； 2.政策解析结果 | W20: 国网财务部-销售电价管理人员；各省（自治区、直辖市）电力公司-财务部门-销售电价管理人员 | X20: 每年 | Y20: 抽查 | AA20: 年度 | AB20: 抽查 | AH20: 是 | AI20: 是 | AJ20: 《国网营销部国网财务部国网数字化部关于加快标准化电价码部署应用的通知》（营销营业〔2025〕83号） | AK20: 国网财务部 | AL20: 无变化，直接引用 | AM20: 无变化，直接引用 | AN20: 省公司 | AO20: 电价、财务 | AP20: 电价专业无意见 | AQ20: =A20=[1]营销售电!A20 -> TRUE | AR20: =B20=[1]营销售电!B20 -> TRUE | AS20: =C20=[1]营销售电!C20 -> TRUE | AT20: =D20=[1]营销售电!D20 -> TRUE | AU20: =E20=[1]营销售电!E20 -> TRUE | AV20: =F20=[1]营销售电!F20 -> TRUE | AW20: =G20=[1]营销售电!G20 -> TRUE | AX20: =H20=[1]营销售电!H20 -> TRUE | ... CA20: =AK20=[1]营销售电!AK20 -> TRUE
I21: 营销售电业务-6.电价码制定与执行-控制措施02 | J21: 营销部门基于电价标准及政策依据匹配形成电价码调整方案，审批后推送智慧财务，经财务部门审核（新增电价码需总部审批）后下发执行。电价码的维护申请、审核、审批、确认均执行线上流转。 | M21: √ | Q21: √ | T21: 系统已建 | U21: 营销2.0系统、智慧财务 | V21: 1.电价标准与电价码匹配记录； 2.电价码调整方案； 3.电价码审核审批记录 | W21: 国网财务部-销售电价管理人员；各省（自治区、直辖市）电力公司-营销部门-电价管理人员；各省（自治区、直辖市）电力公司-财务部门-销售电价管理人员 | X21: 每年 | Y21: 抽查 | AA21: 年度 | AB21: 抽查 | AH21: 是 | AI21: 是 | AJ21: 《国网营销部国网财务部国网数字化部关于加快标准化电价码部署应用的通知》（营销营业〔2025〕83号） | AK21: 国网营销部、国网财务部 | AL21: 无变化，直接引用 | AM21: 无变化，直接引用 | AN21: 省公司 | AO21: 电价 | AP21: 电价专业无意见 | AQ21: =A21=[1]营销售电!A21 -> TRUE | AR21: =B21=[1]营销售电!B21 -> TRUE | AS21: =C21=[1]营销售电!C21 -> TRUE | AT21: =D21=[1]营销售电!D21 -> TRUE | AU21: =E21=[1]营销售电!E21 -> TRUE | AV21: =F21=[1]营销售电!F21 -> TRUE | AW21: =G21=[1]营销售电!G21 -> TRUE | AX21: =H21=[1]营销售电!H21 -> TRUE | ... CA21: =AK21=[1]营销售电!AK21 -> TRUE
I22: 营销售电业务-6.电价码制定与执行-控制措施03 | J22: 营销部门将电价码部署系统并建立电价码与用户档案信息关联关系，确保电价码精准匹配到户。 | M22: √ | T22: 系统已建 | U22: 营销2.0系统 | V22: 1.电价码与用户档案信息关联关系； 2.电价码系统配置记录 | W22: 各省（自治区、直辖市）电力公司-营销部门-电价管理人员 | X22: 每年 | Y22: 抽查 | AA22: 年度 | AB22: 抽查 | AH22: 是 | AI22: 是 | AJ22: 《国网营销部国网财务部国网数字化部关于加快标准化电价码部署应用的通知》（营销营业〔2025〕83号） | AK22: 国网营销部 | AL22: 无变化，直接引用 | AM22: 无变化，直接引用 | AN22: 省公司 | AO22: 电价 | AP22: 电价专业无意见 | AQ22: =A22=[1]营销售电!A22 -> TRUE | AR22: =B22=[1]营销售电!B22 -> TRUE | AS22: =C22=[1]营销售电!C22 -> TRUE | AT22: =D22=[1]营销售电!D22 -> TRUE | AU22: =E22=[1]营销售电!E22 -> TRUE | AV22: =F22=[1]营销售电!F22 -> TRUE | AW22: =G22=[1]营销售电!G22 -> TRUE | AX22: =H22=[1]营销售电!H22 -> TRUE | ... CA22: =AK22=[1]营销售电!AK22 -> TRUE
I23: 营销售电业务-6.电价码制定与执行-控制措施04 | J23: 营销部门协同财务部门对电价码配置与价码执行情况开展数字化校核及在线监控分析。 | S23: √ | T23: 系统待建 | U23: 营销2.0系统 | V23: 1.电价码执行情况记录； 2.电价码统计分析功能及优惠电价执行预警等功能相关记录； 3.标准化电价码智能校核规则库； 4.数字化监督相关资料或稽查工单及处理情况 | W23: 各省（自治区、直辖市）电力公司-营销部门-电价管理人员；各省（自治区、直辖市）电力公司-财务部门-销售电价管理人员 | X23: 每半年 | Y23: 抽查 | AA23: 年度 | AB23: 抽查 | AD23: 电价码执行监督——对电价码配置与执行情况开展在线监督 | AE23: 每季度 | AF23: 全量 | AH23: 是 | AI23: 是 | AJ23: 《国网营销部国网财务部国网数字化部关于加快标准化电价码部署应用的通知》（营销营业〔2025〕83号） | AK23: 国网营销部、国网财务部 | AL23: 无变化，直接引用 | AM23: 无变化，直接引用 | AN23: 省公司 | AO23: 电价 | AP23: 电价专业无意见 | AQ23: =A23=[1]营销售电!A23 -> TRUE | AR23: =B23=[1]营销售电!B23 -> TRUE | AS23: =C23=[1]营销售电!C23 -> TRUE | AT23: =D23=[1]营销售电!D23 -> TRUE | AU23: =E23=[1]营销售电!E23 -> TRUE | AV23: =F23=[1]营销售电!F23 -> TRUE | AW23: =G23=[1]营销售电!G23 -> TRUE | AX23: =H23=[1]营销售电!H23 -> TRUE | ... CA23: =AK23=[1]营销售电!AK23 -> TRUE
C24: 会计信息真实完整、资金资产安全 | D24: 电价执行 | E24: 电价执行与客户用电性质不匹配，造成公司或用户电费资金损失，收入不实 | F24: 19.两部制电价执行不正确：存在应执行未执行两部制电价、分户报装规避两部制电价、变更用电少收基本电费、需量基本电费计收不准确等问题。 | G24: 7.客户电价执行管控 | H24: 客户电价执行与用电性质、行业类别等精准匹配 | I24: 营销售电业务-7.客户电价执行管控-控制措施01 | J24: 营销部门业务受理人员应严格按照客户用电性质、行业类别等匹配执行标准电价码并准确录入系统，经审核后生效。 | M24: √ | T24: 系统已建 | U24: 营销2.0系统 | V24: 1.系统业务工单记录； 2.系统客户电价信息 | W24: 各级单位-营销部门-业务受理、业务审核人员 | X24: 每半年 | Y24: 抽查 | AA24: 年度 | AB24: 抽查 | AH24: 是 | AI24: 是 | AJ24: 《国家电网有限公司电费业务管理办法（征求意见稿）》第三章 电价执行 | AK24: 国网营销部 | AL24: 无变化，直接引用 | AM24: 无变化，直接引用 | AN24: 地市 | AO24: 业扩 | AP24: 业扩专业：无变化，直接引用 | AQ24: =A24=[1]营销售电!A24 -> TRUE | AR24: =B24=[1]营销售电!B24 -> TRUE | AS24: =C24=[1]营销售电!C24 -> TRUE | AT24: =D24=[1]营销售电!D24 -> TRUE | AU24: =E24=[1]营销售电!E24 -> TRUE | AV24: =F24=[1]营销售电!F24 -> TRUE | AW24: =G24=[1]营销售电!G24 -> TRUE | AX24: =H24=[1]营销售电!H24 -> TRUE | ... CA24: =AK24=[1]营销售电!AK24 -> TRUE
I25: 营销售电业务-7.客户电价执行管控-控制措施02 | J25: 营销部门加强客户电价变更管理，对于电价政策变动导致的电价变更应结合电价码联动调整，对于客户用电性质改变导致的电价变更应严格执行与工单关联，其他类型电价变更严格执行授权审批后进行调整。 | M25: √ | T25: 系统已建 | U25: 营销2.0系统 | V25: 系统业务工单记录 | W25: 各级单位-营销部门-电价管理人员 | X25: 每半年 | Y25: 抽查 | AA25: 年度 | AB25: 抽查 | AH25: 是 | AI25: 是 | AJ25: 《国家电网有限公司电费业务管理办法（征求意见稿）》第三章 电价执行 | AK25: 国网营销部 | AL25: 无变化，直接引用 | AM25: 无变化，直接引用 | AN25: 地市 | AO25: 电价 | AP25: 电价专业无意见 | AQ25: =A25=[1]营销售电!A25 -> TRUE | AR25: =B25=[1]营销售电!B25 -> TRUE | AS25: =C25=[1]营销售电!C25 -> TRUE | AT25: =D25=[1]营销售电!D25 -> TRUE | AU25: =E25=[1]营销售电!E25 -> TRUE | AV25: =F25=[1]营销售电!F25 -> TRUE | AW25: =G25=[1]营销售电!G25 -> TRUE | AX25: =H25=[1]营销售电!H25 -> TRUE | ... CA25: =AK25=[1]营销售电!AK25 -> TRUE
I26: 营销售电业务-7.客户电价执行管控-控制措施03 | J26: 营销部门对客户电价执行及变更情况开展数字化在线监督。 | M26: √ | S26: √ | T26: 系统已建 | U26: 营销2.0系统 电价执行辅助管理模块 | V26: 数字化监督相关资料或稽查工单及处理情况 | W26: 各级单位-营销部门-电价管理人员 | X26: 每半年 | Y26: 抽查 | AA26: 年度 | AB26: 抽查 | AD26: 客户电价执行监督——对客户电价执行及变更开展在线监督 | AE26: 每季度 | AF26: 全量 | AH26: 是 | AI26: 是 | AJ26: 《国家电网有限公司电费业务管理办法（征求意见稿）》第三章 电价执行 国网湖南电力营销部关于印发电价执行管理规范指引的通知)（营销〔2025〕5号） | AK26: 国网营销部 | AL26: 新增制度完善、系统优化清单 | AM26: 新增制度完善、系统优化清单 | AN26: 供服、地市 | AO26: 电价 | AP26: 电价专业无意见 | AQ26: =A26=[1]营销售电!A26 -> TRUE | AR26: =B26=[1]营销售电!B26 -> TRUE | AS26: =C26=[1]营销售电!C26 -> TRUE | AT26: =D26=[1]营销售电!D26 -> TRUE | AU26: =E26=[1]营销售电!E26 -> TRUE | AV26: =F26=[1]营销售电!F26 -> TRUE | AW26: =G26=[1]营销售电!G26 -> TRUE | AX26: =H26=[1]营销售电!H26 -> TRUE | ... CA26: =AK26=[1]营销售电!AK26 -> TRUE
A27: 营销售电业务 | B27: 三、电量采集管理 | C27: 会计信息真实完整 | D27: 电量采集 | E27: 未严格执行采集策略，导致电量计量失真。 | G27: 8.采集规则配置 | H27: 电能表示数采集策略应纳入统一管理 | I27: 营销售电业务-8.采集规则配置-控制措施01 | J27: 营销部门要建立电能表示数采集策略统一管理机制，强化规则配置与实施管理。 | M27: √ | T27: 系统已建 | U27: 新一代用电信息采集系统 | V27: 电能表采集数据 | W27: 各省（自治区、直辖市）电力公司-营销部门-计量管理人员 | X27: 每年 | Y27: 抽查 | AA27: 年度 | AB27: 抽查 | AH27: 是 | AI27: 是 | AJ27: 《国家电网有限公司电费业务管理办法（征求意见稿）》第五章 采集抄表 | AK27: 国网营销部 | AL27: 无变化，直接引用 | AM27: 无变化，直接引用 | AN27: 供服 | AO27: 计量 | AP27: 计量无意见 | AQ27: =A27=[1]营销售电!A27 -> TRUE | AR27: =B27=[1]营销售电!B27 -> TRUE | AS27: =C27=[1]营销售电!C27 -> TRUE | AT27: =D27=[1]营销售电!D27 -> TRUE | AU27: =E27=[1]营销售电!E27 -> TRUE | AV27: =F27=[1]营销售电!F27 -> TRUE | AW27: =G27=[1]营销售电!G27 -> TRUE | AX27: =H27=[1]营销售电!H27 -> TRUE | ... CA27: =AK27=[1]营销售电!AK27 -> TRUE
I28: 营销售电业务-8.采集规则配置-控制措施02 | J28: 营销部门对电能表示数采集策略执行情况开展复核与监督。 | M28: √ | T28: 系统已建 | U28: 新一代用电信息采集系统 | V28: 电能表参数任务 | W28: 各省（自治区、直辖市）电力公司-营销部门-计量管理复核人员 | X28: 每年 | Y28: 抽查 | AA28: 年度 | AB28: 抽查 | AH28: 是 | AI28: 是 | AJ28: 《国家电网有限公司电费业务管理办法（征求意见稿）》第五章 采集抄表 | AK28: 国网营销部 | AL28: 无变化，直接引用 | AM28: 无变化，直接引用 | AN28: 供服 | AO28: 计量 | AP28: 计量无意见 | AQ28: =A28=[1]营销售电!A28 -> TRUE | AR28: =B28=[1]营销售电!B28 -> TRUE | AS28: =C28=[1]营销售电!C28 -> TRUE | AT28: =D28=[1]营销售电!D28 -> TRUE | AU28: =E28=[1]营销售电!E28 -> TRUE | AV28: =F28=[1]营销售电!F28 -> TRUE | AW28: =G28=[1]营销售电!G28 -> TRUE | AX28: =H28=[1]营销售电!H28 -> TRUE | ... CA28: =AK28=[1]营销售电!AK28 -> TRUE
C29: 会计信息真实完整 | D29: 电量采集 | E29: 电量采集范围不完整、抄表周期不准确，导致电费收入未可靠计量。 | G29: 9.电能表示数采集 | H29: 电能表示数采集应规范完整、应抄尽抄 | I29: 营销售电业务-9.电能表示数采集-控制措施01 | J29: 电能表示数采集应由用电信息采集系统统一出口，采集范围应完整。 | M29: √ | T29: 系统已建 | U29: 新一代用电信息采集系统 | V29: 1.电能表采集数据； 2.电能表抄表工单 | W29: 各省（自治区、直辖市）电力公司-营销部门-计量管理人员 | X29: 每 半年 | Y29: 抽查 | AA29: 年度 | AB29: 抽查 | AH29: 是 | AI29: 是 | AJ29: 《国家电网有限公司电费业务管理办法（征求意见稿）》第五章 采集抄表 | AK29: 国网营销部 | AL29: 无变化，直接引用 | AM29: 无变化，直接引用 | AN29: 供服 | AO29: 计量 | AP29: 计量无意见 | AQ29: =A29=[1]营销售电!A29 -> TRUE | AR29: =B29=[1]营销售电!B29 -> TRUE | AS29: =C29=[1]营销售电!C29 -> TRUE | AT29: =D29=[1]营销售电!D29 -> TRUE | AU29: =E29=[1]营销售电!E29 -> TRUE | AV29: =F29=[1]营销售电!F29 -> TRUE | AW29: =G29=[1]营销售电!G29 -> TRUE | AX29: =H29=[1]营销售电!H29 -> TRUE | ... CA29: =AK29=[1]营销售电!AK29 -> TRUE
I30: 营销售电业务-9.电能表示数采集-控制措施02 | J30: 营销部门对全量用户抄表完整性开展在线监控。 | S30: √ | T30: 系统已建 | U30: 新一代用电信息采集系统、营销2.0系统 | V30: 1.电能表采集数据； 2.电能表抄表工单 | W30: 各级单位-营销部门-计量（抄表）管理/电费电价管理人员 | X30: 每季度 | Y30: 抽查 | AA30: 年度 | AB30: 抽查 | AD30: 应抄未抄监督——对全量用户抄表完整性开展在线监控 | AE30: 每月 | AF30: 全量 | AH30: 是 | AI30: 是 | AJ30: 《国家电网有限公司电费业务管理办法（征求意见稿）》第五章 采集抄表 | AK30: 国网营销部 | AL30: 无变化，但建议省公司优化系统。 | AM30: 建议在营销2.0系统增加抄表例日缺抄的监控界面。(供服） | AN30: 供服 | AO30: 计量 | AP30: 计量无意见 | AQ30: =A30=[1]营销售电!A30 -> TRUE | AR30: =B30=[1]营销售电!B30 -> TRUE | AS30: =C30=[1]营销售电!C30 -> TRUE | AT30: =D30=[1]营销售电!D30 -> TRUE | AU30: =E30=[1]营销售电!E30 -> TRUE | AV30: =F30=[1]营销售电!F30 -> TRUE | AW30: =G30=[1]营销售电!G30 -> TRUE | AX30: =H30=[1]营销售电!H30 -> TRUE | ... CA30: =AK30=[1]营销售电!AK30 -> TRUE
I31: 营销售电业务-9.电能表示数采集-控制措施03 | J31: 营销部门严格抄表周期管理，以自然月为周期对全体用户进行抄表，抄表周期调整履行严格审批程序。 | M31: √ | T31: 系统已建 | U31: 营销2.0系统 | V31: 1.电能表采集数据； 2.电能表抄表工单； 3.应参与本次抄表算费全量客户抄表信息、实际参与本次抄表算费全量客户抄表信息 | W31: 各级单位-营销部门-计量（抄表）管理/电费电价管理人员 | X31: 每 半年 | Y31: 抽查 | AA31: 年度 | AB31: 抽查 | AH31: 是 | AI31: 是 | AJ31: 《国家电网有限公司电费业务管理办法（征求意见稿）》第五章 采集抄表 | AK31: 国网营销部 | AL31: 无变化，直接引用 | AM31: 无变化，直接引用 | AN31: 省公司、供服、地市 | AO31: 计量、抄表、电费核算 | AP31: 电费专业无意见 | AQ31: =A31=[1]营销售电!A31 -> TRUE | AR31: =B31=[1]营销售电!B31 -> TRUE | AS31: =C31=[1]营销售电!C31 -> TRUE | AT31: =D31=[1]营销售电!D31 -> TRUE | AU31: =E31=[1]营销售电!E31 -> TRUE | AV31: =F31=[1]营销售电!F31 -> TRUE | AW31: =G31=[1]营销售电!G31 -> TRUE | AX31: =H31=[1]营销售电!H31 -> TRUE | ... CA31: =AK31=[1]营销售电!AK31 -> TRUE
I32: 营销售电业务-9.电能表示数采集-控制措施04 | J32: 营销部门应结合当地市场规则及电费结算相关协议确定月内抄表频次。 | M32: √ | T32: 线下管控 | V32: 市场规则及相关文件 | W32: 各省（自治区、直辖市）电力公司-营销部门-电费电价（抄表）管理人员 | X32: 每 半年 | Y32: 抽查 | AA32: 年度 | AB32: 抽查 | AH32: 是 | AI32: 是 | AJ32: 《国家电网有限公司电费业务管理办法（征求意见稿）》第五章 采集抄表 | AK32: 国网营销部 | AL32: 无变化，直接引用 | AM32: 无变化，直接引用 | AN32: 省公司、供服、地市 | AO32: 计量、抄表、电费核算 | AP32: 电费专业无意见 | AQ32: =A32=[1]营销售电!A32 -> TRUE | AR32: =B32=[1]营销售电!B32 -> TRUE | AS32: =C32=[1]营销售电!C32 -> TRUE | AT32: =D32=[1]营销售电!D32 -> TRUE | AU32: =E32=[1]营销售电!E32 -> TRUE | AV32: =F32=[1]营销售电!F32 -> TRUE | AW32: =G32=[1]营销售电!G32 -> TRUE | AX32: =H32=[1]营销售电!H32 -> TRUE | ... CA32: =AK32=[1]营销售电!AK32 -> TRUE
C33: 会计信息真实完整 | D33: 电量采集 | E33: 抄表结果异常，导致电费计算失真。 | F33: 20.营销系统权限管控不严：存在重要业务流程权限设置不合规；电费收费、账务处理、财务审核和违约用电查处、审批等不相容岗位未分离；信息系统权限未严格落实实名制，账号权限与实际权责不符、一人存在多个账号等问题。 | G33: 10.电量采集结果确认 | H33: 电量采集结果应完整、准确 | I33: 营销售电业务-10.电量采集结果确认-控制措施01 | J33: 营销部门建立电量采集结果集中复核机制，健全复核规则，异常事项消缺纳入在线管控。 | M33: √ | T33: 系统已建 | U33: 营销2.0系统 | V33: 电能表采集数据 | W33: 各省（自治区、直辖市）电力公司-营销部门-计量（抄表）管理人员 | X33: 每年 | Y33: 抽查 | AA33: 年度 | AB33: 抽查 | AH33: 是 | AI33: 是 | AJ33: 《国家电网有限公司电费业务管理办法（征求意见稿）》第五章 采集抄表 | AK33: 国网营销部 | AL33: 待定 | AM33: 待定 | AN33: 省公司、供服、地市 | AO33: 计量、营业 | AP33: 计量无意见 | AQ33: =A33=[1]营销售电!A33 -> TRUE | AR33: =B33=[1]营销售电!B33 -> TRUE | AS33: =C33=[1]营销售电!C33 -> TRUE | AT33: =D33=[1]营销售电!D33 -> TRUE | AU33: =E33=[1]营销售电!E33 -> TRUE | AV33: =F33=[1]营销售电!F33 -> TRUE | AW33: =G33=[1]营销售电!G33 -> TRUE | AX33: =H33=[1]营销售电!H33 -> TRUE | ... CA33: =AK33=[1]营销售电!AK33 -> TRUE
I34: 营销售电业务-10.电量采集结果确认-控制措施02 | J34: 营销部门对抄表异常事项消缺实行工单化管理，对不影响量费调整的异常事项消缺，执行本级确认后闭环。对影响量费调整的异常事项消缺，执行分级授权审批机制。 | L34: √ | M34: √ | T34: 系统已建 | U34: 营销2.0系统 | V34: 采集异常工单及审核审批记录 | W34: 各级单位-营销部门-计量（抄表）管理及各级审批人员 | X34: 每 半年 | Y34: 抽查 | AA34: 年度 | AB34: 抽查 | AH34: 是 | AI34: 是 | AJ34: 《国家电网有限公司电费业务管理办法（征求意见稿）》第五章 采集抄表 | AK34: 国网营销部 | AL34: 无变化，直接引用 | AM34: 无变化，直接引用 | AN34: 地市 | AO34: 计量、营业 | AP34: 计量无意见 | AQ34: =A34=[1]营销售电!A34 -> TRUE | AR34: =B34=[1]营销售电!B34 -> TRUE | AS34: =C34=[1]营销售电!C34 -> TRUE | AT34: =D34=[1]营销售电!D34 -> TRUE | AU34: =E34=[1]营销售电!E34 -> TRUE | AV34: =F34=[1]营销售电!F34 -> TRUE | AW34: =G34=[1]营销售电!G34 -> TRUE | AX34: =H34=[1]营销售电!H34 -> TRUE | ... CA34: =AK34=[1]营销售电!AK34 -> TRUE
A35: 营销售电业务 | B35: 四、电费核算与发行管理 | C35: 会计信息真实完整 | D35: 量费计算 | E35: 未严格执行电费计算规则，电费计算结果未经有效复核，导致电费计算结果失真。 | G35: 11.电费计算结果复核 | H35: 电费核算与复核规则应纳入统一管理 | I35: 营销售电业务-11.电费计算结果复核-控制措施01 | J35: 国网营销部对电费核算与复核规则进行集中管理、二级配置与实施，规则应及时动态更新。 | M35: √ | T35: 系统已建 | U35: 营销2.0系统 | V35: 系统电费核算与复核规则 | W35: 国网营销部-电费电价管理人员；各省（自治区、直辖市）电力公司-营销部门-电费电价管理人员 | X35: 每年 | Y35: 抽查 | AA35: 年度 | AB35: 抽查 | AH35: 是 | AI35: 是 | AJ35: 《国家电网有限公司电费业务管理办法（征求意见稿）》第七章 核算出账 | AK35: 国网营销部 | AL35: 无变化，直接引用 | AM35: 无变化，直接引用 | AN35: 国网营销部、省公司 | AO35: 电费电价 | AP35: 电费专业无意见 | AQ35: =A35=[1]营销售电!A35 -> TRUE | AR35: =B35=[1]营销售电!B35 -> TRUE | AS35: =C35=[1]营销售电!C35 -> TRUE | AT35: =D35=[1]营销售电!D35 -> TRUE | AU35: =E35=[1]营销售电!E35 -> TRUE | AV35: =F35=[1]营销售电!F35 -> TRUE | AW35: =G35=[1]营销售电!G35 -> TRUE | AX35: =H35=[1]营销售电!H35 -> TRUE | ... CA35: =AK35=[1]营销售电!AK35 -> TRUE
I36: 营销售电业务-11.电费计算结果复核-控制措施02 | J36: 省公司营销部门应确保通用规则执行到位，对个性化补充规则严格履行审批程序后实施。 | M36: √ | T36: 系统已建 | U36: 营销2.0系统 | V36: 1.系统电费核算与复核规则； 2.系统个性化规则授权审批记录 | W36: 各省（自治区、直辖市）电力公司-营销部门-电费电价管理人员 | X36: 每年 | Y36: 抽查 | AA36: 年度 | AB36: 抽查 | AH36: 是 | AI36: 是 | AJ36: 《国家电网有限公司电费业务管理办法（征求意见稿）》第七章 核算出账 | AK36: 国网营销部 | AL36: 无变化，直接引用 | AM36: 无变化，直接引用 | AN36: 省公司 | AO36: 电费电价 | AP36: 电费专业无意见 | AQ36: =A36=[1]营销售电!A36 -> TRUE | AR36: =B36=[1]营销售电!B36 -> TRUE | AS36: =C36=[1]营销售电!C36 -> TRUE | AT36: =D36=[1]营销售电!D36 -> TRUE | AU36: =E36=[1]营销售电!E36 -> TRUE | AV36: =F36=[1]营销售电!F36 -> TRUE | AW36: =G36=[1]营销售电!G36 -> TRUE | AX36: =H36=[1]营销售电!H36 -> TRUE | ... CA36: =AK36=[1]营销售电!AK36 -> TRUE
I37: 营销售电业务-11.电费计算结果复核-控制措施03 | J37: 营销部门建立量费核算结果集中复核机制，异常事项消缺实行工单化管理，并明确分级分类审批标准。 | L37: √ | M37: √ | T37: 系统已建 | U37: 营销2.0系统 | V37: 量费异常工单及审核审批记录 | W37: 各级单位-营销部门-电费电价管理及各级审批人员 | X37: 每 半年 | Y37: 抽查 | AA37: 年度 | AB37: 抽查 | AH37: 是 | AI37: 是 | AJ37: 《国家电网有限公司电费业务管理办法（征求意见稿）》第七章 核算出账 | AK37: 国网营销部 | AL37: 无变化，直接引用 | AM37: 无变化，直接引用 | AN37: 供服、地市 | AO37: 电费电价 | AP37: 电费专业无意见 | AQ37: =A37=[1]营销售电!A37 -> TRUE | AR37: =B37=[1]营销售电!B37 -> TRUE | AS37: =C37=[1]营销售电!C37 -> TRUE | AT37: =D37=[1]营销售电!D37 -> TRUE | AU37: =E37=[1]营销售电!E37 -> TRUE | AV37: =F37=[1]营销售电!F37 -> TRUE | AW37: =G37=[1]营销售电!G37 -> TRUE | AX37: =H37=[1]营销售电!H37 -> TRUE | ... CA37: =AK37=[1]营销售电!AK37 -> TRUE
C38: 会计信息真实完整、资金资产安全 | D38: 电费发行 | E38: 违规减免电费，导致收入不实、资金损失。 | F38: 20.营销系统权限管控不严：存在重要业务流程权限设置不合规；电费收费、账务处理、财务审核和违约用电查处、审批等不相容岗位未分离；信息系统权限未严格落实实名制，账号权限与实际权责不符、一人存在多个账号等问题。 | G38: 12.电费发行确认 | H38: 电费发行应真实、完整、准确 | I38: 营销售电业务-12.电费发行确认-控制措施01 | J38: 营销部门统一配置电费发行规则，强化电费发行与核算一体化管控，严禁手工篡改发行数据。 | M38: √ | T38: 系统已建 | U38: 营销2.0系统 | V38: 1.系统电费发行工单流转记录； 2.岗位权限配置 | W38: 各省（自治区、直辖市）电力公司-营销部门-电费电价管理人员 | X38: 每年 | Y38: 抽查 | AA38: 年度 | AB38: 抽查 | AH38: 是 | AI38: 是 | AJ38: 《国家电网有限公司电费业务管理办法（征求意见稿）》第七章 核算出账 国网湖南电力营销部关于印发电费结算管理办法的通知（营销〔2022〕27号） 国网湖南电力营销部关于加强电量电费差错风险防控工作的通知（营销〔2024〕36号） | AK38: 国网营销部 | AL38: 新增制度完善清单 | AM38: 新增制度完善清单 | AN38: 供服 | AO38: 电费电价 | AP38: 电价专业无意见 | AQ38: =A38=[1]营销售电!A38 -> TRUE | AR38: =B38=[1]营销售电!B38 -> TRUE | AS38: =C38=[1]营销售电!C38 -> TRUE | AT38: =D38=[1]营销售电!D38 -> TRUE | AU38: =E38=[1]营销售电!E38 -> TRUE | AV38: =F38=[1]营销售电!F38 -> TRUE | AW38: =G38=[1]营销售电!G38 -> TRUE | AX38: =H38=[1]营销售电!H38 -> TRUE | ... CA38: =AK38=[1]营销售电!AK38 -> TRUE
I39: 营销售电业务-12.电费发行确认-控制措施02 | J39: 营销部门协同交易明确月末预估量价规则，预估到日，预估结果确认严格履行审批程序，防止人为调整。 | M39: √ | T39: 系统已建 | U39: 营销2.0系统 | V39: 1.系统电费发行工单流转记录； 2.系统电费退补审批记录及支撑依据； 3.岗位权限配置 | W39: 各省（自治区、直辖市）电力公司-营销部门-电费电价管理人员 | X39: 每 季度 | Y39: 抽查 | AA39: 年度 | AB39: 抽查 | AH39: 是 | AI39: 是 | AJ39: 《国家电网有限公司电费业务管理办法（征求意见稿）》第七章 核算出账 | AK39: 国网营销部 | AL39: 修改控制措施 | AM39: 修改说明：删除预估到日。因国网电费管理办法中未要求预估到日，实际业务是按月预估 | AN39: 供服 | AO39: 电费电价 | AP39: 电价专业无意见 | AQ39: =A39=[1]营销售电!A39 -> TRUE | AR39: =B39=[1]营销售电!B39 -> TRUE | AS39: =C39=[1]营销售电!C39 -> TRUE | AT39: =D39=[1]营销售电!D39 -> TRUE | AU39: =E39=[1]营销售电!E39 -> TRUE | AV39: =F39=[1]营销售电!F39 -> TRUE | AW39: =G39=[1]营销售电!G39 -> TRUE | AX39: =H39=[1]营销售电!H39 -> TRUE | ... CA39: =AK39=[1]营销售电!AK39 -> TRUE
I40: 营销售电业务-12.电费发行确认-控制措施03 | J40: 各单位业务核算人员在算费前，对当月审核规则拦截的涉费工单进行逐一检查，督导处理归档。 | M40: √ | T40: 系统已建 | U40: 营销2.0系统 | V40: 系统试算工单流转记录 | W40: 各级单位-营销部门-业务核算人员 | X40: 每半年 | Y40: 抽查 | AA40: 年度 | AB40: 抽查 | AH40: 是 | AI40: 是 | AJ40: 《国家电网有限公司电费业务管理办法（征求意见稿）》第七章 核算出账 | AK40: 国网营销部 | AL40: 无变化，直接引用 | AM40: 无变化，直接引用 | AN40: 供服、地市 | AO40: 电费电价 | AP40: 电费专业无意见 | AQ40: =A40=[1]营销售电!A40 -> TRUE | AR40: =B40=[1]营销售电!B40 -> TRUE | AS40: =C40=[1]营销售电!C40 -> TRUE | AT40: =D40=[1]营销售电!D40 -> TRUE | AU40: =E40=[1]营销售电!E40 -> TRUE | AV40: =F40=[1]营销售电!F40 -> TRUE | AW40: =G40=[1]营销售电!G40 -> TRUE | AX40: =H40=[1]营销售电!H40 -> TRUE | ... CA40: =AK40=[1]营销售电!AK40 -> TRUE
I41: 营销售电业务-12.电费发行确认-控制措施04 | J41: 营销部门对非政策性电费退补应严格履行分级审批程序。 | L41: √ | T41: 系统已建 | U41: 营销2.0系统 | V41: 1.系统电费退补审批记录及支撑依据； 2.岗位权限配置 | W41: 各级单位-营销部门-电费电价管理及各级审批人员 | X41: 每半年 | Y41: 抽查 | AA41: 年度 | AB41: 抽查 | AH41: 是 | AI41: 是 | AJ41: 《国家电网有限公司电费业务管理办法（征求意见稿）》第七章 核算出账 国网湖南电力市场营销部关于规范电量电费退补管理的通知（营销〔2021〕15号） | AK41: 国网营销部 | AL41: 新增制度完善清单 | AM41: 新增制度完善清单 | AN41: 供服、地市 | AO41: 电费 | AP41: 电费专业无意见 | AQ41: =A41=[1]营销售电!A41 -> TRUE | AR41: =B41=[1]营销售电!B41 -> TRUE | AS41: =C41=[1]营销售电!C41 -> TRUE | AT41: =D41=[1]营销售电!D41 -> TRUE | AU41: =E41=[1]营销售电!E41 -> TRUE | AV41: =F41=[1]营销售电!F41 -> TRUE | AW41: =G41=[1]营销售电!G41 -> TRUE | AX41: =H41=[1]营销售电!H41 -> TRUE | ... CA41: =AK41=[1]营销售电!AK41 -> TRUE
I42: 营销售电业务-12.电费发行确认-控制措施05 | J42: 营销部门对非政策性电费退补开展数字化在线监督。 | M42: √ | S42: √ | T42: 系统已建 | U42: 营销2.0系统 | V42: 数字化监督相关资料或稽查工单及处理情况 | W42: 各级单位-营销部门-电费电价管理人员 | X42: 每半年 | Y42: 抽查 | AA42: 年度 | AB42: 抽查 | AD42: 违规减免电费监督——对非政策性电费退补开展数字化在线监督 | AE42: 每季度 | AF42: 全量 | AH42: 是 | AI42: 是 | AJ42: 《国家电网有限公司电费业务管理办法（征求意见稿）》第七章 核算出账 国网湖南电力市场营销部关于规范电量电费退补管理的通知（营销〔2021〕15号） | AK42: 国网营销部 | AL42: 新增制度完善清单 | AM42: 新增制度完善清单 | AN42: 供服、地市 | AO42: 电费 | AP42: 电费专业无意见 | AQ42: =A42=[1]营销售电!A42 -> TRUE | AR42: =B42=[1]营销售电!B42 -> TRUE | AS42: =C42=[1]营销售电!C42 -> TRUE | AT42: =D42=[1]营销售电!D42 -> TRUE | AU42: =E42=[1]营销售电!E42 -> TRUE | AV42: =F42=[1]营销售电!F42 -> TRUE | AW42: =G42=[1]营销售电!G42 -> TRUE | AX42: =H42=[1]营销售电!H42 -> TRUE | ... CA42: =AK42=[1]营销售电!AK42 -> TRUE
A43: 营销售电业务 | B43: 四、电费核算与发行管理 | C43: 会计信息真实完整、资金资产安全 | D43: 业务费确认 | E43: 业务费收取不规范，造成电费资金损失。 | F43: 18.违约窃电查处不规范：存在未及时查处用户违约用电、窃电行为；违规减免、暂缓应补交的追补电费和违约使用电费等问题。 20.营销系统权限管控不严：电费收费、账务处理、财务审核和违约用电查处、审批等不相容岗位未分离；账号权限与实际权责不符、一人存在多个账号等问题。 | G43: 13.业务费确认 | H43: 业务费应足额、准确收取 | I43: 营销售电业务-13.业务费确认-控制措施01 | J43: 营销部门应严格执行价格主管部门批准的收费项目和计算标准，统一配置业务费计费规则，严禁手工修改系统计算结果。 | M43: √ | P43: √ | T43: 系统已建 | U43: 营销2.0系统 | V43: 1.业务费收费标准； 2，系统业务费计费规则； 3.业务费收费明细 | W43: 各省（自治区、直辖市）电力公司-营销部门-业务费管理人员 | X43: 每年 | Y43: 抽查 | AA43: 年度 | AB43: 抽查 | AH43: 是 | AI43: 是 | AJ43: 《供电营业规则》 | AK43: 国网营销部 | AL43: 无变化，直接引用 | AM43: 无变化，直接引用 | AN43: 省公司 | AO43: 反窃查违、业扩 | AP43: 反窃查违无意见。业扩专业：无变化，直接引用 | AQ43: =A43=[1]营销售电!A43 -> TRUE | AR43: =B43=[1]营销售电!B43 -> TRUE | AS43: =C43=[1]营销售电!C43 -> TRUE | AT43: =D43=[1]营销售电!D43 -> TRUE | AU43: =E43=[1]营销售电!E43 -> TRUE | AV43: =F43=[1]营销售电!F43 -> TRUE | AW43: =G43=[1]营销售电!G43 -> TRUE | AX43: =H43=[1]营销售电!H43 -> TRUE | ... CA43: =AK43=[1]营销售电!AK43 -> TRUE
I44: 营销售电业务-13.业务费确认-控制措施02 | J44: 营销部门对业务费收取、减免（暂缓、退费等）严格履行分级审批程序并线上实施，确保足额收取。 | L44: √ | P44: √ | T44: 系统待建 | U44: 营销2.0系统 | V44: 1.系统审批单； 2.岗位权限配置； 3.退费影像 | W44: 各级单位-营销部门-业务收取、管理及各级审批人员 | X44: 每半年 | Y44: 抽查 | AA44: 年度 | AB44: 抽查 | AH44: 是 | AI44: 是 | AJ44: 《供电营业规则》 | AK44: 国网营销部 | AL44: 无变化，直接引用 | AM44: 无变化，直接引用 | AN44: 地市 | AO44: 反窃查违、业扩 | AP44: 反窃查违无意见。业扩专业：无变化，直接引用 | AQ44: =A44=[1]营销售电!A44 -> TRUE | AR44: =B44=[1]营销售电!B44 -> TRUE | AS44: =C44=[1]营销售电!C44 -> TRUE | AT44: =D44=[1]营销售电!D44 -> TRUE | AU44: =E44=[1]营销售电!E44 -> TRUE | AV44: =F44=[1]营销售电!F44 -> TRUE | AW44: =G44=[1]营销售电!G44 -> TRUE | AX44: =H44=[1]营销售电!H44 -> TRUE | ... CA44: =AK44=[1]营销售电!AK44 -> TRUE
I45: 营销售电业务-13.业务费确认-控制措施03 | J45: 营销部门对违规减免（暂缓）业务费开展数字化在线监督。 | M45: √ | S45: √ | T45: 系统已建 | U45: 营销2.0系统 | V45: 数字化在线监督结果或稽查工单及处理情况 | W45: 各级单位-营销部门-电费电价管理人员各级单位-营销部门-业务收取、管理及各级审批人员 | X45: 每半年 | Y45: 抽查 | AA45: 年度 | AB45: 抽查 | AD45: 违规减免业务费监督——对违规减免（暂缓）业务费开展数字化在线监督 | AE45: 每季度 | AF45: 全量 | AH45: 是 | AI45: 是 | AJ45: 《供电营业规则》 | AK45: 国网营销部 | AL45: 修改责任主体 | AM45: 修改责任主体 | AN45: 地市 | AO45: 反窃查违、业扩 | AP45: 反窃查违无意见。业扩专业：无变化，直接引用 | AQ45: =A45=[1]营销售电!A45 -> TRUE | AR45: =B45=[1]营销售电!B45 -> TRUE | AS45: =C45=[1]营销售电!C45 -> TRUE | AT45: =D45=[1]营销售电!D45 -> TRUE | AU45: =E45=[1]营销售电!E45 -> TRUE | AV45: =F45=[1]营销售电!F45 -> TRUE | AW45: =G45=[1]营销售电!G45 -> TRUE | AX45: =H45=[1]营销售电!H45 -> TRUE | ... CA45: =AK45=[1]营销售电!AK45 -> TRUE
C46: 会计信息真实完整、资金资产安全 | D46: 电费违约金减免 | E46: 违规减免电费违约金，掩盖其欠费事实，后期存在电费无法回收风险。 | F46: 17.违规减免电费违约金：存在电费未足额收回，通过全减另发等方式违规减免应收电费；违规减免或暂缓电费违约金等问题。 20.营销系统权限管控不严：存在重要业务流程权限设置不合规；电费收费、账务处理、财务审核和违约用电查处、审批等不相容岗位未分离；信息系统权限未严格落实实名制，账号权限与实际权责不符、一人存在多个账号等问题。 | G46: 14.电费违约金减免 | H46: 电费违约金应足额、准确收取 | I46: 营销售电业务-14.电费违约金减免-控制措施01 | J46: 营销部门明确电费违约金减免（暂缓）适用情形、支撑材料及分级授权标准。 | M46: √ | T46: 线下管控 | V46: 1.电费违约金减免（暂缓）支撑依据； 2.岗位权限配置 | W46: 各省（自治区、直辖市）电力公司-营销部门-电费电价管理人员 | X46: 每年 | Y46: 抽查 | AA46: 年度 | AB46: 抽查 | AH46: 是 | AI46: 是 | AJ46: 《国家电网有限公司电费业务管理办法（征求意见稿）》第八章 电费收支 第五十条规范电费违约金管理 | AK46: 国网营销部 | AL46: 无变化，直接引用 | AM46: 无变化，直接引用 | AN46: 省公司 | AO46: 电费 | AP46: 电费专业无意见 | AQ46: =A46=[1]营销售电!A46 -> TRUE | AR46: =B46=[1]营销售电!B46 -> TRUE | AS46: =C46=[1]营销售电!C46 -> TRUE | AT46: =D46=[1]营销售电!D46 -> TRUE | AU46: =E46=[1]营销售电!E46 -> TRUE | AV46: =F46=[1]营销售电!F46 -> TRUE | AW46: =G46=[1]营销售电!G46 -> TRUE | AX46: =H46=[1]营销售电!H46 -> TRUE | ... CA46: =AK46=[1]营销售电!AK46 -> TRUE
I47: 营销售电业务-14.电费违约金减免-控制措施02 | J47: 营销部门统一配置电费违约金减免（暂缓）工单及系统审批程序。 | M47: √ | T47: 系统已建 | U47: 营销2.0系统 | V47: 1.系统电费违约金减免（暂缓）工单流转记录； 2.岗位权限配置 | W47: 各省（自治区、直辖市）电力公司-营销部门-电费电价管理人员 | X47: 每年 | Y47: 抽查 | AA47: 年度 | AB47: 抽查 | AH47: 是 | AI47: 是 | AJ47: 《国家电网有限公司电费业务管理办法（征求意见稿）》第八章 电费收支 第五十条规范电费违约金管理 | AK47: 国网营销部 | AL47: 无变化，直接引用 | AM47: 无变化，直接引用 | AN47: 省公司、供服 | AO47: 电费 | AP47: 电费专业无意见 | AQ47: =A47=[1]营销售电!A47 -> TRUE | AR47: =B47=[1]营销售电!B47 -> TRUE | AS47: =C47=[1]营销售电!C47 -> TRUE | AT47: =D47=[1]营销售电!D47 -> TRUE | AU47: =E47=[1]营销售电!E47 -> TRUE | AV47: =F47=[1]营销售电!F47 -> TRUE | AW47: =G47=[1]营销售电!G47 -> TRUE | AX47: =H47=[1]营销售电!H47 -> TRUE | ... CA47: =AK47=[1]营销售电!AK47 -> TRUE
I48: 营销售电业务-14.电费违约金减免-控制措施03 | J48: 营销部门电费管理人员对电费违约金减免（暂缓）支撑材料及工单记录进行复核。 | M48: √ | T48: 系统已建 | U48: 营销2.0系统 | V48: 1.系统电费违约金减免（暂缓）工单流转记录； 2.电费违约金减免（暂缓）支撑依据 | W48: 各级单位-营销部门-电费电价管理人员 | X48: 每半年 | Y48: 抽查 | AA48: 年度 | AB48: 抽查 | AH48: 是 | AI48: 是 | AJ48: 《国家电网有限公司电费业务管理办法（征求意见稿）》第八章 电费收支 第五十条规范电费违约金管理 | AK48: 国网营销部 | AL48: 无变化，直接引用 | AM48: 无变化，直接引用 | AN48: 地市 | AO48: 电费 | AP48: 电费专业无意见 | AQ48: =A48=[1]营销售电!A48 -> TRUE | AR48: =B48=[1]营销售电!B48 -> TRUE | AS48: =C48=[1]营销售电!C48 -> TRUE | AT48: =D48=[1]营销售电!D48 -> TRUE | AU48: =E48=[1]营销售电!E48 -> TRUE | AV48: =F48=[1]营销售电!F48 -> TRUE | AW48: =G48=[1]营销售电!G48 -> TRUE | AX48: =H48=[1]营销售电!H48 -> TRUE | ... CA48: =AK48=[1]营销售电!AK48 -> TRUE
I49: 营销售电业务-14.电费违约金减免-控制措施04 | J49: 营销部门对电费违约金减免（暂缓）开展数字化在线监督。 | M49: √ | S49: √ | T49: 系统已建 | U49: 营销2.0系统 | V49: 数字化在线监督结果或稽查工单及处理情况 | W49: 各级单位-营销部门-电费电价管理人员 | X49: 每半年 | Y49: 抽查 | AA49: 年度 | AB49: 抽查 | AD49: 电费违约金违规减免监督——对电费违约金减免（暂缓）开展在线监督 | AE49: 每季度 | AF49: 全量 | AH49: 是 | AI49: 是 | AJ49: 《国家电网有限公司电费业务管理办法（征求意见稿）》第八章 电费收支 第五十条规范电费违约金管理 | AK49: 国网营销部 | AL49: 无变化，直接引用 | AM49: 无变化，直接引用 | AN49: 地市 | AO49: 电费 | AP49: 电费专业无意见 | AQ49: =A49=[1]营销售电!A49 -> TRUE | AR49: =B49=[1]营销售电!B49 -> TRUE | AS49: =C49=[1]营销售电!C49 -> TRUE | AT49: =D49=[1]营销售电!D49 -> TRUE | AU49: =E49=[1]营销售电!E49 -> TRUE | AV49: =F49=[1]营销售电!F49 -> TRUE | AW49: =G49=[1]营销售电!G49 -> TRUE | AX49: =H49=[1]营销售电!H49 -> TRUE | ... CA49: =AK49=[1]营销售电!AK49 -> TRUE
B50: 五、电费账务及发票管理 | C50: 会计信息真实完整 | D50: 电费账务处理 | E50: 电费账务不准确，导致收入不实风险。 | F50: 20.营销系统权限管控不严：存在重要业务流程权限设置不合规；电费收费、账务处理、财务审核和违约用电查处、审批等不相容岗位未分离；信息系统权限未严格落实实名制，账号权限与实际权责不符、一人存在多个账号等问题。 | G50: 15.电费账务管控 | H50: 电费账务应纳入线上管控 | I50: 营销售电业务-15.电费账务管控-控制措施01 | J50: 电费账务应自动集成电费发行及收费结果，防止人为干预。 | M50: √ | T50: 系统已建 | U50: 营销2.0系统 | V50: 系统电费凭证生成标识 | W50: 各省（自治区、直辖市）电力公司-营销部门-电费管理人员 | X50: 每年 | Y50: 抽查 | AA50: 年度 | AB50: 抽查 | AH50: 是 | AI50: 是 | AJ50: 《国家电网有限公司电费业务管理办法（征求意见稿）》第九章 电费账务 | AK50: 国网营销部 | AL50: 无变化，直接引用 | AM50: 无变化，直接引用 | AN50: 省公司 | AO50: 电费 | AP50: 电费专业无意见 | AQ50: =A50=[1]营销售电!A50 -> TRUE | AR50: =B50=[1]营销售电!B50 -> TRUE | AS50: =C50=[1]营销售电!C50 -> TRUE | AT50: =D50=[1]营销售电!D50 -> TRUE | AU50: =E50=[1]营销售电!E50 -> TRUE | AV50: =F50=[1]营销售电!F50 -> TRUE | AW50: =G50=[1]营销售电!G50 -> TRUE | AX50: =H50=[1]营销售电!H50 -> TRUE | ... CA50: =AK50=[1]营销售电!AK50 -> TRUE
I51: 营销售电业务-15.电费账务管控-控制措施02 | J51: 因核算差错等确需调整账务时由营销部门结合业务联动调整，并严格履行审批程序。 | L51: √ | M51: √ | T51: 系统已建 | U51: 营销2.0系统 | V51: 1.系统电费凭证生成标识； 2.岗位权限配置 | W51: 各级单位-营销部门-电费电价管理及各级审批人员 | X51: 每半年 | Y51: 抽查 | AA51: 年度 | AB51: 抽查 | AH51: 是 | AI51: 是 | AJ51: 《国家电网有限公司电费业务管理办法（征求意见稿）》第九章 电费账务 | AK51: 国网营销部 | AL51: 待定 | AM51: 待定 | AN51: 省公司、供服、地市 | AO51: 电费 | AP51: 电费专业无意见 | AQ51: =A51=[1]营销售电!A51 -> TRUE | AR51: =B51=[1]营销售电!B51 -> TRUE | AS51: =C51=[1]营销售电!C51 -> TRUE | AT51: =D51=[1]营销售电!D51 -> TRUE | AU51: =E51=[1]营销售电!E51 -> TRUE | AV51: =F51=[1]营销售电!F51 -> TRUE | AW51: =G51=[1]营销售电!G51 -> TRUE | AX51: =H51=[1]营销售电!H51 -> TRUE | ... CA51: =AK51=[1]营销售电!AK51 -> TRUE
A52: 营销售电业务 | B52: 五、电费账务及发票管理 | C52: 会计信息真实完整 | D52: 电费账务处理 | E52: 会计政策执行不到位，手工调整账务，导致财务会计信息反映不真实。 | G52: 16.营财账务协同管理 | H52: 营财账务应建立协同管控机制 | I52: 营销售电业务-16.营财账务协同管理-控制措施01 | J52: 财务部门根据会计政策变化、制度调整及时变更会计科目及凭证生成规则，并及时下发执行。 | Q52: √ | T52: 系统已建 | U52: 智慧财务 | V52: 1.会计政策文件； 2.会计规则调整相关文件； 3.系统核算规则 | W52: 国网财务部-总账管理人员；各省（自治区、直辖市）电力公司-财务部门-总账管理人员 | X52: 每年 | Y52: 抽查 | AA52: 年度 | AB52: 抽查 | AH52: 是 | AI52: 是 | AJ52: 《国网营销部财务部关于明确营销2.0系统与智慧共享财务平台系统集成有关问题的意见》（营销营业〔2023〕86号文 ） | AK52: 国网财务部 | AL52: 无变化，直接引用 | AM52: 无变化，直接引用 | AN52: 财务部 | AO52: 财务 | AP52: 账务专业无意见。 | AQ52: =A52=[1]营销售电!A52 -> TRUE | AR52: =B52=[1]营销售电!B52 -> TRUE | AS52: =C52=[1]营销售电!C52 -> TRUE | AT52: =D52=[1]营销售电!D52 -> TRUE | AU52: =E52=[1]营销售电!E52 -> TRUE | AV52: =F52=[1]营销售电!F52 -> TRUE | AW52: =G52=[1]营销售电!G52 -> TRUE | AX52: =H52=[1]营销售电!H52 -> TRUE | ... CA52: =AK52=[1]营销售电!AK52 -> TRUE
I53: 营销售电业务-16.营财账务协同管理-控制措施02 | J53: 营销部门按照财务核算规则开展营销收入、销项税等的账务核算并按日传递凭证。 | Q53: √ | T53: 系统已建 | U53: 智慧财务、营销2.0系统 | V53: 1.系统核算规则； 2.系统电费凭证； 3.营财对账记录 | W53: 各省（自治区、直辖市）电力公司-营销部门-电费管理人员 | X53: 每季度 | Y53: 抽查 | AA53: 年度 | AB53: 抽查 | AH53: 是 | AI53: 是 | AJ53: 《国家电网有限公司电费业务管理办法（征求意见稿）》第九章 电费账务 《国网营销部财务部关于明确营销2.0系统与智慧共享财务平台系统集成有关问题的意见》（营销营业〔2023〕86号文 ） | AK53: 国网营销部 | AL53: 待定 | AN53: 财务部 | AO53: 财务 | AP53: 增加智慧财务系统 | AQ53: =A53=[1]营销售电!A53 -> TRUE | AR53: =B53=[1]营销售电!B53 -> TRUE | AS53: =C53=[1]营销售电!C53 -> TRUE | AT53: =D53=[1]营销售电!D53 -> TRUE | AU53: =E53=[1]营销售电!E53 -> TRUE | AV53: =F53=[1]营销售电!F53 -> TRUE | AW53: =G53=[1]营销售电!G53 -> TRUE | AX53: =H53=[1]营销售电!H53 -> TRUE | ... CA53: =AK53=[1]营销售电!AK53 -> TRUE
I54: 营销售电业务-16.营财账务协同管理-控制措施03 | J54: 财务部门对营销部门会计凭证与会计事务代码匹配性、营财账务一致性开展复核与数字化在线监督，营财差异应及时反馈营销并督导消缺。 | M54: √ | Q54: √ | S54: √ | T54: 系统已建 | U54: 智慧财务、营销2.0系统 | V54: 数字化在线监督结果及异常消缺记录 | W54: 各省（自治区、直辖市）电力公司-财务部门-销售电价管理人员；各省（自治区、直辖市）电力公司-营销部门-电费电价管理人员 | X54: 每季度 | Y54: 抽查 | AA54: 年度 | AB54: 抽查 | AD54: 营财记账监督——营财账务一致性开展在线监督 | AE54: 每月 | AF54: 全量 | AH54: 是 | AI54: 是 | AJ54: 《国网营销部财务部关于明确营销2.0系统与智慧共享财务平台系统集成有关问题的意见》（营销营业〔2023〕86号文 ） | AK54: 国网财务部、国网营销部 | AL54: 待完善系统功能 | AM54: 正在功能开发中，待正式上线后应用。 | AN54: 供服、地市 | AO54: 地市财务、账务 | AP54: 账务专业无意见。 | AQ54: =A54=[1]营销售电!A54 -> TRUE | AR54: =B54=[1]营销售电!B54 -> TRUE | AS54: =C54=[1]营销售电!C54 -> TRUE | AT54: =D54=[1]营销售电!D54 -> TRUE | AU54: =E54=[1]营销售电!E54 -> TRUE | AV54: =F54=[1]营销售电!F54 -> TRUE | AW54: =G54=[1]营销售电!G54 -> TRUE | AX54: =H54=[1]营销售电!H54 -> TRUE | ... CA54: =AK54=[1]营销售电!AK54 -> TRUE
I55: 营销售电业务-16.营财账务协同管理-控制措施04 | J55: 营财账务调整应由营销结合业务进行调整并推送至财务，严禁单方面手工调整营财账务。 | Q55: √ | T55: 系统已建 | U55: 智慧财务、营销2.0系统 | V55: 1.财务记账单凭证明细及审批记录； 2.营销凭证生成标识 | W55: 各级单位-财务部门-销售电价管理人员；各级单位-营销部门-电费电价管理人员 | X55: 每季度 | Y55: 抽查 | AA55: 年度 | AB55: 抽查 | AH55: 是 | AI55: 是 | AJ55: 《国家电网有限公司电费业务管理办法（征求意见稿）》第九章 电费账务 《国网营销部财务部关于明确营销2.0系统与智慧共享财务平台系统集成有关问题的意见》（营销营业〔2023〕86号文 ） | AK55: 国网财务部、国网营销部 | AL55: 无变化，直接引用 | AM55: 无变化，直接引用 | AN55: 供服、地市 | AO55: 财务 | AP55: 账务专业无意见。 | AQ55: =A55=[1]营销售电!A55 -> TRUE | AR55: =B55=[1]营销售电!B55 -> TRUE | AS55: =C55=[1]营销售电!C55 -> TRUE | AT55: =D55=[1]营销售电!D55 -> TRUE | AU55: =E55=[1]营销售电!E55 -> TRUE | AV55: =F55=[1]营销售电!F55 -> TRUE | AW55: =G55=[1]营销售电!G55 -> TRUE | AX55: =H55=[1]营销售电!H55 -> TRUE | ... CA55: =AK55=[1]营销售电!AK55 -> TRUE
C56: 会计信息真实完整、资金资产安全、税务合规 | D56: 电费发票开具 | E56: 电费发票虚开未有效管控，引发税务合规风险。 | G56: 17.电费发票开具 | H56: 电费发票应与电费账单、业务费确认结果一致，严禁篡改开票信息 | I56: 营销售电业务-17.电费发票开具-控制措施01 | J56: 营销部门对电费（业务费）开票实施线上统一管理，强控开票规则与开票权限，不得篡改开票信息，营销开票结果与财务共享。 | M56: √ | Q56: √ | T56: 系统已建 | U56: 营销2.0系统 | V56: 1.营销系统开票票面信息； 2.开票规则 | W56: 各省（自治区、直辖市）电力公司-营销部门-电费管理人员、业务管理人员 | X56: 每半年 | Y56: 抽查 | AA56: 年度 | AB56: 抽查 | AH56: 是 | AI56: 是 | AJ56: 《国家电网有限公司电费业务管理办法（征求意见稿）》第十章 电费票据管理 第六十三条 《国网营销部财务部关于明确营销2.0系统与智慧共享财务平台系统集成有关问题的意见》（营销营业〔2023〕86号） 《国家电网有限公司发票管理规范（征求意见稿）》第二十四条至二十六条 | AK56: 国网营销部 | AL56: 修改责任主体 | AM56: 修改责任主体 | AN56: 省公司 | AO56: 反窃查违、业扩、电费 | AP56: 电费专业无意见。业扩专业：无变化，直接引用 | AQ56: =A56=[1]营销售电!A56 -> TRUE | AR56: =B56=[1]营销售电!B56 -> TRUE | AS56: =C56=[1]营销售电!C56 -> TRUE | AT56: =D56=[1]营销售电!D56 -> TRUE | AU56: =E56=[1]营销售电!E56 -> TRUE | AV56: =F56=[1]营销售电!F56 -> TRUE | AW56: =G56=[1]营销售电!G56 -> TRUE | AX56: =H56=[1]营销售电!H56 -> TRUE | ... CA56: =AK56=[1]营销售电!AK56 -> TRUE
I57: 营销售电业务-17.电费发票开具-控制措施02 | J57: 营销部门对未结清开票、分割开票严格履行审批程序，开票执行与电费账务执行不相容控制。 | K57: √ | L57: √ | T57: 系统已建 | U57: 营销2.0系统 | V57: 1.未结清、分割开票申请及审批资料； 2.系统开票结果 | W57: 各级单位-营销部门-电费管理人员及各级审批人员 | X57: 每季度 | Y57: 抽查 | AA57: 年度 | AB57: 抽查 | AH57: 是 | AI57: 是 | AJ57: 《国家电网有限公司电费业务管理办法（征求意见稿）》第十章 电费票据管理 《国家电网有限公司发票管理规范（征求意见稿）》第二十四条至二十六条 | AK57: 国网营销部 | AL57: 无变化，直接引用 | AM57: 无变化，直接引用 | AN57: 地市 | AO57: 电费 | AP57: 电费专业无意见 | AQ57: =A57=[1]营销售电!A57 -> TRUE | AR57: =B57=[1]营销售电!B57 -> TRUE | AS57: =C57=[1]营销售电!C57 -> TRUE | AT57: =D57=[1]营销售电!D57 -> TRUE | AU57: =E57=[1]营销售电!E57 -> TRUE | AV57: =F57=[1]营销售电!F57 -> TRUE | AW57: =G57=[1]营销售电!G57 -> TRUE | AX57: =H57=[1]营销售电!H57 -> TRUE | ... CA57: =AK57=[1]营销售电!AK57 -> TRUE
I58: 营销售电业务-17.电费发票开具-控制措施03 | J58: 电费（业务费）发票原则上在营销系统进行开具，如客户要求无法满足需在智慧财务（电子税务）开具的，应由营销系统将开票信息推送智慧财务，并推动营销系统改造。在智慧财务开具电费类发票的，履行严格审批程序。 | Q58: √ | T58: 系统待建 | U58: 营销2.0系统、智慧财务、电子税务系统 | V58: 1.营销全量开票信息； 2.智慧财务、电子税务开票信息及营销推送记录； 3.智慧财务开票即审批记录 | W58: 各级单位-营销部门-电费电价管理人员；各级单位-财务部门-税务管理人员 | X58: 每季度 | Y58: 抽查 | AA58: 年度 | AB58: 抽查 | AH58: 是 | AI58: 否 | AJ58: 《国家电网有限公司电费业务管理办法（征求意见稿）》第十章 电费票据管理 第六十三条 《国网营销部财务部关于明确营销2.0系统与智慧共享财务平台系统集成有关问题的意见》（营销营业〔2023〕86号） 《国家电网有限公司发票管理规范（征求意见稿）》第二十四条至二十六条 | AK58: 国网营销部、国网财务部 | AL58: 无变化，直接引用 | AM58: 无变化，直接引用 | AN58: 省公司 | AO58: 电费 | AP58: 电费专业无意见 | AQ58: =A58=[1]营销售电!A58 -> TRUE | AR58: =B58=[1]营销售电!B58 -> TRUE | AS58: =C58=[1]营销售电!C58 -> TRUE | AT58: =D58=[1]营销售电!D58 -> TRUE | AU58: =E58=[1]营销售电!E58 -> TRUE | AV58: =F58=[1]营销售电!F58 -> TRUE | AW58: =G58=[1]营销售电!G58 -> TRUE | AX58: =H58=[1]营销售电!H58 -> TRUE | ... CA58: =AK58=[1]营销售电!AK58 -> TRUE
I59: 营销售电业务-17.电费发票开具-控制措施04 | J59: 财务部门协同营销部门对全量数电票开具情况纳入数字化在线监测。 | M59: √ | S59: √ | T59: 系统待建 | U59: 营销2.0系统、智慧财务 | V59: 数字化在线监督结果及异常消缺记录 | W59: 各级单位-财务部门-税务管理人员；各级单位-营销部门-电费管理人员 | X59: 每季度 | Y59: 抽查 | AA59: 年度 | AB59: 抽查 | AD59: 数电票开票监督——开展全量数电票在线监测 | AE59: 每月 | AF59: 全量 | AH59: 是 | AI59: 否 | AJ59: 《国家电网有限公司电费业务管理办法（征求意见稿）》第十章 电费票据管理 第六十三条 | AK59: 国网财务部、国网营销部 | AL59: 无变化，直接引用 | AM59: 无变化，直接引用 | AN59: 地市 | AO59: 电费 | AP59: 电费专业无意见 | AQ59: =A59=[1]营销售电!A59 -> TRUE | AR59: =B59=[1]营销售电!B59 -> TRUE | AS59: =C59=[1]营销售电!C59 -> TRUE | AT59: =D59=[1]营销售电!D59 -> TRUE | AU59: =E59=[1]营销售电!E59 -> TRUE | AV59: =F59=[1]营销售电!F59 -> TRUE | AW59: =G59=[1]营销售电!G59 -> TRUE | AX59: =H59=[1]营销售电!H59 -> TRUE | ... CA59: =AK59=[1]营销售电!AK59 -> TRUE
A60: 营销售电业务 | B60: 五、电费账务及发票管理 | C60: 会计信息真实完整、资金资产安全、税务合规 | D60: 价外基金上交 | E60: 价外基金列转不及时、上交不准确，引发税务合规风险。 | G60: 18.价外基金上交 | H60: 价外基金征收范围完整、上缴金额准确 | I60: 营销售电业务-18.价外基金上交-控制措施01 | J60: 营销部门强化价外基金与电费发行一体化管控，确保价外基金征收范围完整、金额准确。 | M60: √ | T60: 系统已建 | U60: 营销2.0系统 | V60: 1.电费账单； 2.系统发行数据与营销报表 | W60: 各级单位-营销部门-电费电价管理人员 | X60: 每半年 | Y60: 抽查 | AA60: 年度 | AB60: 抽查 | AH60: 是 | AI60: 是 | AJ60: 《国家电网有限公司电费业务管理办法（征求意见稿）》第二章 电价执行 | AK60: 国网营销部 | AL60: 无变化，直接引用 | AM60: 无变化，直接引用 | AN60: 供服、地市 | AO60: 电费 | AP60: 电费专业无意见 | AQ60: =A60=[1]营销售电!A60 -> TRUE | AR60: =B60=[1]营销售电!B60 -> TRUE | AS60: =C60=[1]营销售电!C60 -> TRUE | AT60: =D60=[1]营销售电!D60 -> TRUE | AU60: =E60=[1]营销售电!E60 -> TRUE | AV60: =F60=[1]营销售电!F60 -> TRUE | AW60: =G60=[1]营销售电!G60 -> TRUE | AX60: =H60=[1]营销售电!H60 -> TRUE | ... CA60: =AK60=[1]营销售电!AK60 -> TRUE
I61: 营销售电业务-18.价外基金上交-控制措施02 | J61: 财务部门完成营销报表、账务信息核对一致性后完成上交，严禁篡改信息。 | M61: √ | T61: 系统已建 | U61: 智慧财务 | V61: 1.系统凭证； 2.系统发行数据与营销报表； | W61: 各级单位-财务部门-销售电价及财税管理人员 | X61: 每半年 | Y61: 抽查 | AA61: 年度 | AB61: 抽查 | AH61: 是 | AI61: 是 | AJ61: 《国家电网有限公司电价工作管理办法》政府性基金及附加管理 《国网财务部 国网营销部关于调整代征政府性基金财务核算和营业开票规则的通知》（财税〔2025〕29号） | AK61: 国网财务部 | AL61: 无变化，直接引用 | AM61: 无变化，直接引用 | AN61: 省公司 | AO61: 财务 | AP61: 账务专业无意见。 财务无意见 | AQ61: =A61=[1]营销售电!A61 -> TRUE | AR61: =B61=[1]营销售电!B61 -> TRUE | AS61: =C61=[1]营销售电!C61 -> TRUE | AT61: =D61=[1]营销售电!D61 -> TRUE | AU61: =E61=[1]营销售电!E61 -> TRUE | AV61: =F61=[1]营销售电!F61 -> TRUE | AW61: =G61=[1]营销售电!G61 -> TRUE | AX61: =H61=[1]营销售电!H61 -> TRUE | ... CA61: =AK61=[1]营销售电!AK61 -> TRUE
I62: 营销售电业务-18.价外基金上交-控制措施03 | J62: 财务部门对下级单位价外基金列转的及时性、准确性复核，确保按期足额上交财政部门。 | P62: √ | Q62: √ | T62: 系统已建 | U62: 智慧财务 | V62: 1.系统凭证； 2.系统上交数据 | W62: 各省（自治区、直辖市）电力公司-财务部门-销售电价及财税管理人员 | X62: 每半年 | Y62: 抽查 | AA62: 年度 | AB62: 抽查 | AH62: 是 | AI62: 是 | AJ62: 《国家电网有限公司电价工作管理办法》政府性基金及附加管理 | AK62: 国网财务部 | AL62: 无变化，直接引用 | AM62: 无变化，直接引用 | AN62: 省公司 | AO62: 财务 | AP62: 账务专业无意见。 财务无意见 | AQ62: =A62=[1]营销售电!A62 -> TRUE | AR62: =B62=[1]营销售电!B62 -> TRUE | AS62: =C62=[1]营销售电!C62 -> TRUE | AT62: =D62=[1]营销售电!D62 -> TRUE | AU62: =E62=[1]营销售电!E62 -> TRUE | AV62: =F62=[1]营销售电!F62 -> TRUE | AW62: =G62=[1]营销售电!G62 -> TRUE | AX62: =H62=[1]营销售电!H62 -> TRUE | ... CA62: =AK62=[1]营销售电!AK62 -> TRUE
I63: 营销售电业务-18.价外基金上交-控制措施04 | J63: 财务部门对价外基金上交情况开展数字化在线监测。 | M63: √ | S63: √ | T63: 系统待建 | U63: 智慧财务 | V63: 数字化在线监督结果及异常消缺记录 | W63: 各省（自治区、直辖市）电力公司-财务部门-销售电价及财税管理人员 | X63: 每半年 | Y63: 抽查 | AA63: 年度 | AB63: 抽查 | AD63: 价外基金上交监测——开展价外基金上交在线监测 | AE63: 每季度 | AF63: 全量 | AH63: 是 | AI63: 是 | AJ63: 《国家电网有限公司电价工作管理办法》政府性基金及附加管理 | AK63: 国网财务部 | AL63: 无变化，直接引用 | AM63: 无变化，直接引用 | AN63: 省公司 | AO63: 财务 | AP63: 账务专业无意见。 财务无意见 | AQ63: =A63=[1]营销售电!A63 -> TRUE | AR63: =B63=[1]营销售电!B63 -> TRUE | AS63: =C63=[1]营销售电!C63 -> TRUE | AT63: =D63=[1]营销售电!D63 -> TRUE | AU63: =E63=[1]营销售电!E63 -> TRUE | AV63: =F63=[1]营销售电!F63 -> TRUE | AW63: =G63=[1]营销售电!G63 -> TRUE | AX63: =H63=[1]营销售电!H63 -> TRUE | ... CA63: =AK63=[1]营销售电!AK63 -> TRUE
B64: 六、电费实收管理 | C64: 资金资产安全 | D64: 收费渠道管理 | E64: 代收渠道未统一管理，代收渠道协议不规范，引发资金挪用、财务账务不合规风险。 | G64: 19.代收渠道运行管理 | H64: 代收渠道应纳入省公司统一管理 | I64: 营销售电业务-19.代收渠道运行管理-控制措施01 | J64: 营销部门协同财务部门严格代收渠道新增、变更审批程序，加强地方代收渠道监控，加速清理超标、低效、扩范围违规代收渠道。 | P64: √ | T64: 线下管控 | V64: 1.新增（变更）代收渠道审批记录； 2.地方代收渠道纳入监控材料 | W64: 各省（自治区、直辖市）电力公司-营销部门-电费管理人员 | X64: 每年 | Y64: 抽查 | AA64: 年度 | AB64: 抽查 | AH64: 是 | AI64: 是 | AJ64: 《国网财务部关于规范和加强商户号管理的通知》（财金〔2025〕2号） 《国家电网有限公司司库管理办法》第二十三条、二十八条、第五章第二节收入管理 | AK64: 国网营销部 | AL64: 无变化，直接引用 | AM64: 无变化，直接引用 | AN64: 供服 | AO64: 账务 | AP64: 账务专业无意见。 | AQ64: =A64=[1]营销售电!A64 -> TRUE | AR64: =B64=[1]营销售电!B64 -> TRUE | AS64: =C64=[1]营销售电!C64 -> TRUE | AT64: =D64=[1]营销售电!D64 -> TRUE | AU64: =E64=[1]营销售电!E64 -> TRUE | AV64: =F64=[1]营销售电!F64 -> TRUE | AW64: =G64=[1]营销售电!G64 -> TRUE | AX64: =H64=[1]营销售电!H64 -> TRUE | ... CA64: =AK64=[1]营销售电!AK64 -> TRUE
I65: 营销售电业务-19.代收渠道运行管理-控制措施02 | J65: 营销部门加强代收渠道协议的统一管理，明确对账与结算责任条款。 | P65: √ | T65: 线下管控 | V65: 代收渠道合作协议（线下） | W65: 各省（自治区、直辖市）电力公司-营销部门-电费管理人员 | X65: 每年 | Y65: 抽查 | AA65: 年度 | AB65: 抽查 | AH65: 是 | AI65: 是 | AJ65: 《国网财务部关于规范和加强商户号管理的通知》（财金〔2025〕2号） 《国家电网有限公司司库管理办法》第二十三条、第五章第二节收入管理 | AK65: 国网营销部 | AL65: 无变化，直接引用 | AM65: 无变化，直接引用 | AN65: 供服 | AO65: 账务 | AP65: 账务专业无意见。 | AQ65: =A65=[1]营销售电!A65 -> TRUE | AR65: =B65=[1]营销售电!B65 -> TRUE | AS65: =C65=[1]营销售电!C65 -> TRUE | AT65: =D65=[1]营销售电!D65 -> TRUE | AU65: =E65=[1]营销售电!E65 -> TRUE | AV65: =F65=[1]营销售电!F65 -> TRUE | AW65: =G65=[1]营销售电!G65 -> TRUE | AX65: =H65=[1]营销售电!H65 -> TRUE | ... CA65: =AK65=[1]营销售电!AK65 -> TRUE
I66: 营销售电业务-19.代收渠道运行管理-控制措施03 | J66: 财务部门协同营销部门将各类代收渠道关联的银行账户、商户号纳入线上监控，营销部门每日开展对账，并及时将对账信息传递财务；财务部门每月对各电费账户、商户号进行资金对账复核，确保资金安全。 | P66: √ | Q66: √ | T66: 系统已建 | U66: 智慧财务、营销2.0系统 | V66: 1.营销对账记录； 2.财务复核记录 | W66: 各省（自治区、直辖市）电力公司-财务部门-资金管理人员；各省（自治区、直辖市）电力公司-营销部门-电费管理人员 | X66: 每季度 | Y66: 抽查 | AA66: 年度 | AB66: 抽查 | AD66: 代收渠道监管——将各类代收渠道关联的银行账户、商户号纳入线上监控 | AE66: 每月 | AF66: 全量 | AH66: 是 | AI66: 是 | AJ66: 《国网财务部关于规范和加强商户号管理的通知》（财金〔2025〕2号） 《国家电网有限公司司库管理办法》第五章第二节收入管理 | AK66: 国网财务部、国网营销部 | AL66: 无变化，直接引用 | AM66: 无变化，直接引用 | AN66: 供服、会服 | AO66: 财务、账务 | AP66: 账务专业无意见。 | AQ66: =A66=[1]营销售电!A66 -> TRUE | AR66: =B66=[1]营销售电!B66 -> TRUE | AS66: =C66=[1]营销售电!C66 -> TRUE | AT66: =D66=[1]营销售电!D66 -> TRUE | AU66: =E66=[1]营销售电!E66 -> TRUE | AV66: =F66=[1]营销售电!F66 -> TRUE | AW66: =G66=[1]营销售电!G66 -> TRUE | AX66: =H66=[1]营销售电!H66 -> TRUE | ... CA66: =AK66=[1]营销售电!AK66 -> TRUE
A67: 营销售电业务 | B67: 六、电费实收管理 | C67: 资金资产安全 | D67: 收费渠道管理 | E67: 资金到账情况未及时监管，导致资金滞留风险。 | G67: 20.代收渠道在途资金管理 | H67: 强化代收渠道对账及结算管控，督导在途资金处理 | I67: 营销售电业务-20.代收渠道在途资金管理-控制措施01 | J67: 营销部门建立每日对账机制，并以核对一致的对账数据为标准进行电费资金清算。 | M67: √ | P67: √ | T67: 系统已建 | U67: 营销2.0系统 | V67: 1.在途资金对账记录； 2.系统资金流水； | W67: 各级单位-营销部门-电费管理人员 | X67: 每月 | Y67: 抽查 | AA67: 年度 | AB67: 抽查 | AH67: 是 | AI67: 是 | AJ67: 《国网财务部关于规范和加强商户号管理的通知》（财金〔2025〕2号） 《国家电网有限公司司库管理办法》第五章第二节收入管理 | AK67: 国网营销部 | AL67: 无变化，直接引用 | AM67: 无变化，直接引用 | AN67: 供服 | AO67: 账务 | AP67: 账务专业无意见。 | AQ67: =A67=[1]营销售电!A67 -> TRUE | AR67: =B67=[1]营销售电!B67 -> TRUE | AS67: =C67=[1]营销售电!C67 -> TRUE | AT67: =D67=[1]营销售电!D67 -> TRUE | AU67: =E67=[1]营销售电!E67 -> TRUE | AV67: =F67=[1]营销售电!F67 -> TRUE | AW67: =G67=[1]营销售电!G67 -> TRUE | AX67: =H67=[1]营销售电!H67 -> TRUE | ... CA67: =AK67=[1]营销售电!AK67 -> TRUE
I68: 营销售电业务-20.代收渠道在途资金管理-控制措施02 | J68: 对于银行代收、商户号收取的尚未清分或清缴至电费账户的资金按在途资金管理与核算。 | Q68: √ | T68: 系统已建 | U68: 营销2.0系统 | V68: 1.在途资金明细； 2.电费账务凭证 | W68: 各级单位-营销部门-电费管理人员 | X68: 每月 | Y68: 抽查 | AA68: 年度 | AB68: 抽查 | AH68: 是 | AI68: 是 | AJ68: 《国网财务部关于规范和加强商户号管理的通知》（财金〔2025〕2号） 《国家电网有限公司司库管理办法》第六条 《国家电网有限公司会计核算办法》 | AK68: 国网营销部 | AL68: 无变化，直接引用 | AM68: 无变化，直接引用 | AN68: 供服 | AO68: 账务 | AP68: 账务专业无意见。 | AQ68: =A68=[1]营销售电!A68 -> TRUE | AR68: =B68=[1]营销售电!B68 -> TRUE | AS68: =C68=[1]营销售电!C68 -> TRUE | AT68: =D68=[1]营销售电!D68 -> TRUE | AU68: =E68=[1]营销售电!E68 -> TRUE | AV68: =F68=[1]营销售电!F68 -> TRUE | AW68: =G68=[1]营销售电!G68 -> TRUE | AX68: =H68=[1]营销售电!H68 -> TRUE | ... CA68: =AK68=[1]营销售电!AK68 -> TRUE
I69: 营销售电业务-20.代收渠道在途资金管理-控制措施03 | J69: 营销部门加强超限未到账的在途资金跟踪处理，开展数字化在线监测并设置资金到账及时性预警。 | P69: √ | S69: √ | T69: 系统待建 | U69: 营销2.0系统 | V69: 数字化在线监督结果及异常消缺记录 | W69: 各级单位-营销部门-电费管理人员 | X69: 每月 | Y69: 抽查 | AA69: 年度 | AB69: 抽查 | AD69: 在途资金监控——对在途资金开展在线监测并设置资金到账及时性预警 | AE69: 每日 | AF69: 全量 | AH69: 是 | AI69: 是 | AJ69: 《国网财务部关于规范和加强商户号管理的通知》（财金〔2025〕2号） 《国家电网有限公司司库管理办法》第六条 | AK69: 国网营销部 | AL69: 无变化，直接引用 | AM69: 无变化，直接引用 | AN69: 供服 | AO69: 账务 | AP69: 账务专业无意见。 | AQ69: =A69=[1]营销售电!A69 -> TRUE | AR69: =B69=[1]营销售电!B69 -> TRUE | AS69: =C69=[1]营销售电!C69 -> TRUE | AT69: =D69=[1]营销售电!D69 -> TRUE | AU69: =E69=[1]营销售电!E69 -> TRUE | AV69: =F69=[1]营销售电!F69 -> TRUE | AW69: =G69=[1]营销售电!G69 -> TRUE | AX69: =H69=[1]营销售电!H69 -> TRUE | ... CA69: =AK69=[1]营销售电!AK69 -> TRUE
C70: 资金资产安全 | D70: 收费渠道管理 | E70: 柜收资金安全性管控不到位，导致现金截留、账实不符、现金流失​​等风险。 | G70: 21.柜台收费在途资金管理 | H70: 柜台收费应与客户准确关联，并及时缴存银行 | I70: 营销售电业务-21.柜台收费在途资金管理-控制措施01 | J70: 营业厅（所）柜收人员收取现金要与客户及收费资金类别精准匹配，当面点清、验明真伪，收费后主动向客户提供收费票据（含电子票据）。 | M70: √ | P70: √ | T70: 线下管控 | V70: 1.系统收费解款记录； 2.银行缴存或到账记录 | W70: 各级单位-营销部门-营业厅柜台收费人员 | X70: 每月 | Y70: 抽查 | AA70: 年度 | AB70: 抽查 | AH70: 是 | AI70: 是 | AJ70: 《国家电网有限公司电费业务管理办法（征求意见稿）》第八章 电费收支 | AK70: 国网营销部 | AL70: 无变化，直接引用 | AM70: 无变化，直接引用 | AN70: 地市 | AO70: 电费 | AP70: 电费专业无意见 | AQ70: =A70=[1]营销售电!A70 -> TRUE | AR70: =B70=[1]营销售电!B70 -> TRUE | AS70: =C70=[1]营销售电!C70 -> TRUE | AT70: =D70=[1]营销售电!D70 -> TRUE | AU70: =E70=[1]营销售电!E70 -> TRUE | AV70: =F70=[1]营销售电!F70 -> TRUE | AW70: =G70=[1]营销售电!G70 -> TRUE | AX70: =H70=[1]营销售电!H70 -> TRUE | ... CA70: =AK70=[1]营销售电!AK70 -> TRUE
I71: 营销售电业务-21.柜台收费在途资金管理-控制措施02 | J71: 对于柜收现金，营业厅（所）收费人员应于日终解款并在线开展现金日记账及在途资金盘点，做到日清日结。现金日记账及现金盘点表应按照电子档案管理要求，取得电子签章或签批后归档，营业厅（所）负责人按月开展检查。 | P71: √ | Q71: √ | T71: 系统已建 | U71: 营销2.0系统 | V71: 1.营销现金日记账； 2.现金盘点表 | W71: 各级单位-营销部门-营业厅柜台收费人员 | X71: 每月 | Y71: 抽查 | AA71: 年度 | AB71: 抽查 | AH71: 是 | AI71: 否 | AJ71: 《国家电网有限公司电费业务管理办法（征求意见稿）》第八章 电费收支 《国家电网有限公司司库管理办法》第六十四条 | AK71: 国网营销部 | AL71: 无变化，直接引用 | AM71: 无变化，直接引用 | AN71: 地市 | AO71: 电费 | AP71: 电费专业无意见 | AQ71: =A71=[1]营销售电!A71 -> TRUE | AR71: =B71=[1]营销售电!B71 -> TRUE | AS71: =C71=[1]营销售电!C71 -> TRUE | AT71: =D71=[1]营销售电!D71 -> TRUE | AU71: =E71=[1]营销售电!E71 -> TRUE | AV71: =F71=[1]营销售电!F71 -> TRUE | AW71: =G71=[1]营销售电!G71 -> TRUE | AX71: =H71=[1]营销售电!H71 -> TRUE | ... CA71: =AK71=[1]营销售电!AK71 -> TRUE
I72: 营销售电业务-21.柜台收费在途资金管理-控制措施03 | J72: 柜收现金应及时缴存银行，通过解款时生成的唯一解款编码关联缴存信息等，确保银行流水与解款记录精准识别，实现自动销账、准确到账。 | M72: √ | P72: √ | T72: 系统待建 | U72: 营销2.0系统 | V72: 1.系统未自动收费记录； 2.系统自动收费记录交易标识或资金编码 | W72: 各级单位-营销部门-电费管理人员 | X72: 每月 | Y72: 抽查 | AA72: 年度 | AB72: 抽查 | AH72: 是 | AI72: 否 | AJ72: 《国家电网有限公司电费业务管理办法（征求意见稿）》第八章 电费收支 《国家电网有限公司司库管理办法》第六十四、六十七条 | AK72: 国网营销部 | AL72: 无变化，直接引用 | AM72: 无变化，直接引用 | AN72: 地市 | AO72: 电费 | AP72: 电费专业无意见 | AQ72: =A72=[1]营销售电!A72 -> TRUE | AR72: =B72=[1]营销售电!B72 -> TRUE | AS72: =C72=[1]营销售电!C72 -> TRUE | AT72: =D72=[1]营销售电!D72 -> TRUE | AU72: =E72=[1]营销售电!E72 -> TRUE | AV72: =F72=[1]营销售电!F72 -> TRUE | AW72: =G72=[1]营销售电!G72 -> TRUE | AX72: =H72=[1]营销售电!H72 -> TRUE | ... CA72: =AK72=[1]营销售电!AK72 -> TRUE
C73: 会计信息真实完整、资金资产安全 | D73: 实收销账 | E73: 电费销账不准确，引发资金流失及应收账款不实风险。 | G73: 22.电费销账标准制定 | H73: 电费销账应明确标准，与资金流水匹配，与客户准确关联 | I73: 营销售电业务-22.电费销账标准制定-控制措施01 | J73: 营销部门以资金流水、代收渠道对账文件、柜收现金等为依据收费到户，严禁在无可信缴费记录前提下完成电费收取。 | M73: √ | P73: √ | T73: 系统已建 | U73: 营销2.0系统 | V73: 1.系统电费一次销根凭证； 2.系统资金流水或代收渠道对账文件或柜收现金（票据） | W73: 各级单位-营销部门-柜收人员、电费管理人员 | X73: 每月 | Y73: 抽查 | AA73: 年度 | AB73: 抽查 | AH73: 是 | AI73: 是 | AJ73: 《国家电网有限公司司库管理办法》第六十七条 | AK73: 国网营销部 | AL73: 无变化，直接引用 | AM73: 无变化，直接引用 | AN73: 省公司、地市 | AO73: 账务 | AP73: 账务专业无意见。 | AQ73: =A73=[1]营销售电!A73 -> TRUE | AR73: =B73=[1]营销售电!B73 -> TRUE | AS73: =C73=[1]营销售电!C73 -> TRUE | AT73: =D73=[1]营销售电!D73 -> TRUE | AU73: =E73=[1]营销售电!E73 -> TRUE | AV73: =F73=[1]营销售电!F73 -> TRUE | AW73: =G73=[1]营销售电!G73 -> TRUE | AX73: =H73=[1]营销售电!H73 -> TRUE | ... CA73: =AK73=[1]营销售电!AK73 -> TRUE
I74: 营销售电业务-22.电费销账标准制定-控制措施02 | J74: 营销部门要采取措施促使银行流水与客户信息对应、与解款记录关联，确保自动收费、自动销账。对于无法自动收费的，应在系统中维护转账用户关系完成收费；需手工收取的原则上使用转账用户收费功能，并严格按照营销系统中银行流水进行收费。 | M74: √ | P74: √ | T74: 系统已建 | U74: 营销2.0系统 | V74: 1.系统人工收费记录； 2.转账用户管理 | W74: 各级单位-营销部门-电费管理人员 | X74: 每月 | Y74: 抽查 | AA74: 年度 | AB74: 抽查 | AH74: 是 | AI74: 否 | AJ74: 《国家电网有限公司电费业务管理办法（征求意见稿）》第八章 电费收支 第四十八条 | AK74: 国网营销部 | AL74: 无变化，直接引用 | AM74: 无变化，直接引用 | AN74: 供服、地市 | AO74: 账务 | AP74: 账务专业无意见。 | AQ74: =A74=[1]营销售电!A74 -> TRUE | AR74: =B74=[1]营销售电!B74 -> TRUE | AS74: =C74=[1]营销售电!C74 -> TRUE | AT74: =D74=[1]营销售电!D74 -> TRUE | AU74: =E74=[1]营销售电!E74 -> TRUE | AV74: =F74=[1]营销售电!F74 -> TRUE | AW74: =G74=[1]营销售电!G74 -> TRUE | AX74: =H74=[1]营销售电!H74 -> TRUE | ... CA74: =AK74=[1]营销售电!AK74 -> TRUE
I75: 营销售电业务-22.电费销账标准制定-控制措施03 | J75: 营销部门电费账务人员对收费记录与凭证开展一致性核对，电费收费与电费账务执行不相容控制。 | M75: √ | T75: 系统待建 | U75: 营销2.0系统 | V75: 1.系统电费一次销根凭证； 2.系统资金流水或代收渠道对账文件或柜收现金（票据）； 3.岗位权限配置 | W75: 各级单位-营销部门-电费管理人员 | X75: 每月 | Y75: 抽查 | AA75: 年度 | AB75: 抽查 | AH75: 是 | AI75: 是 | AJ75: 《国家电网有限公司电费业务管理办法（征求意见稿）》第八章 电费收支 第四十八条 《国家电网有限公司司库管理办法》第六十七、六十九条 | AK75: 国网营销部 | AL75: 无变化，直接引用 | AM75: 无变化，直接引用 | AN75: 供服、地市 | AO75: 账务 | AP75: 账务专业无意见。 | AQ75: =A75=[1]营销售电!A75 -> TRUE | AR75: =B75=[1]营销售电!B75 -> TRUE | AS75: =C75=[1]营销售电!C75 -> TRUE | AT75: =D75=[1]营销售电!D75 -> TRUE | AU75: =E75=[1]营销售电!E75 -> TRUE | AV75: =F75=[1]营销售电!F75 -> TRUE | AW75: =G75=[1]营销售电!G75 -> TRUE | AX75: =H75=[1]营销售电!H75 -> TRUE | ... CA75: =AK75=[1]营销售电!AK75 -> TRUE
A76: 营销售电业务 | B76: 六、电费实收管理 | C76: 会计信息真实完整 | D76: 预收互转 | E76: 电费预收结转不准确，导致账实不符风险。 | F76: 20.营销系统权限管控不严：存在重要业务流程权限设置不合规；电费收费、账务处理、财务审核和违约用电查处、审批等不相容岗位未分离；信息系统权限未严格落实实名制，账号权限与实际权责不符、一人存在多个账号等问题。 | G76: 23.预收互转规则控制 | H76: 预收电费应准确结转，关联到户 | I76: 营销售电业务-23.预收互转规则控制-控制措施01 | J76: 营销部门应明确预收互转规则并进行系统控制，确保预收结转精准到户。 | M76: √ | P76: √ | T76: 系统已建 | U76: 营销2.0系统 | V76: 1.系统预收电费互转规则； 2.系统预收电费互转明细； 3.岗位权限配置 | W76: 各省（自治区、直辖市）电力公司-营销部门-电费管理人员 | X76: 每半年 | Y76: 抽查 | AA76: 年度 | AB76: 抽查 | AH76: 是 | AI76: 是 | AJ76: 《国家电网有限公司电费业务管理办法（征求意见稿）》第九章 电费账务 第六十条、第十一章 风险管控 第六十六条 《电费退费、预收互转规则业务规则（试行）》 | AK76: 国网营销部 | AL76: 无变化，直接引用 | AM76: 无变化，直接引用 | AN76: 省公司 | AO76: 电费 | AP76: 电费专业无意见 | AQ76: =A76=[1]营销售电!A76 -> TRUE | AR76: =B76=[1]营销售电!B76 -> TRUE | AS76: =C76=[1]营销售电!C76 -> TRUE | AT76: =D76=[1]营销售电!D76 -> TRUE | AU76: =E76=[1]营销售电!E76 -> TRUE | AV76: =F76=[1]营销售电!F76 -> TRUE | AW76: =G76=[1]营销售电!G76 -> TRUE | AX76: =H76=[1]营销售电!H76 -> TRUE | ... CA76: =AK76=[1]营销售电!AK76 -> TRUE
I77: 营销售电业务-23.预收互转规则控制-控制措施02 | J77: 营销部门对集团（关联）户设立与变更履行严格审批程序。 | L77: √ | M77: √ | T77: 系统已建 | U77: 营销2.0系统 | V77: 1.系统集团（关联）户申请资料； 2.岗位权限配置 | W77: 各级单位-营销部门-电费管理及各级审批人员 | X77: 每季度 | Y77: 抽查 | AA77: 年度 | AB77: 抽查 | AH77: 是 | AI77: 是 | AJ77: 《国家电网有限公司电费业务管理办法（征求意见稿）》第九章 电费账务 第六十条、第十一章 风险管控 第六十六条 《电费退费、预收互转规则业务规则（试行）》 | AK77: 国网营销部 | AL77: 无变化，直接引用 | AM77: 无变化，直接引用 | AN77: 供服、地市 | AO77: 电费 | AP77: 电费专业无意见 | AQ77: =A77=[1]营销售电!A77 -> TRUE | AR77: =B77=[1]营销售电!B77 -> TRUE | AS77: =C77=[1]营销售电!C77 -> TRUE | AT77: =D77=[1]营销售电!D77 -> TRUE | AU77: =E77=[1]营销售电!E77 -> TRUE | AV77: =F77=[1]营销售电!F77 -> TRUE | AW77: =G77=[1]营销售电!G77 -> TRUE | AX77: =H77=[1]营销售电!H77 -> TRUE | ... CA77: =AK77=[1]营销售电!AK77 -> TRUE
I78: 营销售电业务-23.预收互转规则控制-控制措施03 | J78: 营销部门对集团（关联）户设立规范性、预收结转准确性开展数字化在线监测。 | M78: √ | S78: √ | T78: 系统待建 | U78: 营销2.0系统 | V78: 数字化在线监督结果或稽查工单及处理情况 | W78: 各级单位-营销部门-电费管理人员 | X78: 每季度 | Y78: 抽查 | AA78: 年度 | AB78: 抽查 | AD78: 预收互转监督——对集团（关联）户设立规范性、预收结转准确性开展在线监测 | AE78: 每月 | AF78: 全量 | AH78: 是 | AI78: 是 | AJ78: 《国家电网有限公司电费业务管理办法（征求意见稿）》第九章 电费账务 第六十条 《电费退费、预收互转规则业务规则（试行）》 | AK78: 国网营销部 | AL78: 无变化，直接引用 | AM78: 无变化，直接引用 | AN78: 省公司、地市 | AO78: 电费 | AP78: 电费专业无意见 | AQ78: =A78=[1]营销售电!A78 -> TRUE | AR78: =B78=[1]营销售电!B78 -> TRUE | AS78: =C78=[1]营销售电!C78 -> TRUE | AT78: =D78=[1]营销售电!D78 -> TRUE | AU78: =E78=[1]营销售电!E78 -> TRUE | AV78: =F78=[1]营销售电!F78 -> TRUE | AW78: =G78=[1]营销售电!G78 -> TRUE | AX78: =H78=[1]营销售电!H78 -> TRUE | ... CA78: =AK78=[1]营销售电!AK78 -> TRUE
C79: 会计信息真实完整、资金资产安全 | D79: 电费坏账管理 | E79: 应收电费账龄不准确，引发合规及资金风险。 | G79: 24.电费账龄与客户信用管理 | H79: 电费账龄准确，与客户准确关联 | I79: 营销售电业务-24.电费账龄与客户信用管理-控制措施01 | J79: 营销部门做好应收电费账龄管理，确保每一笔电费账龄准确，电费收取与账务执行不相容控制。 | K79: √ | M79: √ | T79: 系统已建 | U79: 营销2.0系统 | V79: 1.应收电费账龄台账； 2.岗位权限配置 | W79: 各级单位-营销部门-电费管理人员 | X79: 每年 | Y79: 抽查 | AA79: 年度 | AB79: 抽查 | AH79: 是 | AI79: 是 | AJ79: 《国家电网有限公司电费业务管理办法（征求意见稿）》第十一章 风险管控 | AK79: 国网营销部 | AL79: 无变化，直接引用 | AM79: 无变化，直接引用 | AN79: 供服 | AO79: 账务 | AP79: 账务专业无意见。 | AQ79: =A79=[1]营销售电!A79 -> TRUE | AR79: =B79=[1]营销售电!B79 -> TRUE | AS79: =C79=[1]营销售电!C79 -> TRUE | AT79: =D79=[1]营销售电!D79 -> TRUE | AU79: =E79=[1]营销售电!E79 -> TRUE | AV79: =F79=[1]营销售电!F79 -> TRUE | AW79: =G79=[1]营销售电!G79 -> TRUE | AX79: =H79=[1]营销售电!H79 -> TRUE | ... CA79: =AK79=[1]营销售电!AK79 -> TRUE
I80: 营销售电业务-24.电费账龄与客户信用管理-控制措施02 | J80: 营销部门建立客户信用管理，清晰掌握重点客户经营状况，审慎评估回收风险，足额、准确提供应收电费坏账准备计提依据。 | M80: √ | Q80: √ | T80: 系统待建 | U80: 营销2.0系统 | V80: 1.应收电费账龄台账； 2.客户信用管理资料 | W80: 各级单位-营销部门-电费管理人员 | X80: 每年 | Y80: 抽查 | AA80: 年度 | AB80: 抽查 | AH80: 是 | AI80: 是 | AJ80: 《国家电网有限公司电费业务管理办法（征求意见稿）》第十一章 风险管控 第六十六、六十七条 | AK80: 国网营销部 | AL80: 无变化，直接引用 | AM80: 无变化，直接引用 | AN80: 省公司 | AO80: 电费 | AP80: 电费专业无意见 | AQ80: =A80=[1]营销售电!A80 -> TRUE | AR80: =B80=[1]营销售电!B80 -> TRUE | AS80: =C80=[1]营销售电!C80 -> TRUE | AT80: =D80=[1]营销售电!D80 -> TRUE | AU80: =E80=[1]营销售电!E80 -> TRUE | AV80: =F80=[1]营销售电!F80 -> TRUE | AW80: =G80=[1]营销售电!G80 -> TRUE | AX80: =H80=[1]营销售电!H80 -> TRUE | ... CA80: =AK80=[1]营销售电!AK80 -> TRUE
C81: 会计信息真实完整 | D81: 电费坏账管理 | E81: 应收电费坏账未及时计提，计提不准确，导致利润失真风险。 | G81: 25.电费坏账计提与核销 | H81: 坏账计提足额准确 | I81: 营销售电业务-25.电费坏账计提与核销-控制措施01 | J81: 财务部门按照统一的坏账计提政策，制定准确的坏账计提方案。营销部门接收财务坏账计提方案，并根据应收电费账龄和客户信用情况生成坏账计提依据，经财务审核后完成坏账计提（转回）。 | M81: √ | Q81: √ | T81: 系统待建 | U81: 智慧财务、营销2.0系统 | V81: 1.应收电费账龄台账； 2.客户信用管理资料； 3.系统电费坏账计提规则及记录 | W81: 各级单位-财务部门-账务管理人员；各级单位-营销部门-电费管理人员 | X81: 每年 | Y81: 抽查 | AA81: 年度 | AB81: 抽查 | AH81: 是 | AI81: 是 | AJ81: 《国家电网有限公司会计核算办法》第二章债权债务、《国家电网有限公司会计基础管理办法》第六十二条 《国家电网有限公司电费业务管理办法（征求意见稿）》第十一章 风险管控 第六十六、六十七条 | AK81: 国网财务部、国网营销部 | AL81: 无变化，直接引用 | AM81: 无变化，直接引用 | AN81: 省公司、地市 | AO81: 电费、财务 | AP81: 电费专业无意见 财务专业无意见 | AQ81: =A81=[1]营销售电!A81 -> TRUE | AR81: =B81=[1]营销售电!B81 -> TRUE | AS81: =C81=[1]营销售电!C81 -> TRUE | AT81: =D81=[1]营销售电!D81 -> TRUE | AU81: =E81=[1]营销售电!E81 -> TRUE | AV81: =F81=[1]营销售电!F81 -> TRUE | AW81: =G81=[1]营销售电!G81 -> TRUE | AX81: =H81=[1]营销售电!H81 -> TRUE | ... CA81: =AK81=[1]营销售电!AK81 -> TRUE
I82: 营销售电业务-25.电费坏账计提与核销-控制措施02 | J82: 对满足条件的电费坏账，营销部门应履行决策程序，经财务审核后核销，同步做好账销案存管理。 | M82: √ | Q82: √ | T82: 系统待建 | U82: 营销2.0系统、智慧财务 | V82: 1.应收电费账龄台账； 2.客户信用等级评价及其他资料； 3.坏账核销资料 | W82: 各级单位-营销部门-电费管理人员；各级单位-财务部门-账务管理人员 | X82: 每年 | Y82: 抽查 | AA82: 年度 | AB82: 抽查 | AD82: 电费坏账计提监督--对应收电费账龄（超一年以上的欠费）、坏账计提依据及结果进行监督 | AE82: 每年 | AF82: 全量 | AH82: 是 | AI82: 是 | AJ82: 《国家电网有限公司会计核算办法》 《国家电网有限公司会计基础管理办法》第六十二条 | AK82: 国网营销部、国网财务部 | AL82: 无变化，直接引用 | AM82: 无变化，直接引用 | AN82: 省公司、地市 | AO82: 电费、财务 | AP82: 电费专业无意见 财务专业无意见 | AQ82: =A82=[1]营销售电!A82 -> TRUE | AR82: =B82=[1]营销售电!B82 -> TRUE | AS82: =C82=[1]营销售电!C82 -> TRUE | AT82: =D82=[1]营销售电!D82 -> TRUE | AU82: =E82=[1]营销售电!E82 -> TRUE | AV82: =F82=[1]营销售电!F82 -> TRUE | AW82: =G82=[1]营销售电!G82 -> TRUE | AX82: =H82=[1]营销售电!H82 -> TRUE | ... CA82: =AK82=[1]营销售电!AK82 -> TRUE
A83: 营销售电业务 | B83: 六、电费实收管理 | C83: 会计信息真实完整、资金资产安全 | D83: 资金勾对 | E83: 实收账务与资金流水不匹配，导致账实不符风险。 | G83: 26.资金勾对复核 | H83: 电费实收账务与资金流水准确关联 | I83: 营销售电业务-26.资金勾对复核-控制措施01 | J83: 营销部门按日完成资金日流水与账务核对，确保账实相符，同时将收款明细凭证与银行资金流水勾对记录按日传递至财务，电费收费与电费账务执行不相容分离。 | K83: √ | P83: √ | Q83: √ | T83: 系统已建 | U83: 营销2.0系统 | V83: 1.系统资金勾对记录； 2.系统电费实收凭证； 3.营财银线上对账记录 | W83: 各级单位-营销部门-电费管理人员 | X83: 每月 | Y83: 抽查 | AA83: 年度 | AB83: 抽查 | AH83: 是 | AI83: 是 | AJ83: 《国网营销部财务部关于明确营销2.0系统与智慧共享财务平台系统集成有关问题的意见》（营销营业〔2023〕86号） | AK83: 国网营销部 | AL83: 待完善系统功能 | AM83: 按日完成资金日流水与账务核对，确保账实相符，但未按日将记录传递至财务，目前正在系统改造。 | AN83: 供服、会服 | AO83: 账务、账务 | AP83: 账务专业无意见。 | AQ83: =A83=[1]营销售电!A83 -> TRUE | AR83: =B83=[1]营销售电!B83 -> TRUE | AS83: =C83=[1]营销售电!C83 -> TRUE | AT83: =D83=[1]营销售电!D83 -> TRUE | AU83: =E83=[1]营销售电!E83 -> TRUE | AV83: =F83=[1]营销售电!F83 -> TRUE | AW83: =G83=[1]营销售电!G83 -> TRUE | AX83: =H83=[1]营销售电!H83 -> TRUE | ... CA83: =AK83=[1]营销售电!AK83 -> TRUE
I84: 营销售电业务-26.资金勾对复核-控制措施02 | J84: 财务部门按日对营销的对账结果进行复核，开展线上营财银对账。 | M84: √ | Q84: √ | S84: √ | T84: 系统已建 | U84: 智慧财务 | V84: 银企对账记录 | W84: 各省（自治区、直辖市）电力公司-财务部门-资金管理人员 | X84: 每季度 | Y84: 抽查 | AA84: 年度 | AB84: 抽查 | AD84: 银企对账监督——营财银对账 | AE84: 每日 | AF84: 全量 | AH84: 是 | AI84: 是 | AJ84: 《国网营销部财务部关于明确营销2.0系统与智慧共享财务平台系统集成有关问题的意见》（营销营业〔2023〕86号） | AK84: 国网财务部 | AL84: 待完善系统功能 | AM84: 正在功能开发中，待正式上线后应用。 | AN84: 供服、会服 | AO84: 账务、账务 | AP84: 账务专业无意见。 | AQ84: =A84=[1]营销售电!A84 -> TRUE | AR84: =B84=[1]营销售电!B84 -> TRUE | AS84: =C84=[1]营销售电!C84 -> TRUE | AT84: =D84=[1]营销售电!D84 -> TRUE | AU84: =E84=[1]营销售电!E84 -> TRUE | AV84: =F84=[1]营销售电!F84 -> TRUE | AW84: =G84=[1]营销售电!G84 -> TRUE | AX84: =H84=[1]营销售电!H84 -> TRUE | ... CA84: =AK84=[1]营销售电!AK84 -> TRUE
I85: 营销售电业务-26.资金勾对复核-控制措施03 | J85: 财务部门按月开展银行对账单与营财核对一致的收款账务明细勾对校核，编制银行存款（商户号）余额调节表，从严管控未达账项。 | K85: √ | M85: √ | Q85: √ | T85: 系统已建 | U85: 智慧财务 | V85: 1.银企对账记录； 2.银行余额调节表 | W85: 各省（自治区、直辖市）电力公司-财务部门-资金管理人员 | X85: 每季度 | Y85: 抽查 | AA85: 年度 | AB85: 抽查 | AH85: 是 | AI85: 是 | AJ85: 《国网营销部财务部关于明确营销2.0系统与智慧共享财务平台系统集成有关问题的意见》（营销营业〔2023〕86号） 《国家电网有限公司司库管理办法》第三十八条、三十九条 | AK85: 国网财务部 | AL85: 无变化，直接引用 | AM85: 无变化，直接引用 | AN85: 供服、会服 | AO85: 财务 | AP85: 账务专业无意见。 | AQ85: =A85=[1]营销售电!A85 -> TRUE | AR85: =B85=[1]营销售电!B85 -> TRUE | AS85: =C85=[1]营销售电!C85 -> TRUE | AT85: =D85=[1]营销售电!D85 -> TRUE | AU85: =E85=[1]营销售电!E85 -> TRUE | AV85: =F85=[1]营销售电!F85 -> TRUE | AW85: =G85=[1]营销售电!G85 -> TRUE | AX85: =H85=[1]营销售电!H85 -> TRUE | ... CA85: =AK85=[1]营销售电!AK85 -> TRUE
C86: 会计信息真实完整、资金资产安全 | D86: 不明款管理 | E86: 不明款确认及销账不准确，导致资金性质混乱、账实不符风险。 | G86: 27.不明款确认与核销 | H86: 强化不明款管控，不明款销账时应确保与客户精准匹配 | I86: 营销售电业务-27.不明款确认与核销-控制措施01 | J86: 营销部门对长期未关联到户的银行流水应及时确认不明款，并加强清理。 | P86: √ | Q86: √ | T86: 系统已建 | U86: 营销2.0系统 | V86: 1.不明款确认（销账）明细表； 2.系统不明款台账或流水记录 | W86: 各级单位-营销部门-电费管理人员 | X86: 每半年 | Y86: 抽查 | AA86: 年度 | AB86: 抽查 | AH86: 是 | AI86: 否 | AJ86: 《国家电网有限公司电费业务管理办法（征求意见稿）》第二章 职责分工 第九章电费账务 | AK86: 国网营销部 | AL86: 无变化，直接引用 | AM86: 无变化，直接引用 | AN86: 供服、地市 | AO86: 账务、电费 | AP86: 电费专业无意见 | AQ86: =A86=[1]营销售电!A86 -> TRUE | AR86: =B86=[1]营销售电!B86 -> TRUE | AS86: =C86=[1]营销售电!C86 -> TRUE | AT86: =D86=[1]营销售电!D86 -> TRUE | AU86: =E86=[1]营销售电!E86 -> TRUE | AV86: =F86=[1]营销售电!F86 -> TRUE | AW86: =G86=[1]营销售电!G86 -> TRUE | AX86: =H86=[1]营销售电!H86 -> TRUE | ... CA86: =AK86=[1]营销售电!AK86 -> TRUE
I87: 营销售电业务-27.不明款确认与核销-控制措施02 | J87: 营销部门对三年及以上或有确凿证据表明无法支付的不明款项，应及时履行决策程序，经严格审批后结转营业外收入。 | L87: √ | Q87: √ | T87: 线下管控、系统已建 | U87: 营销2.0系统 | V87: 1.不明款转营业外资料； 2.不明款转营业外记录 | W87: 各级单位-营销部门-电费管理及各级审批人员 | X87: 每年 | Y87: 抽查 | AA87: 年度 | AB87: 抽查 | AH87: 是 | AI87: 否 | AJ87: 《国家电网有限公司电费业务管理办法（征求意见稿）》第二章 职责分工 第九章电费账务 《国家电网有限公司会计基础管理办法》中第四节第六十二条 | AK87: 国网营销部 | AL87: 无变化，直接引用 | AM87: 无变化，直接引用 | AN87: 地市 | AO87: 电费 | AP87: 电费专业无意见 | AQ87: =A87=[1]营销售电!A87 -> TRUE | AR87: =B87=[1]营销售电!B87 -> TRUE | AS87: =C87=[1]营销售电!C87 -> TRUE | AT87: =D87=[1]营销售电!D87 -> TRUE | AU87: =E87=[1]营销售电!E87 -> TRUE | AV87: =F87=[1]营销售电!F87 -> TRUE | AW87: =G87=[1]营销售电!G87 -> TRUE | AX87: =H87=[1]营销售电!H87 -> TRUE | ... CA87: =AK87=[1]营销售电!AK87 -> TRUE
I88: 营销售电业务-27.不明款确认与核销-控制措施03 | J88: 财务部门对跨月的不明款项进行督导消缺，并对不明款转营业外规范性开展核查。 | Q88: √ | S88: √ | T88: 系统已建 | U88: 智慧财务 | V88: 1.不明款台账或流水记录； 2.不明款转营业外资料； 3.不明款转营业外记录 | W88: 各级单位-财务部门-资金（总账）管理人员、销售电价管理人员 | X88: 每季度 | Y88: 抽查 | AA88: 年度 | AB88: 抽查 | AD88: 不明款对账监督——对不明款进行预警与督导消缺 | AE88: 每月 | AF88: 全量 | AH88: 是 | AI88: 是 | AJ88: 《国网营销部财务部关于明确营销2.0系统与智慧共享财务平台系统集成有关问题的意见》（营销营业〔2023〕86号） 《国家电网有限公司会计基础管理办法》中第四节第六十二条 | AK88: 国网财务部 | AL88: 无变化，直接引用 | AM88: 无变化，直接引用 | AN88: 地市 | AO88: 财务 | AP88: 账务专业无意见。 | AQ88: =A88=[1]营销售电!A88 -> TRUE | AR88: =B88=[1]营销售电!B88 -> TRUE | AS88: =C88=[1]营销售电!C88 -> TRUE | AT88: =D88=[1]营销售电!D88 -> TRUE | AU88: =E88=[1]营销售电!E88 -> TRUE | AV88: =F88=[1]营销售电!F88 -> TRUE | AW88: =G88=[1]营销售电!G88 -> TRUE | AX88: =H88=[1]营销售电!H88 -> TRUE | ... CA88: =AK88=[1]营销售电!AK88 -> TRUE
A89: 营销售电业务 | B89: 七、营销退费管理 | C89: 会计信息真实完整、资金资产安全 | D89: 退费申请 | E89: 退费资料不真实、系统录入错误，导致虚假退费、重复退费或资金冒领风险。 | F89: 20.营销系统权限管控不严：存在重要业务流程权限设置不合规；电费收费、账务处理、财务审核和违约用电查处、审批等不相容岗位未分离；信息系统权限未严格落实实名制，账号权限与实际权责不符、一人存在多个账号等问题。 | G89: 28.退费申请与退费资料一致性管控 | H89: 退费申请与退费资料一致，系统录入准确 | I89: 营销售电业务-28.退费申请与退费资料一致性管控-控制措施01 | J89: 营销部门明确营销退费场景，建立分类分级审批标准，优先选用原路退回和常用缴费账号退回，并探索建立直退机制。对因客户申请等其他原因非原路退回的提级审批。 | L89: √ | M89: √ | P89: √ | T89: 系统待建 | U89: 营销2.0系统 | V89: 1.退费分级分类审批标准； 2.原路退回管理及建设情况； 3.退费审批分级授权记录 | W89: 各级单位-营销部门-电费管理人员及各级审批人员 | X89: 每半年 | Y89: 抽查 | AA89: 年度 | AB89: 抽查 | AH89: 是 | AI89: 是 | AJ89: 《国家电网有限公司电费业务管理办法（征求意见稿）》第八章 电费收支 第五十一条 《电费退费、预收互转规则业务规则（试行）》 | AK89: 国网营销部 | AL89: 无变化，直接引用 | AM89: 无变化，直接引用 | AN89: 地市 | AO89: 电费 | AP89: 电费专业无意见 | AQ89: =A89=[1]营销售电!A89 -> TRUE | AR89: =B89=[1]营销售电!B89 -> TRUE | AS89: =C89=[1]营销售电!C89 -> TRUE | AT89: =D89=[1]营销售电!D89 -> TRUE | AU89: =E89=[1]营销售电!E89 -> TRUE | AV89: =F89=[1]营销售电!F89 -> TRUE | AW89: =G89=[1]营销售电!G89 -> TRUE | AX89: =H89=[1]营销售电!H89 -> TRUE | ... CA89: =AK89=[1]营销售电!AK89 -> TRUE
I90: 营销售电业务-28.退费申请与退费资料一致性管控-控制措施02 | J90: 营销部门业务受理人员对退费资料完整性、客户关键信息与资料一致性进行核对，加强系统上传影像与线下资料一致性管控，并准确录入系统。 | M90: √ | P90: √ | T90: 线下管控 | V90: 1.系统客户退费资料影像； 2.系统退费信息 | W90: 各级单位-营销部门-业务受理人员 | X90: 每季度 | Y90: 抽查 | AA90: 年度 | AB90: 抽查 | AH90: 是 | AI90: 是 | AJ90: 《国家电网有限公司电费业务管理办法（征求意见稿）》第八章 电费收支 第五十一条 《电费退费、预收互转规则业务规则（试行）》 | AK90: 国网营销部 | AL90: 无变化，直接引用 | AM90: 无变化，直接引用 | AN90: 地市 | AO90: 电费 | AP90: 电费专业无意见 | AQ90: =A90=[1]营销售电!A90 -> TRUE | AR90: =B90=[1]营销售电!B90 -> TRUE | AS90: =C90=[1]营销售电!C90 -> TRUE | AT90: =D90=[1]营销售电!D90 -> TRUE | AU90: =E90=[1]营销售电!E90 -> TRUE | AV90: =F90=[1]营销售电!F90 -> TRUE | AW90: =G90=[1]营销售电!G90 -> TRUE | AX90: =H90=[1]营销售电!H90 -> TRUE | ... CA90: =AK90=[1]营销售电!AK90 -> TRUE
I91: 营销售电业务-28.退费申请与退费资料一致性管控-控制措施03 | J91: 营销部门电费管理人员对系统退费信息与退费资料一致性进行复核。 | M91: √ | T91: 系统已建 | U91: 营销2.0系统 | V91: 系统退费信息及审核记录 | W91: 各级单位-营销部门-电费管理人员 | X91: 每季度 | Y91: 抽查 | AA91: 年度 | AB91: 抽查 | AH91: 是 | AI91: 是 | AJ91: 《国家电网有限公司电费业务管理办法（征求意见稿）》第八章 电费收支 第五十一条 《电费退费、预收互转规则业务规则（试行）》 | AK91: 国网营销部 | AL91: 无变化，直接引用 | AM91: 无变化，直接引用 | AN91: 地市 | AO91: 电费 | AP91: 电费专业无意见 | AQ91: =A91=[1]营销售电!A91 -> TRUE | AR91: =B91=[1]营销售电!B91 -> TRUE | AS91: =C91=[1]营销售电!C91 -> TRUE | AT91: =D91=[1]营销售电!D91 -> TRUE | AU91: =E91=[1]营销售电!E91 -> TRUE | AV91: =F91=[1]营销售电!F91 -> TRUE | AW91: =G91=[1]营销售电!G91 -> TRUE | AX91: =H91=[1]营销售电!H91 -> TRUE | ... CA91: =AK91=[1]营销售电!AK91 -> TRUE
I92: 营销售电业务-28.退费申请与退费资料一致性管控-控制措施04 | J92: 营销部门加强销户（过户）业务联办退费管理，对销户后无法联系客户或客户拒不办理等原因导致的确实无法支付的款项，营销部门及时履行决策程序后，经严格审批后结转营业外收入，并做好账销案存管理。 | L92: √ | Q92: √ | T92: 线下管控、系统已建 | U92: 营销2.0系统 | V92: 1.销户有预收明细； 2.销户有预收转营业外记录； 3.销户有预收转营业外资料 | W92: 各级单位-营销部门-电费管理及各级审批人员 | X92: 每半年 | Y92: 抽查 | AA92: 年度 | AB92: 抽查 | AH92: 是 | AI92: 是 | AJ92: 《国家电网有限公司电费业务管理办法（征求意见稿）》第八章 电费收支 第五十一条 《国家电网有限公司会计基础管理办法》中第四节第六十二条 《电费退费、预收互转规则业务规则（试行）》 | AK92: 国网营销部 | AL92: 无变化，直接引用 | AM92: 无变化，直接引用 | AN92: 地市 | AO92: 电费、业扩 | AP92: 电费专业无意见。业扩专业：无变化，直接引用 | AQ92: =A92=[1]营销售电!A92 -> TRUE | AR92: =B92=[1]营销售电!B92 -> TRUE | AS92: =C92=[1]营销售电!C92 -> TRUE | AT92: =D92=[1]营销售电!D92 -> TRUE | AU92: =E92=[1]营销售电!E92 -> TRUE | AV92: =F92=[1]营销售电!F92 -> TRUE | AW92: =G92=[1]营销售电!G92 -> TRUE | AX92: =H92=[1]营销售电!H92 -> TRUE | ... CA92: =AK92=[1]营销售电!AK92 -> TRUE
I93: 营销售电业务-28.退费申请与退费资料一致性管控-控制措施05 | J93: 财务部门对客户收款信息、退费主体资格开展系统录入信息与退费影像一致性复查，对结转营业外收入规范性开展核查。 | M93: √ | Q93: √ | T93: 系统已建 | U93: 智慧财务 | V93: 1.系统退费信息及审核记录； 2.销户有预收转营业外记录； 3.销户有预收转营业外资料 | W93: 各级单位-财务部门-销售电价管理人员 | X93: 每半年 | Y93: 抽查 | AA93: 年度 | AB93: 抽查 | AH93: 是 | AI93: 是 | AJ93: 《国网营销部财务部关于明确营销2.0系统与智慧共享财务平台系统集成有关问题的意见》（营销营业〔2023〕86号） 《国家电网有限公司会计基础管理办法》中第四节第六十二条 | AK93: 国网财务部 | AL93: 无变化，直接引用 | AM93: 无变化，直接引用 | AN93: 地市 | AO93: 财务 | AP93: 账务专业无意见。 | AQ93: =A93=[1]营销售电!A93 -> TRUE | AR93: =B93=[1]营销售电!B93 -> TRUE | AS93: =C93=[1]营销售电!C93 -> TRUE | AT93: =D93=[1]营销售电!D93 -> TRUE | AU93: =E93=[1]营销售电!E93 -> TRUE | AV93: =F93=[1]营销售电!F93 -> TRUE | AW93: =G93=[1]营销售电!G93 -> TRUE | AX93: =H93=[1]营销售电!H93 -> TRUE | ... CA93: =AK93=[1]营销售电!AK93 -> TRUE
C94: 资金资产安全 | D94: 退费审批 | E94: 退费未经有效审核审批，导致公司资金流失、财务数据失真风险。 | F94: 20.营销系统权限管控不严：存在重要业务流程权限设置不合规；电费收费、账务处理、财务审核和违约用电查处、审批等不相容岗位未分离；信息系统权限未严格落实实名制，账号权限与实际权责不符、一人存在多个账号等问题。 | G94: 29.退费审批权限及流程设置 | H94: 退费资金分级授权科学、合理 | I94: 营销售电业务-29.退费审批权限及流程设置-控制措施01 | J94: 财务部门建立电费退费资金分级授权审批机制，确保系统流程轨迹可视、授权管理科学。 | L94: √ | T94: 系统已建 | U94: 智慧财务 | V94: 1.资金分级授权 2.支付轨迹 | W94: 各省（自治区、直辖市）电力公司-财务部门-资金分级授权管理人员 | X94: 每年 | Y94: 抽查 | AA94: 年度 | AB94: 抽查 | AH94: 是 | AI94: 是 | AJ94: 《国家电网有限公司司库管理办法》第七十四条 | AK94: 国网财务部 | AL94: 无变化，直接引用 | AM94: 无变化，直接引用 | AN94: 省公司 | AO94: 财务 | AP94: 账务专业无意见。 | AQ94: =A94=[1]营销售电!A94 -> TRUE | AR94: =B94=[1]营销售电!B94 -> TRUE | AS94: =C94=[1]营销售电!C94 -> TRUE | AT94: =D94=[1]营销售电!D94 -> TRUE | AU94: =E94=[1]营销售电!E94 -> TRUE | AV94: =F94=[1]营销售电!F94 -> TRUE | AW94: =G94=[1]营销售电!G94 -> TRUE | AX94: =H94=[1]营销售电!H94 -> TRUE | ... CA94: =AK94=[1]营销售电!AK94 -> TRUE
I95: 营销售电业务-29.退费审批权限及流程设置-控制措施02 | J95: 营销部门按照资金分级授权建立内部退费审批流程，对权限配置与岗位权限一致性进行校核。 | L95: √ | M95: √ | P95: √ | T95: 系统已建 | U95: 营销2.0系统 | V95: 1.系统退费审批单； 2.资金分级授权； 3.岗位权限配置； 4.系统退费信息 | W95: 各级单位-营销部门-电费管理及各级审批人员 | X95: 每年 | Y95: 抽查 | AA95: 年度 | AB95: 抽查 | AH95: 是 | AI95: 是 | AJ95: 《国家电网有限公司电费业务管理办法（征求意见稿）》第八章 电费收支 第五十一条 | AK95: 国网营销部 | AL95: 无变化，直接引用 | AM95: 无变化，直接引用 | AN95: 省公司、地市 | AO95: 电费 | AP95: 电费专业无意见 | AQ95: =A95=[1]营销售电!A95 -> TRUE | AR95: =B95=[1]营销售电!B95 -> TRUE | AS95: =C95=[1]营销售电!C95 -> TRUE | AT95: =D95=[1]营销售电!D95 -> TRUE | AU95: =E95=[1]营销售电!E95 -> TRUE | AV95: =F95=[1]营销售电!F95 -> TRUE | AW95: =G95=[1]营销售电!G95 -> TRUE | AX95: =H95=[1]营销售电!H95 -> TRUE | ... CA95: =AK95=[1]营销售电!AK95 -> TRUE
C96: 资金资产安全 | D96: 退费支付 | E96: 退费支付管控不到位，导致资金流向失控，引发资金合规风险。 | G96: 30.退费支付监控 | H96: 严格退费支付管理，确保资金准确支付到户。 | I96: 营销售电业务-30.退费支付监控-控制措施01 | J96: 财务部门建立支付全流程线上监控机制，并配置大额对私、疑似重复等进行复核，确保退费支付安全、准确。 | K96: √ | M96: √ | P96: √ | T96: 系统已建 | U96: 智慧财务 | V96: 系统退费支付审核规则设置记录 | W96: 各省（自治区、直辖市）电力公司-财务部门-资金管理人员 | X96: 每半年 | Y96: 抽查 | AA96: 年度 | AB96: 抽查 | AD96: 退费支付监控——建立支付全流程线上监控 | AE96: 每月 | AF96: 全量 | AH96: 是 | AI96: 是 | AJ96: 《国家电网有限公司司库管理办法》 | AK96: 国网财务部 | AL96: 无变化，直接引用 | AM96: 无变化，直接引用 | AN96: 会服、地市 | AO96: 财务 | AP96: 账务专业无意见。 | AQ96: =A96=[1]营销售电!A96 -> TRUE | AR96: =B96=[1]营销售电!B96 -> TRUE | AS96: =C96=[1]营销售电!C96 -> TRUE | AT96: =D96=[1]营销售电!D96 -> TRUE | AU96: =E96=[1]营销售电!E96 -> TRUE | AV96: =F96=[1]营销售电!F96 -> TRUE | AW96: =G96=[1]营销售电!G96 -> TRUE | AX96: =H96=[1]营销售电!H96 -> TRUE | ... CA96: =AK96=[1]营销售电!AK96 -> TRUE
A97: 营销售电业务 | B97: 八、营销稽查管理 | C97: 会计信息真实完整 | D97: 稽核计划制定 | E97: 营销稽查未有效实施，导致稽查结果失真。 | G97: 31.稽核计划制定 | H97: 健全营销稽查规则，并定期实施 | I97: 营销售电业务-31.稽核计划制定-控制措施01 | J97: 省公司营销部门结合国网稽核规则及增补规则健全营销稽查机制并定期更新。 | M97: √ | T97: 系统已建 | U97: 营销2.0系统 | V97: 系统稽查任务及稽查规则 | W97: 各级单位-营销部门-稽查监控人员 | X97: 每年 | Y97: 抽查 | AA97: 年度 | AB97: 抽查 | AH97: 是 | AI97: 是 | AJ97: 《国家电网有限公司营销稽查监控运营管理办法》 | AK97: 国网营销部 | AL97: 无变化，直接引用 | AM97: 无变化，直接引用 | AN97: 省公司 | AO97: 稽查 | AP97: 无意见 | AQ97: =A97=[1]营销售电!A97 -> TRUE | AR97: =B97=[1]营销售电!B97 -> TRUE | AS97: =C97=[1]营销售电!C97 -> TRUE | AT97: =D97=[1]营销售电!D97 -> TRUE | AU97: =E97=[1]营销售电!E97 -> TRUE | AV97: =F97=[1]营销售电!F97 -> TRUE | AW97: =G97=[1]营销售电!G97 -> TRUE | AX97: =H97=[1]营销售电!H97 -> TRUE | ... CA97: =AK97=[1]营销售电!AK97 -> TRUE
I98: 营销售电业务-31.稽核计划制定-控制措施02 | J98: 各级营销部门门结合稽核规则对业扩报装、计量采集、电费电价、收费及账务等建立日常稽查，形成营销价值闭环稽核管理。 | M98: √ | T98: 系统已建 | U98: 营销2.0系统 | V98: 1.系统稽查任务及稽查规则； 2.系统稽查工单 | W98: 各级单位-营销部门-稽查监控人员 | X98: 每年 | Y98: 抽查 | AA98: 年度 | AB98: 抽查 | AH98: 是 | AI98: 是 | AJ98: 《国家电网有限公司营销稽查监控运营管理办法》 | AK98: 国网营销部 | AL98: 无变化，直接引用 | AM98: 无变化，直接引用 | AN98: 供服、地市 | AO98: 稽查 | AP98: 无意见 | AQ98: =A98=[1]营销售电!A98 -> TRUE | AR98: =B98=[1]营销售电!B98 -> TRUE | AS98: =C98=[1]营销售电!C98 -> TRUE | AT98: =D98=[1]营销售电!D98 -> TRUE | AU98: =E98=[1]营销售电!E98 -> TRUE | AV98: =F98=[1]营销售电!F98 -> TRUE | AW98: =G98=[1]营销售电!G98 -> TRUE | AX98: =H98=[1]营销售电!H98 -> TRUE | ... CA98: =AK98=[1]营销售电!AK98 -> TRUE
C99: 会计信息真实完整 | D99: 稽核工单回单 | E99: 异常问题未有效整改，导致稽查流于形式。 | G99: 32.异常事项闭环销号 | H99: 异常问题处理应建立业稽联动审批机制，确保整改成效 | I99: 营销售电业务-32.异常事项闭环销号-控制措施01 | J99: 营销部门对稽查结果处理明确分类管理标准，并实施业稽联动审批机制，严格履行查办分离，落实整改责任。涉及客户信息变动及量价费调整的应联动业务工单同步调整。涉及客户信息变动及量价费调整的应督办专业发起业务工单进行问题整改 | K99: √ | M99: √ | T99: 系统已建 | U99: 营销2.0系统 | V99: 1.稽查工单处理标准相关规范； 2..系统工单审批流程及岗位权限配置； 3.系统稽查工单； 4.异常问题处理审核审批记录 | W99: 各级单位-营销部门-稽查管理人员 | X99: 每半年 | Y99: 抽查 | AA99: 年度 | AB99: 抽查 | AH99: 是 | AI99: 是 | AJ99: 《国家电网有限公司营销稽查监控运营管理办法》 | AK99: 国网营销部 | AL99: 修改控制措施 | AM99: 修改说明：将“涉及客户信息变动及量价费调整的应联动业务工单同步调整”调整为“涉及客户信息变动及量价费调整的应督办专业发起业务工单进行问题整改”。 | AN99: 供服、地市 | AO99: 稽查 | AP99: 无意见 | AQ99: =A99=[1]营销售电!A99 -> TRUE | AR99: =B99=[1]营销售电!B99 -> TRUE | AS99: =C99=[1]营销售电!C99 -> TRUE | AT99: =D99=[1]营销售电!D99 -> TRUE | AU99: =E99=[1]营销售电!E99 -> TRUE | AV99: =F99=[1]营销售电!F99 -> TRUE | AW99: =G99=[1]营销售电!G99 -> TRUE | AX99: =H99=[1]营销售电!H99 -> TRUE | ... CA99: =AK99=[1]营销售电!AK99 -> TRUE
I100: 营销售电业务-32.异常事项闭环销号-控制措施02 | J100: 营销部门稽查监控人员对稽查异常事项闭环处理情况开展检查，对涉及量价费的调整事项复核消缺。 | M100: √ | T100: 系统已建 | U100: 营销2.0系统 | V100: 1.系统稽查工单； 2.异常问题复核相关资料 | W100: 各级单位-营销部门-稽查监控人员 | X100: 每半年 | Y100: 抽查 | AA100: 年度 | AB100: 抽查 | AH100: 是 | AI100: 是 | AJ100: 《国家电网有限公司营销稽查监控运营管理办法》 | AK100: 国网营销部 | AL100: 无变化，直接引用 | AM100: 无变化，直接引用 | AN100: 供服、地市 | AO100: 稽查 | AP100: 无意见 | AQ100: =A100=[1]营销售电!A100 -> TRUE | AR100: =B100=[1]营销售电!B100 -> TRUE | AS100: =C100=[1]营销售电!C100 -> TRUE | AT100: =D100=[1]营销售电!D100 -> TRUE | AU100: =E100=[1]营销售电!E100 -> TRUE | AV100: =F100=[1]营销售电!F100 -> TRUE | AW100: =G100=[1]营销售电!G100 -> TRUE | AX100: =H100=[1]营销售电!H100 -> TRUE | ... CA100: =AK100=[1]营销售电!AK100 -> TRUE
...

Sheet 典设
A1: 风控矩阵-营销售电
A2: 业务条线 | B2: 业务领域 | C2: 控制目标 | D2: 业务流程步骤 | E2: 经营风险 | F2: 对应屡查屡犯问题清单 | G2: 关键控制节点 | H2: 控制要求与措施 | I2: 控制措施数量 | M2: 控制方式 | N2: 控制系统 | O2: 控制措施分类 | X2: 责任主体 | Y2: 业务自评价 | AC2: 集团监督评价 | AD2: 集团监督评价 | AG2: 数字化监督场景 | AK2: 现有制度及文件落实情况 | AN2: 总部审核部门
I3: 总数量 | J3: 系统-已有数量 | K3: 系统-待建数量 | L3: 线下数量 | O3: 不相容岗位 | P3: 分级授权 | Q3: 业务真实性校验 | R3: 预算管控 | S3: 合同控制 | T3: 收付控制 | U3: 会计监督 | V3: 财产保护 | W3: 分析与评价 | Y3: 评价频率 | Z3: 评价范围 | AA3: 查阅资料 （原始凭证文件） | AB3: 评价结论 | AC3: 评价程序 | AD3: 评价频率 | AE3: 评价范围 | AF3: 评价结论 | AG3: 数字化监督场景 | AH3: 评价频率 | AI3: 评价范围 | AJ3: 评价结论 | AK3: 是否已要求 | AL3: 是否满足要求 | AM3: 对应制度及文件名称
A4: 营销售电业务 | B4: 一、客户信息与合同签订管理 | C4: 会计信息真实完整、资金资产安全 | D4: 业扩报装受理 | E4: 客户信息录入不准确，与现场不一致，引发虚假立户及电费收取不规范风险。 | F4: 19.两部制电价执行不正确：存在应执行未执行两部制电价、分户报装规避两部制电价、变更用电少收基本电费、需量基本电费计收不准确等问题。 | G4: 1.系统客户信息创建 | H4: 控制要求：系统客户信息应与客户报装资料、现场用电情况一致。 控制措施： 1.营销部业务受理人员根据客户报装资料做好系统客户信息的创建，并对报装资料完整性、有效性负责；（线下） 2.营销部业务办理人员结合现场勘查情况对客户关键信息真实性、准确性复核，业务受理与业务办理执行不相容控制；（线下） 3.营销部对分户报装规避基本电费、违规改变用电性质等开展数字化在线监督与现场检查。（系统-已有） 内控载体： 1.系统业扩工单； 2.客户报装原始资料； 3.系统客户档案； 4.系统授权审批记录； 5.工商登记信息。 | I4: 3 | J4: 1 | L4: 2 | M4: 人工控制 系统自动控制 | N4: 营销2.0系统 | O4: √ | Q4: √ | W4: √ | X4: 各单位-营销部-综合柜员、客户经理 | Y4: 年度 | Z4: 抽查 | AA4: 包括不限于： 1、系统业扩工单 2、系统客户档案 3、客户工商登记信息 4、系统授权审批记录 | AC4: 1、检查客户信息登记的完整性，复核已登记客户的工商信息； 2、检查业务经办人与审核人符合不相容岗位分离的原则，避免同一人员同时进行业务办理与审核。 | AD4: 年度 | AE4: 抽查 | AG4: 分户报装规避基本电费监测 | AH4: 每季度 | AI4: 抽查 | AK4: 是 | AL4: 是 | AM4: 《国家电网有限公司业扩报装管理规则（征求意见稿）》第三章 业务受理 | AN4: 营销部
C5: 会计信息真实完整、资金资产安全 | D5: 方案答复与工程实施 | E5: 客户用电容量核定不准确、录入错误，导致基本电费执行不准确、电费少收。 | F5: 19.两部制电价执行不正确：存在应执行未执行两部制电价、分户报装规避两部制电价、变更用电少收基本电费、需量基本电费计收不准确等问题。 | G5: 2.客户用电容量的确定 | H5: 控制要求：系统容量与现场用电情况保持一致。 控制措施： 1.营销部现场勘查人员应准确核定客户用电容量与负荷性质，确保计量、计费方案、供电方式等准确；（线下） 2.对于加装变压器的高压客户，需取得变压器出厂合格证明及型式试验报告等容量信息佐证材料并上传系统，确保系统录入容量与现场用电情况一致；（系统-已有） 3.营销部对超容用电、基本电费异常、高可靠性供电费收取不规范开展数字化在线监督与现场检查。（系统-已有） 内控载体： 1.系统业扩工单（现场勘查验收单）； 2.客户报装原始资料（含用电负荷清单、变压器出厂合格证明及型式试验报告等）； 3.系统客户档案； 4.系统授权审批记录。 | I5: 3 | J5: 2 | L5: 1 | M5: 人工控制 系统自动控制 | N5: 营销2.0系统 | O5: √ | Q5: √ | W5: √ | X5: 各单位-营销部-综合柜员、客户经理 | Y5: 年度 | Z5: 抽查 | AA5: 包括不限于： 1、系统业扩工单 2、客户报装原始资料 3、系统客户档案 4、系统授权审批记录 | AC5: 检核复核客户报装单、作业单、设备领用记录、营销系统客户档案等业务资料，财务结算凭证等，确保业务真实，各项信息记录一致。 | AD5: 年度 | AE5: 抽查 | AG5: 客户容量与电量联动监测​​ | AH5: 每季度 | AI5: 抽查 | AK5: 是 | AL5: 是 | AM5: 《国家电网有限公司业扩报装管理规则（征求意见稿）》第四章 供电方案编制及答复 | AN5: 营销部
C6: 会计信息真实完整、资金资产安全 | D6: 客户信息变更 | E6: 客户信息变更不合规，导致电费计收不准确，引发合规风险。 | F6: 19.两部制电价执行不正确：存在应执行未执行两部制电价、分户报装规避两部制电价、变更用电少收基本电费、需量基本电费计收不准确等问题。 | G6: 3.系统客户信息变更 | H6: 控制要求：客户关键信息变更应结合业务工单联动调整，严禁无业务动因创建或修改客户信息行为。 控制措施： 1.营销部对客户户名、电价、用电容量等关键信息的变更，应结合变更业务联动调整并经审批后实施，业务受理与审批执行不相容控制；（系统-已有） 2.营销部对影响价费关键信息的变更业务开展现场查验，确保用电信息与现场一致。（线下） 内控载体： 1.系统变更工单； 2.客户变更原始资料； 3.系统客户档案； 4.系统授权审批记录。 | I6: 2 | J6: 1 | L6: 1 | M6: 人工控制 系统自动控制 | N6: 营销2.0系统 | O6: √ | Q6: √ | X6: 各单位-营销部-综合柜员、客户经理、电费电价 | Y6: 年度 | Z6: 抽查 | AA6: 包括不限于： 1、系统客户档案 2、系统业扩工单 3、系统授权审批记录 | AC6: 1、检查客户关键信息变更的必要性、合理性，保证信息变更依据充分，支撑资料完整。 2、检查信息变更经办人与审核人符合不相容岗位分离的原则，避免同一人员同时进行信息变更录入与审核。 | AD6: 年度 | AE6: 抽查 | AG6: — | AH6: — | AI6: — | AK6: 是 | AL6: 是 | AM6: 《变更用电业务规则（试行）》 | AN6: 营销部
C7: 会计信息真实完整、资金资产安全 | D7: 合同签订 | E7: 合同签订未使用公司统一且生效文本，导致电费计收合法权益无法得到保障。 | G7: 4.供用电合同签订 | H7: 控制要求：供用电合同签订应使用公司统一且生效的文本。 控制措施： 1.国网营销部统一管理合同文本，并明确执行要求、生效时间，及客户业务变更时不需重签合同的业务类型；（系统-已有） 2.营销部合同签订人员应严格使用统一且生效文本；（系统-已有）； 3.营销部合同审核人员对合同文本使用情况开展审核，合同经办与审核执行不相容控制；（线下） 4.营销部对统一文本之外的特殊约定事项，明确分级审批范围，履行审批流程。（线下） 内控载体： 1.供用电合同； 2.合同统一文本； 3.系统合同信息； 4.系统合同签订及审批记录。 | I7: 4 | J7: 2 | L7: 2 | M7: 人工控制 系统自动控制 | N7: 营销2.0系统 | O7: √ | P7: √ | S7: √ | X7: 总部-营销部-合同管理；各省公司-营销部-合同管理；各单位-营销部-合同管理 | Y7: 年度 | Z7: 抽查 | AA7: 包括不限于： 1、现行有效的合同统一文本 2、供用电合同 3、合同签订及审批记录 | AC7: 1、检查供用电合同归口管理情况，合同文本应使用公司统一模板； 2、供用电合同应及时签订并按规定权限履行复核、审批程序。 | AD7: 年度 | AE7: 抽查 | AG7: — | AH7: — | AI7: — | AK7: 是 | AL7: 否 | AM7: 《国家电网有限公司电费业务管理办法（征求意见稿）》第四章 合同协议 建议明确统一文本执行及特殊约定事项 | AN7: 营销部
C8: 会计信息真实完整、资金资产安全 | D8: 合同签订 | E8: 合同条款与客户报装信息、现场不一致，导致公司收支条款失效，合法权益无法得到保障。 | G8: 5.供用电合同审核 | H8: 控制要求：合同关键信息与客户报装信息保持一致。 控制措施： 1.营销部合同签订人员要确保合同客户信息与业扩报装产生的客户信息保持一致，不得变更；（系统-已有） 2.营销部合同审核人员对合同信息与业扩报装产生的信息一致性进行复核，合同经办与审核执行不相容控制；（线下） 3.营销部合同管理人员应落实合同签订一致性要求，加强系统上传合同与线下纸质合同一致性管控；（系统-已有） 4.营销部对系统合同上传及生效情况开展数字化在线监测（系统-待建）。 内控载体： 1.供用电合同（线下）； 2.系统合同信息； 3.系统客户信息。 | I8: 4 | J8: 2 | K8: 1 | L8: 1 | M8: 人工控制 系统自动控制 | N8: 营销2.0系统 | O8: √ | Q8: √ | S8: √ | W8: √ | X8: 各省公司-营销部-合同管理；各单位-营销部-合同管理 | Y8: 年度 | Z8: 抽查 | AA8: 包括不限于： 1、供用电合同 2、系统客户档案 | AC8: 检查复核合同客户信息与营销系统档案信息的一致性。 | AD8: 年度 | AE8: 抽查 | AG8: 系统生效合同在线监督 | AH8: 每季度 | AI8: 抽查 | AK8: 是 | AL8: 否 | AM8: 《国家电网有限公司电费业务管理办法（征求意见稿）》第四章 合同协议 建议明确合同签订及线上化要求 | AN8: 营销部
B9: 二、电价执行管理 | C9: 会计信息真实完整、资金资产安全 | D9: 电价码制定 | E9: 电价政策执行不到位，系统配置不准确，导致公司电费收入计量不准确、不合规。 | G9: 6.电价码制定与执行 | H9: 控制要求：电价标准与政策匹配，电价码准确配置与执行。 控制措施： 1.财务部根据国家或省内价格政策将电价政策解析形成每类客户执行标准；（线下） 2.营销部匹配形成标准电价码，电价码制定及下发执行审批与复核控制；（线下） 3.营销部建立电价码与分类客户对应关系，并在系统进行配置，确保电价码精准匹配到户；（系统-已有） 4.财务部、营销部对电价码配置与执行情况开展数字化在线监督（系统-待建）。 内控载体： 1.电价政策文件； 2.电价标准与电价码匹配记录； 3.电价码部署及下发记录。 | I9: 4 | J9: 1 | K9: 1 | L9: 2 | M9: 人工控制 系统自动控制 | N9: 智慧财务、营销2.0系统 | O9: √ | P9: √ | Q9: √ | W9: √ | X9: 各省公司-营销部-电费电价；各省公司-财务部-销售电价管理 | Y9: 年度 | Z9: 抽查 | AA9: 包括不限于： 1、电力价格政策文件 2、电价码标准与电价政策文件对应记录 3、电价码部署及下发情况 | AC9: 检查价格管理人员收集价格政策的及时性、准确性，及时完成电价标准的制定与维护工作。 | AD9: 年度 | AE9: 抽查 | AG9: 电价码配置与执行情况监督 | AH9: 每半年； 每季度 | AI9: 全量 | AK9: 是 | AL9: 是 | AM9: 《国网营销部国网财务部国网数字化部关于加快标准化电价码部署应用的通知》（营销营业〔2025〕83号） | AN9: 财务部、营销部
C10: 会计信息真实完整、资金资产安全 | D10: 电价执行 | E10: 电价执行与客户用电性质不匹配，造成公司或用户电费资金损失，收入不实 | F10: 19.两部制电价执行不正确：存在应执行未执行两部制电价、分户报装规避两部制电价、变更用电少收基本电费、需量基本电费计收不准确等问题。 | G10: 7.客户电价执行管控 | H10: 控制要求：客户电价执行与用电性质、行业类别等精准匹配。 控制措施： 1.营销部业务受理人员应严格按照客户用电性质、行业类别等匹配执行标准电价码并准确录入系统，经审核后生效，业务办理与审核执行不相容控制；（系统-已有） 2.营销部应加强客户电价变更管理，对于电价政策变动导致的电价变更应结合电价码联动调整，对于客户用电性质改变导致的电价变更应严格执行与工单关联，其他类型电价变更严格执行授权审批后进行调整；（系统-已有） 3.营销部对客户电价执行及变更情况开展数字化在线监督（系统-已有）。 内控载体： 1.系统业务工单记录； 2.系统客户电价信息。 | I10: 3 | J10: 3 | M10: 系统自动控制 | N10: 营销2.0系统 | O10: √ | Q10: √ | W10: √ | X10: 各省公司-营销部-电费电价；各省公司-财务部-销售电价管理；各单位-营销部-电费电价 | Y10: 半年度 | Z10: 抽查 | AA10: 包括不限于： 1、电价变更工单记录 2、电价码标准与电价政策文件对应记录 3、电价码变更审批记录 | AC10: 1、检查新制定的标准电价应及时准确的录入营销系统，审批人员应对客户用电性质、行业类别、合同主要条款与标准电价匹配复核，保证结算的准确性； 2、检查电价录入与审核符合不相容岗位分离的原则，避免同一人员同时进行标准电价录入与审核工作。 | AD10: 年度 | AE10: 抽查 | AG10: 客户电价执行及变更情况在线监测 | AH10: 每季度 | AI10: 全量 | AK10: 是 | AL10: 否 | AM10: 《国家电网有限公司电费业务管理办法（征求意见稿）》第三章 电价执行 | AN10: 营销部
B11: 三、电量采集管理 | C11: 会计信息真实完整 | D11: 电量采集 | E11: 未严格执行采集策略，导致电量计量失真。 | G11: 8.采集规则配置 | H11: 控制要求：电能表示数采集策略应纳入统一管理。 控制措施： 1.营销部要建立电能表示数采集策略统一管理机制，强化规则配置与实施管理；（系统-已有） 2.营销部对电能表示数采集策略执行情况开展复核与监督。（系统-已有） 内控载体： 1.系统电能表采集策略； 2.电能表采集规则个性化配置审批记录。 | I11: 2 | J11: 2 | M11: 系统自动控制 | N11: 用电信息采集系统、营销2.0系统 | O11: √ | P11: √ | Q11: √ | X11: 各省公司-营销部-计量管理 | Y11: 年度 | Z11: 抽查 | AA11: 包括不限于： 1、计量采集规则 2、计量采集规则变更审批记录 | AC11: 检查电量采集规则的统一性、合理性，各环节业务操作人员权限设置符合不相容岗位分离原则。 | AD11: 年度 | AE11: 抽查 | AG11: — | AH11: — | AI11: — | AK11: 是 | AL11: 是 | AM11: 《国家电网有限公司电费业务管理办法（征求意见稿）》第五章 采集抄表 | AN11: 营销部
C12: 会计信息真实完整 | D12: 电量采集 | E12: 电量采集范围不完整、抄表周期不准确，导致电费收入未可靠计量。 | G12: 9.电能表示数采集 | H12: 控制要求：电能表示数采集应规范完整、应抄尽抄。 控制措施： 1.电能表示数采集应由用电信息采集系统统一出口，采集范围应完整，营销部对全量用户抄表完整性开展在线监控；（系统-已有） 2.营销部严格抄表周期管理，以自然月为周期对全体用户进行抄表，抄表周期调整履行严格审批程序；（系统-已有） 3.营销部应结合当地市场规则及电费结算相关协议确定月内抄表频次。（线下） 内控载体： 1.系统抄表工单； 2.系统客户抄表记录。 | I12: 3 | J12: 2 | L12: 1 | M12: 人工控制 系统自动控制 | N12: 用电信息采集系统、营销2.0系统 | O12: √ | P12: √ | Q12: √ | W12: √ | X12: 各省公司-营销部-计量管理、电费电价；各单位-营销部-采集抄表、业务核算、客户经理 | Y12: 年度 | Z12: 抽查 | AA12: 包括不限于： 1、计量采集规则 2、计量采集规则变更审批记录 | AC12: 检查抄表周期的统一性，按照当地市场规则制定统一的抄表机制。 | AD12: 年度 | AE12: 抽查 | AG12: 电量全量采集在线监督 | AH12: 每月 | AI12: 全量 | AK12: 是 | AL12: 是 | AM12: 《国家电网有限公司电费业务管理办法（征求意见稿）》第五章 采集抄表 | AN12: 营销部
C13: 会计信息真实完整 | D13: 电量采集 | E13: 抄表结果异常，导致电费计算失真。 | F13: 20.营销系统权限管控不严：存在重要业务流程权限设置不合规；电费收费、账务处理、财务审核和违约用电查处、审批等不相容岗位未分离；信息系统权限未严格落实实名制，账号权限与实际权责不符、一人存在多个账号等问题。 | G13: 10.电量采集结果确认 | H13: 控制要求：电量采集结果应完整、准确。 控制措施： 1.营销部建立电量采集结果集中复核机制，健全复核规则，异常事项消缺纳入在线管控；（系统-已有） 2.营销部对异常事项消缺实行工单化管理，对不影响量费调整的异常事项消缺，执行本级确认后闭环；对影响量费调整的异常事项消缺，执行分级授权审批机制。（系统-已有） 内控载体： 1.系统电量采集结果复核规则； 2.系统异常事项处理及审批记录； 3.岗位权限配置。 | I13: 2 | J13: 2 | M13: 系统自动控制 | N13: 营销2.0系统 | O13: √ | P13: √ | Q13: √ | X13: 各省公司-营销部-电费电价；各单位-营销部-业务核算、采集抄表、客户经理 | Y13: 半年度 | Z13: 抽查 | AA13: 包括不限于： 1、计量采集结果复核规则 2、计量采集结果复核规则变更审批记录 | AC13: 检查省公司电量采集结果复核情况，建立重点对异常数据进行复核分析机制。 | AD13: 年度 | AE13: 抽查 | AG13: — | AH13: — | AI13: — | AK13: 是 | AL13: 是 | AM13: 《国家电网有限公司电费业务管理办法（征求意见稿）》第五章 采集抄表 | AN13: 营销部
B14: 四、电费核算与发行管理 | C14: 会计信息真实完整 | D14: 量费计算 | E14: 未严格执行电费计算规则，导致电费计算失真。 | G14: 11.电费计算结果复核 | H14: 控制要求：电费核算与复核规则应纳入统一管理。 控制措施： 1.国网营销部对电费核算与复核规则进行集中管理、二级配置与实施；（系统-已有） 2.省公司营销部应确保通用规则执行到位；（系统-已有） 3.省公司营销部对个性化补充规则严格履行审批程序后实施。（线下） 内控载体： 1.系统电费核算与复核规则； 2.系统个性化规则授权审批记录。 | I14: 3 | J14: 2 | L14: 1 | M14: 人工控制 系统自动控制 | N14: 营销2.0系统 | O14: √ | P14: √ | Q14: √ | X14: 总部-营销部-电费电价；各省公司-营销部-电费电价 | Y14: 半年度 | Z14: 抽查 | AA14: 包括不限于： 1、电费核算规则 2、电费核算规则分级下发记录 3、电费核算规则提报审批记录 | AC14: 检查电费核算执行情况，保证通用规则执行到位，对于差异化补充规则应报国网总部审批。 | AD14: 年度 | AE14: 抽查 | AG14: — | AH14: — | AI14: — | AK14: 是 | AL14: 是 | AM14: 《国家电网有限公司电费业务管理办法（征求意见稿）》第七章 核算出账 | AN14: 营销部
C15: 会计信息真实完整、资金资产安全 | D15: 电费发行 | E15: 违规减免电费，导致收入不实、资金损失。 | F15: 20.营销系统权限管控不严：存在重要业务流程权限设置不合规；电费收费、账务处理、财务审核和违约用电查处、审批等不相容岗位未分离；信息系统权限未严格落实实名制，账号权限与实际权责不符、一人存在多个账号等问题。 | G15: 12.电费发行确认 | H15: 控制要求：电费发行应真实、完整、准确。 控制措施： 1.营销部统一配置电费发行规则，强化电费发行与核算一体化管控，严禁手工篡改发行数据；（系统-已有） 2.营销部协同交易明确月末预估量价规则，预估到日，预估结果确认严格履行审批程序，防止人为调整；（系统-已有） 3.各单位业务核算人员在算费前，对当月审核规则拦截的涉费工单进行逐一检查，督导处理归档；（线下） 4.营销部对非政策性电费退补应严格履行分级审批程序；（系统-已有） 5.营销部对非政策性电费退补开展数字化在线监督。（系统-已有） 内控载体： 1.系统电费发行工单流转记录； 2.系统电费退补审批记录及支撑依据； 3.岗位权限配置。 | I15: 5 | J15: 4 | L15: 1 | M15: 人工控制 系统自动控制 | N15: 营销2.0系统 | O15: √ | P15: √ | Q15: √ | W15: √ | X15: 各省公司营销部-电费电价；各单位-营销部-业务核算 | Y15: 年度 | Z15: 抽查 | AA15: 包括不限于： 1、电费核算结果数据 2、电费发行数据 | AC15: 检查电费核算与发行的一体化建设情况，严禁人为更改相关数据。 | AD15: 年度 | AE15: 抽查 | AG15: 非政策性电费退补在线监督 | AH15: 每月 | AI15: 全量 | AK15: 是 | AL15: 是 | AM15: 《国家电网有限公司电费业务管理办法（征求意见稿）》第七章 核算出账 | AN15: 营销部
C16: 会计信息真实完整、资金资产安全 | D16: 业务费确认 | E16: 业务费收取不规范，造成电费资金损失。 | F16: 18.违约窃电查处不规范：存在未及时查处用户违约用电、窃电行为；违规减免、暂缓应补交的追补电费和违约使用电费等问题。 20.营销系统权限管控不严：存在重要业务流程权限设置不合规；电费收费、账务处理、财务审核和违约用电查处、审批等不相容岗位未分离；信息系统权限未严格落实实名制，账号权限与实际权责不符、一人存在多个账号等问题。 | G16: 13.业务费确认 | H16: 控制要求：业务费应足额、准确收取。 控制措施： 1.营销部应严格执行价格主管部门批准的收费项目和计算标准，统一配置业务费计费规则，严禁手工修改系统计算结果；（系统-已有） 2.营销部对业务费减免（暂缓、退费等）严格履行分级审批程序后实施，并确保足额收取；（系统-已有） 3.营销部对违规减免（暂缓）业务费开展数字化在线监督。（系统-已有） 内控载体： 1.业务费收费标准； 2.系统业务费调整（退费）审批记录及支撑依据； 3.岗位权限配置。 | I16: 3 | J16: 3 | M16: 系统自动控制 | N16: 营销2.0系统 | O16: √ | P16: √ | Q16: √ | W16: √ | X16: 各省公司营销部-电费电价；各单位-营销部-业务核算 | Y16: 年度 | Z16: 抽查 | AA16: 包括不限于： 1、计费结果异常事项清单 2、销号处理审批记录及工单流转记录 | AC16: 检查电计费结果异常事项处理情况，异常事项处理完成后，经销号人员与审批人共同确认，进行销号闭环处理。 | AD16: 年度 | AE16: 抽查 | AG16: 违规减免（暂缓）业务费监督 | AH16: 每月 | AI16: 全量 | AK16: 是 | AL16: 是 | AM16: 《供电营业规则》 | AN16: 营销部
C17: 会计信息真实完整、资金资产安全 | D17: 电费违约金减免 | E17: 违规减免电费违约金，掩盖其欠费事实，后期存在电费无法回收风险。 | F17: 17.违规减免电费违约金：存在电费未足额收回，通过全减另发等方式违规减免应收电费；违规减免或暂缓电费违约金等问题。 20.营销系统权限管控不严：存在重要业务流程权限设置不合规；电费收费、账务处理、财务审核和违约用电查处、审批等不相容岗位未分离；信息系统权限未严格落实实名制，账号权限与实际权责不符、一人存在多个账号等问题。 | G17: 14.电费违约金减免 | H17: 控制要求：电费违约金应足额、准确收取。 控制措施： 1.营销部明确电费违约金减免（暂缓）适用情形、支撑材料及分级授权标准；（线下） 2.营销部统一配置电费违约金减免（暂缓）工单及系统审批程序；（系统-已有） 3.营销部对电费违约金减免（暂缓）开展数字化在线监督。（系统-已有） 内控载体： 1.系统电费违约金减免（暂缓）工单流转记录； 2.电费违约金减免（暂缓）支撑依据； 3.岗位权限配置。 | I17: 3 | J17: 2 | L17: 1 | M17: 人工控制 系统自动控制 | N17: 营销2.0系统 | O17: √ | P17: √ | Q17: √ | W17: √ | X17: 各省公司营销部-电费电价；各单位-营销部-业务核算 | Y17: 年度 | Z17: 抽查 | AA17: 包括不限于： 1、电费核算结果数据 2、电费发行数据 | AC17: 检查电费核算与发行的一体化建设情况，严禁人为更改相关数据。 | AD17: 年度 | AE17: 抽查 | AG17: 违规减免（暂缓）电费违约金监督 | AH17: 每月 | AI17: 全量 | AK17: 是 | AL17: 是 | AM17: 《国家电网有限公司电费业务管理办法（征求意见稿）》第八章 电费收支 第五十条规范电费违约金管理 | AN17: 营销部
B18: 五、电费账务及发票管理 | C18: 会计信息真实完整 | D18: 电费账务处理 | E18: 电费账务不准确，导致收入不实风险。 | F18: 20.营销系统权限管控不严：存在重要业务流程权限设置不合规；电费收费、账务处理、财务审核和违约用电查处、审批等不相容岗位未分离；信息系统权限未严格落实实名制，账号权限与实际权责不符、一人存在多个账号等问题。 | G18: 15.电费账务管控 | H18: 控制要求：电费账务应纳入线上管控。 控制措施： 1.电费账务应自动集成电费发行及收费结果，防止人为干预；（系统-已有） 2.因核算差错确需调整账务时由营销部结合业务联动调整，并严格履行审批程序。（系统-已有） 内控载体： 1.系统电费凭证； 2.系统电费报表； 3.系统凭证制作人员标识； 4.岗位权限配置。 | I18: 2 | J18: 2 | M18: 系统自动控制 | N18: 营销2.0系统 | O18: √ | P18: √ | Q18: √ | X18: 各省公司-营销部-电费电价；各单位-营销部-电费管理 | Y18: 半年度 | Z18: 抽查 | AA18: 包括不限于： 1、电费账务的系统流程配置日志、凭证生成日志 2、凭证支撑数据 | AC18: 检查航务处理、电费核算与发行的一体化管控情况，严禁人为更改相关数据。 | AD18: 年度 | AE18: 抽查 | AG18: — | AH18: — | AI18: — | AK18: 是 | AL18: 否 | AM18: 《国家电网有限公司电费业务管理办法（征求意见稿）》第九章 电费账务 建议明确账务调整时账务调整要求，联动业务进行调整 | AN18: 营销部
C19: 会计信息真实完整 | D19: 电费账务处理 | E19: 会计政策执行不到位，系统配置不准确，导致财务会计信息反应不真实。 | G19: 16.营财账务协同管理 | H19: 控制要求：营财账务应建立协同管控机制。 控制措施： 1.财务部根据会计政策变化、制度调整及时变更会计科目及凭证生成规则，并及时下发执行；（线下） 2.营销部按照财务核算规则开展营销收入、销项税等的账务核算并按日传递凭证；（系统-已有） 3.财务部对营销部会计凭证与会计事务代码匹配性、营财账务一致性开展复核与数字化在线监督，营财差异应及时反馈营销并督导消缺；（系统-待建） 4.严禁手工调账财务账务（系统-已有）。 内控载体： 1.系统核算规则； 2.系统电费凭证； 3.营财对账记录。 | I19: 4 | J19: 2 | K19: 1 | L19: 1 | M19: 系统自动控制 | N19: 营销2.0系统、智慧财务 | O19: √ | Q19: √ | U19: √ | W19: √ | X19: 各省公司-营销部-电费电价；各省公司-财务部-总账管理；各单位-营销部-电费管理；各单位-财务部-销售电价管理 | Y19: 年度 | Z19: 抽查 | AA19: 包括不限于： 1、营财规则同步记录 2、凭证生成日志 3、营财对账记录 | AC19: 检查财务核算与营销账务对接、协调情况，财务部门应根据营销账务传递的账务信息生成财务凭证，财务部门每月开展一次营销账务稽核工作。 | AD19: 年度 | AE19: 抽查 | AG19: 营财一致性对账监督 | AH19: 每月 | AI19: 全量 | AK19: 是 | AL19: 是 | AM19: 《国家电网有限公司电费业务管理办法（征求意见稿）》第九章 电费账务 | AN19: 财务部、营销部
C20: 会计信息真实完整、资金资产安全、税务合规 | D20: 电费发票开具 | E20: 电费发票虚开未有效管控，引发税务合规风险。 | G20: 17.电费发票开具 | H20: 控制要求：电费发票应与电费账单、业务费确认结果一致，严禁篡改开票信息。 控制措施： 1.营销部对电费（业务费）开票实施线上统一管理，强控开票规则与开票权限，不得篡改开票信息，营销开票结果与财务共享（系统-已有）； 2.营销部对未结清开票、分割开票严格履行审批程序，开票执行与审核、开票执行与电费账务执行不相容控制；（系统-待建） 3.财务部加强电子税务系统使用权限管控，严控开票范围，防范虚开风险；（系统-已有） 4.财务部协同营销部对全量数电票开具情况纳入数字化在线监测（系统-待建）。 内控载体： 1.营销系统开票票面信息； 2.营销系统电费账单； 3.非营销系统电费开票票面信息； 4.未结清、分割开票申请及审批资料。 | I20: 4 | J20: 2 | K20: 2 | M20: 人工控制 系统自动控制 | N20: 营销2.0系统、智慧财务、电子税务系统 | O20: √ | Q20: √ | U20: √ | W20: √ | X20: 各省公司-营销部-电费电价；各省公司-财务部-稽查税务；各单位-营销部-综合柜员、电费管理、电费电价；各单位-财务部-税务管理 | Y20: 半年度 | Z20: 抽查 | AA20: 包括不限于： 1、营销系统开票规则 2、营销系统发行数据 3、营销系统开票票面信息 4、非营销系统电费开票票面信息 | AC20: 检查发票开具明细与财务收入确认情况，保证双方信息一致。 | AD20: 年度 | AE20: 抽查 | AG20: 数电票开票监测 | AH20: 每月 | AI20: 全量 | AK20: 是 | AL20: 否 | AM20: 《国家电网有限公司电费业务管理办法（征求意见稿）》第十章 电费票据管理 第六十三条建议明确线上开票要求，如“电费发票应通过营销业务系统、智慧财务或税务专用系统开具，并优先使用营销业务系统，防范虚开风险。” | AN20: 营销部、财务部
C21: 会计信息真实完整、资金资产安全、税务合规 | D21: 价外基金上交 | E21: 价外基金列转不及时、上交不准确，引发税务合规风险。 | G21: 18.价外基金上交 | H21: 控制要求：价外基金征收范围完整、上缴金额准确。 控制措施： 1.营销部强化价外基金与电费发行一体化管控，确保价外基金征收范围完整、金额准确；（系统-已有） 2.财务部完成营销报表、账务信息核对一致性后完成上交，严禁篡改信息；（系统-待建） 3.财务部对下级单位价外基金列转的及时性、准确性复核，确保按期足额上交财政部门，价外基金上交与审批执行不相容控制；（系统-待建） 4.财务部对价外基金上交情况开展数字化在线监测。（系统-待建） 内控载体： 1.系统凭证； 2.系统发行数据与营销报表； 3.系统上交数据。 | I21: 4 | J21: 1 | K21: 3 | M21: 系统自动控制 | N21: 营销2.0系统、智慧财务 | O21: √ | Q21: √ | T21: √ | U21: √ | W21: √ | X21: 各省公司-营销部-电费电价；各省公司-财务部-销售电价管理；各单位-营销部-电费电价；各单位-财务部-销售电价管理 | Y21: 半年度 | Z21: 抽查 | AA21: 包括不限于： 1、应收电费汇总表 2、价外基金城建税金及附加计提表 3、价外基金列转单 4、价外基金上缴支付记录 | AC21: 检查价外基金开展情况，严格按照政策要求进行管理，及时上报营销报表，保证价外基金列转及时、准确，并按期足额上缴。 | AD21: 年度 | AE21: 抽查 | AG21: 价外基金上交监测 | AH21: 每月 | AI21: 全量 | AK21: 是 | AL21: 是 | AM21: 《国家电网有限公司电费业务管理办法（征求意见稿）》第二章 电价执行 | AN21: 营销部、财务部
B22: 六、电费实收管理 | C22: 资金资产安全 | D22: 收费渠道管理 | E22: 代收渠道未统一管理，代收渠道协议不规范，引发资金挪用、财务账务不合规风险。 | G22: 19.代收渠道运行管理 | H22: 控制要求：代收渠道应纳入省公司统一管理。 控制措施： 1.营销部协同财务部严格代收渠道新增、变更审批程序，加强地方代收渠道监控，加速清理超标、低效、扩范围违规代收渠道；（线下） 2.营销部加强代收渠道协议的统一管理，明确对账与结算责任条款；（线下） 3.财务部将各类代收渠道关联的银行账户、商户号纳入智慧财务线上监控，每月对各电费账户、商户号进行资金对账复核，确保资金安全（系统-待建）。 内控载体： 1.新增（变更）代收渠道审批记录； 2.代收渠道合作协议（线下）； 3.代收渠道纳入监控材料； 4.对账记录。 | I22: 3 | K22: 1 | L22: 2 | M22: 人工控制 系统自动控制 | N22: 营销2.0系统、智慧财务 | O22: √ | P22: √ | T22: √ | U22: √ | W22: √ | X22: 各省公司-营销部-电费电价；各省公司-财务部-资金管理 | Y22: 年度 | Z22: 抽查 | AA22: 包括不限于： 1、新增代收渠道审批文件或其他资料 2、代收渠道合作协议 3、代收渠道与电费银行账户关联关系 | AC22: 检查银行代收渠道管控情况，严格执行新增审批，建立银行代收统一管理机制，确保资金安全。 | AD22: 年度 | AE22: 抽查 | AG22: 代收渠道监管 | AH22: 每月 | AI22: 全量 | AK22: 是 | AL22: 是 | AM22: 《国网财务部关于规范和加强商户号管理的通知》（财金〔2025〕2号）、《国家电网有限公司司库管理办法》 | AN22: 营销部、财务部
C23: 资金资产安全 | D23: 收费渠道管理 | E23: 资金到账情况未及时监管，导致资金滞留风险。 | G23: 20.代收渠道在途资金管理 | H23: 控制要求：强化代收渠道对账及结算管控，督导在途资金处理。 控制措施： 1.营销部建立每日对账机制，并以核对一致的对账数据为标准进行电费资金清算；（系统-已有） 2.对于银行代收、商户号收取的尚未清分或清缴至电费账户的资金按在途资金管理与核算；（系统-已有） 3.营销部加强超限未到账的在途资金跟踪处理，开展数字化在线监测并设置资金到账及时性预警（系统-待建）。 内控载体： 1.代收渠道合作协议； 2.在途资金对账记录。 | I23: 3 | J23: 2 | K23: 1 | M23: 系统自动控制 | N23: 营销2.0系统、智慧财务 | O23: √ | T23: √ | U23: √ | W23: √ | X23: 各省公司-营销部-电费电价；各省公司-财务部-资金管理；各单位-营销部-电费管理；各单位-财务部-资金管理、销售电价管理 | Y23: 每季度 | Z23: 抽查 | AA23: 包括不限于： 1、代收渠道合作协议 2、系统流程配置日志 3、代收渠道资金清分流程配置日志 4、代收渠道资金清分记录 | AC23: 检查各渠道电费到账情况，建立预警机制，保证代收资金及时到账，对于超限未到账的资金重点进行跟踪监控，确保资金安全。 | AD23: 年度 | AE23: 抽查 | AG23: 代收渠道在途资金监控 | AH23: 每月 | AI23: 全量 | AK23: 是 | AL23: 是 | AM23: 《国网财务部关于规范和加强商户号管理的通知》（财金〔2025〕2号）、《国家电网有限公司司库管理办法》 | AN23: 营销部、财务部
C24: 资金资产安全 | D24: 收费渠道管理 | E24: 柜收资金安全性管控不到位，导致现金截留、账实不符、现金流失​​等风险。 | G24: 21.柜台收费在途资金管理 | H24: 控制要求：柜台收费应与客户准确关联，并及时缴存银行。 控制措施： 1.营销部柜收人员收取现金要与客户及收费资金类别精准匹配，收费后主动向客户提供收费票据（含电子票据），现金及时缴存银行；（线下） 2.营销部按会计档案管理要求编制现金盘点表，并进行在线布置；（系统-已有） 3.营销部要采取措施促使缴存信息与客户信息对应、与银行流水关联，确保柜收资金完整、准确到账（系统-待建）。 内控载体： 1.系统收费解款记录； 2.现金盘点表。 | I24: 3 | J24: 1 | K24: 1 | L24: 1 | M24: 人工控制 系统自动控制 | N24: 营销2.0系统 | O24: √ | Q24: √ | T24: √ | U24: √ | X24: 各单位-营销部-综合柜员、电费电价 | Y24: 每月 | Z24: 抽查 | AA24: 包括不限于： 1、现金收费凭据 2、营销系统现金销账明细 3、营销系统现金解款记录 | AC24: 1、检查现金业务管控情况，每日进行现金盘点对账，并及时将相关资料传递至财务部门进行账务处理； 2、检查库存现金缴存情况，保证柜台现金及时存入银行，避免资金坐支，保证资金安全。 | AD24: 年度 | AE24: 抽查 | AG24: — | AH24: — | AI24: — | AK24: 是 | AL24: 是 | AM24: 《国家电网有限公司电费业务管理办法（征求意见稿）》第八章 电费收支 《国家电网有限公司司库管理办法》 | AN24: 营销部
C25: 会计信息真实完整、资金资产安全 | D25: 实收销账 | E25: 电费销账不准确，引发资金流失及应收账款不实风险。 | G25: 22.电费销账标准制定 | H25: 控制要求：电费销账应明确标准，与资金流水匹配，与客户准确关联。 控制措施： 1.营销部以资金流水、代收渠道对账文件、柜收现金等为依据收费到户，严禁在无可信缴费记录前提下完成电费收取；（系统-已有） 2.营销部电费账务人员对收费记录与凭证开展一致性核对，电费收费与审核、电费账务执行不相容控制。（系统-待建） 内控载体： 1.系统电费一次销根凭证； 2.系统资金流水。 | I25: 2 | J25: 1 | K25: 1 | M25: 系统自动控制 | N25: 营销2.0系统 | O25: √ | Q25: √ | T25: √ | U25: √ | X25: 各省公司-营销部-电费电价；各单位-营销部-综合柜员、电费管理、电费电价；各单位-财务部-销售电价管理 | Y25: 每年 | Z25: 抽查 | AA25: 包括不限于： 1、系统流程配置日志 2、电费销账记录、财务复核记录 | AC25: 检查电费应收、预付的账务处理情况，杜绝未收款先销账的情况，保证销账业务真实准确。 | AD25: 年度 | AE25: 抽查 | AG25: — | AH25: — | AI25: — | AK25: 是 | AL25: 否 | AM25: 《国家电网有限公司电费业务管理办法（征求意见稿）》第八章 电费收支 第四十八条 建议进一步明确销账标准。 | AN25: 营销部
C26: 会计信息真实完整 | D26: 预收互转 | E26: 电费预收结转不准确，导致账实不符风险。 | F26: 20.营销系统权限管控不严：存在重要业务流程权限设置不合规；电费收费、账务处理、财务审核和违约用电查处、审批等不相容岗位未分离；信息系统权限未严格落实实名制，账号权限与实际权责不符、一人存在多个账号等问题。 | G26: 23.预收互转规则控制 | H26: 控制要求：预收电费应准确结转，关联到户。 控制措施： 1.营销部应明确预收互转规则并进行系统控制，确保预收结转精准到户；（系统-已有） 2.营销部对集团（关联）户设立与变更应履行严格审批程序；（系统-已有） 3.营销部对集团（关联）户设立规范性、预收结转准确性开展数字化在线监测。（系统-待建） 内控载体： 1.系统集团（关联）户申请资料； 2.系统预收电费互转规则； 3.系统预收电费互转明细； 4.岗位权限配置。 | I26: 3 | J26: 2 | K26: 1 | M26: 系统自动控制 | N26: 营销2.0系统 | O26: √ | P26: √ | Q26: √ | T26: √ | W26: √ | X26: 各省公司-营销部-电费电价；各单位-营销部-业务审核 | Y26: 半年度 | Z26: 抽查 | AA26: 包括不限于： 1、预收电费结转的系统规则配置日志 2、预收电费结转记录 | AC26: 检查财务预收款销账管理情况，确保账务处理规范，支撑资料完整，业务真实准确。 | AD26: 年度 | AE26: 抽查 | AG26: 预收互转监督 | AH26: 每月 | AI26: 全量 | AK26: 是 | AL26: 是 | AM26: 《国家电网有限公司电费业务管理办法（征求意见稿）》第九章 电费账务 第六十条 | AN26: 营销部
C27: 会计信息真实完整、资金资产安全 | D27: 电费坏账管理 | E27: 应收电费账龄不准确，引发合规及资金风险。 | G27: 24.电费账龄与客户信用管理 | H27: 控制要求：电费账龄准确，与客户准确关联。 控制措施： 1.营销部做好应收电费账龄管理，确保每一笔电费账龄准确，电费收取与账务执行不相容控制；（系统-已有） 2.营销部建立客户信用管理，清晰掌握重点客户经营状况，为财务部年末计提应收电费坏账准备提供业务基础；（系统-待建） 3.财务部结合营销提供的客户信用情况，执行准确的坏账计提策略。（线下） 内控载体： 1.应收电费账龄台账； 2.客户信用管理资料。 | I27: 3 | J27: 1 | K27: 1 | L27: 1 | M27: 人工控制 系统自动控制 | N27: 营销2.0系统 | O27: √ | Q27: √ | U27: √ | X27: 各单位-营销部-客户经理、电费电价；各单位-财务部-销售电价管理 | Y27: 年度 | Z27: 抽查 | AA27: 包括不限于： 1、应收电费欠费明细台账 2、客户信用等级评价 | AC27: 检查财务往来款明细、应收电费欠费台账，确保双方信息记载一致，复核客户信用等级评价情况，杜绝超信用额度赊销情况。 | AD27: 年度 | AE27: 抽查 | AG27: — | AH27: — | AI27: — | AK27: 是 | AL27: 是 | AM27: 《国家电网有限公司电费业务管理办法（征求意见稿）》第十一章 风险管控《国家电网有限公司电费回收管理办法》 | AN27: 营销部、财务部
C28: 会计信息真实完整 | D28: 电费坏账管理 | E28: 应收电费坏账未及时计提，计提不准确，导致利润失真风险。 | G28: 25.电费坏账计提与核销 | H28: 控制要求：坏账计提足额准确。 控制措施： 1.财务部根据营销提供的电费账龄，按照统一的坏账计提政策，经审批后完成坏账计提（转回），坏账计提与审批严格执行不相容控制；（系统-已有） 2.对满足条件的电费坏账，营销部应履行决策程序后核销，同步做好账销案存管理，财务部进行核查。（线下） 内控载体： 1.应收电费账龄台账； 2.客户信用等级评价及其他资料； 3.系统电费坏账计提规则及记录； 4.坏账核销资料。 | I28: 2 | J28: 1 | L28: 1 | M28: 人工控制 系统自动控制 | N28: 营销2.0系统、智慧财务 | O28: √ | Q28: √ | U28: √ | W28: √ | X28: 各省公司-营销部-电费电价；各省公司-财务部-总账管理；各单位-营销部-电费电价；各单位-财务部-销售电价管理 | Y28: 年度 | Z28: 抽查 | AA28: 包括不限于： 1、应收电费台账（含账龄分析表） 2、应收电费坏账计提规则 3、营销系统应收电费坏账计提记录 | AC28: 检查财务应收电费还账计提与核销资料，确保核销依据充分、合理。 | AD28: 年度 | AE28: 抽查 | AG28: 电费坏账计提监督 | AH28: 每年 | AI28: 全量 | AK28: 是 | AL28: 是 | AM28: 《国家电网有限公司电费回收管理办法》《国家电网有限公司会计核算办法》 | AN28: 财务部、营销部
C29: 会计信息真实完整、资金资产安全 | D29: 资金勾对 | E29: 实收账务与资金流水不匹配，导致账实不符风险。 | G29: 26.资金勾对复核 | H29: 控制要求：电费实收账务与资金流水准确关联。 控制措施： 1.营销部按日完成资金日流水与账务核对，同时将收款明细凭证与银行资金流水勾对记录按日传递至财务，电费收费、账务处理与审核执行不相容分离；（系统-已有） 2.财务部按日对营销的对账结果进行复核，开展线上营财银对账；（系统-已有） 3.财务部按月开展银行对账单与营财核对一致的收款账务明细勾对校核，编制银行存款余额调节表，从严管控未达账项。（系统-已有） 内控载体： 1.系统资金勾对记录； 2.系统电费实收凭证； 3.营财银线上对账记录； 4.银行余额调节表。 | I29: 3 | J29: 3 | M29: 系统自动控制 | N29: 营销2.0系统、智慧财务 | O29: √ | Q29: √ | T29: √ | U29: √ | W29: √ | X29: 各单位-营销部-电费管理；各单位-财务部-资金管理、销售电价管理 | Y29: 每季度 | Z29: 抽查 | AA29: 包括不限于： 1、资金勾对记录与收款明细对应记录 2、营销对账结果复核记录 | AC29: 检查财务资金收款稽核记录，财务部门应每日核对营销收款台账与银行流水记录进行复核，确保资金安全。 | AD29: 年度 | AE29: 抽查 | AG29: 银企对账监督 | AH29: 每月 | AI29: 全量 | AK29: 是 | AL29: 是 | AM29: 《国家电网有限公司电费业务管理办法（征求意见稿）》第二章 职责分工 第九章电费账务 建议增加不明款相关要求 | AN29: 营销部、财务部
C30: 会计信息真实完整、资金资产安全 | D30: 不明款管理 | E30: 不明款确认及销账不准确，导致资金性质混乱、账实不符风险。 | G30: 27.不明款确认与核销 | H30: 控制要求：强化不明款管控，不明款销账时应确保与客户精准匹配。 控制措施： 1.营销部对长期未关联到户的银行流水应及时确认不明款并加强清理；（系统-待建） 2.营销部对三年及以上或有确凿证据表明无法支付的不明款项，应及时履行决策程序，结转营业外收入；（线下） 3.财务部对跨月的不明款项进行督导消缺，并对不明款转营业外规范性开展核查。（线下） 内控载体： 1.不明款确认（销账）明细表； 2.不明款转营业外资料（线下）； 3.系统不明款记录。 | I30: 3 | K30: 1 | L30: 2 | M30: 人工控制 系统自动控制 | N30: 营销2.0系统、智慧财务 | O30: √ | P30: √ | Q30: √ | T30: √ | U30: √ | W30: √ | X30: 各单位-营销部-电费管理；各单位-财务部-销售电价管理 | Y30: 半年度 | Z30: 抽查 | AA30: 包括不限于： 1、不明款确认（销账）明细表 2、不明款项核销上会文件等 3、非原路退回款项证明材料和审批记录 | AC30: 检查不明款项明细表，企业应建立相关督导机制，发现不明款项应及时处理，对于长期挂账的不明款项应履行决策程序后进行销账处理。 | AD30: 年度 | AE30: 抽查 | AG30: 不明款对账监督 | AH30: 每月 | AI30: 全量 | AK30: 是 | AL30: 否 | AM30: 《国网营销部财务部关于明确营销2.0系统与智慧共享财务平台系统集成有关问题的意见》（营销营业〔2023〕86号） | AN30: 营销部、财务部
B31: 七、营销退费管理 | C31: 会计信息真实完整、资金资产安全 | D31: 退费申请 | E31: 退费资料不真实、系统录入错误，导致虚假退费、重复退费或资金冒领风险。 | F31: 20.营销系统权限管控不严：存在重要业务流程权限设置不合规；电费收费、账务处理、财务审核和违约用电查处、审批等不相容岗位未分离；信息系统权限未严格落实实名制，账号权限与实际权责不符、一人存在多个账号等问题。 | G31: 28.退费申请与退费资料一致性管控 | H31: 控制要求：退费申请与退费资料一致，系统录入准确。 控制措施： 1.营销部业务受理人员对退费资料完整性、客户关键信息与资料一致性进行核对，加强系统上传影像与线下资料一致性管控，并准确录入系统；（线下） 2.营销部电费管理人员对系统退费信息与退费资料一致性进行复核，退费受理、退费审核严格执行不相容分离；（线下） 3.营销部对电费（含业务费）退费原则上应原路退回；（系统-待建） 4.对销户后无法联系客户或客户拒不办理等原因导致的确实无法支付的款项，营销部及时履行决策程序后，结转营业外收入，并做好账销案存管理；（线下） 5.财务部对客户收款信息、退费主体资格开展系统录入信息与退费影像一致性复查，对结转营业外收入规范性开展核查。（线下） 内控载体： 1.系统客户退费资料影像； 2.系统退费信息及审核记录； 3.销户有预收转营业外资料（线下）； 4.岗位权限配置。 | I31: 5 | K31: 1 | L31: 4 | M31: 人工控制 系统自动控制 | N31: 营销2.0系统、智慧财务 | O31: √ | P31: √ | Q31: √ | T31: √ | X31: 各单位-营销部-业务受理、电费管理；各单位-财务部-销售电价管理 | Y31: 半年度 | Z31: 抽查 | AA31: 包括不限于： 1、退费审批单 2、客户用电主体资格证明（营业执照或身份证等）、授权委托书等 3、营销系统退费申请审核审批记录 | AC31: 检查电费退费业务，核实退费资料的合理性、完整性、真实性，经有效复核后，提交退费审核申请。 | AD31: 年度 | AE31: 抽查 | AG31: — | AH31: — | AI31: — | AK31: 是 | AL31: 否 | AM31: 《国家电网有限公司电费业务管理办法（征求意见稿）》第八章 电费收支 第五十一条 | AN31: 营销部、财务部
C32: 资金资产安全 | D32: 退费审批 | E32: 退费未经有效审核审批，导致公司资金流失、财务数据失真风险。 | F32: 20.营销系统权限管控不严：存在重要业务流程权限设置不合规；电费收费、账务处理、财务审核和违约用电查处、审批等不相容岗位未分离；信息系统权限未严格落实实名制，账号权限与实际权责不符、一人存在多个账号等问题。 | G32: 29.退费审批权限及流程设置 | H32: 控制要求：退费审批流程设置应科学、合理，与资金分级授权匹配。 控制措施： 1.财务部建立电费退费资金分级授权审批机制，确保系统流程轨迹可视、授权管理科学；（系统-已有） 2.营销部按照资金分级授权建立内部退费审批流程，对权限配置与岗位权限一致性进行校核。（系统-待建） 内控载体： 1.系统退费审批单； 2.资金分级授权； 3.岗位权限配置。 | I32: 2 | J32: 1 | K32: 1 | M32: 系统自动控制 | N32: 营销2.0系统、智慧财务 | O32: √ | P32: √ | T32: √ | X32: 各省公司-营销部、财务部；各单位-营销部、财务部 | Y32: 年度 | Z32: 抽查 | AA32: 包括不限于： 1、退费分级授权审批规范的制定及下发记录 2、系统权限配置日志、系统流程配置日志 3、退费审批单 | AC32: 检查退费分级审核机制，企业应按照规定权限进行退费审批，保证流程清晰完整。 | AD32: 年度 | AE32: 抽查 | AG32: — | AH32: — | AI32: — | AK32: 是 | AL32: 否 | AM32: 《国家电网有限公司电费业务管理办法（征求意见稿）》第八章 电费收支 第五十一条 建议明确分级审批要求“退费申请、审核审批履行不相容控制，确保流程权限设置科学、合规”。 | AN32: 营销部、财务部
C33: 资金资产安全 | D33: 退费支付 | E33: 退费支付管控不到位，导致资金流向失控，引发资金合规风险。 | G33: 30.退费支付监控 | H33: 控制要求：严格退费支付管理，确保资金准确支付到户。 控制措施： 财务部建立支付全流程线上监控机制，并配置大额对私、疑似重复等进行复核，确保退费支付安全、准确。（系统-已有） 内控载体： 1.系统退费支付记录； 2.系统客户退费申请影像； 3.系统退费支付审核规则设置记录； 4.资金分级授权； 5.岗位权限配置。 | I33: 1 | J33: 1 | M33: 系统自动控制 | N33: 智慧财务 | O33: √ | P33: √ | Q33: √ | T33: √ | U33: √ | W33: √ | X33: 各省公司-财务部-资金管理；各单位-财务部-销售电价管理 | Y33: 半年度 | Z33: 抽查 | AA33: 包括不限于： 1、退费支付记录 2、退费支付审批系统设置情况 | AC33: 检查退费资金支付情况，退费应遵循原路退回的原则进行资金支付，如与缴费账户不一致时，应按规定权限履行审批程序。 | AD33: 年度 | AE33: 抽查 | AG33: 退费支付全流程线上监控 | AH33: 每日 | AI33: 全量 | AK33: 是 | AL33: 是 | AM33: 《国家电网有限公司电费业务管理办法（征求意见稿）》第八章 电费收支 第五十一条 建议明确退费支付要求；《国家电网有限公司司库管理办法》 | AN33: 财务部
B34: 八、营销稽查管理 | C34: 会计信息真实完整 | D34: 稽核计划制定 | E34: 营销稽查未有效实施，导致稽查结果失真。 | G34: 31.稽核计划制定 | H34: 控制要求：健全营销稽查规则，并定期实施。 控制措施： 1.省公司营销部结合国网稽核规则及增补规则健全营销稽查机制，增补规则严格履行审批程序后实施；（系统-已有） 2.各级营销部门结合稽核规则对业扩报装、计量采集、电费电价、收费及账务等建立日常稽查，形成营销价值闭环稽核管理。（系统-已有） 内控载体： 1.系统稽查任务及稽查规则； 2.系统稽查工单。 | I34: 2 | J34: 2 | M34: 系统自动控制 | N34: 营销2.0系统 | O34: √ | P34: √ | Q34: √ | X34: 各省公司-营销部-稽查管理；各单位-营销部-稽查监控作业 | Y34: 年度 | Z34: 抽查 | AA34: 包括不限于： 营销稽查工单 | AC34: 1、检查营销制度稽核情况，企业应定期对营销制度进行评估、更新，确保制度内容符合实际业务开展需要，且能覆盖业务全流程管控。 2、检查客户信息记录，通过核对各环节线上、线下单据保证客户信息真实准确； 3.检查电量检测与分析情况，查找重大异常数据，避免违约用电或窃电情况出现； 4、检查电价码执行与变更稽核情况，确保检查频率、范围、内容符合制度要求。 | AD34: 年度 | AE34: 抽查 | AG34: — | AH34: — | AI34: — | AK34: 是 | AL34: 是 | AM34: 《国家电网有限公司营销稽查监控运营管理办法》 | AN34: 营销部
C35: 会计信息真实完整 | D35: 稽核工单回单 | E35: 异常问题未有效整改，导致稽查流于形式。 | F35: 20.营销系统权限管控不严：存在重要业务流程权限设置不合规；电费收费、账务处理、财务审核和违约用电查处、审批等不相容岗位未分离；信息系统权限未严格落实实名制，账号权限与实际权责不符、一人存在多个账号等问题。 | G35: 32.异常事项闭环销号 | H35: 控制要求：异常问题处理应建立业稽联动审批机制，确保整改成效。 控制措施： 1.省公司营销部对稽查结果处理明确分类管理标准，落实整改责任，涉及客户信息变动及量价费调整的应联动业务工单同步调整，并实施业稽联动审批机制；（系统-已有） 2.营销部稽查监控人员对稽查异常事项闭环处理情况开展检查，对涉及量价费的调整事项逐一复核消缺，稽查监控、现场稽查、业务管理执行不相容分离；（线下） 3.营销稽查结果与财务共享。（系统-待建） 内控载体： 1.系统稽查工单； 2.异常问题处理审核审批记录； 3.异常问题处理资料； 4.岗位权限配置； 5.稽查结果共享情况。 | I35: 3 | J35: 1 | K35: 1 | L35: 1 | M35: 人工控制 系统自动控制 | N35: 营销2.0系统 | O35: √ | P35: √ | Q35: √ | U35: √ | W35: √ | X35: 各省公司-营销部-稽查管理；各单位-营销部-营销稽查人员、营销稽查、专业管理 | Y35: 年度 | Z35: 抽查 | AA35: 包括不限于： 营销稽查异常问题处理审核审批记录 | AC35: 检查稽核异常处理记录，企业应对异常情况提出整改意见，并履行分级审批程序后，进行处理。 | AD35: 年度 | AE35: 抽查 | AG35: 营销稽查在线监测与分析 | AH35: 每月 | AI35: 全量 | AK35: 是 | AL35: 是 | AM35: 《国家电网有限公司营销稽查监控运营管理办法》 | AN35: 营销部
B36: 九、计量资产管理 | C36: 会计信息真实完整、资金资产安全 | D36: 计量装置出库 | E36: 计量装置出库出账标准不明确，造成计量装置在库期间核算失真。 | G36: 33.出库出账标准 | H36: 控制要求：明确计量装置出库出账标准。 控制措施： 1.营销部按照一物一码管理计量资产，联动获取计量装置采购价格，匹配计量装置价值信息；（系统-待建） 2.财务部协同营销部统一计量装置出库出账规则，明确计量装置领用、安装关联到户时，出库并记入成本（资产），确保计量装置账实相符；（系统-待建） 3.营销部对计量装置领用与安装随工单流转情况开展在线监测；（系统-待建） 4.财务部对计量装置出库出账标准执行情况开展检查。（线下） 内控载体：包括不限于： 1.计量装置采购计划； 2.计量装置资产系统台账； 3.ERP计量装置采购清单； 4.计量装置成本（资产）入账凭证； 5.计量装置出库记录。 | I36: 4 | J36: 1 | K36: 2 | L36: 1 | M36: 人工控制 系统自动控制 | N36: 营销2.0系统、ERP系统、智慧财务 | O36: √ | Q36: √ | U36: √ | W36: √ | X36: 各省公司-营销部-计量管理；各省公司-财务部-总账管理；各单位-营销部-计量管理；各单位-财务部-会计核算管理 | Y36: 年度 | Z36: 抽查 | AA36: 包括不限于： 1、供用电合同 12、系统客户档案 | AC36: 检查复核合同客户信息与营销系统档案信息的一致性。 | AD36: 年度 | AE36: 抽查 | AG36: 计量装置在线管理 | AH36: 每月 | AI36: 全量 | AK36: 是 | AL36: 否 | AM36: 《国家电网有限公司计量工作管理规定》 建议进一步明确计量装置管理要求 | AN36: 营销部、财务部
C37: 会计信息真实完整、资金资产安全 | D37: 计量装置领用安装 | E37: 计量装置领用出库与安装未准确关联，造成计量装置成本费用与效益不匹配、电费收入核算失真。 | G37: 34.计量表计安装 | H37: 控制要求：计量表计领用与工单关联。 控制措施： 1.营销部对计量表计流转建立工单化管理，确保计量表计领用与安装准确关联、匹配到户；（系统-待建） 2.营销部装表接电人员在表计安装前对表计信息与系统一致性、客户关联性进行检查，并确保初始表码清零。（线下） 内控载体： 1.领用出库记录； 2.系统工单及表计信息。 | I37: 2 | K37: 1 | L37: 1 | M37: 人工控制 系统自动控制 | N37: 营销2.0系统、用电信息采集系统 | O37: √ | Q37: √ | X37: 各单位-营销部-计量管理 | Y37: 年度 | Z37: 抽查 | AA37: 包括不限于： 1、供用电合同 9、系统客户档案 | AC37: 检查复核合同客户信息与营销系统档案信息的一致性。 | AD37: 年度 | AE37: 抽查 | AG37: — | AH37: — | AI37: — | AK37: 是 | AL37: 否 | AM37: 《国家电网有限公司计量工作管理规定》 建议明确计量装置流转工单化管理要求 | AN37: 营销部

Sheet 按照业务条线
A1: 省公司牵头部门 | B1: 业务条线 | C1: 省公司牵头部门
A2: 营销部 | B2: 营销售电业务
A3: 财务部 | B3: 营销售电业务
A4: 法律部 | B4: 交易与购电业务
A5: 发展部 | B5: 交易与购电业务
A6: 国调中心 | B6: 交易与购电业务
A7: 营销部 | B7: 交易与购电业务
A8: 财务部 | B8: 交易与购电业务
A9: 交易中心 | B9: 交易与购电业务
A10: 跨区中心 | B10: 交易与购电业务 | C10: 不适用
A11: 发展部 | B11: 35kv-750kv电网基建项目
A12: 基建部 | B12: 35kv-750kv电网基建项目
A13: 法律部 | B13: 35kv-750kv电网基建项目
A14: 财务部 | B14: 35kv-750kv电网基建项目
A15: 物资部 | B15: 35kv-750kv电网基建项目
A16: 发展部 | B16: 迁改工程管理
A17: 基建部 | B17: 迁改工程管理
A18: 设备部 | B18: 迁改工程管理
A19: 财务部 | B19: 迁改工程管理
A20: 发展部 | B20: 配网工程管理
A21: 设备部 | B21: 配网工程管理
A22: 物资部 | B22: 配网工程管理
... A30: 国调中心 | B30: 设备（资产）管理
A31: 抽蓄事业部 | B31: 设备（资产）管理 | C31: 不适用
A32: 特高压部 | B32: 设备（资产）管理 | C32: 不适用
A33: 财务部 | B33: 设备（资产）管理
A34: 审计部 | B34: 设备（资产）管理
A35: 物资部 | B35: 物资（服务）采购与实施
A36: 财务部 | B36: 物资（服务）采购与实施
A37: 法律部 | B37: 物资（服务）采购与实施
A38: 各项目管理部门 | B38: 物资（服务）采购与实施
A39: 财务部 | B39: 数字化与研发投入
A40: 科技部 | B40: 数字化与研发投入
A41: 数字化部 | B41: 数字化与研发投入
A42: 企管部 | B42: 职工福利保障与薪酬管理
A43: 财务部 | B43: 职工福利保障与薪酬管理
A44: 工会 | B44: 职工福利保障与薪酬管理
... A51: 后勤部 | B51: 员工报账
A52: 国际部 | B52: 员工报账 | C52: 不适用
A53: 党建部 | B53: 员工报账
A54: 物资部 | B54: 员工报账
