Workbook

Sheet 业务流程
A1: 一级流程 | B1: 二级流程 | C1: 三级流程 | D1: 末级流程编号 | E1: 末级流程名称 | F1: 涉及价值管控风险的流程
A2: 市场营销 | B2: 电力市场营销管理 | C2: 有序用电管理 | D2: YX-01-01-01 | E2: 有序用电基础信息管理流程
D3: YX-01-01-02 | E3: 有序用电方案制定流程
D4: YX-01-01-03 | E4: 有序用电预警管理流程
D5: YX-01-01-04 | E5: 有序用电方案实施流程
D6: YX-01-01-05 | E6: 有序用电监督检查管理流程
D7: YX-01-01-06 | E7: 有序用电统计分析管理流程
C8: 市场分析预测管理 | D8: YX-01-02-01 | E8: 短期电力市场分析预测管理流程
D9: YX-01-02-02 | E9: 迎峰度夏（冬）电力供需分析预测管理流程
C10: 能效服务管理 | D10: YX-01-03-01 | E10: 能效服务网络建设运行管理流程
D11: YX-01-03-02 | E11: 能效服务指标管理流程
D12: YX-01-03-03 | E12: 能效服务项目管理流程
C13: 综合能源管理 | D13: YX-01-04-01 | E13: 综合能源服务管理流程 | F13: √
D14: YX-01-04-02 | E14: 需求侧响应管理流程
C15: 自备电厂管理 | D15: YX-01-04-01 | E15: 自备电厂机组并网与电力供应协议管理流程
C16: 智能用电管理 | D16: YX-01-05-01 | E16: 智能充换电服务网络建设项目实施管理流程
D17: YX-01-05-02 | E17: 智能充换电服务网络运营服务管理流程
D18: YX-01-05-03 | E18: 智能充换电服务网络充电设施缺陷管理流程
B19: 营业管理 | C19: 供电营业区管理 | D19: YX-02-01-01 | E19: 供电营业区域管理流程
D20: YX-02-01-02 | E20: 供电营业许可证管理流程
C21: 业扩报装 | D21: YX-02-02-01 | E21: 业扩报装流程与服务要求制定流程 | F21: √
D22: YX-02-02-02 | E22: 220kV及以上业扩报装管理流程
D23: YX-02-02-03 | E23: 110kV业扩报装管理流程
D24: YX-02-02-04 | E24: 35kV业扩报装管理流程
D25: YX-02-02-05 | E25: 10kV业扩报装管理流程
D26: YX-02-02-06 | E26: 低压业扩报装管理流程
D27: YX-02-02-07 | E27: 国家重点工程业扩报装协调管理流程
C28: 变更用电管理 | D28: YX-02-03-01 | E28: 减容管理流程
D29: YX-02-03-02 | E29: 减容恢复管理流程
D30: YX-02-03-03 | E30: 暂停管理流程
D31: YX-02-03-04 | E31: 暂停恢复管理流程
D32: YX-02-03-05 | E32: 暂拆管理流程
D33: YX-02-03-06 | E33: 暂拆复装管理流程
D34: YX-02-03-07 | E34: 暂换管理流程
D35: YX-02-03-08 | E35: 暂换恢复管理流程
D36: YX-02-03-09 | E36: 迁址管理流程
D37: YX-02-03-10 | E37: 移表管理流程
D38: YX-02-03-11 | E38: 销户管理流程
D39: YX-02-03-12 | E39: 过户管理流程
D40: YX-02-03-13 | E40: 更名管理流程
... D47: YX-02-03-20 | E47: 计量装置故障管理流程
C48: 供用电合同管理 | D48: YX-02-04-01 | E48: 供用电合同参考文本管理流程 | F48: √
D49: YX-02-04-02 | E49: 供用电合同签订管理流程
D50: YX-02-04-03 | E50: 供用电合同变更管理流程
D51: YX-02-04-04 | E51: 供用电合同纠纷处理流程
C52: 电费抄核收管理 | D52: YX-02-05-01 | E52: 抄表段管理流程 | F52: √
D53: YX-02-05-02 | E53: 抄表管理流程
D54: YX-02-05-03 | E54: 抄表设备管理流程
D55: YX-02-05-04 | E55: 电费核算管理流程
D56: YX-02-05-05 | E56: 电费退补电量电费管理流程
D57: YX-02-05-06 | E57: 业务费收费管理流程
D58: YX-02-05-07 | E58: 电费收费管理流程
D59: YX-02-05-08 | E59: 电费充值卡管理流程
D60: YX-02-05-09 | E60: 预购电费管理流程
D61: YX-02-05-10 | E61: 金融机构代收电费协议管理流程
D62: YX-02-05-11 | E62: 非金融机构代收网点协议管理流程
D63: YX-02-05-12 | E63: 供电企业自助售电缴费设备管理流程
D64: YX-02-05-13 | E64: 电费分次划拨管理流程
... D85: YX-02-05-34 | E85: 电费退费管理流程
C86: 销售电价管理 | D86: YX-02-06-01 | E86: 销售电价检查管理流程
D87: YX-02-06-02 | E87: 电价、电费标准调整管理流程
C88: 管理线损执行 | D88: YX-02-07-01 | E88: 管理线损执行流程
C89: 供电营业窗口管理 | D89: YX-02-08-01 | E89: 供电营业窗口标准化建设管理流程
D90: YX-02-08-02 | E90: 供电营业窗口服务规范化建设管理流程
C91: 营销信息系统管理 | D91: YX-02-09-01 | E91: 营销信息系统需求管理流程
D92: YX-02-09-02 | E92: 营销信息系统数据质量管理流程
C93: 分布式电源管理 | D93: YX-02-10-01 | E93: 分布式电源并网服务管理流程
D94: YX-02-10-02 | E94: 分布式电源发用电合同管理流程
C95: 客户档案管理 | D95: YX-02-11-01 | E95: 客户档案标准化管理流程 | F95: √
D96: YX-02-11-02 | E96: 客户档案建档管理流程
D97: YX-02-11-03 | E97: 客户档案保管管理流程
D98: YX-02-11-04 | E98: 客户档案借阅管理流程
D99: YX-02-11-05 | E99: 客户档案销毁管理流程
C100: 无表临时用电管理 | D100: YX-02-12-01 | E100: 无表临时用电新装管理流程
D101: YX-02-12-02 | E101: 无表临时用电延期管理流程
D102: YX-02-12-03 | E102: 无表临时用电终止管理流程
C103: 线上渠道运营管理 | D103: YX-02-13-01 | E103: 线上渠道内容管理流程
D104: YX-02-13-02 | E104: 线上渠道活动管理流程
D105: YX-02-13-03 | E105: 线上渠道产品发版管理流程
C106: 购电业务管理 | D106: YX-02-14-01 | E106: 电网企业代理购电管理流程
B107: 电能计量 | C107: 计量标准管理 | D107: YX-03-01-01 | E107: 计量标准需求审核管理流程
D108: YX-03-01-02 | E108: 计量标准建标管理流程
D109: YX-03-01-03 | E109: 计量标准复查管理流程
D110: YX-03-01-04 | E110: 计量标准封存（撤销）管理流程
D111: YX-03-01-05 | E111: 计量标准更换管理流程
D112: YX-03-01-06 | E112: 计量标准量值溯源管理流程
D113: YX-03-01-07 | E113: 计量标准报废管理流程
D114: YX-03-01-08 | E114: 计量标准运维维护管理流程
D115: YX-03-01-09 | E115: 计量标准期间核查管理流程
D116: YX-03-01-10 | E116: 计量自动化生产系统运维管理流程
D117: YX-03-01-11 | E117: 计量自动化生产系统应急管理流程
D118: YX-03-01-12 | E118: 计量标准档案管理流程
C119: 计量安全防护体系管理 | D119: YX-03-02-01 | E119: 密钥系统维护管理流程
D120: YX-03-02-02 | E120: 密钥介质管理流程
D121: YX-03-02-03 | E121: 现场服务终端管理流程
C122: 用电信息采集系统管理 | D122: YX-03-03-01 | E122: 用电信息采集系统建设管理流程
D123: YX-03-03-02 | E123: 用电信息采集系统运行维护管理流程
D124: YX-03-03-03 | E124: 用电信息采集系统终端设备巡视管理流程
D125: YX-03-03-04 | E125: 用电信息采集系统主站设备新增、更换管理流程
D126: YX-03-03-05 | E126: 用电信息采集系统专变终端调试管理流程
...

Sheet 流程图

Sheet 员工报账（核对过程7.23）
A1: 风控矩阵-员工报账
A2: 业务条线 | B2: 业务领域 | C2: 控制目标 | D2: 业务流程步骤 | E2: 经营风险 | F2: 典型问题 | G2: 关键控制点 | H2: 控制要求 | I2: 控制措施 编号 | J2: 控制措施 | K2: 控制措施分类 | T2: 控制方式 | U2: 控制系统 | V2: 控制载体 | W2: 责任主体 | X2: 业务自评价 | AA2: 集团监督 评价 | AD2: 数字化监督场景 | AH2: 现有制度及文件落实情况 | AK2: 总部审核部门 | AL2: 湖南公司审核部门 | AM2: 其他备注
K3: 不相容岗位 | L3: 分级授权 | M3: 业务真实性控制 | N3: 预算管控 | O3: 合同控制 | P3: 收付控制 | Q3: 会计监督 | R3: 财产保护 | S3: 分析与评价 | X3: 评价频率 | Y3: 评价范围 | Z3: 评价结论 | AA3: 评价频率 | AB3: 评价范围 | AC3: 评价结论 | AD3: 数字化监督场景 | AE3: 评价频率 | AF3: 评价范围 | AG3: 评价结论 | AH3: 是否已要求 | AI3: 是否满足要求 | AJ3: 对应制度及文件名称 | AN3: 7.23
A4: 员工报账 | B4: 一、员工差旅 | C4: 资金资产安全 | D4: 出差申请 | E4: 出差事项不真实，出差无实质内容，无明确公务目的，虚列套取费用，导致资金安全风险。 | F4: 87.违规发放津贴补贴：存在多报差旅补贴、虚报差旅补贴等问题。 | G4: 1.出差申请发起 | H4: 出差有明确公务目的，出差时间、地点、人员与出差通知一致。 | I4: 员工报账业务-1.出差申请发起-控制措施01 | J4: 出差员工部门负责人对员工出差内容的复核，重点审查出差申请单人员、地点、事由等信息。 | M4: √ | T4: 系统已建 | U4: 国网商旅 | V4: 1.出差通知、培训通知等出差缘由证明材料。 | W4: 各级单位-各部门-出差人员、各级单位-各部门-负责人、商旅云公司 | X4: 每日 | Y4: 全量检查 | AA4: 每年 | AB4: 抽查 | AD4: 员工差旅出差申请监督场景 | AE4: 每月 | AF4: 抽查 | AH4: 是 | AI4: 是 | AJ4: 《国家电网有限公司差旅费管理办法》（国家电网企管〔2026〕101号）第四条、第二十四条、《国网湖南省电力有限公司关于印发加强差旅费管理有关规定的通知》第二条、第三条 | AK4: 国网财务部 | AL4: 各级单位财务部 | AN4: 补充制度 | AO4: =A4=[1]员工报账!A4 -> TRUE | AP4: =B4=[1]员工报账!B4 -> TRUE | AQ4: =C4=[1]员工报账!C4 -> TRUE | AR4: =D4=[1]员工报账!D4 -> TRUE | AS4: =E4=[1]员工报账!E4 -> TRUE | AT4: =F4=[1]员工报账!F4 -> TRUE | AU4: =G4=[1]员工报账!G4 -> TRUE | AV4: =H4=[1]员工报账!H4 -> TRUE | ... BX4: =AJ4=[1]员工报账!AJ4 -> FALSE
I5: 员工报账业务-1.出差申请发起-控制措施02 | J5: 健全“申请-预订-报销”数据联动校验规则，落实预算控制，系统自动比对出差事项与出差产生的票据的逻辑一致性。 | M5: √ | N5: √ | T5: 系统已建 | U5: 国网商旅 | V5: 1.出差审批单。 | W5: 各级单位-各部门-出差人员、商旅云公司 | X5: 每日 | Y5: 全量检查 | AA5: 每年 | AB5: 抽查 | AD5: 员工差旅出差申请监督场景 | AE5: 每月 | AF5: 抽查 | AH5: 是 | AI5: 是 | AJ5: 《国家电网有限公司差旅费管理办法》（国家电网企管〔2026〕101号）第四条、第二十四条、《国网湖南省电力有限公司关于印发加强差旅费管理有关规定的通知》第二条、第三条 | AK5: 国网财务部 | AL5: 各级单位财务部 | AN5: 补充制度 | AO5: =A5=[1]员工报账!A5 -> TRUE | AP5: =B5=[1]员工报账!B5 -> TRUE | AQ5: =C5=[1]员工报账!C5 -> TRUE | AR5: =D5=[1]员工报账!D5 -> TRUE | AS5: =E5=[1]员工报账!E5 -> TRUE | AT5: =F5=[1]员工报账!F5 -> TRUE | AU5: =G5=[1]员工报账!G5 -> TRUE | AV5: =H5=[1]员工报账!H5 -> TRUE | ... BX5: =AJ5=[1]员工报账!AJ5 -> FALSE
I6: 员工报账业务-1.出差申请发起-控制措施03 | J6: 健全差旅费成本中心校验机制，赴异地挂职、按照规定探亲在途期间出差申请选择原单位成本中心，挂职期间出差申请选择挂职单位成本中心。 | N6: √ | Q6: √ | T6: 系统已建 | U6: 国网商旅 | V6: 1.系统出差申请单校验记录等。 | W6: 各级单位-各部门-出差人员、商旅云公司 | X6: 每日 | Y6: 全量检查 | AA6: 每年 | AB6: 抽查 | AD6: 员工差旅出差申请监督场景 | AE6: 每月 | AF6: 抽查 | AH6: 是 | AI6: 是 | AJ6: 《国家电网有限公司差旅费管理办法》（国家电网企管〔2026〕101号）第四条、第二十四条、《国网湖南省电力有限公司关于印发加强差旅费管理有关规定的通知》第二条、第三条 | AK6: 国网财务部 | AL6: 各级单位财务部 | AN6: 补充制度 | AO6: =A6=[1]员工报账!A6 -> TRUE | AP6: =B6=[1]员工报账!B6 -> TRUE | AQ6: =C6=[1]员工报账!C6 -> TRUE | AR6: =D6=[1]员工报账!D6 -> TRUE | AS6: =E6=[1]员工报账!E6 -> TRUE | AT6: =F6=[1]员工报账!F6 -> TRUE | AU6: =G6=[1]员工报账!G6 -> TRUE | AV6: =H6=[1]员工报账!H6 -> TRUE | ... BX6: =AJ6=[1]员工报账!AJ6 -> FALSE
G7: 2.出差申请审批 | H7: 按规定执行出差审批制度。 | I7: 员工报账业务-2.出差申请审批-控制措施01 | J7: 流程固化与防逆向控制，商旅云公司固化“审批-预订-报销”流程，严格限制并需特殊授权才能“取消审批”等逆向操作。 | L7: √ | Q7: √ | T7: 系统已建 | U7: 国网商旅 | V7: 1.出差通知、培训通知等出差缘由证明材料； 2.出差审批单； 3.系统出差申请单审批轨迹。 | W7: 各级单位-各部门-出差人员、商旅云公司 | X7: 每日 | Y7: 全量检查 | AA7: 每年 | AB7: 抽查 | AD7: 员工差旅出差申请监督场景 | AE7: 每月 | AF7: 抽查 | AH7: 是 | AI7: 是 | AJ7: 《国家电网有限公司差旅费管理办法》（国家电网企管〔2026〕101号）第二十二条 | AK7: 国网财务部 | AL7: 各级单位财务部 | AO7: =A7=[1]员工报账!A7 -> TRUE | AP7: =B7=[1]员工报账!B7 -> TRUE | AQ7: =C7=[1]员工报账!C7 -> TRUE | AR7: =D7=[1]员工报账!D7 -> TRUE | AS7: =E7=[1]员工报账!E7 -> TRUE | AT7: =F7=[1]员工报账!F7 -> TRUE | AU7: =G7=[1]员工报账!G7 -> TRUE | AV7: =H7=[1]员工报账!H7 -> TRUE | ... BX7: =AJ7=[1]员工报账!AJ7 -> TRUE
I8: 员工报账业务-2.出差申请审批-控制措施02 | J8: 全链条强制关联控制，系统强制将“审批单号”作为商旅预订及费用报销的唯一前提。 | Q8: √ | T8: 系统已建 | U8: 国网商旅 | V8: 1.出差通知、培训通知等出差缘由证明材料； 2.出差审批单。 | W8: 各级单位-各部门-出差人员、商旅云公司 | X8: 每日 | Y8: 全量检查 | AA8: 每年 | AB8: 抽查 | AD8: 员工差旅出差申请监督场景 | AE8: 每月 | AF8: 抽查 | AH8: 是 | AI8: 是 | AJ8: 《国家电网有限公司差旅费管理办法》（国家电网企管〔2026〕101号）第四条、第二十四条、第二十六条 | AK8: 国网财务部 | AL8: 各级单位财务部 | AO8: =A8=[1]员工报账!A8 -> TRUE | AP8: =B8=[1]员工报账!B8 -> TRUE | AQ8: =C8=[1]员工报账!C8 -> TRUE | AR8: =D8=[1]员工报账!D8 -> TRUE | AS8: =E8=[1]员工报账!E8 -> TRUE | AT8: =F8=[1]员工报账!F8 -> TRUE | AU8: =G8=[1]员工报账!G8 -> TRUE | AV8: =H8=[1]员工报账!H8 -> TRUE | ... BX8: =AJ8=[1]员工报账!AJ8 -> TRUE
I9: 员工报账业务-2.出差申请审批-控制措施03 | J9: 商旅云公司严禁后台“绿色通道”操作，禁止平台通过电话申请取消审批行为。 | M9: √ | T9: 系统待建 | U9: 国网商旅 | V9: 1.出差通知、培训通知等出差缘由证明材料； 2.出差审批单； 3.系统出差申请单审批轨迹。 | W9: 各级单位-各部门-出差人员、商旅云公司 | X9: 每日 | Y9: 全量检查 | AA9: 每年 | AB9: 抽查 | AD9: 员工差旅出差申请监督场景 | AE9: 每月 | AF9: 抽查 | AH9: 是 | AI9: 是 | AJ9: 《国家电网有限公司差旅费管理办法》（国家电网企管〔2026〕101号）第四条、第二十四条、第二十六条 | AK9: 国网财务部 | AL9: 各级单位财务部 | AO9: =A9=[1]员工报账!A9 -> TRUE | AP9: =B9=[1]员工报账!B9 -> TRUE | AQ9: =C9=[1]员工报账!C9 -> TRUE | AR9: =D9=[1]员工报账!D9 -> TRUE | AS9: =E9=[1]员工报账!E9 -> TRUE | AT9: =F9=[1]员工报账!F9 -> TRUE | AU9: =G9=[1]员工报账!G9 -> TRUE | AV9: =H9=[1]员工报账!H9 -> TRUE | ... BX9: =AJ9=[1]员工报账!AJ9 -> TRUE
A10: 员工报账 | B10: 一、员工差旅 | C10: 税务合规 | D10: 出差申请 | E10: 商旅平台违规取消事前审批流程，导致出现“先出差后申请”的情况，引发舞弊及合规管理风险。 | F10: 87.违规发放津贴补贴：存在多报差旅补贴、虚报差旅补贴等问题。 | G10: 3.出差申请流程控制 | H10: 出差申请日期早于出差日期。 | I10: 员工报账业务-3.出差申请流程控制-控制措施01 | J10: 审批要素完整性校验，系统强制校验审批单的必备要素，对缺少出差事由等关键要素的申请单不予通过。 | M10: √ | T10: 系统已建 | U10: 国网商旅 | V10: 1.系统出差申请单审批轨迹； 2.系统记录的申请单提交时间和出差时间。 | W10: 各级单位-各部门-出差人员、各级单位-各部门-负责人、商旅云公司 | X10: 每日 | Y10: 全量检查 | AA10: 每年 | AB10: 抽查 | AD10: 员工差旅流程配置监督场景 | AE10: 每月 | AF10: 抽查 | AH10: 是 | AI10: 是 | AJ10: 《国家电网有限公司差旅费管理办法》（国家电网企管〔2026〕101号）第五条 | AK10: 国网财务部 | AL10: 各级单位财务部 | AN10: 修改责任主体 | AO10: =A10=[1]员工报账!A10 -> TRUE | AP10: =B10=[1]员工报账!B10 -> TRUE | AQ10: =C10=[1]员工报账!C10 -> TRUE | AR10: =D10=[1]员工报账!D10 -> TRUE | AS10: =E10=[1]员工报账!E10 -> TRUE | AT10: =F10=[1]员工报账!F10 -> TRUE | AU10: =G10=[1]员工报账!G10 -> TRUE | AV10: =H10=[1]员工报账!H10 -> TRUE | ... BX10: =AJ10=[1]员工报账!AJ10 -> TRUE
I11: 员工报账业务-3.出差申请流程控制-控制措施02 | J11: 严格执行不相容控制，系统根据组织架构与授权清单自动匹配并校验审批人权限，防范越权审批 | R11: √ | T11: 系统已建 | U11: 国网商旅 | V11: 1.系统记录的申请单提交时间和出差时间。 | W11: 商旅云公司、各级单位-各部门-出差人员、各级单位-各部门-负责人 | X11: 每日 | Y11: 全量检查 | AA11: 每年 | AB11: 抽查 | AD11: 员工差旅流程配置监督场景 | AE11: 每月 | AF11: 抽查 | AH11: 是 | AI11: 是 | AJ11: 《国家电网有限公司差旅费管理办法》（国家电网企管〔2026〕101号）第五条 | AK11: 国网财务部 | AL11: 各级单位财务部 | AO11: =A11=[1]员工报账!A11 -> TRUE | AP11: =B11=[1]员工报账!B11 -> TRUE | AQ11: =C11=[1]员工报账!C11 -> TRUE | AR11: =D11=[1]员工报账!D11 -> TRUE | AS11: =E11=[1]员工报账!E11 -> TRUE | AT11: =F11=[1]员工报账!F11 -> TRUE | AU11: =G11=[1]员工报账!G11 -> TRUE | AV11: =H11=[1]员工报账!H11 -> TRUE | ... BX11: =AJ11=[1]员工报账!AJ11 -> TRUE
I12: 员工报账业务-3.出差申请流程控制-控制措施03 | J12: 建立定期分析、评价与问责机制，各部门对审批时效、驳回率、特批事项进行专项分析，审计部门、纪检部门等监督部门对违规审批、补批行为依规问责。 | M12: √ | R12: √ | S12: √ | T12: 线下管控 | V12: 1.系统记录的申请单提交时间和出差时间。 | W12: 商旅云公司、各级单位-审计部门、纪检部门等监督部门-监督、纪检管理人员 | X12: 每日 | Y12: 全量检查 | AA12: 每年 | AB12: 抽查 | AD12: 员工差旅流程配置监督场景 | AE12: 每月 | AF12: 抽查 | AH12: 是 | AI12: 是 | AJ12: 《国家电网有限公司差旅费管理办法》（国家电网企管〔2026〕101号）第五条 | AK12: 国网财务部 | AL12: 各级单位财务部 | AN12: 修改责任主体 | AO12: =A12=[1]员工报账!A12 -> TRUE | AP12: =B12=[1]员工报账!B12 -> TRUE | AQ12: =C12=[1]员工报账!C12 -> TRUE | AR12: =D12=[1]员工报账!D12 -> TRUE | AS12: =E12=[1]员工报账!E12 -> TRUE | AT12: =F12=[1]员工报账!F12 -> TRUE | AU12: =G12=[1]员工报账!G12 -> TRUE | AV12: =H12=[1]员工报账!H12 -> TRUE | ... BX12: =AJ12=[1]员工报账!AJ12 -> TRUE
C13: 税务合规 | D13: 差旅预订 | E13: 商旅平台酒店存在棋牌、麻将、电竞等敏感字眼，商旅平台违规上架引发合规风险。 | G13: 4.酒店入驻上架控制 | H13: 酒店资源上架流程合规，且履行必要的审批手续。 | I13: 员工报账业务-4.酒店入驻上架控制-控制措施01 | J13: 商旅云公司强化供应商准入审核，对新签约酒店的的资质有效性、服务适配性以及风险可控性等信息进行事前审核。 | O13: √ | T13: 系统待建 | U13: 国网商旅 | V13: 1.酒店资质、营业执照、房型清单。 | W13: 商旅云公司 | X13: 每日 | Y13: 全量检查 | AA13: 每年 | AB13: 抽查 | AD13: 员工差旅预订监督场景 | AE13: 每月 | AF13: 抽查 | AH13: 是 | AI13: 是 | AJ13: 《国家电网有限公司差旅费管理办法》（国家电网企管〔2026〕101号）第五条 | AK13: 国网财务部 | AL13: 各级单位财务部 | AO13: =A13=[1]员工报账!A13 -> TRUE | AP13: =B13=[1]员工报账!B13 -> TRUE | AQ13: =C13=[1]员工报账!C13 -> TRUE | AR13: =D13=[1]员工报账!D13 -> TRUE | AS13: =E13=[1]员工报账!E13 -> TRUE | AT13: =F13=[1]员工报账!F13 -> TRUE | AU13: =G13=[1]员工报账!G13 -> TRUE | AV13: =H13=[1]员工报账!H13 -> TRUE | ... BX13: =AJ13=[1]员工报账!AJ13 -> TRUE
I14: 员工报账业务-4.酒店入驻上架控制-控制措施02 | J14: 商旅云公司建立并动态更新《敏感词库与酒店属性负面清单》，系统自动拦截负面清单内容并转人工复核。 | O14: √ | Q14: √ | S14: √ | T14: 系统待建 | U14: 国网商旅 | V14: 1.系统敏感词库与酒店属性负面清单。 | W14: 商旅云公司 | X14: 每日 | Y14: 全量检查 | AA14: 每年 | AB14: 抽查 | AD14: 员工差旅预订监督场景 | AE14: 每月 | AF14: 抽查 | AH14: 是 | AI14: 是 | AJ14: 《国家电网有限公司差旅费管理办法》（国家电网企管〔2026〕101号）第五条 | AK14: 国网财务部 | AL14: 各级单位财务部 | AO14: =A14=[1]员工报账!A14 -> TRUE | AP14: =B14=[1]员工报账!B14 -> TRUE | AQ14: =C14=[1]员工报账!C14 -> TRUE | AR14: =D14=[1]员工报账!D14 -> TRUE | AS14: =E14=[1]员工报账!E14 -> TRUE | AT14: =F14=[1]员工报账!F14 -> TRUE | AU14: =G14=[1]员工报账!G14 -> TRUE | AV14: =H14=[1]员工报账!H14 -> TRUE | ... BX14: =AJ14=[1]员工报账!AJ14 -> TRUE
I15: 员工报账业务-4.酒店入驻上架控制-控制措施03 | J15: 追回违规上架酒店产生的资金浪费，并对相关负责人按规定给予处分处理。 | R15: √ | S15: √ | T15: 线下管控 | V15: 1.问责证明材料。 | W15: 商旅云公司 | X15: 每日 | Y15: 全量检查 | AA15: 每年 | AB15: 抽查 | AD15: 员工差旅预订监督场景 | AE15: 每月 | AF15: 抽查 | AH15: 是 | AI15: 是 | AJ15: 《国家电网有限公司差旅费管理办法》（国家电网企管〔2026〕101号）第五条 | AK15: 国网财务部 | AL15: 各级单位财务部 | AO15: =A15=[1]员工报账!A15 -> TRUE | AP15: =B15=[1]员工报账!B15 -> TRUE | AQ15: =C15=[1]员工报账!C15 -> TRUE | AR15: =D15=[1]员工报账!D15 -> TRUE | AS15: =E15=[1]员工报账!E15 -> TRUE | AT15: =F15=[1]员工报账!F15 -> TRUE | AU15: =G15=[1]员工报账!G15 -> TRUE | AV15: =H15=[1]员工报账!H15 -> TRUE | ... BX15: =AJ15=[1]员工报账!AJ15 -> TRUE
C16: 资金资产安全 | D16: 差旅预订 | E16: 酒店价格虚高易引发套取资金，引发廉政风险。 | F16: 87.违规发放津贴补贴：存在多报差旅补贴、虚报差旅补贴等问题。 | G16: 5.单体酒店上架及价格定价管控 | H16: 商旅平台酒店资源价格真实合理。 | I16: 员工报账业务-5.单体酒店上架及价格定价管控-控制措施01 | J16: 增加单体酒店上架申请审批流程，由各单位办公室汇总审核本单位酒店需求，向商旅云公司提交上架。 | L16: √ | O16: √ | T16: 系统已建 | U16: 国网商旅 | V16: 1.协议单体酒店推荐表单。 | W16: 商旅云公司、各级单位-办公室财务部 | X16: 每日 | Y16: 全量检查 | AA16: 每年 | AB16: 抽查 | AD16: 员工差旅预订监督场景 | AE16: 每月 | AF16: 抽查 | AH16: 是 | AI16: 是 | AJ16: 《国家电网有限公司差旅费管理办法》（国家电网企管〔2026〕101号）第五条 | AK16: 国网财务部 | AL16: 各级单位财务部 | AN16: 修改责任主体 | AO16: =A16=[1]员工报账!A16 -> TRUE | AP16: =B16=[1]员工报账!B16 -> TRUE | AQ16: =C16=[1]员工报账!C16 -> TRUE | AR16: =D16=[1]员工报账!D16 -> TRUE | AS16: =E16=[1]员工报账!E16 -> TRUE | AT16: =F16=[1]员工报账!F16 -> TRUE | AU16: =G16=[1]员工报账!G16 -> TRUE | AV16: =H16=[1]员工报账!H16 -> TRUE | ... BX16: =AJ16=[1]员工报账!AJ16 -> TRUE
I17: 员工报账业务-5.单体酒店上架及价格定价管控-控制措施02 | J17: 商旅云公司强化协议签订管控，严格审核酒店资质，严控无理由上架，防范舞弊行为。 | O17: √ | T17: 系统已建 | U17: 国网商旅 | V17: 1.酒单违规风险清单； 2.采购协议酒店清单； 3.酒店上架评审报告。 | W17: 商旅云公司 | X17: 每日 | Y17: 全量检查 | AA17: 每年 | AB17: 抽查 | AD17: 员工差旅预订监督场景 | AE17: 每月 | AF17: 抽查 | AH17: 是 | AI17: 是 | AJ17: 《国家电网有限公司差旅费管理办法》（国家电网企管〔2026〕101号）第五条 | AK17: 国网财务部 | AL17: 各级单位财务部 | AO17: =A17=[1]员工报账!A17 -> TRUE | AP17: =B17=[1]员工报账!B17 -> TRUE | AQ17: =C17=[1]员工报账!C17 -> TRUE | AR17: =D17=[1]员工报账!D17 -> TRUE | AS17: =E17=[1]员工报账!E17 -> TRUE | AT17: =F17=[1]员工报账!F17 -> TRUE | AU17: =G17=[1]员工报账!G17 -> TRUE | AV17: =H17=[1]员工报账!H17 -> TRUE | ... BX17: =AJ17=[1]员工报账!AJ17 -> TRUE
I18: 员工报账业务-5.单体酒店上架及价格定价管控-控制措施03 | J18: 加强员工行为管控，商旅云公司强化酒店订单在线监督，防范员工违规套取资金。 | M18: √ | R18: √ | T18: 系统已建 | U18: 国网商旅 | V18: 1.酒店合作协议。 | W18: 商旅云公司 | X18: 每日 | Y18: 全量检查 | AA18: 每年 | AB18: 抽查 | AD18: 员工差旅预订监督场景 | AE18: 每月 | AF18: 抽查 | AH18: 是 | AI18: 是 | AJ18: 《国家电网有限公司差旅费管理办法》（国家电网企管〔2026〕101号）第五条 | AK18: 国网财务部 | AL18: 各级单位财务部 | AO18: =A18=[1]员工报账!A18 -> TRUE | AP18: =B18=[1]员工报账!B18 -> TRUE | AQ18: =C18=[1]员工报账!C18 -> TRUE | AR18: =D18=[1]员工报账!D18 -> TRUE | AS18: =E18=[1]员工报账!E18 -> TRUE | AT18: =F18=[1]员工报账!F18 -> TRUE | AU18: =G18=[1]员工报账!G18 -> TRUE | AV18: =H18=[1]员工报账!H18 -> TRUE | ... BX18: =AJ18=[1]员工报账!AJ18 -> TRUE
A19: 员工报账 | B19: 一、员工差旅 | C19: 资金资产安全 | D19: 差旅预订 | E19: 酒店价格虚高易引发套取资金，引发廉政风险。 | F19: 87.违规发放津贴补贴：存在多报差旅补贴、虚报差旅补贴等问题。 | G19: 5.单体酒店上架及价格定价管控 | H19: 商旅平台酒店资源价格真实合理。 | I19: 员工报账业务-5.单体酒店上架及价格定价管控-控制措施04 | J19: 建立负面清单，及时清退违规酒店。 | R19: √ | S19: √ | T19: 线下管控 | V19: 1.酒店风险识别机制； 2.员工体验反馈。 | W19: 商旅云公司 | X19: 每日 | Y19: 全量检查 | AA19: 每年 | AB19: 抽查 | AD19: 员工差旅预订监督场景 | AE19: 每月 | AF19: 抽查 | AH19: 是 | AI19: 是 | AJ19: 《国家电网有限公司差旅费管理办法》（国家电网企管〔2026〕101号）第五条 | AK19: 国网财务部 | AL19: 各级单位财务部 | AO19: =A19=[1]员工报账!A19 -> TRUE | AP19: =B19=[1]员工报账!B19 -> TRUE | AQ19: =C19=[1]员工报账!C19 -> TRUE | AR19: =D19=[1]员工报账!D19 -> TRUE | AS19: =E19=[1]员工报账!E19 -> TRUE | AT19: =F19=[1]员工报账!F19 -> TRUE | AU19: =G19=[1]员工报账!G19 -> TRUE | AV19: =H19=[1]员工报账!H19 -> TRUE | ... BX19: =AJ19=[1]员工报账!AJ19 -> TRUE
D20: 差旅预订 | E20: 员工在同一时间段内重复预订酒店资源，存在套取资金风险。 | F20: 87.违规发放津贴补贴：存在多报差旅补贴、虚报差旅补贴等问题。 | G20: 6.酒店预订 | H20: 同一员工在同一时间段内，就同一出差行程，仅能生成一个有效住宿订单。 | I20: 员工报账业务-6.酒店预订-控制措施01 | J20: 商旅云公司完善重复订单系统校验规则，自动拦截并预警同一人员、时段重叠的酒店订单申请。 | M20: √ | T20: 系统已建 | U20: 国网商旅 | V20: 1.商旅订单； 2.出差通知、培训通知等出差缘由证明材料。 | W20: 各级单位-各部门-出差人员、商旅云公司 | X20: 每日 | Y20: 全量检查 | AA20: 每年 | AB20: 抽查 | AD20: 员工差旅预订监督场景 | AE20: 每月 | AF20: 抽查 | AH20: 是 | AI20: 是 | AJ20: 《国家电网有限公司差旅费管理办法》（国家电网企管〔2026〕101号）第二十四条 | AK20: 国网财务部 | AL20: 各级单位财务部 | AO20: =A20=[1]员工报账!A20 -> TRUE | AP20: =B20=[1]员工报账!B20 -> TRUE | AQ20: =C20=[1]员工报账!C20 -> TRUE | AR20: =D20=[1]员工报账!D20 -> TRUE | AS20: =E20=[1]员工报账!E20 -> TRUE | AT20: =F20=[1]员工报账!F20 -> TRUE | AU20: =G20=[1]员工报账!G20 -> TRUE | AV20: =H20=[1]员工报账!H20 -> TRUE | ... BX20: =AJ20=[1]员工报账!AJ20 -> TRUE
I21: 员工报账业务-6.酒店预订-控制措施02 | J21: 商旅云公司健全入住轨迹验证与反馈机制，自动识别入住轨迹异常情况，即时预警有关责任人。 | M21: √ | S21: √ | T21: 系统已建 | U21: 国网商旅 | V21: 1.系统拦截记录。 | W21: 各级单位-各部门-出差人员、商旅云公司 | X21: 每日 | Y21: 全量检查 | AA21: 每年 | AB21: 抽查 | AD21: 员工差旅预订监督场景 | AE21: 每月 | AF21: 抽查 | AH21: 是 | AI21: 是 | AJ21: 《国家电网有限公司差旅费管理办法》（国家电网企管〔2026〕101号）第二十四条 | AK21: 国网财务部 | AL21: 各级单位财务部 | AO21: =A21=[1]员工报账!A21 -> TRUE | AP21: =B21=[1]员工报账!B21 -> TRUE | AQ21: =C21=[1]员工报账!C21 -> TRUE | AR21: =D21=[1]员工报账!D21 -> TRUE | AS21: =E21=[1]员工报账!E21 -> TRUE | AT21: =F21=[1]员工报账!F21 -> TRUE | AU21: =G21=[1]员工报账!G21 -> TRUE | AV21: =H21=[1]员工报账!H21 -> TRUE | ... BX21: =AJ21=[1]员工报账!AJ21 -> TRUE
I22: 员工报账业务-6.酒店预订-控制措施03 | J22: 财务部门加强出差申请与酒店订单的交叉复核，校验人员、时间、订单的合理性与唯一性。 | M22: √ | T22: 系统已建 | U22: 国网商旅 | V22: 1.出差报销单； 2.入住轨迹与异常情况反馈。 | W22: 各级单位-各部门-出差人员、各级单位-财务部门-成本管理人员、商旅云公司 | X22: 每日 | Y22: 全量检查 | AA22: 每年 | AB22: 抽查 | AD22: 员工差旅预订监督场景 | AE22: 每月 | AF22: 抽查 | AH22: 是 | AI22: 是 | AJ22: 《国家电网有限公司差旅费管理办法》（国家电网企管〔2026〕101号）第二十四条 | AK22: 国网财务部 | AL22: 各级单位财务部 | AN22: 修改责任主体 | AO22: =A22=[1]员工报账!A22 -> TRUE | AP22: =B22=[1]员工报账!B22 -> TRUE | AQ22: =C22=[1]员工报账!C22 -> TRUE | AR22: =D22=[1]员工报账!D22 -> TRUE | AS22: =E22=[1]员工报账!E22 -> TRUE | AT22: =F22=[1]员工报账!F22 -> TRUE | AU22: =G22=[1]员工报账!G22 -> TRUE | AV22: =H22=[1]员工报账!H22 -> TRUE | ... BX22: =AJ22=[1]员工报账!AJ22 -> TRUE
C23: 税务合规 | D23: 差旅报销 | E23: 擅自扩大差旅费开支范围，提高差旅费开支标准，增加差旅出行成本。 | F23: 87.违规发放津贴补贴：存在多报差旅补贴、虚报差旅补贴等问题。 | G23: 7.差旅标准执行 | H23: 差旅费开支标准、开支范围符合本单位差旅费标准。 | I23: 员工报账业务-7.差旅标准执行-控制措施01 | J23: 商旅云公司完善差旅费超标刚性管控功能，系统对超标申请酒店、交通工具和差旅补助进行自动隐藏。 | M23: √ | R23: √ | T23: 系统已建 | U23: 国网商旅 | V23: 1.差旅标准系统校验规则库； 2.出差通知、培训通知等出差缘由证明材料； 3.出差审批单； 4.出差报销单。 | W23: 各级单位-财务部门-预算管理人员、各级单位-各部门-出差人员、各级单位-各部门-负责人、各级单位-财务部门-成本管理人员、商旅云公司 | X23: 每日 | Y23: 全量检查 | AA23: 每年 | AB23: 抽查 | AD23: 员工差旅费用标准监督场景 | AE23: 每月 | AF23: 抽查 | AH23: 是 | AI23: 是 | AJ23: 《国家电网有限公司差旅费管理办法》（国家电网企管〔2026〕101号）第八条、第十一条至第十九条 | AK23: 国网财务部 | AL23: 各级单位财务部 | AO23: =A23=[1]员工报账!A23 -> TRUE | AP23: =B23=[1]员工报账!B23 -> TRUE | AQ23: =C23=[1]员工报账!C23 -> TRUE | AR23: =D23=[1]员工报账!D23 -> TRUE | AS23: =E23=[1]员工报账!E23 -> TRUE | AT23: =F23=[1]员工报账!F23 -> TRUE | AU23: =G23=[1]员工报账!G23 -> TRUE | AV23: =H23=[1]员工报账!H23 -> TRUE | ... BX23: =AJ23=[1]员工报账!AJ23 -> TRUE
I24: 员工报账业务-7.差旅标准执行-控制措施02 | J24: 财务部门加强出差类别与出差性质审核，重点关注评标、培训等特殊出差事项政策执行情况。 | M24: √ | Q24: √ | T24: 系统已建 | U24: 国网商旅 | V24: 1.差旅标准系统校验规则库； 2.出差通知、培训通知等出差缘由证明材料； 3.出差审批单； 4.出差报销单。 | W24: 各级单位-财务部门-预算管理人员、各级单位-各部门-负责人、各级单位-财务部门-成本管理人员、商旅云公司 | X24: 每日 | Y24: 全量检查 | AA24: 每年 | AB24: 抽查 | AD24: 员工差旅费用标准监督场景 | AE24: 每月 | AF24: 抽查 | AH24: 是 | AI24: 是 | AJ24: 《国家电网有限公司差旅费管理办法》（国家电网企管〔2026〕101号）第八条、第十一条至第十九条 | AK24: 国网财务部 | AL24: 各级单位财务部 | AO24: =A24=[1]员工报账!A24 -> TRUE | AP24: =B24=[1]员工报账!B24 -> TRUE | AQ24: =C24=[1]员工报账!C24 -> TRUE | AR24: =D24=[1]员工报账!D24 -> TRUE | AS24: =E24=[1]员工报账!E24 -> TRUE | AT24: =F24=[1]员工报账!F24 -> TRUE | AU24: =G24=[1]员工报账!G24 -> TRUE | AV24: =H24=[1]员工报账!H24 -> TRUE | ... BX24: =AJ24=[1]员工报账!AJ24 -> TRUE
I25: 员工报账业务-7.差旅标准执行-控制措施03 | J25: 纪检部门推动退赔与整改机制，对超标报销行为依规严肃问责。 | R25: √ | S25: √ | T25: 线下管控 | V25: 1.问责证明材料。 | W25: 各级单位-财务部门-预算管理人员、各级单位-各部门-出差人员、各级单位-各部门-负责人、各级单位-财务部门-成本管理人员、商旅云公司、各级单位-纪检部门-纪检管理人员 | X25: 每日 | Y25: 全量检查 | AA25: 每年 | AB25: 抽查 | AD25: 员工差旅费用标准监督场景 | AE25: 每月 | AF25: 抽查 | AH25: 是 | AI25: 是 | AJ25: 《国家电网有限公司差旅费管理办法》（国家电网企管〔2026〕101号）第八条、第十一条至第十九条、《国网湖南省电力有限公司关于印发加强差旅费管理有关规定的通知》第一条 | AK25: 国网财务部 | AL25: 各级单位财务部 | AN25: 补充制度 | AO25: =A25=[1]员工报账!A25 -> TRUE | AP25: =B25=[1]员工报账!B25 -> TRUE | AQ25: =C25=[1]员工报账!C25 -> TRUE | AR25: =D25=[1]员工报账!D25 -> TRUE | AS25: =E25=[1]员工报账!E25 -> TRUE | AT25: =F25=[1]员工报账!F25 -> TRUE | AU25: =G25=[1]员工报账!G25 -> TRUE | AV25: =H25=[1]员工报账!H25 -> TRUE | ... BX25: =AJ25=[1]员工报账!AJ25 -> FALSE
A26: 员工报账 | B26: 一、员工差旅 | C26: 资金资产安全 | D26: 差旅报销 | E26: 虚报冒领差旅费，虚列套取费用，导致资金安全风险。 | F26: 87.违规发放津贴补贴：存在多报差旅补贴、虚报差旅补贴等问题。 | G26: 8.差旅报销合规性控制 | H26: 交通费、公杂费、住宿费等报销真实发生，差旅费报销准确。 | I26: 员工报账业务-8.差旅报销合规性控制-控制措施01 | J26: 建立业务部门费用报销前置审核机制，对机票、酒店、火车、补助等金额准确性复核。 | M26: √ | Q26: √ | R26: √ | T26: 系统已建 | U26: 国网商旅 | V26: 1.出差通知、培训通知等出差缘由证明材料； 2.出差审批单； 3.预订的商旅订单； 4.发票； 5.考勤记录。 | W26: 各级单位-各部门-出差人员、各级单位-各部门-出差报销审核人、各级单位-财务部门-成本管理人员、商旅云公司 | X26: 每日 | Y26: 全量检查 | AA26: 每年 | AB26: 抽查 | AD26: 员工差旅报销监督场景 | AE26: 每月 | AF26: 抽查 | AH26: 是 | AI26: 是 | AJ26: 《国网财务部、后勤部关于进一步规范差旅伙食费和交通费收交管理有关事项的通知》第三条、第四条 《国家电网有限公司差旅费管理办法》（国家电网企管〔2026〕101号）第十二条、第十三条、第十七条、第二十四条 | AK26: 国网财务部 | AL26: 各级单位财务部 | AO26: =A26=[1]员工报账!A26 -> TRUE | AP26: =B26=[1]员工报账!B26 -> TRUE | AQ26: =C26=[1]员工报账!C26 -> TRUE | AR26: =D26=[1]员工报账!D26 -> TRUE | AS26: =E26=[1]员工报账!E26 -> TRUE | AT26: =F26=[1]员工报账!F26 -> TRUE | AU26: =G26=[1]员工报账!G26 -> TRUE | AV26: =H26=[1]员工报账!H26 -> TRUE | ... BX26: =AJ26=[1]员工报账!AJ26 -> TRUE
I27: 员工报账业务-8.差旅报销合规性控制-控制措施02 | J27: 商旅云公司强化时空逻辑系统校验，对“出差时间-住宿时间-车票时间”进行自动校验，拦截或预警重叠数据。 | M27: √ | Q27: √ | T27: 系统已建 | U27: 国网商旅 | V27: 1.出差通知、培训通知等出差缘由证明材料； 2.出差审批单； 3.预订的商旅订单； 4.发票； 5.考勤记录。 | W27: 商旅云公司 | X27: 每日 | Y27: 全量检查 | AA27: 每年 | AB27: 抽查 | AD27: 员工差旅报销监督场景 | AE27: 每月 | AF27: 抽查 | AH27: 是 | AI27: 是 | AJ27: 《国网财务部、后勤部关于进一步规范差旅伙食费和交通费收交管理有关事项的通知》第三条、第四条 《国家电网有限公司差旅费管理办法》（国家电网企管〔2026〕101号第十二条、第十三条、第十七条、第二十四条 | AK27: 国网财务部 | AL27: 各级单位财务部 | AO27: =A27=[1]员工报账!A27 -> TRUE | AP27: =B27=[1]员工报账!B27 -> TRUE | AQ27: =C27=[1]员工报账!C27 -> TRUE | AR27: =D27=[1]员工报账!D27 -> TRUE | AS27: =E27=[1]员工报账!E27 -> TRUE | AT27: =F27=[1]员工报账!F27 -> TRUE | AU27: =G27=[1]员工报账!G27 -> TRUE | AV27: =H27=[1]员工报账!H27 -> TRUE | ... BX27: =AJ27=[1]员工报账!AJ27 -> TRUE
I28: 员工报账业务-8.差旅报销合规性控制-控制措施03 | J28: 商旅云公司健全票据使用状态规则，重点筛查“未使用”的交通票据，防范员工利用废票虚报费用或重复报销。 | M28: √ | R28: √ | T28: 系统已建 | U28: 国网商旅 | V28: 1.出差通知、培训通知等出差缘由证明材料； 2.出差审批单； 3.预订的商旅订单； 4.发票； 5.考勤记录。 | W28: 各级单位-各部门-出差人员、各级单位-各部门-出差报销审核人、各级单位-财务部门-成本管理人员、商旅云公司 | X28: 每日 | Y28: 全量检查 | AA28: 每年 | AB28: 抽查 | AD28: 员工差旅报销监督场景 | AE28: 每月 | AF28: 抽查 | AH28: 是 | AI28: 是 | AJ28: 《国网财务部、后勤部关于进一步规范差旅伙食费和交通费收交管理有关事项的通知》第三条、第四条 《国家电网有限公司差旅费管理办法》（国家电网企管〔2026〕101号）第十七条、第二十四条 | AK28: 国网财务部 | AL28: 各级单位财务部 | AO28: =A28=[1]员工报账!A28 -> TRUE | AP28: =B28=[1]员工报账!B28 -> TRUE | AQ28: =C28=[1]员工报账!C28 -> TRUE | AR28: =D28=[1]员工报账!D28 -> TRUE | AS28: =E28=[1]员工报账!E28 -> TRUE | AT28: =F28=[1]员工报账!F28 -> TRUE | AU28: =G28=[1]员工报账!G28 -> TRUE | AV28: =H28=[1]员工报账!H28 -> TRUE | ... BX28: =AJ28=[1]员工报账!AJ28 -> TRUE
I29: 员工报账业务-8.差旅报销合规性控制-控制措施04 | J29: 财务部门加强差旅报销审核力度，对同一时段连续出差公杂费、伙食补助费进行复核，避免重复计算。 | M29: √ | Q29: √ | T29: 系统已建 | U29: 国网商旅 | V29: 1.出差通知、培训通知等出差缘由证明材料； 2.出差审批单； 3.预订的商旅订单； 4.发票； 5.考勤记录。 | W29: 各级单位-各部门-出差人员、各级单位-各部门-出差报销审核人、各级单位-财务部门-成本管理人员、商旅云公司 | X29: 每日 | Y29: 全量检查 | AA29: 每年 | AB29: 抽查 | AD29: 员工差旅报销监督场景 | AE29: 每月 | AF29: 抽查 | AH29: 是 | AI29: 是 | AJ29: 《国网财务部、后勤部关于进一步规范差旅伙食费和交通费收交管理有关事项的通知》第三条、第四条 《国家电网有限公司差旅费管理办法》（国家电网企管〔2026〕101号第十二条、第十三条、第十七条、第二十四条 | AK29: 国网财务部 | AL29: 各级单位财务部 | AO29: =A29=[1]员工报账!A29 -> TRUE | AP29: =B29=[1]员工报账!B29 -> TRUE | AQ29: =C29=[1]员工报账!C29 -> TRUE | AR29: =D29=[1]员工报账!D29 -> TRUE | AS29: =E29=[1]员工报账!E29 -> TRUE | AT29: =F29=[1]员工报账!F29 -> TRUE | AU29: =G29=[1]员工报账!G29 -> TRUE | AV29: =H29=[1]员工报账!H29 -> TRUE | ... BX29: =AJ29=[1]员工报账!AJ29 -> TRUE
A30: 员工报账 | B30: 一、员工差旅 | C30: 资金资产安全 | D30: 差旅报销 | E30: 虚报冒领差旅费，虚列套取费用，导致资金安全风险。 | F30: 87.违规发放津贴补贴：存在多报差旅补贴、虚报差旅补贴等问题。 | G30: 8.差旅报销合规性控制 | H30: 交通费、公杂费、住宿费等报销真实发生，差旅费报销准确。 | I30: 员工报账业务-8.差旅报销合规性控制-控制措施05 | J30: 纪检部门完善违规问责与闭环管理机制，对未缴纳伙食费用套取各类补助和虚报行为进行问责，追回资金，并纳入个人诚信记录。 | M30: √ | R30: √ | S30: √ | T30: 线下管控 | V30: 1.问责证明材料。 | W30: 各级单位-各部门-出差人员、各级单位-各部门-出差报销审核人、各级单位-财务部门-成本管理人员、商旅云公司、各级单位-纪检部门-纪检管理人员 | X30: 每日 | Y30: 全量检查 | AA30: 每年 | AB30: 抽查 | AD30: 员工差旅报销监督场景 | AE30: 每月 | AF30: 抽查 | AH30: 是 | AI30: 是 | AJ30: 《国网财务部、后勤部关于进一步规范差旅伙食费和交通费收交管理有关事项的通知》第三条、第四条 《国家电网有限公司差旅费管理办法》（国家电网企管〔2026〕101号）第十七条、第二十四条、《国网湖南省电力有限公司关于印发加强差旅费管理有关规定的通知》第一条 | AK30: 国网财务部 | AL30: 各级单位财务部 | AN30: 补充制度 | AO30: =A30=[1]员工报账!A30 -> TRUE | AP30: =B30=[1]员工报账!B30 -> TRUE | AQ30: =C30=[1]员工报账!C30 -> TRUE | AR30: =D30=[1]员工报账!D30 -> TRUE | AS30: =E30=[1]员工报账!E30 -> TRUE | AT30: =F30=[1]员工报账!F30 -> TRUE | AU30: =G30=[1]员工报账!G30 -> TRUE | AV30: =H30=[1]员工报账!H30 -> TRUE | ... BX30: =AJ30=[1]员工报账!AJ30 -> FALSE
E31: 员工自付单据中的人员、时间与地点未在出差范围内，虚报支出，套取资金，导致公司经济利益受损。 | G31: 9.自付单据审核 | H31: 自付单据中人员、时间、地点与出差申请单一致，自付交通费、住宿费符合差旅费标准。 | I31: 员工报账业务-9.自付单据审核-控制措施01 | J31: 商旅云公司健全“单轨控制”，系统强制关联“已完成审批单”与“线上支付订单”，并推动与税务平台直连，减少发票人工上传环节。 | S31: √ | T31: 系统待建 | U31: 国网商旅 | V31: 1.发票； 2.差旅费标准； 3.出差通知、培训通知等出差缘由证明材料； 4.出差审批单； 5.出差报销单。 | W31: 各级单位-各部门-出差人员、商旅云公司 | X31: 每日 | Y31: 全量检查 | AA31: 每年 | AB31: 抽查 | AD31: 员工差旅报销监督场景 | AE31: 每月 | AF31: 抽查 | AH31: 是 | AI31: 是 | AJ31: 《国家电网有限公司差旅费管理办法》（国家电网企管〔2026〕101号）第八条、第十一条、第二十四条 | AK31: 国网财务部 | AL31: 各级单位财务部 | AO31: =A31=[1]员工报账!A31 -> TRUE | AP31: =B31=[1]员工报账!B31 -> TRUE | AQ31: =C31=[1]员工报账!C31 -> TRUE | AR31: =D31=[1]员工报账!D31 -> TRUE | AS31: =E31=[1]员工报账!E31 -> TRUE | AT31: =F31=[1]员工报账!F31 -> TRUE | AU31: =G31=[1]员工报账!G31 -> TRUE | AV31: =H31=[1]员工报账!H31 -> TRUE | ... BX31: =AJ31=[1]员工报账!AJ31 -> TRUE
I32: 员工报账业务-9.自付单据审核-控制措施02 | J32: 强化线下报销验证，未实现系统“单轨控制”的单位强化事前审批，强制“行程轨迹佐证”，同时借助第三方工具“建立发票真伪与重复报销”校验机制。 | M32: √ | Q32: √ | R32: √ | T32: 线下管控 | V32: 1.发票； 2.差旅费标准； 3.出差通知、培训通知等出差缘由证明材料； 4.出差审批单； 5.出差报销单。 | W32: 各级单位-各部门-出差人员、各级单位-各部门-负责人、商旅云公司 | X32: 每日 | Y32: 全量检查 | AA32: 每年 | AB32: 抽查 | AD32: 员工差旅报销监督场景 | AE32: 每月 | AF32: 抽查 | AH32: 是 | AI32: 是 | AJ32: 《国家电网有限公司差旅费管理办法》（国家电网企管〔2026〕101号）第八条、第十一条、第二十四条 | AK32: 国网财务部 | AL32: 各级单位财务部 | AN32: 修改责任主体 | AO32: =A32=[1]员工报账!A32 -> TRUE | AP32: =B32=[1]员工报账!B32 -> TRUE | AQ32: =C32=[1]员工报账!C32 -> TRUE | AR32: =D32=[1]员工报账!D32 -> TRUE | AS32: =E32=[1]员工报账!E32 -> TRUE | AT32: =F32=[1]员工报账!F32 -> TRUE | AU32: =G32=[1]员工报账!G32 -> TRUE | AV32: =H32=[1]员工报账!H32 -> TRUE | ... BX32: =AJ32=[1]员工报账!AJ32 -> TRUE
I33: 员工报账业务-9.自付单据审核-控制措施03 | J33: 财务部门规范自付单据与标准审核流程，逐一核对自付单据人员、时间、地点，并审核费用标准是否符合公司规定。 | M33: √ | Q33: √ | R33: √ | T33: 系统已建 | U33: 国网商旅 | V33: 1.发票； 2.差旅费标准； 3.出差通知、培训通知等出差缘由证明材料； 4.出差审批单； 5.出差报销单。 | W33: 各级单位-各部门-出差人员、商旅云公司、各级单位-财务部门-成本管理人员 | X33: 每日 | Y33: 全量检查 | AA33: 每年 | AB33: 抽查 | AD33: 员工差旅报销监督场景 | AE33: 每月 | AF33: 抽查 | AH33: 是 | AI33: 是 | AJ33: 《国家电网有限公司差旅费管理办法》（国家电网企管〔2026〕101号）第八条、第十一条、第二十四条 | AK33: 国网财务部 | AL33: 各级单位财务部 | AO33: =A33=[1]员工报账!A33 -> TRUE | AP33: =B33=[1]员工报账!B33 -> TRUE | AQ33: =C33=[1]员工报账!C33 -> TRUE | AR33: =D33=[1]员工报账!D33 -> TRUE | AS33: =E33=[1]员工报账!E33 -> TRUE | AT33: =F33=[1]员工报账!F33 -> TRUE | AU33: =G33=[1]员工报账!G33 -> TRUE | AV33: =H33=[1]员工报账!H33 -> TRUE | ... BX33: =AJ33=[1]员工报账!AJ33 -> TRUE
I34: 员工报账业务-9.自付单据审核-控制措施04 | J34: 纪检部门严肃查处违规行为，追回资金损失，严肃查处并予以通报。 | M34: √ | R34: √ | T34: 线下管控 | V34: 1.商旅平台数据线上预订率、电子票据抓取率。 | W34: 各级单位-各部门-出差人员、商旅云公司、各级单位-纪检部门-纪检管理人员 | X34: 每日 | Y34: 全量检查 | AA34: 每年 | AB34: 抽查 | AD34: 员工差旅报销监督场景 | AE34: 每月 | AF34: 抽查 | AH34: 是 | AI34: 是 | AJ34: 《国家电网有限公司差旅费管理办法》（国家电网企管〔2026〕101号）第八条、第十一条、第二十四条、《国网湖南省电力有限公司关于印发加强差旅费管理有关规定的通知》第一条 | AK34: 国网财务部 | AL34: 各级单位财务部 | AN34: 补充制度 | AO34: =A34=[1]员工报账!A34 -> TRUE | AP34: =B34=[1]员工报账!B34 -> TRUE | AQ34: =C34=[1]员工报账!C34 -> TRUE | AR34: =D34=[1]员工报账!D34 -> TRUE | AS34: =E34=[1]员工报账!E34 -> TRUE | AT34: =F34=[1]员工报账!F34 -> TRUE | AU34: =G34=[1]员工报账!G34 -> TRUE | AV34: =H34=[1]员工报账!H34 -> TRUE | ... BX34: =AJ34=[1]员工报账!AJ34 -> FALSE
A35: 员工报账 | B35: 一、员工差旅 | C35: 税务合规、资金资产安全 | D35: 报销申请 | E35: 成本费用报销事项不真实、审批流程不规范，导致成本入账科目错误、虚列成本费用、套取资金私设“小金库”。 | G35: 10.报销事项合规性控制 | H35: 在规定列支范围内，以真实发生的事项发起报销申请，履行规范审批流程。 | I35: 员工报账业务-10.报销事项合规性控制-控制措施01 | J35: 费用报销部门履行费用报销分级授权审批流程，对报销申请事项的真实性进行人工复核，复核报销审批单、费用明细清单、发票或收据、合同或协议等附件的完整性。 | L35: √ | R35: √ | T35: 线下管控 | V35: 1.成本费用报销审批单； 2.费用明细清单； 3.发票或收据； 4.合同或协议； 5.系统审批记录。 | W35: 各级单位-各部门-报账人员、各级单位-各部门-负责人、各级单位-财务部门-成本管理人员 | X35: 每季度 | Y35: 抽查 | AA35: 每年 | AB35: 抽查 | AD35: 报销真实性监督场景 | AE35: 每年 | AF35: 抽查 | AH35: 是 | AI35: 是 | AJ35: 《国家电网有限公司会计基础管理办法》（国家电网企管〔2019〕132号）第八条、第五十四条 《关于加强中央企业资金内部控制管理有关事项的通知》（国资发监督〔2021〕19 号）第十三条、《国网湖南省电力有限公司关于印发加强差旅费管理有关规定的通知》第一条 | AK35: 国网财务部、国网企管部、国网后勤部、国网国际部 | AL35: 各级单位财务部、各级单位企管部（人资部）、各级单位后勤部、 | AN35: 补充制度 | AO35: =A35=[1]员工报账!A35 -> TRUE | AP35: =B35=[1]员工报账!B35 -> TRUE | AQ35: =C35=[1]员工报账!C35 -> TRUE | AR35: =D35=[1]员工报账!D35 -> TRUE | AS35: =E35=[1]员工报账!E35 -> TRUE | AT35: =F35=[1]员工报账!F35 -> TRUE | AU35: =G35=[1]员工报账!G35 -> TRUE | AV35: =H35=[1]员工报账!H35 -> TRUE | ... BX35: =AJ35=[1]员工报账!AJ35 -> FALSE
I36: 员工报账业务-10.报销事项合规性控制-控制措施02 | J36: 加强挂职人员费用报销成本中心校验，挂职期间费用报销申请需选择挂职单位成本中心。 | Q36: √ | T36: 系统已建 | U36: 智慧共享财务平台 | V36: 1.成本费用报销审批单； 2.费用明细清单； 3.发票或收据； 4.合同或协议； 5.系统审批记录。 | W36: 各级单位-各部门-报账人员、各级单位-各部门-负责人、各级单位-财务部门-成本管理人员 | X36: 每季度 | Y36: 抽查 | AA36: 每年 | AB36: 抽查 | AD36: 报销真实性监督场景 | AE36: 每年 | AF36: 抽查 | AH36: 是 | AI36: 是 | AJ36: 《国家电网有限公司会计基础管理办法》（国家电网企管〔2019〕132号）第八条、第五十四条 《关于加强中央企业资金内部控制管理有关事项的通知》（国资发监督〔2021〕19 号）第十三条、《国网湖南省电力有限公司关于印发加强差旅费管理有关规定的通知》第三条 | AK36: 国网财务部、国网企管部、国网后勤部、国网国际部 | AL36: 各级单位财务部、各级单位企管部（人资部）、各级单位后勤部、 | AN36: 补充制度 | AO36: =A36=[1]员工报账!A36 -> TRUE | AP36: =B36=[1]员工报账!B36 -> TRUE | AQ36: =C36=[1]员工报账!C36 -> TRUE | AR36: =D36=[1]员工报账!D36 -> TRUE | AS36: =E36=[1]员工报账!E36 -> TRUE | AT36: =F36=[1]员工报账!F36 -> TRUE | AU36: =G36=[1]员工报账!G36 -> TRUE | AV36: =H36=[1]员工报账!H36 -> TRUE | ... BX36: =AJ36=[1]员工报账!AJ36 -> FALSE
I37: 员工报账业务-10.报销事项合规性控制-控制措施03 | J37: 财务部门对费用报销选择业务事项准确性进行复核，校验报销流程和成本中心准确性。 | M37: √ | Q37: √ | T37: 系统已建 | U37: 智慧共享财务平台 | V37: 1.成本费用报销审批单； 2.费用明细清单； 3.发票或收据； 4.合同或协议； 5.系统审批记录。 | W37: 各级单位-各部门-报账人员、各级单位-各部门-负责人、各级单位-财务部门-成本管理人员 | X37: 每季度 | Y37: 抽查 | AA37: 每年 | AB37: 抽查 | AD37: 报销真实性监督场景 | AE37: 每年 | AF37: 抽查 | AH37: 是 | AI37: 是 | AJ37: 《国家电网有限公司会计基础管理办法》（国家电网企管〔2019〕132号）第八条、第五十四条 《关于加强中央企业资金内部控制管理有关事项的通知》（国资发监督〔2021〕19 号）第十三条 | AK37: 国网财务部、国网企管部、国网后勤部、国网国际部 | AL37: 各级单位财务部、各级单位企管部（人资部）、各级单位后勤部、 | AO37: =A37=[1]员工报账!A37 -> TRUE | AP37: =B37=[1]员工报账!B37 -> TRUE | AQ37: =C37=[1]员工报账!C37 -> TRUE | AR37: =D37=[1]员工报账!D37 -> TRUE | AS37: =E37=[1]员工报账!E37 -> TRUE | AT37: =F37=[1]员工报账!F37 -> TRUE | AU37: =G37=[1]员工报账!G37 -> TRUE | AV37: =H37=[1]员工报账!H37 -> TRUE | ... BX37: =AJ37=[1]员工报账!AJ37 -> TRUE
I38: 员工报账业务-10.报销事项合规性控制-控制措施04 | J38: 进行违规责任追究，对虚列成本费用、套取资金私设“小金库”的人员根据相关规定进行违规责任追究。 | R38: √ | T38: 线下管控 | V38: 1.责任追究证明材料。 | W38: 各级单位-各部门-报账人员、各级单位-各部门-负责人、各级单位-财务部门-成本管理人员、各级单位-纪检部门-纪检管理人员 | X38: 每季度 | Y38: 抽查 | AA38: 每年 | AB38: 抽查 | AD38: 报销真实性监督场景 | AE38: 每年 | AF38: 抽查 | AH38: 是 | AI38: 是 | AJ38: 《国家电网有限公司会计基础管理办法》（国家电网企管〔2019〕132号）第八条、第五十四条 《关于加强中央企业资金内部控制管理有关事项的通知》（国资发监督〔2021〕19 号）第十三条 | AK38: 国网财务部、国网企管部、国网后勤部、国网国际部 | AL38: 各级单位财务部、各级单位企管部（人资部）、各级单位后勤部、 | AO38: =A38=[1]员工报账!A38 -> TRUE | AP38: =B38=[1]员工报账!B38 -> TRUE | AQ38: =C38=[1]员工报账!C38 -> TRUE | AR38: =D38=[1]员工报账!D38 -> TRUE | AS38: =E38=[1]员工报账!E38 -> TRUE | AT38: =F38=[1]员工报账!F38 -> TRUE | AU38: =G38=[1]员工报账!G38 -> TRUE | AV38: =H38=[1]员工报账!H38 -> TRUE | ... BX38: =AJ38=[1]员工报账!AJ38 -> TRUE
B39: 二、通用报账 | C39: 税务合规 | D39: 费用报销 | E39: 发票信息不准确、不完整，与报销业务不一致导致税务风险 | G39: 11.报销发票审核 | H39: 报销发票真实、准确、完整 | I39: 员工报账业务-11.报销发票审核-控制措施01 | J39: 归口管理部门对报销发票、入库单、采购订单物品对应关系进行复核，确认购物清单通过税务防伪系统开具。 | L39: √ | M39: √ | T39: 系统已建 | U39: 智慧共享财务平台 | V39: 1.成本费用报销申请单； 2.费用明细清单； 3.发票或收据、购物清单； 4.合同或协议。 | W39: 各级单位-各部门-报账人员、各级单位-各部门-负责人、各级单位-财务部门-成本管理人员 | X39: 每季度 | Y39: 抽查 | AA39: 每年 | AB39: 抽查 | AD39: 发票审核管理监督场景 | AE39: 每年 | AF39: 抽查 | AH39: 是 | AI39: 是 | AJ39: 国家电网企管〔2019〕132号《国家电网有限公司会计基础管理办法》第五十条 | AK39: 国网财务部、国网企管部、国网后勤部、国网国际部 | AL39: 各级单位财务部、各级单位企管部（人资部）、各级单位后勤部、 | AO39: =A39=[1]员工报账!A39 -> TRUE | AP39: =B39=[1]员工报账!B39 -> TRUE | AQ39: =C39=[1]员工报账!C39 -> TRUE | AR39: =D39=[1]员工报账!D39 -> TRUE | AS39: =E39=[1]员工报账!E39 -> TRUE | AT39: =F39=[1]员工报账!F39 -> TRUE | AU39: =G39=[1]员工报账!G39 -> TRUE | AV39: =H39=[1]员工报账!H39 -> TRUE | ... BX39: =AJ39=[1]员工报账!AJ39 -> TRUE
I40: 员工报账业务-11.报销发票审核-控制措施02 | J40: 各部门建立发票“谁提交、谁审核、谁负责”闭环管理机制,发票提交人落实发票验真责任。 | M40: √ | R40: √ | T40: 系统已建 | U40: 智慧共享财务平台 | V40: 1.成本费用报销申请单； 2.费用明细清单； 3.发票或收据、购物清单； 4.合同或协议。 | W40: 各级单位-各部门-报账人员、各级单位-各部门-负责人 | X40: 每季度 | Y40: 抽查 | AA40: 每年 | AB40: 抽查 | AD40: 发票审核管理监督场景 | AE40: 每年 | AF40: 抽查 | AH40: 是 | AI40: 是 | AJ40: 国家电网企管〔2019〕132号《国家电网有限公司会计基础管理办法》第五十条 | AK40: 国网企管部、国网后勤部、国网国际部 | AL40: 各级单位财务部、各级单位企管部（人资部）、各级单位后勤部 | AO40: =A40=[1]员工报账!A40 -> TRUE | AP40: =B40=[1]员工报账!B40 -> TRUE | AQ40: =C40=[1]员工报账!C40 -> TRUE | AR40: =D40=[1]员工报账!D40 -> TRUE | AS40: =E40=[1]员工报账!E40 -> TRUE | AT40: =F40=[1]员工报账!F40 -> TRUE | AU40: =G40=[1]员工报账!G40 -> TRUE | AV40: =H40=[1]员工报账!H40 -> TRUE | ... BX40: =AJ40=[1]员工报账!AJ40 -> TRUE
A41: 员工报账 | B41: 二、通用报账 | C41: 税务合规 | D41: 费用报销 | E41: 发票信息不准确、不完整，与报销业务不一致导致税务风险 | G41: 11.报销发票审核 | H41: 报销发票真实、准确、完整 | I41: 员工报账业务-11.报销发票审核-控制措施03 | J41: 发票提交人对增值税发票税率与合同条款进行复核，确认货物及应税劳务名称准确、金额及税率与合同一致，确认发票项目名称中不包含“茶叶、烟、酒水、门票、景区”等敏感字眼，确认销售方名称中不包含“会所、健身房、俱乐部、KTV、景区、洗浴中心”等敏感字眼。 | O41: √ | T41: 系统已建 线下管控 | U41: 智慧共享财务平台 | V41: 1.成本费用报销申请单； 2.费用明细清单； 3.发票或收据、购物清单； 4.合同或协议。 | W41: 各级单位-各部门-报账人员、各级单位-各部门-负责人 | X41: 每季度 | Y41: 抽查 | AA41: 每年 | AB41: 抽查 | AD41: 发票审核管理监督场景 | AE41: 每年 | AF41: 抽查 | AH41: 是 | AI41: 是 | AJ41: 国家电网企管〔2019〕132号《国家电网有限公司会计基础管理办法》第五十条 | AK41: 国网财务部、国网企管部、国网后勤部、国网国际部 | AL41: 各级单位财务部、各级单位企管部（人资部）、各级单位后勤部 | AN41: 修改控制方式，线上改为线下 | AO41: =A41=[1]员工报账!A41 -> TRUE | AP41: =B41=[1]员工报账!B41 -> TRUE | AQ41: =C41=[1]员工报账!C41 -> TRUE | AR41: =D41=[1]员工报账!D41 -> TRUE | AS41: =E41=[1]员工报账!E41 -> TRUE | AT41: =F41=[1]员工报账!F41 -> TRUE | AU41: =G41=[1]员工报账!G41 -> TRUE | AV41: =H41=[1]员工报账!H41 -> TRUE | ... BX41: =AJ41=[1]员工报账!AJ41 -> TRUE
I42: 员工报账业务-11.报销发票审核-控制措施04 | J42: 财务部门对发票开具的完整性、合规性进行复核，检查发票名目是否包含固定资产目录所列资产，福利费增值税进项税不得抵扣。 | Q42: √ | R42: √ | T42: 线下管控 | V42: 1.成本费用报销申请单； 2.费用明细清单； 3.发票或收据、购物清单； 4.合同或协议。 | W42: 各级单位-各部门-报账人员、各级单位-各部门-负责人、各级单位-财务部门-成本管理人员 | X42: 每季度 | Y42: 抽查 | AA42: 每年 | AB42: 抽查 | AD42: 发票审核管理监督场景 | AE42: 每年 | AF42: 抽查 | AH42: 是 | AI42: 是 | AJ42: 国家电网企管〔2019〕132号《国家电网有限公司会计基础管理办法》第五十条 | AK42: 国网财务部、国网企管部、国网后勤部、国网国际部 | AL42: 各级单位财务部、各级单位企管部（人资部）、各级单位后勤部 | AO42: =A42=[1]员工报账!A42 -> TRUE | AP42: =B42=[1]员工报账!B42 -> TRUE | AQ42: =C42=[1]员工报账!C42 -> TRUE | AR42: =D42=[1]员工报账!D42 -> TRUE | AS42: =E42=[1]员工报账!E42 -> TRUE | AT42: =F42=[1]员工报账!F42 -> TRUE | AU42: =G42=[1]员工报账!G42 -> TRUE | AV42: =H42=[1]员工报账!H42 -> TRUE | ... BX42: =AJ42=[1]员工报账!AJ42 -> TRUE
I43: 员工报账业务-11.报销发票审核-控制措施05 | J43: 财务人员对开具虚假发票套取资金等问题进行复核。 | M43: √ | Q43: √ | T43: 线下管控 | V43: 1.成本费用报销申请单； 2.费用明细清单； 3.发票或收据、购物清单； 4.合同或协议。 | W43: 各级单位-各部门-报账人员、各级单位-各部门-负责人、各级单位-财务部门-成本管理人员、各级单位-财务部门-税务管理人员 | X43: 每季度 | Y43: 抽查 | AA43: 每年 | AB43: 抽查 | AD43: 发票审核管理监督场景 | AE43: 每年 | AF43: 抽查 | AH43: 是 | AI43: 是 | AJ43: 国家电网企管〔2019〕132号《国家电网有限公司会计基础管理办法》第五十条 | AK43: 国网财务部、国网企管部、国网后勤部、国网国际部 | AL43: 各级单位财务部、各级单位企管部（人资部）、各级单位后勤部 | AN43: 修改责任主体 | AO43: =A43=[1]员工报账!A43 -> TRUE | AP43: =B43=[1]员工报账!B43 -> TRUE | AQ43: =C43=[1]员工报账!C43 -> TRUE | AR43: =D43=[1]员工报账!D43 -> TRUE | AS43: =E43=[1]员工报账!E43 -> TRUE | AT43: =F43=[1]员工报账!F43 -> TRUE | AU43: =G43=[1]员工报账!G43 -> TRUE | AV43: =H43=[1]员工报账!H43 -> TRUE | ... BX43: =AJ43=[1]员工报账!AJ43 -> TRUE
D44: 公务接待活动 | E44: 未严格执行公务接待制度，虚列公务接待清单套取公务接待费用，引发资金支出及合规风险。 | G44: 12.公务接待范围、执行制度、费用报销 | H44: 严格执行公务接待制度，确保公务接待费支出规范。 | I44: 员工报账业务-12.公务接待范围、执行制度、费用报销-控制措施01 | J44: 接待部门做好公务接待过程管控。①严格公务接待审批。按照《国家电网有限公司公务接待管理办法》要求，根据公函内容中来访对象、人数等，报相应公司（或部门）领导审批。②规范公务接待组织。承办部门公务接待要严格按照本单位贯彻落实中央八项规定实施细则有关规定执行。严控陪同人数，不得层层多人陪同等。③严格执行清单制度。按照《国家电网有限公司公务接待管理办法》要求，公务活动结束后，接待部门应当如实填写接待清单，包括接待对象的单位、姓名、职务和接待项目、时间、场所、费用等内容，经本部门负责同志审签。④规范做好报销。接待费用应当及时结算，不得用公款报销或者支付应当由个人负担的费用。禁止借公务接待名义列支其他支出等。 | M44: √ | T44: 线下管控 | V44: 1.派出单位公函(或通知)； 2.公务接待清单； 3.财务票据。 | W44: 各级单位-接待承办部门-报账人员、各级单位-接待承办部门-负责人、各级单位-接待管理部门-接待管理人员、各级单位-接待管理部门-负责人 | X44: 每季度 | Y44: 抽查 | AA44: 每年 | AB44: 抽查 | AD44: 公务接待费列支范围监督场景 | AE44: 每年 | AF44: 抽查 | AH44: 是 | AI44: 是 | AJ44: 《国家电网有限公司厉行节约反对浪费实施办法》（国家电网企管〔2025〕421号）第二十四条 《关于做好会议、接待管理相关事项报备报批工作的通知》（办值通〔2025〕55号） 《国家电网有限公司公务接待管理办法》国家电网企管〔2025〕267号 第五至十九 | AK44: 国网办公室 | AL44: 各级单位办公室 | AO44: =A44=[1]员工报账!A44 -> TRUE | AP44: =B44=[1]员工报账!B44 -> TRUE | AQ44: =C44=[1]员工报账!C44 -> TRUE | AR44: =D44=[1]员工报账!D44 -> TRUE | AS44: =E44=[1]员工报账!E44 -> TRUE | AT44: =F44=[1]员工报账!F44 -> TRUE | AU44: =G44=[1]员工报账!G44 -> TRUE | AV44: =H44=[1]员工报账!H44 -> TRUE | ... BX44: =AJ44=[1]员工报账!AJ44 -> TRUE
A45: 员工报账 | B45: 二、通用报账 | C45: 税务合规 | D45: 公务接待活动 | E45: 未严格执行公务接待制度，虚列公务接待清单套取公务接待费用，引发资金支出及合规风险。 | G45: 12.公务接待范围、执行制度、费用报销 | H45: 严格执行公务接待制度，确保公务接待费支出规范。 | I45: 员工报账业务-12.公务接待范围、执行制度、费用报销-控制措施02 | J45: 归口管理部门做好复核。对接待部门提交的接待清单中人员、住宿安排、用车安排、费用等进行复核。 | L45: √ | T45: 线下管控 | V45: 1.派出单位公函(或通知)； 2.公务接待清单； 3.财务票据。 | W45: 各级单位-接待承办部门-报账人员、各级单位-接待承办部门-负责人、各级单位-接待管理部门-接待管理人员、各级单位-接待管理部门-负责人 | X45: 每季度 | Y45: 抽查 | AA45: 每年 | AB45: 抽查 | AD45: 公务接待费列支范围监督场景 | AE45: 每年 | AF45: 抽查 | AH45: 是 | AI45: 是 | AJ45: 《国家电网有限公司厉行节约反对浪费实施办法》（国家电网企管〔2025〕421号）第二十四条 《关于做好会议、接待管理相关事项报备报批工作的通知》（办值通〔2025〕55号） 《国家电网有限公司公务接待管理办法》国家电网企管〔2025〕267号 第五至十九条 | AK45: 国网办公室 | AL45: 各级单位办公室 | AO45: =A45=[1]员工报账!A45 -> TRUE | AP45: =B45=[1]员工报账!B45 -> TRUE | AQ45: =C45=[1]员工报账!C45 -> TRUE | AR45: =D45=[1]员工报账!D45 -> TRUE | AS45: =E45=[1]员工报账!E45 -> TRUE | AT45: =F45=[1]员工报账!F45 -> TRUE | AU45: =G45=[1]员工报账!G45 -> TRUE | AV45: =H45=[1]员工报账!H45 -> TRUE | ... BX45: =AJ45=[1]员工报账!AJ45 -> TRUE
I46: 员工报账业务-12.公务接待范围、执行制度、费用报销-控制措施03 | J46: 财务部门做好报销审核。按照财务业务流程要求，做好报销审核、检查材料完备。 | Q46: √ | R46: √ | T46: 线下管控 | V46: 1.派出单位公函(或通知)； 2.公务接待清单； 3.财务票据。 | W46: 各级单位-接待承办部门-报账人员、各级单位-接待承办部门-负责人、各级单位-接待管理部门-接待管理人员、各级单位-接待管理部门-负责人、各级单位-财务部门-成本管理人员 | X46: 每季度 | Y46: 抽查 | AA46: 每年 | AB46: 抽查 | AD46: 公务接待费列支范围监督场景 | AE46: 每年 | AF46: 抽查 | AH46: 是 | AI46: 是 | AJ46: 《国家电网有限公司厉行节约反对浪费实施办法》（国家电网企管〔2025〕421号）第二十四条 《关于做好会议、接待管理相关事项报备报批工作的通知》（办值通〔2025〕55号） 《国家电网有限公司公务接待管理办法》国家电网企管〔2025〕267号 第五至十九条 | AK46: 国网办公室 | AL46: 各级单位办公室 | AO46: =A46=[1]员工报账!A46 -> TRUE | AP46: =B46=[1]员工报账!B46 -> TRUE | AQ46: =C46=[1]员工报账!C46 -> TRUE | AR46: =D46=[1]员工报账!D46 -> TRUE | AS46: =E46=[1]员工报账!E46 -> TRUE | AT46: =F46=[1]员工报账!F46 -> TRUE | AU46: =G46=[1]员工报账!G46 -> TRUE | AV46: =H46=[1]员工报账!H46 -> TRUE | ... BX46: =AJ46=[1]员工报账!AJ46 -> TRUE
C47: 资金资产安全 | D47: 公务车辆单车核算 | E47: 员工未严格执行公务车辆单车核算要求，通过伪造票据、虚报里程、费用金额、虚构用车场景等方式套取企业资金，导致企业成本虚增、资金流失风险。 | F47: 82.公务用车管控不严：存在新购置及长租公务用车未及时接入统一车辆管理平台过程监督管理；在公务用车维修等费用中虚列名目、处理其他无关费用或费用依据不足；超编超标超范围配置公务用车等问题。 | G47: 13.公务车辆单车核算管理 | H47: 严格执行公务车辆单车核算管理要求，据实报销车辆使用费。 | I47: 员工报账业务-13.公务车辆单车核算管理-控制措施01 | J47: 通过统一车辆平台进行系统控制，自动比对用车时间、目的地与车辆通行费发票时间、行程轨迹的匹配性，规避虚列费用。 | M47: √ | T47: 系统待建 | U47: 统一车辆平台 | V47: 1.公务车辆管理台账； 2.车辆单车核算台账； 3.ETC通行费明细清单； 4.费用明细清单； 5.发票或收据； 6.合同或协议。 | W47: 各级单位-公务车辆管理部门-车辆管理人员、各级单位-公务车辆管理部门-负责人 | X47: 每季度 | Y47: 抽查 | AA47: 每年 | AB47: 抽查 | AD47: 车辆使用费监督场景 | AE47: 每年 | AF47: 抽查 | AH47: 是 | AI47: 是 | AJ47: 《国家电网有限公司公务用车管理办法》（规章制度编号:国网(后勤/2)724-2025）第十一至十九条、第二十一条、第三十二条. | AK47: 国网后勤部 | AL47: 各级单位后勤部 | AO47: =A47=[1]员工报账!A47 -> TRUE | AP47: =B47=[1]员工报账!B47 -> TRUE | AQ47: =C47=[1]员工报账!C47 -> TRUE | AR47: =D47=[1]员工报账!D47 -> TRUE | AS47: =E47=[1]员工报账!E47 -> TRUE | AT47: =F47=[1]员工报账!F47 -> TRUE | AU47: =G47=[1]员工报账!G47 -> TRUE | AV47: =H47=[1]员工报账!H47 -> TRUE | ... BX47: =AJ47=[1]员工报账!AJ47 -> TRUE
I48: 员工报账业务-13.公务车辆单车核算管理-控制措施02 | J48: 系统直联控制，通过智慧共享财务平台直联统一车辆平台对单车核算台账明细进行系统控制，严禁列支保养、维修、年检、燃油等范围外费用，增加“车辆费用类型白名单”控制，超出范围的费用类型系统自动拒绝，并推送异常报告。 | N48: √ | O48: √ | T48: 系统待建 | U48: 智慧共享财务平台 | V48: 1.公务车辆管理台账； 2.车辆单车核算台账； 3.ETC通行费明细清单； 4.费用明细清单； 5.发票或收据； 6.合同或协议。 | W48: 各级单位-公务车辆管理部门-车辆管理人员、各级单位-公务车辆管理部门-负责人 | X48: 每季度 | Y48: 抽查 | AA48: 每年 | AB48: 抽查 | AD48: 车辆使用费监督场景 | AE48: 每年 | AF48: 抽查 | AH48: 是 | AI48: 是 | AJ48: 《国家电网有限公司公务用车管理办法》（规章制度编号:国网(后勤/2)724-2025）第十一至十九条、第二十一条、第三十二条. | AK48: 国网后勤部 | AL48: 各级单位后勤部 | AO48: =A48=[1]员工报账!A48 -> TRUE | AP48: =B48=[1]员工报账!B48 -> TRUE | AQ48: =C48=[1]员工报账!C48 -> TRUE | AR48: =D48=[1]员工报账!D48 -> TRUE | AS48: =E48=[1]员工报账!E48 -> TRUE | AT48: =F48=[1]员工报账!F48 -> TRUE | AU48: =G48=[1]员工报账!G48 -> TRUE | AV48: =H48=[1]员工报账!H48 -> TRUE | ... BX48: =AJ48=[1]员工报账!AJ48 -> TRUE
A49: 员工报账 | B49: 二、通用报账 | C49: 资金资产安全 | D49: 公务车辆单车核算 | E49: 员工未严格执行公务车辆单车核算要求，通过伪造票据、虚报里程、费用金额、虚构用车场景等方式套取企业资金，导致企业成本虚增、资金流失风险。 | F49: 82.公务用车管控不严：存在新购置及长租公务用车未及时接入统一车辆管理平台过程监督管理；在公务用车维修等费用中虚列名目、处理其他无关费用或费用依据不足；超编超标超范围配置公务用车等问题。 | I49: 员工报账业务-13.公务车辆单车核算管理-控制措施03 | J49: 未实现系统直联控制的单位应加强线下审核，车辆管理部门对单车费用明细（油费、过路费、停车费、维修费等）与用车申请单（事前提交，注明用车时间、事由、目的地）、车辆行驶里程记录（行车记录、起止日期）进行复核，严禁套取费用。 | M49: √ | R49: √ | T49: 线下管控 | V49: 1.公务车辆管理台账； 2.车辆单车核算台账； 3.ETC通行费明细清单； 4.费用明细清单； 5.发票或收据； 6.合同或协议。 | W49: 各级单位-公务车辆管理部门-车辆管理人员、各级单位-公务车辆管理部门-负责人、各级单位-财务部门-成本管理人员 | X49: 每季度 | Y49: 抽查 | AA49: 每年 | AB49: 抽查 | AD49: 车辆使用费监督场景 | AE49: 每年 | AF49: 抽查 | AH49: 是 | AI49: 是 | AJ49: 《国家电网有限公司公务用车管理办法》（规章制度编号:国网(后勤/2)724-2025）第十一至十九条、第二十一条、第三十二条. | AK49: 国网后勤部 | AL49: 各级单位后勤部 | AO49: =A49=[1]员工报账!A49 -> TRUE | AP49: =B49=[1]员工报账!B49 -> TRUE | AQ49: =C49=[1]员工报账!C49 -> TRUE | AR49: =D49=[1]员工报账!D49 -> TRUE | AS49: =E49=[1]员工报账!E49 -> TRUE | AT49: =F49=[1]员工报账!F49 -> TRUE | AU49: =G49=[1]员工报账!G49 -> TRUE | AV49: =H49=[1]员工报账!H49 -> TRUE | ... BX49: =AJ49=[1]员工报账!AJ49 -> TRUE
C50: 税务合规 | D50: 因公出国（境）管理 | E50: 超标准列支因公出国（境）经费，引发合规风险。 | G50: 14.因公出国（境）经费使用 | H50: 因公出国（境）经费标准使用符合规定，在规定范围内报销。 | I50: 员工报账业务-14.因公出国（境）经费使用-控制措施01 | J50: 归口管理部门对经批准的计划申请表进行复核，确认外事服务机构的收费标准不高于同业收费平均水平，落实预算控制要求。 | N50: √ | R50: √ | T50: 线下管控 | V50: 1.计划申请表及年度预算； 2.住宿费和伙食费发票； 3.费用报销审批单； 4.因公出国（境）费用计划申请； 5.因公出国（境）费用结算表。 | W50: 各级单位-各部门-报账人员、各级单位-各部门-负责人、各级单位-因公出国（境）经费归口管理部门-负责人、各级单位-财务部门-成本管理人员 | X50: 每季度 | Y50: 抽查 | AA50: 每年 | AB50: 抽查 | AD50: 因公出国（境）经费监督场景 | AE50: 每年 | AF50: 抽查 | AH50: 是 | AI50: 是 | AJ50: 《国家电网有限公司因公出国（境）经费管理办法》（国家电网企管〔2019〕715号）第八至十四条 | AK50: 国网国际部 | AO50: =A50=[1]员工报账!A50 -> TRUE | AP50: =B50=[1]员工报账!B50 -> TRUE | AQ50: =C50=[1]员工报账!C50 -> TRUE | AR50: =D50=[1]员工报账!D50 -> TRUE | AS50: =E50=[1]员工报账!E50 -> TRUE | AT50: =F50=[1]员工报账!F50 -> TRUE | AU50: =G50=[1]员工报账!G50 -> TRUE | AV50: =H50=[1]员工报账!H50 -> TRUE | ... BX50: =AJ50=[1]员工报账!AJ50 -> TRUE
I51: 员工报账业务-14.因公出国（境）经费使用-控制措施02 | J51: 归口管理部门对因公出国（境）经费列支范围进行复核，确认赠送礼品、安排宴请等均按照国务院、财政部、外交部有关规定执行。 | L51: √ | M51: √ | O51: √ | T51: 线下管控 | V51: 1.计划申请表及年度预算； 2.住宿费和伙食费发票； 3.费用报销审批单； 4.因公出国（境）费用计划申请； 5.因公出国（境）费用结算表。 | W51: 各级单位-各部门-报账人员、各级单位-各部门-负责人、各级单位-因公出国（境）经费归口管理部门-负责人 | X51: 每季度 | Y51: 抽查 | AA51: 每年 | AB51: 抽查 | AD51: 因公出国（境）经费监督场景 | AE51: 每年 | AF51: 抽查 | AH51: 是 | AI51: 是 | AJ51: 《国家电网有限公司因公出国（境）经费管理办法》（国家电网企管〔2019〕715号）第八至十四条 | AK51: 国网国际部 | AO51: =A51=[1]员工报账!A51 -> TRUE | AP51: =B51=[1]员工报账!B51 -> TRUE | AQ51: =C51=[1]员工报账!C51 -> TRUE | AR51: =D51=[1]员工报账!D51 -> TRUE | AS51: =E51=[1]员工报账!E51 -> TRUE | AT51: =F51=[1]员工报账!F51 -> TRUE | AU51: =G51=[1]员工报账!G51 -> TRUE | AV51: =H51=[1]员工报账!H51 -> TRUE | ... BX51: =AJ51=[1]员工报账!AJ51 -> TRUE
I52: 员工报账业务-14.因公出国（境）经费使用-控制措施03 | J52: 财务部门加强审核，按照科学预算、厉行节约的原则对因公出国（境）经费列支住宿费、伙食费、公杂费使用标准进行复核。 | Q52: √ | R52: √ | T52: 线下管控 | V52: 1.计划申请表及年度预算； 2.住宿费和伙食费发票； 3.费用报销审批单； 4.因公出国（境）费用计划申请； 5.因公出国（境）费用结算表。 | W52: 各级单位-各部门-报账人员、各级单位-各部门-负责人、各级单位-因公出国（境）经费归口管理部门-负责人、各级单位-财务部门-成本管理人员 | X52: 每季度 | Y52: 抽查 | AA52: 每年 | AB52: 抽查 | AD52: 因公出国（境）经费监督场景 | AE52: 每年 | AF52: 抽查 | AH52: 是 | AI52: 是 | AJ52: 《国家电网有限公司因公出国（境）经费管理办法》（国家电网企管〔2019〕715号）第八至十四条 | AK52: 国网国际部 | AO52: =A52=[1]员工报账!A52 -> TRUE | AP52: =B52=[1]员工报账!B52 -> TRUE | AQ52: =C52=[1]员工报账!C52 -> TRUE | AR52: =D52=[1]员工报账!D52 -> TRUE | AS52: =E52=[1]员工报账!E52 -> TRUE | AT52: =F52=[1]员工报账!F52 -> TRUE | AU52: =G52=[1]员工报账!G52 -> TRUE | AV52: =H52=[1]员工报账!H52 -> TRUE | ... BX52: =AJ52=[1]员工报账!AJ52 -> TRUE
A53: 员工报账 | B53: 二、通用报账 | C53: 资金资产安全 | D53: 会议费用报销（三公经费） | E53: 超期、超规模、超标准组织会议，计划外会议未规范履行报批程序，会议开支金额超会议费用预算，引发资金安全及合规管理风险。 | G53: 15.会议规模、费用报销 | H53: 合理确定会议规格，严格控制会议费预算规模。 | I53: 员工报账业务-15.会议规模、费用报销-控制措施01 | J53: 主办部门做好会议过程管控。① 做好会议筹备。按照会议类别，确定会议规模、会期、人数、会场、预算等。② 严格会议审批。按照《国家电网有限公司会议管理办法》要求，由主办部门履行内部审批流程，填写计划内会议费用申请表，提出申请，经本部门主要负责人签字。③ 规范会议组织。不得到豪华酒店、度假村和党中央、国务院明令禁止的风景名胜区召开会议，精简会务安排、严肃会议纪律。④ 规范会议报销。按照《国家电网有限公司会议管理办法》要求，会议费用报销应严格执行公司报销管理规定，由主办部门提出申请，经本部门主要负责人签字。严禁借会议名义列支或报销与会议无关的费用等。 | L53: √ | M53: √ | T53: 线下管控 | V53: 1.年度会议计划表； 2.计划内会议费用申请表； 3.会议通知、会议议程、参会名单； 4.发票或电子结算单； 5.计划外会议审批表。 | W53: 各级单位-会议承办部门-报账人员、各级单位-会议承办部门-负责人、各级单位-会议管理部门-会议管理人员、各级单位-会议管理部门-负责人 | X53: 每季度 | Y53: 抽查 | AA53: 每年 | AB53: 抽查 | AD53: 会议费监督场景 | AE53: 每年 | AF53: 抽查 | AH53: 是 | AI53: 是 | AJ53: 《国家电网有限公司会议管理办法》（国家电网企管〔2025〕267号）第七至十二条、第二十一至二十二条、第二十七至三十二条、第三十四至三十九条等。 《关于做好会议、接待管理相关事项报备报批工作的通知》（办值通〔2025〕55号） | AK53: 国网办公室 | AL53: 各级单位办公室 | AO53: =A53=[1]员工报账!A53 -> TRUE | AP53: =B53=[1]员工报账!B53 -> TRUE | AQ53: =C53=[1]员工报账!C53 -> TRUE | AR53: =D53=[1]员工报账!D53 -> TRUE | AS53: =E53=[1]员工报账!E53 -> TRUE | AT53: =F53=[1]员工报账!F53 -> TRUE | AU53: =G53=[1]员工报账!G53 -> TRUE | AV53: =H53=[1]员工报账!H53 -> TRUE | ... BX53: =AJ53=[1]员工报账!AJ53 -> TRUE
I54: 员工报账业务-15.会议规模、费用报销-控制措施02 | J54: 归口管理部门做好复核。对主办部门提交的计划内会议费用申请表、计划外会议审批表中会议计划、时间、地点、规模、预算、标准审批等进行复核。 | N54: √ | O54: √ | T54: 线下管控 | V54: 1.年度会议计划表； 2.计划内会议费用申请表； 3.会议通知、会议议程、参会名单； 4.发票或电子结算单； 5.计划外会议审批表。 | W54: 各级单位-会议承办部门-报账人员、各级单位-会议承办部门-负责人、各级单位-会议管理部门-会议管理人员、各级单位-会议管理部门-负责人 | X54: 每季度 | Y54: 抽查 | AA54: 每年 | AB54: 抽查 | AD54: 会议费监督场景 | AE54: 每年 | AF54: 抽查 | AH54: 是 | AI54: 是 | AJ54: 《国家电网有限公司会议管理办法》（国家电网企管〔2025〕267号）第七至十二条、第二十一至二十二条、第二十七至三十二条、第三十四至三十九条等。 《关于做好会议、接待管理相关事项报备报批工作的通知》（办值通〔2025〕55号） | AK54: 国网办公室 | AL54: 各级单位办公室 | AO54: =A54=[1]员工报账!A54 -> TRUE | AP54: =B54=[1]员工报账!B54 -> TRUE | AQ54: =C54=[1]员工报账!C54 -> TRUE | AR54: =D54=[1]员工报账!D54 -> TRUE | AS54: =E54=[1]员工报账!E54 -> TRUE | AT54: =F54=[1]员工报账!F54 -> TRUE | AU54: =G54=[1]员工报账!G54 -> TRUE | AV54: =H54=[1]员工报账!H54 -> TRUE | ... BX54: =AJ54=[1]员工报账!AJ54 -> TRUE
I55: 员工报账业务-15.会议规模、费用报销-控制措施03 | J55: 财务部门做好报销审核。按照财务业务流程要求，做好报销审核、检查材料完备。 | Q55: √ | R55: √ | T55: 线下管控 | V55: 1.年度会议计划表； 2.计划内会议费用申请表； 3.会议通知、会议议程、参会名单； 4.发票或电子结算单； 5.计划外会议审批表。 | W55: 各级单位-会议承办部门-报账人员、各级单位-会议承办部门-负责人、各级单位-会议管理部门-会议管理人员、各级单位-会议管理部门-负责人、各级单位-财务部门-成本管理人员 | X55: 每季度 | Y55: 抽查 | AA55: 每年 | AB55: 抽查 | AD55: 会议费监督场景 | AE55: 每年 | AF55: 抽查 | AH55: 是 | AI55: 是 | AJ55: 《国家电网有限公司会议管理办法》（国家电网企管〔2025〕267号）第七至十二条、第二十一至二十二条、第二十七至三十二条、第三十四至三十九条等。 《关于做好会议、接待管理相关事项报备报批工作的通知》（办值通〔2025〕55号） | AK55: 国网办公室 | AL55: 各级单位办公室 | AO55: =A55=[1]员工报账!A55 -> TRUE | AP55: =B55=[1]员工报账!B55 -> TRUE | AQ55: =C55=[1]员工报账!C55 -> TRUE | AR55: =D55=[1]员工报账!D55 -> TRUE | AS55: =E55=[1]员工报账!E55 -> TRUE | AT55: =F55=[1]员工报账!F55 -> TRUE | AU55: =G55=[1]员工报账!G55 -> TRUE | AV55: =H55=[1]员工报账!H55 -> TRUE | ... BX55: =AJ55=[1]员工报账!AJ55 -> TRUE
A56: 员工报账 | B56: 二、通用报账 | C56: 资金资产安全 | D56: 办公费管理 | E56: 虚列、套取办公费，引发合规风险。 | G56: 16.办公费使用 | H56: 办公费在规定范围内据实报销。办公费报销中的结算依据充分，完整，有效，结算依据审核轨迹完整。 | I56: 员工报账业务-16.办公费使用-控制措施01 | J56: 归口管理部门对办公费用使用范围进行复核，确保不包含党报党刊费、营销业务电费发票印制费、护肤膏、防晒霜、牙膏、工作服、多功能一体机、打印机、投影仪、礼品、食堂餐座椅等费用，禁止虚列、套取办公费行为。 | L56: √ | M56: √ | O56: √ | T56: 线下管控 | V56: 1.成本费用报销审批单； 2.发票； 3.入库单或到货验收单； 4.购置审批表； 5.采购合同； 6.办公用品领用清单； 7.费用结算清单。 | W56: 各级单位-各部门-报账人员、各级单位-各部门-负责人、各级单位-办公用品管理部门-办公用品管理人员、各级单位-办公用品管理部门-负责人 | X56: 每季度 | Y56: 抽查 | AA56: 每年 | AB56: 抽查 | AD56: 办公费监督场景 | AE56: 每年 | AF56: 抽查 | AH56: 是 | AI56: 是 | AJ56: 《国家电网有限公司会计基础管理办法》（国家电网企管〔2019〕132号）第五十四条 | AK56: 国网后勤部 | AL56: 各级单位办公室 | AO56: =A56=[1]员工报账!A56 -> TRUE | AP56: =B56=[1]员工报账!B56 -> TRUE | AQ56: =C56=[1]员工报账!C56 -> TRUE | AR56: =D56=[1]员工报账!D56 -> TRUE | AS56: =E56=[1]员工报账!E56 -> TRUE | AT56: =F56=[1]员工报账!F56 -> TRUE | AU56: =G56=[1]员工报账!G56 -> TRUE | AV56: =H56=[1]员工报账!H56 -> TRUE | ... BX56: =AJ56=[1]员工报账!AJ56 -> TRUE
I57: 员工报账业务-16.办公费使用-控制措施02 | J57: 财务人员加强规范性审核，对照审批轨迹、费用结算清单、办公用品领用清单复核业务规范性。 | Q57: √ | R57: √ | T57: 线下管控 | V57: 1.成本费用报销审批单； 2.发票； 3.入库单或到货验收单； 4.购置审批表； 5.采购合同； 6.办公用品领用清单； 7.费用结算清单。 | W57: 各级单位-各部门-报账人员、各级单位-各部门-负责人、各级单位-办公用品管理部门-办公用品管理人员、各级单位-办公用品管理部门-负责人、各级单位-财务部门-成本管理人员 | X57: 每季度 | Y57: 抽查 | AA57: 每年 | AB57: 抽查 | AD57: 办公费监督场景 | AE57: 每年 | AF57: 抽查 | AH57: 是 | AI57: 是 | AJ57: 《国家电网有限公司会计基础管理办法》（国家电网企管〔2019〕132号）第五十四条 | AK57: 国网后勤部 | AL57: 各级单位办公室 | AO57: =A57=[1]员工报账!A57 -> TRUE | AP57: =B57=[1]员工报账!B57 -> TRUE | AQ57: =C57=[1]员工报账!C57 -> TRUE | AR57: =D57=[1]员工报账!D57 -> TRUE | AS57: =E57=[1]员工报账!E57 -> TRUE | AT57: =F57=[1]员工报账!F57 -> TRUE | AU57: =G57=[1]员工报账!G57 -> TRUE | AV57: =H57=[1]员工报账!H57 -> TRUE | ... BX57: =AJ57=[1]员工报账!AJ57 -> TRUE
C58: 税务合规 | D58: 办公用品选购 | E58: 办公用品到货商品与采购清单不一致，“私下换货”，引发合规风险。 | G58: 17.办公用品采购、发放 | H58: 办公用品采购、发放规范有序。 | I58: 员工报账业务-17.办公用品采购、发放-控制措施01 | J58: 物资部门对国网商城上架商品与物流信息一致性进行校验，规避换货舞弊行为。 | O58: √ | T58: 线下管控 | V58: 1.办公用品采购申请单； 2.发票； 3.入库单或货物交接单； 4.购置审批表。 | W58: 各级单位-办公用品管理部门-办公用品管理人员、各级单位-办公用品管理部门-负责人、各级单位-物资部门-电商采购执行与监督人员、各级单位-物资部门-负责人 | X58: 每季度 | Y58: 抽查 | AA58: 每年 | AB58: 抽查 | AD58: 办公费列支范围监督场景 | AE58: 每年 | AF58: 抽查 | AH58: 是 | AI58: 是 | AJ58: 《国家电网有限公司零星物资及办公用品选购专区管理细则》（国家电网企管〔2024〕301 号）第二十八条、第二十九条 | AK58: 国网后勤部、国网物资部 | AL58: 各级单位后勤部（办公室）、各级单位物资部 | AO58: =A58=[1]员工报账!A58 -> TRUE | AP58: =B58=[1]员工报账!B58 -> TRUE | AQ58: =C58=[1]员工报账!C58 -> TRUE | AR58: =D58=[1]员工报账!D58 -> TRUE | AS58: =E58=[1]员工报账!E58 -> TRUE | AT58: =F58=[1]员工报账!F58 -> TRUE | AU58: =G58=[1]员工报账!G58 -> TRUE | AV58: =H58=[1]员工报账!H58 -> TRUE | ... BX58: =AJ58=[1]员工报账!AJ58 -> TRUE
I59: 员工报账业务-17.办公用品采购、发放-控制措施02 | J59: 归口管理部门建立需求、审批、选购等关键角色不相容控制，实现权力分散与监督。 | L59: √ | T59: 线下管控 | V59: 1.办公用品采购申请单； 2.发票； 3.入库单或货物交接单； 4.购置审批表。 | W59: 各级单位-办公用品管理部门-办公用品管理人员、各级单位-办公用品管理部门-负责人、各级单位-物资部门-电商采购执行与监督人员、各级单位-物资部门-负责人 | X59: 每季度 | Y59: 抽查 | AA59: 每年 | AB59: 抽查 | AD59: 办公费列支范围监督场景 | AE59: 每年 | AF59: 抽查 | AH59: 是 | AI59: 是 | AJ59: 《国家电网有限公司零星物资及办公用品选购专区管理细则》（国家电网企管〔2024〕301 号）第二十八条、第二十九条 | AK59: 国网后勤部、国网物资部 | AL59: 各级单位后勤部（办公室）、各级单位物资部 | AO59: =A59=[1]员工报账!A59 -> TRUE | AP59: =B59=[1]员工报账!B59 -> TRUE | AQ59: =C59=[1]员工报账!C59 -> TRUE | AR59: =D59=[1]员工报账!D59 -> TRUE | AS59: =E59=[1]员工报账!E59 -> TRUE | AT59: =F59=[1]员工报账!F59 -> TRUE | AU59: =G59=[1]员工报账!G59 -> TRUE | AV59: =H59=[1]员工报账!H59 -> TRUE | ... BX59: =AJ59=[1]员工报账!AJ59 -> TRUE
I60: 员工报账业务-17.办公用品采购、发放-控制措施03 | J60: 物资部门建立办公用品由物资部门和办公用品保管人员共同验收工作机制，双方均在货物交接单据上签字确认。 | O60: √ | R60: √ | T60: 线下管控 | V60: 1.办公用品采购申请单； 2.发票； 3.入库单或货物交接单； 4.购置审批表。 | W60: 各级单位-办公用品管理部门-办公用品管理人员、各级单位-办公用品管理部门-负责人、各级单位-物资部门-电商采购执行与监督人员、各级单位-物资部门-负责人 | X60: 每季度 | Y60: 抽查 | AA60: 每年 | AB60: 抽查 | AD60: 办公费列支范围监督场景 | AE60: 每年 | AF60: 抽查 | AH60: 是 | AI60: 是 | AJ60: 《国家电网有限公司零星物资及办公用品选购专区管理细则》（国家电网企管〔2024〕301 号）第二十八条、第二十九条 | AK60: 国网后勤部、国网物资部 | AL60: 各级单位后勤部（办公室）、各级单位物资部 | AO60: =A60=[1]员工报账!A60 -> TRUE | AP60: =B60=[1]员工报账!B60 -> TRUE | AQ60: =C60=[1]员工报账!C60 -> TRUE | AR60: =D60=[1]员工报账!D60 -> TRUE | AS60: =E60=[1]员工报账!E60 -> TRUE | AT60: =F60=[1]员工报账!F60 -> TRUE | AU60: =G60=[1]员工报账!G60 -> TRUE | AV60: =H60=[1]员工报账!H60 -> TRUE | ... BX60: =AJ60=[1]员工报账!AJ60 -> TRUE
A61: 员工报账 | B61: 二、通用报账 | C61: 税务合规 | D61: 办公用品选购 | E61: 办公用品到货商品与采购清单不一致，“私下换货”，引发合规风险。 | G61: 17.办公用品采购、发放 | H61: 办公用品采购、发放规范有序。 | I61: 员工报账业务-17.办公用品采购、发放-控制措施04 | J61: 办公用品管理部门确保办公用品发放规范有序。 | R61: √ | T61: 线下管控 | V61: 1.办公用品领用清单。 | W61: 各级单位-办公用品管理部门-办公用品管理人员、各级单位-办公用品管理部门-负责人 | X61: 每季度 | Y61: 抽查 | AA61: 每年 | AB61: 抽查 | AD61: 办公费列支范围监督场景 | AE61: 每年 | AF61: 抽查 | AH61: 是 | AI61: 是 | AJ61: 《国家电网有限公司零星物资及办公用品选购专区管理细则》（国家电网企管〔2024〕301 号）第二十八条、第二十九条 | AK61: 国网后勤部 | AL61: 各级单位后勤部（办公室） | AO61: =A61=[1]员工报账!A61 -> TRUE | AP61: =B61=[1]员工报账!B61 -> TRUE | AQ61: =C61=[1]员工报账!C61 -> TRUE | AR61: =D61=[1]员工报账!D61 -> TRUE | AS61: =E61=[1]员工报账!E61 -> TRUE | AT61: =F61=[1]员工报账!F61 -> TRUE | AU61: =G61=[1]员工报账!G61 -> TRUE | AV61: =H61=[1]员工报账!H61 -> TRUE | ... BX61: =AJ61=[1]员工报账!AJ61 -> TRUE
C62: 税务合规 | D62: 党组织工作经费使用 | E62: 超范围、超标准列支党组织工作经费，导致成本不实，引发合规风险。 | G62: 18.党组织工作经费报销 | H62: 党组织工作经费在规定范围内报销。 | I62: 员工报账业务-18.党组织工作经费报销-控制措施01 | J62: 归口管理部门对党组织工作经费清单进行复核，确保费用用于党内开支教育、宣传思想、主题实践活动及党内评选表彰等与党（团）的建设直接相关的工作和活动。 | L62: √ | T62: 线下管控 | V62: 1.成本费用报销审批单； 2.费用明细清单； 3.发票或收据。 | W62: 各级单位-各部门-报账人员、各级单位-各部门-负责人、各级单位-党建部门-负责人 | X62: 每季度 | Y62: 抽查 | AA62: 每年 | AB62: 抽查 | AD62: 党组织工作经列支范围监督场景 | AE62: 每年 | AF62: 抽查 | AH62: 是 | AI62: 是 | AJ62: 《国家电网有限公司党组织工作经费管理办法（试行）》（国家电网党〔2018〕96号）第八条、第九条、第十三条、第十四条 | AK62: 党组党建部 | AL62: 各级单位党建部 | AO62: =A62=[1]员工报账!A62 -> TRUE | AP62: =B62=[1]员工报账!B62 -> TRUE | AQ62: =C62=[1]员工报账!C62 -> TRUE | AR62: =D62=[1]员工报账!D62 -> TRUE | AS62: =E62=[1]员工报账!E62 -> TRUE | AT62: =F62=[1]员工报账!F62 -> TRUE | AU62: =G62=[1]员工报账!G62 -> TRUE | AV62: =H62=[1]员工报账!H62 -> TRUE | ... BX62: =AJ62=[1]员工报账!AJ62 -> TRUE
I63: 员工报账业务-18.党组织工作经费报销-控制措施02 | J63: 财务部门对报销费用超范围开支情况进行校验，严禁列支豪华酒店、度假村等场所费用。 | Q63: √ | R63: √ | T63: 线下管控 | V63: 1.成本费用报销审批单； 2.费用明细清单； 3.发票或收据。 | W63: 各级单位-各部门-报账人员、各级单位-各部门-负责人、各级单位-党建部门-负责人、各级单位-财务部门-成本管理人员 | X63: 每季度 | Y63: 抽查 | AA63: 每年 | AB63: 抽查 | AD63: 党组织工作经列支范围监督场景 | AE63: 每年 | AF63: 抽查 | AH63: 是 | AI63: 是 | AJ63: 《国家电网有限公司党组织工作经费管理办法（试行）》（国家电网党〔2018〕96号）第八条、第九条、第十三条、第十四条 | AK63: 党组党建部 | AL63: 各级单位党建部 | AO63: =A63=[1]员工报账!A63 -> TRUE | AP63: =B63=[1]员工报账!B63 -> TRUE | AQ63: =C63=[1]员工报账!C63 -> TRUE | AR63: =D63=[1]员工报账!D63 -> TRUE | AS63: =E63=[1]员工报账!E63 -> TRUE | AT63: =F63=[1]员工报账!F63 -> TRUE | AU63: =G63=[1]员工报账!G63 -> TRUE | AV63: =H63=[1]员工报账!H63 -> TRUE | ... BX63: =AJ63=[1]员工报账!AJ63 -> TRUE
C64: 税务合规、资金资产安全 | D64: 安全费使用 | E64: 超范围列支安全费，虚列挤占安全专项费用，导致合规风险。 | G64: 19.安全费报销 | H64: 安全费在规定范围内报销。 | I64: 员工报账业务-19.安全费报销-控制措施01 | J64: 实物管理部门规范建立资产卡片，针对使用安全费用形成固定资产、无形资产的规范建立资产卡片，确保相关资产折旧准确计入安全费。 | M64: √ | T64: 系统已建 | U64: ERP | V64: 1.成本费用报销审批单； 2.费用明细清单； 3.发票或收据； 4.建设合同。 | W64: 各级单位-各部门-报账人员、各级单位-各部门-负责人、各级单位-安监部门-消防与安保管理人员、各级单位-安监部门-负责人 | X64: 每季度 | Y64: 抽查 | AA64: 每年 | AB64: 抽查 | AD64: 安全费列支范围监督场景 | AE64: 每年 | AF64: 抽查 | AH64: 是 | AI64: 是 | AJ64: 《国家电网有限公司安全生产费用提取和使用管理办法》（国家电网企管〔2023〕399号）第十条、第十三条、第二十五条 | AK64: 国网安监部 | AL64: 各级单位安监部 | AO64: =A64=[1]员工报账!A64 -> TRUE | AP64: =B64=[1]员工报账!B64 -> TRUE | AQ64: =C64=[1]员工报账!C64 -> TRUE | AR64: =D64=[1]员工报账!D64 -> TRUE | AS64: =E64=[1]员工报账!E64 -> TRUE | AT64: =F64=[1]员工报账!F64 -> TRUE | AU64: =G64=[1]员工报账!G64 -> TRUE | AV64: =H64=[1]员工报账!H64 -> TRUE | ... BX64: =AJ64=[1]员工报账!AJ64 -> TRUE
I65: 员工报账业务-19.安全费报销-控制措施02 | J65: 建设单位及时支付安全费用，应当在合同中单独约定并于工程开工日一个月内向承包单位至少支付 50%安全费用。 | O65: √ | P65: √ | T65: 线下管控 | V65: 1.成本费用报销审批单； 2.费用明细清单； 3.发票或收据； 4.建设合同。 | W65: 各级单位-各部门-报账人员、各级单位-各部门-负责人、各级单位-安监部门-消防与安保管理人员、各级单位-安监部门-负责人 | X65: 每季度 | Y65: 抽查 | AA65: 每年 | AB65: 抽查 | AD65: 安全费列支范围监督场景 | AE65: 每年 | AF65: 抽查 | AH65: 是 | AI65: 是 | AJ65: 《国家电网有限公司安全生产费用提取和使用管理办法》（国家电网企管〔2023〕399号）第十条、第十三条、第二十条、第二十五条 | AK65: 国网安监部 | AL65: 各级单位安监部 | AO65: =A65=[1]员工报账!A65 -> TRUE | AP65: =B65=[1]员工报账!B65 -> TRUE | AQ65: =C65=[1]员工报账!C65 -> TRUE | AR65: =D65=[1]员工报账!D65 -> TRUE | AS65: =E65=[1]员工报账!E65 -> TRUE | AT65: =F65=[1]员工报账!F65 -> TRUE | AU65: =G65=[1]员工报账!G65 -> TRUE | AV65: =H65=[1]员工报账!H65 -> TRUE | ... BX65: =AJ65=[1]员工报账!AJ65 -> TRUE
I66: 员工报账业务-19.安全费报销-控制措施03 | J66: 总包单位及时支付安全费用，总包单位应当在合同中单独约定并于分包工程开工日一个月内将至少50%安全费用直接支付分包单位并监督使用，分包单位不再重复提取。 | O66: √ | P66: √ | T66: 线下管控 | V66: 1.成本费用报销审批单； 2.费用明细清单； 3.发票或收据； 4.建设合同。 | W66: 各级单位-各部门-报账人员、各级单位-各部门-负责人、各级单位-安监部门-消防与安保管理人员、各级单位-安监部门-负责人 | X66: 每季度 | Y66: 抽查 | AA66: 每年 | AB66: 抽查 | AD66: 安全费列支范围监督场景 | AE66: 每年 | AF66: 抽查 | AH66: 是 | AI66: 是 | AJ66: 《国家电网有限公司安全生产费用提取和使用管理办法》（国家电网企管〔2023〕399号）第十条、第十三条、第二十条、第二十五条 | AK66: 国网安监部 | AL66: 各级单位安监部 | AO66: =A66=[1]员工报账!A66 -> TRUE | AP66: =B66=[1]员工报账!B66 -> TRUE | AQ66: =C66=[1]员工报账!C66 -> TRUE | AR66: =D66=[1]员工报账!D66 -> TRUE | AS66: =E66=[1]员工报账!E66 -> TRUE | AT66: =F66=[1]员工报账!F66 -> TRUE | AU66: =G66=[1]员工报账!G66 -> TRUE | AV66: =H66=[1]员工报账!H66 -> TRUE | ... BX66: =AJ66=[1]员工报账!AJ66 -> TRUE
A67: 员工报账 | B67: 二、通用报账 | C67: 税务合规、资金资产安全 | D67: 安全费使用 | E67: 超范围列支安全费，虚列挤占安全专项费用，导致合规风险。 | G67: 19.安全费报销 | H67: 安全费在规定范围内报销。 | I67: 员工报账业务-19.安全费报销-控制措施04 | J67: 归口管理部门对安全工器具领用、保管进行监督，确保不发生安全工器具过期等问题。 | R67: √ | T67: 线下管控 系统已建 | U67: 安全风险管控监督平台 | V67: 1.成本费用报销审批单； 2.费用明细清单； 3.发票或收据； 4.建设合同。 | W67: 各级单位-各部门-报账人员、各级单位-各部门-负责人、各级单位-安监部门-消防与安保管理人员、各级单位-安监部门-负责人 | X67: 每季度 | Y67: 抽查 | AA67: 每年 | AB67: 抽查 | AD67: 安全费列支范围监督场景 | AE67: 每年 | AF67: 抽查 | AH67: 是 | AI67: 是 | AJ67: 《国家电网有限公司安全生产费用提取和使用管理办法》（国家电网企管〔2023〕399号）第十条、第十三条、第二十五条 | AK67: 国网安监部 | AL67: 各级单位安监部 | AN67: 修改控制方式，修改控制载体 | AO67: =A67=[1]员工报账!A67 -> TRUE | AP67: =B67=[1]员工报账!B67 -> TRUE | AQ67: =C67=[1]员工报账!C67 -> TRUE | AR67: =D67=[1]员工报账!D67 -> TRUE | AS67: =E67=[1]员工报账!E67 -> TRUE | AT67: =F67=[1]员工报账!F67 -> TRUE | AU67: =G67=[1]员工报账!G67 -> TRUE | AV67: =H67=[1]员工报账!H67 -> TRUE | ... BX67: =AJ67=[1]员工报账!AJ67 -> TRUE
I68: 员工报账业务-19.安全费报销-控制措施05 | J68: 财务部门对安全费列支情况进行复核，禁止列支职工薪酬福利、治安服务费等无关费用。 | M68: √ | P68: √ | Q68: √ | T68: 线下管控 | V68: 1.成本费用报销审批单； 2.费用明细清单； 3.发票或收据； 4.建设合同。 | W68: 各级单位-各部门-报账人员、各级单位-各部门-负责人、各级单位-安监部门-消防与安保管理人员、各级单位-安监部门-负责人、各级单位-财务部门-成本管理人员 | X68: 每季度 | Y68: 抽查 | AA68: 每年 | AB68: 抽查 | AD68: 安全费列支范围监督场景 | AE68: 每年 | AF68: 抽查 | AH68: 是 | AI68: 是 | AJ68: 《国家电网有限公司安全生产费用提取和使用管理办法》（国家电网企管〔2023〕399号）第十条、第十三条、第二十五条 | AK68: 国网安监部 | AL68: 各级单位安监部 | AO68: =A68=[1]员工报账!A68 -> TRUE | AP68: =B68=[1]员工报账!B68 -> TRUE | AQ68: =C68=[1]员工报账!C68 -> TRUE | AR68: =D68=[1]员工报账!D68 -> TRUE | AS68: =E68=[1]员工报账!E68 -> TRUE | AT68: =F68=[1]员工报账!F68 -> TRUE | AU68: =G68=[1]员工报账!G68 -> TRUE | AV68: =H68=[1]员工报账!H68 -> TRUE | ... BX68: =AJ68=[1]员工报账!AJ68 -> TRUE
A69: 员工报账 | B69: 二、通用报账 | C69: 税务合规、资金资产安全 | D69: 青苗赔偿现场核定 | E69: 与现场标准、数量不一致导致青苗赔偿有误，造成青苗赔偿费重复计、多付。 | G69: 21.现场青苗赔偿类型、数量的确定 | H69: 青苗赔付类型、数量与现场一致。 | I69: 员工报账业务-21.现场青苗赔偿类型、数量的确定-控制措施01 | J69: 归口管理部门对赔偿真实性进行复核，确保进行了三方（赔偿方、受偿方、监理或基层组织）现场联合勘测清点并签字确认。 | L69: √ | O69: √ | R69: √ | T69: 线下管控 | V69: 1.用地批复文件； 2.地方补偿标准文件； 3.联合现场勘测记录； 4.地上附着物和青苗调查登记表、补偿结果确认表； 5.被补偿人身份证明； 6.青苗及地上附着物权属证明； 7.青苗补偿协议。 | W69: 各级单位-各部门-报账人员、各级单位-各部门-负责人、各级单位-归口管理部门-负责人 | X69: 每季度 | Y69: 抽查 | AA69: 每年 | AB69: 抽查 | AD69: 青苗赔偿费监督场景 | AE69: 每年 | AF69: 抽查 | AH69: 是 | AI69: 是 | AJ69: 《国家电网有限公司会计基础管理办法》（国家电网企管〔2019〕132号）附件：电网企业经济业务审核手册 | AK69: 国网财务部 | AL69: 各级单位财务部 | AO69: =A69=[1]员工报账!A73 -> TRUE | AP69: =B69=[1]员工报账!B73 -> TRUE | AQ69: =C69=[1]员工报账!C73 -> TRUE | AR69: =D69=[1]员工报账!D73 -> TRUE | AS69: =E69=[1]员工报账!E73 -> TRUE | AT69: =F69=[1]员工报账!F73 -> TRUE | AU69: =G69=[1]员工报账!G73 -> TRUE | AV69: =H69=[1]员工报账!H73 -> TRUE | ... BX69: =AJ69=[1]员工报账!AJ73 -> TRUE
I70: 员工报账业务-21.现场青苗赔偿类型、数量的确定-控制措施02 | J70: 归口管理部门对补偿协仪进行复核，确保协议包括标的物位置、权属、地类、面积、附着物种类与数量等关键信息。 | M70: √ | O70: √ | T70: 线下管控 | V70: 1.用地批复文件； 2.地方补偿标准文件； 3.联合现场勘测记录； 4.地上附着物和青苗调查登记表、补偿结果确认表； 5.被补偿人身份证明； 6.青苗及地上附着物权属证明； 7.青苗补偿协议。 | W70: 各级单位-各部门-报账人员、各级单位-各部门-负责人、各级单位-归口管理部门-负责人 | X70: 每季度 | Y70: 抽查 | AA70: 每年 | AB70: 抽查 | AD70: 青苗赔偿费监督场景 | AE70: 每年 | AF70: 抽查 | AH70: 是 | AI70: 是 | AJ70: 《国家电网有限公司会计基础管理办法》（国家电网企管〔2019〕132号）附件：电网企业经济业务审核手册 | AK70: 国网财务部 | AL70: 各级单位财务部 | AO70: =A70=[1]员工报账!A74 -> TRUE | AP70: =B70=[1]员工报账!B74 -> TRUE | AQ70: =C70=[1]员工报账!C74 -> TRUE | AR70: =D70=[1]员工报账!D74 -> TRUE | AS70: =E70=[1]员工报账!E74 -> TRUE | AT70: =F70=[1]员工报账!F74 -> TRUE | AU70: =G70=[1]员工报账!G74 -> TRUE | AV70: =H70=[1]员工报账!H74 -> TRUE | ... BX70: =AJ70=[1]员工报账!AJ74 -> TRUE
I71: 员工报账业务-21.现场青苗赔偿类型、数量的确定-控制措施03 | J71: 财务部门对赔偿单价与地方政府指导标准进行校验。 | Q71: √ | R71: √ | T71: 线下管控 | V71: 1.用地批复文件； 2.地方补偿标准文件； 3.联合现场勘测记录； 4.地上附着物和青苗调查登记表、补偿结果确认表； 5.被补偿人身份证明； 6.青苗及地上附着物权属证明； 7.青苗补偿协议。 | W71: 各级单位-各部门-报账人员、各级单位-各部门-负责人、各级单位-归口管理部门-负责人、各级单位-财务部门-工程财务管理人员 | X71: 每季度 | Y71: 抽查 | AA71: 每年 | AB71: 抽查 | AD71: 青苗赔偿费监督场景 | AE71: 每年 | AF71: 抽查 | AH71: 是 | AI71: 是 | AJ71: 《国家电网有限公司会计基础管理办法》（国家电网企管〔2019〕132号）附件：电网企业经济业务审核手册 | AK71: 国网财务部 | AL71: 各级单位财务部 | AO71: =A71=[1]员工报账!A75 -> TRUE | AP71: =B71=[1]员工报账!B75 -> TRUE | AQ71: =C71=[1]员工报账!C75 -> TRUE | AR71: =D71=[1]员工报账!D75 -> TRUE | AS71: =E71=[1]员工报账!E75 -> TRUE | AT71: =F71=[1]员工报账!F75 -> TRUE | AU71: =G71=[1]员工报账!G75 -> TRUE | AV71: =H71=[1]员工报账!H75 -> TRUE | ... BX71: =AJ71=[1]员工报账!AJ75 -> TRUE
C72: 税务合规 | D72: 青苗赔偿资金申 请支付 | E72: 与赔付人实际不一致，虚列套取资金，造成青苗赔偿费多付、错付。 | G72: 22.青苗赔偿支付对象的确定 | H72: 青苗赔付资金支付对象与现场一致。 | I72: 员工报账业务-22.青苗赔偿支付对象的确定-控制措施01 | J72: 归口管理部门对资金支付与补偿协议支付条款进行校验。 | O72: √ | P72: √ | T72: 线下管控 | V72: 1.用地批复文件； 2.地方补偿标准文件； 3.联合现场勘测记录； 4.地上附着物和青苗调查登记表、补偿结果确认表； 5.被补偿人身份证明； 6.青苗及地上附着物权属证明； 7.青苗补偿协议。 | W72: 各级单位-各部门-报账人员、各级单位-各部门-负责人、各级单位-归口管理部门-负责人 | X72: 每季度 | Y72: 抽查 | AA72: 每年 | AB72: 抽查 | AD72: 青苗赔偿费监督场景 | AE72: 每年 | AF72: 抽查 | AH72: 是 | AI72: 是 | AJ72: 《国家电网有限公司会计基础管理办法》（国家电网企管〔2019〕132号）附件：电网企业经济业务审核手册 | AK72: 国网财务部 | AL72: 各级单位财务部 | AO72: =A72=[1]员工报账!A76 -> TRUE | AP72: =B72=[1]员工报账!B76 -> TRUE | AQ72: =C72=[1]员工报账!C76 -> TRUE | AR72: =D72=[1]员工报账!D76 -> TRUE | AS72: =E72=[1]员工报账!E76 -> TRUE | AT72: =F72=[1]员工报账!F76 -> TRUE | AU72: =G72=[1]员工报账!G76 -> TRUE | AV72: =H72=[1]员工报账!H76 -> TRUE | ... BX72: =AJ72=[1]员工报账!AJ76 -> TRUE
I73: 员工报账业务-22.青苗赔偿支付对象的确定-控制措施02 | J73: 财务部门对赔偿资金安全、足额、直达权利人情况进行复核。 | P73: √ | R73: √ | T73: 线下管控 | V73: 1.用地批复文件； 2.地方补偿标准文件； 3.联合现场勘测记录； 4.地上附着物和青苗调查登记表、补偿结果确认表； 5.被补偿人身份证明； 6.青苗及地上附着物权属证明； 7.青苗补偿协议。 | W73: 各级单位-各部门-报账人员、各级单位-各部门-负责人、各级单位-归口管理部门-负责人、各级单位-财务部门-工程财务管理人员 | X73: 每季度 | Y73: 抽查 | AA73: 每年 | AB73: 抽查 | AD73: 青苗赔偿费监督场景 | AE73: 每年 | AF73: 抽查 | AH73: 是 | AI73: 是 | AJ73: 《国家电网有限公司会计基础管理办法》（国家电网企管〔2019〕132号）附件：电网企业经济业务审核手册 | AK73: 国网财务部 | AL73: 各级单位财务部 | AO73: =A73=[1]员工报账!A77 -> TRUE | AP73: =B73=[1]员工报账!B77 -> TRUE | AQ73: =C73=[1]员工报账!C77 -> TRUE | AR73: =D73=[1]员工报账!D77 -> TRUE | AS73: =E73=[1]员工报账!E77 -> TRUE | AT73: =F73=[1]员工报账!F77 -> TRUE | AU73: =G73=[1]员工报账!G77 -> TRUE | AV73: =H73=[1]员工报账!H77 -> TRUE | ... BX73: =AJ73=[1]员工报账!AJ77 -> TRUE
A74: 员工报账 | B74: 二、通用报账 | C74: 税务合规、资金资产安全 | D74: 资金支付 | E74: 未按合同约定付款、无预算、超越权限办理支付审批业务，引发资金安全风险。 | F74: 06.债权债务清理不及时：存在应收账款长期未收回、应收款项核销依据不充分、客户工程款清理不及时，存在潜亏风险、长期应付款未及时清理、款项未及时结算形成隐性债权债务等问题。 04.超期未支付民营及中小企业款项：存在未按规定及时清理民营及中小企业应付款项；经营指标不真实，存在隐性债务；项目已完工未签合同、未及时结算、未按时入账、未开票等；以资金困难、存在纠纷、转包分包等不正当理由延期支付工程款；合同设置不合理支付条款等问题。 | G74: 23.资金支付管理 | H74: 资金支付规范安全。 | I74: 员工报账业务-23.资金支付管理-控制措施01 | J74: 资金支付发起部门对资金支付与合同约定付款条款进行复核。 | M74: √ | O74: √ | T74: 线下管控 | V74: 1.到货验收单； 2.费用明细清单； 3.发票或收据； 4.合同或协议； 5.付款申请单。 | W74: 各级单位-资金支付发起部门-报账人员、各级单位-资金支付发起部门-负责人、各级单位-财务部门-成本管理人员、各级单位-财务部门-资金管理人员、各级单位-财务部门-负责人 | X74: 每季度 | Y74: 抽查 | AA74: 每年 | AB74: 抽查 | AD74: 资金支付管理监督场景 | AE74: 每年 | AF74: 抽查 | AH74: 是 | AI74: 是 | AJ74: 《保障中小企业款项支付条例》第九条、第十条 《国家电网有限公司合同管理办法》（国家电网企管〔2020〕832号）第四十六条 《国家电网有限公司会计基础管理办法》（国家电网企管〔2019〕132号）第五十四条 《关于加强中央企业资金内部控制管理有关事项的通知》（国资发监督〔2021〕19 号）第十三条 | AK74: 国网财务部 | AL74: 各级单位财务部 | AO74: =A74=[1]员工报账!A78 -> TRUE | AP74: =B74=[1]员工报账!B78 -> TRUE | AQ74: =C74=[1]员工报账!C78 -> TRUE | AR74: =D74=[1]员工报账!D78 -> TRUE | AS74: =E74=[1]员工报账!E78 -> TRUE | AT74: =F74=[1]员工报账!F78 -> TRUE | AU74: =G74=[1]员工报账!G78 -> TRUE | AV74: =H74=[1]员工报账!H78 -> TRUE | ... BX74: =AJ74=[1]员工报账!AJ78 -> TRUE
I75: 员工报账业务-23.资金支付管理-控制措施02 | J75: 资金支付发起部门对付款信息与合同约定进行校验，确保使用合同约定账户支付。 | O75: √ | P75: √ | T75: 线下管控 | V75: 1.到货验收单； 2.费用明细清单； 3.发票或收据； 4.合同或协议； 5.付款申请单。 | W75: 各级单位-资金支付发起部门-报账人员、各级单位-资金支付发起部门-负责人、各级单位-财务部门-成本管理人员、各级单位-财务部门-资金管理人员、各级单位-财务部门-负责人 | X75: 每季度 | Y75: 抽查 | AA75: 每年 | AB75: 抽查 | AD75: 资金支付管理监督场景 | AE75: 每年 | AF75: 抽查 | AH75: 是 | AI75: 是 | AJ75: 《保障中小企业款项支付条例》第九条、第十条 《国家电网有限公司合同管理办法》（国家电网企管〔2020〕832号）第四十六条 《国家电网有限公司会计基础管理办法》（国家电网企管〔2019〕132号）第五十四条 《关于加强中央企业资金内部控制管理有关事项的通知》（国资发监督〔2021〕19 号）第十三条 | AK75: 国网财务部 | AL75: 各级单位财务部 | AO75: =A75=[1]员工报账!A79 -> TRUE | AP75: =B75=[1]员工报账!B79 -> TRUE | AQ75: =C75=[1]员工报账!C79 -> TRUE | AR75: =D75=[1]员工报账!D79 -> TRUE | AS75: =E75=[1]员工报账!E79 -> TRUE | AT75: =F75=[1]员工报账!F79 -> TRUE | AU75: =G75=[1]员工报账!G79 -> TRUE | AV75: =H75=[1]员工报账!H79 -> TRUE | ... BX75: =AJ75=[1]员工报账!AJ79 -> TRUE
I76: 员工报账业务-23.资金支付管理-控制措施03 | J76: 财务部门对资金分级授权审批流程和预算批准的付款额度进行复核，确认无误后进行付款。 | K76: √ | L76: √ | Q76: √ | T76: 系统已建 | U76: 智慧共享财务平台 | V76: 1.到货验收单； 2.费用明细清单； 3.发票或收据； 4.合同或协议； 5.付款申请单。 | W76: 各级单位-资金支付发起部门-报账人员、各级单位-资金支付发起部门-负责人、各级单位-财务部门-成本管理人员、各级单位-财务部门-资金管理人员、各级单位-财务部门-负责人 | X76: 每季度 | Y76: 抽查 | AA76: 每年 | AB76: 抽查 | AD76: 资金支付管理监督场景 | AE76: 每年 | AF76: 抽查 | AH76: 是 | AI76: 是 | AJ76: 《保障中小企业款项支付条例》第九条、第十条 《国家电网有限公司合同管理办法》（国家电网企管〔2020〕832号）第四十六条 《国家电网有限公司会计基础管理办法》（国家电网企管〔2019〕132号）第五十四条 《关于加强中央企业资金内部控制管理有关事项的通知》（国资发监督〔2021〕19 号）第十三条 | AK76: 国网财务部 | AL76: 各级单位财务部 | AO76: =A76=[1]员工报账!A80 -> TRUE | AP76: =B76=[1]员工报账!B80 -> TRUE | AQ76: =C76=[1]员工报账!C80 -> TRUE | AR76: =D76=[1]员工报账!D80 -> TRUE | AS76: =E76=[1]员工报账!E80 -> TRUE | AT76: =F76=[1]员工报账!F80 -> TRUE | AU76: =G76=[1]员工报账!G80 -> TRUE | AV76: =H76=[1]员工报账!H80 -> TRUE | ... BX76: =AJ76=[1]员工报账!AJ80 -> TRUE
I77: 员工报账业务-23.资金支付管理-控制措施04 | J77: 财务部门对未履行“三重一大”决策程序和联签制度等特殊支付事项进行复核，禁止出现化整为零规避大额资金支付集体决策程序等问题。 | L77: √ | P77: √ | Q77: √ | T77: 线下管控 | V77: 1.到货验收单； 2.费用明细清单； 3.发票或收据； 4.合同或协议； 5.付款申请单。 | W77: 各级单位-资金支付发起部门-报账人员、各级单位-资金支付发起部门-负责人、各级单位-财务部门-成本管理人员、各级单位-财务部门-资金管理人员、各级单位-财务部门-负责人 | X77: 每季度 | Y77: 抽查 | AA77: 每年 | AB77: 抽查 | AD77: 资金支付管理监督场景 | AE77: 每年 | AF77: 抽查 | AH77: 是 | AI77: 是 | AJ77: 《保障中小企业款项支付条例》第九条、第十条 《国家电网有限公司合同管理办法》（国家电网企管〔2020〕832号）第四十六条 《国家电网有限公司会计基础管理办法》（国家电网企管〔2019〕132号）第五十四条 《关于加强中央企业资金内部控制管理有关事项的通知》（国资发监督〔2021〕19 号）第十三条 | AK77: 国网财务部 | AL77: 各级单位财务部 | AO77: =A77=[1]员工报账!A81 -> TRUE | AP77: =B77=[1]员工报账!B81 -> TRUE | AQ77: =C77=[1]员工报账!C81 -> TRUE | AR77: =D77=[1]员工报账!D81 -> TRUE | AS77: =E77=[1]员工报账!E81 -> TRUE | AT77: =F77=[1]员工报账!F81 -> TRUE | AU77: =G77=[1]员工报账!G81 -> TRUE | AV77: =H77=[1]员工报账!H81 -> TRUE | ... BX77: =AJ77=[1]员工报账!AJ81 -> TRUE
I78: 员工报账业务-23.资金支付管理-控制措施05 | J78: 财务部门对大额资金对私支付进行校验，严控大额资金对私支付问题发生。 | M78: √ | P78: √ | Q78: √ | T78: 线下管控 | V78: 1.到货验收单； 2.费用明细清单； 3.发票或收据； 4.合同或协议； 5.付款申请单。 | W78: 各级单位-资金支付发起部门-报账人员、各级单位-资金支付发起部门-负责人、各级单位-财务部门-成本管理人员、各级单位-财务部门-资金管理人员、各级单位-财务部门-负责人 | X78: 每季度 | Y78: 抽查 | AA78: 每年 | AB78: 抽查 | AD78: 资金支付管理监督场景 | AE78: 每年 | AF78: 抽查 | AH78: 是 | AI78: 是 | AJ78: 《保障中小企业款项支付条例》第九条、第十条 《国家电网有限公司合同管理办法》（国家电网企管〔2020〕832号）第四十六条 《国家电网有限公司会计基础管理办法》（国家电网企管〔2019〕132号）第五十四条 《关于加强中央企业资金内部控制管理有关事项的通知》（国资发监督〔2021〕19 号）第十三条 | AK78: 国网财务部 | AL78: 各级单位财务部 | AO78: =A78=[1]员工报账!A82 -> TRUE | AP78: =B78=[1]员工报账!B82 -> TRUE | AQ78: =C78=[1]员工报账!C82 -> TRUE | AR78: =D78=[1]员工报账!D82 -> TRUE | AS78: =E78=[1]员工报账!E82 -> TRUE | AT78: =F78=[1]员工报账!F82 -> TRUE | AU78: =G78=[1]员工报账!G82 -> TRUE | AV78: =H78=[1]员工报账!H82 -> TRUE | ... BX78: =AJ78=[1]员工报账!AJ82 -> TRUE
A79: 员工报账 | C79: 税务合规 | D79: 管理咨询费使用 | E79: 超范围列支管理咨询费引发引发合规风险。 | G79: 24.管理咨询费报销 | H79: 管理咨询费在规定范围内报销。 | I79: 员工报账业务-24.管理咨询费报销-控制措施01 | J79: 归口管理部门对管理咨询费进行复核，不得用于电网规划研究、工程前期咨询、信息系统建设等技术咨询与开发，不得用于法律、税务、审计、会计等常规性的中介机构服务开支。 | L79: √ | T79: 线下管控 | V79: 1.成本费用报销审批单； 2.费用明细清单； 3.发票或收据； 4.合同或协议。 | W79: 各级单位-各部门-报账人员、各级单位-各部门-负责人、各级单位-办公室-负责人 | X79: 每季度 | Y79: 抽查 | AA79: 每年 | AB79: 抽查 | AD79: 管理咨询费列支范围监督场景 | AE79: 每年 | AF79: 抽查 | AH79: 是 | AI79: 是 | AJ79: 国家电网公司管理咨询项目管理办法》第二条、第十五条 | AK79: 国网办公室 | AL79: 各级单位办公室 | AO79: =A79=[1]员工报账!A83 -> TRUE | AP79: =B79=[1]员工报账!B83 -> TRUE | AQ79: =C79=[1]员工报账!C83 -> TRUE | AR79: =D79=[1]员工报账!D83 -> TRUE | AS79: =E79=[1]员工报账!E83 -> TRUE | AT79: =F79=[1]员工报账!F83 -> TRUE | AU79: =G79=[1]员工报账!G83 -> TRUE | AV79: =H79=[1]员工报账!H83 -> TRUE | ... BX79: =AJ79=[1]员工报账!AJ83 -> TRUE
I80: 员工报账业务-24.管理咨询费报销-控制措施02 | J80: 规范管理咨询费列支间接费用和支付进度。项目经费需至少分两次进行支付，两次支付时，最后一笔经费支出不得低于合同总额的30%；三次及以上支付时，最后一笔经费支出不得低于合同总额的10%。 | Q80: √ | R80: √ | T80: 线下管控 | V80: 1.付款申请单； 2.合同或协议。 | W80: 各级单位-各部门-报账人员、各级单位-各部门-负责人、各级单位-办公室-负责人、各级单位-财务部门-成本管理人员 | X80: 每季度 | Y80: 抽查 | AA80: 每年 | AB80: 抽查 | AD80: 管理咨询费列支范围监督场景 | AE80: 每年 | AF80: 抽查 | AH80: 是 | AI80: 是 | AJ80: 《国家电网公司管理咨询项目管理办法》第十四条、第三十八条 | AK80: 国网办公室 | AL80: 各级单位办公室 | AO80: =A80=[1]员工报账!A84 -> TRUE | AP80: =B80=[1]员工报账!B84 -> TRUE | AQ80: =C80=[1]员工报账!C84 -> TRUE | AR80: =D80=[1]员工报账!D84 -> TRUE | AS80: =E80=[1]员工报账!E84 -> TRUE | AT80: =F80=[1]员工报账!F84 -> TRUE | AU80: =G80=[1]员工报账!G84 -> TRUE | AV80: =H80=[1]员工报账!H84 -> TRUE | ... BX80: =AJ80=[1]员工报账!AJ84 -> TRUE
A81: 员工报账 | B81: 二、通用报账 | C81: 税务合规、成本精益管理 | D81: 生产车辆使用费管理 | E81: 各单位生产用车较多，车辆使用费存在管控不严，通过伪造票据、虚报里程、费用等方式套取企业资金，导致企业成本虚增、资金流失风险。 | F81: 生产用车管控不严：“一车一卡”加油落实不到位，造成平均油耗异常，在车辆维修等费用中虚列名目、处理其他无关费用或费用依据不足。 | G81: 25.生产车辆使用费管控 | H81: 费用管控，车费使用费按单车实行台账管理，加强车辆燃油、充电、修理费用管控，节约成本费用，防范廉政风险。 | I81: 员工报账业务-25.生产车辆使用费管控-控制措施01 | J81: 生产车辆加油执行“一车一卡”，一张油卡固定一个车牌号码。 | M81: √ | R81: √ | T81: 线下管控 | V81: 1.加油卡； 2.车辆百公里油耗定额表 | W81: 各级单位-后勤部门（生产用车管理部门）-车辆管理人员 | X81: 每季度 | Y81: 抽查 | AA81: 每年 | AB81: 抽查 | AH81: 是 | AI81: 是 | AL81: 各级单位后勤部（生产用车管理部门） | AN81: 新增关键控制点“生产车辆使用费管控” | AO81: =A81=[1]员工报账!A85 -> FALSE | AP81: =B81=[1]员工报账!B85 -> FALSE | AQ81: =C81=[1]员工报账!C85 -> FALSE | AR81: =D81=[1]员工报账!D85 -> FALSE | AS81: =E81=[1]员工报账!E85 -> FALSE | AT81: =F81=[1]员工报账!F85 -> FALSE | AU81: =G81=[1]员工报账!G85 -> FALSE | AV81: =H81=[1]员工报账!H85 -> FALSE | ... BX81: =AJ81=[1]员工报账!AJ85 -> TRUE
I82: 员工报账业务-25.生产车辆使用费管控-控制措施02 | J82: 各单位车辆运行管理部门应加强车辆维修真实性控制，按照维修申请、审批、验收结算分离原则控制车辆维修。 | K82: √ | M82: √ | T82: 线下管控 | V82: 1.车辆维保合同； 2.车辆维修与保养通知单； | W82: 各级单位-后勤部门（生产用车管理部门）-车辆管理人员、各级单位-后勤部门（生产用车管理部门）-负责人、各级单位-财务部门-成本管理人员 | X82: 每季度 | Y82: 抽查 | AA82: 每年 | AB82: 抽查 | AH82: 是 | AI82: 是 | AL82: 各级单位后勤部（生产用车管理部门） | AN82: 新增关键控制点“生产车辆使用费管控” | AO82: =A82=[1]员工报账!A86 -> TRUE | AP82: =B82=[1]员工报账!B86 -> TRUE | AQ82: =C82=[1]员工报账!C86 -> TRUE | AR82: =D82=[1]员工报账!D86 -> TRUE | AS82: =E82=[1]员工报账!E86 -> TRUE | AT82: =F82=[1]员工报账!F86 -> TRUE | AU82: =G82=[1]员工报账!G86 -> TRUE | AV82: =H82=[1]员工报账!H86 -> TRUE | ... BX82: =AJ82=[1]员工报账!AJ86 -> TRUE
I83: 员工报账业务-25.生产车辆使用费管控-控制措施03 | J83: 各单位车辆运行管理部门应加强车辆使用费台账管理，对单车费用明细（油费、过路费、停车费、维修费等）与用车申请单（事前提交，注明用车时间、事由、目的地）、车辆行驶里程记录（行车记录、起止日期）进行复核，严禁套取费用。 | M83: √ | T83: 线下管控 | V83: 1.车辆维保合同； 2.生产车辆使用费管理台账 | W83: 各级单位-后勤部门（生产用车管理部门）-车辆管理人员、各级单位-后勤部门（生产用车管理部门）-负责人、各级单位-财务部门-成本管理人员 | X83: 每季度 | Y83: 抽查 | AA83: 每年 | AB83: 抽查 | AH83: 是 | AI83: 是 | AJ83: 国网湖南省电力有限公司关于印发《生产服务用车管理实施细则》的通知（湘电公司设备〔2025〕372号） | AL83: 各级单位后勤部（生产用车管理部门） | AN83: 新增关键控制点“生产车辆使用费管控” | AO83: =A83=[1]员工报账!A87 -> TRUE | AP83: =B83=[1]员工报账!B87 -> TRUE | AQ83: =C83=[1]员工报账!C87 -> TRUE | AR83: =D83=[1]员工报账!D87 -> TRUE | AS83: =E83=[1]员工报账!E87 -> TRUE | AT83: =F83=[1]员工报账!F87 -> TRUE | AU83: =G83=[1]员工报账!G87 -> TRUE | AV83: =H83=[1]员工报账!H87 -> TRUE | ... BX83: =AJ83=[1]员工报账!AJ87 -> FALSE
I84: 员工报账业务-25.生产车辆使用费管控-控制措施04 | J84: 各单位财务部门应严格审核车辆使用费用各类发票与明细清单的一致性、审核合同折扣率、合同税率的执行情况，车辆保险费应归口核算至财产保险费。 | N84: √ | Q84: √ | T84: 线下管控 | V84: 1.车辆维保合同； 2.车辆维修与保养通知单； 3.车辆维修费用清单； 4.加油清单； 5.发票 | W84: 各级单位-后勤部门（生产用车管理部门）-车辆管理人员、各级单位-后勤部门（生产用车管理部门）-负责人、各级单位-财务部门-成本管理人员、各级单位-财务部门-成本管理人员 | X84: 每季度 | Y84: 抽查 | AA84: 每年 | AB84: 抽查 | AH84: 是 | AI84: 是 | AJ84: 国网湖南电力财务部关于印发支出类经济业务财务报销审核指引的通知（财〔2022〕22 号） | AL84: 各级单位后勤部（生产用车管理部门） | AN84: 新增关键控制点“生产车辆使用费管控” | AO84: =A84=[1]员工报账!A88 -> TRUE | AP84: =B84=[1]员工报账!B88 -> TRUE | AQ84: =C84=[1]员工报账!C88 -> TRUE | AR84: =D84=[1]员工报账!D88 -> TRUE | AS84: =E84=[1]员工报账!E88 -> TRUE | AT84: =F84=[1]员工报账!F88 -> TRUE | AU84: =G84=[1]员工报账!G88 -> TRUE | AV84: =H84=[1]员工报账!H88 -> TRUE | ... BX84: =AJ84=[1]员工报账!AJ88 -> FALSE
A85: 员工报账 | B85: 二、通用报账 | C85: 税务合规、降本增效 | D85: 零星租车与运输服务 | E85: 零星租车不规范，存在虚列套取风险。 | F85: 1.零星租车管控不严在自有车辆充足的情况下仍然租赁外部车辆。 2.报销环节存在重复报销，虚假报销套取费用。 | G85: 26.零星租车与运输服务报销 | H85: 后勤管理部门加强零星租车管控，自有车辆充足的情况下不允许租用外部车辆。 | I85: 员工报账业务-26.零星租车与运输服务报销-控制措施01 | J85: 零星车辆租赁（运输服务）需求，按照就近响应、统筹优化原则，实施车辆运输服务框架采购。 | O85: √ | T85: 线下管控 | V85: 1.零星租车合同； 2.租用车辆行驶证、驾驶证； | W85: 各级单位-后勤管理部门-车辆管理人员 | X85: 每季度 | Y85: 抽查 | AA85: 每年 | AB85: 抽查 | AH85: 是 | AI85: 是 | AJ85: 国网湖南省电力有限公司关于印发《国网湖南省电力有限公司车辆租赁及车辆运输服务管理办法》的通知（湘电公司后勤〔2025〕356 号）第二十五条 | AL85: 各级单位后勤部 | AN85: 新增关键控制点“零星租车与运输服务报销” | AO85: =A85=[1]员工报账!A89 -> FALSE | AP85: =B85=[1]员工报账!B89 -> FALSE | AQ85: =C85=[1]员工报账!C89 -> FALSE | AR85: =D85=[1]员工报账!D89 -> FALSE | AS85: =E85=[1]员工报账!E89 -> FALSE | AT85: =F85=[1]员工报账!F89 -> FALSE | AU85: =G85=[1]员工报账!G89 -> FALSE | AV85: =H85=[1]员工报账!H89 -> FALSE | ... BX85: =AJ85=[1]员工报账!AJ89 -> FALSE
I86: 员工报账业务-26.零星租车与运输服务报销-控制措施02 | J86: 各单位有关部门（班组）提出零星租车申请后，需经本单位后勤管理部门审批，后勤管理部门结合本单位现有车辆情况判断是否同意租赁，审批租赁车辆的必要性。自营项目租用吊车等特种车辆应经本单位电网技术部等生产管理部门审批。 | K86: √ | M86: √ | T86: 线下管控 | V86: 1.零星租车合同； 2.租用车辆行驶证、驾驶证； 3.零星租车申请单、审批单。 | W86: 各级单位-后勤管理部门-车辆管理人员、各级单位-电网技术部门-负责人 | X86: 每季度 | Y86: 抽查 | AA86: 每年 | AB86: 抽查 | AH86: 是 | AI86: 是 | AJ86: 国网湖南省电力有限公司关于印发《国网湖南省电力有限公司车辆租赁及车辆运输服务管理办法》的通知（湘电公司后勤〔2025〕356 号）第六条、第七条 | AL86: 各级单位后勤部 | AN86: 新增关键控制点“零星租车与运输服务报销” | AO86: =A86=[1]员工报账!A90 -> TRUE | AP86: =B86=[1]员工报账!B90 -> TRUE | AQ86: =C86=[1]员工报账!C90 -> TRUE | AR86: =D86=[1]员工报账!D90 -> TRUE | AS86: =E86=[1]员工报账!E90 -> TRUE | AT86: =F86=[1]员工报账!F90 -> TRUE | AU86: =G86=[1]员工报账!G90 -> TRUE | AV86: =H86=[1]员工报账!H90 -> TRUE | ... BX86: =AJ86=[1]员工报账!AJ90 -> FALSE
I87: 员工报账业务-26.零星租车与运输服务-控制措施03 | J87: 各单位后勤管理部门应加强租车结算管理，建立租赁车辆运行费用台账，严格按照实际次数、里程和合同价格结算。自营项目租用吊车、挖机等机械由生产管理部门建立台账，严格按照实际作业台班和合同价格结算。 | M87: √ | T87: 线下管控 | V87: 1.零星租车合同； 2.零星租车申请单； 3.零星租车台账（清单）； 4.零星租车发票。 | W87: 各级单位-后勤管理部门-车辆管理人员、各级单位-电网技术部门-项目管理人员 | X87: 每季度 | Y87: 抽查 | AA87: 每年 | AB87: 抽查 | AH87: 是 | AI87: 是 | AJ87: 国网湖南省电力有限公司关于印发《国网湖南省电力有限公司车辆租赁及车辆运输服务管理办法》的通知（湘电公司后勤〔2025〕356 号）第二十一条 | AL87: 各级单位后勤部 | AN87: 新增关键控制点“零星租车与运输服务报销” | AO87: =A87=[1]员工报账!A91 -> TRUE | AP87: =B87=[1]员工报账!B91 -> TRUE | AQ87: =C87=[1]员工报账!C91 -> TRUE | AR87: =D87=[1]员工报账!D91 -> TRUE | AS87: =E87=[1]员工报账!E91 -> TRUE | AT87: =F87=[1]员工报账!F91 -> TRUE | AU87: =G87=[1]员工报账!G91 -> TRUE | AV87: =H87=[1]员工报账!H91 -> TRUE | ... BX87: =AJ87=[1]员工报账!AJ91 -> FALSE
I88: 员工报账业务-26.零星租车与运输服务-控制措施04 | J88: 各单位财务部门审核零星租车报销发票金额与租车明细的一致性，审核合同折扣率、合同税率的执行情况。 | Q88: √ | T88: 线下管控 | V88: 1.零星租车合同； 2.零星租车申请单； 3.零星租车台账（清单）； 4.零星租车发票。 | W88: 各级单位-后勤管理部门-车辆管理人员、各级单位-电网技术部门-项目管理人员、各级单位-财务部门-成本管理人员 | X88: 每季度 | Y88: 抽查 | AA88: 每年 | AB88: 抽查 | AH88: 是 | AI88: 是 | AJ88: 国网湖南电力财务部关于印发支出类经济业务财务报销审核指引的通知（财〔2022〕22 号） | AL88: 各级单位财务部 | AN88: 新增关键控制点“零星租车与运输服务报销” | AO88: =A88=[1]员工报账!A92 -> TRUE | AP88: =B88=[1]员工报账!B92 -> TRUE | AQ88: =C88=[1]员工报账!C92 -> TRUE | AR88: =D88=[1]员工报账!D92 -> TRUE | AS88: =E88=[1]员工报账!E92 -> TRUE | AT88: =F88=[1]员工报账!F92 -> TRUE | AU88: =G88=[1]员工报账!G92 -> TRUE | AV88: =H88=[1]员工报账!H92 -> TRUE | ... BX88: =AJ88=[1]员工报账!AJ92 -> FALSE
A89: 员工报账 | B89: 二、通用报账 | C89: 税务合规、降本增效 | D89: 零星劳务 | E89: 自营项目零星劳务管理不规范，各类检查虚列套取现象频发。 | F89: 零星劳务员工管理不规范，存在重复报销，虚假用工套取费用。 | G89: 27.零星劳务管控 | H89: 加强零星用工管理，明确零星用工范围，实行利用自营用工系统实行台账管理，避免重负报销、虚假报销。 | I89: 员工报账业务-27.零星劳务管控-控制措施01 | J89: 自营项目的专业主管部门明确采取劳务外包的范围，不得从事核心业务或涉密工作。零星劳务人员应通过合规的招标方式，确定固定的服务商，实际需要用工时从签订合同的服务商范围内选用不得直接与个人签订用工协议。 | O89: √ | T89: 线下管控 | V89: 1.零星用工合同； 2.零星用工服务商中标通知书。 | W89: 各级单位-运检、配网、营销部门-项目管理人员、各级单位-运检、配网、营销部门-负责人 | X89: 每季度 | Y89: 抽查 | AA89: 每年 | AB89: 抽查 | AH89: 是 | AI89: 是 | AJ89: 国网湖南省电力有限公司关于印发自营模式下规范使用零星劳务人员指导意见的通知（湘电公司人资〔2022〕13号） | AL89: 各级单位零星用工使用部门 | AN89: 新增关键控制点“零星劳务管控” | AO89: =A89=[1]员工报账!A93 -> FALSE | AP89: =B89=[1]员工报账!B93 -> FALSE | AQ89: =C89=[1]员工报账!C93 -> FALSE | AR89: =D89=[1]员工报账!D93 -> FALSE | AS89: =E89=[1]员工报账!E93 -> FALSE | AT89: =F89=[1]员工报账!F93 -> FALSE | AU89: =G89=[1]员工报账!G93 -> FALSE | AV89: =H89=[1]员工报账!H93 -> FALSE | ... BX89: =AJ89=[1]员工报账!AJ93 -> FALSE
I90: 员工报账业务-27.零星劳务管控-控制措施02 | J90: 各单位自营项目主管部门制定零星用指导价，用工指导价包含服务商税费、管理费、食宿费、交通费、劳务人员工资等费用。各单位与服务商签订的劳务合同不得超过最高限价。 | O90: √ | T90: 线下管控 | V90: 1.零星用工合同； 2.零星用工服务商中标通知书。 | W90: 各级单位-运检、配网、营销部门-项目管理人员、各级单位-运检、配网、营销部门-负责人 | X90: 每季度 | Y90: 抽查 | AA90: 每年 | AB90: 抽查 | AH90: 是 | AI90: 是 | AJ90: 国网湖南省电力有限公司关于印发自营模式下规范使用零星劳务人员指导意见的通知（湘电公司人资〔2022〕13号） | AL90: 各级单位零星用工使用部门 | AN90: 新增关键控制点“零星劳务管控” | AO90: =A90=[1]员工报账!A94 -> TRUE | AP90: =B90=[1]员工报账!B94 -> TRUE | AQ90: =C90=[1]员工报账!C94 -> TRUE | AR90: =D90=[1]员工报账!D94 -> TRUE | AS90: =E90=[1]员工报账!E94 -> TRUE | AT90: =F90=[1]员工报账!F94 -> TRUE | AU90: =G90=[1]员工报账!G94 -> TRUE | AV90: =H90=[1]员工报账!H94 -> TRUE | ... BX90: =AJ90=[1]员工报账!AJ94 -> FALSE
I91: 员工报账业务-27.零星劳务管控-控制措施03 | J91: 各单位零星劳务使用部门、财务部门要严格审核用工的真实性、合理性，对同一身份证号码在同一时段不同班组或供电所用工的不予结算。 | K91: √ | M91: √ | T91: 线下管控 | V91: 1.零星用工合同； 2.零星用工服务商中标通知书。 3.零星用工申请单； 4.零星用工结算单； 5.零星用工发票。 | W91: 各级单位-运检、配网、营销部门-项目管理人员、各级单位-运检、配网、营销部门-报销审核人、各级单位-财务部门-会计核算人员 | X91: 每季度 | Y91: 抽查 | AA91: 每年 | AB91: 抽查 | AH91: 是 | AI91: 是 | AJ91: 国网湖南省电力有限公司关于印发自营模式下规范使用零星劳务人员指导意见的通知（湘电公司人资〔2022〕13号） | AL91: 各级单位财务部 | AN91: 新增关键控制点“零星劳务管控” | AO91: =A91=[1]员工报账!A95 -> TRUE | AP91: =B91=[1]员工报账!B95 -> TRUE | AQ91: =C91=[1]员工报账!C95 -> TRUE | AR91: =D91=[1]员工报账!D95 -> TRUE | AS91: =E91=[1]员工报账!E95 -> TRUE | AT91: =F91=[1]员工报账!F95 -> TRUE | AU91: =G91=[1]员工报账!G95 -> TRUE | AV91: =H91=[1]员工报账!H95 -> TRUE | ... BX91: =AJ91=[1]员工报账!AJ95 -> FALSE
A92: 员工报账 | B92: 二、通用报账 | C92: 合规政策 | D92: 物业管理费 | E92: 超范围、标准、重复列支物业管理费引发引发合规稽查风险和资金支付风险。 | F92: 物业管理费报销全流程存在资料缺失、支付不合规等多项问题： 1.报销无完整产权租赁依据，无物业租赁服务合同。 2.报销中出现同一物业点重复申报物业费、申报金额超出合同业务收费标准。 3.未按合同约定计费周期申报费用，提前列支尚未发生的物业管理费。 4.未区分自用、外租场地费用，虚增物业管理费，导致资金无依据流出。 5.房屋维修项目结算不实，铝合金中空玻璃窗、墙面墙砖等多结算面积，多计多结维修费用。 6.物业合同中已包含城区办公楼绿植租摆特约服务，又重复向花卉园艺场采购绿植租摆业务，重复结算物业管理费。 | G92: 28.物业管理费报销 | H92: 物业管理费在规定范围内报销 | I92: 员工报账业务-28.物业管理费管控-控制措施01 | J92: 归口管理部门对物业管理费用的数量、质量进行复核评价；核对计费周期、收费标准后再发起报销流程。 | K92: √ | M92: √ | Q92: √ | T92: 系统已建 | U92: 智慧共享财务平台 | V92: 1.报销 ( 资金支付 ) 审批单； 2.增值税专用发票； 3.合同； 4.费用清单 | W92: 各级单位-后勤部（综合服务中心）-报账人员、各级单位-后勤部（综合服务中心）-负责人 | X92: 每季度 | Y92: 抽查 | AA92: 每年 | AB92: 抽查 | AD92: 管理物业管理费监督场景 | AE92: 每年 | AF92: 抽查 | AH92: 是 | AI92: 是 | AJ92: 《国家电网有限公司会计基础管理办法 》（国网（财/2） 350-2018） （国家电网企管〔2019〕 132号） 、 《国家电网有限公司会计核算办法2021》（国网（财/2） 469-2020） | AL92: 各级单位后勤部（综合服务中心） | AM92: 需补充业务部门流程存在的风险控制点和控制措施，并同步补充业务相关的对应制度及文件，要求超输公司7.23日反馈 | AN92: 新增关键控制点“物业管理费报销” | AO92: =A92=[1]员工报账!A96 -> FALSE | AP92: =B92=[1]员工报账!B96 -> FALSE | AQ92: =C92=[1]员工报账!C96 -> FALSE | AR92: =D92=[1]员工报账!D96 -> FALSE | AS92: =E92=[1]员工报账!E96 -> FALSE | AT92: =F92=[1]员工报账!F96 -> FALSE | AU92: =G92=[1]员工报账!G96 -> FALSE | AV92: =H92=[1]员工报账!H96 -> FALSE | ... BX92: =AJ92=[1]员工报账!AJ96 -> FALSE
I93: 员工报账业务-28.物业管理费管控-控制措施02 | J93: 财务审核环节核查票据、附件完整度，校验申报金额、缴费周期与合同条款一致性；对无依据、超额、超前和重复支付物业费予以驳回。 | K93: √ | M93: √ | Q93: √ | T93: 系统已建 | U93: 智慧共享财务平台 | V93: 1.报销 ( 资金支付 ) 审批单； 2.增值税专用发票； 3.合同； 4.费用清单 | W93: 各级单位-后勤部（综合服务中心）-报账人员、各级单位-后勤部（综合服务中心）-负责人、各级单位-财务部门-成本管理人员 | X93: 每季度 | Y93: 抽查 | AA93: 每年 | AB93: 抽查 | AD93: 管理物业管理费监督场景 | AE93: 每年 | AF93: 抽查 | AH93: 是 | AI93: 是 | AJ93: 《国家电网有限公司会计基础管理办法 》（国网（财/2） 350-2018） （国家电网企管〔2019〕 132号） 、 《国家电网有限公司会计核算办法2021》（国网（财/2） 469-2020） | AL93: 各级单位后勤部（综合服务中心）、各级单位财务部 | AM93: 需补充业务部门流程存在的风险控制点和控制措施，并同步补充业务相关的对应制度及文件，要求超输公司7.23日反馈 | AN93: 新增关键控制点“物业管理费报销” | AO93: =A93=[1]员工报账!A97 -> TRUE | AP93: =B93=[1]员工报账!B97 -> TRUE | AQ93: =C93=[1]员工报账!C97 -> TRUE | AR93: =D93=[1]员工报账!D97 -> TRUE | AS93: =E93=[1]员工报账!E97 -> TRUE | AT93: =F93=[1]员工报账!F97 -> TRUE | AU93: =G93=[1]员工报账!G97 -> TRUE | AV93: =H93=[1]员工报账!H97 -> TRUE | ... BX93: =AJ93=[1]员工报账!AJ97 -> FALSE
A94: 员工报账 | B94: 二、通用报账 | C94: 合规政策 | D94: 物业管理费 | E94: 超范围、超额重复列支水电费引发引发合规风险和资金支付风险。 | F94: 办公场地水电费报销存在费用公私不明确，垫付套取资金风险。 1.存在办公区无单独抄表计量，需员工先垫付给第三方后取得电费发票再报销，存在私下串通私套费用列支。 2.存在超期，超额和重复报销情况，缺少缴费明细，费用难以追源核对。 | G94: 29.水电费报销 | H94: 水电费在规定范围内报销 | I94: 员工报账业务-29.水电费管控-控制措施01 | J94: 归口部门把控费用真实、合规性，按期及时报销，留存水电费抄表台账，全过程监管支出真实性。 | K94: √ | N94: √ | Q94: √ | T94: 系统已建 | U94: 智慧共享财务平台 | V94: 1.报销 ( 资金支付 ) 审批单； 2.增值税发票或收据 | W94: 各级单位-后勤部（综合服务中心）-报账人员、各级单位-后勤部（综合服务中心）-负责人、各级单位-运维检修部-报账人员、各级单位-运维检修部-负责人 | X94: 每季度 | Y94: 抽查 | AA94: 每年 | AB94: 抽查 | AD94: 管理水电费监督场景 | AE94: 每年 | AF94: 抽查 | AH94: 是 | AI94: 是 | AJ94: 《国家电网有限公司会计基础管理办法 》（国网（财/2） 350-2018） （国家电网企管〔2019〕 132号） 、 《国家电网有限公司会计核算办法2021》（国网（财/2） 469-2020） | AL94: 各级单位后勤部（综合服务中心）、各级单位-运维检修部 | AM94: 需补充业务部门流程存在的风险控制点和控制措施，并同步补充业务相关的对应制度及文件，要求超输公司7.23日反馈 | AN94: 新增关键控制点“水电费报销” | AO94: =A94=[1]员工报账!A98 -> FALSE | AP94: =B94=[1]员工报账!B98 -> FALSE | AQ94: =C94=[1]员工报账!C98 -> FALSE | AR94: =D94=[1]员工报账!D98 -> FALSE | AS94: =E94=[1]员工报账!E98 -> FALSE | AT94: =F94=[1]员工报账!F98 -> FALSE | AU94: =G94=[1]员工报账!G98 -> FALSE | AV94: =H94=[1]员工报账!H98 -> FALSE | ... BX94: =AJ94=[1]员工报账!AJ98 -> FALSE
I95: 员工报账业务-29.水电费管控-控制措施02 | J95: 财务部门审核发票、收据金额的准确性，按实际发生据实报账，提供垫付支付凭证。 | K95: √ | N95: √ | Q95: √ | T95: 系统已建 | U95: 智慧共享财务平台 | V95: 1.报销 ( 资金支付 ) 审批单； 2.增值税发票或收据 | W95: 各级单位-后勤部（综合服务中心）-报账人员、各级单位-后勤部（综合服务中心）-负责人、各级单位-运维检修部-报账人员、各级单位-运维检修部-负责人各级单位-财务部门-成本管理人员 | X95: 每季度 | Y95: 抽查 | AA95: 每年 | AB95: 抽查 | AD95: 管理水电费监督场景 | AE95: 每年 | AF95: 抽查 | AH95: 是 | AI95: 是 | AJ95: 《国家电网有限公司会计基础管理办法 》（国网（财/2） 350-2018） （国家电网企管〔2019〕 132号） 、 《国家电网有限公司会计核算办法2021》（国网（财/2） 469-2020） | AL95: 各级单位后勤部（综合服务中心）、各级单位-运维检修部、各级单位财务部 | AM95: 需补充业务部门流程存在的风险控制点和控制措施，并同步补充业务相关的对应制度及文件，要求超输公司7.23日反馈 | AN95: 新增关键控制点“水电费报销” | AO95: =A95=[1]员工报账!A99 -> TRUE | AP95: =B95=[1]员工报账!B99 -> TRUE | AQ95: =C95=[1]员工报账!C99 -> TRUE | AR95: =D95=[1]员工报账!D99 -> TRUE | AS95: =E95=[1]员工报账!E99 -> TRUE | AT95: =F95=[1]员工报账!F99 -> TRUE | AU95: =G95=[1]员工报账!G99 -> TRUE | AV95: =H95=[1]员工报账!H99 -> TRUE | ... BX95: =AJ95=[1]员工报账!AJ99 -> FALSE
A96: 员工报账 | B96: 二、通用报账 | C96: 合规政策 | D96: 房屋修理费 | E96: 超额、高套虚列房屋修理费引发引发合规风险和资金支付风险。 | F96: 后勤项目高套材料单价，多计多结资金。 1.房屋零星维修项目，与施工方签订施工合同，其中某些施工材料价格偏高，劳务分包施工，上下游管控监督不力，其中材料结算价格高套单价，超过市场普遍价格。导致多计多结导致审计整改。 2.房屋维修项目超预算，增补项目未经上级单位批准，擅自扩大后勤项目预算安排。 | G96: 30.房屋修理费报销 | H96: 房屋修理费在规定范围内报销 | I96: 员工报账业务-30.房屋修理费管控-控制措施01 | J96: 归口部门对工程施行全过程过程结果监督。 1.房屋维修立项前执行多方比价机制，严格建材、人工单价，杜绝高于市场价签约；2.项目负责人对工程实际用量，留存现场照片，施工台账进行合规审核；3.完工后对工程量签单、竣工验收报告真实性进行把控，无验收资料不允发起报账。 | K96: √ | N96: √ | Q96: √ | T96: 系统已建 | U96: 智慧共享财务平台 | V96: 1.报销 ( 资金支付 ) 审批单； 2.增值税发票或收据； 3.合同； 4.开工报告； 5.工程量签证单； 6.竣工验收报告； 7.项目结算表 、审计报告 ( 审定表签章页 ) | W96: 各级单位-后勤部（综合服务中心）-报账人员、各级单位-后勤部（综合服务中心）-负责人、各级单位-运维检修部-报账人员、各级单位-运维检修部-负责人 | X96: 每季度 | Y96: 抽查 | AA96: 每年 | AB96: 抽查 | AD96: 管理房屋维修费监督场景 | AE96: 每年 | AF96: 抽查 | AH96: 是 | AI96: 是 | AJ96: 《国家电网有限公司会计基础管理办法 》（国网（财/2） 350-2018） （国家电网企管〔2019〕 132号） 、 《国家电网有限公司会计核算办法2021》 （国网（财/2） 469-2022） | AL96: 各级单位后勤部（综合服务中心）、各级单位-运维检修部 | AM96: 需补充业务部门流程存在的风险控制点和控制措施，并同步补充业务相关的对应制度及文件，要求超输公司7.23日反馈 | AN96: 新增关键控制点“房屋修理费报销” | AO96: =A96=[1]员工报账!A100 -> FALSE | AP96: =B96=[1]员工报账!B100 -> FALSE | AQ96: =C96=[1]员工报账!C100 -> FALSE | AR96: =D96=[1]员工报账!D100 -> FALSE | AS96: =E96=[1]员工报账!E100 -> FALSE | AT96: =F96=[1]员工报账!F100 -> FALSE | AU96: =G96=[1]员工报账!G100 -> FALSE | AV96: =H96=[1]员工报账!H100 -> FALSE | ... BX96: =AJ96=[1]员工报账!AJ100 -> FALSE
I97: 员工报账业务-30.房屋修理费管控-控制措施02 | J97: 财务审核对合理性和资金安全做把控1.着重审核发票、结算清单金额 ，核对计价标准、工程量与验收资料是否匹配。2.严格规范报销附件要求，工程结算清单，施工合同和签证单缺一不可，对资料不全、单价异常的单据驳回，不予付款。 | K97: √ | N97: √ | Q97: √ | T97: 系统已建 | U97: 智慧共享财务平台 | V97: 1.报销 ( 资金支付 ) 审批单； 2.增值税发票或收据； 3.合同； 4.开工报告； 5.工程量签证单； 6.竣工验收报告； 7.项目结算表 、审计报告 ( 审定表签章页 ) | W97: 各级单位-后勤部（综合服务中心）-报账人员、各级单位-后勤部（综合服务中心）-负责人、各级单位-运维检修部-报账人员、各级单位-运维检修部-负责人各级单位-财务部门-成本管理人员 | X97: 每季度 | Y97: 抽查 | AA97: 每年 | AB97: 抽查 | AD97: 管理房屋维修费监督场景 | AE97: 每年 | AF97: 抽查 | AH97: 是 | AI97: 是 | AJ97: 《国家电网有限公司会计基础管理办法 》（国网（财/2） 350-2018） （国家电网企管〔2019〕 132号） 、 《国家电网有限公司会计核算办法2021》 （国网（财/2） 469-2022） | AL97: 各级单位后勤部（综合服务中心）、各级单位-运维检修部、各级单位财务部 | AM97: 需补充业务部门流程存在的风险控制点和控制措施，并同步补充业务相关的对应制度及文件，要求超输公司7.23日反馈 | AN97: 新增关键控制点“房屋修理费报销” | AO97: =A97=[1]员工报账!A101 -> TRUE | AP97: =B97=[1]员工报账!B101 -> TRUE | AQ97: =C97=[1]员工报账!C101 -> TRUE | AR97: =D97=[1]员工报账!D101 -> TRUE | AS97: =E97=[1]员工报账!E101 -> TRUE | AT97: =F97=[1]员工报账!F101 -> TRUE | AU97: =G97=[1]员工报账!G101 -> TRUE | AV97: =H97=[1]员工报账!H101 -> TRUE | ... BX97: =AJ97=[1]员工报账!AJ101 -> FALSE
A98: 员工报账 | B98: 二、通用报账 | C98: 合规政策 | D98: 租赁费 | E98: 未规范区分租赁类型，合同管理滞后、超标准列支租金形成资金浪费带来审计、税务稽查合规风险， | F98: 租赁业务从合同签订到资金保险全流程存在多项管控漏洞。1.报销时未区区分经营租赁、融资租赁导致账务核算分类错误； 2.合同签订滞后导致租赁起始入账时间与实际使用期间不一致，容易造成使用纠纷； 3.支付租金时，出租方开票的计费周期、金额与合同条款约定不一致。 | G98: 31.租赁费报销 | H98: 租赁费在规定范围内报销 | I98: 员工报账业务-31.租赁费管控-控制措施01 | J98: 落实租赁事前审批、合同管控、财务多层复核，规范租赁费保险全流程，业务端建立合同分级审批机制，大额的租赁签订要全流程监控 | K98: √ | N98: √ | Q98: √ | T98: 系统已建 | U98: 智慧共享财务平台 | V98: 1.报销 ( 资金支付 ) 审批单； 2.增值税发票或收据； 3.合同或协议； 4产权证明材料； 5.完税证明； 6.个人身份证、银行卡复印件 | W98: 各级单位-各部门-报账人员、各级单位-各部门-负责人、 | X98: 每季度 | Y98: 抽查 | AA98: 每年 | AB98: 抽查 | AD98: 管理租赁费监督场景 | AE98: 每年 | AF98: 抽查 | AH98: 是 | AI98: 是 | AJ98: 《国家电网有限公司会计基础管理办法 》( 国网 ( 财/2) 350-2018) ( 国家电网企管〔2019〕 132号 ) 、《 国家电网有限公司会 计核算办法2021》 ( 国网 (财/2) 469- 2020) 、《国网湖南省电力有限公司关于进 一步加强资金支付安全管理的通知 》( 湘电 公司财〔2018〕940号 ) | AL98: 各级单位后勤部（综合服务中心）、各级单位设备部、各级单位财务部 | AM98: 需补充业务部门流程存在的风险控制点和控制措施，并同步补充业务相关的对应制度及文件，要求超输公司7.23日反馈 | AN98: 新增关键控制点“租赁费报销” | AO98: =A98=[1]员工报账!A102 -> FALSE | AP98: =B98=[1]员工报账!B102 -> FALSE | AQ98: =C98=[1]员工报账!C102 -> FALSE | AR98: =D98=[1]员工报账!D102 -> FALSE | AS98: =E98=[1]员工报账!E102 -> FALSE | AT98: =F98=[1]员工报账!F102 -> FALSE | AU98: =G98=[1]员工报账!G102 -> FALSE | AV98: =H98=[1]员工报账!H102 -> FALSE | ... BX98: =AJ98=[1]员工报账!AJ102 -> FALSE
I99: 员工报账业务-31.租赁费管控-控制措施02 | J99: 财务审核时核验附件完整性和合规性，需有产权证明和个税完税证明；租赁个人房屋时，根据合同签订时间判断租赁类别，严格确保开票金额、租期与租赁合同保持一致，资料不符不允报销付款。 | K99: √ | N99: √ | Q99: √ | T99: 系统已建 | U99: 智慧共享财务平台 | V99: 1.报销 ( 资金支付 ) 审批单； 2.增值税发票或收据； 3.合同或协议； 4产权证明材料； 5.完税证明； 6.个人身份证、银行卡复印件 | W99: 各级单位-各部门-报账人员、各级单位-各部门-负责人、各级单位-财务部门-成本管理人员 | X99: 每季度 | Y99: 抽查 | AA99: 每年 | AB99: 抽查 | AD99: 管理租赁费监督场景 | AE99: 每年 | AF99: 抽查 | AH99: 是 | AI99: 是 | AJ99: 《国家电网有限公司会计基础管理办法 》( 国网 ( 财/2) 350-2018) ( 国家电网企管〔2019〕 132号 ) 、《 国家电网有限公司会 计核算办法2021》 ( 国网 (财/2) 469- 2020) 、《国网湖南省电力有限公司关于进 一步加强资金支付安全管理的通知 》( 湘电 公司财〔2018〕940号 ) | AL99: 各级单位后勤部（综合服务中心）、各级单位设备部、各级单位财务部 | AM99: 需补充业务部门流程存在的风险控制点和控制措施，并同步补充业务相关的对应制度及文件，要求超输公司7.23日反馈 | AN99: 新增关键控制点“租赁费报销” | AO99: =A99=[1]员工报账!A103 -> TRUE | AP99: =B99=[1]员工报账!B103 -> TRUE | AQ99: =C99=[1]员工报账!C103 -> TRUE | AR99: =D99=[1]员工报账!D103 -> TRUE | AS99: =E99=[1]员工报账!E103 -> TRUE | AT99: =F99=[1]员工报账!F103 -> TRUE | AU99: =G99=[1]员工报账!G103 -> TRUE | AV99: =H99=[1]员工报账!H103 -> TRUE | ... BX99: =AJ99=[1]员工报账!AJ103 -> FALSE

Sheet 员工报账（确认三清单版本核对过程7.30）
A1: 风控矩阵-员工报账
A2: 业务条线 | B2: 业务领域 | C2: 控制目标 | D2: 业务流程步骤 | E2: 经营风险 | F2: 典型问题 | G2: 关键控制点 | H2: 控制要求 | I2: 控制措施 编号 | J2: 控制措施 | K2: 控制措施分类 | T2: 控制方式 | U2: 控制系统 | V2: 控制载体 | W2: 责任主体 | X2: 业务自评价 | AA2: 集团监督 评价 | AD2: 数字化监督场景 | AH2: 现有制度及文件落实情况 | AK2: 总部审核部门 | AL2: 湖南公司审核部门 | AM2: 其他备注 | AN2: 7.23 | AO2: 7.3
K3: 不相容岗位 | L3: 分级授权 | M3: 业务真实性控制 | N3: 预算管控 | O3: 合同控制 | P3: 收付控制 | Q3: 会计监督 | R3: 财产保护 | S3: 分析与评价 | X3: 评价频率 | Y3: 评价范围 | Z3: 评价结论 | AA3: 评价频率 | AB3: 评价范围 | AC3: 评价结论 | AD3: 数字化监督场景 | AE3: 评价频率 | AF3: 评价范围 | AG3: 评价结论 | AH3: 是否已要求 | AI3: 是否满足要求 | AJ3: 对应制度及文件名称
A4: 员工报账 | B4: 一、员工差旅 | C4: 资金资产安全 | D4: 出差申请 | E4: 出差事项不真实，出差无实质内容，无明确公务目的，虚列套取费用，导致资金安全风险。 | F4: 87.违规发放津贴补贴：存在多报差旅补贴、虚报差旅补贴等问题。 | G4: 1.出差申请发起 | H4: 出差有明确公务目的，出差时间、地点、人员与出差通知一致。 | I4: 员工报账业务-1.出差申请发起-控制措施01 | J4: 出差员工部门负责人对员工出差内容的复核，重点审查出差申请单人员、地点、事由等信息。 | M4: √ | T4: 系统已建 | U4: 国网商旅 | V4: 1.出差通知、培训通知等出差缘由证明材料。 | W4: 各级单位-各部门-出差人员、各级单位-各部门-负责人、商旅云公司 | X4: 每日 | Y4: 全量检查 | AA4: 每年 | AB4: 抽查 | AD4: 员工差旅出差申请监督场景 | AE4: 每月 | AF4: 抽查 | AH4: 是 | AI4: 是 | AJ4: 《国家电网有限公司差旅费管理办法》（国家电网企管〔2026〕101号）第四条、第二十四条、《国网湖南省电力有限公司关于印发加强差旅费管理有关规定的通知》第二条、第三条 | AK4: 国网财务部 | AL4: 各级单位财务部 | AN4: 补充制度 | AP4: =A4=[2]员工报账!A4 -> TRUE | AQ4: =B4=[2]员工报账!B4 -> TRUE | AR4: =C4=[2]员工报账!C4 -> TRUE | AS4: =D4=[2]员工报账!D4 -> TRUE | AT4: =E4=[2]员工报账!E4 -> TRUE | AU4: =F4=[2]员工报账!F4 -> TRUE | AV4: =G4=[2]员工报账!G4 -> TRUE | AW4: =H4=[2]员工报账!H4 -> TRUE | ... BZ4: =AK4=[2]员工报账!AK4 -> TRUE
I5: 员工报账业务-1.出差申请发起-控制措施02 | J5: 健全“申请-预订-报销”数据联动校验规则，落实预算控制，系统自动比对出差事项与出差产生的票据的逻辑一致性。 | M5: √ | N5: √ | T5: 系统已建 | U5: 国网商旅 | V5: 1.出差审批单。 | W5: 各级单位-各部门-出差人员、商旅云公司 | X5: 每日 | Y5: 全量检查 | AA5: 每年 | AB5: 抽查 | AD5: 员工差旅出差申请监督场景 | AE5: 每月 | AF5: 抽查 | AH5: 是 | AI5: 是 | AJ5: 《国家电网有限公司差旅费管理办法》（国家电网企管〔2026〕101号）第四条、第二十四条、《国网湖南省电力有限公司关于印发加强差旅费管理有关规定的通知》第二条、第三条 | AK5: 国网财务部 | AL5: 各级单位财务部 | AN5: 补充制度 | AP5: =A5=[2]员工报账!A5 -> TRUE | AQ5: =B5=[2]员工报账!B5 -> TRUE | AR5: =C5=[2]员工报账!C5 -> TRUE | AS5: =D5=[2]员工报账!D5 -> TRUE | AT5: =E5=[2]员工报账!E5 -> TRUE | AU5: =F5=[2]员工报账!F5 -> TRUE | AV5: =G5=[2]员工报账!G5 -> TRUE | AW5: =H5=[2]员工报账!H5 -> TRUE | ... BZ5: =AK5=[2]员工报账!AK5 -> TRUE
I6: 员工报账业务-1.出差申请发起-控制措施03 | J6: 健全差旅费成本中心校验机制，赴异地挂职、按照规定探亲在途期间出差申请选择原单位成本中心，挂职期间出差申请选择挂职单位成本中心。 | N6: √ | Q6: √ | T6: 系统已建 | U6: 国网商旅 | V6: 1.系统出差申请单校验记录等。 | W6: 各级单位-各部门-出差人员、商旅云公司 | X6: 每日 | Y6: 全量检查 | AA6: 每年 | AB6: 抽查 | AD6: 员工差旅出差申请监督场景 | AE6: 每月 | AF6: 抽查 | AH6: 是 | AI6: 是 | AJ6: 《国家电网有限公司差旅费管理办法》（国家电网企管〔2026〕101号）第四条、第二十四条、《国网湖南省电力有限公司关于印发加强差旅费管理有关规定的通知》第二条、第三条 | AK6: 国网财务部 | AL6: 各级单位财务部 | AN6: 补充制度 | AP6: =A6=[2]员工报账!A6 -> TRUE | AQ6: =B6=[2]员工报账!B6 -> TRUE | AR6: =C6=[2]员工报账!C6 -> TRUE | AS6: =D6=[2]员工报账!D6 -> TRUE | AT6: =E6=[2]员工报账!E6 -> TRUE | AU6: =F6=[2]员工报账!F6 -> TRUE | AV6: =G6=[2]员工报账!G6 -> TRUE | AW6: =H6=[2]员工报账!H6 -> TRUE | ... BZ6: =AK6=[2]员工报账!AK6 -> TRUE
G7: 2.出差申请审批 | H7: 按规定执行出差审批制度。 | I7: 员工报账业务-2.出差申请审批-控制措施01 | J7: 流程固化与防逆向控制，商旅云公司固化“审批-预订-报销”流程，严格限制并需特殊授权才能“取消审批”等逆向操作。 | L7: √ | Q7: √ | T7: 系统已建 | U7: 国网商旅 | V7: 1.出差通知、培训通知等出差缘由证明材料； 2.出差审批单； 3.系统出差申请单审批轨迹。 | W7: 各级单位-各部门-出差人员、商旅云公司 | X7: 每日 | Y7: 全量检查 | AA7: 每年 | AB7: 抽查 | AD7: 员工差旅出差申请监督场景 | AE7: 每月 | AF7: 抽查 | AH7: 是 | AI7: 是 | AJ7: 《国家电网有限公司差旅费管理办法》（国家电网企管〔2026〕101号）第二十二条 | AK7: 国网财务部 | AL7: 各级单位财务部 | AP7: =A7=[2]员工报账!A7 -> TRUE | AQ7: =B7=[2]员工报账!B7 -> TRUE | AR7: =C7=[2]员工报账!C7 -> TRUE | AS7: =D7=[2]员工报账!D7 -> TRUE | AT7: =E7=[2]员工报账!E7 -> TRUE | AU7: =F7=[2]员工报账!F7 -> TRUE | AV7: =G7=[2]员工报账!G7 -> TRUE | AW7: =H7=[2]员工报账!H7 -> TRUE | ... BZ7: =AK7=[2]员工报账!AK7 -> TRUE
I8: 员工报账业务-2.出差申请审批-控制措施02 | J8: 全链条强制关联控制，系统强制将“审批单号”作为商旅预订及费用报销的唯一前提。 | Q8: √ | T8: 系统已建 | U8: 国网商旅 | V8: 1.出差通知、培训通知等出差缘由证明材料； 2.出差审批单。 | W8: 各级单位-各部门-出差人员、商旅云公司 | X8: 每日 | Y8: 全量检查 | AA8: 每年 | AB8: 抽查 | AD8: 员工差旅出差申请监督场景 | AE8: 每月 | AF8: 抽查 | AH8: 是 | AI8: 是 | AJ8: 《国家电网有限公司差旅费管理办法》（国家电网企管〔2026〕101号）第四条、第二十四条、第二十六条 | AK8: 国网财务部 | AL8: 各级单位财务部 | AP8: =A8=[2]员工报账!A8 -> TRUE | AQ8: =B8=[2]员工报账!B8 -> TRUE | AR8: =C8=[2]员工报账!C8 -> TRUE | AS8: =D8=[2]员工报账!D8 -> TRUE | AT8: =E8=[2]员工报账!E8 -> TRUE | AU8: =F8=[2]员工报账!F8 -> TRUE | AV8: =G8=[2]员工报账!G8 -> TRUE | AW8: =H8=[2]员工报账!H8 -> TRUE | ... BZ8: =AK8=[2]员工报账!AK8 -> TRUE
I9: 员工报账业务-2.出差申请审批-控制措施03 | J9: 商旅云公司严禁后台“绿色通道”操作，禁止平台通过电话申请取消审批行为。 | M9: √ | T9: 系统待建 | U9: 国网商旅 | V9: 1.出差通知、培训通知等出差缘由证明材料； 2.出差审批单； 3.系统出差申请单审批轨迹。 | W9: 各级单位-各部门-出差人员、商旅云公司 | X9: 每日 | Y9: 全量检查 | AA9: 每年 | AB9: 抽查 | AD9: 员工差旅出差申请监督场景 | AE9: 每月 | AF9: 抽查 | AH9: 是 | AI9: 是 | AJ9: 《国家电网有限公司差旅费管理办法》（国家电网企管〔2026〕101号）第四条、第二十四条、第二十六条 | AK9: 国网财务部 | AL9: 各级单位财务部 | AP9: =A9=[2]员工报账!A9 -> TRUE | AQ9: =B9=[2]员工报账!B9 -> TRUE | AR9: =C9=[2]员工报账!C9 -> TRUE | AS9: =D9=[2]员工报账!D9 -> TRUE | AT9: =E9=[2]员工报账!E9 -> TRUE | AU9: =F9=[2]员工报账!F9 -> TRUE | AV9: =G9=[2]员工报账!G9 -> TRUE | AW9: =H9=[2]员工报账!H9 -> TRUE | ... BZ9: =AK9=[2]员工报账!AK9 -> TRUE
A10: 员工报账 | B10: 一、员工差旅 | C10: 税务合规 | D10: 出差申请 | E10: 商旅平台违规取消事前审批流程，导致出现“先出差后申请”的情况，引发舞弊及合规管理风险。 | F10: 87.违规发放津贴补贴：存在多报差旅补贴、虚报差旅补贴等问题。 | G10: 3.出差申请流程控制 | H10: 出差申请日期早于出差日期。 | I10: 员工报账业务-3.出差申请流程控制-控制措施01 | J10: 审批要素完整性校验，系统强制校验审批单的必备要素，对缺少出差事由等关键要素的申请单不予通过。 | M10: √ | T10: 系统已建 | U10: 国网商旅 | V10: 1.系统出差申请单审批轨迹； 2.系统记录的申请单提交时间和出差时间。 | W10: 各级单位-各部门-出差人员、各级单位-各部门-负责人、商旅云公司 | X10: 每日 | Y10: 全量检查 | AA10: 每年 | AB10: 抽查 | AD10: 员工差旅流程配置监督场景 | AE10: 每月 | AF10: 抽查 | AH10: 是 | AI10: 是 | AJ10: 《国家电网有限公司差旅费管理办法》（国家电网企管〔2026〕101号）第五条 | AK10: 国网财务部 | AL10: 各级单位财务部 | AN10: 修改责任主体 | AP10: =A10=[2]员工报账!A10 -> TRUE | AQ10: =B10=[2]员工报账!B10 -> TRUE | AR10: =C10=[2]员工报账!C10 -> TRUE | AS10: =D10=[2]员工报账!D10 -> TRUE | AT10: =E10=[2]员工报账!E10 -> TRUE | AU10: =F10=[2]员工报账!F10 -> TRUE | AV10: =G10=[2]员工报账!G10 -> TRUE | AW10: =H10=[2]员工报账!H10 -> TRUE | ... BZ10: =AK10=[2]员工报账!AK10 -> TRUE
I11: 员工报账业务-3.出差申请流程控制-控制措施02 | J11: 严格执行不相容控制，系统根据组织架构与授权清单自动匹配并校验审批人权限，防范越权审批 | R11: √ | T11: 系统已建 | U11: 国网商旅 | V11: 1.系统记录的申请单提交时间和出差时间。 | W11: 商旅云公司、各级单位-各部门-出差人员、各级单位-各部门-负责人 | X11: 每日 | Y11: 全量检查 | AA11: 每年 | AB11: 抽查 | AD11: 员工差旅流程配置监督场景 | AE11: 每月 | AF11: 抽查 | AH11: 是 | AI11: 是 | AJ11: 《国家电网有限公司差旅费管理办法》（国家电网企管〔2026〕101号）第五条 | AK11: 国网财务部 | AL11: 各级单位财务部 | AP11: =A11=[2]员工报账!A11 -> TRUE | AQ11: =B11=[2]员工报账!B11 -> TRUE | AR11: =C11=[2]员工报账!C11 -> TRUE | AS11: =D11=[2]员工报账!D11 -> TRUE | AT11: =E11=[2]员工报账!E11 -> TRUE | AU11: =F11=[2]员工报账!F11 -> TRUE | AV11: =G11=[2]员工报账!G11 -> TRUE | AW11: =H11=[2]员工报账!H11 -> TRUE | ... BZ11: =AK11=[2]员工报账!AK11 -> TRUE
I12: 员工报账业务-3.出差申请流程控制-控制措施03 | J12: 建立定期分析、评价与问责机制，各部门对审批时效、驳回率、特批事项进行专项分析，审计部门、纪检部门等监督部门对违规审批、补批行为依规问责。 | M12: √ | R12: √ | S12: √ | T12: 线下管控 | V12: 1.系统记录的申请单提交时间和出差时间。 | W12: 商旅云公司、各级单位-审计部门、纪检部门等监督部门-监督、纪检管理人员 | X12: 每日 | Y12: 全量检查 | AA12: 每年 | AB12: 抽查 | AD12: 员工差旅流程配置监督场景 | AE12: 每月 | AF12: 抽查 | AH12: 是 | AI12: 是 | AJ12: 《国家电网有限公司差旅费管理办法》（国家电网企管〔2026〕101号）第五条 | AK12: 国网财务部 | AL12: 各级单位财务部 | AN12: 修改责任主体 | AP12: =A12=[2]员工报账!A12 -> TRUE | AQ12: =B12=[2]员工报账!B12 -> TRUE | AR12: =C12=[2]员工报账!C12 -> TRUE | AS12: =D12=[2]员工报账!D12 -> TRUE | AT12: =E12=[2]员工报账!E12 -> TRUE | AU12: =F12=[2]员工报账!F12 -> TRUE | AV12: =G12=[2]员工报账!G12 -> TRUE | AW12: =H12=[2]员工报账!H12 -> TRUE | ... BZ12: =AK12=[2]员工报账!AK12 -> TRUE
C13: 税务合规 | D13: 差旅预订 | E13: 商旅平台酒店存在棋牌、麻将、电竞等敏感字眼，商旅平台违规上架引发合规风险。 | G13: 4.酒店入驻上架控制 | H13: 酒店资源上架流程合规，且履行必要的审批手续。 | I13: 员工报账业务-4.酒店入驻上架控制-控制措施01 | J13: 商旅云公司强化供应商准入审核，对新签约酒店的的资质有效性、服务适配性以及风险可控性等信息进行事前审核。 | O13: √ | T13: 系统待建 | U13: 国网商旅 | V13: 1.酒店资质、营业执照、房型清单。 | W13: 商旅云公司 | X13: 每日 | Y13: 全量检查 | AA13: 每年 | AB13: 抽查 | AD13: 员工差旅预订监督场景 | AE13: 每月 | AF13: 抽查 | AH13: 是 | AI13: 是 | AJ13: 《国家电网有限公司差旅费管理办法》（国家电网企管〔2026〕101号）第五条 | AK13: 国网财务部 | AL13: 各级单位财务部 | AP13: =A13=[2]员工报账!A13 -> TRUE | AQ13: =B13=[2]员工报账!B13 -> TRUE | AR13: =C13=[2]员工报账!C13 -> TRUE | AS13: =D13=[2]员工报账!D13 -> TRUE | AT13: =E13=[2]员工报账!E13 -> TRUE | AU13: =F13=[2]员工报账!F13 -> TRUE | AV13: =G13=[2]员工报账!G13 -> TRUE | AW13: =H13=[2]员工报账!H13 -> TRUE | ... BZ13: =AK13=[2]员工报账!AK13 -> TRUE
I14: 员工报账业务-4.酒店入驻上架控制-控制措施02 | J14: 商旅云公司建立并动态更新《敏感词库与酒店属性负面清单》，系统自动拦截负面清单内容并转人工复核。 | O14: √ | Q14: √ | S14: √ | T14: 系统待建 | U14: 国网商旅 | V14: 1.系统敏感词库与酒店属性负面清单。 | W14: 商旅云公司 | X14: 每日 | Y14: 全量检查 | AA14: 每年 | AB14: 抽查 | AD14: 员工差旅预订监督场景 | AE14: 每月 | AF14: 抽查 | AH14: 是 | AI14: 是 | AJ14: 《国家电网有限公司差旅费管理办法》（国家电网企管〔2026〕101号）第五条 | AK14: 国网财务部 | AL14: 各级单位财务部 | AP14: =A14=[2]员工报账!A14 -> TRUE | AQ14: =B14=[2]员工报账!B14 -> TRUE | AR14: =C14=[2]员工报账!C14 -> TRUE | AS14: =D14=[2]员工报账!D14 -> TRUE | AT14: =E14=[2]员工报账!E14 -> TRUE | AU14: =F14=[2]员工报账!F14 -> TRUE | AV14: =G14=[2]员工报账!G14 -> TRUE | AW14: =H14=[2]员工报账!H14 -> TRUE | ... BZ14: =AK14=[2]员工报账!AK14 -> TRUE
I15: 员工报账业务-4.酒店入驻上架控制-控制措施03 | J15: 追回违规上架酒店产生的资金浪费，并对相关负责人按规定给予处分处理。 | R15: √ | S15: √ | T15: 线下管控 | V15: 1.问责证明材料。 | W15: 商旅云公司 | X15: 每日 | Y15: 全量检查 | AA15: 每年 | AB15: 抽查 | AD15: 员工差旅预订监督场景 | AE15: 每月 | AF15: 抽查 | AH15: 是 | AI15: 是 | AJ15: 《国家电网有限公司差旅费管理办法》（国家电网企管〔2026〕101号）第五条 | AK15: 国网财务部 | AL15: 各级单位财务部 | AP15: =A15=[2]员工报账!A15 -> TRUE | AQ15: =B15=[2]员工报账!B15 -> TRUE | AR15: =C15=[2]员工报账!C15 -> TRUE | AS15: =D15=[2]员工报账!D15 -> TRUE | AT15: =E15=[2]员工报账!E15 -> TRUE | AU15: =F15=[2]员工报账!F15 -> TRUE | AV15: =G15=[2]员工报账!G15 -> TRUE | AW15: =H15=[2]员工报账!H15 -> TRUE | ... BZ15: =AK15=[2]员工报账!AK15 -> TRUE
C16: 资金资产安全 | D16: 差旅预订 | E16: 酒店价格虚高易引发套取资金，引发廉政风险。 | F16: 87.违规发放津贴补贴：存在多报差旅补贴、虚报差旅补贴等问题。 | G16: 5.单体酒店上架及价格定价管控 | H16: 商旅平台酒店资源价格真实合理。 | I16: 员工报账业务-5.单体酒店上架及价格定价管控-控制措施01 | J16: 增加单体酒店上架申请审批流程，由各单位办公室汇总审核本单位酒店需求，向商旅云公司提交上架。 | L16: √ | O16: √ | T16: 系统已建 | U16: 国网商旅 | V16: 1.协议单体酒店推荐表单。 | W16: 商旅云公司、各级单位-办公室财务部 | X16: 每日 | Y16: 全量检查 | AA16: 每年 | AB16: 抽查 | AD16: 员工差旅预订监督场景 | AE16: 每月 | AF16: 抽查 | AH16: 是 | AI16: 是 | AJ16: 《国家电网有限公司差旅费管理办法》（国家电网企管〔2026〕101号）第五条 | AK16: 国网财务部 | AL16: 各级单位财务部 | AN16: 修改责任主体 | AP16: =A16=[2]员工报账!A16 -> TRUE | AQ16: =B16=[2]员工报账!B16 -> TRUE | AR16: =C16=[2]员工报账!C16 -> TRUE | AS16: =D16=[2]员工报账!D16 -> TRUE | AT16: =E16=[2]员工报账!E16 -> TRUE | AU16: =F16=[2]员工报账!F16 -> TRUE | AV16: =G16=[2]员工报账!G16 -> TRUE | AW16: =H16=[2]员工报账!H16 -> TRUE | ... BZ16: =AK16=[2]员工报账!AK16 -> TRUE
I17: 员工报账业务-5.单体酒店上架及价格定价管控-控制措施02 | J17: 商旅云公司强化协议签订管控，严格审核酒店资质，严控无理由上架，防范舞弊行为。 | O17: √ | T17: 系统已建 | U17: 国网商旅 | V17: 1.酒单违规风险清单； 2.采购协议酒店清单； 3.酒店上架评审报告。 | W17: 商旅云公司 | X17: 每日 | Y17: 全量检查 | AA17: 每年 | AB17: 抽查 | AD17: 员工差旅预订监督场景 | AE17: 每月 | AF17: 抽查 | AH17: 是 | AI17: 是 | AJ17: 《国家电网有限公司差旅费管理办法》（国家电网企管〔2026〕101号）第五条 | AK17: 国网财务部 | AL17: 各级单位财务部 | AP17: =A17=[2]员工报账!A17 -> TRUE | AQ17: =B17=[2]员工报账!B17 -> TRUE | AR17: =C17=[2]员工报账!C17 -> TRUE | AS17: =D17=[2]员工报账!D17 -> TRUE | AT17: =E17=[2]员工报账!E17 -> TRUE | AU17: =F17=[2]员工报账!F17 -> TRUE | AV17: =G17=[2]员工报账!G17 -> TRUE | AW17: =H17=[2]员工报账!H17 -> TRUE | ... BZ17: =AK17=[2]员工报账!AK17 -> TRUE
I18: 员工报账业务-5.单体酒店上架及价格定价管控-控制措施03 | J18: 加强员工行为管控，商旅云公司强化酒店订单在线监督，防范员工违规套取资金。 | M18: √ | R18: √ | T18: 系统已建 | U18: 国网商旅 | V18: 1.酒店合作协议。 | W18: 商旅云公司 | X18: 每日 | Y18: 全量检查 | AA18: 每年 | AB18: 抽查 | AD18: 员工差旅预订监督场景 | AE18: 每月 | AF18: 抽查 | AH18: 是 | AI18: 是 | AJ18: 《国家电网有限公司差旅费管理办法》（国家电网企管〔2026〕101号）第五条 | AK18: 国网财务部 | AL18: 各级单位财务部 | AP18: =A18=[2]员工报账!A18 -> TRUE | AQ18: =B18=[2]员工报账!B18 -> TRUE | AR18: =C18=[2]员工报账!C18 -> TRUE | AS18: =D18=[2]员工报账!D18 -> TRUE | AT18: =E18=[2]员工报账!E18 -> TRUE | AU18: =F18=[2]员工报账!F18 -> TRUE | AV18: =G18=[2]员工报账!G18 -> TRUE | AW18: =H18=[2]员工报账!H18 -> TRUE | ... BZ18: =AK18=[2]员工报账!AK18 -> TRUE
A19: 员工报账 | B19: 一、员工差旅 | C19: 资金资产安全 | D19: 差旅预订 | E19: 酒店价格虚高易引发套取资金，引发廉政风险。 | F19: 87.违规发放津贴补贴：存在多报差旅补贴、虚报差旅补贴等问题。 | G19: 5.单体酒店上架及价格定价管控 | H19: 商旅平台酒店资源价格真实合理。 | I19: 员工报账业务-5.单体酒店上架及价格定价管控-控制措施04 | J19: 建立负面清单，及时清退违规酒店。 | R19: √ | S19: √ | T19: 线下管控 | V19: 1.酒店风险识别机制； 2.员工体验反馈。 | W19: 商旅云公司 | X19: 每日 | Y19: 全量检查 | AA19: 每年 | AB19: 抽查 | AD19: 员工差旅预订监督场景 | AE19: 每月 | AF19: 抽查 | AH19: 是 | AI19: 是 | AJ19: 《国家电网有限公司差旅费管理办法》（国家电网企管〔2026〕101号）第五条 | AK19: 国网财务部 | AL19: 各级单位财务部 | AP19: =A19=[2]员工报账!A19 -> TRUE | AQ19: =B19=[2]员工报账!B19 -> TRUE | AR19: =C19=[2]员工报账!C19 -> TRUE | AS19: =D19=[2]员工报账!D19 -> TRUE | AT19: =E19=[2]员工报账!E19 -> TRUE | AU19: =F19=[2]员工报账!F19 -> TRUE | AV19: =G19=[2]员工报账!G19 -> TRUE | AW19: =H19=[2]员工报账!H19 -> TRUE | ... BZ19: =AK19=[2]员工报账!AK19 -> TRUE
D20: 差旅预订 | E20: 员工在同一时间段内重复预订酒店资源，存在套取资金风险。 | F20: 87.违规发放津贴补贴：存在多报差旅补贴、虚报差旅补贴等问题。 | G20: 6.酒店预订 | H20: 同一员工在同一时间段内，就同一出差行程，仅能生成一个有效住宿订单。 | I20: 员工报账业务-6.酒店预订-控制措施01 | J20: 商旅云公司完善重复订单系统校验规则，自动拦截并预警同一人员、时段重叠的酒店订单申请。 | M20: √ | T20: 系统已建 | U20: 国网商旅 | V20: 1.商旅订单； 2.出差通知、培训通知等出差缘由证明材料。 | W20: 各级单位-各部门-出差人员、商旅云公司 | X20: 每日 | Y20: 全量检查 | AA20: 每年 | AB20: 抽查 | AD20: 员工差旅预订监督场景 | AE20: 每月 | AF20: 抽查 | AH20: 是 | AI20: 是 | AJ20: 《国家电网有限公司差旅费管理办法》（国家电网企管〔2026〕101号）第二十四条 | AK20: 国网财务部 | AL20: 各级单位财务部 | AP20: =A20=[2]员工报账!A20 -> TRUE | AQ20: =B20=[2]员工报账!B20 -> TRUE | AR20: =C20=[2]员工报账!C20 -> TRUE | AS20: =D20=[2]员工报账!D20 -> TRUE | AT20: =E20=[2]员工报账!E20 -> TRUE | AU20: =F20=[2]员工报账!F20 -> TRUE | AV20: =G20=[2]员工报账!G20 -> TRUE | AW20: =H20=[2]员工报账!H20 -> TRUE | ... BZ20: =AK20=[2]员工报账!AK20 -> TRUE
I21: 员工报账业务-6.酒店预订-控制措施02 | J21: 商旅云公司健全入住轨迹验证与反馈机制，自动识别入住轨迹异常情况，即时预警有关责任人。 | M21: √ | S21: √ | T21: 系统已建 | U21: 国网商旅 | V21: 1.系统拦截记录。 | W21: 各级单位-各部门-出差人员、商旅云公司 | X21: 每日 | Y21: 全量检查 | AA21: 每年 | AB21: 抽查 | AD21: 员工差旅预订监督场景 | AE21: 每月 | AF21: 抽查 | AH21: 是 | AI21: 是 | AJ21: 《国家电网有限公司差旅费管理办法》（国家电网企管〔2026〕101号）第二十四条 | AK21: 国网财务部 | AL21: 各级单位财务部 | AP21: =A21=[2]员工报账!A21 -> TRUE | AQ21: =B21=[2]员工报账!B21 -> TRUE | AR21: =C21=[2]员工报账!C21 -> TRUE | AS21: =D21=[2]员工报账!D21 -> TRUE | AT21: =E21=[2]员工报账!E21 -> TRUE | AU21: =F21=[2]员工报账!F21 -> TRUE | AV21: =G21=[2]员工报账!G21 -> TRUE | AW21: =H21=[2]员工报账!H21 -> TRUE | ... BZ21: =AK21=[2]员工报账!AK21 -> TRUE
I22: 员工报账业务-6.酒店预订-控制措施03 | J22: 财务部门加强出差申请与酒店订单的交叉复核，校验人员、时间、订单的合理性与唯一性。 | M22: √ | T22: 系统已建 | U22: 国网商旅 | V22: 1.出差报销单； 2.入住轨迹与异常情况反馈。 | W22: 各级单位-各部门-出差人员、各级单位-财务部门-成本管理人员、商旅云公司 | X22: 每日 | Y22: 全量检查 | AA22: 每年 | AB22: 抽查 | AD22: 员工差旅预订监督场景 | AE22: 每月 | AF22: 抽查 | AH22: 是 | AI22: 是 | AJ22: 《国家电网有限公司差旅费管理办法》（国家电网企管〔2026〕101号）第二十四条 | AK22: 国网财务部 | AL22: 各级单位财务部 | AN22: 修改责任主体 | AP22: =A22=[2]员工报账!A22 -> TRUE | AQ22: =B22=[2]员工报账!B22 -> TRUE | AR22: =C22=[2]员工报账!C22 -> TRUE | AS22: =D22=[2]员工报账!D22 -> TRUE | AT22: =E22=[2]员工报账!E22 -> TRUE | AU22: =F22=[2]员工报账!F22 -> TRUE | AV22: =G22=[2]员工报账!G22 -> TRUE | AW22: =H22=[2]员工报账!H22 -> TRUE | ... BZ22: =AK22=[2]员工报账!AK22 -> TRUE
C23: 税务合规 | D23: 差旅报销 | E23: 擅自扩大差旅费开支范围，提高差旅费开支标准，增加差旅出行成本。 | F23: 87.违规发放津贴补贴：存在多报差旅补贴、虚报差旅补贴等问题。 | G23: 7.差旅标准执行 | H23: 差旅费开支标准、开支范围符合本单位差旅费标准。 | I23: 员工报账业务-7.差旅标准执行-控制措施01 | J23: 商旅云公司完善差旅费超标刚性管控功能，系统对超标申请酒店、交通工具和差旅补助进行自动隐藏。 | M23: √ | R23: √ | T23: 系统已建 | U23: 国网商旅 | V23: 1.差旅标准系统校验规则库； 2.出差通知、培训通知等出差缘由证明材料； 3.出差审批单； 4.出差报销单。 | W23: 各级单位-财务部门-预算管理人员、各级单位-各部门-出差人员、各级单位-各部门-负责人、各级单位-财务部门-成本管理人员、商旅云公司 | X23: 每日 | Y23: 全量检查 | AA23: 每年 | AB23: 抽查 | AD23: 员工差旅费用标准监督场景 | AE23: 每月 | AF23: 抽查 | AH23: 是 | AI23: 是 | AJ23: 《国家电网有限公司差旅费管理办法》（国家电网企管〔2026〕101号）第八条、第十一条至第十九条 | AK23: 国网财务部 | AL23: 各级单位财务部 | AP23: =A23=[2]员工报账!A23 -> TRUE | AQ23: =B23=[2]员工报账!B23 -> TRUE | AR23: =C23=[2]员工报账!C23 -> TRUE | AS23: =D23=[2]员工报账!D23 -> TRUE | AT23: =E23=[2]员工报账!E23 -> TRUE | AU23: =F23=[2]员工报账!F23 -> TRUE | AV23: =G23=[2]员工报账!G23 -> TRUE | AW23: =H23=[2]员工报账!H23 -> TRUE | ... BZ23: =AK23=[2]员工报账!AK23 -> TRUE
I24: 员工报账业务-7.差旅标准执行-控制措施02 | J24: 财务部门加强出差类别与出差性质审核，重点关注评标、培训等特殊出差事项政策执行情况。 | M24: √ | Q24: √ | T24: 系统已建 | U24: 国网商旅 | V24: 1.差旅标准系统校验规则库； 2.出差通知、培训通知等出差缘由证明材料； 3.出差审批单； 4.出差报销单。 | W24: 各级单位-财务部门-预算管理人员、各级单位-各部门-负责人、各级单位-财务部门-成本管理人员、商旅云公司 | X24: 每日 | Y24: 全量检查 | AA24: 每年 | AB24: 抽查 | AD24: 员工差旅费用标准监督场景 | AE24: 每月 | AF24: 抽查 | AH24: 是 | AI24: 是 | AJ24: 《国家电网有限公司差旅费管理办法》（国家电网企管〔2026〕101号）第八条、第十一条至第十九条 | AK24: 国网财务部 | AL24: 各级单位财务部 | AP24: =A24=[2]员工报账!A24 -> TRUE | AQ24: =B24=[2]员工报账!B24 -> TRUE | AR24: =C24=[2]员工报账!C24 -> TRUE | AS24: =D24=[2]员工报账!D24 -> TRUE | AT24: =E24=[2]员工报账!E24 -> TRUE | AU24: =F24=[2]员工报账!F24 -> TRUE | AV24: =G24=[2]员工报账!G24 -> TRUE | AW24: =H24=[2]员工报账!H24 -> TRUE | ... BZ24: =AK24=[2]员工报账!AK24 -> TRUE
I25: 员工报账业务-7.差旅标准执行-控制措施03 | J25: 纪检部门推动退赔与整改机制，对超标报销行为依规严肃问责。 | R25: √ | S25: √ | T25: 线下管控 | V25: 1.问责证明材料。 | W25: 各级单位-财务部门-预算管理人员、各级单位-各部门-出差人员、各级单位-各部门-负责人、各级单位-财务部门-成本管理人员、商旅云公司、各级单位-纪检部门-纪检管理人员 | X25: 每日 | Y25: 全量检查 | AA25: 每年 | AB25: 抽查 | AD25: 员工差旅费用标准监督场景 | AE25: 每月 | AF25: 抽查 | AH25: 是 | AI25: 是 | AJ25: 《国家电网有限公司差旅费管理办法》（国家电网企管〔2026〕101号）第八条、第十一条至第十九条、《国网湖南省电力有限公司关于印发加强差旅费管理有关规定的通知》第一条 | AK25: 国网财务部 | AL25: 各级单位财务部 | AN25: 补充制度 | AP25: =A25=[2]员工报账!A25 -> TRUE | AQ25: =B25=[2]员工报账!B25 -> TRUE | AR25: =C25=[2]员工报账!C25 -> TRUE | AS25: =D25=[2]员工报账!D25 -> TRUE | AT25: =E25=[2]员工报账!E25 -> TRUE | AU25: =F25=[2]员工报账!F25 -> TRUE | AV25: =G25=[2]员工报账!G25 -> TRUE | AW25: =H25=[2]员工报账!H25 -> TRUE | ... BZ25: =AK25=[2]员工报账!AK25 -> TRUE
A26: 员工报账 | B26: 一、员工差旅 | C26: 资金资产安全 | D26: 差旅报销 | E26: 虚报冒领差旅费，虚列套取费用，导致资金安全风险。 | F26: 87.违规发放津贴补贴：存在多报差旅补贴、虚报差旅补贴等问题。 | G26: 8.差旅报销合规性控制 | H26: 交通费、公杂费、住宿费等报销真实发生，差旅费报销准确。 | I26: 员工报账业务-8.差旅报销合规性控制-控制措施01 | J26: 建立业务部门费用报销前置审核机制，对机票、酒店、火车、补助等金额准确性复核。 | M26: √ | Q26: √ | R26: √ | T26: 系统已建 | U26: 国网商旅 | V26: 1.出差通知、培训通知等出差缘由证明材料； 2.出差审批单； 3.预订的商旅订单； 4.发票； 5.考勤记录。 | W26: 各级单位-各部门-出差人员、各级单位-各部门-出差报销审核人、各级单位-财务部门-成本管理人员、商旅云公司 | X26: 每日 | Y26: 全量检查 | AA26: 每年 | AB26: 抽查 | AD26: 员工差旅报销监督场景 | AE26: 每月 | AF26: 抽查 | AH26: 是 | AI26: 是 | AJ26: 《国网财务部、后勤部关于进一步规范差旅伙食费和交通费收交管理有关事项的通知》第三条、第四条 《国家电网有限公司差旅费管理办法》（国家电网企管〔2026〕101号）第十二条、第十三条、第十七条、第二十四条 | AK26: 国网财务部 | AL26: 各级单位财务部 | AP26: =A26=[2]员工报账!A26 -> TRUE | AQ26: =B26=[2]员工报账!B26 -> TRUE | AR26: =C26=[2]员工报账!C26 -> TRUE | AS26: =D26=[2]员工报账!D26 -> TRUE | AT26: =E26=[2]员工报账!E26 -> TRUE | AU26: =F26=[2]员工报账!F26 -> TRUE | AV26: =G26=[2]员工报账!G26 -> TRUE | AW26: =H26=[2]员工报账!H26 -> TRUE | ... BZ26: =AK26=[2]员工报账!AK26 -> TRUE
I27: 员工报账业务-8.差旅报销合规性控制-控制措施02 | J27: 商旅云公司强化时空逻辑系统校验，对“出差时间-住宿时间-车票时间”进行自动校验，拦截或预警重叠数据。 | M27: √ | Q27: √ | T27: 系统已建 | U27: 国网商旅 | V27: 1.出差通知、培训通知等出差缘由证明材料； 2.出差审批单； 3.预订的商旅订单； 4.发票； 5.考勤记录。 | W27: 商旅云公司 | X27: 每日 | Y27: 全量检查 | AA27: 每年 | AB27: 抽查 | AD27: 员工差旅报销监督场景 | AE27: 每月 | AF27: 抽查 | AH27: 是 | AI27: 是 | AJ27: 《国网财务部、后勤部关于进一步规范差旅伙食费和交通费收交管理有关事项的通知》第三条、第四条 《国家电网有限公司差旅费管理办法》（国家电网企管〔2026〕101号第十二条、第十三条、第十七条、第二十四条 | AK27: 国网财务部 | AL27: 各级单位财务部 | AP27: =A27=[2]员工报账!A27 -> TRUE | AQ27: =B27=[2]员工报账!B27 -> TRUE | AR27: =C27=[2]员工报账!C27 -> TRUE | AS27: =D27=[2]员工报账!D27 -> TRUE | AT27: =E27=[2]员工报账!E27 -> TRUE | AU27: =F27=[2]员工报账!F27 -> TRUE | AV27: =G27=[2]员工报账!G27 -> TRUE | AW27: =H27=[2]员工报账!H27 -> TRUE | ... BZ27: =AK27=[2]员工报账!AK27 -> TRUE
I28: 员工报账业务-8.差旅报销合规性控制-控制措施03 | J28: 商旅云公司健全票据使用状态规则，重点筛查“未使用”的交通票据，防范员工利用废票虚报费用或重复报销。 | M28: √ | R28: √ | T28: 系统已建 | U28: 国网商旅 | V28: 1.出差通知、培训通知等出差缘由证明材料； 2.出差审批单； 3.预订的商旅订单； 4.发票； 5.考勤记录。 | W28: 各级单位-各部门-出差人员、各级单位-各部门-出差报销审核人、各级单位-财务部门-成本管理人员、商旅云公司 | X28: 每日 | Y28: 全量检查 | AA28: 每年 | AB28: 抽查 | AD28: 员工差旅报销监督场景 | AE28: 每月 | AF28: 抽查 | AH28: 是 | AI28: 是 | AJ28: 《国网财务部、后勤部关于进一步规范差旅伙食费和交通费收交管理有关事项的通知》第三条、第四条 《国家电网有限公司差旅费管理办法》（国家电网企管〔2026〕101号）第十七条、第二十四条 | AK28: 国网财务部 | AL28: 各级单位财务部 | AP28: =A28=[2]员工报账!A28 -> TRUE | AQ28: =B28=[2]员工报账!B28 -> TRUE | AR28: =C28=[2]员工报账!C28 -> TRUE | AS28: =D28=[2]员工报账!D28 -> TRUE | AT28: =E28=[2]员工报账!E28 -> TRUE | AU28: =F28=[2]员工报账!F28 -> TRUE | AV28: =G28=[2]员工报账!G28 -> TRUE | AW28: =H28=[2]员工报账!H28 -> TRUE | ... BZ28: =AK28=[2]员工报账!AK28 -> TRUE
I29: 员工报账业务-8.差旅报销合规性控制-控制措施04 | J29: 财务部门加强差旅报销审核力度，对同一时段连续出差公杂费、伙食补助费进行复核，避免重复计算。 | M29: √ | Q29: √ | T29: 系统已建 | U29: 国网商旅 | V29: 1.出差通知、培训通知等出差缘由证明材料； 2.出差审批单； 3.预订的商旅订单； 4.发票； 5.考勤记录。 | W29: 各级单位-各部门-出差人员、各级单位-各部门-出差报销审核人、各级单位-财务部门-成本管理人员、商旅云公司 | X29: 每日 | Y29: 全量检查 | AA29: 每年 | AB29: 抽查 | AD29: 员工差旅报销监督场景 | AE29: 每月 | AF29: 抽查 | AH29: 是 | AI29: 是 | AJ29: 《国网财务部、后勤部关于进一步规范差旅伙食费和交通费收交管理有关事项的通知》第三条、第四条 《国家电网有限公司差旅费管理办法》（国家电网企管〔2026〕101号第十二条、第十三条、第十七条、第二十四条 | AK29: 国网财务部 | AL29: 各级单位财务部 | AP29: =A29=[2]员工报账!A29 -> TRUE | AQ29: =B29=[2]员工报账!B29 -> TRUE | AR29: =C29=[2]员工报账!C29 -> TRUE | AS29: =D29=[2]员工报账!D29 -> TRUE | AT29: =E29=[2]员工报账!E29 -> TRUE | AU29: =F29=[2]员工报账!F29 -> TRUE | AV29: =G29=[2]员工报账!G29 -> TRUE | AW29: =H29=[2]员工报账!H29 -> TRUE | ... BZ29: =AK29=[2]员工报账!AK29 -> TRUE
A30: 员工报账 | B30: 一、员工差旅 | C30: 资金资产安全 | D30: 差旅报销 | E30: 虚报冒领差旅费，虚列套取费用，导致资金安全风险。 | F30: 87.违规发放津贴补贴：存在多报差旅补贴、虚报差旅补贴等问题。 | G30: 8.差旅报销合规性控制 | H30: 交通费、公杂费、住宿费等报销真实发生，差旅费报销准确。 | I30: 员工报账业务-8.差旅报销合规性控制-控制措施05 | J30: 纪检部门完善违规问责与闭环管理机制，对未缴纳伙食费用套取各类补助和虚报行为进行问责，追回资金，并纳入个人诚信记录。 | M30: √ | R30: √ | S30: √ | T30: 线下管控 | V30: 1.问责证明材料。 | W30: 各级单位-各部门-出差人员、各级单位-各部门-出差报销审核人、各级单位-财务部门-成本管理人员、商旅云公司、各级单位-纪检部门-纪检管理人员 | X30: 每日 | Y30: 全量检查 | AA30: 每年 | AB30: 抽查 | AD30: 员工差旅报销监督场景 | AE30: 每月 | AF30: 抽查 | AH30: 是 | AI30: 是 | AJ30: 《国网财务部、后勤部关于进一步规范差旅伙食费和交通费收交管理有关事项的通知》第三条、第四条 《国家电网有限公司差旅费管理办法》（国家电网企管〔2026〕101号）第十七条、第二十四条、《国网湖南省电力有限公司关于印发加强差旅费管理有关规定的通知》第一条 | AK30: 国网财务部 | AL30: 各级单位财务部 | AN30: 补充制度 | AP30: =A30=[2]员工报账!A30 -> TRUE | AQ30: =B30=[2]员工报账!B30 -> TRUE | AR30: =C30=[2]员工报账!C30 -> TRUE | AS30: =D30=[2]员工报账!D30 -> TRUE | AT30: =E30=[2]员工报账!E30 -> TRUE | AU30: =F30=[2]员工报账!F30 -> TRUE | AV30: =G30=[2]员工报账!G30 -> TRUE | AW30: =H30=[2]员工报账!H30 -> TRUE | ... BZ30: =AK30=[2]员工报账!AK30 -> TRUE
E31: 员工自付单据中的人员、时间与地点未在出差范围内，虚报支出，套取资金，导致公司经济利益受损。 | G31: 9.自付单据审核 | H31: 自付单据中人员、时间、地点与出差申请单一致，自付交通费、住宿费符合差旅费标准。 | I31: 员工报账业务-9.自付单据审核-控制措施01 | J31: 商旅云公司健全“单轨控制”，系统强制关联“已完成审批单”与“线上支付订单”，并推动与税务平台直连，减少发票人工上传环节。 | S31: √ | T31: 系统待建 | U31: 国网商旅 | V31: 1.发票； 2.差旅费标准； 3.出差通知、培训通知等出差缘由证明材料； 4.出差审批单； 5.出差报销单。 | W31: 各级单位-各部门-出差人员、商旅云公司 | X31: 每日 | Y31: 全量检查 | AA31: 每年 | AB31: 抽查 | AD31: 员工差旅报销监督场景 | AE31: 每月 | AF31: 抽查 | AH31: 是 | AI31: 是 | AJ31: 《国家电网有限公司差旅费管理办法》（国家电网企管〔2026〕101号）第八条、第十一条、第二十四条 | AK31: 国网财务部 | AL31: 各级单位财务部 | AP31: =A31=[2]员工报账!A31 -> TRUE | AQ31: =B31=[2]员工报账!B31 -> TRUE | AR31: =C31=[2]员工报账!C31 -> TRUE | AS31: =D31=[2]员工报账!D31 -> TRUE | AT31: =E31=[2]员工报账!E31 -> TRUE | AU31: =F31=[2]员工报账!F31 -> TRUE | AV31: =G31=[2]员工报账!G31 -> TRUE | AW31: =H31=[2]员工报账!H31 -> TRUE | ... BZ31: =AK31=[2]员工报账!AK31 -> TRUE
I32: 员工报账业务-9.自付单据审核-控制措施02 | J32: 强化线下报销验证，未实现系统“单轨控制”的单位强化事前审批，强制“行程轨迹佐证”，同时借助第三方工具“建立发票真伪与重复报销”校验机制。 | M32: √ | Q32: √ | R32: √ | T32: 线下管控 | V32: 1.发票； 2.差旅费标准； 3.出差通知、培训通知等出差缘由证明材料； 4.出差审批单； 5.出差报销单。 | W32: 各级单位-各部门-出差人员、各级单位-各部门-负责人、商旅云公司 | X32: 每日 | Y32: 全量检查 | AA32: 每年 | AB32: 抽查 | AD32: 员工差旅报销监督场景 | AE32: 每月 | AF32: 抽查 | AH32: 是 | AI32: 是 | AJ32: 《国家电网有限公司差旅费管理办法》（国家电网企管〔2026〕101号）第八条、第十一条、第二十四条 | AK32: 国网财务部 | AL32: 各级单位财务部 | AN32: 修改责任主体 | AP32: =A32=[2]员工报账!A32 -> TRUE | AQ32: =B32=[2]员工报账!B32 -> TRUE | AR32: =C32=[2]员工报账!C32 -> TRUE | AS32: =D32=[2]员工报账!D32 -> TRUE | AT32: =E32=[2]员工报账!E32 -> TRUE | AU32: =F32=[2]员工报账!F32 -> TRUE | AV32: =G32=[2]员工报账!G32 -> TRUE | AW32: =H32=[2]员工报账!H32 -> TRUE | ... BZ32: =AK32=[2]员工报账!AK32 -> TRUE
I33: 员工报账业务-9.自付单据审核-控制措施03 | J33: 财务部门规范自付单据与标准审核流程，逐一核对自付单据人员、时间、地点，并审核费用标准是否符合公司规定。 | M33: √ | Q33: √ | R33: √ | T33: 系统已建 | U33: 国网商旅 | V33: 1.发票； 2.差旅费标准； 3.出差通知、培训通知等出差缘由证明材料； 4.出差审批单； 5.出差报销单。 | W33: 各级单位-各部门-出差人员、商旅云公司、各级单位-财务部门-成本管理人员 | X33: 每日 | Y33: 全量检查 | AA33: 每年 | AB33: 抽查 | AD33: 员工差旅报销监督场景 | AE33: 每月 | AF33: 抽查 | AH33: 是 | AI33: 是 | AJ33: 《国家电网有限公司差旅费管理办法》（国家电网企管〔2026〕101号）第八条、第十一条、第二十四条 | AK33: 国网财务部 | AL33: 各级单位财务部 | AP33: =A33=[2]员工报账!A33 -> TRUE | AQ33: =B33=[2]员工报账!B33 -> TRUE | AR33: =C33=[2]员工报账!C33 -> TRUE | AS33: =D33=[2]员工报账!D33 -> TRUE | AT33: =E33=[2]员工报账!E33 -> TRUE | AU33: =F33=[2]员工报账!F33 -> TRUE | AV33: =G33=[2]员工报账!G33 -> TRUE | AW33: =H33=[2]员工报账!H33 -> TRUE | ... BZ33: =AK33=[2]员工报账!AK33 -> TRUE
I34: 员工报账业务-9.自付单据审核-控制措施04 | J34: 纪检部门严肃查处违规行为，追回资金损失，严肃查处并予以通报。 | M34: √ | R34: √ | T34: 线下管控 | V34: 1.商旅平台数据线上预订率、电子票据抓取率。 | W34: 各级单位-各部门-出差人员、商旅云公司、各级单位-纪检部门-纪检管理人员 | X34: 每日 | Y34: 全量检查 | AA34: 每年 | AB34: 抽查 | AD34: 员工差旅报销监督场景 | AE34: 每月 | AF34: 抽查 | AH34: 是 | AI34: 是 | AJ34: 《国家电网有限公司差旅费管理办法》（国家电网企管〔2026〕101号）第八条、第十一条、第二十四条、《国网湖南省电力有限公司关于印发加强差旅费管理有关规定的通知》第一条 | AK34: 国网财务部 | AL34: 各级单位财务部 | AN34: 补充制度 | AP34: =A34=[2]员工报账!A34 -> TRUE | AQ34: =B34=[2]员工报账!B34 -> TRUE | AR34: =C34=[2]员工报账!C34 -> TRUE | AS34: =D34=[2]员工报账!D34 -> TRUE | AT34: =E34=[2]员工报账!E34 -> TRUE | AU34: =F34=[2]员工报账!F34 -> TRUE | AV34: =G34=[2]员工报账!G34 -> TRUE | AW34: =H34=[2]员工报账!H34 -> TRUE | ... BZ34: =AK34=[2]员工报账!AK34 -> TRUE
A35: 员工报账 | B35: 一、员工差旅 | C35: 税务合规、资金资产安全 | D35: 报销申请 | E35: 成本费用报销事项不真实、审批流程不规范，导致成本入账科目错误、虚列成本费用、套取资金私设“小金库”。 | G35: 10.报销事项合规性控制 | H35: 在规定列支范围内，以真实发生的事项发起报销申请，履行规范审批流程。 | I35: 员工报账业务-10.报销事项合规性控制-控制措施01 | J35: 费用报销部门履行费用报销分级授权审批流程，对报销申请事项的真实性进行人工复核，复核报销审批单、费用明细清单、发票或收据、合同或协议等附件的完整性。 | L35: √ | R35: √ | T35: 线下管控 | V35: 1.成本费用报销审批单； 2.费用明细清单； 3.发票或收据； 4.合同或协议； 5.系统审批记录。 | W35: 各级单位-各部门-报账人员、各级单位-各部门-负责人、各级单位-财务部门-成本管理人员 | X35: 每季度 | Y35: 抽查 | AA35: 每年 | AB35: 抽查 | AD35: 报销真实性监督场景 | AE35: 每年 | AF35: 抽查 | AH35: 是 | AI35: 是 | AJ35: 《国家电网有限公司会计基础管理办法》（国家电网企管〔2019〕132号）第八条、第五十四条 《关于加强中央企业资金内部控制管理有关事项的通知》（国资发监督〔2021〕19 号）第十三条、《国网湖南省电力有限公司关于印发加强差旅费管理有关规定的通知》第一条 | AK35: 国网财务部、国网企管部、国网后勤部、国网国际部 | AL35: 各级单位财务部、各级单位企管部（人资部）、各级单位后勤部、 | AN35: 补充制度 | AP35: =A35=[2]员工报账!A35 -> TRUE | AQ35: =B35=[2]员工报账!B35 -> TRUE | AR35: =C35=[2]员工报账!C35 -> TRUE | AS35: =D35=[2]员工报账!D35 -> TRUE | AT35: =E35=[2]员工报账!E35 -> TRUE | AU35: =F35=[2]员工报账!F35 -> TRUE | AV35: =G35=[2]员工报账!G35 -> TRUE | AW35: =H35=[2]员工报账!H35 -> TRUE | ... BZ35: =AK35=[2]员工报账!AK35 -> TRUE
I36: 员工报账业务-10.报销事项合规性控制-控制措施02 | J36: 加强挂职人员费用报销成本中心校验，挂职期间费用报销申请需选择挂职单位成本中心。 | Q36: √ | T36: 系统已建 | U36: 智慧共享财务平台 | V36: 1.成本费用报销审批单； 2.费用明细清单； 3.发票或收据； 4.合同或协议； 5.系统审批记录。 | W36: 各级单位-各部门-报账人员、各级单位-各部门-负责人、各级单位-财务部门-成本管理人员 | X36: 每季度 | Y36: 抽查 | AA36: 每年 | AB36: 抽查 | AD36: 报销真实性监督场景 | AE36: 每年 | AF36: 抽查 | AH36: 是 | AI36: 是 | AJ36: 《国家电网有限公司会计基础管理办法》（国家电网企管〔2019〕132号）第八条、第五十四条 《关于加强中央企业资金内部控制管理有关事项的通知》（国资发监督〔2021〕19 号）第十三条、《国网湖南省电力有限公司关于印发加强差旅费管理有关规定的通知》第三条 | AK36: 国网财务部、国网企管部、国网后勤部、国网国际部 | AL36: 各级单位财务部、各级单位企管部（人资部）、各级单位后勤部、 | AN36: 补充制度 | AP36: =A36=[2]员工报账!A36 -> TRUE | AQ36: =B36=[2]员工报账!B36 -> TRUE | AR36: =C36=[2]员工报账!C36 -> TRUE | AS36: =D36=[2]员工报账!D36 -> TRUE | AT36: =E36=[2]员工报账!E36 -> TRUE | AU36: =F36=[2]员工报账!F36 -> TRUE | AV36: =G36=[2]员工报账!G36 -> TRUE | AW36: =H36=[2]员工报账!H36 -> TRUE | ... BZ36: =AK36=[2]员工报账!AK36 -> TRUE
I37: 员工报账业务-10.报销事项合规性控制-控制措施03 | J37: 财务部门对费用报销选择业务事项准确性进行复核，校验报销流程和成本中心准确性。 | M37: √ | Q37: √ | T37: 系统已建 | U37: 智慧共享财务平台 | V37: 1.成本费用报销审批单； 2.费用明细清单； 3.发票或收据； 4.合同或协议； 5.系统审批记录。 | W37: 各级单位-各部门-报账人员、各级单位-各部门-负责人、各级单位-财务部门-成本管理人员 | X37: 每季度 | Y37: 抽查 | AA37: 每年 | AB37: 抽查 | AD37: 报销真实性监督场景 | AE37: 每年 | AF37: 抽查 | AH37: 是 | AI37: 是 | AJ37: 《国家电网有限公司会计基础管理办法》（国家电网企管〔2019〕132号）第八条、第五十四条 《关于加强中央企业资金内部控制管理有关事项的通知》（国资发监督〔2021〕19 号）第十三条 | AK37: 国网财务部、国网企管部、国网后勤部、国网国际部 | AL37: 各级单位财务部、各级单位企管部（人资部）、各级单位后勤部、 | AP37: =A37=[2]员工报账!A37 -> TRUE | AQ37: =B37=[2]员工报账!B37 -> TRUE | AR37: =C37=[2]员工报账!C37 -> TRUE | AS37: =D37=[2]员工报账!D37 -> TRUE | AT37: =E37=[2]员工报账!E37 -> TRUE | AU37: =F37=[2]员工报账!F37 -> TRUE | AV37: =G37=[2]员工报账!G37 -> TRUE | AW37: =H37=[2]员工报账!H37 -> TRUE | ... BZ37: =AK37=[2]员工报账!AK37 -> TRUE
I38: 员工报账业务-10.报销事项合规性控制-控制措施04 | J38: 进行违规责任追究，对虚列成本费用、套取资金私设“小金库”的人员根据相关规定进行违规责任追究。 | R38: √ | T38: 线下管控 | V38: 1.责任追究证明材料。 | W38: 各级单位-各部门-报账人员、各级单位-各部门-负责人、各级单位-财务部门-成本管理人员、各级单位-纪检部门-纪检管理人员 | X38: 每季度 | Y38: 抽查 | AA38: 每年 | AB38: 抽查 | AD38: 报销真实性监督场景 | AE38: 每年 | AF38: 抽查 | AH38: 是 | AI38: 是 | AJ38: 《国家电网有限公司会计基础管理办法》（国家电网企管〔2019〕132号）第八条、第五十四条 《关于加强中央企业资金内部控制管理有关事项的通知》（国资发监督〔2021〕19 号）第十三条 | AK38: 国网财务部、国网企管部、国网后勤部、国网国际部 | AL38: 各级单位财务部、各级单位企管部（人资部）、各级单位后勤部、 | AP38: =A38=[2]员工报账!A38 -> TRUE | AQ38: =B38=[2]员工报账!B38 -> TRUE | AR38: =C38=[2]员工报账!C38 -> TRUE | AS38: =D38=[2]员工报账!D38 -> TRUE | AT38: =E38=[2]员工报账!E38 -> TRUE | AU38: =F38=[2]员工报账!F38 -> TRUE | AV38: =G38=[2]员工报账!G38 -> TRUE | AW38: =H38=[2]员工报账!H38 -> TRUE | ... BZ38: =AK38=[2]员工报账!AK38 -> TRUE
B39: 二、通用报账 | C39: 税务合规 | D39: 费用报销 | E39: 发票信息不准确、不完整，与报销业务不一致导致税务风险 | G39: 11.报销发票审核 | H39: 报销发票真实、准确、完整 | I39: 员工报账业务-11.报销发票审核-控制措施01 | J39: 归口管理部门对报销发票、入库单、采购订单物品对应关系进行复核，确认购物清单通过税务防伪系统开具。 | L39: √ | M39: √ | T39: 系统已建 | U39: 智慧共享财务平台 | V39: 1.成本费用报销申请单； 2.费用明细清单； 3.发票或收据、购物清单； 4.合同或协议。 | W39: 各级单位-各部门-报账人员、各级单位-各部门-负责人、各级单位-财务部门-成本管理人员 | X39: 每季度 | Y39: 抽查 | AA39: 每年 | AB39: 抽查 | AD39: 发票审核管理监督场景 | AE39: 每年 | AF39: 抽查 | AH39: 是 | AI39: 是 | AJ39: 国家电网企管〔2019〕132号《国家电网有限公司会计基础管理办法》第五十条 | AK39: 国网财务部、国网企管部、国网后勤部、国网国际部 | AL39: 各级单位财务部、各级单位企管部（人资部）、各级单位后勤部、 | AP39: =A39=[2]员工报账!A39 -> TRUE | AQ39: =B39=[2]员工报账!B39 -> TRUE | AR39: =C39=[2]员工报账!C39 -> TRUE | AS39: =D39=[2]员工报账!D39 -> TRUE | AT39: =E39=[2]员工报账!E39 -> TRUE | AU39: =F39=[2]员工报账!F39 -> TRUE | AV39: =G39=[2]员工报账!G39 -> TRUE | AW39: =H39=[2]员工报账!H39 -> TRUE | ... BZ39: =AK39=[2]员工报账!AK39 -> TRUE
I40: 员工报账业务-11.报销发票审核-控制措施02 | J40: 各部门建立发票“谁提交、谁审核、谁负责”闭环管理机制,发票提交人落实发票验真责任。 | M40: √ | R40: √ | T40: 系统已建 | U40: 智慧共享财务平台 | V40: 1.成本费用报销申请单； 2.费用明细清单； 3.发票或收据、购物清单； 4.合同或协议。 | W40: 各级单位-各部门-报账人员、各级单位-各部门-负责人 | X40: 每季度 | Y40: 抽查 | AA40: 每年 | AB40: 抽查 | AD40: 发票审核管理监督场景 | AE40: 每年 | AF40: 抽查 | AH40: 是 | AI40: 是 | AJ40: 国家电网企管〔2019〕132号《国家电网有限公司会计基础管理办法》第五十条 | AK40: 国网企管部、国网后勤部、国网国际部 | AL40: 各级单位财务部、各级单位企管部（人资部）、各级单位后勤部 | AP40: =A40=[2]员工报账!A40 -> TRUE | AQ40: =B40=[2]员工报账!B40 -> TRUE | AR40: =C40=[2]员工报账!C40 -> TRUE | AS40: =D40=[2]员工报账!D40 -> TRUE | AT40: =E40=[2]员工报账!E40 -> TRUE | AU40: =F40=[2]员工报账!F40 -> TRUE | AV40: =G40=[2]员工报账!G40 -> TRUE | AW40: =H40=[2]员工报账!H40 -> TRUE | ... BZ40: =AK40=[2]员工报账!AK40 -> TRUE
A41: 员工报账 | B41: 二、通用报账 | C41: 税务合规 | D41: 费用报销 | E41: 发票信息不准确、不完整，与报销业务不一致导致税务风险 | G41: 11.报销发票审核 | H41: 报销发票真实、准确、完整 | I41: 员工报账业务-11.报销发票审核-控制措施03 | J41: 发票提交人对增值税发票税率与合同条款进行复核，确认货物及应税劳务名称准确、金额及税率与合同一致，确认发票项目开票明细【开票方信息】名称中不包含“茶叶、烟、酒水、门票、景区”等敏感字眼，确认销售方名称中不包含“会所、健身房、俱乐部、KTV、景区、洗浴中心”等敏感字眼。 | O41: √ | T41: 系统已建 | U41: 智慧共享财务平台 | V41: 1.成本费用报销申请单； 2.费用明细清单； 3.发票或收据、购物清单； 4.合同或协议。 | W41: 各级单位-各部门-报账人员、各级单位-各部门-负责人 | X41: 每季度 | Y41: 抽查 | AA41: 每年 | AB41: 抽查 | AD41: 发票审核管理监督场景 | AE41: 每年 | AF41: 抽查 | AH41: 是 | AI41: 是 | AJ41: 国家电网企管〔2019〕132号《国家电网有限公司会计基础管理办法》第五十条 | AK41: 国网财务部、国网企管部、国网后勤部、国网国际部 | AL41: 各级单位财务部、各级单位企管部（人资部）、各级单位后勤部 | AN41: 修改控制方式，修改控制系统，线上改为线下 | AO41: 修改控制措施 | AP41: =A41=[2]员工报账!A41 -> TRUE | AQ41: =B41=[2]员工报账!B41 -> TRUE | AR41: =C41=[2]员工报账!C41 -> TRUE | AS41: =D41=[2]员工报账!D41 -> TRUE | AT41: =E41=[2]员工报账!E41 -> TRUE | AU41: =F41=[2]员工报账!F41 -> TRUE | AV41: =G41=[2]员工报账!G41 -> TRUE | AW41: =H41=[2]员工报账!H41 -> TRUE | ... BZ41: =AK41=[2]员工报账!AK41 -> TRUE
I42: 员工报账业务-11.报销发票审核-控制措施04 | J42: 财务部门对发票开具的完整性、合规性进行复核，检查发票名目是否包含固定资产目录所列资产，福利费增值税进项税不得抵扣。 | Q42: √ | R42: √ | T42: 线下管控 | V42: 1.成本费用报销申请单； 2.费用明细清单； 3.发票或收据、购物清单； 4.合同或协议。 | W42: 各级单位-各部门-报账人员、各级单位-各部门-负责人、各级单位-财务部门-成本管理人员 | X42: 每季度 | Y42: 抽查 | AA42: 每年 | AB42: 抽查 | AD42: 发票审核管理监督场景 | AE42: 每年 | AF42: 抽查 | AH42: 是 | AI42: 是 | AJ42: 国家电网企管〔2019〕132号《国家电网有限公司会计基础管理办法》第五十条 | AK42: 国网财务部、国网企管部、国网后勤部、国网国际部 | AL42: 各级单位财务部、各级单位企管部（人资部）、各级单位后勤部 | AP42: =A42=[2]员工报账!A42 -> TRUE | AQ42: =B42=[2]员工报账!B42 -> TRUE | AR42: =C42=[2]员工报账!C42 -> TRUE | AS42: =D42=[2]员工报账!D42 -> TRUE | AT42: =E42=[2]员工报账!E42 -> TRUE | AU42: =F42=[2]员工报账!F42 -> TRUE | AV42: =G42=[2]员工报账!G42 -> TRUE | AW42: =H42=[2]员工报账!H42 -> TRUE | ... BZ42: =AK42=[2]员工报账!AK42 -> TRUE
I43: 员工报账业务-11.报销发票审核-控制措施05 | J43: 财务人员对开具虚假发票套取资金等问题进行复核。 | M43: √ | Q43: √ | T43: 线下管控 | V43: 1.成本费用报销申请单； 2.费用明细清单； 3.发票或收据、购物清单； 4.合同或协议。 | W43: 各级单位-各部门-报账人员、各级单位-各部门-负责人、各级单位-财务部门-成本管理人员、各级单位-财务部门-税务管理人员 | X43: 每季度 | Y43: 抽查 | AA43: 每年 | AB43: 抽查 | AD43: 发票审核管理监督场景 | AE43: 每年 | AF43: 抽查 | AH43: 是 | AI43: 是 | AJ43: 国家电网企管〔2019〕132号《国家电网有限公司会计基础管理办法》第五十条 | AK43: 国网财务部、国网企管部、国网后勤部、国网国际部 | AL43: 各级单位财务部、各级单位企管部（人资部）、各级单位后勤部 | AN43: 修改责任主体 | AP43: =A43=[2]员工报账!A43 -> TRUE | AQ43: =B43=[2]员工报账!B43 -> TRUE | AR43: =C43=[2]员工报账!C43 -> TRUE | AS43: =D43=[2]员工报账!D43 -> TRUE | AT43: =E43=[2]员工报账!E43 -> TRUE | AU43: =F43=[2]员工报账!F43 -> TRUE | AV43: =G43=[2]员工报账!G43 -> TRUE | AW43: =H43=[2]员工报账!H43 -> TRUE | ... BZ43: =AK43=[2]员工报账!AK43 -> TRUE
D44: 公务接待活动 | E44: 未严格执行公务接待制度，虚列公务接待清单套取公务接待费用，引发资金支出及合规风险。 | G44: 12.公务接待范围、执行制度、费用报销 | H44: 严格执行公务接待制度，确保公务接待费支出规范。 | I44: 员工报账业务-12.公务接待范围、执行制度、费用报销-控制措施01 | J44: 接待部门做好公务接待过程管控。①严格公务接待审批。按照《国家电网有限公司公务接待管理办法》要求，根据公函内容中来访对象、人数等，报相应公司（或部门）领导审批。②规范公务接待组织。承办部门公务接待要严格按照本单位贯彻落实中央八项规定实施细则有关规定执行。严控陪同人数，不得层层多人陪同等。③严格执行清单制度。按照《国家电网有限公司公务接待管理办法》要求，公务活动结束后，接待部门应当如实填写接待清单，包括接待对象的单位、姓名、职务和接待项目、时间、场所、费用等内容，经本部门负责同志审签。④规范做好报销。接待费用应当及时结算，不得用公款报销或者支付应当由个人负担的费用。禁止借公务接待名义列支其他支出等。 | M44: √ | T44: 线下管控 | V44: 1.派出单位公函(或通知)； 2.公务接待清单； 3.财务票据。 | W44: 各级单位-接待承办部门-报账人员、各级单位-接待承办部门-负责人、各级单位-接待管理部门-接待管理人员、各级单位-接待管理部门-负责人 | X44: 每季度 | Y44: 抽查 | AA44: 每年 | AB44: 抽查 | AD44: 公务接待费列支范围监督场景 | AE44: 每年 | AF44: 抽查 | AH44: 是 | AI44: 是 | AJ44: 《国家电网有限公司厉行节约反对浪费实施办法》（国家电网企管〔2025〕421号）第二十四条 《关于做好会议、接待管理相关事项报备报批工作的通知》（办值通〔2025〕55号） 《国家电网有限公司公务接待管理办法》国家电网企管〔2025〕267号 第五至十九 | AK44: 国网办公室 | AL44: 各级单位办公室 | AP44: =A44=[2]员工报账!A44 -> TRUE | AQ44: =B44=[2]员工报账!B44 -> TRUE | AR44: =C44=[2]员工报账!C44 -> TRUE | AS44: =D44=[2]员工报账!D44 -> TRUE | AT44: =E44=[2]员工报账!E44 -> TRUE | AU44: =F44=[2]员工报账!F44 -> TRUE | AV44: =G44=[2]员工报账!G44 -> TRUE | AW44: =H44=[2]员工报账!H44 -> TRUE | ... BZ44: =AK44=[2]员工报账!AK44 -> TRUE
A45: 员工报账 | B45: 二、通用报账 | C45: 税务合规 | D45: 公务接待活动 | E45: 未严格执行公务接待制度，虚列公务接待清单套取公务接待费用，引发资金支出及合规风险。 | G45: 12.公务接待范围、执行制度、费用报销 | H45: 严格执行公务接待制度，确保公务接待费支出规范。 | I45: 员工报账业务-12.公务接待范围、执行制度、费用报销-控制措施02 | J45: 归口管理部门做好复核。对接待部门提交的接待清单中人员、住宿安排、用车安排、费用等进行复核。 | L45: √ | T45: 线下管控 | V45: 1.派出单位公函(或通知)； 2.公务接待清单； 3.财务票据。 | W45: 各级单位-接待承办部门-报账人员、各级单位-接待承办部门-负责人、各级单位-接待管理部门-接待管理人员、各级单位-接待管理部门-负责人 | X45: 每季度 | Y45: 抽查 | AA45: 每年 | AB45: 抽查 | AD45: 公务接待费列支范围监督场景 | AE45: 每年 | AF45: 抽查 | AH45: 是 | AI45: 是 | AJ45: 《国家电网有限公司厉行节约反对浪费实施办法》（国家电网企管〔2025〕421号）第二十四条 《关于做好会议、接待管理相关事项报备报批工作的通知》（办值通〔2025〕55号） 《国家电网有限公司公务接待管理办法》国家电网企管〔2025〕267号 第五至十九条 | AK45: 国网办公室 | AL45: 各级单位办公室 | AP45: =A45=[2]员工报账!A45 -> TRUE | AQ45: =B45=[2]员工报账!B45 -> TRUE | AR45: =C45=[2]员工报账!C45 -> TRUE | AS45: =D45=[2]员工报账!D45 -> TRUE | AT45: =E45=[2]员工报账!E45 -> TRUE | AU45: =F45=[2]员工报账!F45 -> TRUE | AV45: =G45=[2]员工报账!G45 -> TRUE | AW45: =H45=[2]员工报账!H45 -> TRUE | ... BZ45: =AK45=[2]员工报账!AK45 -> TRUE
I46: 员工报账业务-12.公务接待范围、执行制度、费用报销-控制措施03 | J46: 财务部门做好报销审核。按照财务业务流程要求，做好报销审核、检查材料完备。 | Q46: √ | R46: √ | T46: 线下管控 | V46: 1.派出单位公函(或通知)； 2.公务接待清单； 3.财务票据。 | W46: 各级单位-接待承办部门-报账人员、各级单位-接待承办部门-负责人、各级单位-接待管理部门-接待管理人员、各级单位-接待管理部门-负责人、各级单位-财务部门-成本管理人员 | X46: 每季度 | Y46: 抽查 | AA46: 每年 | AB46: 抽查 | AD46: 公务接待费列支范围监督场景 | AE46: 每年 | AF46: 抽查 | AH46: 是 | AI46: 是 | AJ46: 《国家电网有限公司厉行节约反对浪费实施办法》（国家电网企管〔2025〕421号）第二十四条 《关于做好会议、接待管理相关事项报备报批工作的通知》（办值通〔2025〕55号） 《国家电网有限公司公务接待管理办法》国家电网企管〔2025〕267号 第五至十九条 | AK46: 国网办公室 | AL46: 各级单位办公室 | AP46: =A46=[2]员工报账!A46 -> TRUE | AQ46: =B46=[2]员工报账!B46 -> TRUE | AR46: =C46=[2]员工报账!C46 -> TRUE | AS46: =D46=[2]员工报账!D46 -> TRUE | AT46: =E46=[2]员工报账!E46 -> TRUE | AU46: =F46=[2]员工报账!F46 -> TRUE | AV46: =G46=[2]员工报账!G46 -> TRUE | AW46: =H46=[2]员工报账!H46 -> TRUE | ... BZ46: =AK46=[2]员工报账!AK46 -> TRUE
C47: 资金资产安全 | D47: 公务车辆单车核算 | E47: 员工未严格执行公务车辆单车核算要求，通过伪造票据、虚报里程、费用金额、虚构用车场景等方式套取企业资金，导致企业成本虚增、资金流失风险。 | F47: 82.公务用车管控不严：存在新购置及长租公务用车未及时接入统一车辆管理平台过程监督管理；在公务用车维修等费用中虚列名目、处理其他无关费用或费用依据不足；超编超标超范围配置公务用车等问题。 | G47: 13.公务车辆单车核算管理 | H47: 严格执行公务车辆单车核算管理要求，据实报销车辆使用费。 | I47: 员工报账业务-13.公务车辆单车核算管理-控制措施01 | J47: 通过统一车辆平台进行系统控制，自动比对用车时间、目的地与车辆通行费发票时间、行程轨迹的匹配性，规避虚列费用。 | M47: √ | T47: 系统待建 | U47: 统一车辆平台 | V47: 1.公务车辆管理台账； 2.车辆单车核算台账； 3.ETC通行费明细清单； 4.费用明细清单； 5.发票或收据； 6.合同或协议。 | W47: 各级单位-公务车辆管理部门-车辆管理人员、各级单位-公务车辆管理部门-负责人 | X47: 每季度 | Y47: 抽查 | AA47: 每年 | AB47: 抽查 | AD47: 车辆使用费监督场景 | AE47: 每年 | AF47: 抽查 | AH47: 是 | AI47: 是 | AJ47: 《国家电网有限公司公务用车管理办法》（规章制度编号:国网(后勤/2)724-2025）第十一至十九条、第二十一条、第三十二条. | AK47: 国网后勤部 | AL47: 各级单位后勤部 | AP47: =A47=[2]员工报账!A47 -> TRUE | AQ47: =B47=[2]员工报账!B47 -> TRUE | AR47: =C47=[2]员工报账!C47 -> TRUE | AS47: =D47=[2]员工报账!D47 -> TRUE | AT47: =E47=[2]员工报账!E47 -> TRUE | AU47: =F47=[2]员工报账!F47 -> TRUE | AV47: =G47=[2]员工报账!G47 -> TRUE | AW47: =H47=[2]员工报账!H47 -> TRUE | ... BZ47: =AK47=[2]员工报账!AK47 -> TRUE
I48: 员工报账业务-13.公务车辆单车核算管理-控制措施02 | J48: 系统直联控制，通过智慧共享财务平台直联统一车辆平台对单车核算台账明细进行系统控制，严禁列支保养、维修、年检、燃油等范围外费用，增加“车辆费用类型白名单”控制，超出范围的费用类型系统自动拒绝，并推送异常报告。 | N48: √ | O48: √ | T48: 系统待建 | U48: 智慧共享财务平台 | V48: 1.公务车辆管理台账； 2.车辆单车核算台账； 3.ETC通行费明细清单； 4.费用明细清单； 5.发票或收据； 6.合同或协议。 | W48: 各级单位-公务车辆管理部门-车辆管理人员、各级单位-公务车辆管理部门-负责人 | X48: 每季度 | Y48: 抽查 | AA48: 每年 | AB48: 抽查 | AD48: 车辆使用费监督场景 | AE48: 每年 | AF48: 抽查 | AH48: 是 | AI48: 是 | AJ48: 《国家电网有限公司公务用车管理办法》（规章制度编号:国网(后勤/2)724-2025）第十一至十九条、第二十一条、第三十二条. | AK48: 国网后勤部 | AL48: 各级单位后勤部 | AP48: =A48=[2]员工报账!A48 -> TRUE | AQ48: =B48=[2]员工报账!B48 -> TRUE | AR48: =C48=[2]员工报账!C48 -> TRUE | AS48: =D48=[2]员工报账!D48 -> TRUE | AT48: =E48=[2]员工报账!E48 -> TRUE | AU48: =F48=[2]员工报账!F48 -> TRUE | AV48: =G48=[2]员工报账!G48 -> TRUE | AW48: =H48=[2]员工报账!H48 -> TRUE | ... BZ48: =AK48=[2]员工报账!AK48 -> TRUE
A49: 员工报账 | B49: 二、通用报账 | C49: 资金资产安全 | D49: 公务车辆单车核算 | E49: 员工未严格执行公务车辆单车核算要求，通过伪造票据、虚报里程、费用金额、虚构用车场景等方式套取企业资金，导致企业成本虚增、资金流失风险。 | F49: 82.公务用车管控不严：存在新购置及长租公务用车未及时接入统一车辆管理平台过程监督管理；在公务用车维修等费用中虚列名目、处理其他无关费用或费用依据不足；超编超标超范围配置公务用车等问题。 | I49: 员工报账业务-13.公务车辆单车核算管理-控制措施03 | J49: 未实现系统直联控制的单位应加强线下审核，车辆管理部门对单车费用明细（油费、过路费、停车费、维修费等）与用车申请单（事前提交，注明用车时间、事由、目的地）、车辆行驶里程记录（行车记录、起止日期）进行复核，严禁套取费用。 | M49: √ | R49: √ | T49: 线下管控 | V49: 1.公务车辆管理台账； 2.车辆单车核算台账； 3.ETC通行费明细清单； 4.费用明细清单； 5.发票或收据； 6.合同或协议。 | W49: 各级单位-公务车辆管理部门-车辆管理人员、各级单位-公务车辆管理部门-负责人、各级单位-财务部门-成本管理人员 | X49: 每季度 | Y49: 抽查 | AA49: 每年 | AB49: 抽查 | AD49: 车辆使用费监督场景 | AE49: 每年 | AF49: 抽查 | AH49: 是 | AI49: 是 | AJ49: 《国家电网有限公司公务用车管理办法》（规章制度编号:国网(后勤/2)724-2025）第十一至十九条、第二十一条、第三十二条. | AK49: 国网后勤部 | AL49: 各级单位后勤部 | AP49: =A49=[2]员工报账!A49 -> TRUE | AQ49: =B49=[2]员工报账!B49 -> TRUE | AR49: =C49=[2]员工报账!C49 -> TRUE | AS49: =D49=[2]员工报账!D49 -> TRUE | AT49: =E49=[2]员工报账!E49 -> TRUE | AU49: =F49=[2]员工报账!F49 -> TRUE | AV49: =G49=[2]员工报账!G49 -> TRUE | AW49: =H49=[2]员工报账!H49 -> TRUE | ... BZ49: =AK49=[2]员工报账!AK49 -> TRUE
C50: 税务合规 | D50: 因公出国（境）管理 | E50: 超标准列支因公出国（境）经费，引发合规风险。 | G50: 14.因公出国（境）经费使用 | H50: 因公出国（境）经费标准使用符合规定，在规定范围内报销。 | I50: 员工报账业务-14.因公出国（境）经费使用-控制措施01 | J50: 归口管理部门对经批准的计划申请表进行复核，确认外事服务机构的收费标准不高于同业收费平均水平，落实预算控制要求。 | N50: √ | R50: √ | T50: 线下管控 | V50: 1.计划申请表及年度预算； 2.住宿费和伙食费发票； 3.费用报销审批单； 4.因公出国（境）费用计划申请； 5.因公出国（境）费用结算表。 | W50: 各级单位-各部门-报账人员、各级单位-各部门-负责人、各级单位-因公出国（境）经费归口管理部门-负责人、各级单位-财务部门-成本管理人员 | X50: 每季度 | Y50: 抽查 | AA50: 每年 | AB50: 抽查 | AD50: 因公出国（境）经费监督场景 | AE50: 每年 | AF50: 抽查 | AH50: 是 | AI50: 是 | AJ50: 《国家电网有限公司因公出国（境）经费管理办法》（国家电网企管〔2019〕715号）第八至十四条 | AK50: 国网国际部 | AP50: =A50=[2]员工报账!A50 -> TRUE | AQ50: =B50=[2]员工报账!B50 -> TRUE | AR50: =C50=[2]员工报账!C50 -> TRUE | AS50: =D50=[2]员工报账!D50 -> TRUE | AT50: =E50=[2]员工报账!E50 -> TRUE | AU50: =F50=[2]员工报账!F50 -> TRUE | AV50: =G50=[2]员工报账!G50 -> TRUE | AW50: =H50=[2]员工报账!H50 -> TRUE | ... BZ50: =AK50=[2]员工报账!AK50 -> TRUE
I51: 员工报账业务-14.因公出国（境）经费使用-控制措施02 | J51: 归口管理部门对因公出国（境）经费列支范围进行复核，确认赠送礼品、安排宴请等均按照国务院、财政部、外交部有关规定执行。 | L51: √ | M51: √ | O51: √ | T51: 线下管控 | V51: 1.计划申请表及年度预算； 2.住宿费和伙食费发票； 3.费用报销审批单； 4.因公出国（境）费用计划申请； 5.因公出国（境）费用结算表。 | W51: 各级单位-各部门-报账人员、各级单位-各部门-负责人、各级单位-因公出国（境）经费归口管理部门-负责人 | X51: 每季度 | Y51: 抽查 | AA51: 每年 | AB51: 抽查 | AD51: 因公出国（境）经费监督场景 | AE51: 每年 | AF51: 抽查 | AH51: 是 | AI51: 是 | AJ51: 《国家电网有限公司因公出国（境）经费管理办法》（国家电网企管〔2019〕715号）第八至十四条 | AK51: 国网国际部 | AP51: =A51=[2]员工报账!A51 -> TRUE | AQ51: =B51=[2]员工报账!B51 -> TRUE | AR51: =C51=[2]员工报账!C51 -> TRUE | AS51: =D51=[2]员工报账!D51 -> TRUE | AT51: =E51=[2]员工报账!E51 -> TRUE | AU51: =F51=[2]员工报账!F51 -> TRUE | AV51: =G51=[2]员工报账!G51 -> TRUE | AW51: =H51=[2]员工报账!H51 -> TRUE | ... BZ51: =AK51=[2]员工报账!AK51 -> TRUE
I52: 员工报账业务-14.因公出国（境）经费使用-控制措施03 | J52: 财务部门加强审核，按照科学预算、厉行节约的原则对因公出国（境）经费列支住宿费、伙食费、公杂费使用标准进行复核。 | Q52: √ | R52: √ | T52: 线下管控 | V52: 1.计划申请表及年度预算； 2.住宿费和伙食费发票； 3.费用报销审批单； 4.因公出国（境）费用计划申请； 5.因公出国（境）费用结算表。 | W52: 各级单位-各部门-报账人员、各级单位-各部门-负责人、各级单位-因公出国（境）经费归口管理部门-负责人、各级单位-财务部门-成本管理人员 | X52: 每季度 | Y52: 抽查 | AA52: 每年 | AB52: 抽查 | AD52: 因公出国（境）经费监督场景 | AE52: 每年 | AF52: 抽查 | AH52: 是 | AI52: 是 | AJ52: 《国家电网有限公司因公出国（境）经费管理办法》（国家电网企管〔2019〕715号）第八至十四条 | AK52: 国网国际部 | AP52: =A52=[2]员工报账!A52 -> TRUE | AQ52: =B52=[2]员工报账!B52 -> TRUE | AR52: =C52=[2]员工报账!C52 -> TRUE | AS52: =D52=[2]员工报账!D52 -> TRUE | AT52: =E52=[2]员工报账!E52 -> TRUE | AU52: =F52=[2]员工报账!F52 -> TRUE | AV52: =G52=[2]员工报账!G52 -> TRUE | AW52: =H52=[2]员工报账!H52 -> TRUE | ... BZ52: =AK52=[2]员工报账!AK52 -> TRUE
A53: 员工报账 | B53: 二、通用报账 | C53: 资金资产安全 | D53: 会议费用报销（三公经费） | E53: 超期、超规模、超标准组织会议，计划外会议未规范履行报批程序，会议开支金额超会议费用预算，引发资金安全及合规管理风险。 | G53: 15.会议规模、费用报销 | H53: 合理确定会议规格，严格控制会议费预算规模。 | I53: 员工报账业务-15.会议规模、费用报销-控制措施01 | J53: 主办部门做好会议过程管控。① 做好会议筹备。按照会议类别，确定会议规模、会期、人数、会场、预算等。② 严格会议审批。按照《国家电网有限公司会议管理办法》要求，由主办部门履行内部审批流程，填写计划内会议费用申请表，提出申请，经本部门主要负责人签字。③ 规范会议组织。不得到豪华酒店、度假村和党中央、国务院明令禁止的风景名胜区召开会议，精简会务安排、严肃会议纪律。④ 规范会议报销。按照《国家电网有限公司会议管理办法》要求，会议费用报销应严格执行公司报销管理规定，由主办部门提出申请，经本部门主要负责人签字。严禁借会议名义列支或报销与会议无关的费用等。 | L53: √ | M53: √ | T53: 线下管控 | V53: 1.年度会议计划表； 2.计划内会议费用申请表； 3.会议通知、会议议程、参会名单； 4.发票或电子结算单； 5.计划外会议审批表。 | W53: 各级单位-会议承办部门-报账人员、各级单位-会议承办部门-负责人、各级单位-会议管理部门-会议管理人员、各级单位-会议管理部门-负责人 | X53: 每季度 | Y53: 抽查 | AA53: 每年 | AB53: 抽查 | AD53: 会议费监督场景 | AE53: 每年 | AF53: 抽查 | AH53: 是 | AI53: 是 | AJ53: 《国家电网有限公司会议管理办法》（国家电网企管〔2025〕267号）第七至十二条、第二十一至二十二条、第二十七至三十二条、第三十四至三十九条等。 《关于做好会议、接待管理相关事项报备报批工作的通知》（办值通〔2025〕55号） | AK53: 国网办公室 | AL53: 各级单位办公室 | AP53: =A53=[2]员工报账!A53 -> TRUE | AQ53: =B53=[2]员工报账!B53 -> TRUE | AR53: =C53=[2]员工报账!C53 -> TRUE | AS53: =D53=[2]员工报账!D53 -> TRUE | AT53: =E53=[2]员工报账!E53 -> TRUE | AU53: =F53=[2]员工报账!F53 -> TRUE | AV53: =G53=[2]员工报账!G53 -> TRUE | AW53: =H53=[2]员工报账!H53 -> TRUE | ... BZ53: =AK53=[2]员工报账!AK53 -> TRUE
I54: 员工报账业务-15.会议规模、费用报销-控制措施02 | J54: 归口管理部门做好复核。对主办部门提交的计划内会议费用申请表、计划外会议审批表中会议计划、时间、地点、规模、预算、标准审批等进行复核。 | N54: √ | O54: √ | T54: 线下管控 | V54: 1.年度会议计划表； 2.计划内会议费用申请表； 3.会议通知、会议议程、参会名单； 4.发票或电子结算单； 5.计划外会议审批表。 | W54: 各级单位-会议承办部门-报账人员、各级单位-会议承办部门-负责人、各级单位-会议管理部门-会议管理人员、各级单位-会议管理部门-负责人 | X54: 每季度 | Y54: 抽查 | AA54: 每年 | AB54: 抽查 | AD54: 会议费监督场景 | AE54: 每年 | AF54: 抽查 | AH54: 是 | AI54: 是 | AJ54: 《国家电网有限公司会议管理办法》（国家电网企管〔2025〕267号）第七至十二条、第二十一至二十二条、第二十七至三十二条、第三十四至三十九条等。 《关于做好会议、接待管理相关事项报备报批工作的通知》（办值通〔2025〕55号） | AK54: 国网办公室 | AL54: 各级单位办公室 | AP54: =A54=[2]员工报账!A54 -> TRUE | AQ54: =B54=[2]员工报账!B54 -> TRUE | AR54: =C54=[2]员工报账!C54 -> TRUE | AS54: =D54=[2]员工报账!D54 -> TRUE | AT54: =E54=[2]员工报账!E54 -> TRUE | AU54: =F54=[2]员工报账!F54 -> TRUE | AV54: =G54=[2]员工报账!G54 -> TRUE | AW54: =H54=[2]员工报账!H54 -> TRUE | ... BZ54: =AK54=[2]员工报账!AK54 -> TRUE
I55: 员工报账业务-15.会议规模、费用报销-控制措施03 | J55: 财务部门做好报销审核。按照财务业务流程要求，做好报销审核、检查材料完备。 | Q55: √ | R55: √ | T55: 线下管控 | V55: 1.年度会议计划表； 2.计划内会议费用申请表； 3.会议通知、会议议程、参会名单； 4.发票或电子结算单； 5.计划外会议审批表。 | W55: 各级单位-会议承办部门-报账人员、各级单位-会议承办部门-负责人、各级单位-会议管理部门-会议管理人员、各级单位-会议管理部门-负责人、各级单位-财务部门-成本管理人员 | X55: 每季度 | Y55: 抽查 | AA55: 每年 | AB55: 抽查 | AD55: 会议费监督场景 | AE55: 每年 | AF55: 抽查 | AH55: 是 | AI55: 是 | AJ55: 《国家电网有限公司会议管理办法》（国家电网企管〔2025〕267号）第七至十二条、第二十一至二十二条、第二十七至三十二条、第三十四至三十九条等。 《关于做好会议、接待管理相关事项报备报批工作的通知》（办值通〔2025〕55号） | AK55: 国网办公室 | AL55: 各级单位办公室 | AP55: =A55=[2]员工报账!A55 -> TRUE | AQ55: =B55=[2]员工报账!B55 -> TRUE | AR55: =C55=[2]员工报账!C55 -> TRUE | AS55: =D55=[2]员工报账!D55 -> TRUE | AT55: =E55=[2]员工报账!E55 -> TRUE | AU55: =F55=[2]员工报账!F55 -> TRUE | AV55: =G55=[2]员工报账!G55 -> TRUE | AW55: =H55=[2]员工报账!H55 -> TRUE | ... BZ55: =AK55=[2]员工报账!AK55 -> TRUE
A56: 员工报账 | B56: 二、通用报账 | C56: 资金资产安全 | D56: 办公费管理 | E56: 虚列、套取办公费，引发合规风险。 | G56: 16.办公费使用 | H56: 办公费在规定范围内据实报销。办公费报销中的结算依据充分，完整，有效，结算依据审核轨迹完整。 | I56: 员工报账业务-16.办公费使用-控制措施01 | J56: 归口管理部门对办公费用使用范围进行复核，确保不包含党报党刊费、营销业务电费发票印制费、护肤膏、防晒霜、牙膏、工作服、多功能一体机、打印机、投影仪、礼品、食堂餐座椅等费用，禁止虚列、套取办公费行为。 | L56: √ | M56: √ | O56: √ | T56: 线下管控 | V56: 1.成本费用报销审批单； 2.发票； 3.入库单或到货验收单； 4.购置审批表； 5.采购合同； 6.办公用品领用清单； 7.费用结算清单。 | W56: 各级单位-各部门-报账人员、各级单位-各部门-负责人、各级单位-办公用品管理部门-办公用品管理人员、各级单位-办公用品管理部门-负责人 | X56: 每季度 | Y56: 抽查 | AA56: 每年 | AB56: 抽查 | AD56: 办公费监督场景 | AE56: 每年 | AF56: 抽查 | AH56: 是 | AI56: 是 | AJ56: 《国家电网有限公司会计基础管理办法》（国家电网企管〔2019〕132号）第五十四条 | AK56: 国网后勤部 | AL56: 各级单位办公室 | AP56: =A56=[2]员工报账!A56 -> TRUE | AQ56: =B56=[2]员工报账!B56 -> TRUE | AR56: =C56=[2]员工报账!C56 -> TRUE | AS56: =D56=[2]员工报账!D56 -> TRUE | AT56: =E56=[2]员工报账!E56 -> TRUE | AU56: =F56=[2]员工报账!F56 -> TRUE | AV56: =G56=[2]员工报账!G56 -> TRUE | AW56: =H56=[2]员工报账!H56 -> TRUE | ... BZ56: =AK56=[2]员工报账!AK56 -> TRUE
I57: 员工报账业务-16.办公费使用-控制措施02 | J57: 财务人员加强规范性审核，对照审批轨迹、费用结算清单、办公用品领用清单复核业务规范性。 | Q57: √ | R57: √ | T57: 线下管控 | V57: 1.成本费用报销审批单； 2.发票； 3.入库单或到货验收单； 4.购置审批表； 5.采购合同； 6.办公用品领用清单； 7.费用结算清单。 | W57: 各级单位-各部门-报账人员、各级单位-各部门-负责人、各级单位-办公用品管理部门-办公用品管理人员、各级单位-办公用品管理部门-负责人、各级单位-财务部门-成本管理人员 | X57: 每季度 | Y57: 抽查 | AA57: 每年 | AB57: 抽查 | AD57: 办公费监督场景 | AE57: 每年 | AF57: 抽查 | AH57: 是 | AI57: 是 | AJ57: 《国家电网有限公司会计基础管理办法》（国家电网企管〔2019〕132号）第五十四条 | AK57: 国网后勤部 | AL57: 各级单位办公室 | AP57: =A57=[2]员工报账!A57 -> TRUE | AQ57: =B57=[2]员工报账!B57 -> TRUE | AR57: =C57=[2]员工报账!C57 -> TRUE | AS57: =D57=[2]员工报账!D57 -> TRUE | AT57: =E57=[2]员工报账!E57 -> TRUE | AU57: =F57=[2]员工报账!F57 -> TRUE | AV57: =G57=[2]员工报账!G57 -> TRUE | AW57: =H57=[2]员工报账!H57 -> TRUE | ... BZ57: =AK57=[2]员工报账!AK57 -> TRUE
C58: 税务合规 | D58: 办公用品选购 | E58: 办公用品到货商品与采购清单不一致，“私下换货”，引发合规风险。 | G58: 17.办公用品采购、发放 | H58: 办公用品采购、发放规范有序。 | I58: 员工报账业务-17.办公用品采购、发放-控制措施01 | J58: 物资部门对国网商城上架商品与物流信息一致性进行校验，规避换货舞弊行为。 | O58: √ | T58: 线下管控 | V58: 1.办公用品采购申请单； 2.发票； 3.入库单或货物交接单； 4.购置审批表。 | W58: 各级单位-办公用品管理部门-办公用品管理人员、各级单位-办公用品管理部门-负责人、各级单位-物资部门-电商采购执行与监督人员、各级单位-物资部门-负责人 | X58: 每季度 | Y58: 抽查 | AA58: 每年 | AB58: 抽查 | AD58: 办公费列支范围监督场景 | AE58: 每年 | AF58: 抽查 | AH58: 是 | AI58: 是 | AJ58: 《国家电网有限公司零星物资及办公用品选购专区管理细则》（国家电网企管〔2024〕301 号）第二十八条、第二十九条 | AK58: 国网后勤部、国网物资部 | AL58: 各级单位后勤部（办公室）、各级单位物资部 | AP58: =A58=[2]员工报账!A58 -> TRUE | AQ58: =B58=[2]员工报账!B58 -> TRUE | AR58: =C58=[2]员工报账!C58 -> TRUE | AS58: =D58=[2]员工报账!D58 -> TRUE | AT58: =E58=[2]员工报账!E58 -> TRUE | AU58: =F58=[2]员工报账!F58 -> TRUE | AV58: =G58=[2]员工报账!G58 -> TRUE | AW58: =H58=[2]员工报账!H58 -> TRUE | ... BZ58: =AK58=[2]员工报账!AK58 -> TRUE
I59: 员工报账业务-17.办公用品采购、发放-控制措施02 | J59: 归口管理部门建立需求、审批、选购等关键角色不相容控制，实现权力分散与监督。 | L59: √ | T59: 线下管控 | V59: 1.办公用品采购申请单； 2.发票； 3.入库单或货物交接单； 4.购置审批表。 | W59: 各级单位-办公用品管理部门-办公用品管理人员、各级单位-办公用品管理部门-负责人、各级单位-物资部门-电商采购执行与监督人员、各级单位-物资部门-负责人 | X59: 每季度 | Y59: 抽查 | AA59: 每年 | AB59: 抽查 | AD59: 办公费列支范围监督场景 | AE59: 每年 | AF59: 抽查 | AH59: 是 | AI59: 是 | AJ59: 《国家电网有限公司零星物资及办公用品选购专区管理细则》（国家电网企管〔2024〕301 号）第二十八条、第二十九条 | AK59: 国网后勤部、国网物资部 | AL59: 各级单位后勤部（办公室）、各级单位物资部 | AP59: =A59=[2]员工报账!A59 -> TRUE | AQ59: =B59=[2]员工报账!B59 -> TRUE | AR59: =C59=[2]员工报账!C59 -> TRUE | AS59: =D59=[2]员工报账!D59 -> TRUE | AT59: =E59=[2]员工报账!E59 -> TRUE | AU59: =F59=[2]员工报账!F59 -> TRUE | AV59: =G59=[2]员工报账!G59 -> TRUE | AW59: =H59=[2]员工报账!H59 -> TRUE | ... BZ59: =AK59=[2]员工报账!AK59 -> TRUE
I60: 员工报账业务-17.办公用品采购、发放-控制措施03 | J60: 物资部门建立办公用品由物资部门和办公用品保管人员共同验收工作机制，双方均在货物交接单据上签字确认。 | O60: √ | R60: √ | T60: 线下管控 | V60: 1.办公用品采购申请单； 2.发票； 3.入库单或货物交接单； 4.购置审批表。 | W60: 各级单位-办公用品管理部门-办公用品管理人员、各级单位-办公用品管理部门-负责人、各级单位-物资部门-电商采购执行与监督人员、各级单位-物资部门-负责人 | X60: 每季度 | Y60: 抽查 | AA60: 每年 | AB60: 抽查 | AD60: 办公费列支范围监督场景 | AE60: 每年 | AF60: 抽查 | AH60: 是 | AI60: 是 | AJ60: 《国家电网有限公司零星物资及办公用品选购专区管理细则》（国家电网企管〔2024〕301 号）第二十八条、第二十九条 | AK60: 国网后勤部、国网物资部 | AL60: 各级单位后勤部（办公室）、各级单位物资部 | AP60: =A60=[2]员工报账!A60 -> TRUE | AQ60: =B60=[2]员工报账!B60 -> TRUE | AR60: =C60=[2]员工报账!C60 -> TRUE | AS60: =D60=[2]员工报账!D60 -> TRUE | AT60: =E60=[2]员工报账!E60 -> TRUE | AU60: =F60=[2]员工报账!F60 -> TRUE | AV60: =G60=[2]员工报账!G60 -> TRUE | AW60: =H60=[2]员工报账!H60 -> TRUE | ... BZ60: =AK60=[2]员工报账!AK60 -> TRUE
A61: 员工报账 | B61: 二、通用报账 | C61: 税务合规 | D61: 办公用品选购 | E61: 办公用品到货商品与采购清单不一致，“私下换货”，引发合规风险。 | G61: 17.办公用品采购、发放 | H61: 办公用品采购、发放规范有序。 | I61: 员工报账业务-17.办公用品采购、发放-控制措施04 | J61: 办公用品管理部门确保办公用品发放规范有序。 | R61: √ | T61: 线下管控 | V61: 1.办公用品领用清单。 | W61: 各级单位-办公用品管理部门-办公用品管理人员、各级单位-办公用品管理部门-负责人 | X61: 每季度 | Y61: 抽查 | AA61: 每年 | AB61: 抽查 | AD61: 办公费列支范围监督场景 | AE61: 每年 | AF61: 抽查 | AH61: 是 | AI61: 是 | AJ61: 《国家电网有限公司零星物资及办公用品选购专区管理细则》（国家电网企管〔2024〕301 号）第二十八条、第二十九条 | AK61: 国网后勤部 | AL61: 各级单位后勤部（办公室） | AP61: =A61=[2]员工报账!A61 -> TRUE | AQ61: =B61=[2]员工报账!B61 -> TRUE | AR61: =C61=[2]员工报账!C61 -> TRUE | AS61: =D61=[2]员工报账!D61 -> TRUE | AT61: =E61=[2]员工报账!E61 -> TRUE | AU61: =F61=[2]员工报账!F61 -> TRUE | AV61: =G61=[2]员工报账!G61 -> TRUE | AW61: =H61=[2]员工报账!H61 -> TRUE | ... BZ61: =AK61=[2]员工报账!AK61 -> TRUE
C62: 税务合规 | D62: 党组织工作经费使用 | E62: 超范围、超标准列支党组织工作经费，导致成本不实，引发合规风险。 | G62: 18.党组织工作经费报销 | H62: 党组织工作经费在规定范围内报销。 | I62: 员工报账业务-18.党组织工作经费报销-控制措施01 | J62: 归口管理部门对党组织工作经费清单进行复核，确保费用用于党内开支教育、宣传思想、主题实践活动及党内评选表彰等与党（团）的建设直接相关的工作和活动。 | L62: √ | T62: 线下管控 | V62: 1.成本费用报销审批单； 2.费用明细清单； 3.发票或收据。 | W62: 各级单位-各部门-报账人员、各级单位-各部门-负责人、各级单位-党建部门-负责人 | X62: 每季度 | Y62: 抽查 | AA62: 每年 | AB62: 抽查 | AD62: 党组织工作经列支范围监督场景 | AE62: 每年 | AF62: 抽查 | AH62: 是 | AI62: 是 | AJ62: 《国家电网有限公司党组织工作经费管理办法（试行）》（国家电网党〔2018〕96号）第八条、第九条、第十三条、第十四条 | AK62: 党组党建部 | AL62: 各级单位党建部 | AP62: =A62=[2]员工报账!A62 -> TRUE | AQ62: =B62=[2]员工报账!B62 -> TRUE | AR62: =C62=[2]员工报账!C62 -> TRUE | AS62: =D62=[2]员工报账!D62 -> TRUE | AT62: =E62=[2]员工报账!E62 -> TRUE | AU62: =F62=[2]员工报账!F62 -> TRUE | AV62: =G62=[2]员工报账!G62 -> TRUE | AW62: =H62=[2]员工报账!H62 -> TRUE | ... BZ62: =AK62=[2]员工报账!AK62 -> TRUE
I63: 员工报账业务-18.党组织工作经费报销-控制措施02 | J63: 财务部门对报销费用超范围开支情况进行校验，严禁列支豪华酒店、度假村等场所费用。 | Q63: √ | R63: √ | T63: 线下管控 | V63: 1.成本费用报销审批单； 2.费用明细清单； 3.发票或收据。 | W63: 各级单位-各部门-报账人员、各级单位-各部门-负责人、各级单位-党建部门-负责人、各级单位-财务部门-成本管理人员 | X63: 每季度 | Y63: 抽查 | AA63: 每年 | AB63: 抽查 | AD63: 党组织工作经列支范围监督场景 | AE63: 每年 | AF63: 抽查 | AH63: 是 | AI63: 是 | AJ63: 《国家电网有限公司党组织工作经费管理办法（试行）》（国家电网党〔2018〕96号）第八条、第九条、第十三条、第十四条 | AK63: 党组党建部 | AL63: 各级单位党建部 | AP63: =A63=[2]员工报账!A63 -> TRUE | AQ63: =B63=[2]员工报账!B63 -> TRUE | AR63: =C63=[2]员工报账!C63 -> TRUE | AS63: =D63=[2]员工报账!D63 -> TRUE | AT63: =E63=[2]员工报账!E63 -> TRUE | AU63: =F63=[2]员工报账!F63 -> TRUE | AV63: =G63=[2]员工报账!G63 -> TRUE | AW63: =H63=[2]员工报账!H63 -> TRUE | ... BZ63: =AK63=[2]员工报账!AK63 -> TRUE
C64: 税务合规、资金资产安全 | D64: 安全费使用 | E64: 超范围列支安全费，虚列挤占安全专项费用，导致合规风险。 | G64: 19.安全费报销 | H64: 安全费在规定范围内报销。 | I64: 员工报账业务-19.安全费报销-控制措施01 | J64: 实物管理部门规范建立资产卡片，针对使用安全费用形成固定资产、无形资产的规范建立资产卡片，确保相关资产折旧准确计入安全费。 | M64: √ | T64: 系统已建 | U64: ERP | V64: 1.成本费用报销审批单； 2.费用明细清单； 3.发票或收据； 4.建设合同。 | W64: 各级单位-各部门-报账人员、各级单位-各部门-负责人、各级单位-安监部门-消防与安保管理人员、各级单位-安监部门-负责人 | X64: 每季度 | Y64: 抽查 | AA64: 每年 | AB64: 抽查 | AD64: 安全费列支范围监督场景 | AE64: 每年 | AF64: 抽查 | AH64: 是 | AI64: 是 | AJ64: 《国家电网有限公司安全生产费用提取和使用管理办法》（国家电网企管〔2023〕399号）第十条、第十三条、第二十五条 | AK64: 国网安监部 | AL64: 各级单位安监部 | AP64: =A64=[2]员工报账!A64 -> TRUE | AQ64: =B64=[2]员工报账!B64 -> TRUE | AR64: =C64=[2]员工报账!C64 -> TRUE | AS64: =D64=[2]员工报账!D64 -> TRUE | AT64: =E64=[2]员工报账!E64 -> TRUE | AU64: =F64=[2]员工报账!F64 -> TRUE | AV64: =G64=[2]员工报账!G64 -> TRUE | AW64: =H64=[2]员工报账!H64 -> TRUE | ... BZ64: =AK64=[2]员工报账!AK64 -> TRUE
I65: 员工报账业务-19.安全费报销-控制措施02 | J65: 建设单位及时支付安全费用，应当在合同中单独约定并于工程开工日一个月内向承包单位至少支付 50%安全费用。 | O65: √ | P65: √ | T65: 线下管控 | V65: 1.成本费用报销审批单； 2.费用明细清单； 3.发票或收据； 4.建设合同。 | W65: 各级单位-各部门-报账人员、各级单位-各部门-负责人、各级单位-安监部门-消防与安保管理人员、各级单位-安监部门-负责人 | X65: 每季度 | Y65: 抽查 | AA65: 每年 | AB65: 抽查 | AD65: 安全费列支范围监督场景 | AE65: 每年 | AF65: 抽查 | AH65: 是 | AI65: 是 | AJ65: 《国家电网有限公司安全生产费用提取和使用管理办法》（国家电网企管〔2023〕399号）第十条、第十三条、第二十条、第二十五条 | AK65: 国网安监部 | AL65: 各级单位安监部 | AP65: =A65=[2]员工报账!A65 -> TRUE | AQ65: =B65=[2]员工报账!B65 -> TRUE | AR65: =C65=[2]员工报账!C65 -> TRUE | AS65: =D65=[2]员工报账!D65 -> TRUE | AT65: =E65=[2]员工报账!E65 -> TRUE | AU65: =F65=[2]员工报账!F65 -> TRUE | AV65: =G65=[2]员工报账!G65 -> TRUE | AW65: =H65=[2]员工报账!H65 -> TRUE | ... BZ65: =AK65=[2]员工报账!AK65 -> TRUE
I66: 员工报账业务-19.安全费报销-控制措施03 | J66: 总包单位及时支付安全费用，总包单位应当在合同中单独约定并于分包工程开工日一个月内将至少50%安全费用直接支付分包单位并监督使用，分包单位不再重复提取。 | O66: √ | P66: √ | T66: 线下管控 | V66: 1.成本费用报销审批单； 2.费用明细清单； 3.发票或收据； 4.建设合同。 | W66: 各级单位-各部门-报账人员、各级单位-各部门-负责人、各级单位-安监部门-消防与安保管理人员、各级单位-安监部门-负责人 | X66: 每季度 | Y66: 抽查 | AA66: 每年 | AB66: 抽查 | AD66: 安全费列支范围监督场景 | AE66: 每年 | AF66: 抽查 | AH66: 是 | AI66: 是 | AJ66: 《国家电网有限公司安全生产费用提取和使用管理办法》（国家电网企管〔2023〕399号）第十条、第十三条、第二十条、第二十五条 | AK66: 国网安监部 | AL66: 各级单位安监部 | AP66: =A66=[2]员工报账!A66 -> TRUE | AQ66: =B66=[2]员工报账!B66 -> TRUE | AR66: =C66=[2]员工报账!C66 -> TRUE | AS66: =D66=[2]员工报账!D66 -> TRUE | AT66: =E66=[2]员工报账!E66 -> TRUE | AU66: =F66=[2]员工报账!F66 -> TRUE | AV66: =G66=[2]员工报账!G66 -> TRUE | AW66: =H66=[2]员工报账!H66 -> TRUE | ... BZ66: =AK66=[2]员工报账!AK66 -> TRUE
A67: 员工报账 | B67: 二、通用报账 | C67: 税务合规、资金资产安全 | D67: 安全费使用 | E67: 超范围列支安全费，虚列挤占安全专项费用，导致合规风险。 | G67: 19.安全费报销 | H67: 安全费在规定范围内报销。 | I67: 员工报账业务-19.安全费报销-控制措施04 | J67: 归口管理部门对安全工器具领用、保管进行监督，确保不发生安全工器具过期等问题。 | R67: √ | T67: 线下管控 系统已建 | U67: 安全风险管控监督平台 | V67: 1.成本费用报销审批单； 2.费用明细清单； 3.发票或收据； 4.建设合同。 | W67: 各级单位-各部门-报账人员、各级单位-各部门-负责人、各级单位-安监部门-消防与安保管理人员、各级单位-安监部门-负责人 | X67: 每季度 | Y67: 抽查 | AA67: 每年 | AB67: 抽查 | AD67: 安全费列支范围监督场景 | AE67: 每年 | AF67: 抽查 | AH67: 是 | AI67: 是 | AJ67: 《国家电网有限公司安全生产费用提取和使用管理办法》（国家电网企管〔2023〕399号）第十条、第十三条、第二十五条 | AK67: 国网安监部 | AL67: 各级单位安监部 | AN67: 修改控制方式，修改控制系统 | AP67: =A67=[2]员工报账!A67 -> TRUE | AQ67: =B67=[2]员工报账!B67 -> TRUE | AR67: =C67=[2]员工报账!C67 -> TRUE | AS67: =D67=[2]员工报账!D67 -> TRUE | AT67: =E67=[2]员工报账!E67 -> TRUE | AU67: =F67=[2]员工报账!F67 -> TRUE | AV67: =G67=[2]员工报账!G67 -> TRUE | AW67: =H67=[2]员工报账!H67 -> TRUE | ... BZ67: =AK67=[2]员工报账!AK67 -> TRUE
I68: 员工报账业务-19.安全费报销-控制措施05 | J68: 财务部门对安全费列支情况进行复核，禁止列支职工薪酬福利、治安服务费等无关费用。 | M68: √ | P68: √ | Q68: √ | T68: 线下管控 | V68: 1.成本费用报销审批单； 2.费用明细清单； 3.发票或收据； 4.建设合同。 | W68: 各级单位-各部门-报账人员、各级单位-各部门-负责人、各级单位-安监部门-消防与安保管理人员、各级单位-安监部门-负责人、各级单位-财务部门-成本管理人员 | X68: 每季度 | Y68: 抽查 | AA68: 每年 | AB68: 抽查 | AD68: 安全费列支范围监督场景 | AE68: 每年 | AF68: 抽查 | AH68: 是 | AI68: 是 | AJ68: 《国家电网有限公司安全生产费用提取和使用管理办法》（国家电网企管〔2023〕399号）第十条、第十三条、第二十五条 | AK68: 国网安监部 | AL68: 各级单位安监部 | AP68: =A68=[2]员工报账!A68 -> TRUE | AQ68: =B68=[2]员工报账!B68 -> TRUE | AR68: =C68=[2]员工报账!C68 -> TRUE | AS68: =D68=[2]员工报账!D68 -> TRUE | AT68: =E68=[2]员工报账!E68 -> TRUE | AU68: =F68=[2]员工报账!F68 -> TRUE | AV68: =G68=[2]员工报账!G68 -> TRUE | AW68: =H68=[2]员工报账!H68 -> TRUE | ... BZ68: =AK68=[2]员工报账!AK68 -> TRUE
A69: 员工报账 | B69: 二、通用报账 | C69: 税务合规、资金资产安全 | D69: 青苗赔偿现场核定 | E69: 与现场标准、数量不一致导致青苗赔偿有误，造成青苗赔偿费重复计、多付。 | G69: 21.现场青苗赔偿类型、数量的确定 | H69: 青苗赔付类型、数量与现场一致。 | I69: 员工报账业务-21.现场青苗赔偿类型、数量的确定-控制措施01 | J69: 归口管理部门对赔偿真实性进行复核，确保进行了三方（赔偿方、受偿方、监理或基层组织）现场联合勘测清点并签字确认。 | L69: √ | O69: √ | R69: √ | T69: 线下管控 | V69: 1.用地批复文件； 2.地方补偿标准文件； 3.联合现场勘测记录； 4.地上附着物和青苗调查登记表、补偿结果确认表； 5.被补偿人身份证明； 6.青苗及地上附着物权属证明； 7.青苗补偿协议。 | W69: 各级单位-各部门-报账人员、各级单位-各部门-负责人、各级单位-归口管理部门-负责人 | X69: 每季度 | Y69: 抽查 | AA69: 每年 | AB69: 抽查 | AD69: 青苗赔偿费监督场景 | AE69: 每年 | AF69: 抽查 | AH69: 是 | AI69: 是 | AJ69: 《国家电网有限公司会计基础管理办法》（国家电网企管〔2019〕132号）附件：电网企业经济业务审核手册 | AK69: 国网财务部 | AL69: 各级单位财务部 | AP69: =A69=[2]员工报账!A69 -> TRUE | AQ69: =B69=[2]员工报账!B69 -> TRUE | AR69: =C69=[2]员工报账!C69 -> TRUE | AS69: =D69=[2]员工报账!D69 -> TRUE | AT69: =E69=[2]员工报账!E69 -> TRUE | AU69: =F69=[2]员工报账!F69 -> TRUE | AV69: =G69=[2]员工报账!G69 -> TRUE | AW69: =H69=[2]员工报账!H69 -> TRUE | ... BZ69: =AK69=[2]员工报账!AK69 -> TRUE
I70: 员工报账业务-21.现场青苗赔偿类型、数量的确定-控制措施02 | J70: 归口管理部门对补偿协仪进行复核，确保协议包括标的物位置、权属、地类、面积、附着物种类与数量等关键信息。 | M70: √ | O70: √ | T70: 线下管控 | V70: 1.用地批复文件； 2.地方补偿标准文件； 3.联合现场勘测记录； 4.地上附着物和青苗调查登记表、补偿结果确认表； 5.被补偿人身份证明； 6.青苗及地上附着物权属证明； 7.青苗补偿协议。 | W70: 各级单位-各部门-报账人员、各级单位-各部门-负责人、各级单位-归口管理部门-负责人 | X70: 每季度 | Y70: 抽查 | AA70: 每年 | AB70: 抽查 | AD70: 青苗赔偿费监督场景 | AE70: 每年 | AF70: 抽查 | AH70: 是 | AI70: 是 | AJ70: 《国家电网有限公司会计基础管理办法》（国家电网企管〔2019〕132号）附件：电网企业经济业务审核手册 | AK70: 国网财务部 | AL70: 各级单位财务部 | AP70: =A70=[2]员工报账!A70 -> TRUE | AQ70: =B70=[2]员工报账!B70 -> TRUE | AR70: =C70=[2]员工报账!C70 -> TRUE | AS70: =D70=[2]员工报账!D70 -> TRUE | AT70: =E70=[2]员工报账!E70 -> TRUE | AU70: =F70=[2]员工报账!F70 -> TRUE | AV70: =G70=[2]员工报账!G70 -> TRUE | AW70: =H70=[2]员工报账!H70 -> TRUE | ... BZ70: =AK70=[2]员工报账!AK70 -> TRUE
I71: 员工报账业务-21.现场青苗赔偿类型、数量的确定-控制措施03 | J71: 财务部门对赔偿单价与地方政府指导标准进行校验。 | Q71: √ | R71: √ | T71: 线下管控 | V71: 1.用地批复文件； 2.地方补偿标准文件； 3.联合现场勘测记录； 4.地上附着物和青苗调查登记表、补偿结果确认表； 5.被补偿人身份证明； 6.青苗及地上附着物权属证明； 7.青苗补偿协议。 | W71: 各级单位-各部门-报账人员、各级单位-各部门-负责人、各级单位-归口管理部门-负责人、各级单位-财务部门-工程财务管理人员 | X71: 每季度 | Y71: 抽查 | AA71: 每年 | AB71: 抽查 | AD71: 青苗赔偿费监督场景 | AE71: 每年 | AF71: 抽查 | AH71: 是 | AI71: 是 | AJ71: 《国家电网有限公司会计基础管理办法》（国家电网企管〔2019〕132号）附件：电网企业经济业务审核手册 | AK71: 国网财务部 | AL71: 各级单位财务部 | AP71: =A71=[2]员工报账!A71 -> TRUE | AQ71: =B71=[2]员工报账!B71 -> TRUE | AR71: =C71=[2]员工报账!C71 -> TRUE | AS71: =D71=[2]员工报账!D71 -> TRUE | AT71: =E71=[2]员工报账!E71 -> TRUE | AU71: =F71=[2]员工报账!F71 -> TRUE | AV71: =G71=[2]员工报账!G71 -> TRUE | AW71: =H71=[2]员工报账!H71 -> TRUE | ... BZ71: =AK71=[2]员工报账!AK71 -> TRUE
C72: 税务合规 | D72: 青苗赔偿资金申 请支付 | E72: 与赔付人实际不一致，虚列套取资金，造成青苗赔偿费多付、错付。 | G72: 22.青苗赔偿支付对象的确定 | H72: 青苗赔付资金支付对象与现场一致。 | I72: 员工报账业务-22.青苗赔偿支付对象的确定-控制措施01 | J72: 归口管理部门对资金支付与补偿协议支付条款进行校验。 | O72: √ | P72: √ | T72: 线下管控 | V72: 1.用地批复文件； 2.地方补偿标准文件； 3.联合现场勘测记录； 4.地上附着物和青苗调查登记表、补偿结果确认表； 5.被补偿人身份证明； 6.青苗及地上附着物权属证明； 7.青苗补偿协议。 | W72: 各级单位-各部门-报账人员、各级单位-各部门-负责人、各级单位-归口管理部门-负责人 | X72: 每季度 | Y72: 抽查 | AA72: 每年 | AB72: 抽查 | AD72: 青苗赔偿费监督场景 | AE72: 每年 | AF72: 抽查 | AH72: 是 | AI72: 是 | AJ72: 《国家电网有限公司会计基础管理办法》（国家电网企管〔2019〕132号）附件：电网企业经济业务审核手册 | AK72: 国网财务部 | AL72: 各级单位财务部 | AP72: =A72=[2]员工报账!A72 -> TRUE | AQ72: =B72=[2]员工报账!B72 -> TRUE | AR72: =C72=[2]员工报账!C72 -> TRUE | AS72: =D72=[2]员工报账!D72 -> TRUE | AT72: =E72=[2]员工报账!E72 -> TRUE | AU72: =F72=[2]员工报账!F72 -> TRUE | AV72: =G72=[2]员工报账!G72 -> TRUE | AW72: =H72=[2]员工报账!H72 -> TRUE | ... BZ72: =AK72=[2]员工报账!AK72 -> TRUE
I73: 员工报账业务-22.青苗赔偿支付对象的确定-控制措施02 | J73: 财务部门对赔偿资金安全、足额、直达权利人情况进行复核。 | P73: √ | R73: √ | T73: 线下管控 | V73: 1.用地批复文件； 2.地方补偿标准文件； 3.联合现场勘测记录； 4.地上附着物和青苗调查登记表、补偿结果确认表； 5.被补偿人身份证明； 6.青苗及地上附着物权属证明； 7.青苗补偿协议。 | W73: 各级单位-各部门-报账人员、各级单位-各部门-负责人、各级单位-归口管理部门-负责人、各级单位-财务部门-工程财务管理人员 | X73: 每季度 | Y73: 抽查 | AA73: 每年 | AB73: 抽查 | AD73: 青苗赔偿费监督场景 | AE73: 每年 | AF73: 抽查 | AH73: 是 | AI73: 是 | AJ73: 《国家电网有限公司会计基础管理办法》（国家电网企管〔2019〕132号）附件：电网企业经济业务审核手册 | AK73: 国网财务部 | AL73: 各级单位财务部 | AP73: =A73=[2]员工报账!A73 -> TRUE | AQ73: =B73=[2]员工报账!B73 -> TRUE | AR73: =C73=[2]员工报账!C73 -> TRUE | AS73: =D73=[2]员工报账!D73 -> TRUE | AT73: =E73=[2]员工报账!E73 -> TRUE | AU73: =F73=[2]员工报账!F73 -> TRUE | AV73: =G73=[2]员工报账!G73 -> TRUE | AW73: =H73=[2]员工报账!H73 -> TRUE | ... BZ73: =AK73=[2]员工报账!AK73 -> TRUE
A74: 员工报账 | B74: 二、通用报账 | C74: 税务合规、资金资产安全 | D74: 资金支付 | E74: 未按合同约定付款、无预算、超越权限办理支付审批业务，引发资金安全风险。 | F74: 06.债权债务清理不及时：存在应收账款长期未收回、应收款项核销依据不充分、客户工程款清理不及时，存在潜亏风险、长期应付款未及时清理、款项未及时结算形成隐性债权债务等问题。 04.超期未支付民营及中小企业款项：存在未按规定及时清理民营及中小企业应付款项；经营指标不真实，存在隐性债务；项目已完工未签合同、未及时结算、未按时入账、未开票等；以资金困难、存在纠纷、转包分包等不正当理由延期支付工程款；合同设置不合理支付条款等问题。 | G74: 23.资金支付管理 | H74: 资金支付规范安全。 | I74: 员工报账业务-23.资金支付管理-控制措施01 | J74: 资金支付发起部门对资金支付与合同约定付款条款进行复核。 | M74: √ | O74: √ | T74: 线下管控 | V74: 1.到货验收单； 2.费用明细清单； 3.发票或收据； 4.合同或协议； 5.付款申请单。 | W74: 各级单位-资金支付发起部门-报账人员、各级单位-资金支付发起部门-负责人、各级单位-财务部门-成本管理人员、各级单位-财务部门-资金管理人员、各级单位-财务部门-负责人 | X74: 每季度 | Y74: 抽查 | AA74: 每年 | AB74: 抽查 | AD74: 资金支付管理监督场景 | AE74: 每年 | AF74: 抽查 | AH74: 是 | AI74: 是 | AJ74: 《保障中小企业款项支付条例》第九条、第十条 《国家电网有限公司合同管理办法》（国家电网企管〔2020〕832号）第四十六条 《国家电网有限公司会计基础管理办法》（国家电网企管〔2019〕132号）第五十四条 《关于加强中央企业资金内部控制管理有关事项的通知》（国资发监督〔2021〕19 号）第十三条 | AK74: 国网财务部 | AL74: 各级单位财务部 | AP74: =A74=[2]员工报账!A74 -> TRUE | AQ74: =B74=[2]员工报账!B74 -> TRUE | AR74: =C74=[2]员工报账!C74 -> TRUE | AS74: =D74=[2]员工报账!D74 -> TRUE | AT74: =E74=[2]员工报账!E74 -> TRUE | AU74: =F74=[2]员工报账!F74 -> TRUE | AV74: =G74=[2]员工报账!G74 -> TRUE | AW74: =H74=[2]员工报账!H74 -> TRUE | ... BZ74: =AK74=[2]员工报账!AK74 -> TRUE
I75: 员工报账业务-23.资金支付管理-控制措施02 | J75: 资金支付发起部门对付款信息与合同约定进行校验，确保使用合同约定账户支付。 | O75: √ | P75: √ | T75: 线下管控 | V75: 1.到货验收单； 2.费用明细清单； 3.发票或收据； 4.合同或协议； 5.付款申请单。 | W75: 各级单位-资金支付发起部门-报账人员、各级单位-资金支付发起部门-负责人、各级单位-财务部门-成本管理人员、各级单位-财务部门-资金管理人员、各级单位-财务部门-负责人 | X75: 每季度 | Y75: 抽查 | AA75: 每年 | AB75: 抽查 | AD75: 资金支付管理监督场景 | AE75: 每年 | AF75: 抽查 | AH75: 是 | AI75: 是 | AJ75: 《保障中小企业款项支付条例》第九条、第十条 《国家电网有限公司合同管理办法》（国家电网企管〔2020〕832号）第四十六条 《国家电网有限公司会计基础管理办法》（国家电网企管〔2019〕132号）第五十四条 《关于加强中央企业资金内部控制管理有关事项的通知》（国资发监督〔2021〕19 号）第十三条 | AK75: 国网财务部 | AL75: 各级单位财务部 | AP75: =A75=[2]员工报账!A75 -> TRUE | AQ75: =B75=[2]员工报账!B75 -> TRUE | AR75: =C75=[2]员工报账!C75 -> TRUE | AS75: =D75=[2]员工报账!D75 -> TRUE | AT75: =E75=[2]员工报账!E75 -> TRUE | AU75: =F75=[2]员工报账!F75 -> TRUE | AV75: =G75=[2]员工报账!G75 -> TRUE | AW75: =H75=[2]员工报账!H75 -> TRUE | ... BZ75: =AK75=[2]员工报账!AK75 -> TRUE
I76: 员工报账业务-23.资金支付管理-控制措施03 | J76: 财务部门对资金分级授权审批流程和预算批准的付款额度进行复核，确认无误后进行付款。 | K76: √ | L76: √ | Q76: √ | T76: 系统已建 | U76: 智慧共享财务平台 | V76: 1.到货验收单； 2.费用明细清单； 3.发票或收据； 4.合同或协议； 5.付款申请单。 | W76: 各级单位-资金支付发起部门-报账人员、各级单位-资金支付发起部门-负责人、各级单位-财务部门-成本管理人员、各级单位-财务部门-资金管理人员、各级单位-财务部门-负责人 | X76: 每季度 | Y76: 抽查 | AA76: 每年 | AB76: 抽查 | AD76: 资金支付管理监督场景 | AE76: 每年 | AF76: 抽查 | AH76: 是 | AI76: 是 | AJ76: 《保障中小企业款项支付条例》第九条、第十条 《国家电网有限公司合同管理办法》（国家电网企管〔2020〕832号）第四十六条 《国家电网有限公司会计基础管理办法》（国家电网企管〔2019〕132号）第五十四条 《关于加强中央企业资金内部控制管理有关事项的通知》（国资发监督〔2021〕19 号）第十三条 | AK76: 国网财务部 | AL76: 各级单位财务部 | AP76: =A76=[2]员工报账!A76 -> TRUE | AQ76: =B76=[2]员工报账!B76 -> TRUE | AR76: =C76=[2]员工报账!C76 -> TRUE | AS76: =D76=[2]员工报账!D76 -> TRUE | AT76: =E76=[2]员工报账!E76 -> TRUE | AU76: =F76=[2]员工报账!F76 -> TRUE | AV76: =G76=[2]员工报账!G76 -> TRUE | AW76: =H76=[2]员工报账!H76 -> TRUE | ... BZ76: =AK76=[2]员工报账!AK76 -> TRUE
I77: 员工报账业务-23.资金支付管理-控制措施04 | J77: 财务部门对未履行“三重一大”决策程序和联签制度等特殊支付事项进行复核，禁止出现化整为零规避大额资金支付集体决策程序等问题。 | L77: √ | P77: √ | Q77: √ | T77: 线下管控 | V77: 1.到货验收单； 2.费用明细清单； 3.发票或收据； 4.合同或协议； 5.付款申请单。 | W77: 各级单位-资金支付发起部门-报账人员、各级单位-资金支付发起部门-负责人、各级单位-财务部门-成本管理人员、各级单位-财务部门-资金管理人员、各级单位-财务部门-负责人 | X77: 每季度 | Y77: 抽查 | AA77: 每年 | AB77: 抽查 | AD77: 资金支付管理监督场景 | AE77: 每年 | AF77: 抽查 | AH77: 是 | AI77: 是 | AJ77: 《保障中小企业款项支付条例》第九条、第十条 《国家电网有限公司合同管理办法》（国家电网企管〔2020〕832号）第四十六条 《国家电网有限公司会计基础管理办法》（国家电网企管〔2019〕132号）第五十四条 《关于加强中央企业资金内部控制管理有关事项的通知》（国资发监督〔2021〕19 号）第十三条 | AK77: 国网财务部 | AL77: 各级单位财务部 | AP77: =A77=[2]员工报账!A77 -> TRUE | AQ77: =B77=[2]员工报账!B77 -> TRUE | AR77: =C77=[2]员工报账!C77 -> TRUE | AS77: =D77=[2]员工报账!D77 -> TRUE | AT77: =E77=[2]员工报账!E77 -> TRUE | AU77: =F77=[2]员工报账!F77 -> TRUE | AV77: =G77=[2]员工报账!G77 -> TRUE | AW77: =H77=[2]员工报账!H77 -> TRUE | ... BZ77: =AK77=[2]员工报账!AK77 -> TRUE
I78: 员工报账业务-23.资金支付管理-控制措施05 | J78: 财务部门对大额资金对私支付进行校验，严控大额资金对私支付问题发生。 | M78: √ | P78: √ | Q78: √ | T78: 线下管控 | V78: 1.到货验收单； 2.费用明细清单； 3.发票或收据； 4.合同或协议； 5.付款申请单。 | W78: 各级单位-资金支付发起部门-报账人员、各级单位-资金支付发起部门-负责人、各级单位-财务部门-成本管理人员、各级单位-财务部门-资金管理人员、各级单位-财务部门-负责人 | X78: 每季度 | Y78: 抽查 | AA78: 每年 | AB78: 抽查 | AD78: 资金支付管理监督场景 | AE78: 每年 | AF78: 抽查 | AH78: 是 | AI78: 是 | AJ78: 《保障中小企业款项支付条例》第九条、第十条 《国家电网有限公司合同管理办法》（国家电网企管〔2020〕832号）第四十六条 《国家电网有限公司会计基础管理办法》（国家电网企管〔2019〕132号）第五十四条 《关于加强中央企业资金内部控制管理有关事项的通知》（国资发监督〔2021〕19 号）第十三条 | AK78: 国网财务部 | AL78: 各级单位财务部 | AP78: =A78=[2]员工报账!A78 -> TRUE | AQ78: =B78=[2]员工报账!B78 -> TRUE | AR78: =C78=[2]员工报账!C78 -> TRUE | AS78: =D78=[2]员工报账!D78 -> TRUE | AT78: =E78=[2]员工报账!E78 -> TRUE | AU78: =F78=[2]员工报账!F78 -> TRUE | AV78: =G78=[2]员工报账!G78 -> TRUE | AW78: =H78=[2]员工报账!H78 -> TRUE | ... BZ78: =AK78=[2]员工报账!AK78 -> TRUE
A79: 员工报账 | C79: 税务合规 | D79: 管理咨询费使用 | E79: 超范围列支管理咨询费引发引发合规风险。 | G79: 24.管理咨询费报销 | H79: 管理咨询费在规定范围内报销。 | I79: 员工报账业务-24.管理咨询费报销-控制措施01 | J79: 归口管理部门对管理咨询费进行复核，不得用于电网规划研究、工程前期咨询、信息系统建设等技术咨询与开发，不得用于法律、税务、审计、会计等常规性的中介机构服务开支。 | L79: √ | T79: 线下管控 | V79: 1.成本费用报销审批单； 2.费用明细清单； 3.发票或收据； 4.合同或协议。 | W79: 各级单位-各部门-报账人员、各级单位-各部门-负责人、各级单位-办公室-负责人 | X79: 每季度 | Y79: 抽查 | AA79: 每年 | AB79: 抽查 | AD79: 管理咨询费列支范围监督场景 | AE79: 每年 | AF79: 抽查 | AH79: 是 | AI79: 是 | AJ79: 国家电网公司管理咨询项目管理办法》第二条、第十五条 | AK79: 国网办公室 | AL79: 各级单位办公室 | AP79: =A79=[2]员工报账!A79 -> TRUE | AQ79: =B79=[2]员工报账!B79 -> TRUE | AR79: =C79=[2]员工报账!C79 -> TRUE | AS79: =D79=[2]员工报账!D79 -> TRUE | AT79: =E79=[2]员工报账!E79 -> TRUE | AU79: =F79=[2]员工报账!F79 -> TRUE | AV79: =G79=[2]员工报账!G79 -> TRUE | AW79: =H79=[2]员工报账!H79 -> TRUE | ... BZ79: =AK79=[2]员工报账!AK79 -> TRUE
I80: 员工报账业务-24.管理咨询费报销-控制措施02 | J80: 规范管理咨询费列支间接费用和支付进度。项目经费需至少分两次进行支付，两次支付时，最后一笔经费支出不得低于合同总额的30%；三次及以上支付时，最后一笔经费支出不得低于合同总额的10%。 | Q80: √ | R80: √ | T80: 线下管控 | V80: 1.付款申请单； 2.合同或协议。 | W80: 各级单位-各部门-报账人员、各级单位-各部门-负责人、各级单位-办公室-负责人、各级单位-财务部门-成本管理人员 | X80: 每季度 | Y80: 抽查 | AA80: 每年 | AB80: 抽查 | AD80: 管理咨询费列支范围监督场景 | AE80: 每年 | AF80: 抽查 | AH80: 是 | AI80: 是 | AJ80: 《国家电网公司管理咨询项目管理办法》第十四条、第三十八条 | AK80: 国网办公室 | AL80: 各级单位办公室 | AP80: =A80=[2]员工报账!A80 -> TRUE | AQ80: =B80=[2]员工报账!B80 -> TRUE | AR80: =C80=[2]员工报账!C80 -> TRUE | AS80: =D80=[2]员工报账!D80 -> TRUE | AT80: =E80=[2]员工报账!E80 -> TRUE | AU80: =F80=[2]员工报账!F80 -> TRUE | AV80: =G80=[2]员工报账!G80 -> TRUE | AW80: =H80=[2]员工报账!H80 -> TRUE | ... BZ80: =AK80=[2]员工报账!AK80 -> TRUE
A81: 员工报账 | B81: 二、通用报账 | C81: 税务合规、成本精益管理 | D81: 生产车辆使用费管理 | E81: 各单位生产用车较多，车辆使用费存在管控不严，通过伪造票据、虚报里程、费用等方式套取企业资金，导致企业成本虚增、资金流失风险。 | F81: 生产用车管控不严：“一车一卡”加油落实不到位，造成平均油耗异常，在车辆维修等费用中虚列名目、处理其他无关费用或费用依据不足。 | G81: 25.生产车辆使用费管控 | H81: 费用管控，车费使用费按单车实行台账管理，加强车辆燃油、充电、修理费用管控，节约成本费用，防范廉政风险。 | I81: 员工报账业务-25.生产车辆使用费管控-控制措施01 | J81: 生产车辆加油执行“一车一卡”，一张油卡固定一个车牌号码。 | M81: √ | R81: √ | T81: 线下管控 | V81: 1.加油卡； 2.车辆百公里油耗定额表 | W81: 各级单位-后勤部门（生产用车管理部门）-车辆管理人员 | X81: 每季度 | Y81: 抽查 | AA81: 每年 | AB81: 抽查 | AH81: 是 | AI81: 是 | AL81: 各级单位后勤部（生产用车管理部门） | AN81: 新增关键控制点“生产车辆使用费管控” | AP81: =A81=[2]员工报账!A81 -> TRUE | AQ81: =B81=[2]员工报账!B81 -> TRUE | AR81: =C81=[2]员工报账!C81 -> TRUE | AS81: =D81=[2]员工报账!D81 -> TRUE | AT81: =E81=[2]员工报账!E81 -> TRUE | AU81: =F81=[2]员工报账!F81 -> TRUE | AV81: =G81=[2]员工报账!G81 -> TRUE | AW81: =H81=[2]员工报账!H81 -> TRUE | ... BZ81: =AK81=[2]员工报账!AK81 -> TRUE
I82: 员工报账业务-25.生产车辆使用费管控-控制措施02 | J82: 各单位车辆运行管理部门应加强车辆维修真实性控制，按照维修申请、审批、验收结算分离原则控制车辆维修。 | K82: √ | M82: √ | T82: 线下管控 | V82: 1.车辆维保合同； 2.车辆维修与保养通知单； | W82: 各级单位-后勤部门（生产用车管理部门）-车辆管理人员、各级单位-后勤部门（生产用车管理部门）-负责人、各级单位-财务部门-成本管理人员 | X82: 每季度 | Y82: 抽查 | AA82: 每年 | AB82: 抽查 | AH82: 是 | AI82: 是 | AL82: 各级单位后勤部（生产用车管理部门） | AN82: 新增关键控制点“生产车辆使用费管控” | AP82: =A82=[2]员工报账!A82 -> TRUE | AQ82: =B82=[2]员工报账!B82 -> TRUE | AR82: =C82=[2]员工报账!C82 -> TRUE | AS82: =D82=[2]员工报账!D82 -> TRUE | AT82: =E82=[2]员工报账!E82 -> TRUE | AU82: =F82=[2]员工报账!F82 -> TRUE | AV82: =G82=[2]员工报账!G82 -> TRUE | AW82: =H82=[2]员工报账!H82 -> TRUE | ... BZ82: =AK82=[2]员工报账!AK82 -> TRUE
I83: 员工报账业务-25.生产车辆使用费管控-控制措施03 | J83: 各单位车辆运行管理部门应加强车辆使用费台账管理，对单车费用明细（油费、过路费、停车费、维修费等）与用车申请单（事前提交，注明用车时间、事由、目的地）、车辆行驶里程记录（行车记录、起止日期）进行复核，严禁套取费用。 | M83: √ | T83: 线下管控 | V83: 1.车辆维保合同； 2.生产车辆使用费管理台账 | W83: 各级单位-后勤部门（生产用车管理部门）-车辆管理人员、各级单位-后勤部门（生产用车管理部门）-负责人、各级单位-财务部门-成本管理人员 | X83: 每季度 | Y83: 抽查 | AA83: 每年 | AB83: 抽查 | AH83: 是 | AI83: 是 | AJ83: 国网湖南省电力有限公司关于印发《生产服务用车管理实施细则》的通知（湘电公司设备〔2025〕372号） | AL83: 各级单位后勤部（生产用车管理部门） | AN83: 新增关键控制点“生产车辆使用费管控” | AP83: =A83=[2]员工报账!A83 -> TRUE | AQ83: =B83=[2]员工报账!B83 -> TRUE | AR83: =C83=[2]员工报账!C83 -> TRUE | AS83: =D83=[2]员工报账!D83 -> TRUE | AT83: =E83=[2]员工报账!E83 -> TRUE | AU83: =F83=[2]员工报账!F83 -> TRUE | AV83: =G83=[2]员工报账!G83 -> TRUE | AW83: =H83=[2]员工报账!H83 -> TRUE | ... BZ83: =AK83=[2]员工报账!AK83 -> TRUE
I84: 员工报账业务-25.生产车辆使用费管控-控制措施04 | J84: 各单位财务部门应严格审核车辆使用费用各类发票与明细清单的一致性、审核合同折扣率、合同税率的执行情况，车辆保险费应归口核算至财产保险费。 | N84: √ | Q84: √ | T84: 线下管控 | V84: 1.车辆维保合同； 2.车辆维修与保养通知单； 3.车辆维修费用清单； 4.加油清单； 5.发票 | W84: 各级单位-后勤部门（生产用车管理部门）-车辆管理人员、各级单位-后勤部门（生产用车管理部门）-负责人、各级单位-财务部门-成本管理人员、各级单位-财务部门-成本管理人员 | X84: 每季度 | Y84: 抽查 | AA84: 每年 | AB84: 抽查 | AH84: 是 | AI84: 是 | AJ84: 国网湖南电力财务部关于印发支出类经济业务财务报销审核指引的通知（财〔2022〕22 号） | AL84: 各级单位后勤部（生产用车管理部门） | AN84: 新增关键控制点“生产车辆使用费管控” | AP84: =A84=[2]员工报账!A84 -> TRUE | AQ84: =B84=[2]员工报账!B84 -> TRUE | AR84: =C84=[2]员工报账!C84 -> TRUE | AS84: =D84=[2]员工报账!D84 -> TRUE | AT84: =E84=[2]员工报账!E84 -> TRUE | AU84: =F84=[2]员工报账!F84 -> TRUE | AV84: =G84=[2]员工报账!G84 -> TRUE | AW84: =H84=[2]员工报账!H84 -> TRUE | ... BZ84: =AK84=[2]员工报账!AK84 -> TRUE
A85: 员工报账 | B85: 二、通用报账 | C85: 税务合规、降本增效 | D85: 零星租车与运输服务 | E85: 零星租车不规范，存在虚列套取风险。 | F85: 1.零星租车管控不严在自有车辆充足的情况下仍然租赁外部车辆。 2.报销环节存在重复报销，虚假报销套取费用。 | G85: 26.零星租车与运输服务报销 | H85: 后勤管理部门加强零星租车管控，自有车辆充足的情况下不允许租用外部车辆。 | I85: 员工报账业务-26.零星租车与运输服务报销-控制措施01 | J85: 零星车辆租赁（运输服务）需求，按照就近响应、统筹优化原则，实施车辆运输服务框架采购。 | O85: √ | T85: 线下管控 | V85: 1.零星租车合同； 2.租用车辆行驶证、驾驶证； | W85: 各级单位-后勤管理部门-车辆管理人员 | X85: 每季度 | Y85: 抽查 | AA85: 每年 | AB85: 抽查 | AH85: 是 | AI85: 是 | AJ85: 国网湖南省电力有限公司关于印发《国网湖南省电力有限公司车辆租赁及车辆运输服务管理办法》的通知（湘电公司后勤〔2025〕356 号）第二十五条 | AL85: 各级单位后勤部 | AN85: 新增关键控制点“零星租车与运输服务报销” | AP85: =A85=[2]员工报账!A85 -> TRUE | AQ85: =B85=[2]员工报账!B85 -> TRUE | AR85: =C85=[2]员工报账!C85 -> TRUE | AS85: =D85=[2]员工报账!D85 -> TRUE | AT85: =E85=[2]员工报账!E85 -> TRUE | AU85: =F85=[2]员工报账!F85 -> TRUE | AV85: =G85=[2]员工报账!G85 -> TRUE | AW85: =H85=[2]员工报账!H85 -> TRUE | ... BZ85: =AK85=[2]员工报账!AK85 -> TRUE
I86: 员工报账业务-26.零星租车与运输服务报销-控制措施02 | J86: 各单位有关部门（班组）提出零星租车申请后，需经本单位后勤管理部门审批，后勤管理部门结合本单位现有车辆情况判断是否同意租赁，审批租赁车辆的必要性。自营项目租用吊车等特种车辆应经本单位电网技术部等生产管理部门审批。 | K86: √ | M86: √ | T86: 线下管控 | V86: 1.零星租车合同； 2.租用车辆行驶证、驾驶证； 3.零星租车申请单、审批单。 | W86: 各级单位-后勤管理部门-车辆管理人员、各级单位-电网技术部门-负责人 | X86: 每季度 | Y86: 抽查 | AA86: 每年 | AB86: 抽查 | AH86: 是 | AI86: 是 | AJ86: 国网湖南省电力有限公司关于印发《国网湖南省电力有限公司车辆租赁及车辆运输服务管理办法》的通知（湘电公司后勤〔2025〕356 号）第六条、第七条 | AL86: 各级单位后勤部 | AN86: 新增关键控制点“零星租车与运输服务报销” | AP86: =A86=[2]员工报账!A86 -> TRUE | AQ86: =B86=[2]员工报账!B86 -> TRUE | AR86: =C86=[2]员工报账!C86 -> TRUE | AS86: =D86=[2]员工报账!D86 -> TRUE | AT86: =E86=[2]员工报账!E86 -> TRUE | AU86: =F86=[2]员工报账!F86 -> TRUE | AV86: =G86=[2]员工报账!G86 -> TRUE | AW86: =H86=[2]员工报账!H86 -> TRUE | ... BZ86: =AK86=[2]员工报账!AK86 -> TRUE
I87: 员工报账业务-26.零星租车与运输服务-控制措施03 | J87: 各单位后勤管理部门应加强租车结算管理，建立租赁车辆运行费用台账，严格按照实际次数、里程和合同价格结算。自营项目租用吊车、挖机等机械由生产管理部门建立台账，严格按照实际作业台班和合同价格结算。 | M87: √ | T87: 线下管控 | V87: 1.零星租车合同； 2.零星租车申请单； 3.零星租车台账（清单）； 4.零星租车发票。 | W87: 各级单位-后勤管理部门-车辆管理人员、各级单位-电网技术部门-项目管理人员 | X87: 每季度 | Y87: 抽查 | AA87: 每年 | AB87: 抽查 | AH87: 是 | AI87: 是 | AJ87: 国网湖南省电力有限公司关于印发《国网湖南省电力有限公司车辆租赁及车辆运输服务管理办法》的通知（湘电公司后勤〔2025〕356 号）第二十一条 | AL87: 各级单位后勤部 | AN87: 新增关键控制点“零星租车与运输服务报销” | AP87: =A87=[2]员工报账!A87 -> TRUE | AQ87: =B87=[2]员工报账!B87 -> TRUE | AR87: =C87=[2]员工报账!C87 -> TRUE | AS87: =D87=[2]员工报账!D87 -> TRUE | AT87: =E87=[2]员工报账!E87 -> TRUE | AU87: =F87=[2]员工报账!F87 -> TRUE | AV87: =G87=[2]员工报账!G87 -> TRUE | AW87: =H87=[2]员工报账!H87 -> TRUE | ... BZ87: =AK87=[2]员工报账!AK87 -> TRUE
I88: 员工报账业务-26.零星租车与运输服务-控制措施04 | J88: 各单位财务部门审核零星租车报销发票金额与租车明细的一致性，审核合同折扣率、合同税率的执行情况。 | Q88: √ | T88: 线下管控 | V88: 1.零星租车合同； 2.零星租车申请单； 3.零星租车台账（清单）； 4.零星租车发票。 | W88: 各级单位-后勤管理部门-车辆管理人员、各级单位-电网技术部门-项目管理人员、各级单位-财务部门-成本管理人员 | X88: 每季度 | Y88: 抽查 | AA88: 每年 | AB88: 抽查 | AH88: 是 | AI88: 是 | AJ88: 国网湖南电力财务部关于印发支出类经济业务财务报销审核指引的通知（财〔2022〕22 号） | AL88: 各级单位财务部 | AN88: 新增关键控制点“零星租车与运输服务报销” | AP88: =A88=[2]员工报账!A88 -> TRUE | AQ88: =B88=[2]员工报账!B88 -> TRUE | AR88: =C88=[2]员工报账!C88 -> TRUE | AS88: =D88=[2]员工报账!D88 -> TRUE | AT88: =E88=[2]员工报账!E88 -> TRUE | AU88: =F88=[2]员工报账!F88 -> TRUE | AV88: =G88=[2]员工报账!G88 -> TRUE | AW88: =H88=[2]员工报账!H88 -> TRUE | ... BZ88: =AK88=[2]员工报账!AK88 -> TRUE
A89: 员工报账 | B89: 二、通用报账 | C89: 税务合规、降本增效 | D89: 零星劳务 | E89: 自营项目零星劳务管理不规范，各类检查虚列套取现象频发。 | F89: 零星劳务员工管理不规范，存在重复报销，虚假用工套取费用。 | G89: 27.零星劳务管控 | H89: 加强零星用工管理，明确零星用工范围，实行利用自营用工系统实行台账管理，避免重负报销、虚假报销。 | I89: 员工报账业务-27.零星劳务管控-控制措施01 | J89: 自营项目的专业主管部门明确采取劳务外包的范围，不得从事核心业务或涉密工作。零星劳务人员应通过合规的招标方式，确定固定的服务商，实际需要用工时从签订合同的服务商范围内选用不得直接与个人签订用工协议。 | O89: √ | T89: 线下管控 | V89: 1.零星用工合同； 2.零星用工服务商中标通知书。 | W89: 各级单位-运检、配网、营销部门-项目管理人员、各级单位-运检、配网、营销部门-负责人 | X89: 每季度 | Y89: 抽查 | AA89: 每年 | AB89: 抽查 | AH89: 是 | AI89: 是 | AJ89: 国网湖南省电力有限公司关于印发自营模式下规范使用零星劳务人员指导意见的通知（湘电公司人资〔2022〕13号） | AL89: 各级单位零星用工使用部门 | AN89: 新增关键控制点“零星劳务管控” | AP89: =A89=[2]员工报账!A89 -> TRUE | AQ89: =B89=[2]员工报账!B89 -> TRUE | AR89: =C89=[2]员工报账!C89 -> TRUE | AS89: =D89=[2]员工报账!D89 -> TRUE | AT89: =E89=[2]员工报账!E89 -> TRUE | AU89: =F89=[2]员工报账!F89 -> TRUE | AV89: =G89=[2]员工报账!G89 -> TRUE | AW89: =H89=[2]员工报账!H89 -> TRUE | ... BZ89: =AK89=[2]员工报账!AK89 -> TRUE
I90: 员工报账业务-27.零星劳务管控-控制措施02 | J90: 各单位自营项目主管部门制定零星用指导价，用工指导价包含服务商税费、管理费、食宿费、交通费、劳务人员工资等费用。各单位与服务商签订的劳务合同不得超过最高限价。 | O90: √ | T90: 线下管控 | V90: 1.零星用工合同； 2.零星用工服务商中标通知书。 | W90: 各级单位-运检、配网、营销部门-项目管理人员、各级单位-运检、配网、营销部门-负责人 | X90: 每季度 | Y90: 抽查 | AA90: 每年 | AB90: 抽查 | AE90: 每年 | AF90: 抽查 | AH90: 是 | AI90: 是 | AJ90: 国网湖南省电力有限公司关于印发自营模式下规范使用零星劳务人员指导意见的通知（湘电公司人资〔2022〕13号） | AL90: 各级单位零星用工使用部门 | AN90: 新增关键控制点“零星劳务管控” | AP90: =A90=[2]员工报账!A90 -> TRUE | AQ90: =B90=[2]员工报账!B90 -> TRUE | AR90: =C90=[2]员工报账!C90 -> TRUE | AS90: =D90=[2]员工报账!D90 -> TRUE | AT90: =E90=[2]员工报账!E90 -> TRUE | AU90: =F90=[2]员工报账!F90 -> TRUE | AV90: =G90=[2]员工报账!G90 -> TRUE | AW90: =H90=[2]员工报账!H90 -> TRUE | ... BZ90: =AK90=[2]员工报账!AK90 -> TRUE
I91: 员工报账业务-27.零星劳务管控-控制措施03 | J91: 各单位零星劳务使用部门、财务部门要严格审核用工的真实性、合理性，对同一身份证号码在同一时段不同班组或供电所用工的不予结算。 | K91: √ | M91: √ | T91: 线下管控 | V91: 1.零星用工合同； 2.零星用工服务商中标通知书。 3.零星用工申请单； 4.零星用工结算单； 5.零星用工发票。 | W91: 各级单位-运检、配网、营销部门-项目管理人员、各级单位-运检、配网、营销部门-报销审核人、各级单位-财务部门-会计核算人员 | X91: 每季度 | Y91: 抽查 | AA91: 每年 | AB91: 抽查 | AE91: 每年 | AF91: 抽查 | AH91: 是 | AI91: 是 | AJ91: 国网湖南省电力有限公司关于印发自营模式下规范使用零星劳务人员指导意见的通知（湘电公司人资〔2022〕13号） | AL91: 各级单位财务部 | AN91: 新增关键控制点“零星劳务管控” | AP91: =A91=[2]员工报账!A91 -> TRUE | AQ91: =B91=[2]员工报账!B91 -> TRUE | AR91: =C91=[2]员工报账!C91 -> TRUE | AS91: =D91=[2]员工报账!D91 -> TRUE | AT91: =E91=[2]员工报账!E91 -> TRUE | AU91: =F91=[2]员工报账!F91 -> TRUE | AV91: =G91=[2]员工报账!G91 -> TRUE | AW91: =H91=[2]员工报账!H91 -> TRUE | ... BZ91: =AK91=[2]员工报账!AK91 -> TRUE
A92: 员工报账 | B92: 二、通用报账 | C92: 合规政策 | D92: 物业管理费 | E92: 超范围、标准、重复列支物业管理费引发引发合规稽查风险和资金支付风险。 | F92: 物业管理费缺失全流程资料、虚报列支不合规等多项问题： 1.合同签订前核定物业费使用范围不严，办公面积存在错误和虚假列支服务事项等。 2.费用开支无完整产权租赁依据，无物业租赁服务合同。 3.同一物业点重复申报物业费、申报金额超出合同业务收费标准。 4.部分经办人未按合同约定计费周期申报费用，提前列支尚未发生的物业管理费。 5.未区分自用、外租场地费用，虚增物业管理费，导致资金无依据流出。 | G92: 28.物业管理费报销 | H92: 物业管理费在规定范围内报销 | I92: 员工报账业务-28.物业管理费管控-控制措施01 | J92: 业务部门签合同前核定物业费范围，对办公面积审核，特约服务界定把关。 | K92: √ | M92: √ | O92: √ | T92: 线下管控 | V92: 1.报销 ( 资金支付 ) 审批单； 2.增值税专用发票； 3.合同； 4.费用清单 | W92: 各级单位-后勤部（综合服务中心）-报账人员、各级单位-后勤部（综合服务中心）-负责人 | X92: 每季度 | Y92: 抽查 | AA92: 每年 | AB92: 抽查 | AE92: 每年 | AF92: 抽查 | AH92: 是 | AI92: 是 | AJ92: 后勤〔2024〕31号《国网湖南电力后勤部关于加强办公用房物业服务项目规范化管理的通知》、《 国家电网有限公司会计基础管理办法 》（国网（财/2） 350-2018） （国家电网企管〔2019〕 132号） 、 《国家电网有限公司会计核算办法2021》 （国网（财/2） 469-2020） | AL92: 各级单位后勤部（综合服务中心） | AN92: 新增关键控制点“物业管理费报销” | AP92: =A92=[2]员工报账!A92 -> TRUE | AQ92: =B92=[2]员工报账!B92 -> TRUE | AR92: =C92=[2]员工报账!C92 -> TRUE | AS92: =D92=[2]员工报账!D92 -> TRUE | AT92: =E92=[2]员工报账!E92 -> TRUE | AU92: =F92=[2]员工报账!F92 -> TRUE | AV92: =G92=[2]员工报账!G92 -> TRUE | AW92: =H92=[2]员工报账!H92 -> TRUE | ... BZ92: =AK92=[2]员工报账!AK92 -> TRUE
I93: 员工报账业务-28.物业管理费管控-控制措施02 | J93: 归口管理部门对物业管理费用的数量、质量进行复核评价；核对计费周期、收费标准后再发起报销流程。 | K93: √ | M93: √ | N93: √ | O93: √ | T93: 线下管控 | V93: 1.报销 ( 资金支付 ) 审批单； 2.增值税专用发票； 3.合同； 4.费用清单 | W93: 各级单位-后勤部（综合服务中心）-报账人员、各级单位-后勤部（综合服务中心）-负责人 | X93: 每季度 | Y93: 抽查 | AA93: 每年 | AB93: 抽查 | AE93: 每年 | AF93: 抽查 | AH93: 是 | AI93: 是 | AJ93: 后勤〔2024〕31号《国网湖南电力后勤部关于加强办公用房物业服务项目规范化管理的通知》、《 国家电网有限公司会计基础管理办法 》（国网（财/2） 350-2018） （国家电网企管〔2019〕 132号） 、 《国家电网有限公司会计核算办法2021》 （国网（财/2） 469-2020） | AP93: =A93=[2]员工报账!A93 -> TRUE | AQ93: =B93=[2]员工报账!B93 -> TRUE | AR93: =C93=[2]员工报账!C93 -> TRUE | AS93: =D93=[2]员工报账!D93 -> TRUE | AT93: =E93=[2]员工报账!E93 -> TRUE | AU93: =F93=[2]员工报账!F93 -> TRUE | AV93: =G93=[2]员工报账!G93 -> TRUE | AW93: =H93=[2]员工报账!H93 -> TRUE | ... BZ93: =AK93=[2]员工报账!AK93 -> TRUE
I94: 员工报账业务-28.物业管理费管控-控制措施03 | J94: 财务审核环节核查票据、附件完整度，校验申报金额、缴费周期与合同条款一致性；对无依据、超额、超前和重复支付物业费予以驳回。 | K94: √ | M94: √ | P94: √ | Q94: √ | T94: 线下管控 | V94: 1.报销 ( 资金支付 ) 审批单； 2.增值税专用发票； 3.合同； 4.费用清单 | W94: 各级单位-后勤部（综合服务中心）-报账人员、各级单位-后勤部（综合服务中心）-负责人、各级单位-财务部门-成本管理人员 | X94: 每季度 | Y94: 抽查 | AA94: 每年 | AB94: 抽查 | AE94: 每年 | AF94: 抽查 | AH94: 是 | AI94: 是 | AJ94: 《国家电网有限公司会计基础管理办法 》（国网（财/2） 350-2018） （国家电网企管〔2019〕 132号） 、 《国家电网有限公司会计核算办法2021》（国网（财/2） 469-2020） | AL94: 各级单位后勤部（综合服务中心）、各级单位财务部 | AN94: 新增关键控制点“物业管理费报销” | AP94: =A94=[2]员工报账!A94 -> TRUE | AQ94: =B94=[2]员工报账!B94 -> TRUE | AR94: =C94=[2]员工报账!C94 -> TRUE | AS94: =D94=[2]员工报账!D94 -> TRUE | AT94: =E94=[2]员工报账!E94 -> TRUE | AU94: =F94=[2]员工报账!F94 -> TRUE | AV94: =G94=[2]员工报账!G94 -> TRUE | AW94: =H94=[2]员工报账!H94 -> TRUE | ... BZ94: =AK94=[2]员工报账!AK94 -> TRUE
A95: 员工报账 | B95: 二、通用报账 | C95: 合规政策 | D95: 物业管理费 | E95: 超范围、超额重复列支水电费引发引发合规风险和资金支付风险。 | F95: 办公场地水电费报销存在费用公私不明确，垫付套取资金风险。 1.存在办公区无单独抄表计量，需员工先垫付给第三方后取得电费发票再报销，存在私下串通私套费用列支。 2.存在超期，超额和重复报销情况，缺少缴费明细，费用难以追源核对。 | G95: 29.水电费报销 | H95: 水电费在规定范围内报销 | I95: 员工报账业务-29.水电费管控-控制措施01 | J95: 经手部门需定期及时报销，归口管理部门留存水电费抄表台账，全过程监管支出真实性。非自来水公司的供水单位提供用水，需要乡或村一级出具的供水证明。 | K95: √ | M95: √ | N95: √ | O95: √ | T95: 线下管控 | V95: 1.报销 ( 资金支付 ) 审批单； 2.增值税发票或收据 | W95: 各级单位-后勤部（综合服务中心）-报账人员、各级单位-后勤部（综合服务中心）-负责人、各级单位-运维检修部-报账人员、各级单位-运维检修部-负责人 | X95: 每季度 | Y95: 抽查 | AA95: 每年 | AB95: 抽查 | AE95: 每年 | AF95: 抽查 | AH95: 是 | AI95: 是 | AJ95: 《国家电网有限公司会计基础管理办法 》（国网（财/2） 350-2018） （国家电网企管〔2019〕 132号） 、 《国家电网有限公司会计核算办法2021》（国网（财/2） 469-2020） | AL95: 各级单位后勤部（综合服务中心）、各级单位-运维检修部 | AN95: 新增关键控制点“水电费报销” | AP95: =A95=[2]员工报账!A95 -> TRUE | AQ95: =B95=[2]员工报账!B95 -> TRUE | AR95: =C95=[2]员工报账!C95 -> TRUE | AS95: =D95=[2]员工报账!D95 -> TRUE | AT95: =E95=[2]员工报账!E95 -> TRUE | AU95: =F95=[2]员工报账!F95 -> TRUE | AV95: =G95=[2]员工报账!G95 -> TRUE | AW95: =H95=[2]员工报账!H95 -> TRUE | ... BZ95: =AK95=[2]员工报账!AK95 -> TRUE
I96: 员工报账业务-29.水电费管控-控制措施02 | J96: 财务部门审核发票、收据金额的准确性，按实际发生据实报账，提供垫付支付凭证。 | K96: √ | P96: √ | Q96: √ | T96: 线下管控 | V96: 1.报销 ( 资金支付 ) 审批单； 2.增值税发票或收据 | W96: 各级单位-后勤部（综合服务中心）-报账人员、各级单位-后勤部（综合服务中心）-负责人、各级单位-运维检修部-报账人员、各级单位-运维检修部-负责人各级单位-财务部门-成本管理人员 | X96: 每季度 | Y96: 抽查 | AA96: 每年 | AB96: 抽查 | AE96: 每年 | AF96: 抽查 | AH96: 是 | AI96: 是 | AJ96: 《国家电网有限公司会计基础管理办法 》（国网（财/2） 350-2018） （国家电网企管〔2019〕 132号） 、 《国家电网有限公司会计核算办法2021》（国网（财/2） 469-2020） | AL96: 各级单位后勤部（综合服务中心）、各级单位-运维检修部、各级单位财务部 | AN96: 新增关键控制点“水电费报销” | AP96: =A96=[2]员工报账!A96 -> TRUE | AQ96: =B96=[2]员工报账!B96 -> TRUE | AR96: =C96=[2]员工报账!C96 -> TRUE | AS96: =D96=[2]员工报账!D96 -> TRUE | AT96: =E96=[2]员工报账!E96 -> TRUE | AU96: =F96=[2]员工报账!F96 -> TRUE | AV96: =G96=[2]员工报账!G96 -> TRUE | AW96: =H96=[2]员工报账!H96 -> TRUE | ... BZ96: =AK96=[2]员工报账!AK96 -> TRUE
A97: 员工报账 | B97: 二、通用报账 | C97: 合规政策 | D97: 房屋修理费 | E97: 超额、高套虚列房屋修理费引发引发合规风险和资金支付风险。 | F97: 后勤项目高套材料单价，多计多结资金。 1.房屋零星维修项目，与施工方签订施工合同，其中某些施工材料价格偏高，劳务分包施工，上下游管控监督不力，其中材料结算价格高套单价，超过市场普遍价格。导致多计多结导致审计整改。 2.房屋维修项目超预算，增补项目未经上级单位批准，擅自扩大后勤项目预算安排。 | G97: 30.房屋修理费报销 | H97: 房屋修理费在规定范围内报销 | I97: 员工报账业务-30.房屋修理费管控-控制措施01 | J97: 归口部门对工程施行全过程及结果监督，严格需求审核各单位提交的含维修内容、紧急程度的任务单，审核是否属于零星维修范围。 | K97: √ | L97: √ | M97: √ | N97: √ | O97: √ | T97: 线下管控 | V97: 1.报销 ( 资金支付 ) 审批单； 2.增值税发票或收据； 3.合同； 4.开工报告； 5.工程量签证单； 6.竣工验收报告； 7.项目结算表 、审计报告 ( 审定表签章页 ) | W97: 各级单位-后勤部（综合服务中心）-报账人员、各级单位-后勤部（综合服务中心）-负责人、各级单位-运维检修部-报账人员、各级单位-运维检修部-负责人 | X97: 每季度 | Y97: 抽查 | AA97: 每年 | AB97: 抽查 | AE97: 每年 | AF97: 抽查 | AH97: 是 | AI97: 是 | AJ97: 《国家电网有限公司会计基础管理办法 》（国网（财/2） 350-2018） （国家电网企管〔2019〕 132号） 、 《国家电网有限公司会计核算办法2021》 （国网（财/2） 469-2022） | AL97: 各级单位后勤部（综合服务中心）、各级单位-运维检修部 | AN97: 新增关键控制点“房屋修理费报销” | AP97: =A97=[2]员工报账!A97 -> TRUE | AQ97: =B97=[2]员工报账!B97 -> TRUE | AR97: =C97=[2]员工报账!C97 -> TRUE | AS97: =D97=[2]员工报账!D97 -> TRUE | AT97: =E97=[2]员工报账!E97 -> TRUE | AU97: =F97=[2]员工报账!F97 -> TRUE | AV97: =G97=[2]员工报账!G97 -> TRUE | AW97: =H97=[2]员工报账!H97 -> TRUE | ... BZ97: =AK97=[2]员工报账!AK97 -> TRUE
I98: 员工报账业务-30.房屋修理费管控-控制措施02 | J98: 要求施工单位及时提交含施工照片、工程量明细的签证单，由需求单位与归口部门共同核对确认，避免工程量数据失真、台账不清。汇总整理任务单、签证单等全套台账资料，提交结算单位开展单价专项审核，规范资金使用，严控单价风险。 | K98: √ | L98: √ | M98: √ | N98: √ | O98: √ | T98: 线下管控 | V98: 1.报销 ( 资金支付 ) 审批单； 2.增值税发票或收据； 3.合同； 4.开工报告； 5.工程量签证单； 6.竣工验收报告； 7.项目结算表 、审计报告 ( 审定表签章页 ) | W98: 各级单位-后勤部（综合服务中心）-报账人员、各级单位-后勤部（综合服务中心）-负责人、各级单位-运维检修部-报账人员、各级单位-运维检修部-负责人 | X98: 每季度 | Y98: 抽查 | AA98: 每年 | AB98: 抽查 | AE98: 每年 | AF98: 抽查 | AH98: 是 | AI98: 是 | AJ98: 《国家电网有限公司会计基础管理办法 》（国网（财/2） 350-2018） （国家电网企管〔2019〕 132号） 、 《国家电网有限公司会计核算办法2021》 （国网（财/2） 469-2022） | AL98: 各级单位后勤部（综合服务中心）、各级单位-运维检修部 | AN98: 新增关键控制点“房屋修理费报销” | AP98: =A98=[2]员工报账!A98 -> TRUE | AQ98: =B98=[2]员工报账!B98 -> TRUE | AR98: =C98=[2]员工报账!C98 -> TRUE | AS98: =D98=[2]员工报账!D98 -> TRUE | AT98: =E98=[2]员工报账!E98 -> TRUE | AU98: =F98=[2]员工报账!F98 -> TRUE | AV98: =G98=[2]员工报账!G98 -> TRUE | AW98: =H98=[2]员工报账!H98 -> TRUE | ... BZ98: =AK98=[2]员工报账!AK98 -> TRUE
I99: 员工报账业务-30.房屋修理费管控-控制措施03 | J99: 财务审核对合理性和资金安全做把控1.着重审核发票、结算清单金额 ，核对计价标准、工程量与验收资料是否匹配。2.严格规范报销附件要求，工程结算清单，施工合同和签证单缺一不可，对资料不全、单价异常的单据驳回，不予付款。 | K99: √ | N99: √ | Q99: √ | T99: 线下管控 | V99: 1.报销 ( 资金支付 ) 审批单； 2.增值税发票或收据； 3.合同； 4.开工报告； 5.工程量签证单； 6.竣工验收报告； 7.项目结算表 、审计报告 ( 审定表签章页 ) | W99: 各级单位-后勤部（综合服务中心）-报账人员、各级单位-后勤部（综合服务中心）-负责人、各级单位-运维检修部-报账人员、各级单位-运维检修部-负责人各级单位-财务部门-成本管理人员 | X99: 每季度 | Y99: 抽查 | AA99: 每年 | AB99: 抽查 | AE99: 每年 | AF99: 抽查 | AH99: 是 | AI99: 是 | AJ99: 《国家电网有限公司会计基础管理办法 》（国网（财/2） 350-2018） （国家电网企管〔2019〕 132号） 、 《国家电网有限公司会计核算办法2021》 （国网（财/2） 469-2022） | AL99: 各级单位后勤部（综合服务中心）、各级单位-运维检修部、各级单位财务部 | AN99: 新增关键控制点“房屋修理费报销” | AP99: =A99=[2]员工报账!A99 -> TRUE | AQ99: =B99=[2]员工报账!B99 -> TRUE | AR99: =C99=[2]员工报账!C99 -> TRUE | AS99: =D99=[2]员工报账!D99 -> TRUE | AT99: =E99=[2]员工报账!E99 -> TRUE | AU99: =F99=[2]员工报账!F99 -> TRUE | AV99: =G99=[2]员工报账!G99 -> TRUE | AW99: =H99=[2]员工报账!H99 -> TRUE | ... BZ99: =AK99=[2]员工报账!AK99 -> TRUE
A100: 员工报账 | B100: 二、通用报账 | C100: 合规政策 | D100: 租赁费 | E100: 未规范区分租赁类型，合同管理滞后、超标准列支租金形成资金浪费带来审计、税务稽查合规风险， | F100: 租赁业务从合同签订到资金保险全流程存在多项管控漏洞。 1.未按规定履行决策和审批程序或超越权限范围租赁资产。 2.资产租赁未履行评估备案和审批程序，导致公司利益损失； 3.违反资产评估相关规定，故意隐匿评估范围资产，或向评估机构提供虚假会计资料，导致评估结果失真，造成经济损失； 4.违反公平交易原则，以不合理价格出租资产，或低于租赁价转租资产； 5.因管理不善或人为故意等原因造成租赁资产盘亏、毁损等，造成资产损失。 | G100: 31.租赁费报销 | H100: 租赁费在规定范围内报销 | I100: 员工报账业务-31.租赁费管控-控制措施01 | J100: 实物资产管理部门负责提出资产承租、出租需求；负责承租、出租资产验收、盘点和移交，签订经营租赁合同；负责承租、出租资产实物账管理，做好经营性租赁合同的租金催收和支付。严格实行分类管理、分级审批管理，不得超范围出租或私自办理资产出租业务，不得无偿占有、使用公司资产。 | K100: √ | N100: √ | Q100: √ | T100: 线下管控 | V100: 1.需求审批单 2.资产评估报告 3.合同或协议； 4产权证明材料； | W100: 各级单位-各部门-报账人员、各级单位-各部门-负责人、 | X100: 每季度 | Y100: 抽查 | AA100: 每年 | AB100: 抽查 | AE100: 每年 | AF100: 抽查 | AH100: 是 | AI100: 是 | AJ100: 《国家电网有限公司会计基础管理办法 》( 国网 ( 财/2) 350-2018) ( 国家电网企管〔2019〕 132号 ) 、《 国家电网有限公司会 计核算办法2021》 ( 国网 (财/2) 469- 2020) 、 | AL100: 各级单位后勤部（综合服务中心）、各级单位设备部 | AN100: 新增关键控制点“租赁费报销” | AP100: =A100=[2]员工报账!A100 -> TRUE | AQ100: =B100=[2]员工报账!B100 -> TRUE | AR100: =C100=[2]员工报账!C100 -> TRUE | AS100: =D100=[2]员工报账!D100 -> TRUE | AT100: =E100=[2]员工报账!E100 -> TRUE | AU100: =F100=[2]员工报账!F100 -> TRUE | AV100: =G100=[2]员工报账!G100 -> TRUE | AW100: =H100=[2]员工报账!H100 -> TRUE | ... BZ100: =AK100=[2]员工报账!AK100 -> TRUE
...

Sheet 员工报账（9.2）
A1: 风控矩阵-员工报账
A2: 业务条线 | B2: 业务领域 | C2: 控制目标 | D2: 业务流程步骤 | E2: 经营风险 | F2: 典型问题 | G2: 关键控制点 | H2: 控制要求 | I2: 控制措施 编号 | J2: 控制措施 | K2: 控制措施分类 | T2: 控制方式 | U2: 控制系统 | V2: 控制载体 | W2: 责任主体 | X2: 业务自评价 | AA2: 集团监督 评价 | AD2: 数字化监督场景 | AH2: 现有制度及文件落实情况 | AK2: 总部审核部门 | AL2: 湖南公司审核部门 | AM2: 是否适用
K3: 不相容岗位 | L3: 分级授权 | M3: 业务真实性控制 | N3: 预算管控 | O3: 合同控制 | P3: 收付控制 | Q3: 会计监督 | R3: 财产保护 | S3: 分析与评价 | X3: 评价频率 | Y3: 评价范围 | Z3: 评价结论 | AA3: 评价频率 | AB3: 评价范围 | AC3: 评价结论 | AD3: 数字化监督场景 | AE3: 评价频率 | AF3: 评价范围 | AG3: 评价结论 | AH3: 是否已要求 | AI3: 是否满足要求 | AJ3: 对应制度及文件名称
A4: 员工报账 | B4: 一、员工差旅 | C4: 资金资产安全 | D4: 出差申请 | E4: 出差事项不真实，出差无实质内容，无明确公务目的，虚列套取费用，导致资金安全风险。 | F4: 87.违规发放津贴补贴：存在多报差旅补贴、虚报差旅补贴等问题。 | G4: 1.出差申请发起 | H4: 出差有明确公务目的，出差时间、地点、人员与出差通知一致。 | I4: 员工报账业务-1.出差申请发起-控制措施01 | J4: 出差员工部门负责人对员工出差内容的复核，重点审查出差申请单人员、地点、事由等信息。 | M4: √ | T4: 系统已建 | U4: 国网商旅 | V4: 1.出差通知、培训通知等出差缘由证明材料。 | W4: 各级单位-各部门-出差人员、各级单位-各部门-负责人、商旅云公司 | X4: 每日 | Y4: 全量检查 | AA4: 每年 | AB4: 抽查 | AD4: 员工差旅出差申请监督场景 | AE4: 每月 | AF4: 抽查 | AH4: 是 | AI4: 是 | AJ4: 《国家电网有限公司差旅费管理办法》（国家电网企管〔2026〕101号）第四条、第二十四条、《国网湖南省电力有限公司关于印发加强差旅费管理有关规定的通知》第二条、第三条 | AK4: 国网财务部 | AL4: 各级单位财务部 | AM4: 是
I5: 员工报账业务-1.出差申请发起-控制措施02 | J5: 健全“申请-预订-报销”数据联动校验规则，落实预算控制，系统自动比对出差事项与出差产生的票据的逻辑一致性。 | M5: √ | N5: √ | T5: 系统已建 | U5: 国网商旅 | V5: 1.出差审批单。 | W5: 各级单位-各部门-出差人员、商旅云公司 | X5: 每日 | Y5: 全量检查 | AA5: 每年 | AB5: 抽查 | AD5: 员工差旅出差申请监督场景 | AE5: 每月 | AF5: 抽查 | AH5: 是 | AI5: 是 | AJ5: 《国家电网有限公司差旅费管理办法》（国家电网企管〔2026〕101号）第四条、第二十四条、《国网湖南省电力有限公司关于印发加强差旅费管理有关规定的通知》第二条、第三条 | AK5: 国网财务部 | AL5: 各级单位财务部 | AM5: 否
I6: 员工报账业务-1.出差申请发起-控制措施03 | J6: 健全差旅费成本中心校验机制，赴异地挂职、按照规定探亲在途期间出差申请选择原单位成本中心，挂职期间出差申请选择挂职单位成本中心。 | N6: √ | Q6: √ | T6: 系统已建 | U6: 国网商旅 | V6: 1.系统出差申请单校验记录等。 | W6: 各级单位-各部门-出差人员、商旅云公司 | X6: 每日 | Y6: 全量检查 | AA6: 每年 | AB6: 抽查 | AD6: 员工差旅出差申请监督场景 | AE6: 每月 | AF6: 抽查 | AH6: 是 | AI6: 是 | AJ6: 《国家电网有限公司差旅费管理办法》（国家电网企管〔2026〕101号）第四条、第二十四条、《国网湖南省电力有限公司关于印发加强差旅费管理有关规定的通知》第二条、第三条 | AK6: 国网财务部 | AL6: 各级单位财务部 | AM6: 是
G7: 2.出差申请审批 | H7: 按规定执行出差审批制度。 | I7: 员工报账业务-2.出差申请审批-控制措施01 | J7: 流程固化与防逆向控制，商旅云公司固化“审批-预订-报销”流程，严格限制并需特殊授权才能“取消审批”等逆向操作。 | L7: √ | Q7: √ | T7: 系统已建 | U7: 国网商旅 | V7: 1.出差通知、培训通知等出差缘由证明材料； 2.出差审批单； 3.系统出差申请单审批轨迹。 | W7: 各级单位-各部门-出差人员、商旅云公司 | X7: 每日 | Y7: 全量检查 | AA7: 每年 | AB7: 抽查 | AD7: 员工差旅出差申请监督场景 | AE7: 每月 | AF7: 抽查 | AH7: 是 | AI7: 是 | AJ7: 《国家电网有限公司差旅费管理办法》（国家电网企管〔2026〕101号）第二十二条 | AK7: 国网财务部 | AL7: 各级单位财务部 | AM7: 否
I8: 员工报账业务-2.出差申请审批-控制措施02 | J8: 全链条强制关联控制，系统强制将“审批单号”作为商旅预订及费用报销的唯一前提。 | Q8: √ | T8: 系统已建 | U8: 国网商旅 | V8: 1.出差通知、培训通知等出差缘由证明材料； 2.出差审批单。 | W8: 各级单位-各部门-出差人员、商旅云公司 | X8: 每日 | Y8: 全量检查 | AA8: 每年 | AB8: 抽查 | AD8: 员工差旅出差申请监督场景 | AE8: 每月 | AF8: 抽查 | AH8: 是 | AI8: 是 | AJ8: 《国家电网有限公司差旅费管理办法》（国家电网企管〔2026〕101号）第四条、第二十四条、第二十六条 | AK8: 国网财务部 | AL8: 各级单位财务部 | AM8: 否
I9: 员工报账业务-2.出差申请审批-控制措施03 | J9: 商旅云公司严禁后台“绿色通道”操作，禁止平台通过电话申请取消审批行为。 | M9: √ | T9: 系统待建 | U9: 国网商旅 | V9: 1.出差通知、培训通知等出差缘由证明材料； 2.出差审批单； 3.系统出差申请单审批轨迹。 | W9: 各级单位-各部门-出差人员、商旅云公司 | X9: 每日 | Y9: 全量检查 | AA9: 每年 | AB9: 抽查 | AD9: 员工差旅出差申请监督场景 | AE9: 每月 | AF9: 抽查 | AH9: 是 | AI9: 是 | AJ9: 《国家电网有限公司差旅费管理办法》（国家电网企管〔2026〕101号）第四条、第二十四条、第二十六条 | AK9: 国网财务部 | AL9: 各级单位财务部 | AM9: 否
A10: 员工报账 | B10: 一、员工差旅 | C10: 税务合规 | D10: 出差申请 | E10: 商旅平台违规取消事前审批流程，导致出现“先出差后申请”的情况，引发舞弊及合规管理风险。 | F10: 87.违规发放津贴补贴：存在多报差旅补贴、虚报差旅补贴等问题。 | G10: 3.出差申请流程控制 | H10: 出差申请日期早于出差日期。 | I10: 员工报账业务-3.出差申请流程控制-控制措施01 | J10: 审批要素完整性校验，系统强制校验审批单的必备要素，对缺少出差事由等关键要素的申请单不予通过。 | M10: √ | T10: 系统已建 | U10: 国网商旅 | V10: 1.系统出差申请单审批轨迹； 2.系统记录的申请单提交时间和出差时间。 | W10: 商旅云公司 | X10: 每日 | Y10: 全量检查 | AA10: 每年 | AB10: 抽查 | AD10: 员工差旅流程配置监督场景 | AE10: 每月 | AF10: 抽查 | AH10: 是 | AI10: 是 | AJ10: 《国家电网有限公司差旅费管理办法》（国家电网企管〔2026〕101号）第五条 | AK10: 国网财务部 | AL10: 各级单位财务部 | AM10: 否
I11: 员工报账业务-3.出差申请流程控制-控制措施02 | J11: 严格执行不相容控制，系统根据组织架构与授权清单自动匹配并校验审批人权限，防范越权审批 | R11: √ | T11: 系统已建 | U11: 国网商旅 | V11: 1.系统记录的申请单提交时间和出差时间。 | W11: 商旅云公司、各级单位-各部门-出差人员、各级单位-各部门-负责人 | X11: 每日 | Y11: 全量检查 | AA11: 每年 | AB11: 抽查 | AD11: 员工差旅流程配置监督场景 | AE11: 每月 | AF11: 抽查 | AH11: 是 | AI11: 是 | AJ11: 《国家电网有限公司差旅费管理办法》（国家电网企管〔2026〕101号）第五条 | AK11: 国网财务部 | AL11: 各级单位财务部 | AM11: 否
I12: 员工报账业务-3.出差申请流程控制-控制措施03 | J12: 建立定期分析、评价与问责机制，各部门对审批时效、驳回率、特批事项进行专项分析，审计部门、纪检部门等监督部门对违规审批、补批行为依规问责。 | M12: √ | R12: √ | S12: √ | T12: 线下管控 | V12: 1.系统记录的申请单提交时间和出差时间。 | W12: 商旅云公司、各级单位-审计部门、纪检部门等监督部门-监督、纪检管理人员 | X12: 每日 | Y12: 全量检查 | AA12: 每年 | AB12: 抽查 | AD12: 员工差旅流程配置监督场景 | AE12: 每月 | AF12: 抽查 | AH12: 是 | AI12: 是 | AJ12: 《国家电网有限公司差旅费管理办法》（国家电网企管〔2026〕101号）第五条 | AK12: 国网财务部 | AL12: 各级单位财务部 | AM12: 是
C13: 税务合规 | D13: 差旅预订 | E13: 商旅平台酒店存在棋牌、麻将、电竞等敏感字眼，商旅平台违规上架引发合规风险。 | G13: 4.酒店入驻上架控制 | H13: 酒店资源上架流程合规，且履行必要的审批手续。 | I13: 员工报账业务-4.酒店入驻上架控制-控制措施01 | J13: 商旅云公司强化供应商准入审核，对新签约酒店的的资质有效性、服务适配性以及风险可控性等信息进行事前审核。 | O13: √ | T13: 系统待建 | U13: 国网商旅 | V13: 1.酒店资质、营业执照、房型清单。 | W13: 商旅云公司 | X13: 每日 | Y13: 全量检查 | AA13: 每年 | AB13: 抽查 | AD13: 员工差旅预订监督场景 | AE13: 每月 | AF13: 抽查 | AH13: 是 | AI13: 是 | AJ13: 《国家电网有限公司差旅费管理办法》（国家电网企管〔2026〕101号）第五条 | AK13: 国网财务部 | AL13: 各级单位财务部 | AM13: 否
I14: 员工报账业务-4.酒店入驻上架控制-控制措施02 | J14: 商旅云公司建立并动态更新《敏感词库与酒店属性负面清单》，系统自动拦截负面清单内容并转人工复核。 | O14: √ | Q14: √ | S14: √ | T14: 系统待建 | U14: 国网商旅 | V14: 1.系统敏感词库与酒店属性负面清单。 | W14: 商旅云公司 | X14: 每日 | Y14: 全量检查 | AA14: 每年 | AB14: 抽查 | AD14: 员工差旅预订监督场景 | AE14: 每月 | AF14: 抽查 | AH14: 是 | AI14: 是 | AJ14: 《国家电网有限公司差旅费管理办法》（国家电网企管〔2026〕101号）第五条 | AK14: 国网财务部 | AL14: 各级单位财务部 | AM14: 否
I15: 员工报账业务-4.酒店入驻上架控制-控制措施03 | J15: 追回违规上架酒店产生的资金浪费，并对相关负责人按规定给予处分处理。 | R15: √ | S15: √ | T15: 线下管控 | V15: 1.问责证明材料。 | W15: 商旅云公司 | X15: 每日 | Y15: 全量检查 | AA15: 每年 | AB15: 抽查 | AD15: 员工差旅预订监督场景 | AE15: 每月 | AF15: 抽查 | AH15: 是 | AI15: 是 | AJ15: 《国家电网有限公司差旅费管理办法》（国家电网企管〔2026〕101号）第五条 | AK15: 国网财务部 | AL15: 各级单位财务部 | AM15: 否
C16: 资金资产安全 | D16: 差旅预订 | E16: 酒店价格虚高易引发套取资金，引发廉政风险。 | F16: 87.违规发放津贴补贴：存在多报差旅补贴、虚报差旅补贴等问题。 | G16: 5.单体酒店上架及价格定价管控 | H16: 商旅平台酒店资源价格真实合理。 | I16: 员工报账业务-5.单体酒店上架及价格定价管控-控制措施01 | J16: 增加单体酒店上架申请审批流程，由各单位办公室汇总审核本单位酒店需求，向商旅云公司提交上架。 | L16: √ | O16: √ | T16: 系统已建 | U16: 国网商旅 | V16: 1.协议单体酒店推荐表单。 | W16: 商旅云公司、各级单位-办公室财务部、省公司-财务部 | X16: 每日 | Y16: 全量检查 | AA16: 每年 | AB16: 抽查 | AD16: 员工差旅预订监督场景 | AE16: 每月 | AF16: 抽查 | AH16: 是 | AI16: 是 | AJ16: 《国家电网有限公司差旅费管理办法》（国家电网企管〔2026〕101号）第五条 | AK16: 国网财务部 | AL16: 各级单位财务部 | AM16: 是
I17: 员工报账业务-5.单体酒店上架及价格定价管控-控制措施02 | J17: 商旅云公司强化协议签订管控，严格审核酒店资质，严控无理由上架，防范舞弊行为。 | O17: √ | T17: 系统已建 | U17: 国网商旅 | V17: 1.酒单违规风险清单； 2.采购协议酒店清单； 3.酒店上架评审报告。 | W17: 商旅云公司 | X17: 每日 | Y17: 全量检查 | AA17: 每年 | AB17: 抽查 | AD17: 员工差旅预订监督场景 | AE17: 每月 | AF17: 抽查 | AH17: 是 | AI17: 是 | AJ17: 《国家电网有限公司差旅费管理办法》（国家电网企管〔2026〕101号）第五条 | AK17: 国网财务部 | AL17: 各级单位财务部 | AM17: 否
I18: 员工报账业务-5.单体酒店上架及价格定价管控-控制措施03 | J18: 加强员工行为管控，商旅云公司强化酒店订单在线监督，防范员工违规套取资金。 | M18: √ | R18: √ | T18: 系统已建 | U18: 国网商旅 | V18: 1.酒店合作协议。 | W18: 商旅云公司 | X18: 每日 | Y18: 全量检查 | AA18: 每年 | AB18: 抽查 | AD18: 员工差旅预订监督场景 | AE18: 每月 | AF18: 抽查 | AH18: 是 | AI18: 是 | AJ18: 《国家电网有限公司差旅费管理办法》（国家电网企管〔2026〕101号）第五条 | AK18: 国网财务部 | AL18: 各级单位财务部 | AM18: 否
A19: 员工报账 | B19: 一、员工差旅 | C19: 资金资产安全 | D19: 差旅预订 | E19: 酒店价格虚高易引发套取资金，引发廉政风险。 | F19: 87.违规发放津贴补贴：存在多报差旅补贴、虚报差旅补贴等问题。 | G19: 5.单体酒店上架及价格定价管控 | H19: 商旅平台酒店资源价格真实合理。 | I19: 员工报账业务-5.单体酒店上架及价格定价管控-控制措施04 | J19: 建立负面清单，及时清退违规酒店。 | R19: √ | S19: √ | T19: 线下管控 | V19: 1.酒店风险识别机制； 2.员工体验反馈。 | W19: 商旅云公司 | X19: 每日 | Y19: 全量检查 | AA19: 每年 | AB19: 抽查 | AD19: 员工差旅预订监督场景 | AE19: 每月 | AF19: 抽查 | AH19: 是 | AI19: 是 | AJ19: 《国家电网有限公司差旅费管理办法》（国家电网企管〔2026〕101号）第五条 | AK19: 国网财务部 | AL19: 各级单位财务部 | AM19: 否
D20: 差旅预订 | E20: 员工在同一时间段内重复预订酒店资源，存在套取资金风险。 | F20: 87.违规发放津贴补贴：存在多报差旅补贴、虚报差旅补贴等问题。 | G20: 6.酒店预订 | H20: 同一员工在同一时间段内，就同一出差行程，仅能生成一个有效住宿订单。 | I20: 员工报账业务-6.酒店预订-控制措施01 | J20: 商旅云公司完善重复订单系统校验规则，自动拦截并预警同一人员、时段重叠的酒店订单申请。 | M20: √ | T20: 系统已建 | U20: 国网商旅 | V20: 1.商旅订单； 2.出差通知、培训通知等出差缘由证明材料。 | W20: 各级单位-各部门-出差人员、商旅云公司 | X20: 每日 | Y20: 全量检查 | AA20: 每年 | AB20: 抽查 | AD20: 员工差旅预订监督场景 | AE20: 每月 | AF20: 抽查 | AH20: 是 | AI20: 是 | AJ20: 《国家电网有限公司差旅费管理办法》（国家电网企管〔2026〕101号）第二十四条 | AK20: 国网财务部 | AL20: 各级单位财务部 | AM20: 否
I21: 员工报账业务-6.酒店预订-控制措施02 | J21: 商旅云公司健全入住轨迹验证与反馈机制，自动识别入住轨迹异常情况，即时预警有关责任人。 | M21: √ | S21: √ | T21: 系统已建 | U21: 国网商旅 | V21: 1.系统拦截记录。 | W21: 各级单位-各部门-出差人员、商旅云公司 | X21: 每日 | Y21: 全量检查 | AA21: 每年 | AB21: 抽查 | AD21: 员工差旅预订监督场景 | AE21: 每月 | AF21: 抽查 | AH21: 是 | AI21: 是 | AJ21: 《国家电网有限公司差旅费管理办法》（国家电网企管〔2026〕101号）第二十四条 | AK21: 国网财务部 | AL21: 各级单位财务部 | AM21: 否
I22: 员工报账业务-6.酒店预订-控制措施03 | J22: 财务部门加强出差申请与酒店订单的交叉复核，校验人员、时间、订单的合理性与唯一性。 | M22: √ | T22: 系统已建 | U22: 国网商旅 | V22: 1.出差报销单； 2.入住轨迹与异常情况反馈。 | W22: 各级单位-各部门-出差人员、各级单位-财务部门-成本管理人员、商旅云公司 | X22: 每日 | Y22: 全量检查 | AA22: 每年 | AB22: 抽查 | AD22: 员工差旅预订监督场景 | AE22: 每月 | AF22: 抽查 | AH22: 是 | AI22: 是 | AJ22: 《国家电网有限公司差旅费管理办法》（国家电网企管〔2026〕101号）第二十四条 | AK22: 国网财务部 | AL22: 各级单位财务部 | AM22: 是
C23: 税务合规 | D23: 差旅报销 | E23: 擅自扩大差旅费开支范围，提高差旅费开支标准，增加差旅出行成本。 | F23: 87.违规发放津贴补贴：存在多报差旅补贴、虚报差旅补贴等问题。 | G23: 7.差旅标准执行 | H23: 差旅费开支标准、开支范围符合本单位差旅费标准。 | I23: 员工报账业务-7.差旅标准执行-控制措施01 | J23: 商旅云公司完善差旅费超标刚性管控功能，系统对超标申请酒店、交通工具和差旅补助进行自动隐藏。 | M23: √ | R23: √ | T23: 系统已建 | U23: 国网商旅 | V23: 1.差旅标准系统校验规则库； 2.出差通知、培训通知等出差缘由证明材料； 3.出差审批单； 4.出差报销单。 | W23: 各级单位-财务部门-预算管理人员、各级单位-各部门-出差人员、各级单位-各部门-负责人、各级单位-财务部门-成本管理人员、商旅云公司 | X23: 每日 | Y23: 全量检查 | AA23: 每年 | AB23: 抽查 | AD23: 员工差旅费用标准监督场景 | AE23: 每月 | AF23: 抽查 | AH23: 是 | AI23: 是 | AJ23: 《国家电网有限公司差旅费管理办法》（国家电网企管〔2026〕101号）第八条、第十一条至第十九条 | AK23: 国网财务部 | AL23: 各级单位财务部 | AM23: 否
I24: 员工报账业务-7.差旅标准执行-控制措施02 | J24: 财务部门加强出差类别与出差性质审核，重点关注评标、培训等特殊出差事项政策执行情况。 | M24: √ | Q24: √ | T24: 系统已建 | U24: 国网商旅 | V24: 1.差旅标准系统校验规则库； 2.出差通知、培训通知等出差缘由证明材料； 3.出差审批单； 4.出差报销单。 | W24: 各级单位-财务部门-预算管理人员、各级单位-各部门-负责人、各级单位-财务部门-成本管理人员、商旅云公司 | X24: 每日 | Y24: 全量检查 | AA24: 每年 | AB24: 抽查 | AD24: 员工差旅费用标准监督场景 | AE24: 每月 | AF24: 抽查 | AH24: 是 | AI24: 是 | AJ24: 《国家电网有限公司差旅费管理办法》（国家电网企管〔2026〕101号）第八条、第十一条至第十九条 | AK24: 国网财务部 | AL24: 各级单位财务部 | AM24: 是
I25: 员工报账业务-7.差旅标准执行-控制措施03 | J25: 纪检部门推动退赔与整改机制，对超标报销行为依规严肃问责。 | R25: √ | S25: √ | T25: 线下管控 | V25: 1.问责证明材料。 | W25: 各级单位-财务部门-预算管理人员、各级单位-各部门-出差人员、各级单位-各部门-负责人、各级单位-财务部门-成本管理人员、商旅云公司、各级单位-纪检部门-纪检管理人员 | X25: 每日 | Y25: 全量检查 | AA25: 每年 | AB25: 抽查 | AD25: 员工差旅费用标准监督场景 | AE25: 每月 | AF25: 抽查 | AH25: 是 | AI25: 是 | AJ25: 《国家电网有限公司差旅费管理办法》（国家电网企管〔2026〕101号）第八条、第十一条至第十九条、《国网湖南省电力有限公司关于印发加强差旅费管理有关规定的通知》第一条 | AK25: 国网财务部 | AL25: 各级单位财务部 | AM25: 是
A26: 员工报账 | B26: 一、员工差旅 | C26: 资金资产安全 | D26: 差旅报销 | E26: 虚报冒领差旅费，虚列套取费用，导致资金安全风险。 | F26: 87.违规发放津贴补贴：存在多报差旅补贴、虚报差旅补贴等问题。 | G26: 8.差旅报销合规性控制 | H26: 交通费、公杂费、住宿费等报销真实发生，差旅费报销准确。 | I26: 员工报账业务-8.差旅报销合规性控制-控制措施01 | J26: 建立业务部门费用报销前置审核机制，对机票、酒店、火车、补助等金额准确性复核。 | M26: √ | Q26: √ | R26: √ | T26: 系统已建 | U26: 国网商旅 | V26: 1.出差通知、培训通知等出差缘由证明材料； 2.出差审批单； 3.预订的商旅订单； 4.发票； 5.考勤记录。 | W26: 各级单位-各部门-出差人员、各级单位-各部门-出差报销审核人、各级单位-财务部门-成本管理人员、商旅云公司 | X26: 每日 | Y26: 全量检查 | AA26: 每年 | AB26: 抽查 | AD26: 员工差旅报销监督场景 | AE26: 每月 | AF26: 抽查 | AH26: 是 | AI26: 是 | AJ26: 《国网财务部、后勤部关于进一步规范差旅伙食费和交通费收交管理有关事项的通知》第三条、第四条 《国家电网有限公司差旅费管理办法》（国家电网企管〔2026〕101号）第十二条、第十三条、第十七条、第二十四条 | AK26: 国网财务部 | AL26: 各级单位财务部 | AM26: 是
I27: 员工报账业务-8.差旅报销合规性控制-控制措施02 | J27: 商旅云公司强化时空逻辑系统校验，对“出差时间-住宿时间-车票时间”进行自动校验，拦截或预警重叠数据。 | M27: √ | Q27: √ | T27: 系统已建 | U27: 国网商旅 | V27: 1.出差通知、培训通知等出差缘由证明材料； 2.出差审批单； 3.预订的商旅订单； 4.发票； 5.考勤记录。 | W27: 商旅云公司 | X27: 每日 | Y27: 全量检查 | AA27: 每年 | AB27: 抽查 | AD27: 员工差旅报销监督场景 | AE27: 每月 | AF27: 抽查 | AH27: 是 | AI27: 是 | AJ27: 《国网财务部、后勤部关于进一步规范差旅伙食费和交通费收交管理有关事项的通知》第三条、第四条 《国家电网有限公司差旅费管理办法》（国家电网企管〔2026〕101号第十二条、第十三条、第十七条、第二十四条 | AK27: 国网财务部 | AL27: 各级单位财务部 | AM27: 否
I28: 员工报账业务-8.差旅报销合规性控制-控制措施03 | J28: 商旅云公司健全票据使用状态规则，重点筛查“未使用”的交通票据，防范员工利用废票虚报费用或重复报销。 | M28: √ | R28: √ | T28: 系统已建 | U28: 国网商旅 | V28: 1.出差通知、培训通知等出差缘由证明材料； 2.出差审批单； 3.预订的商旅订单； 4.发票； 5.考勤记录。 | W28: 各级单位-各部门-出差人员、各级单位-各部门-出差报销审核人、各级单位-财务部门-成本管理人员、商旅云公司 | X28: 每日 | Y28: 全量检查 | AA28: 每年 | AB28: 抽查 | AD28: 员工差旅报销监督场景 | AE28: 每月 | AF28: 抽查 | AH28: 是 | AI28: 是 | AJ28: 《国网财务部、后勤部关于进一步规范差旅伙食费和交通费收交管理有关事项的通知》第三条、第四条 《国家电网有限公司差旅费管理办法》（国家电网企管〔2026〕101号）第十七条、第二十四条 | AK28: 国网财务部 | AL28: 各级单位财务部 | AM28: 否
I29: 员工报账业务-8.差旅报销合规性控制-控制措施04 | J29: 财务部门加强差旅报销审核力度，对同一时段连续出差公杂费、伙食补助费进行复核，避免重复计算。 | M29: √ | Q29: √ | T29: 系统已建 | U29: 国网商旅 | V29: 1.出差通知、培训通知等出差缘由证明材料； 2.出差审批单； 3.预订的商旅订单； 4.发票； 5.考勤记录。 | W29: 各级单位-各部门-出差人员、各级单位-各部门-出差报销审核人、各级单位-财务部门-成本管理人员、商旅云公司 | X29: 每日 | Y29: 全量检查 | AA29: 每年 | AB29: 抽查 | AD29: 员工差旅报销监督场景 | AE29: 每月 | AF29: 抽查 | AH29: 是 | AI29: 是 | AJ29: 《国网财务部、后勤部关于进一步规范差旅伙食费和交通费收交管理有关事项的通知》第三条、第四条 《国家电网有限公司差旅费管理办法》（国家电网企管〔2026〕101号第十二条、第十三条、第十七条、第二十四条 | AK29: 国网财务部 | AL29: 各级单位财务部 | AM29: 是
A30: 员工报账 | B30: 一、员工差旅 | C30: 资金资产安全 | D30: 差旅报销 | E30: 虚报冒领差旅费，虚列套取费用，导致资金安全风险。 | F30: 87.违规发放津贴补贴：存在多报差旅补贴、虚报差旅补贴等问题。 | G30: 8.差旅报销合规性控制 | H30: 交通费、公杂费、住宿费等报销真实发生，差旅费报销准确。 | I30: 员工报账业务-8.差旅报销合规性控制-控制措施05 | J30: 纪检部门完善违规问责与闭环管理机制，对未缴纳伙食费用套取各类补助和虚报行为进行问责，追回资金，并纳入个人诚信记录。 | M30: √ | R30: √ | S30: √ | T30: 线下管控 | V30: 1.问责证明材料。 | W30: 各级单位-各部门-出差人员、各级单位-各部门-出差报销审核人、各级单位-财务部门-成本管理人员、商旅云公司、各级单位-纪检部门-纪检管理人员 | X30: 每日 | Y30: 全量检查 | AA30: 每年 | AB30: 抽查 | AD30: 员工差旅报销监督场景 | AE30: 每月 | AF30: 抽查 | AH30: 是 | AI30: 是 | AJ30: 《国网财务部、后勤部关于进一步规范差旅伙食费和交通费收交管理有关事项的通知》第三条、第四条 《国家电网有限公司差旅费管理办法》（国家电网企管〔2026〕101号）第十七条、第二十四条、《国网湖南省电力有限公司关于印发加强差旅费管理有关规定的通知》第一条 | AK30: 国网财务部 | AL30: 各级单位财务部 | AM30: 是
E31: 员工自付单据中的人员、时间与地点未在出差范围内，虚报支出，套取资金，导致公司经济利益受损。 | G31: 9.自付单据审核 | H31: 自付单据中人员、时间、地点与出差申请单一致，自付交通费、住宿费符合差旅费标准。 | I31: 员工报账业务-9.自付单据审核-控制措施01 | J31: 商旅云公司健全“单轨控制”，系统强制关联“已完成审批单”与“线上支付订单”，并推动与税务平台直连，减少发票人工上传环节。 | S31: √ | T31: 系统待建 | U31: 国网商旅 | V31: 1.发票； 2.差旅费标准； 3.出差通知、培训通知等出差缘由证明材料； 4.出差审批单； 5.出差报销单。 | W31: 各级单位-各部门-出差人员、商旅云公司 | X31: 每日 | Y31: 全量检查 | AA31: 每年 | AB31: 抽查 | AD31: 员工差旅报销监督场景 | AE31: 每月 | AF31: 抽查 | AH31: 是 | AI31: 是 | AJ31: 《国家电网有限公司差旅费管理办法》（国家电网企管〔2026〕101号）第八条、第十一条、第二十四条 | AK31: 国网财务部 | AL31: 各级单位财务部 | AM31: 否
I32: 员工报账业务-9.自付单据审核-控制措施02 | J32: 强化线下报销验证，未实现系统“单轨控制”的单位强化事前审批，强制“行程轨迹佐证”，同时借助第三方工具“建立发票真伪与重复报销”校验机制。 | M32: √ | Q32: √ | R32: √ | T32: 线下管控 | V32: 1.发票； 2.差旅费标准； 3.出差通知、培训通知等出差缘由证明材料； 4.出差审批单； 5.出差报销单。 | W32: 各级单位-各部门-出差人员、各级单位-各部门-负责人、商旅云公司 | X32: 每日 | Y32: 全量检查 | AA32: 每年 | AB32: 抽查 | AD32: 员工差旅报销监督场景 | AE32: 每月 | AF32: 抽查 | AH32: 是 | AI32: 是 | AJ32: 《国家电网有限公司差旅费管理办法》（国家电网企管〔2026〕101号）第八条、第十一条、第二十四条 | AK32: 国网财务部 | AL32: 各级单位财务部 | AM32: 否
I33: 员工报账业务-9.自付单据审核-控制措施03 | J33: 财务部门规范自付单据与标准审核流程，逐一核对自付单据人员、时间、地点，并审核费用标准是否符合公司规定。 | M33: √ | Q33: √ | R33: √ | T33: 系统已建 | U33: 国网商旅 | V33: 1.发票； 2.差旅费标准； 3.出差通知、培训通知等出差缘由证明材料； 4.出差审批单； 5.出差报销单。 | W33: 各级单位-各部门-出差人员、商旅云公司、各级单位-财务部门-成本管理人员 | X33: 每日 | Y33: 全量检查 | AA33: 每年 | AB33: 抽查 | AD33: 员工差旅报销监督场景 | AE33: 每月 | AF33: 抽查 | AH33: 是 | AI33: 是 | AJ33: 《国家电网有限公司差旅费管理办法》（国家电网企管〔2026〕101号）第八条、第十一条、第二十四条 | AK33: 国网财务部 | AL33: 各级单位财务部 | AM33: 是
I34: 员工报账业务-9.自付单据审核-控制措施04 | J34: 纪检部门严肃查处违规行为，追回资金损失，严肃查处并予以通报。 | M34: √ | R34: √ | T34: 线下管控 | V34: 1.商旅平台数据线上预订率、电子票据抓取率。 | W34: 各级单位-各部门-出差人员、商旅云公司、各级单位-纪检部门-纪检管理人员 | X34: 每日 | Y34: 全量检查 | AA34: 每年 | AB34: 抽查 | AD34: 员工差旅报销监督场景 | AE34: 每月 | AF34: 抽查 | AH34: 是 | AI34: 是 | AJ34: 《国家电网有限公司差旅费管理办法》（国家电网企管〔2026〕101号）第八条、第十一条、第二十四条、《国网湖南省电力有限公司关于印发加强差旅费管理有关规定的通知》第一条 | AK34: 国网财务部 | AL34: 各级单位财务部 | AM34: 是
A35: 员工报账 | B35: 一、员工差旅 | C35: 税务合规、资金资产安全 | D35: 报销申请 | E35: 成本费用报销事项不真实、审批流程不规范，导致成本入账科目错误、虚列成本费用、套取资金私设“小金库”。 | G35: 10.报销事项合规性控制 | H35: 在规定列支范围内，以真实发生的事项发起报销申请，履行规范审批流程。 | I35: 员工报账业务-10.报销事项合规性控制-控制措施01 | J35: 费用报销部门履行费用报销分级授权审批流程，对报销申请事项的真实性进行人工复核，复核报销审批单、费用明细清单、发票或收据、合同或协议等附件的完整性。 | L35: √ | R35: √ | T35: 线下管控 | V35: 1.成本费用报销审批单； 2.费用明细清单； 3.发票或收据； 4.合同或协议； 5.系统审批记录。 | W35: 各级单位-各部门-报账人员、各级单位-各部门-负责人、各级单位-财务部门-成本管理人员 | X35: 每季度 | Y35: 抽查 | AA35: 每年 | AB35: 抽查 | AD35: 报销真实性监督场景 | AE35: 每年 | AF35: 抽查 | AH35: 是 | AI35: 是 | AJ35: 《国家电网有限公司会计基础管理办法》（国家电网企管〔2019〕132号）第八条、第五十四条 《关于加强中央企业资金内部控制管理有关事项的通知》（国资发监督〔2021〕19 号）第十三条、《国网湖南省电力有限公司关于印发加强差旅费管理有关规定的通知》第一条 | AK35: 国网财务部、国网企管部、国网后勤部、国网国际部 | AL35: 各级单位财务部、各级单位企管部（人资部）、各级单位后勤部、 | AM35: 是
I36: 员工报账业务-10.报销事项合规性控制-控制措施02 | J36: 加强挂职人员费用报销成本中心校验，挂职期间费用报销申请需选择挂职单位成本中心。 | Q36: √ | T36: 系统已建 | U36: 智慧共享财务平台 | V36: 1.成本费用报销审批单； 2.费用明细清单； 3.发票或收据； 4.合同或协议； 5.系统审批记录。 | W36: 各级单位-各部门-报账人员、各级单位-各部门-负责人、各级单位-财务部门-成本管理人员 | X36: 每季度 | Y36: 抽查 | AA36: 每年 | AB36: 抽查 | AD36: 报销真实性监督场景 | AE36: 每年 | AF36: 抽查 | AH36: 是 | AI36: 是 | AJ36: 《国家电网有限公司会计基础管理办法》（国家电网企管〔2019〕132号）第八条、第五十四条 《关于加强中央企业资金内部控制管理有关事项的通知》（国资发监督〔2021〕19 号）第十三条、《国网湖南省电力有限公司关于印发加强差旅费管理有关规定的通知》第三条 | AK36: 国网财务部、国网企管部、国网后勤部、国网国际部 | AL36: 各级单位财务部、各级单位企管部（人资部）、各级单位后勤部、 | AM36: 是
I37: 员工报账业务-10.报销事项合规性控制-控制措施03 | J37: 财务部门对费用报销选择业务事项准确性进行复核，校验报销流程和成本中心准确性。 | M37: √ | Q37: √ | T37: 系统已建 | U37: 智慧共享财务平台 | V37: 1.成本费用报销审批单； 2.费用明细清单； 3.发票或收据； 4.合同或协议； 5.系统审批记录。 | W37: 各级单位-各部门-报账人员、各级单位-各部门-负责人、各级单位-财务部门-成本管理人员 | X37: 每季度 | Y37: 抽查 | AA37: 每年 | AB37: 抽查 | AD37: 报销真实性监督场景 | AE37: 每年 | AF37: 抽查 | AH37: 是 | AI37: 是 | AJ37: 《国家电网有限公司会计基础管理办法》（国家电网企管〔2019〕132号）第八条、第五十四条 《关于加强中央企业资金内部控制管理有关事项的通知》（国资发监督〔2021〕19 号）第十三条 | AK37: 国网财务部、国网企管部、国网后勤部、国网国际部 | AL37: 各级单位财务部、各级单位企管部（人资部）、各级单位后勤部、 | AM37: 是
I38: 员工报账业务-10.报销事项合规性控制-控制措施04 | J38: 进行违规责任追究，对虚列成本费用、套取资金私设“小金库”的人员根据相关规定进行违规责任追究。 | R38: √ | T38: 线下管控 | V38: 1.责任追究证明材料。 | W38: 各级单位-各部门-报账人员、各级单位-各部门-负责人、各级单位-财务部门-成本管理人员、各级单位-纪检部门-纪检管理人员 | X38: 每季度 | Y38: 抽查 | AA38: 每年 | AB38: 抽查 | AD38: 报销真实性监督场景 | AE38: 每年 | AF38: 抽查 | AH38: 是 | AI38: 是 | AJ38: 《国家电网有限公司会计基础管理办法》（国家电网企管〔2019〕132号）第八条、第五十四条 《关于加强中央企业资金内部控制管理有关事项的通知》（国资发监督〔2021〕19 号）第十三条 | AK38: 国网财务部、国网企管部、国网后勤部、国网国际部 | AL38: 各级单位财务部、各级单位企管部（人资部）、各级单位后勤部、 | AM38: 是
B39: 二、通用报账 | C39: 税务合规 | D39: 费用报销 | E39: 发票信息不准确、不完整，与报销业务不一致导致税务风险 | G39: 11.报销发票审核 | H39: 报销发票真实、准确、完整 | I39: 员工报账业务-11.报销发票审核-控制措施01 | J39: 归口管理部门对报销发票、入库单、采购订单物品对应关系进行复核，确认购物清单通过税务防伪系统开具。 | L39: √ | M39: √ | T39: 系统已建 | U39: 智慧共享财务平台 | V39: 1.成本费用报销申请单； 2.费用明细清单； 3.发票或收据、购物清单； 4.合同或协议。 | W39: 各级单位-各部门-报账人员、各级单位-各部门-负责人、各级单位-财务部门-成本管理人员 | X39: 每季度 | Y39: 抽查 | AA39: 每年 | AB39: 抽查 | AD39: 发票审核管理监督场景 | AE39: 每年 | AF39: 抽查 | AH39: 是 | AI39: 是 | AJ39: 国家电网企管〔2019〕132号《国家电网有限公司会计基础管理办法》第五十条 | AK39: 国网财务部、国网企管部、国网后勤部、国网国际部 | AL39: 各级单位财务部、各级单位企管部（人资部）、各级单位后勤部、 | AM39: 是
I40: 员工报账业务-11.报销发票审核-控制措施02 | J40: 各部门建立发票“谁提交、谁审核、谁负责”闭环管理机制,发票提交人落实发票验真责任。 | M40: √ | R40: √ | T40: 系统已建 | U40: 智慧共享财务平台 | V40: 1.成本费用报销申请单； 2.费用明细清单； 3.发票或收据、购物清单； 4.合同或协议。 | W40: 各级单位-各部门-报账人员、各级单位-各部门-负责人 | X40: 每季度 | Y40: 抽查 | AA40: 每年 | AB40: 抽查 | AD40: 发票审核管理监督场景 | AE40: 每年 | AF40: 抽查 | AH40: 是 | AI40: 是 | AJ40: 国家电网企管〔2019〕132号《国家电网有限公司会计基础管理办法》第五十条 | AK40: 国网企管部、国网后勤部、国网国际部 | AL40: 各级单位财务部、各级单位企管部（人资部）、各级单位后勤部 | AM40: 是
A41: 员工报账 | B41: 二、通用报账 | C41: 税务合规 | D41: 费用报销 | E41: 发票信息不准确、不完整，与报销业务不一致导致税务风险 | G41: 11.报销发票审核 | H41: 报销发票真实、准确、完整 | I41: 员工报账业务-11.报销发票审核-控制措施03 | J41: 发票提交人对增值税发票税率与合同条款进行复核，确认货物及应税劳务名称准确、金额及税率与合同一致，确认发票项目开票明细【开票方信息】名称中不包含“茶叶、烟、酒水、门票、景区”等敏感字眼，确认销售方名称中不包含“会所、健身房、俱乐部、KTV、景区、洗浴中心”等敏感字眼。 | O41: √ | T41: 系统已建 | U41: 智慧共享财务平台 | V41: 1.成本费用报销申请单； 2.费用明细清单； 3.发票或收据、购物清单； 4.合同或协议。 | W41: 各级单位-各部门-报账人员、各级单位-各部门-负责人 | X41: 每季度 | Y41: 抽查 | AA41: 每年 | AB41: 抽查 | AD41: 发票审核管理监督场景 | AE41: 每年 | AF41: 抽查 | AH41: 是 | AI41: 是 | AJ41: 国家电网企管〔2019〕132号《国家电网有限公司会计基础管理办法》第五十条 | AK41: 国网财务部、国网企管部、国网后勤部、国网国际部 | AL41: 各级单位财务部、各级单位企管部（人资部）、各级单位后勤部 | AM41: 是
I42: 员工报账业务-11.报销发票审核-控制措施04 | J42: 财务部门对发票开具的完整性、合规性进行复核，检查发票名目是否包含固定资产目录所列资产，福利费增值税进项税不得抵扣。 | Q42: √ | R42: √ | T42: 线下管控 | V42: 1.成本费用报销申请单； 2.费用明细清单； 3.发票或收据、购物清单； 4.合同或协议。 | W42: 各级单位-各部门-报账人员、各级单位-各部门-负责人、各级单位-财务部门-成本管理人员 | X42: 每季度 | Y42: 抽查 | AA42: 每年 | AB42: 抽查 | AD42: 发票审核管理监督场景 | AE42: 每年 | AF42: 抽查 | AH42: 是 | AI42: 是 | AJ42: 国家电网企管〔2019〕132号《国家电网有限公司会计基础管理办法》第五十条 | AK42: 国网财务部、国网企管部、国网后勤部、国网国际部 | AL42: 各级单位财务部、各级单位企管部（人资部）、各级单位后勤部 | AM42: 是
I43: 员工报账业务-11.报销发票审核-控制措施05 | J43: 财务人员对开具虚假发票套取资金等问题进行复核。 | M43: √ | Q43: √ | T43: 线下管控 | V43: 1.成本费用报销申请单； 2.费用明细清单； 3.发票或收据、购物清单； 4.合同或协议。 | W43: 各级单位-各部门-报账人员、各级单位-各部门-负责人、各级单位-财务部门-成本管理人员 | X43: 每季度 | Y43: 抽查 | AA43: 每年 | AB43: 抽查 | AD43: 发票审核管理监督场景 | AE43: 每年 | AF43: 抽查 | AH43: 是 | AI43: 是 | AJ43: 国家电网企管〔2019〕132号《国家电网有限公司会计基础管理办法》第五十条 | AK43: 国网财务部、国网企管部、国网后勤部、国网国际部 | AL43: 各级单位财务部、各级单位企管部（人资部）、各级单位后勤部 | AM43: 是
D44: 公务接待活动 | E44: 未严格执行公务接待制度，虚列公务接待清单套取公务接待费用，引发资金支出及合规风险。 | G44: 12.公务接待范围、执行制度、费用报销 | H44: 严格执行公务接待制度，确保公务接待费支出规范。 | I44: 员工报账业务-12.公务接待范围、执行制度、费用报销-控制措施01 | J44: 接待部门做好公务接待过程管控。①严格公务接待审批。按照《国家电网有限公司公务接待管理办法》要求，根据公函内容中来访对象、人数等，报相应公司（或部门）领导审批。②规范公务接待组织。承办部门公务接待要严格按照本单位贯彻落实中央八项规定实施细则有关规定执行。严控陪同人数，不得层层多人陪同等。③严格执行清单制度。按照《国家电网有限公司公务接待管理办法》要求，公务活动结束后，接待部门应当如实填写接待清单，包括接待对象的单位、姓名、职务和接待项目、时间、场所、费用等内容，经本部门负责同志审签。④规范做好报销。接待费用应当及时结算，不得用公款报销或者支付应当由个人负担的费用。禁止借公务接待名义列支其他支出等。 | M44: √ | T44: 线下管控 | V44: 1.派出单位公函(或通知)； 2.公务接待清单； 3.财务票据。 | W44: 各级单位-接待承办部门-报账人员、各级单位-接待承办部门-负责人、各级单位-接待管理部门-接待管理人员、各级单位-接待管理部门-负责人 | X44: 每季度 | Y44: 抽查 | AA44: 每年 | AB44: 抽查 | AD44: 公务接待费列支范围监督场景 | AE44: 每年 | AF44: 抽查 | AH44: 是 | AI44: 是 | AJ44: 《国家电网有限公司厉行节约反对浪费实施办法》（国家电网企管〔2025〕421号）第二十四条 《关于做好会议、接待管理相关事项报备报批工作的通知》（办值通〔2025〕55号） 《国家电网有限公司公务接待管理办法》国家电网企管〔2025〕267号 第五至十九 | AK44: 国网办公室 | AL44: 各级单位办公室 | AM44: 是
A45: 员工报账 | B45: 二、通用报账 | C45: 税务合规 | D45: 公务接待活动 | E45: 未严格执行公务接待制度，虚列公务接待清单套取公务接待费用，引发资金支出及合规风险。 | G45: 12.公务接待范围、执行制度、费用报销 | H45: 严格执行公务接待制度，确保公务接待费支出规范。 | I45: 员工报账业务-12.公务接待范围、执行制度、费用报销-控制措施02 | J45: 归口管理部门做好复核。对接待部门提交的接待清单中人员、住宿安排、用车安排、费用等进行复核。 | L45: √ | T45: 线下管控 | V45: 1.派出单位公函(或通知)； 2.公务接待清单； 3.财务票据。 | W45: 各级单位-接待承办部门-报账人员、各级单位-接待承办部门-负责人、各级单位-接待管理部门-接待管理人员、各级单位-接待管理部门-负责人 | X45: 每季度 | Y45: 抽查 | AA45: 每年 | AB45: 抽查 | AD45: 公务接待费列支范围监督场景 | AE45: 每年 | AF45: 抽查 | AH45: 是 | AI45: 是 | AJ45: 《国家电网有限公司厉行节约反对浪费实施办法》（国家电网企管〔2025〕421号）第二十四条 《关于做好会议、接待管理相关事项报备报批工作的通知》（办值通〔2025〕55号） 《国家电网有限公司公务接待管理办法》国家电网企管〔2025〕267号 第五至十九条 | AK45: 国网办公室 | AL45: 各级单位办公室 | AM45: 是
I46: 员工报账业务-12.公务接待范围、执行制度、费用报销-控制措施03 | J46: 财务部门做好报销审核。按照财务业务流程要求，做好报销审核、检查材料完备。 | Q46: √ | R46: √ | T46: 线下管控 | V46: 1.派出单位公函(或通知)； 2.公务接待清单； 3.财务票据。 | W46: 各级单位-接待承办部门-报账人员、各级单位-接待承办部门-负责人、各级单位-接待管理部门-接待管理人员、各级单位-接待管理部门-负责人、各级单位-财务部门-成本管理人员 | X46: 每季度 | Y46: 抽查 | AA46: 每年 | AB46: 抽查 | AD46: 公务接待费列支范围监督场景 | AE46: 每年 | AF46: 抽查 | AH46: 是 | AI46: 是 | AJ46: 《国家电网有限公司厉行节约反对浪费实施办法》（国家电网企管〔2025〕421号）第二十四条 《关于做好会议、接待管理相关事项报备报批工作的通知》（办值通〔2025〕55号） 《国家电网有限公司公务接待管理办法》国家电网企管〔2025〕267号 第五至十九条 | AK46: 国网办公室 | AL46: 各级单位办公室 | AM46: 是
C47: 资金资产安全 | D47: 公务车辆单车核算 | E47: 员工未严格执行公务车辆单车核算要求，通过伪造票据、虚报里程、费用金额、虚构用车场景等方式套取企业资金，导致企业成本虚增、资金流失风险。 | F47: 82.公务用车管控不严：存在新购置及长租公务用车未及时接入统一车辆管理平台过程监督管理；在公务用车维修等费用中虚列名目、处理其他无关费用或费用依据不足；超编超标超范围配置公务用车等问题。 | G47: 13.公务车辆单车核算管理 | H47: 严格执行公务车辆单车核算管理要求，据实报销车辆使用费。 | I47: 员工报账业务-13.公务车辆单车核算管理-控制措施01 | J47: 通过统一车辆平台进行系统控制，自动比对用车时间、目的地与车辆通行费发票时间、行程轨迹的匹配性，规避虚列费用。 | M47: √ | T47: 系统待建 | U47: 统一车辆平台 | V47: 1.公务车辆管理台账； 2.车辆单车核算台账； 3.ETC通行费明细清单； 4.费用明细清单； 5.发票或收据； 6.合同或协议。 | W47: 各级单位-公务车辆管理部门-车辆管理人员、各级单位-公务车辆管理部门-负责人 | X47: 每季度 | Y47: 抽查 | AA47: 每年 | AB47: 抽查 | AD47: 车辆使用费监督场景 | AE47: 每年 | AF47: 抽查 | AH47: 是 | AI47: 是 | AJ47: 《国家电网有限公司公务用车管理办法》（规章制度编号:国网(后勤/2)724-2025）第十一至十九条、第二十一条、第三十二条. | AK47: 国网后勤部 | AL47: 各级单位后勤部 | AM47: 是
I48: 员工报账业务-13.公务车辆单车核算管理-控制措施02 | J48: 系统直联控制，通过智慧共享财务平台直联统一车辆平台对单车核算台账明细进行系统控制，严禁列支保养、维修、年检、燃油等范围外费用，增加“车辆费用类型白名单”控制，超出范围的费用类型系统自动拒绝，并推送异常报告。 | N48: √ | O48: √ | T48: 系统待建 | U48: 智慧共享财务平台 | V48: 1.公务车辆管理台账； 2.车辆单车核算台账； 3.ETC通行费明细清单； 4.费用明细清单； 5.发票或收据； 6.合同或协议。 | W48: 各级单位-公务车辆管理部门-车辆管理人员、各级单位-公务车辆管理部门-负责人 | X48: 每季度 | Y48: 抽查 | AA48: 每年 | AB48: 抽查 | AD48: 车辆使用费监督场景 | AE48: 每年 | AF48: 抽查 | AH48: 是 | AI48: 是 | AJ48: 《国家电网有限公司公务用车管理办法》（规章制度编号:国网(后勤/2)724-2025）第十一至十九条、第二十一条、第三十二条. | AK48: 国网后勤部 | AL48: 各级单位后勤部 | AM48: 是
A49: 员工报账 | B49: 二、通用报账 | C49: 资金资产安全 | D49: 公务车辆单车核算 | E49: 员工未严格执行公务车辆单车核算要求，通过伪造票据、虚报里程、费用金额、虚构用车场景等方式套取企业资金，导致企业成本虚增、资金流失风险。 | F49: 82.公务用车管控不严：存在新购置及长租公务用车未及时接入统一车辆管理平台过程监督管理；在公务用车维修等费用中虚列名目、处理其他无关费用或费用依据不足；超编超标超范围配置公务用车等问题。 | I49: 员工报账业务-13.公务车辆单车核算管理-控制措施03 | J49: 未实现系统直联控制的单位应加强线下审核，车辆管理部门对单车费用明细（油费、过路费、停车费、维修费等）与用车申请单（事前提交，注明用车时间、事由、目的地）、车辆行驶里程记录（行车记录、起止日期）进行复核，严禁套取费用。 | M49: √ | R49: √ | T49: 线下管控 | V49: 1.公务车辆管理台账； 2.车辆单车核算台账； 3.ETC通行费明细清单； 4.费用明细清单； 5.发票或收据； 6.合同或协议。 | W49: 各级单位-公务车辆管理部门-车辆管理人员、各级单位-公务车辆管理部门-负责人、各级单位-财务部门-成本管理人员 | X49: 每季度 | Y49: 抽查 | AA49: 每年 | AB49: 抽查 | AD49: 车辆使用费监督场景 | AE49: 每年 | AF49: 抽查 | AH49: 是 | AI49: 是 | AJ49: 《国家电网有限公司公务用车管理办法》（规章制度编号:国网(后勤/2)724-2025）第十一至十九条、第二十一条、第三十二条. | AK49: 国网后勤部 | AL49: 各级单位后勤部 | AM49: 是
C50: 税务合规 | D50: 因公出国（境）管理 | E50: 超标准列支因公出国（境）经费，引发合规风险。 | G50: 14.因公出国（境）经费使用 | H50: 因公出国（境）经费标准使用符合规定，在规定范围内报销。 | I50: 员工报账业务-14.因公出国（境）经费使用-控制措施01 | J50: 归口管理部门对经批准的计划申请表进行复核，确认外事服务机构的收费标准不高于同业收费平均水平，落实预算控制要求。 | N50: √ | R50: √ | T50: 线下管控 | V50: 1.计划申请表及年度预算； 2.住宿费和伙食费发票； 3.费用报销审批单； 4.因公出国（境）费用计划申请； 5.因公出国（境）费用结算表。 | W50: 各级单位-各部门-报账人员、各级单位-各部门-负责人、各级单位-因公出国（境）经费归口管理部门-负责人、各级单位-财务部门-成本管理人员 | X50: 每季度 | Y50: 抽查 | AA50: 每年 | AB50: 抽查 | AD50: 因公出国（境）经费监督场景 | AE50: 每年 | AF50: 抽查 | AH50: 是 | AI50: 是 | AJ50: 《国家电网有限公司因公出国（境）经费管理办法》（国家电网企管〔2019〕715号）第八至十四条 | AK50: 国网国际部 | AM50: 是
I51: 员工报账业务-14.因公出国（境）经费使用-控制措施02 | J51: 归口管理部门对因公出国（境）经费列支范围进行复核，确认赠送礼品、安排宴请等均按照国务院、财政部、外交部有关规定执行。 | L51: √ | M51: √ | O51: √ | T51: 线下管控 | V51: 1.计划申请表及年度预算； 2.住宿费和伙食费发票； 3.费用报销审批单； 4.因公出国（境）费用计划申请； 5.因公出国（境）费用结算表。 | W51: 各级单位-各部门-报账人员、各级单位-各部门-负责人、各级单位-因公出国（境）经费归口管理部门-负责人 | X51: 每季度 | Y51: 抽查 | AA51: 每年 | AB51: 抽查 | AD51: 因公出国（境）经费监督场景 | AE51: 每年 | AF51: 抽查 | AH51: 是 | AI51: 是 | AJ51: 《国家电网有限公司因公出国（境）经费管理办法》（国家电网企管〔2019〕715号）第八至十四条 | AK51: 国网国际部 | AM51: 是
I52: 员工报账业务-14.因公出国（境）经费使用-控制措施03 | J52: 财务部门加强审核，按照科学预算、厉行节约的原则对因公出国（境）经费列支住宿费、伙食费、公杂费使用标准进行复核。 | Q52: √ | R52: √ | T52: 线下管控 | V52: 1.计划申请表及年度预算； 2.住宿费和伙食费发票； 3.费用报销审批单； 4.因公出国（境）费用计划申请； 5.因公出国（境）费用结算表。 | W52: 各级单位-各部门-报账人员、各级单位-各部门-负责人、各级单位-因公出国（境）经费归口管理部门-负责人、各级单位-财务部门-成本管理人员 | X52: 每季度 | Y52: 抽查 | AA52: 每年 | AB52: 抽查 | AD52: 因公出国（境）经费监督场景 | AE52: 每年 | AF52: 抽查 | AH52: 是 | AI52: 是 | AJ52: 《国家电网有限公司因公出国（境）经费管理办法》（国家电网企管〔2019〕715号）第八至十四条 | AK52: 国网国际部 | AM52: 是
A53: 员工报账 | B53: 二、通用报账 | C53: 资金资产安全 | D53: 会议费用报销（三公经费） | E53: 超期、超规模、超标准组织会议，计划外会议未规范履行报批程序，会议开支金额超会议费用预算，引发资金安全及合规管理风险。 | G53: 15.会议规模、费用报销 | H53: 合理确定会议规格，严格控制会议费预算规模。 | I53: 员工报账业务-15.会议规模、费用报销-控制措施01 | J53: 主办部门做好会议过程管控。① 做好会议筹备。按照会议类别，确定会议规模、会期、人数、会场、预算等。② 严格会议审批。按照《国家电网有限公司会议管理办法》要求，由主办部门履行内部审批流程，填写计划内会议费用申请表，提出申请，经本部门主要负责人签字。③ 规范会议组织。不得到豪华酒店、度假村和党中央、国务院明令禁止的风景名胜区召开会议，精简会务安排、严肃会议纪律。④ 规范会议报销。按照《国家电网有限公司会议管理办法》要求，会议费用报销应严格执行公司报销管理规定，由主办部门提出申请，经本部门主要负责人签字。严禁借会议名义列支或报销与会议无关的费用等。 | L53: √ | M53: √ | T53: 线下管控 | V53: 1.年度会议计划表； 2.计划内会议费用申请表； 3.会议通知、会议议程、参会名单； 4.发票或电子结算单； 5.计划外会议审批表。 | W53: 各级单位-会议承办部门-报账人员、各级单位-会议承办部门-负责人、各级单位-会议管理部门-会议管理人员、各级单位-会议管理部门-负责人 | X53: 每季度 | Y53: 抽查 | AA53: 每年 | AB53: 抽查 | AD53: 会议费监督场景 | AE53: 每年 | AF53: 抽查 | AH53: 是 | AI53: 是 | AJ53: 《国家电网有限公司会议管理办法》（国家电网企管〔2025〕267号）第七至十二条、第二十一至二十二条、第二十七至三十二条、第三十四至三十九条等。 《关于做好会议、接待管理相关事项报备报批工作的通知》（办值通〔2025〕55号） | AK53: 国网办公室 | AL53: 各级单位办公室 | AM53: 是
I54: 员工报账业务-15.会议规模、费用报销-控制措施02 | J54: 归口管理部门做好复核。对主办部门提交的计划内会议费用申请表、计划外会议审批表中会议计划、时间、地点、规模、预算、标准审批等进行复核。 | N54: √ | O54: √ | T54: 线下管控 | V54: 1.年度会议计划表； 2.计划内会议费用申请表； 3.会议通知、会议议程、参会名单； 4.发票或电子结算单； 5.计划外会议审批表。 | W54: 各级单位-会议承办部门-报账人员、各级单位-会议承办部门-负责人、各级单位-会议管理部门-会议管理人员、各级单位-会议管理部门-负责人 | X54: 每季度 | Y54: 抽查 | AA54: 每年 | AB54: 抽查 | AD54: 会议费监督场景 | AE54: 每年 | AF54: 抽查 | AH54: 是 | AI54: 是 | AJ54: 《国家电网有限公司会议管理办法》（国家电网企管〔2025〕267号）第七至十二条、第二十一至二十二条、第二十七至三十二条、第三十四至三十九条等。 《关于做好会议、接待管理相关事项报备报批工作的通知》（办值通〔2025〕55号） | AK54: 国网办公室 | AL54: 各级单位办公室 | AM54: 是
I55: 员工报账业务-15.会议规模、费用报销-控制措施03 | J55: 财务部门做好报销审核。按照财务业务流程要求，做好报销审核、检查材料完备。 | Q55: √ | R55: √ | T55: 线下管控 | V55: 1.年度会议计划表； 2.计划内会议费用申请表； 3.会议通知、会议议程、参会名单； 4.发票或电子结算单； 5.计划外会议审批表。 | W55: 各级单位-会议承办部门-报账人员、各级单位-会议承办部门-负责人、各级单位-会议管理部门-会议管理人员、各级单位-会议管理部门-负责人、各级单位-财务部门-成本管理人员 | X55: 每季度 | Y55: 抽查 | AA55: 每年 | AB55: 抽查 | AD55: 会议费监督场景 | AE55: 每年 | AF55: 抽查 | AH55: 是 | AI55: 是 | AJ55: 《国家电网有限公司会议管理办法》（国家电网企管〔2025〕267号）第七至十二条、第二十一至二十二条、第二十七至三十二条、第三十四至三十九条等。 《关于做好会议、接待管理相关事项报备报批工作的通知》（办值通〔2025〕55号） | AK55: 国网办公室 | AL55: 各级单位办公室 | AM55: 是
A56: 员工报账 | B56: 二、通用报账 | C56: 资金资产安全 | D56: 办公费管理 | E56: 虚列、套取办公费，引发合规风险。 | G56: 16.办公费使用 | H56: 办公费在规定范围内据实报销。办公费报销中的结算依据充分，完整，有效，结算依据审核轨迹完整。 | I56: 员工报账业务-16.办公费使用-控制措施01 | J56: 归口管理部门对办公费用使用范围进行复核，确保不包含党报党刊费、营销业务电费发票印制费、护肤膏、防晒霜、牙膏、工作服、多功能一体机、打印机、投影仪、礼品、食堂餐座椅等费用，禁止虚列、套取办公费行为。 | L56: √ | M56: √ | O56: √ | T56: 线下管控 | V56: 1.成本费用报销审批单； 2.发票； 3.入库单或到货验收单； 4.购置审批表； 5.采购合同； 6.办公用品领用清单； 7.费用结算清单。 | W56: 各级单位-各部门-报账人员、各级单位-各部门-负责人、各级单位-办公用品管理部门-办公用品管理人员、各级单位-办公用品管理部门-负责人 | X56: 每季度 | Y56: 抽查 | AA56: 每年 | AB56: 抽查 | AD56: 办公费监督场景 | AE56: 每年 | AF56: 抽查 | AH56: 是 | AI56: 是 | AJ56: 《国家电网有限公司会计基础管理办法》（国家电网企管〔2019〕132号）第五十四条 | AK56: 国网后勤部 | AL56: 各级单位办公室 | AM56: 是
I57: 员工报账业务-16.办公费使用-控制措施02 | J57: 财务人员加强规范性审核，对照审批轨迹、费用结算清单、办公用品领用清单复核业务规范性。 | Q57: √ | R57: √ | T57: 线下管控 | V57: 1.成本费用报销审批单； 2.发票； 3.入库单或到货验收单； 4.购置审批表； 5.采购合同； 6.办公用品领用清单； 7.费用结算清单。 | W57: 各级单位-各部门-报账人员、各级单位-各部门-负责人、各级单位-办公用品管理部门-办公用品管理人员、各级单位-办公用品管理部门-负责人、各级单位-财务部门-成本管理人员 | X57: 每季度 | Y57: 抽查 | AA57: 每年 | AB57: 抽查 | AD57: 办公费监督场景 | AE57: 每年 | AF57: 抽查 | AH57: 是 | AI57: 是 | AJ57: 《国家电网有限公司会计基础管理办法》（国家电网企管〔2019〕132号）第五十四条 | AK57: 国网后勤部 | AL57: 各级单位办公室 | AM57: 是
C58: 税务合规 | D58: 办公用品选购 | E58: 办公用品到货商品与采购清单不一致，“私下换货”，引发合规风险。 | G58: 17.办公用品采购、发放 | H58: 办公用品采购、发放规范有序。 | I58: 员工报账业务-17.办公用品采购、发放-控制措施01 | J58: 物资部门对国网商城上架商品与物流信息一致性进行校验，规避换货舞弊行为。 | O58: √ | T58: 线下管控 | V58: 1.办公用品采购申请单； 2.发票； 3.入库单或货物交接单； 4.购置审批表。 | W58: 各级单位-办公用品管理部门-办公用品管理人员、各级单位-办公用品管理部门-负责人、各级单位-物资部门-电商采购执行与监督人员、各级单位-物资部门-负责人 | X58: 每季度 | Y58: 抽查 | AA58: 每年 | AB58: 抽查 | AD58: 办公费列支范围监督场景 | AE58: 每年 | AF58: 抽查 | AH58: 是 | AI58: 是 | AJ58: 《国家电网有限公司零星物资及办公用品选购专区管理细则》（国家电网企管〔2024〕301 号）第二十八条、第二十九条 | AK58: 国网后勤部、国网物资部 | AL58: 各级单位后勤部（办公室）、各级单位物资部 | AM58: 是
I59: 员工报账业务-17.办公用品采购、发放-控制措施02 | J59: 归口管理部门建立需求、审批、选购等关键角色不相容控制，实现权力分散与监督。 | L59: √ | T59: 线下管控 | V59: 1.办公用品采购申请单； 2.发票； 3.入库单或货物交接单； 4.购置审批表。 | W59: 各级单位-办公用品管理部门-办公用品管理人员、各级单位-办公用品管理部门-负责人、各级单位-物资部门-电商采购执行与监督人员、各级单位-物资部门-负责人 | X59: 每季度 | Y59: 抽查 | AA59: 每年 | AB59: 抽查 | AD59: 办公费列支范围监督场景 | AE59: 每年 | AF59: 抽查 | AH59: 是 | AI59: 是 | AJ59: 《国家电网有限公司零星物资及办公用品选购专区管理细则》（国家电网企管〔2024〕301 号）第二十八条、第二十九条 | AK59: 国网后勤部、国网物资部 | AL59: 各级单位后勤部（办公室）、各级单位物资部 | AM59: 是
I60: 员工报账业务-17.办公用品采购、发放-控制措施03 | J60: 物资部门建立办公用品由物资部门和办公用品保管人员共同验收工作机制，双方均在货物交接单据上签字确认。 | O60: √ | R60: √ | T60: 线下管控 | V60: 1.办公用品采购申请单； 2.发票； 3.入库单或货物交接单； 4.购置审批表。 | W60: 各级单位-办公用品管理部门-办公用品管理人员、各级单位-办公用品管理部门-负责人、各级单位-物资部门-电商采购执行与监督人员、各级单位-物资部门-负责人 | X60: 每季度 | Y60: 抽查 | AA60: 每年 | AB60: 抽查 | AD60: 办公费列支范围监督场景 | AE60: 每年 | AF60: 抽查 | AH60: 是 | AI60: 是 | AJ60: 《国家电网有限公司零星物资及办公用品选购专区管理细则》（国家电网企管〔2024〕301 号）第二十八条、第二十九条 | AK60: 国网后勤部、国网物资部 | AL60: 各级单位后勤部（办公室）、各级单位物资部 | AM60: 是
A61: 员工报账 | B61: 二、通用报账 | C61: 税务合规 | D61: 办公用品选购 | E61: 办公用品到货商品与采购清单不一致，“私下换货”，引发合规风险。 | G61: 17.办公用品采购、发放 | H61: 办公用品采购、发放规范有序。 | I61: 员工报账业务-17.办公用品采购、发放-控制措施04 | J61: 办公用品管理部门确保办公用品发放规范有序。 | R61: √ | T61: 线下管控 | V61: 1.办公用品领用清单。 | W61: 各级单位-办公用品管理部门-办公用品管理人员、各级单位-办公用品管理部门-负责人 | X61: 每季度 | Y61: 抽查 | AA61: 每年 | AB61: 抽查 | AD61: 办公费列支范围监督场景 | AE61: 每年 | AF61: 抽查 | AH61: 是 | AI61: 是 | AJ61: 《国家电网有限公司零星物资及办公用品选购专区管理细则》（国家电网企管〔2024〕301 号）第二十八条、第二十九条 | AK61: 国网后勤部 | AL61: 各级单位后勤部（办公室） | AM61: 是
C62: 税务合规 | D62: 党组织工作经费使用 | E62: 超范围、超标准列支党组织工作经费，导致成本不实，引发合规风险。 | G62: 18.党组织工作经费报销 | H62: 党组织工作经费在规定范围内报销。 | I62: 员工报账业务-18.党组织工作经费报销-控制措施01 | J62: 归口管理部门对党组织工作经费清单进行复核，确保费用用于党内开支教育、宣传思想、主题实践活动及党内评选表彰等与党（团）的建设直接相关的工作和活动。 | L62: √ | T62: 线下管控 | V62: 1.成本费用报销审批单； 2.费用明细清单； 3.发票或收据。 | W62: 各级单位-各部门-报账人员、各级单位-各部门-负责人、各级单位-党建部门-组织建设与党员管理专责、各级单位-党建部门-负责人 | X62: 每季度 | Y62: 抽查 | AA62: 每年 | AB62: 抽查 | AD62: 党组织工作经列支范围监督场景 | AE62: 每年 | AF62: 抽查 | AH62: 是 | AI62: 是 | AJ62: 《国家电网有限公司党组织工作经费管理办法（试行）》（国家电网党〔2018〕96号）第八条、第九条、第十三条、第十四条 | AK62: 党组党建部 | AL62: 各级单位党建部 | AM62: 是
I63: 员工报账业务-18.党组织工作经费报销-控制措施02 | J63: 财务部门对报销费用超范围开支情况进行校验，严禁列支豪华酒店、度假村等场所费用。 | Q63: √ | R63: √ | T63: 线下管控 | V63: 1.成本费用报销审批单； 2.费用明细清单； 3.发票或收据。 | W63: 各级单位-各部门-报账人员、各级单位-各部门-负责人、各级单位-党建部门-负责人、各级单位-财务部门-成本管理人员 | X63: 每季度 | Y63: 抽查 | AA63: 每年 | AB63: 抽查 | AD63: 党组织工作经列支范围监督场景 | AE63: 每年 | AF63: 抽查 | AH63: 是 | AI63: 是 | AJ63: 《国家电网有限公司党组织工作经费管理办法（试行）》（国家电网党〔2018〕96号）第八条、第九条、第十三条、第十四条 | AK63: 党组党建部 | AL63: 各级单位党建部 | AM63: 是
C64: 税务合规、资金资产安全 | D64: 安全费使用 | E64: 超范围列支安全费，虚列挤占安全专项费用，导致合规风险。 | G64: 19.安全费报销 | H64: 安全费在规定范围内报销。 | I64: 员工报账业务-19.安全费报销-控制措施01 | J64: 实物管理部门规范建立资产卡片，针对使用安全费用形成固定资产、无形资产的规范建立资产卡片，确保相关资产折旧准确计入安全费。 | M64: √ | T64: 系统已建 | U64: ERP | V64: 1.成本费用报销审批单； 2.费用明细清单； 3.发票或收据； 4.建设合同。 | W64: 各级单位-各部门-报账人员、各级单位-各部门-负责人、各级单位-安监部门-消防与安保管理人员、各级单位-安监部门-负责人 | X64: 每季度 | Y64: 抽查 | AA64: 每年 | AB64: 抽查 | AD64: 安全费列支范围监督场景 | AE64: 每年 | AF64: 抽查 | AH64: 是 | AI64: 是 | AJ64: 《国家电网有限公司安全生产费用提取和使用管理办法》（国家电网企管〔2023〕399号）第十条、第十三条、第二十五条 | AK64: 国网安监部 | AL64: 各级单位安监部 | AM64: 是
I65: 员工报账业务-19.安全费报销-控制措施02 | J65: 建设单位及时支付安全费用，应当在合同中单独约定并于工程开工日一个月内向承包单位至少支付 50%安全费用。 | O65: √ | P65: √ | T65: 线下管控 | V65: 1.成本费用报销审批单； 2.费用明细清单； 3.发票或收据； 4.建设合同。 | W65: 各级单位-各部门-报账人员、各级单位-各部门-负责人、各级单位-安监部门-消防与安保管理人员、各级单位-安监部门-负责人、各级单位-建设部门-项目经理 | X65: 每季度 | Y65: 抽查 | AA65: 每年 | AB65: 抽查 | AD65: 安全费列支范围监督场景 | AE65: 每年 | AF65: 抽查 | AH65: 是 | AI65: 是 | AJ65: 《国家电网有限公司安全生产费用提取和使用管理办法》（国家电网企管〔2023〕399号）第十条、第十三条、第二十条、第二十五条 | AK65: 国网安监部 | AL65: 各级单位安监部 | AM65: 是
I66: 员工报账业务-19.安全费报销-控制措施03 | J66: 总包单位及时支付安全费用，总包单位应当在合同中单独约定并于分包工程开工日一个月内将至少50%安全费用直接支付分包单位并监督使用，分包单位不再重复提取。 | O66: √ | P66: √ | T66: 线下管控 | V66: 1.成本费用报销审批单； 2.费用明细清单； 3.发票或收据； 4.建设合同。 | W66: 各级单位-各部门-报账人员、各级单位-各部门-负责人、各级单位-安监部门-消防与安保管理人员、各级单位-安监部门-负责人、各总包单位-项目经理 | X66: 每季度 | Y66: 抽查 | AA66: 每年 | AB66: 抽查 | AD66: 安全费列支范围监督场景 | AE66: 每年 | AF66: 抽查 | AH66: 是 | AI66: 是 | AJ66: 《国家电网有限公司安全生产费用提取和使用管理办法》（国家电网企管〔2023〕399号）第十条、第十三条、第二十条、第二十五条 | AK66: 国网安监部 | AL66: 各级单位安监部 | AM66: 是
A67: 员工报账 | B67: 二、通用报账 | C67: 税务合规、资金资产安全 | D67: 安全费使用 | E67: 超范围列支安全费，虚列挤占安全专项费用，导致合规风险。 | G67: 19.安全费报销 | H67: 安全费在规定范围内报销。 | I67: 员工报账业务-19.安全费报销-控制措施04 | J67: 归口管理部门对安全工器具领用、保管进行监督，确保不发生安全工器具过期等问题。 | R67: √ | T67: 线下管控 系统已建 | U67: 安全风险管控监督平台 | V67: 1.成本费用报销审批单； 2.费用明细清单； 3.发票或收据； 4.建设合同。 | W67: 各级单位-各部门-报账人员、各级单位-各部门-负责人、各级单位-安监部门-消防与安保管理人员、各级单位-安监部门-负责人 | X67: 每季度 | Y67: 抽查 | AA67: 每年 | AB67: 抽查 | AD67: 安全费列支范围监督场景 | AE67: 每年 | AF67: 抽查 | AH67: 是 | AI67: 是 | AJ67: 《国家电网有限公司安全生产费用提取和使用管理办法》（国家电网企管〔2023〕399号）第十条、第十三条、第二十五条 | AK67: 国网安监部 | AL67: 各级单位安监部 | AM67: 是
I68: 员工报账业务-19.安全费报销-控制措施05 | J68: 财务部门对安全费列支情况进行复核，禁止列支职工薪酬福利、治安服务费等无关费用。 | M68: √ | P68: √ | Q68: √ | T68: 线下管控 | V68: 1.成本费用报销审批单； 2.费用明细清单； 3.发票或收据； 4.建设合同。 | W68: 各级单位-各部门-报账人员、各级单位-各部门-负责人、各级单位-安监部门-消防与安保管理人员、各级单位-安监部门-负责人、各级单位-财务部门-成本管理人员 | X68: 每季度 | Y68: 抽查 | AA68: 每年 | AB68: 抽查 | AD68: 安全费列支范围监督场景 | AE68: 每年 | AF68: 抽查 | AH68: 是 | AI68: 是 | AJ68: 《国家电网有限公司安全生产费用提取和使用管理办法》（国家电网企管〔2023〕399号）第十条、第十三条、第二十五条 | AK68: 国网安监部 | AL68: 各级单位安监部 | AM68: 是
A69: 员工报账 | B69: 二、通用报账 | C69: 税务合规、资金资产安全 | D69: 青苗赔偿现场核定 | E69: 与现场标准、数量不一致导致青苗赔偿有误，造成青苗赔偿费重复计、多付。 | G69: 21.现场青苗赔偿类型、数量的确定 | H69: 青苗赔付类型、数量与现场一致。 | I69: 员工报账业务-21.现场青苗赔偿类型、数量的确定-控制措施01 | J69: 归口管理部门对赔偿真实性进行复核，确保进行了三方（赔偿方、受偿方、监理或基层组织）现场联合勘测清点并签字确认。 | L69: √ | O69: √ | R69: √ | T69: 线下管控 | V69: 1.用地批复文件； 2.地方补偿标准文件； 3.联合现场勘测记录； 4.地上附着物和青苗调查登记表、补偿结果确认表； 5.被补偿人身份证明； 6.青苗及地上附着物权属证明； 7.青苗补偿协议。 | W69: 各级单位-各部门-项目管理或报账人员、各级单位-各部门-负责人、各级单位-归口管理部门-负责人 | X69: 每季度 | Y69: 抽查 | AA69: 每年 | AB69: 抽查 | AD69: 青苗赔偿费监督场景 | AE69: 每年 | AF69: 抽查 | AH69: 是 | AI69: 是 | AJ69: 《国家电网有限公司会计基础管理办法》（国家电网企管〔2019〕132号）附件：电网企业经济业务审核手册 | AK69: 国网财务部 | AL69: 各级单位财务部 | AM69: 是
