Workbook

Sheet 隔页
A1: 二、财务管理

Sheet 财务矩阵
A1: 财务管理风控矩阵
A2: 业 务 条 线 | B2: 业 务 领 域 | C2: 控 制 目 标 | D2: 业务流程步骤 | E2: 经营风险 | F2: 典型问题 | G2: 关键控制点 | H2: 控制要求 | I2: 控制措施 编号 | J2: 控制措施 | K2: 控制措施分类 | T2: 控制方式 | U2: 控制系统 | V2: 控制载体 | W2: 责任主体 | X2: 业务自评价 | AA2: 集团监督评价 | AD2: 数字化监督场景 | AH2: 现有制度及文件落实情况 | AK2: 总部审核部门
K3: 不相容岗位 | L3: 分级授权 | M3: 业务真实性控制 | N3: 预算管控 | O3: 合同控制 | P3: 收付控制 | Q3: 会计监督 | R3: 财产保护 | S3: 分析与评价 | X3: 评价频率 | Y3: 评价范围 | Z3: 评价结论 | AA3: 评价频率 | AB3: 评价范围 | AC3: 评价结论 | AD3: 数字化监督场景 | AE3: 监督频率 | AF3: 监督范围 | AG3: 评价结论 | AH3: 是否已要求 | AI3: 是否满足要求 | AJ3: 对应制度及文件名称
A4: 财务管理 | B4: 一、核算范围 | C4: 会计信息真实完整 | D4: 会计主体管理 | E4: 会计主体创建不规范、不及时，影响合并范围完整性、准确性，导致会计信息不准确。 | F4: 会计主体创建不合规：对工商登记持股超过50%的实际经营企业，未创建会计主体单独核算，导致合并范围不完整、合并报表信息不准确。 | G4: 1.会计主体完整性管控 | H4: 会计主体与工商、产权登记衔接一致，合并范围完整。 | I4: 财务管理-1.会计主体完整性管控-控制措施01 | J4: 合并范围完整性控制。每月，各级单位会计人员在线跟踪比对工商、产权登记与报表合并范围一致性，以控制为基础，原则上工商登记持股50%以上企业均需办理产权登记、规范取得控制权并纳入合并范围。确有问题的，应及时规范调整。 | M4: √ | Q4: √ | T4: 线上管控-待建 | U4: 智慧共享财务平台、主数据管理平台（MDM3.0) | V4: 1.会计核算主体建立（变更）申请单 2.营业执照、产权登记资料等 | W4: 各级单位-财务资产部-总账报表管理、各级单位-财务资产部-资产及产权管理 | X4: 每月 | Y4: 全查 | AA4: 每年 | AB4: 全查 | AD4: 合并范围完整性监督场景 | AE4: 每月 | AF4: 全查 | AH4: 是 | AI4: 是 | AJ4: 《国家电网有限公司会计基础管理办法》（国家电网企管〔2019〕132号）第四章 核算与报告第三十七条、第四十四条 《国家电网有限公司关于做好2025年度财务决算工作的通知》（国家电网财〔2025〕649号） | AK4: 国网财务部
I5: 财务管理-1.会计主体完整性管控-控制措施02 | J5: 会计主体创建和变更控制。各级单位财务人员应遵循先产权后工商的要求，根据产权和工商登记结果，及时创建会计主体，并履行二级单位、国网财务部审批程序，规范纳入合并范围。对于无人资组织、未办理工商登记的会计主体，由二级单位分管财务领导审批后，提交国网财务部审批。 | L5: √ | M5: √ | T5: 线上管控-已建 | U5: 智慧共享财务平台、主数据管理平台（MDM3.0) | V5: 1.会计核算主体建立（变更）申请单 2.工商登记、税务登记、产权登记资料等 | W5: 各级单位-财务资产部-总账报表管理、各级单位-财务资产部-资产及产权管理 | X5: 每月 | Y5: 全查 | AA5: 每年 | AB5: 全查 | AD5: 会计主体创建变更规范性监督场景 | AE5: 每月 | AF5: 全查 | AH5: 是 | AI5: 是 | AJ5: 《国家电网有限公司会计基础管理办法》（国家电网企管〔2019〕132号）第四章 核算与报告第三十七条、第四十四条 《关于智慧共享财务平台与人资0系统管理融合有关事项的通知》（财会〔2025〕15号） | AK5: 国网财务部
E6: 科目维度使用不统一、不规范，影响会计信息准确性和可比性。 | F6: 科目维度使用不规范：凭证科目维度与实际业务不匹配，影响会计信息反映准确性；集团内不同单位对同类业务核算科目维度不统一，导致会计信息不可比。 | G6: 2.业务完整性管控 | H6: 统一会计科目和管理维度体系，规范科目维度使用，确保会计信息准确可比。 | I6: 财务管理-2.业务完整性管控-控制措施01 | J6: 会计科目和管理维度统一性规范性控制。国网公司建立统一的会计科目和管理维度体系，并实施分业态管理，各级单位根据业态标识规范引用。在公司统一体系下，各级单位因自身业务特点和内部管理要求，确需对相关管理维度枚举值进行细化的，需依次履行二级单位、国网财务部审批程序。 | L6: √ | Q6: √ | T6: 线上管控-已建 | U6: 智慧共享财务平台、主数据管理平台（MDM2.0） | V6: 1.管理维度体系清单 2.管理维度系统截图 3.管理维度细化申请与审批记录 | W6: 市公司-财务资产部-会计核算处（数据处）总账管理 | X6: 每年 | Y6: 全查 | AA6: 每年 | AB6: 全查 | AD6: 科目维度规范性监督场景 | AE6: 每年 | AF6: 全查 | AH6: 是 | AI6: 是 | AJ6: 《国家电网有限公司会计基础管理办法》（国家电网企管〔2019〕132号）第四章 核算与报告第四十条、第四十四条 《国家电网有限公司财务管理通则》（国家电网企管〔2020〕763号）第三章 管理内容与管理流程第二节 会计核算第二十一条 | AK6: 国网财务部
C7: 资金资产安全、税务合规 | E7: 部分属于成本中心的分支机构，因独立核算增值税，存在进项税长期大额留抵情况，导致资金长期占用风险。 | F7: 分支机构责任中心判定缺少管控：未对新设分支机构责任中心进行定性审批，导致部分成本费用中心采取增值税独立核算模式，因应税收入较少，导致进项税长期大额留抵，地方财政紧张申请退税困难，严重影响资金使用效率。 | G7: 3.分支机构责任中心判定 | H7: 新设分支机构必须准确、合理进行责任中心判定，并明确增值税核算缴纳方式。 | I7: 财务管理-3.分支机构开办费列支管控-控制措施01 | J7: 各级单位在新设分支机构时，财务部门应当根据分支机构职责定位、主营业务，准确判定责任中心类型。对外交易业务相对独立、收入来源较为稳定的利润中心，可申请增值税独立核算；无可靠收入来源、仅发挥业务支撑作用的成本中心、费用中心，原则上应向税务机关办理与总机构汇总核算增值税。 | M7: √ | R7: √ | T7: 线下管控 | V7: 1.分支机构设立的决策性文件； 2.分支机构设立审批表 | W7: 各级单位-财务资产部-预算管理、税金管理、市公司-财务资产部-会计核算处（数据处）总账管理 | X7: 每年 | Y7: 全查 | AA7: 每年 | AB7: 全查 | AH7: 是 | AI7: 是 | AJ7: 《国家电网有限公司税务管理办法》（国家电网财〔2026〕202号）第三章第十一条、第四章第十八条 | AK7: 国网财务部
C8: 税务合规 | D8: 纳税主体管理 | E8: 税务登记或信息变更不及时、证件遗失或未按规定办理登记等情况，导致税务主体资格问题，影响正常经营并可能被处以罚款。 | F8: 未在规定时间内完成税务登记/变更，违反税收征管法相关要求，面临税务机关处罚。 | G8: 4.纳税主体税务登记控制 | H8: 纳税主体设立及税务登记变更信息准确、及时完整。 | I8: 财务管理-4.纳税主体税务登记控制-控制措施01 | J8: 在办理完成产权、工商登记后，各级单位财务部需进行税务登记，应综合考虑业务类型、经营规模等因素，科学选择纳税模式。存续期间发生信息变更时，应当在工商登记变更后及时完成税务登记证变更。 | M8: √ | Q8: √ | T8: 线上管控-已建 | U8: 智慧共享财务平台 | V8: 1.设立及变更登记决策文件 2.工商登记、税务登记、产权登记资料等 | W8: 各级单位-财务资产部-税金管理、资产及产权管理、各级单位-办公室（党委办公室）-法律事务管理、市公司-法律合规部-合规处（数据处）法治合规事务管理 | X8: 每年 | Y8: 全查 | AA8: 每年 | AB8: 全查 | AH8: 是 | AI8: 是 | AJ8: 《国家电网有限公司税务管理办法》（国家电网财〔2026〕202号）第三章第十条到第十四条 | AK8: 国网财务部
A9: 财务管理 | B9: 一、核算范围 | C9: 会计信息真实完整 | D9: 会计政策管理 | E9: 会计政策和会计估计分类和分级授权标准不明确，导致执行不统一，影响会计信息准确性和可比性。 | F9: 会计政策和会计估计分类和分级授权不规范：未明确会计政策和会计估计分类管控和分级授权标准，导致会计信息执行不统一、反映不准确。 | G9: 5.会计政策和会计估计分类管控和分级授权管理 | H9: 明确会计政策、会计估计分类管控和分级授权标准。 | I9: 财务管理-5.会计政策和会计估计分类管控和分级授权管理-控制措施01 | J9: 会计政策和会计估计分类管控及分级授权控制。国网公司统一建立会计政策和会计估计分类管控及分级授权标准，明确政策清单，对应收款项坏账计提组合及比例、固定资产折旧方法和年限区间、投资性房地产后续计量方法等，由国网公司统一确定；对固定资产折旧年限等公司统一政策下的具体执行值，由各级单位履行决策程序后确定具体执行标准，并向国网公司备案或经总部审批。 | L9: √ | T9: 线上管控-待建 | U9: 智慧共享财务平台 | V9: 1.会计政策和会计估计分类管控清单（待总部下发） 2.会计政策、会计估计分级授权清单（待总部下发） | W9: 国网财务部-总账管理人员、市公司-财务资产部-会计核算处（数据处）总账管理、市公司-财务资产部-工程资产处资产管理 | X9: 每年 | Y9: 全查 | AA9: 每年 | AB9: 全查 | AD9: 会计政策、会计估计分类管控及分级授权标准监督场景 | AE9: 每年 | AF9: 全查 | AH9: 是 | AI9: 是 | AJ9: 《国家电网有限公司会计基础管理办法》（国家电网企管〔2019〕132号）第四章 核算与报告第三十九条、第四十四条 | AK9: 国网财务部
E10: 会计政策和会计估计执行不统一、不规范，导致会计信息不准确、经营业绩失真。 | F10: 会计政策和会计估计执行不统一：未严格执行公司统一的会计政策和会计估计，导致会计信息反映不准确、不可比。 | G10: 6.会计政策和会计估计执行管控 | H10: 严格执行统一的会计政策和会计估计标准。 | I10: 财务管理-6.会计政策和会计估计执行管控-控制措施01 | J10: 会计政策和会计估计执行统一性控制。国网公司将统一会计政策和会计估计管控要求嵌入在线业财处理流程，确保全流程规范遵循。每月末，各级单位财务人员对本单位统一政策执行情况进行全面检查，确保反映准确。 | Q10: √ | T10: 线上管控-待建 | U10: 智慧共享财务平台 | V10: 1.会计政策和会计估计分类管控清单（待总部下发） 2.会计政策、会计估计分级授权清单（待总部下发） | W10: 国网财务部-总账管理人员、各级单位-财务资产部-总账报表管理 | X10: 每月 | Y10: 抽查 | AA10: 每年 | AB10: 抽查 | AD10: 会计政策和会计估计规范性监督场景 | AE10: 每月 | AF10: 抽查 | AH10: 是 | AI10: 是 | AJ10: 《国家电网有限公司会计基础管理办法》（国家电网企管〔2019〕132号）第四章 核算与报告第三十九条、第四十四条 | AK10: 国网财务部
E11: 会计政策和会计估计变更不规范、随意调节，跨年调整经营指标，导致会计信息不准确、经营业绩失真。 | F11: 会计政策和会计估计变更流程不规范：变更程序不规范、审核把关不严，滥用变更人为调节年度间财务状况、经营成果，导致会计信息不准确。 | G11: 7.会计政策和会计估计变更审批 | H11: 会计政策和会计估计变更审批统一规范。 | I11: 财务管理-7.会计政策和会计估计变更审批-控制措施01 | J11: 会计政策和会计估计变更审批控制。对会计政策和会计估计变更事项，根据分类管控及分级授权标准，分层级履行党组（党委）会前置研究、董事会或类似机构决策等程序。 | L11: √ | T11: 线下管控 | V11: 1.内部决策文件 | W11: 各级单位-财务资产部-总账报表管理 | X11: 每年 | Y11: 抽查 | AA11: 每年 | AB11: 抽查 | AH11: 是 | AI11: 是 | AJ11: 《国家电网有限公司会计基础管理办法》（国家电网企管〔2019〕132号）第四章 核算与报告第三十九条、第四十四条 | AK11: 国网财务部
C12: 资金资产安全、会计信息真实完整 | D12: 会计岗位管理 | E12: 会计不相容权责未分离，审核审批不合规，容易引发财务舞弊，造成资金挪用、资产损失、会计信息失真。 | F12: 不相容岗位权责未分离：会计兼任出纳、业务审批、财产保管等职责，导致资金资产损失长期隐匿未被发现；凭证制单与审核、审批由同一人负责，容易造成会计舞弊。 | G12: 8.会计不相容岗位管控 | H12: 严格会计不相容岗位相分离。 | I12: 财务管理-8.会计不相容岗位管控-控制措施01 | J12: 不相容岗位相分离控制。各级单位财务部门严格按照不相容岗位相分离的要求，规范设置会计岗位、匹配财务人员。 | K12: √ | L12: √ | T12: 线上管控-已建 | U12: 智慧共享财务平台 | V12: 1.岗位设置与岗位职责说明 2.系统角色和权限配置表 | W12: 各级单位-财务资产部-主任、市公司-财务资产部-主任 | X12: 每月 | Y12: 全查 | AA12: 每年 | AB12: 全查 | AD12: 不相容岗位分离监督场景 | AE12: 每年 | AF12: 全查 | AH12: 是 | AI12: 是 | AJ12: 《国家电网有限公司会计基础管理办法》（国家电网企管〔2019〕132号）第三章 会计机构和会计人员第十六条 《会计基础工作规范》（征求意见稿）第二章 会计机构和会计岗位第十一条 | AK12: 国网财务部
I13: 财务管理-8.会计不相容岗位管控-控制措施02 | J13: 各级单位严格落实财务人员任职回避制度。单位负责人直系亲属不得担任本单位财务机构负责人和会计主管，财务机构负责人和会计主管的直系亲属不得在本单位会计机构中担任出纳。 | K13: √ | T13: 线下管控 | V13: 1.岗位人员清单 2.出纳及财务主任人员信息表 | W13: 各级单位-财务资产部-主任、市公司-财务资产部-主任 | X13: 每年 | Y13: 全查 | AA13: 每年 | AB13: 全查 | AH13: 是 | AI13: 是 | AJ13: 《国家电网有限公司司库管理办法》（国网（财/2）3452023）第十章第二百八十三条 《国家电网有限公司会计基础管理办法》（国家电网企管〔2019〕132号）第三章 会计机构和会计人员第二十条 | AK13: 国网财务部
I14: 财务管理-8.会计不相容岗位管控-控制措施03 | J14: 各级单位要建立资金管理岗轮岗、交流和强制休假机制。替岗人员应在替岗期间完成现金、银行账户余额、重要票据核对及未达账项核实工作，并编制核查报告、审核存档。 | K14: √ | T14: 线下管控 | V14: 1.岗位交接表 2.稽核报告 3.考勤表 | W14: 各级单位-财务资产部-资金管理 | X14: 每季度 | Y14: 全查 | AA14: 每季度 | AB14: 全查 | AH14: 是 | AI14: 是 | AJ14: 《国家电网有限公司司库管理办法》（国网（财/2）3452023）第十一章第二百八十四条 | AK14: 国网财务部
A15: 财务管理 | B15: 一、核算范围 | C15: 资金资产安全、会计信息真实完整 | D15: 会计岗位管理 | E15: 会计岗位交接不规范，影响会计工作组织和会计信息质量。 | F15: 会计岗位交接资料不完整、监交不到位：移交清册等资料不完整，资金、凭证、账簿等财务数据未核对，交接过程未经过监交人监督，交接前后财务信息不衔接、不准确。 | G15: 9.会计岗位交接管控 | H15: 规范会计工作交接，确保会计资料衔接一致。 | I15: 财务管理-9.会计岗位交接管控-控制措施01 | J15: 会计工作交接规范性控制。各级单位财务人员办理移交手续前，应完成未了事项，编制移交清册，并与接管人员逐项核对确认。办理交接手续，必须有监交人负责监交；交接完毕后，交接双方和监交人员要在移交清册上签名或者盖章。财务负责人的岗位交接，应该由分管财务工作的领导监交。 | K15: √ | Q15: √ | T15: 线上管控-待建 | U15: 智慧共享财务平台 | V15: 1.会计岗位交接报告 | W15: 各级单位-财务资产部-会计岗位人员、各级单位-财务资产部-主任、各级单位-领导干部-副总经理 | X15: 每年 | Y15: 全查 | AA15: 每年 | AB15: 全查 | AH15: 是 | AI15: 是 | AJ15: 《国家电网有限公司会计基础管理办法》（国家电网企管〔2019〕132号）第三章 会计机构和会计人员第三节 会计工作交接 《国家电网有限公司司库管理办法》（国网（财/2）3452024）第三章第二百八十五条 | AK15: 国网财务部
B16: 二、账户管理 | C16: 资金资产安全 | D16: 银行账户开立 | E16: 银行账户开立未履行审批手续，易滋生账外账及小金库，账户未纳入系统统一监管，账实不符，引发资金流失风险。 | F16: 1.银行账户未批先设：未经上级或总部批准擅自在线下开立账户。 2.银行账户开立后，未纳入中台统一管理。 3.基本账户超范围开立 4.非经营类账户未纳入中台统一管理 | G16: 10.银行账户合规开立控制 | H16: 严格履行银行账户开立审批手续，规范开户渠道、开户主体，严禁未批先设；定期从人民银行或基本户开户银行获取全量账户清单，排查“应纳未纳”风险。 | I16: 财务管理-10.银行账户合规开立控制-控制措施01 | J16: 各级单位财务部门从严控制银行账户开立机构，基本账户不得出现违反公司规定的标准开立，其他账户应在开户机构白名单范围内选择，不在白名单范围内的开户事项，须履行二级单位本部审核和总部审批。 | L16: √ | M16: √ | T16: 线上管控-已建 | U16: 智慧共享财务平台 | V16: 1.银行账户开立申请单或银行账户开立业务办理回执 | W16: 各级单位-财务资产部-出纳管理、各级单位-财务资产部-资金管理 | X16: 每季度 | Y16: 抽查 | AA16: 每年 | AB16: 抽查 | AH16: 是 | AI16: 是 | AJ16: 《国家电网有限公司司库管理办法》（国网（财/2）3452023）第三章第二十八条、第三十条、第三十一条 | AK16: 国网财务部
I17: 财务管理-10.银行账户合规开立控制-控制措施02 | J17: 各级单位业务部门按照“谁开立谁负责”原则，通过智慧共享财务平台办理银行账户开立申请，并履行内部审批，开立后在规定时间内完成智慧共享财务平台信息维护。 | L17: √ | O17: √ | T17: 线上管控-已建 | U17: 智慧共享财务平台 | V17: 1.银行账户开立业务办理回执 2.银行账户开立申请单 | W17: 各级单位-业务部门-经办人员、各级单位-业务部门-部门负责人、各级单位-财务资产部-出纳管理、各级单位-财务资产部-资金管理、各级单位-财务资产部-主任 | X17: 每季度 | Y17: 抽查 | AA17: 每年 | AB17: 抽查 | AH17: 是 | AI17: 是 | AJ17: 《国家电网有限公司司库管理办法》（国网（财/2）3452023）第三章第三十条、第三十一条、第三十二条、第三十三条、第三十四条、第三十五条 | AK17: 国网财务部
I18: 财务管理-10.银行账户合规开立控制-控制措施03 | J18: 各级单位财务部门（经营类账户）或业务部门（非经营类账户）规范银行账户开立经办管理，须由本人或授权人员办理，经办人员应为正式编制，手续须由至少两名人员共同办理，强化岗位制衡。其中，非经营类账户指含党团工会、出资举办的事业单位以及以公司名义设立或举办的各类组织、单位等所有非并表主体账户。 | K18: √ | T18: 线下管控 | V18: 1.银行账户开立业务办理回执（两名经办人员签字） | W18: 各级单位-财务资产部-财务主任、各级单位-财务资产部-经办人员 | X18: 每季度 | Y18: 抽查 | AA18: 每年 | AB18: 抽查 | AH18: 是 | AI18: 是 | AJ18: 《国家电网有限公司司库管理办法》（国网（财/2）3452023）第三章第三十六条 《国家电网有限公司关于印发〈“四严五强六十条”资金安全管理规程〉及资金安全监控规则的通知》（国家电网财[2021]329号）第26条 | AK18: 国网财务部
I19: 财务管理-10.银行账户合规开立控制-控制措施04 | J19: 各级单位财务部门定期从人民银行或基本户开户银行获取全量已开立银行结算账户清单，与智慧共享财务平台账户台账逐项核对，排查“应纳未纳”等异常，确保账户台账全面覆盖、信息完整。 | M19: √ | S19: √ | T19: 线下管控 | V19: 1.开立银行账户清单 | W19: 各级单位-财务资产部-出纳管理、各级单位-财务资产部-资金管理 | X19: 每季度 | Y19: 抽查 | AA19: 每年 | AB19: 抽查 | AH19: 否 | AI19: 否 | AK19: 国网财务部
I20: 财务管理-10.银行账户合规开立控制-控制措施05 | J20: 中国电财严格核验内部账户开立审批手续，审批流程完备合规后方可受理开户业务。 | M20: √ | T20: 线上管控-已建 | U20: 智慧共享财务平台 | V20: 1.银行账户开立申请单 | W20: 中国电财-直属营业部门或营业部门（司库服务部门）-综合柜员-结算业务负责人 | X20: 每季度 | Y20: 抽查 | AA20: 每年 | AB20: 抽查 | AH20: 是 | AI20: 是 | AJ20: 《中国电力财务有限公司结算账户管理规定》（中国电财〔2024〕215号）第三章第二十三条 | AK20: 国网财务部
A21: 财务管理 | B21: 二、账户管理 | C21: 资金资产安全 | D21: 银行账户开立 | E21: 银行账户开立未履行审批手续，易滋生账外账及小金库，账户未纳入系统统一监管，账实不符，引发资金流失风险。 | F21: 1.银行账户未批先设：未经上级或总部批准擅自在线下开立账户。 2.银行账户开立后，未纳入中台统一管理。 3.基本账户超范围开立 4.非经营类账户未纳入中台统一管理。 | G21: 10.银行账户合规开立控制 | H21: 严格履行银行账户开立审批手续，规范开户渠道、开户主体，严禁未批先设；定期从人民银行或基本户开户银行获取全量账户清单，排查“应纳未纳”风险。 | I21: 财务管理-10.银行账户合规开立控制-控制措施06 | J21: 各级单位财务部门严格执行“先有产权、再建核算账套、后开账户”规则，推动账户模块与产权系统、核算系统数据贯通。产权发生变更时，系统自动推送账户调整预警任务，强制同步办理变更或撤销，杜绝“工商已注销、账户未撤销”。针对系统内产权划转，建立专用账户变更流程，划转完成后原单位账户台账自动删除，新单位自动继承账户信息，无需手工操作。 | M21: √ | T21: 线上管控-待建 | U21: 智慧共享财务平台 | V21: 1.系统中已销户账户清单 2.产权变动相关资料 | W21: 各级单位-财务资产部-出纳管理、各级单位-财务资产部-资金管理、各级单位-财务资产部-会计核算管理、各级单位-财务资产部-资产及产权管理、各级单位-财务资产部-主任 | X21: 每季度 | Y21: 抽查 | AA21: 每年 | AB21: 抽查 | AH21: 否 | AI21: 否 | AK21: 国网财务部
E22: 银行账户未及时办理监控授权，资金动向无法实时监测，异常交易识别不及时，易诱发资金违规占用及挪用风险。 | F22: 对具备监控条件的银行账户未及时办理监控授权（银企直联），造成个别账户脱离监管，造成资金损失风险。 | G22: 11.银行账户办理监控控制 | H22: 银行账户及时纳入监控，定期监控资金流水动向及频次。 | I22: 财务管理-11.银行账户办理监控控制-控制措施01 | J22: 各级单位财务部门（经营类账户）或业务部门（非经营类账户）对具备监控条件的银行账户在完成开立时在规定时间内办理监控授权，确保纳入公司资金监控体系。 | L22: √ | M22: √ | T22: 线上管控-待建 | U22: 智慧共享财务平台 | V22: 1.《资金结算系统账户服务注册（变更）申请表》 | W22: 各级单位-财务资产部-出纳管理、各级单位-财务资产部-资金管理、各级单位-财务资产部-主任、各级单位-业务部门-经办人员、各级单位-业务部门-部门负责人 | X22: 每季度 | Y22: 抽查 | AA22: 每年 | AB22: 抽查 | AH22: 是 | AI22: 是 | AJ22: 《国家电网有限公司司库管理办法》（国网（财/2）3452023）第三章第三十七条、第三十八条 | AK22: 国网财务部
I23: 财务管理-11.银行账户办理监控控制-控制措施02 | J23: 各单位应在完成银行账户变更相关手续后15个工作日内办理授权变更工作，银行账户撤销应在终止监控授权后及时办理销户手续。 | L23: √ | M23: √ | T23: 线上管控-已建 | U23: 智慧共享财务平台 | V23: 1.《资金结算系统账户服务注册（变更）申请表》 2.《资金结算系统 CA 证书（变更）申请单》 3.《终止银企互联账户授权书》 | W23: 各级单位-财务资产部-出纳管理、各级单位-财务资产部-资金管理、各级单位-财务资产部-主任、各级单位-业务部门-经办人、各级单位-业务部门-部门负责人 | X23: 每季度 | Y23: 抽查 | AA23: 年度 | AB23: 抽查 | AH23: 是 | AI23: 是 | AJ23: 《国家电网有限公司司库管理办法》（国网（财/2）345-2027）第三章第三十七条 | AK23: 国网财务部
C24: 资金资产安全 | D24: 商户号开立 | E24: 商户号开立未履行审批手续，缺少财务监督，易形成账外资金、私设小金库，引发资金流失风险。 | F24: 商户号未按规定履行审批流程，未严格审核开户机构（服务商）资质和协议，开通了转账功能，导致资金损失风险。 | G24: 12.商户号合规开立控制 | H24: 严格履行商户号开立审批手续，规范开户渠道、开户主体，严禁未批先设，严禁超标准开设。 | I24: 财务管理-12.商户号合规开立控制-控制措施01 | J24: 各级单位业务部门严格执行商户号开立白名单（微信、支付宝、银联商务、电e宝）管理，通过智慧共享财务平台办理商户号开立审批，不在白名单范围内的开户事项，须履行二级单位本部审核和总部审批，严禁未批先开。开立后在规定时间内完成智慧共享财务平台纳管，未经审批私自开立及未按规定时间纳管的商户号的视为小金库。 | L24: √ | M24: √ | O24: √ | T24: 线上管控-待建 | U24: 智慧共享财务平台 | V24: 1.营业执照 2.组织机构设置文件 3.商户号开立业务办理回执（若有） | W24: 各级单位-财务资产部-出纳管理、各级单位-财务资产部-资金管理、各级单位-财务资产部-主任、各级单位-业务部门-经办人员、各级单位-业务部门-部门负责人 | X24: 每季度 | Y24: 抽查 | AA24: 每年 | AB24: 抽查 | AH24: 是 | AI24: 是 | AJ24: 《国网财务部关于规范和加强商户号管理的通知》（财金[2025]2号）第二章第1条、第3条、第5条 | AK24: 国网财务部
I25: 财务管理-12.商户号合规开立控制-控制措施02 | J25: 各级单位财务部门对商户号开立协议进行审核，核验绑定账户为本单位或上级单位对公账户，向关联银行账户提现资金周期不得超过T+1且自动划转。 | M25: √ | O25: √ | P25: √ | T25: 线上管控-待建 | U25: 智慧共享财务平台、数字化法治企业建设平台 | V25: 1.商户号开立协议 | W25: 各级单位-财务资产部-出纳管理、各级单位-财务资产部-资金管理、各级单位-财务资产部-主任 | X25: 每季度 | Y25: 抽查 | AA25: 每年 | AB25: 抽查 | AH25: 是 | AI25: 是 | AJ25: 《国网财务部关于规范和加强商户号管理的通知》（财金[2025]2号）第二章第4条，第三章第7条 | AK25: 国网财务部
E26: 商户号未及时办理监控授权，资金动向无法实时监测，异常交易识别不及时，易诱发资金违规占用及挪用风险。 | F26: 1.商户号未办理监控授权； 2.提现周期较长，向关联银行账户提现周期超过T+1日，资金未能及时回笼，存在资金沉淀及安全风险。 | G26: 13.商户号办理监控控制 | H26: 商户号及时纳入监控，定期监控资金流水动向及频次。 | I26: 财务管理-13.商户号办理监控控制-控制措施01 | J26: 各级单位业务部门对具备监控条件的商户号在完成开立手续后的规定时间内向数科公司办理商户号监控授权，确保纳入公司资金监控体系。 | L26: √ | M26: √ | T26: 线上管控-已建 | U26: 智慧共享财务平台 | V26: 1.监控授权书 | W26: 各级单位-业务部门-经办人、各级单位-业务部门-部门负责人 | X26: 每季度 | Y26: 抽查 | AA26: 每年 | AB26: 抽查 | AH26: 是 | AI26: 是 | AJ26: 《国网财务部关于规范和加强商户号管理的通知》（财金[2025]2号）第四章第10条 《国家电网有限公司司库管理办法》（国网（财/2）3452023）第三章第三十七条 | AK26: 国网财务部
I27: 财务管理-13.商户号办理监控控制-控制措施02 | J27: 各级单位财务部门监控商户号资金，核查是否存在除“T+1”日自动划转至上级账户外的资金沉淀。 | P27: √ | T27: 线上管控-待建 | U27: 智慧共享财务平台 | V27: 1.资金流水明细 2.余额调节表 | W27: 各级单位-财务资产部-出纳管理、各级单位-财务资产部-资金管理、各级单位-财务资产部-主任 | X27: 每季度 | Y27: 抽查 | AA27: 每年 | AB27: 抽查 | AH27: 是 | AI27: 是 | AJ27: 《国网财务部关于规范和加强商户号管理的通知》（财金[2025]2号）第四章第12条 | AK27: 国网财务部
A28: 财务管理 | B28: 二、账户管理 | C28: 资金资产安全 | D28: 数字钱包开立 | E28: 数字钱包开立未履行审批手续，易滋生账外账及小金库，未纳入系统统一监管，账实不符，引发资金流失风险。 | G28: 14.数字钱包合规开立控制 | H28: 严格履行数字钱包开立审批手续，规范开户渠道、开户主体，严禁未批先设。 | I28: 财务管理-14.数字钱包合规开立控制-控制措施01 | J28: 通过智慧共享财务平台办理数字钱包开、变、销审批，限定工行、农行、中行、建行、交行、邮储6家银行办理，超出管控标准及开户范围的，须经各二级单位本部审核和总部审批；相关手续办结后规定时间内，须在智慧共享财务平台完成开户信息维护。 | L28: √ | M28: √ | T28: 线上管控-已建 | U28: 智慧共享财务平台 | V28: 1.数字钱包开立申请 2.数字钱包开立业务办理回执 3.数字钱包登记审批单 4.数字钱包台账 | W28: 各级单位-财务资产部-出纳管理、各级单位-财务资产部-资金管理、各级单位-财务资产部-主任、各级单位-业务部门-经办人员、各级单位-业务部门-部门负责人 | X28: 每季度 | Y28: 抽查 | AA28: 每年 | AB28: 抽查 | AH28: 是 | AI28: 是 | AJ28: 《国家电网有限公司司库管理办法》（国网（财/2）3452023）第三章第二十八条、第三十五条 | AK28: 国网财务部
I29: 财务管理-14.数字钱包合规开立控制-控制措施02 | J29: 各级单位财务部门规范数字钱包开立经办管理，须由本人或授权人员办理，经办人员应为正式编制，手续须由至少两名人员共同办理，强化岗位制衡。 | K29: √ | T29: 线下管控 | V29: 1.数字钱包开立业务办理回执 | W29: 各级单位-财务资产部-主任、各级单位-财务资产部-经办人员 | X29: 每季度 | Y29: 抽查 | AA29: 每年 | AB29: 抽查 | AH29: 是 | AI29: 是 | AJ29: 《国家电网有限公司司库管理办法》（国网（财/2）3452023）第三章第三十六条 | AK29: 国网财务部
G30: 15.数字钱包监控控制 | H30: 数字钱包及时纳入监控，定期监控资金流水动向及频次。 | I30: 财务管理-15.数字钱包办理监控控制-控制措施01 | J30: 各级单位对具备监控条件的数字钱包在完成开立后，需在规定时限内办理监控授权，确保纳入公司资金监控体系。 | L30: √ | M30: √ | T30: 线上管控-已建 | U30: 智慧共享财务平台 | V30: 1.《银企互联数字人民币钱包授权书》 2.《资金结算系统数字人民币钱包服务注册（变更）申请表》 3.《资金结算系统数字人民币钱包流程注册（变更）申请表》 | W30: 各级单位-财务资产部-出纳管理、各级单位-财务资产部-资金管理、各级单位-财务资产部-主任 | X30: 每季度 | Y30: 抽查 | AA30: 每年 | AB30: 抽查 | AH30: 是 | AI30: 是 | AJ30: 《国家电网有限公司司库管理办法》（国网（财/2）3452023）第三章第三十七条 | AK30: 国网财务部
C31: 资金资产安全 | D31: 银行账户变更 | E31: 银行账户变更不及时，与经营信息不一致；账户信息变更后未同步更新智慧共享财务平台登记信息，可能导致台账数据失真。 | G31: 16.银行账户变更及时性、必要性控制 | H31: 银行账户信息纳入管控并及时变更 | I31: 财务管理-16.银行账户变更及时性控制-控制措施01 | J31: 各级单位财务部门（经营类账户）或业务部门（非经营类账户）对于银行账户经营信息、账户属性发生变动的，及时完成变更分级审批流程；对于经营类账户的特殊事项变更（包括集团账户变更为独立账户、监控账户变更为无法监控账户、其他分类变更为专用账户），须经各二级单位本部审核和公司总部审批；账户信息变更后，按规定时间在智慧共享财务平台维护登记，确保银行账户台账信息准确、账实相符。 | L31: √ | M31: √ | T31: 线上管控-已建 | U31: 智慧共享财务平台 | V31: 1.《资金结算系统账户服务注册（变更）申请书》 | W31: 各级单位-财务资产部-出纳管理、各级单位-财务资产部-资金管理、各级单位-财务资产部-主任 各级单位-业务部门-经办人员、各级单位-业务部门-部门负责人 | X31: 每季度 | Y31: 抽查 | AA31: 每年 | AB31: 抽查 | AH31: 是 | AI31: 是 | AJ31: 《国家电网有限公司司库管理办法》（国网（财/2）3452023）第三章第三十条、第三十五条、第三十七条、第三十八条 《国家电网有限公司关于印发〈“四严五强六十条”资金安全管理规程〉及资金安全监控规则的通知》（国家电网财[2021]329号）第26条、27条 | AK31: 国网财务部
I32: 财务管理-16.银行账户变更及时性控制-控制措施02 | J32: 各级单位财务部门（经营类账户）或业务部门（非经营类账户）规范银行账户变更经办管理，经办人员应为正式编制，手续须由至少两名人员共同办理，强化岗位制衡。 | K32: √ | T32: 线下管控 | V32: 1.银行账户变更业务办理回执（两名经办人员签字） | W32: 各级单位-财务资产部-财务主任、各级单位-业务部门-部门负责人 | X32: 每季度 | Y32: 抽查 | AA32: 每年 | AB32: 抽查 | AH32: 是 | AI32: 是 | AJ32: 《国家电网有限公司司库管理办法》（国网（财/2）3452023）第三章第三十六条 | AK32: 国网财务部
C33: 资金资产安全 | D33: 商户号变更 | E33: 商户号变更不及时，与经营信息不一致；账户信息变更后未同步更新智慧共享财务平台登记信息，可能导致台账数据失真。 | G33: 17.商户号变更及时性、必要性控制 | H33: 商户号信息纳入管控并及时变更 | I33: 财务管理-17.商户号信息纳入管控并及时变更-控制措施01 | J33: 各级单位业务部门对商户号相关信息发生变更时，应在智慧共享财务平台发起商户号变更申请，其中，商户号关联银行账户变更通过各二级单位本部审核、公司总部审批，其他变更由各二级单位自行管理。完成线下信息变更及线上变更登记审批后，须在规定时间内在智慧共享财务平台维护登记，确保商户号台账信息准确、账实相符。 | L33: √ | M33: √ | T33: 线上管控-已建 | U33: 智慧共享财务平台 | V33: 1.《资金结算系统商户号服务注册（变更）申请书》 | W33: 各级单位-财务资产部-出纳管理、各级单位-财务资产部--资金管理、各级单位-财务资产部-主任、各级单位-业务部门-经办人员、各级单位-业务部门-部门负责人 | X33: 每季度 | Y33: 抽查 | AA33: 每年 | AB33: 抽查 | AH33: 是 | AI33: 是 | AJ33: 《国家电网有限公司司库管理办法》（国网（财/2）3452023）第三章第三十条、第三十五条、第三十七条、第三十八条 《国网财务部关于规范和加强商户号管理的通知》（财金[2025]2号）第五章一十五条 | AK33: 国网财务部
A34: 财务管理 | B34: 二、账户管理 | C34: 资金资产安全 | D34: 数字钱包变更 | E34: 数字钱包变更不及时，与经营信息不一致；账户信息变更后未同步更新智慧共享财务平台登记信息，可能导致台账数据失真。 | G34: 18.数字钱包变更及时性、必要性控制 | H34: 数字钱包信息纳入管控并及时变更 | I34: 财务管理-18.数字钱包信息纳入管控并及时变更-控制措施01 | J34: 各级单位财务部门对于数字钱包经营信息、账户属性发生变动的，及时完成变更分级审批流程，对于特殊事项变更（监控账户变更为无法监控账户），须经各二级单位本部审核和公司总部审批；信息变更后，按规定时间在智慧共享财务平台维护登记，确保数字钱台账信息准确、账实相符。 | L34: √ | M34: √ | T34: 线上管控-已建 | U34: 智慧共享财务平台 | V34: 1.《资金结算系统数字人民币钱包服务注册（变更）申请书》 | W34: 各级单位-财务资产部-出纳管理、各级单位-财务资产部-资金管理、各级单位-财务资产部-主任、各级单位-业务部门-经办人员、各级单位-业务部门-部门负责人 | X34: 每季度 | Y34: 抽查 | AA34: 每年 | AB34: 抽查 | AH34: 是 | AI34: 是 | AJ34: 《国家电网有限公司司库管理办法》（国网（财/2）3452023）第三章第三十条、第三十二条、第三十三条、第三十五条、第三十七条、第三十八条 | AK34: 国网财务部
I35: 财务管理-18.数字钱包信息纳入管控并及时变更-控制措施02 | J35: 各级单位财务部门规范数字钱包变更经办管理，经办人员应为正式编制，手续须由至少两名人员共同办理，强化岗位制衡。 | K35: √ | T35: 线下管控 | V35: 1.数字钱包变更业务办理回执（两名经办人员签字） | W35: 各级单位-财务资产部-主任、各级单位-业务部门-部门负责人 | X35: 每季度 | Y35: 抽查 | AA35: 每年 | AB35: 抽查 | AH35: 是 | AI35: 是 | AJ35: 《国家电网有限公司司库管理办法》（国网（财/2）3452023）第三章第三十六条 | AK35: 国网财务部
C36: 资金资产安全 | D36: 银行账户撤销 | E36: 银行账户撤销不及时，销户滞后于工商主体注销，久悬账户未及时注销，应销未销诱发“账外账”风险。 | F36: 1.银行账户注销不及时：开立主体已完成工商注销，但账户仍存续。 2.低效、无效账户及久悬账户未及时清理。 3.银行已销户未登记：银行账户已注销，但在中台台账登记不及时。 | G36: 19.银行账户注销及时性、规范性控制 | H36: 银行账户在工商变更或注销前、业务完结后（如工程完结农民工专户及时注销）完成账户注销，及时登记台账。 | I36: 财务管理-19.银行账户注销及时性、规范性控制-控制措施01 | J36: 各级单位财务部门（经营类账户）或业务部门（非经营类账户）规范银行账户撤销经办管理，须由本人或授权人员办理，经办人员应为正式编制，手续须由至少两名人员共同办理，强化岗位制衡。 | K36: √ | T36: 线下管控 | V36: 1.银行账户撤销业务办理回执（两人签字） | W36: 各级单位-财务资产部-主任、各级单位-业务部门-部门负责人 | X36: 每季度 | Y36: 抽查 | AA36: 每年 | AB36: 抽查 | AH36: 是 | AI36: 是 | AJ36: 《国家电网有限公司司库管理办法》（国网（财/2）3452023）第三章第三节第三十六条 | AK36: 国网财务部
I37: 财务管理-19.银行账户注销及时性、规范性控制-控制措施02 | J37: 各级单位财务部门（经营类账户）或业务部门（非经营类账户）规范办理银行账户注销，终止监控授权后按制度要求时限办理销户，严格执行先销账户、后销工商主体顺序，注销相关手续办结后在规定时间内，完成智慧共享财务平台销户登记，报二级单位备案。 | L37: √ | M37: √ | T37: 线上管控-已建 | U37: 智慧共享财务平台 | V37: 1.《资金结算系统账户服务注册（变更）申请表》 2.银行账户撤销业务办理回执 | W37: 各级单位-财务资产部-出纳管理、各级单位-财务资产部-资金管理、各级单位-财务资产部-主任、各级单位-业务部门-经办人员、各级单位-业务部门-部门负责人 | X37: 每季度 | Y37: 抽查 | AA37: 每年 | AB37: 抽查 | AH37: 是 | AI37: 是 | AJ37: 《国家电网有限公司司库管理办法》（国网（财/2）3452023）第三章第二十九条、第三十六条、第三十七条 | AK37: 国网财务部
I38: 财务管理-19.银行账户注销及时性、规范性控制-控制措施03 | J38: 各级单位财务部门加强低效、无效账户监控。销户资金应及时、全量回笼。 | Q38: √ | T38: 线上管控-待建 | U38: 智慧共享财务平台 | V38: 1.低效账户督办单 2.银行账户撤销业务办理回执（若有） | W38: 各级单位-财务资产部-出纳管理、各级单位-财务资产部-资金管理、各级单位-财务资产部-主任、各级单位-业务部门-经办人员、各级单位-业务部门-部门负责人 | X38: 每季度 | Y38: 抽查 | AA38: 每年 | AB38: 抽查 | AH38: 是 | AI38: 是 | AJ38: 《国家电网有限公司司库管理办法》（国网（财/2）3452023）第三章第三十九条、第十一章第二百九十八条 | AK38: 国网财务部
C39: 资金资产安全 | D39: 商户号撤销 | E39: 商户号撤销不及时，销户滞后于工商主体注销，应销未销诱发“账外账”风险。 | G39: 20.商户号注销及时性、规范性控制 | H39: 商户号在工商注销前完成账户注销，及时登记台账。 | I39: 财务管理-20.商户号注销及时性、规范性控制-控制措施01 | J39: 各级单位业务部门提交商户号撤销资料，负责资料完整性、真实性。 | M39: √ | T39: 线下管控 | V39: 1.商户号注销申请书 | W39: 各级单位-业务部门-经办人员、各级单位-业务部门-部门负责人 | X39: 每季度 | Y39: 抽查 | AA39: 每年 | AB39: 抽查 | AH39: 否 | AI39: 否 | AK39: 国网财务部
I40: 财务管理-20.商户号注销及时性、规范性控制-控制措施02 | J40: 各级单位业务部门规范商户号注销程序，及时完成商户号资金清算。商户号注销时，应在智慧共享财务平台发起商户号注销申请，注销审批流程由各二级单位审批。销户资金应及时、全量回笼。 | L40: √ | M40: √ | T40: 线上管控-待建 | U40: 智慧共享财务平台 | V40: 1.商户号撤销业务办理回执（若有） | W40: 各级单位-财务资产部-出纳管理、各级单位-财务资产部-资金管理、各级单位-财务资产部-主任、各级单位-业务部门-经办人员、各级单位-业务部门-部门负责人 | X40: 每季度 | Y40: 抽查 | AA40: 每年 | AB40: 抽查 | AH40: 是 | AI40: 是 | AJ40: 《国家电网有限公司司库管理办法》（国网（财/2）3452023）第三章第二十九条、第三十六条、第三十七条 《国网财务部关于规范和加强商户号管理的通知》（财金[2025]2号）第二章第6条 | AK40: 国网财务部
A41: 财务管理 | B41: 二、账户管理 | C41: 资金资产安全 | D41: 数字钱包撤销 | E41: 数字钱包撤销不规范，销户滞后于工商主体注销，应销未销诱发“账外账”风险。 | G41: 21.数字钱包注销及时性、规范性控制 | H41: 数字钱包在工商注销前完成账户注销，及时登记台账。 | I41: 财务管理-21.数字钱包注销及时性、规范性控制-控制措施01 | J41: 各级单位规范数字钱包撤销经办管理，须由本人或授权人员办理，经办人员应为正式编制，手续须由至少两名人员共同办理，强化岗位制衡。 | K41: √ | T41: 线下管控 | V41: 1.数字钱包注销业务办理回执（两名经办人员签字） | W41: 各级单位-财务资产部-财务主任、各级单位-业务部门-部门负责人 | X41: 每季度 | Y41: 抽查 | AA41: 每年 | AB41: 抽查 | AH41: 是 | AI41: 是 | AJ41: 《国家电网有限公司司库管理办法》（国网（财/2）3452023）第三章第三十六条 | AK41: 国网财务部
I42: 财务管理-21.数字钱包注销及时性、规范性控制-控制措施02 | J42: 各级单位财务部门规范办理数字钱包注销，终止监控授权后按制度要求时限办理销户，严格执行先销数字钱包、后销工商主体顺序，注销后在智慧共享财务平台完成登记。销户资金应及时、全量回笼。 | L42: √ | M42: √ | T42: 线上管控-已建 | U42: 智慧共享财务平台 | V42: 1.《终止银企互联数字人民币钱包授权书》 2.《资金结算系统数字人民币钱包服务注册（变更）申请表》 3.数字人民币撤销业务办理回执（若有） | W42: 各级单位-财务资产部-出纳管理、各级单位-财务资产部-资金管理、各级单位-财务资产部-主任、各级单位-业务部门-经办人员、各级单位-业务部门-部门负责人 | X42: 每季度 | Y42: 抽查 | AA42: 每年 | AB42: 抽查 | AH42: 是 | AI42: 是 | AJ42: 《国家电网有限公司司库管理办法》（国网（财/2）3452023）第三章第二十九条、第三十六条、第三十七条 | AK42: 国网财务部
C43: 会计信息真实完整 | D43: 账户核算范围管理 | E43: 银行账户核算不完整，会计信息不准确，产生资金安全风险。 | F43: 银行账户核算不完整：账内银行账户与开户清单、账内商户号与开立商户号清单不一致，存在账外资金，导致资金失管、账实不符，引发资金安全风险。 | G43: 22.账户完整性管控 | H43: 银行账户和商户号核算完整、准确。 | I43: 财务管理-22.账户完整性管控-控制措施01 | J43: 银行账户和商户号核算完整性控制。各级单位财务人员会同决算审计会计师事务所，前往人民银行或基本户开户行打印全量开户清单；会计师事务所对商户号进行函证，逐一与账内核算的银行账户和商户号进行比对，确保以公司名义开立、可独立支配账户资金、承担资金安全管理责任的银行账户和商户号，均完整纳入账内核算。 | M43: √ | Q43: √ | T43: 线上管控-待建 | U43: 智慧共享财务平台 | V43: 1.银行账户开立清单 2.商户号清单 | W43: 各级单位-财务资产部-总账报表管理、各级单位-财务资产部-出纳管理人员、各级单位-财务资产部-资金管理、各级单位-财务资产部-主任 | X43: 每季度 | Y43: 全查 | AA43: 每年 | AB43: 全查 | AD43: 账户完整性监督场景 | AE43: 每季度 | AF43: 全查 | AH43: 是 | AI43: 是 | AJ43: 《国家电网有限公司司库管理办法》（国网（财/2）3452023）第三章 银行账户（数字钱包）管理第二十五条、第十一章 资金安全管理第三百〇四条 《国网财务部关于进一步加强社会保障有关账户管理和资金核算的通知》（财金〔2024〕12号） | AK43: 国网财务部
B44: 三、预算管理 | C44: 会计信息真实完整、资金资产安全、税务合规 | D44: 战略支撑 （事前） | E44: 1.财务规划与公司战略协同不足，未有效承接战略指标体系。 2.规划没有科学分解到年度预算，落地执行出现偏差。 3.预算编制未与核价规则有效衔接，导致核价结果不及预期，进而影响战略目标的实现。 | F44: 规划目标与战略脱节：未按照战略目标体系设置规划目标，各级规划目标未有效协同，目标测算未与核价规则衔接，年度决算完成后未与规划目标进行对比分析。 | G44: 23.规划目标与战略一致性审核 | H44: 规划目标测算有效衔接战略指标体系及核价规则，推动规划投资全部纳入核价、核价规则深度融入经营，经营成果有效落实规划。 | I44: 财务管理-23.规划目标与战略一致性审核-控制措施01 | J44: 战略指标一致性审查。国网及各二级单位财务部门在规划编制环节核查经营目标与战略指标体系的一致性，对指标缺失或脱节的情形，不予通过。 | N44: √ | Q44: √ | T44: 线下管控 | V44: 1.公司战略规划方案 2.公司预算方案 | W44: 市公司-财务资产部-预算管理处预算管理 | X44: 每年 | Y44: 全查 | AA44: 每年 | AB44: 全查 | AH44: 是 | AI44: 是 | AJ44: 《国家电网有限公司全面预算管理办法》（国网（财/2）3752026）第三条、第十四条 | AK44: 国网财务部
I45: 财务管理-23.规划目标与战略一致性审核-控制措施02 | J45: 建立“五年规划、三年核价、年度经营”相贯通的滚动预算管控机制。国网及各二级单位财务部门在智慧共享财务平台部署多维联动测算模型，建立“1+N”管控场景（1个监管业务典型场景，N个非监管业务个性化场景），在进行财务规划编制时，以核价参数为约束，合理安排规划期年度经营目标、投资和成本，逐年滚动预测，对比分析规划目标、核价参数落实情况，科学编制预算。 | N45: √ | Q45: √ | S45: √ | T45: 线上管控-待建 | U45: 智慧共享财务平台 | V45: 1.公司战略规划方案 2.公司预算方案 3.多维联动测算模型 | W45: 市公司-财务资产部-预算管理处预算管理 | X45: 每年 | Y45: 全查 | AA45: 每年 | AB45: 全查 | AD45: 多维联动测算模型场景 | AE45: 每年 | AF45: 全查 | AH45: 是 | AI45: 是 | AJ45: 《国家电网有限公司全面预算管理办法》（国网（财/2）3752026）第三条、第二十二条 | AK45: 国网财务部
A46: 财务管理 | B46: 三、预算管理 | C46: 会计信息真实完整、资金资产安全、税务合规 | D46: 战略支撑 （事前） | E46: 1.决策依据不充分，对经营形势研判不足，缺乏充分调研和可行性分析。 2.决策流程不规范，未严格履行决策程序，导致预算决策出现偏差。 3.预算调整不及时，预算基础或边际条件发生重大变化时，未及时履行预算调整程序。 | F46: 预算决策流程不规范：重大项目投资未按规定履行本单位“三重一大”决策程序；预算决策流程流于形式，部分事项先执行后补签、越权审批或缺少书面记录；项目已出现明显亏损或环境变化，仍继续投入，缺少主动中止或调整的机制。 | G46: 24.预算决策程序审核 | H46: 预算决策依据充分、完整，程序规范、有效，及时响应预算基础或边际条件重大变化，确保公司经营稳健。 | I46: 财务管理-24.预算决策程序审核-控制措施01 | J46: 强化事前可研论证。每年，各级单位业务部门结合实际情况，明确本专业投入重点，并据此组织开展可研评审及项目储备。原则上所有纳入业务预算的项目均需履行项目储备程序，并向财务部门提供项目清单，清单中包括以下信息：项目名称、金额、建设内容、可研评审及批复文号等。 | M46: √ | N46: √ | T46: 线下管控 | V46: 1.项目立项相关材料 2.储备项目明细 | W46: 各级单位-业务部门-经办人员 | X46: 每年 | Y46: 抽查 | AA46: 每年 | AB46: 抽查 | AH46: 是 | AI46: 是 | AJ46: 《国家电网有限公司全面预算管理办法》（国网（财/2）3752026）第十六条、第二十四条第二十二条财预〔2025〕27号 国网财务部关于印发《国家电网有限公司财务支出可研经济性与财务合规性评价工作指引（2025）》的通知第一章4 | AK46: 国网财务部
I47: 财务管理-24.预算决策程序审核-控制措施02 | J47: 规范决策程序。各级单位办公室、法律部门等归口管理部门制定决策事项清单，对需纳入“三重一大”决策的预算事项进行明确；对预算方案决策程序进行合规性审核，决策会议由专人记录，会议纪要由会议主持人或公司主要负责同志签发，事后及时归档，确保决策流程完整规范。 | M47: √ | N47: √ | T47: 线下管控 | V47: 1.决策事项清单 2.会议纪要 | W47: 各级单位-业务部门-经办人员、各级单位-财务资产部-预算管理、各级单位-办办公室（党委办公室）-法律事务管理 | X47: 每年 | Y47: 全查 | AA47: 每年 | AB47: 全查 | AH47: 是 | AI47: 是 | AJ47: 《国家电网有限公司全面预算管理办法》（国网（财/2）3752026）第十四条、第十五条 | AK47: 国网财务部
I48: 财务管理-24.预算决策程序审核-控制措施03 | J48: 及时履行预算调整程序。在预算基础或边际条件发生重大变化时，各级单位业务部门要及时向财务部提出预算调整建议，财务部门要及时组织开展经营分析，及时启动预算调整程序，在预算调整批复后，及时推进落地实施，确保公司稳健经营。 | N48: √ | Q48: √ | T48: 线上管控-已建 | U48: 智慧共享财务平台 | V48: 1.公司预算调整方案 2.决策记录 | W48: 各级单位-业务部门-经办人员、各级单位-财务资产部-预算管理 | X48: 每年 | Y48: 全查 | AA48: 每年 | AB48: 全查 | AD48: 预算调整合规性场景 | AE48: 每年 | AF48: 全查 | AH48: 是 | AI48: 是 | AJ48: 《国家电网有限公司全面预算管理办法》（国网（财/2）3752026）第三十七条、第三十八条、三十九条 | AK48: 国网财务部
E49: 1.预算责任泛化。预算责任框架体系尚未健全完善，立项颗粒度不精细，预期目标不明确，导致资源错配或低效使用。 2.资源分配不精准。资源投入与公司重点任务脱节，区域、网架资源分配不均衡、布局不合理，影响电网均衡发展。 | F49: 生产性投入不足：资源分配结构不合理，生产性投入占比偏低，难以满足安全生产、设备运维等核心业务需求。 | G49: 25.资源配置精准性管控 | H49: 资源分配满足公司战略落地、监审核价、业务发展等预期目标要求，并确保预算责任主体明确。 | I49: 财务管理-25.资源配置精准性管控-控制措施01 | J49: 完善预算责任框架体系。各级单位财务部门在智慧共享财务平台中，完善预算责任框架体系，细化成本中心、利润中心，延伸至供电所或班组，并将预算指标层层分解。 | N49: √ | Q49: √ | T49: 线上管控-待建 | U49: 智慧共享财务平台 | V49: 1.预算责任框架体系 | W49: 各级单位-财务资产部-预算管理 | X49: 每年 | Y49: 全查 | AA49: 每年 | AB49: 全查 | AD49: 资源配置精准性监督场景 | AE49: 每年 | AF49: 全查 | AH49: 是 | AI49: 是 | AJ49: 《国家电网有限公司全面预算管理办法》（国网（财/2）3752026）第三十二条、第三十三条 | AK49: 国网财务部
I50: 财务管理-25.资源配置精准性管控-控制措施02 | J50: 强化财务支出分类管理。健全财务支出四级分类体系，对于资产动因类支出，原则上应关联至三级同源目录资产（价值核算单元）；对于组织动因类支出，分解至具体业务单元或部门，原则上以供电所为最小单元进行建项和执行管控。 | N50: √ | Q50: √ | T50: 线下管控 | V50: 1.预算分解明细 | W50: 各级单位-财务资产部-成本管理、各级单位-业务部门-经办人员、各级单位-财务资产部-预算管理 | X50: 每年 | Y50: 全查 | AA50: 每年 | AB50: 全查 | AH50: 是 | AI50: 是 | AJ50: 《国家电网有限公司全面预算管理办法》（国网（财/2）3752026）第三十二条、第三十三条、《国家电网有限公司成本管理办法》（国网（财2）347-2025）第十六条 | AK50: 国网财务部
I51: 财务管理-25.资源配置精准性管控-控制措施03 | J51: 依托作业标准成本开展资源配置。国网财务部根据业务部门、各级单位在线填报或通过系统推送变电站数量、线路长度、人员数量等业务动因参数，组织审定各业务投向、各级单位标准成本，并以此为基础，编制下达检修运维费用预算。电网业务板块，各级单位财务部门开展本地化改造，在上级核定的成本预算范围内，开展本层级检修运维费用预算分解。产业、金融、国际、战新等其他业务板块，开展其他运营标准成本本地化改造，加强费用预算管控。 | N51: √ | Q51: √ | T51: 线上管控-已建 | U51: 智慧共享财务平台 | V51: 1.标准成本体系 | W51: 市公司-财务资产部-预算管理处预算管理、各级单位-业务部门-经办人员 | X51: 每年 | Y51: 全查 | AA51: 每年 | AB51: 全查 | AD51: 预算下达模块 | AE51: 每年 | AF51: 全查 | AH51: 是 | AI51: 是 | AJ51: 《国家电网有限公司全面预算管理办法》（国网（财/2）3752026）第二十五条、第三十二条 | AK51: 国网财务部
I52: 财务管理-25.资源配置精准性管控-控制措施04 | J52: 各级单位财务部门应主动通过管控措施推动节约型企业建设，将非生产性支出、节约型企业建设等作为重点任务纳入相关工作方案或指标考核体系，推动资源分配向生产一线倾斜，严控非生产性支出。 | N52: √ | T52: 线下管控 | V52: 1.提质增效相关工作方案（任务） | W52: 各级单位-业务部门-经办人员、各级单位-财务资产部-预算管理 | X52: 每年 | Y52: 全查 | AA52: 每年 | AB52: 全查 | AI52: 是 | AJ52: 《国家电网有限公司全面预算管理办法》（国网（财/2）375-2026）第三十二条；《国网重庆市电力公司保障稳健经营工作方案》（渝电财〔2025〕8号） | AK52: 国网财务部
A53: 财务管理 | B53: 三、预算管理 | C53: 会计信息真实完整、资金资产安全、税务合规 | D53: 执行控制 （事中） | E53: 缺乏经营目标过程管控，未及时进行预算执行情况分析，导致预算执行不均衡或年度预算目标无法完成。 | F53: 未完成预算下达指标：决算审核后，部分经营指标未完成年度预算下达目标。 | G53: 26.预算执行情况分析 | H53: 严格预算执行控制，及时发现和报告重大预算事项，顺利实现公司战略及经营目标。 | I53: 财务管理-26.预算执行情况分析-控制措施01 | J53: 定期开展预算执行情况分析。国网及各级单位财务部门设定月度预算执行目标，在智慧共享财务平台部署，并设置预警阈值，各级单位财务部门将实际执行进度与预算进度进行对比分析，并提前制定预控措施，确保均衡规范完成年度目标，其中：对于电网监管业务，重点关注电量及增速、电价水平、成本入账进度、利润水平等执行情况及均衡性；对于产业、金融、国际、战新及原集体企业等市场化业务，重点关注利润进度、毛利率水平、关联交易情况等。 | N53: √ | Q53: √ | S53: √ | T53: 线上管控-待建 | U53: 智慧共享财务平台 | V53: 1.预算执行分析相关资料 | W53: 各级单位-财务资产部-预算管理、各级单位-财务资产部-成本管理 | X53: 每年 | Y53: 抽查 | AA53: 每年 | AB53: 抽查 | AD53: 预算执行精准性监督场景 | AE53: 每月 | AF53: 全查 | AH53: 是 | AI53: 是 | AJ53: 《国家电网有限公司全面预算管理办法》（国网（财/2）3752026）第三十六条、第四十条-第四十三条、《国家电网有限公司成本管理办法》（国网（财2）347-2025）第三十六条-第三十七条 | AK53: 国网财务部
I54: 财务管理-26.预算执行情况分析-控制措施02 | J54: 加强预算执行情况分析结果应用。各级单位财务部门结合自身实际，将预算执行情况纳入绩效考核。 | N54: √ | Q54: √ | S54: √ | T54: 线下管控 | V54: 1.预算执行考核相关资料 | W54: 各级单位-财务资产部-预算管理、各级单位-财务资产部-成本管理 | X54: 每季度 | Y54: 抽查 | AA54: 每季度 | AB54: 抽查 | AI54: 是 | AJ54: 《国家电网有限公司全面预算管理办法》（国网（财/2）375-2026）第三十六条、第四十条-第四十三条；《国家电网有限公司成本管理办法》（国网（财2）347-2025）第三十六条-第三十七条 | AK54: 国网财务部
E55: 成本预算执行管控不严，导致成本列支不规范、超预算列支等问题，包括： （1）无预算、超预算列支成本，导致预算管控失效，引发资金管控风险； （2）预算单控费用执行不严，“三公”经费、会议费等重点支出预算未实施单项控制，引发重点费用管控失效风险； （3）资本性支出与成本性支出未严格区分，导致会计核算混乱，引发会计信息质量失真； （4）项目支出不规范，实际列支内容与预算安排不一致，引发项目资金滥用及会计信息失真风险； | F55: 成本性项目及资本性项目列支超年度预算：部分成本性项目及资本性项目在列支时，未及时履行调整流程，导致实际支出超出年度预算。 | G55: 27.各会计科目、项目预算系统编制及控制 | H55: 公司各会计科目、项目预算统一管理，严禁发生预算外支出。 | I55: 财务管理-27.各会计科目、项目预算系统编制及控制-控制措施01 | J55: 系统部署项目预算控制规则。国网及各二级单位财务部门根据项目可研批复金额，在智慧共享财务平台中对各类成本性、资本性项目、费用科目配置预算及控制规则，通过系统预警、规则强控，确保无预算不支出、有预算不超支。 | N55: √ | Q55: √ | T55: 线上管控-已建 | U55: 智慧共享财务平台 | V55: 1.业务预算需求审批表 2.项目可研评审批复文件 | W55: 各级单位-财务资产部-预算管理、各级单位-财务资产部-工程财务管理 | X55: 每年 | Y55: 抽查 | AA55: 每年 | AB55: 抽查 | AD55: 预算规则执行监督场景 | AE55: 每年 | AF55: 全查 | AH55: 是 | AI55: 是 | AJ55: 《国家电网有限公司全面预算管理办法》（国网（财/2）3752026）第三十五条 | AK55: 国网财务部
F56: 单项费用控制失效：对于“三公” 经费、会议费进行总额控制，未单独进行预算分解，无法进行单项控制。 | G56: 28.重点单项费用预算编制及控制 | H56: 重点费用单项列支规范，与预算下达指标保持一致。 | I56: 财务管理-28.重点单项费用预算编制及控制-控制措施01 | J56: 上级部署单控费用预算。国网及各二级单位财务部门在智慧共享财务平台中根据年度预算对“三公”经费、会议费等实施单项控制，由上级单位在系统中核定，各级单位如需调整需履行预算调整程序，确保重点费用预算能控、在控。 | N56: √ | Q56: √ | T56: 线上管控-已建 | U56: 智慧共享财务平台 | V56: 1.成本费用管理情况表 2.单项费用预算。 | W56: 各级单位-财务资产部-预算管理、各级单位-财务资产部-成本管理 | X56: 每年 | Y56: 抽查 | AA56: 每年 | AB56: 抽查 | AD56: 单项费用预算执行监督场景 | AE56: 每年 | AF56: 全查 | AH56: 是 | AI56: 是 | AJ56: 《国家电网有限公司全面预算管理办法》（国网（财/2）3752026）第三十五条 | AK56: 国网财务部
F57: 项目立项管理不规范：项目可研审核不严格，例如，存在通过生产大修项目购买电脑、隔离开关等固定资产的情况。 | G57: 29.项目可研经济性、财务合规性检查 | H57: 项目立项规范合规，项目支出性质准确。 | I57: 财务管理-29.项目可研经济性、财务合规性检查-控制措施01 | J57: 开展项目支出性质检查。各级单位财务部门协同各级业务归口管理部门、各级经研院所组织开展项目可研经济性、财务合规性评审，检查立项依据是否充分、立项类别是否准确，重点关注：报告中应包含维修资产的设备编码、资产原值等关键信息，检查项目金额是否超过维修资产原值的50%，物料清单中是否包含固定资产目录中设备。 | N57: √ | Q57: √ | T57: 线下管控 | V57: 1.项目可研报告或建议书 2.储备项目明细 | W57: 各级单位-财务资产部-工程财务管理、各级单位-财务资产部-成本管理 | X57: 每年 | Y57: 抽查 | AA57: 每年 | AB57: 抽查 | AH57: 是 | AI57: 是 | AJ57: 国家电网有限公司全面预算管理办法》（国网（财/2）375-2026）第二十四条；《国家电网有限公司财务支出可研经济性与财务合规性评价工作指引（2025）》（财预〔2025〕27号）第一章4 | AK57: 国网财务部
F58: 项目结算不准确：多结算施工费用；虚列项目，跨期结算项目费用，结算依据不充分。 | G58: 30.项目预算执行控制 | H58: 项目支出规范，实际列支内容与预算安排保持一致。 | I58: 财务管理-30.项目预算执行控制-控制措施01 | J58: 开展项目实施内容检查。各级单位业务部门在项目完工后，应组织专业机构出具项目结算报告（资料），并对项目支出内容进行检查，重点关注：施工费结算方式是否与合同一致、是否采购可研资料之外的物料、实施内容是否变更，如有变更是否履行变更程序等。各级单位财务部门在智慧共享财务平台中对项目支出合同、发票、上传的材料，参考项目可研资料中项目实施内容，从完整性、规范性、合理性等方面进行线上审核，确保项目支出规范。 | M58: √ | N58: √ | Q58: √ | T58: 线上管控-已建 | U58: 智慧共享财务平台 | V58: 1.项目结算报告（资料） 2.项目支出报账材料 3.项目可研资料 | W58: 各级单位-业务部门-经办人员、各级单位-财务资产部-成本管理、各级单位-财务资产部-工程财务管理 | X58: 每年 | Y58: 抽查 | AA58: 每年 | AB58: 抽查 | AD58: 项目预算执行监督场景 | AE58: 每年 | AF58: 全查 | AH58: 是 | AI58: 是 | AJ58: 《国家电网有限公司全面预算管理办法》（国网（财/2）3752026）第三十四条 | AK58: 国网财务部
A59: 财务管理 | B59: 三、预算管理 | C59: 会计信息真实完整、资金资产安全、税务合规 | D59: 执行控制 （事中） | E59: （5）成本开支内容不符合输配电成本监审要求，影响输配电价格核定，引发监管合规风险。 | F59: 监管单位成本预算安排规模与监审要求不符：材料修理费、其他运营费用安排严重偏离成本监审费率，与非监管单位关联交易利润率超10%，监管业务中列支广告宣传费（不含停电故障信息公告、电力安全保护宣传、电力设备安全警示等）等。 | G59: 31.预算编制与输配电成本一致性审核 | H59: 成本开支符合输配电成本监审要求。 | I59: 财务管理-31.预算编制与输配电成本一致性审核-控制措施01 | J59: 强化核价规则约束。市公司财务部门根据成本监审及核价规则，设置预警规则，监控成本执行情况，重点关注：材料修理费、其他运营费用（含管理类费用）费率是否与核价费率严重偏离，引发成本核减或费率下滑风险；各级单位对广告宣传费、研究开发费等特殊敏感会计科目严格审核，确保相关成本支出符合成本监审要求。 | N59: √ | Q59: √ | T59: 线上管控-待建 | U59: 智慧共享财务平台 | V59: 1.成本支出相关资料 | W59: 市公司-财务资产部-电价管理处输配电价管理、市公司-财务资产部-预算管理处预算管理、各级单位-财务资产部-成本管理 | X59: 每年 | Y59: 抽查 | AA59: 每年 | AB59: 抽查 | AH59: 是 | AI59: 是 | AJ59: 《国家电网有限公司全面预算管理办法》（国网（财/2）3752026）第二十二条、第三十五条 | AK59: 国网财务部
B60: 四、会计核算 | C60: 会计信息真实完整、资金资产安全 | D60: 收入核算管理 | E60: 收入真实性核查不足、收入确认不完整、不准确，提前、延后或跨期确认收入，未严格核查“三流”一致性、“两头在外”购销业务，导致收入核算不准确、经营成果不可靠、资金与合规风险。 | F60: 5.收入确认不完整、不准确：业务部门未及时提交履约进度等结算资料、资料不完整，导致收入确认不完整、不准确；业务部门违规开展虚假贸易，伪造收入结算资料，导致会计信息失真；财务部门未准确区分总额法和净额法，导致收入核算不准确。 | G60: 32.售电收入管控 | H60: 严格审核营财数据一致性，确保售电收入确认完整。 | I60: 财务管理-32.售电收入管控-控制措施01 | J60: 营财数据一致性控制。每月初，各级单位财务人员对售电收入财务汇总账与营销账务的一致性进行全面核对，发现营财差异，需及时查明原因，并进行营财联动调整，严禁财务手工调整。 | M60: √ | Q60: √ | S60: √ | T60: 线上管控-待建 | U60: 智慧共享财务平台、营销2.0系统 | V60: 1.营销传入电费凭证 2.营财对账相关资料 | W60: 各级单位-营销部-电费管理、各级单位-财务资产部-收入/价格管理 | X60: 每季度 | Y60: 抽查 | AA60: 每季度 | AB60: 抽查 | AD60: 营财数据一致性监督场景 | AE60: 每月 | AF60: 全查 | AH60: 是 | AI60: 是 | AJ60: 《关于明确营销0系统与智慧共享财务平台系统集成有关问题的意见》（营销营业〔2023〕86号）二、高频业务处理流程标准化 | AK60: 国网财务部
I61: 财务管理-32.售电收入管控-控制措施02 | J61: 售电业务营财集成控制。国网营销部、国网财务部根据业务场景，共同制定营财集成规则并在线固化。各级单位财务人员在月度结账前，全面排查非集成售电收入凭证，对异常情况及时查明原因，规范冲销调整。 | M61: √ | Q61: √ | T61: 线上管控-待建 | U61: 智慧共享财务平台 | V61: 1.营财集成凭证或非集成凭证 | W61: 国网财务部-总账管理人员、国网财务部-电费电价管理人员、各级单位-财务资产部-总账报表管理、收入/价格管理 | X61: 每季度 | Y61: 抽查 | AA61: 每季度 | AB61: 抽查 | AD61: 售电业务营财集成控制监督场景 | AE61: 每月 | AF61: 全查 | AH61: 是 | AI61: 是 | AJ61: 《关于明确营销0系统与智慧共享财务平台系统集成有关问题的意见》（营销营业〔2023〕86号）二、高频业务处理流程标准化 《国家电网有限公司2025年度财务决算审计工作指引》 | AK61: 国网财务部
G62: 33.非电收入管控 | H62: 严格审核收入真实性、准确性、完整性， 准确反映经营成果。 | I62: 财务管理-33.非电收入管控-控制措施01 | J62: 收入真实性监督。各级单位财务人员在收入报账审核时，通过检查合同、发票、出库单、物流单、签收单、完工验收单等，识别虚构业务情形，对收入真实性进行监督。 | M62: √ | O62: √ | Q62: √ | T62: 线上管控-待建 | U62: 智慧共享财务平台 | V62: 1.收入确认资料 | W62: 各级单位-财务资产部-收入/价格管理 | X62: 每月 | Y62: 抽查 | AA62: 每月 | AB62: 抽查 | AD62: 收入真实性监督场景 | AE62: 每月 | AF62: 抽查 | AH62: 是 | AI62: 是 | AJ62: 《国家电网有限公司会计核算办法》（国家电网企管〔2026〕101号）第四章、第十九章至第二十三章 《国家电网有限公司会计基础管理办法》（国家电网企管〔2019〕132号）附则一、收入业务 3.《会计基础工作规范》（征求意见稿）第五章 第三十九条 4.《国家电网有限公司2025年度财务决算审计工作指引》 | AK62: 国网财务部
I63: 财务管理-33.非电收入管控-控制措施02 | J63: 收入完整性监督。各级单位财务人员通过检查收款记录、结算单据以及业务系统中销售发货、服务进度、施工进度等记录，对收入报账的完整性进行监督。 | M63: √ | Q63: √ | T63: 线上管控-待建 | U63: 智慧共享财务平台 | V63: 1.收入确认资料 | W63: 各级单位-财务资产部-收入/价格管理 | X63: 每月 | Y63: 抽查 | AA63: 每月 | AB63: 抽查 | AD63: 收入完整性监督场景 | AE63: 每月 | AF63: 抽查 | AH63: 是 | AI63: 是 | AJ63: 《国家电网有限公司会计核算办法》（国家电网企管〔2026〕101号）第四章、第十九章至第二十三章 《国家电网有限公司会计基础管理办法》（国家电网企管〔2019〕132号）附则一、收入业务 3.《会计基础工作规范》（征求意见稿）第五章 第三十九条 4.《国家电网有限公司2025年度财务决算审计工作指引》 | AK63: 国网财务部
I64: 财务管理-33.非电收入管控-控制措施03 | J64: 收入确认准确性控制。各级单位财务人员根据合同、物流仓储记录等，准确判断合同中承担的主要责任或代理责任，规范选取总额法或净额法核算。国网公司细化产品服务分类，在线固化各类型业务核算规则，实施收入确认准确性在线、精准控制。 | M64: √ | Q64: √ | T64: 线上管控-待建 | U64: 智慧共享财务平台 | V64: 1.收入确认资料 | W64: 国网财务部-总账管理人员、各级单位-财务资产部-收入/价格管理 | X64: 每月 | Y64: 抽查 | AA64: 每月 | AB64: 抽查 | AD64: 收入确认准确性监督场景 | AE64: 每月 | AF64: 抽查 | AH64: 是 | AI64: 是 | AJ64: 《国家电网有限公司关于强化“三道防线”协同管控切实防范贸易业务风险的通知》（国家电网财〔2024〕406号） 《国家电网有限公司2025年度财务决算审计工作指引》 | AK64: 国网财务部
A65: 财务管理 | B65: 四、会计核算 | C65: 会计信息真实完整、资金资产安全 | D65: 收入核算管理 | E65: 收入真实性核查不足、收入确认不完整、不准确，提前、延后或跨期确认收入，未严格核查“三流”一致性、“两头在外”购销业务，导致收入核算不准确、经营成果不可靠、资金与合规风险。 | F65: 5.收入确认不完整、不准确：业务部门未及时提交履约进度等结算资料、资料不完整，导致收入确认不完整、不准确；业务部门违规开展虚假贸易，伪造收入结算资料，导致会计信息失真；财务部门未准确区分总额法和净额法，导致收入核算不准确。 | G65: 33.非电收入管控 | H65: 严格审核收入真实性、准确性、完整性， 准确反映经营成果。 | I65: 财务管理-33.非电收入管控-控制措施04 | J65: 资金流、发票流、账务流一致性监督。各级单位财务人员严格审核业务执行中与上下游企业资金收付和发票开具情况，对按净额法核算的业务，原则上不得介入上下游资金流、发票流，避免垫付资金风险。发现“三流”不一致带来的资金垫付风险，应停止办理报账，并及时向单位负责人报告。 | M65: √ | P65: √ | Q65: √ | T65: 线上管控-待建 | U65: 智慧共享财务平台 | V65: 1.合同 2.银行回单 3.发票 | W65: 各级单位-财务资产部-收入/价格管理 | X65: 每月 | Y65: 抽查 | AA65: 每年 | AB65: 抽查 | AD65: “三流”一致性监督场景 | AE65: 每月 | AF65: 抽查 | AH65: 是 | AI65: 是 | AJ65: 《国家电网有限公司关于强化“三道防线”协同管控切实防范贸易业务风险的通知》（国家电网财〔2024〕406号） 《国家电网有限公司2025年度财务决算审计工作指引》 | AK65: 国网财务部
I66: 财务管理-33.非电收入管控-控制措施05 | J66: 贸易业务规范性监督。对于“两头在外”购销业务，各级单位财务人员严格审核业务审批、上下游关联关系、仓储物流、毛利率水平等情况，发现异常情况及时截停业务。对于业务部门提交垫付资金、大额预付、往来款项互抵等异常事项，财务部门要向本单位主要负责同志和贸易业务分管领导报告，启动业务真实性合规性调查，并暂停资金支付；经调查认定为违规贸易业务的，要逐级上报至国网财务部，并终止支付、督促业务部门停止业务。 | M66: √ | P66: √ | Q66: √ | T66: 线上管控-待建 | U66: 智慧共享财务平台 | V66: 1.业务审批记录 2.上下游关联关系核查资料 3.仓储物流单 4.毛利率分析记录 | W66: 各级单位-财务资产部-收入/价格管理 | X66: 每季度 | Y66: 抽查 | AA66: 每年 | AB66: 抽查 | AD66: 贸易业务规范性监督场景 | AE66: 每季度 | AF66: 抽查 | AH66: 是 | AI66: 是 | AJ66: 《国家电网有限公司关于强化“三道防线”协同管控切实防范贸易业务风险的通知》（国家电网财〔2024〕406号） 《国家电网有限公司2025年度财务决算审计工作指引》 | AK66: 国网财务部
C67: 会计信息真实完整、资金资产安全 | D67: 成本费用核算管理 | E67: 成本费用列支不真实、不完整、不规范，造成利润不实、资金资产流失。 | F67: 成本费用不真实、不完整、不规范：成本结转、成本记账无依据或依据不充分，年末发生大额成本入账但与实际履约进度不符，超标准、超预算报销差旅费、会议费等，收入成本不匹配、项目毛利率异常，影响会计信息真实性、准确性。 | G67: 34.成本真实性管控 | H67: 经济业务成本费用真实发生、有据可查。 | I67: 财务管理-34.成本真实性管控-控制措施01 | J67: 成本费用真实性监督。各级单位财务人员在成本报账审核时，通过检查采购或服务合同、发票以及入库验收、工程施工、劳务考勤等佐证资料，核查实际履约情况，对成本费用真实性进行监督。各业务部门并对原始凭证所记载经济业务事项的真实性、有效性负责。 | M67: √ | O67: √ | Q67: √ | T67: 线上管控-待建 | U67: 智慧共享财务平台 | V67: 1.合同 2.发票 3.成本报销相关资料 | W67: 各级单位-财务资产部-成本管理 | X67: 每月 | Y67: 全查 | AA67: 每季度 | AB67: 全查 | AD67: 成本费用报账真实性监督场景 | AE67: 每月 | AF67: 全查 | AH67: 是 | AI67: 是 | AJ67: 《国家电网有限公司会计基础管理办法》（国家电网企管〔2019〕132号）第二章 职责分工 第八条、第四章 核算与报告第五十四条、附则二、成本费用业务 《国家电网有限公司2025年度财务决算审计工作指引》 | AK67: 国网财务部
G68: 35.成本合规性、完整性管控 | H68: 经济业务成本费用报账规范、完整，与公司经营相关、符合制度要求。 | I68: 财务管理-35.成本合规性、完整性管控-控制措施01 | J68: 成本费用合规性监督。国网财务部会同各部门、各级单位，将“三公”经费等重点费用纳入预算事前管控与报销严格审核；各级单位财务人员在成本报账审核时，对照公司制度要求检查成本费用超标准、超范围等情况，对成本费用合规性进行监督。 | N68: √ | Q68: √ | T68: 线上管控-待建 | U68: 智慧共享财务平台、国网商旅 | V68: 1.报账附件 | W68: 各级单位-财务资产部-成本管理 | X68: 每月 | Y68: 全查 | AA68: 每季度 | AB68: 全查 | AD68: 成本费用报账合规性、完整性监督场景 | AE68: 每月 | AF68: 全查 | AH68: 是 | AI68: 是 | AJ68: 《国家电网有限公司会计基础管理办法》（国家电网企管〔2019〕132号）第二章 第八条、第四章 第五十四条、附则二、成本费用业务 | AK68: 国网财务部
I69: 财务管理-35.成本合规性、完整性管控-控制措施02 | J69: 成本费用完整性监督。各级单位财务人员通过检查付款记录、结算单据、施工进度月度工程报量表等，对成本报账的完整性进行监督。 | M69: √ | Q69: √ | T69: 线上管控-待建 | U69: 智慧共享财务平台 | V69: 1.报账附件 | W69: 各级单位-财务资产部-成本管理 | X69: 每月 | Y69: 全查 | AA69: 每季度 | AB69: 全查 | AD69: 成本费用报账合规性、完整性监督场景 | AE69: 每月 | AF69: 全查 | AH69: 是 | AI69: 是 | AJ69: 《国家电网有限公司会计基础管理办法》（国家电网企管〔2019〕132号）第二章 第八条、第四章 第五十四条、附则二、成本费用业务 | AK69: 国网财务部
G70: 36.收入成本匹配性管控 | H70: 收入确认时点、规模与成本匹配，准确反映公司经营成果。 | I70: 财务管理-36.收入成本匹配性管控-控制措施01 | J70: 收入成本匹配性监督。各级单位财务人员通过检查收发货记录、服务履约记录、项目毛利率以及账面合同履约成本、合同负债、往来款项等挂账情况，动态监控合同、项目等收入成本匹配性，及时向业务部门发出预警督办，确保收入成本动态匹配、反映准确。 | M70: √ | O70: √ | Q70: √ | T70: 线上管控-待建 | U70: 智慧共享财务平台 | V70: 1.合同 2.发票 3.其他报销相关资料 | W70: 各级单位-财务资产部-收入/价格管理、各级单位-财务资产部-成本管理 | X70: 每月 | Y70: 全查 | AA70: 每季度 | AB70: 全查 | AD70: 收入成本匹配性核查场景 | AE70: 每月 | AF70: 全查 | AH70: 是 | AI70: 是 | AJ70: 《国家电网有限公司会计核算办法》（国家电网企管〔2026〕101号）第十九章 工程施工业务第二节 项目建设期 《国家电网有限公司2025年度财务决算审计工作指引》 | AK70: 国网财务部
A71: 财务管理 | B71: 四、会计核算 | C71: 会计信息真实完整、资金资产安全 | D71: 往来会计管理 | E71: 往来客商使用不规范，通过一次性（过渡）客商无依据暂估收入成本，导致往来信息不准确，存在人为调节利润风险。 | F71: 挂账对象不规范：将可对应至具体客户或供应商的往来款项挂账至一次性（过渡）客商。 | G71: 37.往来挂账规范性管控 | H71: 规范往来客商使用，除特殊情形外不使用一次性（过渡）客商。 | I71: 财务管理-37.往来挂账规范性管控-控制措施01 | J71: 往来挂账规范性控制。各级单位财务人员根据具体业务事项，将往来款项规范挂账至具体客户或供应商。除总部统一明确的特殊情形外，不得挂账至一次性（过渡）客商。 | M71: √ | Q71: √ | T71: 线上管控-待建 | U71: 智慧共享财务平台 | V71: 1.一次性（过渡）客商标准场景清单 | W71: 各级单位-财务资产部-会计核算管理 | X71: 每季度 | Y71: 抽查 | AA71: 每季度 | AB71: 抽查 | AD71: 往来挂账规范性监督场景 | AE71: 每季度 | AF71: 全查 | AH71: 是 | AI71: 是 | AJ71: 《国家电网有限公司会计基础管理办法》（国家电网企管〔2019〕132号）第四章 第二节 第四十四条 《国家电网有限公司2025年度财务决算审计工作指引》 3.《国家电网有限公司会计核算办法》（国家电网企管〔2026〕101号）第二章 | AK71: 国网财务部
E72: 往来款项清账不及时，债权债务底数不清，易形成呆账、坏账，造成资金损失风险。 | F72: 往来款项清账不及时不规范：往来款项清账不及时、账龄不准确，未及时识别收付款风险，导致坏账计提错误或资金损失。 | G72: 38.往来清账及时性管控 | H72: 及时、规范开展往来清账，确保往来款项余额和账龄准确。 | I72: 财务管理-38.往来清账及时性管控-管控措施01 | J72: 往来清账及时性控制。各级单位财务人员动态监测智慧共享财务平台往来款项清账情况，严格规范清账，避免错清、多清、漏清，确保台账数据准确；对特殊情况产生的应清未清事项，及时查明原因、规范处理，确保日清日结。 | P72: √ | Q72: √ | T72: 线上管控-已建 | U72: 智慧共享财务平台 | V72: 1.往来标签设置台账 2.应清未清账记录 | W72: 各级单位-财务资产部-会计核算管理 | X72: 每月 | Y72: 全查 | AA72: 每月 | AB72: 全查 | AD72: 往来款项清账及时性监督场景 | AE72: 每月 | AF72: 全查 | AH72: 是 | AI72: 是 | AJ72: 《国家电网有限公司会计基础管理办法》（国家电网企管〔2019〕132号）第四章 第六十二条 《国家电网有限公司2025年度财务决算审计工作指引》 | AK72: 国网财务部
E73: 往来款项对账不及时，债权债务底数不清，易造成资金损失风险。 | F73: 往来款项对账不规范：应付款项对账不准确，导致重复付款、超额付款，造成资金损失；对账流于形式，未发现往来款项错收、错付、漏记账、重复记账问题，产生资金挪用、往来舞弊风险。 | G73: 39.往来对账规范性管控 | H73: 规范开展往来对账，确保往来款项余额准确、账实相符。 | I73: 财务管理-39.往来对账规范性管控-管控措施01 | J73: 往来对账规范性控制。对账龄1年以上、逾期、债务人经营异常或单一客商挂账金额重大的往来款项，各级单位要会同会计师事务所，通过询证函等书面方式，对上年末挂账余额进行对账确认。函证结果不一致的，在决算中查明原因，规范调整账务。 | Q73: √ | S73: √ | T73: 线下管控 | V73: 1.询证函 2.往来台账查询（明细） | W73: 各级单位-财务资产部-会计核算管理 | X73: 每年 | Y73: 全查 | AA73: 每年 | AB73: 全查 | AH73: 是 | AI73: 是 | AJ73: 《国家电网有限公司会计基础管理办法》（国家电网企管〔2019〕132号）第四章 第六十二条 《国家电网有限公司2025年度财务决算审计工作指引》 | AK73: 国网财务部
E74: 应收款项回收不及时、长期挂账，造成资金占用、坏账损失风险。应付款项支付不及时，导致合同违约、信用受损，产生舆情及合规风险。 | F74: 债权债务清理不及时：应收款项催收不及时、回款周期长，资金周转压力大，增加坏账损失风险；应付款项长期挂账未清理，容易引发合同与法律纠纷。 | G74: 40.长期挂账款项管理 | H74: 建立长期挂账款项清理机制，避免长期挂账、逾期挂账。 | I74: 财务管理-40.长期挂账款项管理-控制措施01 | J74: 往来款项收付及时性监督。各级单位业务经办人员挂票时在付款信息中的到期日处填写合同约定的支付日期，由各级单位财务部审核，在合同约定的付款节点前，及时向业务部门经办人员发送付款提醒。 | Q74: √ | S74: √ | T74: 线上管控-待建 | U74: 智慧共享财务平台、数字化法治企业建设平台、ECP系统（国家电网新一代电子商务平台） | V74: 1.往来标签设置台账 | W74: 各级单位-财务资产部-会计核算管理 | X74: 每月 | Y74: 抽查 | AA74: 每季度 | AB74: 抽查 | AD74: 往来款项收付及时性监督场景 | AE74: 每月 | AF74: 全查 | AH74: 是 | AI74: 是 | AJ74: 《国家电网有限公司会计基础管理办法》（国家电网企管〔2019〕132号）第四章 第六十二条 | AK74: 国网财务部
I75: 财务管理-40.长期挂账款项管理-控制措施02 | J75: 往来款项风险监测预警。各级单位财务部门对长账龄、逾期、债务人经营异常等往来款项，按月向业务部门在线发送往来状态和风险预警，加强过程管控。 | Q75: √ | S75: √ | T75: 线上管控-待建 | U75: 智慧共享财务平台 | V75: 1.往来标签设置台账 | W75: 各级单位-财务资产部-会计核算管理 | X75: 每月 | Y75: 抽查 | AA75: 每季度 | AB75: 抽查 | AD75: 往来款项风险监测预警监督场景 | AE75: 每月 | AF75: 全查 | AH75: 是 | AI75: 是 | AJ75: 《国家电网有限公司会计基础管理办法》（国家电网企管〔2019〕132号）第四章 第六十二条 《国家电网有限公司2025年度财务决算审计工作指引》 | AK75: 国网财务部
A76: 财务管理 | B76: 四、会计核算 | C76: 会计信息真实完整、资金资产安全 | D76: 往来会计管理 | E76: 坏账准备计提不及时、不准确，影响资产计量真实性，导致会计信息质量受损；往来款项核销不规范，导致资产流失及合规风险。 | F76: 坏账计提不准确、往来款项核销不规范：坏账计提未执行公司统一政策，高风险债务人应收款项未按单项认定计提坏账，导致坏账计提金额不准确；往来款项核销依据不充分、审批程序不合规，违规核销损害公司利益。 | G76: 41.坏账准备及往来款项处置管理 | H76: 统一坏账计提政策，确保坏账计提金额准确；严格清查核实往来款项无法收付情况，规范履行核销程序。 | I76: 财务管理-41.坏账准备及往来款项处置管理-控制措施01 | J76: 应收款项坏账计提准确性控制。对组合认定款项，国网公司统一在线设置各类应收款项组合计提比例；各级单位财务人员动态、在线监测应收款项账龄准确性，确保自动、准确计提；对个别认定款项，各级单位财务人员在线跟踪监测长账龄、逾期、债务人经营异常等款项，组织业务部门及时评估回收风险，回收风险较大的，按单项认定足额计提坏账。 | Q76: √ | T76: 线上管控-已建 | U76: 智慧共享财务平台 | V76: 1.坏账准备计提（转回）内部审批单等相关资料 | W76: 国网财务部-总账管理人员、各级单位-财务资产部-会计核算管理 | X76: 每年 | Y76: 抽查 | AA76: 每年 | AB76: 抽查 | AD76: 坏账准备计提准确性监督场景 | AE76: 每月 | AF76: 全查 | AH76: 是 | AI76: 是 | AJ76: 《国家电网有限公司会计基础管理办法》（国家电网企管〔2019〕132号）第四章 第六十二条、第七章 附则三、资产业务（三）坏账准备 《国家电网有限公司会计核算办法》（国家电网企管〔2026〕101号）第二章 第一节 3.《国家电网有限公司2025年度财务决算审计工作指引》 | AK76: 国网财务部
I77: 财务管理-41.坏账准备及往来款项处置管理-控制措施02 | J77: 往来款项核销规范性控制。对确实无法收回的应收款项或无需支付的应付款项，各级单位财务人员严格审核业务部门提供的企业注销、法院判决裁定等佐证，会同业务部门规范履行内部决策、中介机构鉴证等程序后，进行账销案存处理。 | L77: √ | Q77: √ | T77: 线下管控 | V77: 1.应收款项核销佐证依据 2.应付款项核销佐证依据 3.内部决策文件 4.中介机构鉴证报告（依据会计核算办法2026版相应调整） | W77: 各级单位-财务资产部-会计核算管理 | X77: 每年 | Y77: 抽查 | AA77: 每年 | AB77: 抽查 | AH77: 是 | AI77: 是 | AJ77: 《国家电网有限公司会计基础管理办法》（国家电网企管〔2019〕132号）第四章 第六十二条、第七章 附则三、资产业务（三）坏账准备 《国家电网有限公司会计核算办法》（国家电网企管〔2026〕101号）第二章 债权债务第一节 债权管理、第二节 债务管理 3.《国家电网有限公司2025年度财务决算审计工作指引》 | AK77: 国网财务部
B78: 五、税务管理 | C78: 税务合规 | D78: 税基管理 | E78: 计税依据不完整、不准确，税收优惠政策适用不当等情况，导致应纳税所得额、应纳税额计算错误，税费核算失真，增加税务检查风险和企业税负。 | F78: 1.未按纳税义务发生时间及时确认应税所得；2.发生的成本费用、取得进项税发票，不符合税法规定，无法税前扣除或抵扣进项税；3.房产、土地、印花等财产行为税的计税依据不完整、不准确；4.税收优惠政策适用条件、程序或备查资料不合规等。导致税款少缴、晚缴问题，存在税务检查及产生滞纳金风险。 | G78: 42.税基溯源管理控制 | H78: 计税依据完整准确、合法合规使用税收优惠政策、准确计算应纳税所得额和应纳税额。 | I78: 财务管理-42.税基溯源管理控制-控制措施01 | J78: 针对增值税，应完整溯源业务活动，识别资产无偿划转等应税交易行为，规范确认应税项目、适用税率及纳税义务发生时点，合规开具和收取发票，准确计算应纳税额。合理确定计税方式与预征率（额），依法享受加计抵减等税收优惠政策，及时办理留抵退税业务。 | M78: √ | Q78: √ | T78: 线上管控-待建 | U78: 智慧共享财务平台 | V78: 1.发票 2.通用报账单 3.进项税凭证 | W78: 各级单位-业务部门-经办人员、各级单位-财务资产部-税金管理 | X78: 每月 | Y78: 全查 | AA78: 每年 | AB78: 抽查 | AH78: 是 | AI78: 是 | AJ78: 《国家电网有限公司税务管理办法》（国网（财/2）2022026）第四章第十八条 | AK78: 国网财务部
I79: 财务管理-42.税基溯源管理控制-控制措施02 | J79: 针对企业所得税，应完整溯源业务活动，及时规范确认收入、成本、资产、负债等，明确各类税会差异事项，识别永久性与暂时性差异，建立台账并滚动跟进递延事项的处理。在业务源头前置税收优惠执行标准，强化过程管控，依法享受研发费用加计扣除、“三免三减半”、固定资产一次性扣除、专用设备抵减等税收优惠政策。企业改制重组、资产划转要充分考虑特殊性税务处理的适用情形，符合税收优惠政策的，依法办理减免税申报。 | M79: √ | Q79: √ | T79: 线上管控-待建 | U79: 智慧共享财务平台 | V79: 1.企业所得税汇算清缴申报表 2.税会差异台账 | W79: 各级单位-财务资产部-税金管理 | X79: 每年 | Y79: 全查 | AA79: 每年 | AB79: 抽查 | AH79: 是 | AI79: 是 | AJ79: 《国家电网有限公司税务管理办法》（国网（财/2）2022026）第四章第十九条 | AK79: 国网财务部
I80: 财务管理-42.税基溯源管理控制-控制措施03 | J80: 针对其他税种，应建立完整准确、信息一致的计税台账，及时更新涉税信息，调整计税依据与税率标准，确保各项涉税业务及时准确缴纳各项税费。 | M80: √ | Q80: √ | T80: 线上管控-已建 | U80: 智慧共享财务平台 | V80: 1.各项税费的税基台账 | W80: 各级单位-财务资产部-税金管理 | X80: 每月 | Y80: 全查 | AA80: 每季度 | AB80: 抽查 | AH80: 是 | AI80: 是 | AJ80: 《国家电网有限公司税务管理办法》（国网（财/2）2022026）第四章第二十条至第二十六条 | AK80: 国网财务部
A81: 财务管理 | B81: 五、税务管理 | C81: 税务合规 | D81: 发票管理 | E81: 发票开具金额错误、票面信息不规范；取得进项发票不合规，无法抵扣；进项发票认证不及时、不完整。 | F81: 1.未按实际应税业务开具增值税专用发票，引发税务检查和处罚风险；2.取得进项发票不规范，导致进项税额不应抵扣，引发税务检查风险，同时增加税负；3.增值税专用发票认证不及时，进项税额未及时抵扣，造成账务与申报表差异，增加税负。 | G81: 43.发票合规管理控制 | H81: 开具发票税率、税项符合税法规定，金额、税额准确；取得进项发票票面信息符合税法规定、与业务实质一致，当期勾选认证的进项发票税额与账面入账税额保持一致。 | I81: 财务管理-43.发票合规管理控制-控制措施01 | J81: 在发票开具时，系统自动校验税率税项与业务事项的一致性，并与业务单据核对开出发票金额的一致性。 | K81: √ | M81: √ | T81: 线上管控-已建 | U81: 智慧共享财务平台、营销2.0系统 | V81: 1.发票、电费发行数据 | W81: 各级单位-业务部门-经办人员、各级单位-财务资产部-税金管理 | X81: 每月 | Y81: 全查 | AA81: 每年 | AB81: 抽查 | AH81: 是 | AI81: 是 | AJ81: 《国家电网有限公司税务管理办法》（国家电网财〔2026〕202号）第五章 | AK81: 国网财务部
I82: 财务管理-43.发票合规管理控制-控制措施02 | J82: 收到发票报销入账时，校验发票票面信息（购买方信息、销售方信息、货物/服务核心信息、金额）等信息与合同信息的一致性。 | M82: √ | O82: √ | Q82: √ | T82: 线上管控-已建 | U82: 智慧共享财务平台 | V82: 1.发票 2.合同 | W82: 各级单位-业务部门-经办人员、各级单位-财务资产部-税金管理、成本管理、工程财务管理、资产及产权管理、物资管理 | X82: 每月 | Y82: 全查 | AA82: 每年 | AB82: 抽查 | AH82: 是 | AI82: 是 | AJ82: 《国家电网有限公司税务管理办法》（国家电网财〔2026〕202号）第五章 | AK82: 国网财务部
I83: 财务管理-43.发票合规管理控制-控制措施03 | J83: 集体福利、个人消费、简易计税、免税、非应税交易及其他不得抵扣进项税项目，取得增值税专用发票的应转出进项税。 | M83: √ | O83: √ | Q83: √ | T83: 线下管控 | V83: 1.发票 2.合同 | W83: 各级单位-业务部门-经办人员、各级单位-财务资产部-税金管理、成本管理、工程财务管理、资产及产权管理、物资管理 | X83: 每月 | Y83: 全查 | AA83: 每年 | AB83: 抽查 | AH83: 是 | AI83: 是 | AJ83: 《国家电网有限公司税务管理办法》（国家电网财〔2026〕202号）第五章 | AK83: 国网财务部
I84: 财务管理-43.发票合规管理控制-控制措施04 | J84: 当月完成当月入账发票勾选认证，确保认证税额与入账税额一致。 | M84: √ | Q84: √ | T84: 线上管控-已建 | U84: 智慧共享财务平台 、电子税务局 | V84: 1.发票 2.账务数据 | W84: 各级单位-财务资产部-税金管理 | X84: 每月 | Y84: 全查 | AA84: 每年 | AB84: 抽查 | AH84: 是 | AI84: 是 | AJ84: 《国家电网有限公司税务管理办法》（国家电网财〔2026〕202号）第五章 | AK84: 国网财务部
C85: 税务合规 | D85: 纳税申报管理 | E85: 申报表填写错误、与账务数据不一致、未及时申报等情况，导致申报信息错误，多缴或少缴税款，产生滞纳金等风险。 | F85: 1.申报表数据与账务数据不一致；2.申报数据计算、填写错误；3.纳税申报表逾期未申报。 | G85: 44.合规纳税申报控制 | H85: 申报数据必须源自账务数据，申报表内、表间逻辑关系校验无误、税款计算无误，在税法规定的申报纳税期限内完成申报。 | I85: 财务管理-44.合规纳税申报控制-控制措施01 | J85: 税务申报表数据与与账务数据进行勾稽校验，同时申报表内与表间进行核验，确保逻辑关系无误、税金计算准确。 | M85: √ | Q85: √ | T85: 线上管控-待建 | U85: 智慧共享财务平台 、电子税务局 | V85: 1.账务数据 2.纳税申报表 | W85: 各级单位-财务资产部-税金管理 | X85: 每月 | Y85: 全查 | AA85: 每季度 | AB85: 抽查 | AH85: 是 | AI85: 是 | AJ85: 《国家电网有限公司税务管理办法》（国家电网财〔2026〕202号）第六章 | AK85: 国网财务部
I86: 财务管理-44.合规纳税申报控制-控制措施02 | J86: 税务申报建立日历提醒机制，在征期结束前3天需要税务管理专工进行进度确认，并向相关单位发送预警。 | Q86: √ | T86: 线上管控-待建 | U86: 智慧共享财务平台 | V86: 1.纳税申报表 | W86: 各级单位-财务资产部-税金管理 | X86: 每月 | Y86: 全查 | AA86: 每季度 | AB86: 抽查 | AH86: 是 | AI86: 是 | AJ86: 《国家电网有限公司税务管理办法》（国家电网财〔2026〕202号）第六章 | AK86: 国网财务部
B87: 六、资金活动 | C87: 资金资产安全 | D87: 账户使用-收入 | E87: 现金收入未及时缴存，易发生截留挪用、私设小金库等舞弊行为；滞留现金保管不当，易造成资金失窃盗用风险 | G87: 45.现金收费解缴控制 | H87: 规范现金收缴，加强留存资金保管，严防资金挪用、私设账外资金及被盗流失风险。 | I87: 财务管理-45.现金收费解缴控制-控制措施01 | J87: 各级单位收现人员应于收款当日缴存公司账户，解款单据应由经办人员部门或班组负责人审核后方可办理银行缴存，且需至少安排两人办理。对于无法当日缴存的零星现金，应及时存放于专用保险箱（柜）保管，于下一个工作日解缴银行。 | K87: √ | L87: √ | P87: √ | T87: 线下管控 | V87: 1.现金解款单 2.保险柜 | W87: 各级单位-网格化供电中心-营业班营业专责工、各级单位-网格化供电中心-营业班班长、各级单位-业务部门-经办人、部门负责人 | X87: 每月 | Y87: 全查 | AA87: 每月 | AB87: 全查 | AH87: 是 | AI87: 是 | AJ87: 《国家电网有限公司司库管理办法》（国网（财/2）3452023）第五章第七十六条 | AK87: 国网财务部
I88: 财务管理-45.现金收费解缴控制-控制措施02 | J88: 各级单位收现人员收取或留存现金当日进行现金盘点，做到日清日结，编制《现金盘点表》，经办人员经过监盘人、部门或班组负责人审核签字后，按月装订成册并归档。 | K88: √ | Q88: √ | T88: 线上管控-待建 | U88: 营销2.0系统 | V88: 1.现金盘点表 | W88: 各级单位-网格化供电中心-营业班营业专责工、各级单位-网格化供电中心-营业班班长、各级单位-业务部门-经办人、各级单位-业务部门-部门负责人 | X88: 每月 | Y88: 抽查 | AA88: 每年 | AB88: 抽查 | AH88: 是 | AI88: 是 | AJ88: 《国家电网有限公司司库管理办法》（国网（财/2）3452023）第五章第七十六条 | AK88: 国网财务部
I89: 财务管理-45.现金收费解缴控制-控制措施03 | J89: 各级单位收现人员所在部门负责人（或供电营业厅负责人）每月至少应现场监督盘点留存的现金一次，确保账实相符。 | M89: √ | Q89: √ | T89: 线下管控 | V89: 1.现金盘点表 | W89: 各级单位-网格化供电中心-营业班营业专责工、各级单位-业务部门-部门负责人 | X89: 每月 | Y89: 抽查 | AA89: 每月 | AB89: 抽查 | AH89: 是 | AI89: 是 | AJ89: 《国家电网有限公司司库管理办法》（国网（财/2）3452023）第五章第七十六条 | AK89: 国网财务部
I90: 财务管理-45.现金收费解缴控制-控制措施04 | J90: 各级单位财务部门对现金盘点情况进行抽查，核对账实一致性。 | Q90: √ | T90: 线上管控-待建 | U90: 智慧共享财务平台、营销2.0系统 | V90: 1.现金盘点表 | W90: 各级单位-财务资产部-资金管理 | X90: 每月 | Y90: 抽查 | AA90: 每月 | AB90: 抽查 | AH90: 是 | AI90: 是 | AJ90: 《国家电网有限公司司库管理办法》（国网（财/2）3452023）第五章第七十六条 | AK90: 国网财务部
I91: 财务管理-45.现金收费解缴控制-控制措施05 | J91: 各级单位营业场所配置视频监控设备与保险柜，现金存放区域安装防盗设施与报警系统，保障资金存放安全。 | M91: √ | T91: 线下管控 | V91: 1.保险柜 | W91: 各级单位-网格化供电中心-营业班班长、各级单位-业务部门-部门负责人 | X91: 每年 | Y91: 抽查 | AA91: 每年 | AB91: 抽查 | AH91: 是 | AI91: 是 | AJ91: 《国家电网有限公司司库管理办法》（国网（财/2）3452023）第五章第七十五条 | AK91: 国网财务部
A92: 财务管理 | B92: 六、资金活动 | C92: 资金资产安全 | D92: 账户使用-收入 | E92: 账户资金到账确认不及时，收入核算科目使用不规范，易造成会计核算失真，引发会计信息质量风险。 | G92: 46.账户资金到账确认控制 | H92: 按日开展资金流水清分，按类别规范界定资金归属，保障资金核算合规、账实一致。 | I92: 财务管理-46.收款结算合规性控制-控制措施01 | J92: 各级单位财务部门按日根据银行账户收款交易流水开展资金清分，严格落实收款分拣与款项归类内控要求，规范收款全流程操作：按业务类型（主营业务收入、其他业务收入、政府补助、其他应付款等）、会计科目（应收、预收等）、账户类型（贷款户、电费户等）、科目维度（服务款、质保金、商品款等）按现金流类型划分资金归属规范划分资金归属，保障资金清分合规、账实相符。 | M92: √ | P92: √ | Q92: √ | T92: 线上管控-已建 | U92: 智慧共享财务平台 | V92: 1.银行流水 2.收入业务类型勾对记录 3.收入确认凭证 | W92: 各级单位-业务部门-经办人员、 市公司-资金集约中心-收款省级管理人员、各级单位-财务资产部-收入/价格管理、各级单位-财务资产部-会计核算管理 | X92: 每月 | Y92: 全查 | AA92: 每年 | AB92: 全查 | AH92: 是 | AI92: 是 | AJ92: 《国家电网有限公司司库管理办法》（国网（财/2）3452023）第五章第七十三条、第八十二条 《国家电网有限公司会计基础管理办法》（国网（财/2）3502018）第四章第三十八条 | AK92: 国网财务部
E93: 未审慎甄别票据品类及信用等级，违规收取高风险与贴现受限票据，票据到期兑付管控不到位，易遭遇拒付拖欠，引发资金损失风险。 | G93: 47.应收票据可靠性、合规性管控 | H93: 加强票据收取、保管、贴现等环节的违约风险管理 | I93: 财务管理-47.应收票据可靠性、合规性管控-控制措施01 | J93: 各级单位财务部门票据管理人员执行票据收取标准，核验主体类型、承兑方资质及银行信用等级，拒收低信用等级票据。 | M93: √ | T93: 线上管控-待建 | U93: 智慧共享财务平台 | V93: 1.合同 2.票据收取系统截图 | W93: 各级单位-财务资产部-资金管理、各级单位-财务资产部-出纳管理、各级单位-财务资产部-主任、各级单位-业务部门-经办人员 | X93: 每月 | Y93: 全查 | AA93: 每月 | AB93: 全查 | AH93: 是 | AI93: 是 | AJ93: 《国家电网有限公司司库管理办法》（国网（财/2）3452023）第五章第一百〇三条 | AK93: 国网财务部
I94: 财务管理-47.应收票据可靠性、合规性管控-控制措施02 | J94: 各级单位财务部门票据管理人员收取银行承兑汇票时，须核验协议约定贴现利息由客户承担。对于不能实现贴现并由对方承担贴现利息的，须本单位主要负责人审签并报二级单位审批，履行分级审批程序。收票账户优先使用指定内部结算账户。 | L94: √ | O94: √ | T94: 线上管控-待建 | U94: 智慧共享财务平台 | V94: 1.合同 2.不收贴现息申请表 | W94: 各级单位-财务资产部-资金管理、各级单位-财务资产部-出纳管理、各级单位-财务资产部-主任 | X94: 每月 | Y94: 全查 | AA94: 每月 | AB94: 全查 | AH94: 是 | AI94: 是 | AJ94: 《国家电网有限公司司库管理办法》（国网（财/2）3452023）第五章第一百〇条、第一百〇三条、第一百〇五条 | AK94: 国网财务部
E95: 未审慎甄别票据品类及信用等级，违规收取高风险与贴现受限票据，票据到期兑付管控不到位，易遭遇拒付拖欠，引发资金损失风险。 | G95: 47.应收票据可靠性、合规性管控 | H95: 加强票据收取、保管、贴现等环节的违约风险管理 | I95: 财务管理-47.应收票据可靠性、合规性管控-控制措施03 | J95: 各级单位财务部门票据管理人员建立票据到期监控机制，跟踪未托收票据，及时确认到账，对异常情况查明处置，确保票据资金按期回笼。 | P95: √ | T95: 线上管控-待建 | U95: 智慧共享财务平台 | V95: 1.应收票据台账 2.银行流水、银行回单 | W95: 各级单位-财务资产部-资金管理 | X95: 每月 | Y95: 全查 | AA95: 每月 | AB95: 全查 | AH95: 是 | AI95: 是 | AJ95: 《国家电网有限公司司库管理办法》（国网（财/2）3452023）第五章第一百〇一条 | AK95: 国网财务部
I96: 财务管理-47.应收票据可靠性、合规性管控-控制措施04 | J96: 各级单位财务部门票据管理人员每月对票据进行盘点，确保票据账实相符。 | Q96: √ | T96: 线上管控-待建 | U96: 智慧共享财务平台 | V96: 1.票据盘点表 2.票据台账 | W96: 各级单位-财务资产部-资金管理、各级单位-财务资产部-主任 | X96: 每月 | Y96: 全查 | AA96: 每月 | AB96: 全查 | AH96: 是 | AI96: 是 | AJ96: 《国家电网有限公司司库管理办法》（国网（财/2）3452023）第五章第一百〇四条 | AK96: 国网财务部
C97: 资金资产安全 | D97: 账户使用-支付 | E97: 授权边界模糊、审批流于形式易引发资金挪用、超权限支付及管控失效的资金安全与合规风险。 | G97: 48.资金支付审批权限控制 | H97: 强化资金分级授权管控，规范授权范围、审批层级与责任边界，杜绝越权审批、超权限支付。 | I97: 财务管理-48.资金支付审批权限控制-控制措施01 | J97: 各级单位所有付款订单均应由业务部门发起，全程线上审批、严禁篡改。严禁无付款订单、原始凭据先行付款。资金集约中心不能主动发起对外付款业务。 | K97: √ | P97: √ | T97: 线上管控-已建 | U97: 智慧共享财务平台 | V97: 1.付款申请单、采购类报账单、通用报账单 | W97: 各级单位-业务部门-经办人、各级单位-业务部门-部门负责人 | X97: 每月 | Y97: 全查 | AA97: 每月 | AB97: 全查 | AH97: 是 | AI97: 是 | AJ97: 《国家电网有限公司司库管理办法》（国网（财/2）3452023）第五章第八十七条、第八十八条 | AK97: 国网财务部
I98: 财务管理-48.资金支付审批权限控制-控制措施02 | J98: 各级单位财务部门制定资金支付分级授权标准，将权限、额度与流程嵌入智慧共享财务平台实施刚性控制；支付按授权办理，全程留痕、可追溯。 | L98: √ | P98: √ | T98: 线上管控-已建 | U98: 智慧共享财务平台 | V98: 1.资金分级授权文件 2.资金支付审批单 | W98: 各级单位-财务资产部-主任 | X98: 每年 | Y98: 全查 | AA98: 每年 | AB98: 全查 | AH98: 是 | AI98: 是 | AJ98: 《国家电网有限公司司库管理办法》（国网（财/2）3452023）第五章第八十六条 | AK98: 国网财务部
E99: 传统结算台账未登记或登记不及时，未经事前审批，造成资金流失风险。 | G99: 49.传统结算事前审批控制 | H99: 从严管控传统结算方式支出，严格执行“先审批、后付款”，履行传统结算方式事前审批及台账登记。 | I99: 财务管理-49.传统结算事前审批控制-控制措施01 | J99: 各级单位对传统结算方式实行事前审批，核验使用范围与合规性。 | L99: √ | M99: √ | P99: √ | T99: 线上管控-已建 | U99: 智慧共享财务平台 | V99: 1.传统结算方式台账 | W99: 各级单位-财务资产部-主任 | X99: 每月 | Y99: 全查 | AA99: 每月 | AB99: 全查 | AH99: 是 | AI99: 是 | AJ99: 《国家电网有限公司司库管理办法》（国网（财/2）3452023）第五章第七十条 | AK99: 国网财务部
I100: 财务管理-49.传统结算事前审批控制-控制措施02 | J100: 各级单位当日完成传统结算业务台账登记，并按月报上级单位备案。 | L100: √ | M100: √ | T100: 线下管控 | V100: 1.传统结算方式台账登记表 | W100: 各级单位-业务部门-经办人员、各级单位-业务部门-部门负责人、各级单位-财务资产部-出纳管理、各级单位-财务资产部-资金管理、各级单位-财务资产部-主任 | X100: 每月 | Y100: 全查 | AA100: 每月 | AB100: 全查 | AH100: 是 | AI100: 是 | AJ100: 《国家电网有限公司司库管理办法》（国网（财/2）3452023）第五章第七十条 | AK100: 国网财务部
...

Sheet 预算
A2: 业 务 条 线 | B2: 业 务 领 域 | C2: 控 制 目 标 | D2: 业务流程步骤 | E2: 经营风险 | F2: 典型问题 | G2: 关键控制点 | H2: 控制要求 | I2: 控制措施 编号 | J2: 控制措施 | K2: 控制措施分类 | T2: 控制方式 | U2: 控制系统 | V2: 控制载体 | W2: 责任主体 | X2: 业务自评价 | AA2: 集团监督评价 | AD2: 数字化监督场景 | AH2: 现有制度及文件落实情况 | AK2: 总部审核部门
K3: 不相容岗位 | L3: 分级授权 | M3: 业务真实性控制 | N3: 预算管控 | O3: 合同控制 | P3: 收付控制 | Q3: 会计监督 | R3: 财产保护 | S3: 分析与评价 | X3: 评价频率 | Y3: 评价范围 | Z3: 评价结论 | AA3: 评价频率 | AB3: 评价范围 | AC3: 评价结论 | AD3: 数字化监督场景 | AE3: 监督频率 | AF3: 监督范围 | AG3: 评价结论 | AH3: 是否已要求 | AI3: 是否满足要求 | AJ3: 对应制度及文件名称
A4: 财务管理 | B4: 三、预算管理 | C4: 会计信息真实完整、资金资产安全、税务合规 | D4: 战略支撑 （事前） | E4: 1.财务规划与公司战略协同不足，未有效承接战略指标体系。 2.规划没有科学分解到年度预算，落地执行出现偏差。 3.预算编制未与核价规则有效衔接，导致核价结果不及预期，进而影响战略目标的实现。 | F4: 规划目标与战略脱节：未按照战略目标体系设置规划目标，各级规划目标未有效协同，目标测算未与核价规则衔接，年度决算完成后未与规划目标进行对比分析。 | G4: 21.规划目标与战略一致性审核 | H4: 规划目标测算有效衔接战略指标体系及核价规则，推动规划投资全部纳入核价、核价规则深度融入经营，经营成果有效落实规划。 | I4: 财务管理-21.规划目标与战略一致性审核-控制措施01 | J4: 战略指标一致性审查。国网及各二级单位财务部门在规划编制环节核查经营目标与战略指标体系的一致性，对指标缺失或脱节的情形，不予通过。 | N4: √ | Q4: √ | T4: 线下管控 | V4: 1.公司战略规划方案 2.公司预算方案。 | W4: 各级单位-财务部门-预算管理人员 | X4: 年度 | Y4: 全量 | AA4: 年度 | AB4: 全量 | AH4: 是 | AI4: 是 | AJ4: 《国家电网有限公司全面预算管理办法》（国网（财/2）375-2026）第三条、第十四条 | AK4: 国网财务部
I5: 财务管理-21.规划目标与战略一致性审核-控制措施02 | J5: 建立“五年规划、三年核价、年度经营”相贯通的滚动预算管控机制。国网及各二级单位财务部门在智慧共享财务平台部署多维联动测算模型，建立“1+N”管控场景（1个监管业务典型场景，N个非监管业务个性化场景），在进行财务规划编制时，以核价参数为约束，合理安排规划期年度经营目标、投资和成本，逐年滚动预测，对比分析规划目标、核价参数落实情况，科学编制预算。 | N5: √ | Q5: √ | S5: √ | T5: 线上管控-待建 | U5: 智慧共享财务平台 | V5: 1.公司战略规划方案 2.公司预算方案 3.多维联动测算模型。 | W5: 各级单位-财务部门-预算管理人员 | X5: 年度 | Y5: 全量 | AA5: 年度 | AB5: 全量 | AD5: 多维联动测算模型 | AE5: 年度 | AF5: 全量 | AH5: 是 | AI5: 是 | AJ5: 《国家电网有限公司全面预算管理办法》（国网（财/2）375-2026）第三条、第十四条、第二十二条 | AK5: 国网财务部
E6: 1.决策依据不充分，对经营形势研判不足，缺乏充分调研和可行性分析。 2.决策流程不规范，未严格履行决策程序，导致预算决策出现偏差。 3.预算调整不及时，预算基础或边际条件发生重大变化时，未及时履行预算调整程序。 | F6: 预算决策流程不规范：重大项目投资未按规定履行本单位“三重一大”决策程序；预算决策流程流于形式，部分事项先执行后补签、越权审批或缺少书面记录；项目已出现明显亏损或环境变化，仍继续投入，缺少主动中止或调整的机制。 | G6: 22.预算决策程序审核 | H6: 预算决策依据充分、完整，程序规范、有效，及时响应预算基础或边际条件重大变化，确保公司经营稳健。 | I6: 财务管理-22.预算决策程序审核-控制措施01 | J6: 强化事前可研论证。每年，各级单位业务部门结合实际情况，明确本专业投入重点，并据此组织开展可研评审及项目储备。原则上所有纳入业务预算的项目均需履行项目储备程序，并向财务部门提供项目清单，清单中包括以下信息：项目名称、金额、建设内容、可研评审及批复文号等。 | M6: √ | N6: √ | T6: 线下管控 | V6: 1.项目立项相关材料 2.储备项目明细。 | W6: 各级单位-业务部门-经办人 | X6: 年度 | Y6: 抽查 | AA6: 年度 | AB6: 抽查 | AH6: 是 | AI6: 是 | AJ6: 《国家电网有限公司全面预算管理办法》（国网（财/2）375-2026）第十六条、第二十四条第二十二条;财预〔2025〕27号 国网财务部关于印发《国家电网有限公司财务支出可研经济性与财务合规性评价工作指引（2025）》的通知第一章1.4 | AK6: 国网财务部
I7: 财务管理-22.预算决策程序审核-控制措施02 | J7: 规范决策程序。各级单位办公室、法律部门等归口管理部门制定决策事项清单，对需纳入“三重一大”决策的预算事项进行明确；对预算方案决策程序进行合规性审核，决策会议由专人记录，会议纪要由会议主持人或公司主要负责同志签发，事后及时归档，确保决策流程完整规范。 | M7: √ | N7: √ | T7: 线下管控 | V7: 1.决策事项清单 2.会议纪要。 | W7: 各级单位-业务部门-经办人 | X7: 年度 | Y7: 全量 | AA7: 年度 | AB7: 全量 | AH7: 是 | AI7: 是 | AJ7: 《国家电网有限公司全面预算管理办法》（国网（财/2）375-2026）第十四条、第十五条 | AK7: 国网财务部
I8: 财务管理-22.预算决策程序审核-控制措施03 | J8: 及时履行预算调整程序。在预算基础或边际条件发生重大变化时，各级单位业务部门要及时向财务部提出预算调整建议，财务部门要及时组织开展经营分析，及时启动预算调整程序，在预算调整批复后，及时推进落地实施，确保公司稳健经营。 | N8: √ | Q8: √ | T8: 线上管控-已建 | U8: 智慧共享财务平台 | V8: 1.公司预算调整方案 2.决策记录。 | W8: 各级单位-业务部门-经办人、各级单位-财务部门-预算管理人员 | X8: 年度 | Y8: 全量 | AA8: 年度 | AB8: 全量 | AD8: 预算调整模块 | AE8: 年度 | AF8: 全量 | AH8: 是 | AI8: 是 | AJ8: 《国家电网有限公司全面预算管理办法》（国网（财/2）375-2026）第三十七条、第三十八条、三十九条 | AK8: 国网财务部
E9: 1.预算责任泛化。预算责任框架体系尚未健全完善，立项颗粒度不精细，预期目标不明确，导致资源错配或低效使用。 2.资源分配不精准。资源投入与公司重点任务脱节，区域、网架资源分配不均衡、布局不合理，影响电网均衡发展。 | F9: 生产性投入不足：资源分配结构不合理，生产性投入占比偏低，难以满足安全生产、设备运维等核心业务需求。 | G9: 23.资源配置精准性管控 | H9: 资源分配满足公司战略落地、监审核价、业务发展等预期目标要求，并确保预算责任主体明确。 | I9: 财务管理-23.资源配置精准性管控-控制措施01 | J9: 完善预算责任框架体系。各级单位财务部门在智慧共享财务平台中，完善预算责任框架体系，细化成本中心、利润中心，延伸至供电所或班组（产业、金融、国际、战新等其他业务板块根据自身业务实际设置成本中心、利润中心），并将预算指标层层分解。 | N9: √ | Q9: √ | T9: 线上管控-待建 | U9: 智慧共享财务平台 | V9: 1.预算责任框架体系。 | W9: 各级单位-财务部门-预算管理人员 | X9: 年度 | Y9: 全量 | AA9: 年度 | AB9: 全量 | AD9: 预算下达模块 | AE9: 年度 | AF9: 全量 | AH9: 是 | AI9: 是 | AJ9: 《国家电网有限公司全面预算管理办法》（国网（财/2）375-2026）第三十二条、第三十三条 | AK9: 国网财务部
I10: 财务管理-23.资源配置精准性管控-控制措施02 | J10: 强化财务支出分类管理。健全财务支出四级分类体系，对于资产动因类支出，原则上应关联至三级同源目录资产（价值核算单元）；对于组织动因类支出，分解至具体业务单元或部门，原则上以供电所为最小单元进行建项和执行管控。 | N10: √ | Q10: √ | T10: 线下管控 | V10: 1.预算分解明细。 | W10: 各级单位-财务部门-成本管理人员 | X10: 年度 | Y10: 全量 | AA10: 年度 | AB10: 全量 | AH10: 是 | AI10: 是 | AJ10: 《国家电网有限公司全面预算管理办法》（国网（财/2）375-2026）第三十二条、第三十三条 | AK10: 国网财务部
I11: 财务管理-23.资源配置精准性管控-控制措施03 | J11: 依托作业标准成本开展资源配置。国网财务部根据业务部门、各级单位在线填报或通过系统推送变电站数量、线路长度、人员数量等业务动因参数，组织审定各业务投向、各级单位标准成本，并以此为基础，编制下达检修运维费用预算。电网业务板块，各级单位财务部门开展本地化改造，在上级核定的成本预算范围内，开展本层级检修运维费用预算分解。产业、金融、国际、战新等其他业务板块，开展其他运营标准成本本地化改造，加强费用预算管控。 | N11: √ | Q11: √ | T11: 线上管控-已建 | U11: 智慧共享财务平台 | V11: 1.标准成本体系。 | W11: 各级单位-财务部门-成本管理人员 | X11: 年度 | Y11: 全量 | AA11: 年度 | AB11: 全量 | AD11: 预算下达模块 | AE11: 年度 | AF11: 全量 | AH11: 是 | AI11: 是 | AJ11: 《国家电网有限公司全面预算管理办法》（国网（财/2）375-2026）第二十五条、第三十二条 | AK11: 国网财务部
A12: 财务管理 | B12: 三、预算管理 | C12: 会计信息真实完整、资金资产安全、税务合规 | D12: 执行控制 （事中） | E12: 缺乏经营目标过程管控，未及时进行预算执行情况分析，导致预算执行不均衡或年度预算目标无法完成。 | F12: 未完成预算下达指标：决算审核后，部分经营指标未完成年度预算下达目标。 | G12: 24.预算执行情况分析 | H12: 严格预算执行控制，及时发现和报告重大预算事项，顺利实现公司战略及经营目标。 | I12: 财务管理-24.预算执行情况分析-控制措施01 | J12: 定期开展预算执行情况分析。国网及各级单位财务部门设定月度预算执行目标，在智慧共享财务平台部署，并设置预警阈值，每月，各级单位财务部门将实际执行进度与预算进度进行对比分析，并提前制定预控措施，确保均衡规范完成年度目标，其中：对于电网监管业务，重点关注电量及增速、电价水平、成本入账进度、利润水平等执行情况及均衡性；对于产业、金融、国际、战新及原集体企业等市场化业务，重点关注利润进度、毛利率水平、关联交易情况等。 | N12: √ | Q12: √ | S12: √ | T12: 线上管控-待建 | U12: 智慧共享财务平台 | V12: 1.预算执行分析报告。 | W12: 各级单位-财务部门-预算管理人员 | X12: 年度 | Y12: 抽查 | AA12: 年度 | AB12: 抽查 | AD12: 预算分析模块 | AE12: 每月 | AF12: 全量 | AH12: 是 | AI12: 是 | AJ12: 《国家电网有限公司全面预算管理办法》（国网（财/2）375-2026）第四十条-第四十三条 | AK12: 国网财务部
E13: 成本预算执行管控不严，导致成本列支不规范、超预算列支等问题，包括： （1）无预算、超预算列支成本，导致预算管控失效，引发资金管控风险； （2）预算单控费用执行不严，“三公”经费、会议费等重点支出预算未实施单项控制，引发重点费用管控失效风险； （3）资本性支出与成本性支出未严格区分，导致会计核算混乱，引发会计信息质量失真； （4）项目支出不规范，实际列支内容与预算安排不一致，引发项目资金滥用及会计信息失真风险； | F13: 成本性项目及资本性项目列支超年度预算：部分成本性项目及资本性项目在列支时，未及时履行调整流程，导致实际支出超出年度预算。 | G13: 25.各会计科目、项目预算系统编制及控制 | H13: 公司可控费用纳入预算统一管理，严禁发生预算外支出。 | I13: 财务管理-25.各会计科目、项目预算系统编制及控制-控制措施01 | J13: 系统部署项目预算控制规则。国网及各二级单位财务部门根据项目可研批复金额，在智慧共享财务平台中对各类成本性、资本性项目、费用科目配置预算及控制规则，通过系统预警、规则强控，确保无预算不支出、有预算不超支。 | N13: √ | Q13: √ | T13: 线上管控-已建 | U13: 智慧共享财务平台 | V13: 1.业务预算需求审批表 2.项目可研评审批复文件。 | W13: 各级单位-财务部门-项目管理人员 | X13: 年度 | Y13: 抽查 | AA13: 年度 | AB13: 抽查 | AD13: 财务预算编审控制和预算申报服务模块 | AE13: 年度 | AF13: 全量 | AH13: 是 | AI13: 是 | AJ13: 《国家电网有限公司全面预算管理办法》（国网（财/2）375-2026）第三十五条 | AK13: 国网财务部
F14: 单项费用控制失效：对于“三公” 经费、会议费进行总额控制，未单独进行预算分解，无法进行单项控制。 | G14: 26.重点单项费用预算编制及控制 | H14: 重点费用单项列支规范，与预算下达指标保持一致。 | I14: 财务管理-26.重点单项费用预算编制及控制-控制措施01 | J14: 上级部署单控费用预算。国网及各二级单位财务部门在智慧共享财务平台中根据年度预算对“三公”经费、会议费等实施单项控制，由上级单位在系统中核定，各级单位如需调整需履行预算调整程序，确保重点费用预算能控、在控。 | N14: √ | Q14: √ | T14: 线上管控-已建 | U14: 智慧共享财务平台 | V14: 1.费用支出明细 2.单项费用预算。 | W14: 各级单位-财务部门-预算管理人员 | X14: 年度 | Y14: 抽查 | AA14: 年度 | AB14: 抽查 | AD14: 财务预算申报服务模块 | AE14: 年度 | AF14: 全量 | AH14: 是 | AI14: 是 | AJ14: 《国家电网有限公司全面预算管理办法》（国网（财/2）375-2026）第三十五条 | AK14: 国网财务部
F15: 项目立项管理不规范：项目可研审核不严格，例如，存在通过生产大修项目购买电脑、隔离开关等固定资产的情况。 | G15: 27.项目可研经济性、财务合规性检查 | H15: 项目立项规范合规，项目支出性质准确。 | I15: 财务管理-27.项目可研经济性、财务合规性检查-控制措施01 | J15: 开展项目支出性质检查。各级单位财务部门协同各级业务归口管理部门、各级经研院所组织开展项目可研经济性、财务合规性评审，检查立项依据是否充分、立项类别是否准确，重点关注：报告中应包含维修资产的设备编码、资产原值等关键信息，检查项目金额是否超过维修资产原值的50%，物料清单中是否包含固定资产目录中设备。 | N15: √ | Q15: √ | T15: 线下管控 | V15: 1.项目可研报告或建议书 2.储备项目明细。 | W15: 各级单位-财务部门-项目管理人员 | X15: 年度 | Y15: 抽查 | AA15: 年度 | AB15: 抽查 | AH15: 是 | AI15: 是 | AJ15: 《国家电网有限公司全面预算管理办法》（国网（财/2）375-2026）第十六条、第二十二条;财预〔2025〕27号 国网财务部关于印发《国家电网有限公司财务支出可研经济性与财务合规性评价工作指引（2025）》的通知第一章1.4 | AK15: 国网财务部
F16: 项目结算不准确：多结算施工费用；虚列项目，跨期结算项目费用，结算依据不充分。 | G16: 28.项目预算执行控制 | H16: 项目支出规范，实际列支内容与预算安排保持一致。 | I16: 财务管理-28.项目预算执行控制-控制措施01 | J16: 开展项目实施内容检查。各级单位业务部门在项目完工后，应组织专业机构出具项目结算报告，并对项目支出内容进行检查，重点关注：施工费结算方式是否与合同一致、是否采购可研报告之外的物料、实施内容是否变更，如有变更是否履行变更程序等。各级单位财务部门在智慧共享财务平台中对项目支出合同、发票、上传的材料，参考项目可研报告中项目实施内容，从完整性、规范性、合理性等方面进行线上审核，确保项目支出规范。 | M16: √ | N16: √ | Q16: √ | T16: 线上管控-已建 | U16: 智慧共享财务平台 | V16: 1.项目结算报告 2.项目支出报账材料 3.项目可研报告。 | W16: 各级单位-业务部门-经办人、各级单位-财务部门-项目管理人员 | X16: 年度 | Y16: 抽查 | AA16: 年度 | AB16: 抽查 | AD16: 采购服务报账模块 | AE16: 年度 | AF16: 全量 | AH16: 是 | AI16: 是 | AJ16: 《国家电网有限公司全面预算管理办法》（国网（财/2）375-2026）第三十四条、第三十五条 | AK16: 国网财务部
A17: 财务管理 | B17: 三、预算管理 | C17: 会计信息真实完整、资金资产安全、税务合规 | D17: 执行控制 （事中） | E17: （5）成本开支内容不符合输配电成本监审要求，影响输配电价格核定，引发监管合规风险。 | F17: 监管单位成本预算安排规模与监审要求不符：材料修理费、其他运营费用安排严重偏离成本监审费率，与非监管单位关联交易利润率超10%，监管业务中列支广告宣传费（不含停电故障信息公告、电力安全保护宣传、电力设备安全警示等）等。 | G17: 29.预算编制与输配电成本一致性审核 | H17: 成本开支符合输配电成本监审要求。 | I17: 财务管理-29.预算编制与输配电成本一致性审核-控制措施01 | J17: 强化核价规则约束。各级单位财务部门根据成本监审及核价规则，设置预警规则，监控成本执行情况，重点关注：材料修理费、其他运营费用（含管理类费用）费率是否与核价费率严重偏离，引发成本核减或费率下滑风险；对广告宣传费、研究开发费等特殊敏感会计科目严格审核，确保相关成本支出符合成本监审要求。 | N17: √ | Q17: √ | T17: 线下管控 | V17: 1.成本支出相关资料。 | W17: 各级单位-财务部门-电价管理人员 | X17: 年度 | Y17: 抽查 | AA17: 年度 | AB17: 抽查 | AH17: 是 | AI17: 是 | AJ17: 《国家电网有限公司全面预算管理办法》（国网（财/2）375-2026）第二十二条、第三十五条 | AK17: 国网财务部
C18: 会计信息真实完整、资金资产安全、税务合规 | D18: 闭环管控 （事后） | E18: 未按照预算责任框架体系对各级经营单元进行投入产出评价，未对资源配置提出针对性管理建议，导致资源投入与业务指标提升关联度不高，引发低效无效风险。 | F18: 投入产出评价结果失真。受预算责任框架体系不完善、资源投向不清晰、资源投入与业务指标提升关联度不高等影响，投入产出评价结果不精准，无法有效指导后续资源分配。 | G18: 75.投入产出分析评价 | H18: 依托预算责任体系及项目四级分类体系，开展投入产出分析，指导后续资源配置。 | I18: 财务管理-75.投入产出分析评价-控制措施01 | J18: 定期开展投入产出评价。各级单位财务部门定期组织相关业务部门，对已完工项目投入产出情况开展评价，其中：对于资产动因类支出，通过与作业标准成本比、与同类设备支出水平比、检查预期目标实现情况等方式进行评价；对于组织动因类支出，通过横向对标、与历史水平对比等方式开展评价。 | N18: √ | Q18: √ | S18: √ | T18: 线下管控 | V18: 1.项目投入明细 2.项目产出评价结果。 | W18: 各级单位-财务部门-项目管理人员 | X18: 年度 | Y18: 抽查 | AA18: 年度 | AB18: 抽查 | AH18: 是 | AI18: 是 | AJ18: 《国家电网有限公司全面预算管理办法》（国网（财/2）375-2026）第四十一条、第四十二条、第四十三条 | AK18: 国网财务部
I19: 财务管理-75.投入产出分析评价-控制措施02 | J19: 加强评价结果应用。各级单位财务部门定期将投入产出评价结果推送业务部门，并指导后续业务预算审核； 各级单位业务部门结合实际对评价结果进行分析，对评价规则进行完善和反馈，持续提升评价精准性，并参考开展后续投向安排、设备选型等工作。 | N19: √ | Q19: √ | S19: √ | T19: 线下管控 | V19: 1.项目投入明细 2.项目产出评价结果。 | W19: 各级单位-业务部门-经办人、各级单位-财务部门-项目管理人员 | X19: 年度 | Y19: 抽查 | AA19: 年度 | AB19: 抽查 | AH19: 是 | AI19: 是 | AJ19: 《国家电网有限公司全面预算管理办法》（国网（财/2）375-2026）第四十一条、第四十二条、第四十三条、第三十六条 | AK19: 国网财务部
C20: 会计信息真实完整、资金资产安全、税务合规 | D20: 考核评价 （事后） | E20: 业绩考核指标体系制定不科学、执行不到位，未能有效引导各级单位落实公司战略要求，导致评价失真或偏离经营目标。 | F20: 考核指标设定不合理。指标设定明显超出下级单位能力，引发指标造假等问题。 | G20: 76.指标体系科学性审核 | H20: 充分发挥业绩考核指挥棒作用，引导各级单位精准完成经营目标。 | I20: 财务管理-76.指标体系科学性审核-控制措施01 | J20: 精简高效设置财务考核指标体系。每年，国网财务部及各二级单位财务部门结合公司战略及年度重点工作、各业务板块经营目标，差异化制定财务关键业绩考核指标，充分征求各级单位意见建议，重点关注：指标体系完整性、目标设置合理性、指标量化可比性。 | N20: √ | Q20: √ | S20: √ | T20: 线下管控 | V20: 1.年度关键业绩指标考核体系。 | W20: 各级单位-财务部门-预算管理人员 | X20: 年度 | Y20: 全量 | AA20: 年度 | AB20: 全量 | AH20: 是 | AI20: 是 | AJ20: 《国家电网有限公司全面预算管理办法》（国网（财/2）375-2026）第四十条、第四十一条、第四十二条、第四十三条 | AK20: 国网财务部
I21: 财务管理-76.指标体系科学性审核-控制措施02 | J21: 规范财务业绩考核工作流程。每年，国网财务部及各二级单位财务部门将关键业绩指标体系及考核规则通过智慧共享财务平台推送至企管部业绩考核系统，考核阶段，指标数据通过智慧共享财务平台自动获取，线上开展各级单位业绩还原事项评审，确保考核评价公平性、透明性。 | N21: √ | Q21: √ | S21: √ | T21: 线上管控-待建 | U21: 智慧共享财务平台 | V21: 1.决算报表、财务快报 2.特殊事项说明。 | W21: 各级单位-财务部门-预算管理人员 | X21: 年度 | Y21: 全量 | AA21: 年度 | AB21: 全量 | AD21: 预算考核模块 | AE21: 年度 | AH21: 是 | AI21: 是 | AJ21: 《国家电网有限公司全面预算管理办法》（国网（财/2）375-2026）第四十条、第四十一条、第四十二条、第四十三条 | AK21: 国网财务部

Sheet 整体情况
I1: 财务管理矩阵整体情况
A2: 会计 | B2: 会计 | C2: 预算 | D2: 预算 | E2: 股权 | F2: 股权 | G2: 资金 | H2: 资金 | I2: 序号 | J2: 业务领域 | K2: 步骤 | L2: 专业 | M2: 控制点 | N2: 控制措施 | O2: 备注
A3: 会计 | B3: 核算范围管理 | C3: 预算 | D3: 战略支撑 （事前） | E3: 股权 | F3: 1.股权投资项目储备 | G3: 资金 | H3: 银行账户开立 | I3: 1 | J3: 产权管理 | K3: 股权投资项目储备 | L3: 股权 | M3: 2 | N3: 9
A4: 会计 | B4: 会计政策管理 | C4: 预算 | D4: 经营决策 （事前） | E4: 股权 | F4: 2.投资项目决策管理 | G4: 资金 | H4: 商户号开立 | I4: 2 | K4: 投资项目决策管理 | L4: 股权 | M4: 1 | N4: 3
A5: 会计 | B5: 会计岗位管理 | C5: 预算 | D5: 资源分配 （事前） | E5: 股权 | F5: 3.股权投资项目计划预算管理 | G5: 资金 | H5: 数字钱包开立 | I5: 3 | K5: 股权投资项目计划预算管理 | L5: 股权 | M5: 1 | N5: 3
A6: 会计 | B6: 收入核算管理 | C6: 预算 | D6: 执行控制 （事中） | E6: 股权 | F6: 4.股权投资项目实施管理 | G6: 资金 | H6: 银行账户变更 | I6: 4 | K6: 股权投资项目实施管理 | L6: 股权 | M6: 3 | N6: 11
A7: 会计 | B7: 成本费用核算管理 | C7: 预算 | D7: 闭环管控 （事后） | E7: 股权 | F7: 5.股权投资项目后评价管理 | G7: 资金 | H7: 商户号变更 | I7: 5 | K7: 分支机构管理 | L7: 股权 | M7: 1 | N7: 2
A8: 会计 | B8: 往来会计管理 | C8: 预算 | D8: 考核评价 （事后） | E8: 股权 | F8: 6.股东权利行使与公司治理管理 | G8: 资金 | H8: 数字钱包变更 | I8: 6 | K8: 股权优化清理管理 | L8: 股权 | M8: 1 | N8: 6
A9: 会计 | B9: 总账会计管理 | E9: 股权 | F9: 7.股权优化清理管理 | G9: 资金 | H9: 账户使用-收入 | I9: 7 | K9: 股权转让项目管理 | L9: 股权 | M9: 5 | N9: 11
A10: 会计 | B10: 会计档案管理 | E10: 股权 | F10: 8.分支机构管理 | G10: 资金 | H10: 账户使用-支付 | I10: 8 | K10: 股权划转项目管理 | L10: 股权 | M10: 2 | N10: 6
E11: 股权 | F11: 9.股权转让项目管理 | G11: 资金 | H11: 账户使用-对账 | I11: 9 | K11: 增资扩股项目管理 | L11: 股权 | M11: 3 | N11: 8
E12: 股权 | F12: 10.股权划转项目管理 | G12: 资金 | H12: 账户使用-前置机数据管理 | I12: 10 | K12: 终止清算项目管理 | L12: 股权 | M12: 2 | N12: 6
E13: 股权 | F13: 11.增资扩股项目管理 | G13: 资金 | H13: 账户使用-密钥 | I13: 11 | K13: 股东权利行使与公司治理管理 | L13: 股权 | M13: 4 | N13: 16
E14: 股权 | F14: 12.终止清算项目管理 | G14: 资金 | H14: 账户使用-印鉴 | I14: 12 | K14: 参股企业运营管理 | L14: 股权 | M14: 5 | N14: 17
E15: 股权 | F15: 13.参股企业运营管理 | G15: 资金 | H15: 银行账户撤销 | I15: 13 | K15: 资产评估管理 | L15: 股权 | M15: 4 | N15: 11
E16: 股权 | F16: 14.资产评估管理 | G16: 资金 | H16: 商户号撤销 | I16: 14 | J16: 核算范围 | K16: 会计主体管理 | L16: 会计 | M16: 2 | N16: 3 | O16: 原核算范围管理
G17: 资金 | H17: 数字钱包撤销 | I17: 15 | K17: 会计政策管理 | L17: 会计 | M17: 3 | N17: 3
G18: 资金 | H18: 担保管理 | I18: 16 | K18: 会计岗位管理 | L18: 会计 | M18: 2 | N18: 4
G19: 资金 | H19: 人员管理 | I19: 17 | K19: 人员管理 | L19: 资金 | M19: 1 | N19: 3 | O19: 并入会计岗位管理
I20: 17 | J20: 账户管理 | K20: 银行账户开立 | L20: 资金 | M20: 2 | N20: 7
I21: 18 | K21: 商户号开立 | L21: 资金 | M21: 2 | N21: 4
I22: 19 | K22: 数字钱包开立 | L22: 资金 | M22: 2 | N22: 3
I23: 20 | K23: 银行账户变更 | L23: 资金 | M23: 1 | N23: 2
I24: 21 | K24: 商户号变更 | L24: 资金 | M24: 1 | N24: 1
I25: 22 | K25: 数字钱包变更 | L25: 资金 | M25: 1 | N25: 2
I26: 23 | K26: 银行账户撤销 | L26: 资金 | M26: 1 | N26: 3
I27: 24 | K27: 商户号撤销 | L27: 资金 | M27: 1 | N27: 2
I28: 25 | K28: 数字钱包撤销 | L28: 资金 | M28: 1 | N28: 2
I29: 26 | K29: 账户核算范围管理 | L29: 会计 | M29: 1 | N29: 1 | O29: 自会计主体管理分离
I30: 27 | J30: 预算管理 | K30: 战略支撑（事前） | L30: 预算 | M30: 1 | N30: 2
I31: 28 | K31: 经营决策（事前） | L31: 预算 | M31: 1 | N31: 3
I32: 29 | K32: 资源分配（事前） | L32: 预算 | M32: 1 | N32: 3
I33: 30 | K33: 执行控制（事中） | L33: 预算 | M33: 6 | N33: 6
I34: 31 | J34: 会计核算 | K34: 收入核算管理 | L34: 会计 | M34: 2 | N34: 7
I35: 32 | K35: 成本费用核算管理 | L35: 会计 | M35: 3 | N35: 4
I36: 33 | K36: 往来会计管理 | L36: 会计 | M36: 5 | N36: 7
I37: 34 | J37: 资金活动 | K37: 账户使用-收入 | L37: 资金 | M37: 3 | N37: 10
I38: 35 | K38: 账户使用-支付 | L38: 资金 | M38: 5 | N38: 18
I39: 36 | K39: 账户使用-对账 | L39: 资金 | M39: 3 | N39: 4
I40: 37 | K40: 账户使用-前置机数据管理 | L40: 资金 | M40: 1 | N40: 2
I41: 38 | K41: 账户使用-密钥 | L41: 资金 | M41: 7 | N41: 17
I42: 39 | K42: 账户使用-印鉴 | L42: 资金 | M42: 5 | N42: 11
I43: 40 | K43: 担保管理 | L43: 资金 | M43: 5 | N43: 10
I44: 41 | J44: 评价分析 | K44: 总账会计管理 | L44: 会计 | M44: 6 | N44: 9
I45: 42 | K45: 闭环管控（事后） | L45: 预算 | M45: 1 | N45: 2
I46: 43 | K46: 考核评价（事后） | L46: 预算 | M46: 1 | N46: 2
I47: 44 | K47: 股权投资项目后评价管理 | L47: 股权 | M47: 2 | N47: 5
I48: 45 | J48: 档案管理 | K48: 会计档案管理 | L48: 会计 | M48: 2 | N48: 2
J49: 合计 | M49: 114 | N49: 270

Sheet Sheet1
A1: 风控矩阵-财务管理
A2: 业 务 条 线 | B2: 业 务 领 域 | C2: 控 制 目 标 | D2: 业务流程步骤 | E2: 经营风险 | F2: 典型问题 | G2: 关键控制点 | H2: 控制要求 | I2: 控制措施 编号 | J2: 控制措施 | K2: 控制措施分类 | T2: 控制方式 | U2: 控制系统 | V2: 控制载体 | W2: 责任主体 | X2: 业务自评价 | AA2: 集团监督评价 | AD2: 数字化监督场景 | AH2: 现有制度及文件落实情况 | AK2: 总部审核部门 | AL2: 关联关系
K3: 不相容岗位 | L3: 分级授权 | M3: 业务真实性校验 | N3: 预算管控 | O3: 合同控制 | P3: 收付控制 | Q3: 会计监督 | R3: 财产保护 | S3: 分析与评价 | X3: 评价频率 | Y3: 评价范围 | Z3: 评价结论 | AA3: 评价频率 | AB3: 评价范围 | AC3: 评价结论 | AD3: 数字化监督场景 | AE3: 监督频率 | AF3: 监督范围 | AG3: 评价结论 | AH3: 是否已要求 | AI3: 是否满足要求 | AJ3: 对应制度及文件名称
A4: 财务管理 | B4: 会计核算 | C4: 会计信息真实完整 | D4: 核算范围管理 | E4: 会计主体创建不规范、不及时，影响合并范围完整性、准确性，导致会计信息不准确。 | F4: 会计主体创建不合规：对工商登记持股超过50%的实际经营企业、未创建会计主体单独核算，导致合并范围不完整、合并报表信息不准确。 | G4: 1.会计主体完整性管控 | H4: 会计主体与工商登记、人资组织、产权组织衔接一致，合并范围完整。 | I4: 会计核算-1.会计主体完整性管控-控制措施01 | J4: 1.合并范围完整性控制。每月，各单位会计人员在线跟踪比对工商、产权登记与报表合并范围一致性，原则上工商登记持股50%以上企业需全部办理产权登记、规范取得控制权并纳入合并范围。确有问题的，应及时规范调整。 | M4: √ | Q4: √ | T4: 线上管控-待建 | U4: 智慧共享财务平台、主数据管理平台（MDM3.0) | V4: 1.会计核算主体建立（变更）申请单 2.工商登记、税务登记、产权登记资料等 | W4: 各单位-财务部-总账管理 | X4: 每月 | Y4: 全量 | AA4: 年度 | AB4: 全量 | AD4: 合并范围完整性监督场景（已建） | AE4: 每月 | AF4: 全量 | AH4: 是 | AI4: 是 | AJ4: 1.《国家电网有限公司会计基础管理办法》（国家电网企管〔2019〕132号）-第四章 核算与报告-第三十七条、第四十四条 2.《国家电网有限公司关于做好2025年度财务决算工作的通知》（国家电网财〔2025〕649号） | AK4: 财务部
I5: 会计核算-1.会计主体完整性管控-控制措施02 | J5: 2.会计主体创建和变更控制：各单位会计人员应遵循先产权后工商的要求，根据产权和工商登记结果，及时创建会计主体，并履行二级单位、总部财务部审批程序，规范纳入合并范围。对于无人资组织、未办理工商登记的会计主体，由二级单位分管财务领导审批后，提交国网财务部审批。 | L5: √ | M5: √ | T5: 线上管控-已建 | U5: 智慧共享财务平台、主数据管理平台（MDM3.0) | V5: 1.会计核算主体建立（变更）申请单 2.人资部门关于会计主体建立（变更）的文件 3.工商登记、税务登记、产权登记资料等 | W5: 各单位-财务部-总账管理 | X5: 每月 | Y5: 全量 | AA5: 年度 | AB5: 全量 | AD5: 会计主体创建变更规范性监督场景（已建） | AE5: 每月 | AF5: 全量 | AH5: 是 | AI5: 是 | AJ5: 1.《国家电网有限公司会计基础管理办法》（国家电网企管〔2019〕132号）-第四章 核算与报告-第三十七条、第四十四条 2.《关于智慧共享财务平台与人资2.0系统管理融合有关事项的通知》（财会〔2025〕15号） | AK5: 财务部
E6: 银行账户核算不完整，会计信息不准确，产生资金安全风险。 | F6: 银行账户核算不完整：账内银行账户与开户清单、账内商户号与开立商户号清单不一致，存在账外资金，导致资金失管、账实不符，引发资金安全风险。 | G6: 2.账户完整性管控 | H6: 银行账户和商户号核算完整、准确。 | I6: 会计核算-2.账户完整性管控-控制措施01 | J6: 银行账户和商户号核算完整性控制。每年10月底前、次年1月初，各单位会计人员会同决算审计会计师事务所，前往人民银行或基本户开户行打印全量开户清单；登录各商户号网上平台，获取全量商户号清单。逐一与账内核算银行账户和商户号进行比对，确保以公司名义开立、可独立支配账户资金、承担资金安全管理责任的银行账户和商户号，均完整纳入账内核算。 | M6: √ | Q6: √ | T6: 线上管控-待建 | U6: 智慧共享财务平台 | V6: 1.银行账户开立清单 2.商户号清单 | W6: 各单位-财务部-总账管理 | X6: 每季 | Y6: 全量 | AA6: 年度 | AB6: 全量 | AD6: 账户完整性监督场景（待建） | AE6: 每季 | AF6: 全量 | AH6: 是 | AI6: 是 | AJ6: 1.《国家电网有限公司司库管理办法》（国家电网企管〔2023〕88号）-第三章 银行账户（数字钱包）管理-第二十五条 2.《国网财务部关于进一步加强社会保障有关账户管理和资金核算的通知》（财金〔2024〕12号） 3.《国家电网有限公司2025年度财务决算审计工作指引》 | AK6: 财务部
E7: 科目维度使用不统一、不规范，影响会计信息准确性和可比性。 | F7: 科目维度使用不规范：凭证科目维度与实际业务不匹配，影响会计信息反映准确性；集团内不同单位对同类业务核算科目维度不统一，导致会计信息不可比。 | G7: 3.业务完整性管控 | H7: 统一会计科目和管理维度体系，规范科目维度使用，确保会计信息准确可比。 | I7: 会计核算-3.业务完整性管控-控制措施01 | J7: 会计科目和管理维度统一性规范性控制。 公司总部建立统一的会计科目和管理维度体系，并实施分业态管理，各单位根据业态标识规范引用。在公司统一体系下，各单位因自身业务特点和内部管理要求，确需对相关管理维度枚举值进行细化的，需依次履行二级单位、总部财务部审批程序。 | L7: √ | Q7: √ | T7: 线上管控-已建 | U7: 智慧共享财务平台 | V7: 1.集团会计科目和管理维度体系清单 2.科目维度系统配置文件 3.维度细化申请与审批记录 | W7: 各单位-财务部-总账管理 | X7: 年度 | Y7: 全量 | AA7: 年度 | AB7: 全量 | AD7: 科目维度规范性监督场景（已建） | AE7: 年度 | AF7: 全量 | AH7: 是 | AI7: 是 | AJ7: 1.《国家电网有限公司会计基础管理办法》（国家电网企管〔2019〕132号）-第四章 核算与报告-第四十条、第四十四条 2.《国家电网有限公司财务管理通则》（国家电网企管〔2020〕763号）-第三章 管理内容与管理流程-第二节 会计核算-第二十一条 | AK7: 财务部 | AL7: 关联预算管理-3.资源配置精准性管控-控制措施01
C8: 会计信息真实完整 | D8: 会计政策管理 | E8: 会计政策和会计估计分类和分级授权标准不明确，导致执行不统一，影响会计信息准确性和可比性。 | F8: 会计政策和会计估计分类和分级授权不规范：未明确会计政策和会计估计分类管控和分级授权标准，导致会计信息执行不统一、反映不准确。 | G8: 4.会计政策和会计估计分类管控和分级授权管理 | H8: 明确会计政策、会计估计分类管控和分级授权标准。 | I8: 会计核算-4.会计政策和会计估计分类管控和分级授权管理-控制措施01 | J8: 会计政策和会计估计分类管控及分级授权控制：公司总部统一建立会计政策和会计估计分类管控及分级授权标准，明确政策清单，对应收款项坏账计提比例、固定资产折旧方法和年限区间、投资性房地产后续计量方法等，由公司总部统一确定；对固定资产折旧年限等公司统一政策下的具体执行值，由各单位履行决策程序后确定具体执行标准并向公司总部备案。 | L8: √ | T8: 线上管控-待建 | U8: 智慧共享财务平台 | V8: 1.会计政策和会计估计分类管控清单 2.会计政策、会计估计分级授权清单 | W8: 总部-财务部-总账管理 | X8: 年度 | Y8: 全量 | AA8: 年度 | AB8: 全量 | AD8: 会计政策、会计估计分类管控及分级授权标准监督场景（待建） | AE8: 年度 | AF8: 全量 | AH8: 是 | AI8: 是 | AJ8: 《国家电网有限公司会计基础管理办法》（国家电网企管〔2019〕132号）-第四章 核算与报告-第三十九条、第四十四条 | AK8: 财务部
A9: 财务管理 | B9: 会计核算 | C9: 会计信息真实完整 | D9: 会计政策管理 | E9: 会计政策和会计估计执行不统一、不规范，导致会计信息不准确、经营业绩失真。 | F9: 会计政策和会计估计执行不统一：未严格执行公司统一的会计政策和会计估计，导致会计信息反映不准确、不可比。 | G9: 5.会计政策和会计估计执行管控 | H9: 严格执行统一的会计政策和会计估计标准。 | I9: 会计核算-5.会计政策和会计估计执行管控-控制措施01 | J9: 会计政策和会计估计执行统一性控制：公司总部将统一会计政策和会计估计管控要求嵌入在线业财处理流程，确保全流程规范遵循。每月末，各单位会计人员对本单位统一政策执行情况进行全面检查，确保反映准确。 | Q9: √ | T9: 线上管控-待建 | U9: 智慧共享财务平台 | V9: 1.会计政策和会计估计分类管控清单 2.会计政策、会计估计分级授权清单 | W9: 总部-财务部-总账管理 各单位-财务部-总账管理 | X9: 年度 | Y9: 抽查 | AA9: 年度 | AB9: 抽查 | AD9: 会计政策和会计估计规范性监督场景（待建） | AE9: 年度 | AF9: 抽查 | AH9: 是 | AI9: 是 | AJ9: 《国家电网有限公司会计基础管理办法》（国家电网企管〔2019〕132号）-第四章 核算与报告-第三十九条、第四十四条 | AK9: 财务部
E10: 会计政策和会计估计变更不规范、随意调节，跨年调整经营指标，导致会计信息不准确、经营业绩失真。 | F10: 会计政策和会计估计变更流程不规范：变更程序不规范、审核把关不严，滥用变更人为调节年度间财务状况、经营成果，导致会计信息不准确。 | G10: 6.会计政策和会计估计变更审批 | H10: 会计政策和会计估计变更审批统一规范。 | I10: 会计核算-6.会计政策和会计估计变更审批-控制措施01 | J10: 会计政策和会计估计变更审批控制。对会计政策和会计估计变更事项，根据分类管控及分级授权标准，分层级履行党组（党委）会前置研究、董事会或类似机构决策等程序。 | L10: √ | T10: 线下管控 | V10: 会计政策和会计估计变更申请单 | W10: 各单位-财务部-总账管理 | X10: 年度 | Y10: 抽查 | AA10: 年度 | AB10: 抽查 | AH10: 是 | AI10: 是 | AJ10: 《国家电网有限公司会计基础管理办法》（国家电网企管〔2019〕132号）-第四章 核算与报告-第三十九条、第四十四条 | AK10: 财务部
C11: 企业经营管理合法合规、资金资产安全、会计信息真实完整 | D11: 会计岗位管理 | E11: 会计不相容权责未分离，审核审批不合规，容易引发财务舞弊，造成资金挪用、资产损失、会计信息失真。 | F11: 不相容岗位权责未分离：会计兼任出纳、业务审批、财产保管等职责，导致资金资产损失长期隐匿未被发现；凭证制单与审核、审批由同一人负责，容易造成会计舞弊。 | G11: 7.会计不相容岗位管控 | H11: 严格会计不相容岗位相分离。 | I11: 会计核算-7.会计不相容岗位管控-控制措施01 | J11: 不相容岗位相分离控制。各单位财务部门严格按照不相容岗位相分离的要求，规范设置会计岗位、匹配会计人员。 | K11: √ | L11: √ | T11: 线下管控 | V11: 1.岗位设置与岗位职责说明 2.系统角色和权限配置表 | W11: 各单位-财务部-财务负责人 | X11: 月度 | Y11: 全量 | AA11: 年度 | AB11: 全量 | AH11: 是 | AI11: 是 | AJ11: 1.《国家电网有限公司会计基础管理办法》（国家电网企管〔2019〕132号）-第三章 会计机构和会计人员-第十六条 2.《会计基础工作规范》（征求意见稿）-第二章 会计机构和会计岗位-第十一条 | AK11: 财务部
E12: 会计岗位交接不规范，影响会计工作组织和会计信息质量。 | F12: 会计岗位交接资料不完整、监交不到位：移交清册等资料不完整，资金、凭证、账簿等财务数据未核对，交接过程未经过监交人监督，交接前后财务信息不衔接、不准确。 | G12: 8.会计岗位交接管控 | H12: 规范会计工作交接，确保会计资料衔接一致。 | I12: 会计核算-8.会计岗位交接管控-控制措施03 | J12: 会计工作交接规范性控制。各单位会计人员办理移交手续前，应完成未了事项，编制移交清册，并与接管人员逐项核对确认。办理交接手续，必须有监交人负责监交；交接完毕后，交接双方和监交人员要在移交清册上签名或者盖章。 | Q12: √ | T12: 线下管控 | V12: 1.会计岗位交接清单 2.移交清册 3.本岗位相关业务流程、信息系统功能、注意事项及未了事项等的书面说明 4.交接归档留存资料 | W12: 各单位-财务部-风险内控与稽核评价管理 | X12: 年度 | Y12: 全量 | AA12: 年度 | AB12: 全量 | AH12: 是 | AI12: 是 | AJ12: 《国家电网有限公司会计基础管理办法》（国家电网企管〔2019〕132号）-第三章 会计机构和会计人员-第三节 会计工作交接 | AK12: 财务部
A13: 财务管理 | B13: 会计核算 | C13: 会计信息真实完整、资金资产安全 | D13: 收入核算管理 | E13: 收入真实性核查不足、收入确认不完整、不准确，提前、延后或跨期确认收入，未严格核查“三流”一致性、“两头在外”购销业务，导致收入核算不准确、经营成果不可靠、资金与合规风险。 | F13: 5.收入确认不完整、不准确：业务部门未及时提交履约进度等结算资料、资料不完整，导致收入确认不完整、不准确；业务部门违规开展虚假贸易，伪造收入结算资料，导致会计信息失真；财务部门未准确区分总额法和净额法，导致收入核算不准确。 | G13: 9.售电收入管控 | H13: 严格审核营财数据一致性，确保售电收入确认完整。 | I13: 会计核算-9.售电收入管控-控制措施01 | J13: 1.营财数据一致性控制。每月末，各单位财务人员对售电收入财务汇总账与营销账务的一致性进行全面核对，发现营财差异，需及时查明原因，并进行营财联动调整，严禁财务手工调整。 | M13: √ | Q13: √ | S13: √ | T13: 线上管控-待建 | U13: 智慧共享财务平台、营销2.0系统 | V13: 1.营销传入电费凭证 2.营财对账记录 | W13: 各单位-营销部-电费电价管理 各单位-财务部-电费电价管理 | X13: 每季 | Y13: 抽查 | AA13: 每季 | AB13: 抽查 | AD13: 营财数据一致性监督场景（已建） | AE13: 每月 | AF13: 全量 | AH13: 是 | AI13: 是 | AJ13: 《关于明确营销2.0系统与智慧共享财务平台系统集成有关问题的意见》（营销营业〔2023〕86号）-二、高频业务处理流程标准化 | AK13: 财务部
I14: 会计核算-9.售电收入管控-控制措施02 | J14: 2.售电业务营财集成控制。总部营销部、财务部根据业务场景，共同制定营财集成规则并在线固化。各单位财务人员在月度结账前，全面排查非集成售电收入凭证，对异常情况及时查明原因，规范冲销调整。 | M14: √ | Q14: √ | T14: 线上管控-待建 | U14: 智慧共享财务平台 | V14: 营财一体化核算规则 | W14: 总部-财务部-总账管理 总部-财务部-电费电价管理 各单位-财务部-总账管理 | X14: 每季 | Y14: 抽查 | AA14: 每季 | AB14: 抽查 | AH14: 是 | AI14: 是 | AJ14: 1.《关于明确营销2.0系统与智慧共享财务平台系统集成有关问题的意见》（营销营业〔2023〕86号）-二、高频业务处理流程标准化 2.《国家电网有限公司2025年度财务决算审计工作指引》 | AK14: 财务部
G15: 10.非电收入管控 | H15: 严格审核收入真实性、准确性、完整性， 准确反映经营成果。 | I15: 会计核算-10.非电收入管控-控制措施01 | J15: 1.收入真实性监督。各单位会计人员在收入报账审核时，通过检查合同、发票、出库单、物流单、签收单、完工验收单等，识别虚构业务情形，对收入真实性进行监督。 | M15: √ | O15: √ | Q15: √ | T15: 线上管控-待建 | U15: 智慧共享财务平台 | V15: 合同、发票、出库单、物流单、签收单、完工验收单等收入报账附件 | W15: 各单位-财务部-收入会计 | X15: 每月 | Y15: 抽查 | AA15: 每月 | AB15: 抽查 | AD15: 收入真实性监督场景（待建） | AE15: 每月 | AF15: 抽查 | AH15: 是 | AI15: 是 | AJ15: 1.《国家电网有限公司会计核算办法》（国家电网企管〔2026〕101号）-第四章、第十九章至第二十三章 2.《国家电网有限公司会计基础管理办法》（国家电网企管〔2019〕132号）-附则-一、收入业务 3.《会计基础工作规范》（征求意见稿）-第五章 会计监督-第三十九条 4.《国家电网有限公司2025年度财务决算审计工作指引》 | AK15: 财务部
I16: 会计核算-10.非电收入管控-控制措施02 | J16: 2.收入完整性监督。各单位会计人员通过检查收款记录、结算单据以及业务系统中销售发货、服务进度、施工进度等记录，对收入报账的完整性进行监督。 | M16: √ | Q16: √ | T16: 线上管控-待建 | U16: 智慧共享财务平台 | V16: 合同、发票、银行回单、结算单据、销售发货单、服务进度表、施工进度表等收入报账附件 | W16: 各单位-财务部-收入会计 | X16: 每月 | Y16: 抽查 | AA16: 每月 | AB16: 抽查 | AD16: 收入完整性监督场景（待建） | AE16: 每月 | AF16: 抽查 | AH16: 是 | AI16: 是 | AJ16: 1.《国家电网有限公司会计核算办法》（国家电网企管〔2026〕101号）-第四章、第十九章至第二十三章 2.《国家电网有限公司会计基础管理办法》（国家电网企管〔2019〕132号）-附则-一、收入业务 3.《会计基础工作规范》（征求意见稿）-第五章 会计监督-第三十九条 4.《国家电网有限公司2025年度财务决算审计工作指引》 | AK16: 财务部
I17: 会计核算-10.非电收入管控-控制措施03 | J17: 3.收入确认准确性控制。各单位会计人员根据合同、物流仓储记录等，准确判断合同中承担的主要责任或代理责任，规范选取总额法或净额法核算。公司总部细化产品服务分类，在线固化各类型业务核算规则，实施收入确认准确性在线、精准控制。 | M17: √ | Q17: √ | T17: 线上管控-待建 | U17: 智慧共享财务平台 | V17: 1.合同 2.物流仓储记录 | W17: 总部-财务部-总账管理 各单位-财务部-收入会计 | X17: 每月 | Y17: 抽查 | AA17: 每月 | AB17: 抽查 | AD17: 收入确认准确性监督场景（待建） | AE17: 每月 | AF17: 抽查 | AH17: 是 | AI17: 是 | AJ17: 1.《国家电网有限公司关于强化“三道防线”协同管控切实防范贸易业务风险的通知》（国家电网财〔2024〕406号） 2.《国家电网有限公司2025年度财务决算审计工作指引》 | AK17: 财务部
I18: 会计核算-10.非电收入管控-控制措施04 | J18: 4.资金流、发票流、账务流一致性监督。各单位会计人员严格审核业务执行中与上下游企业资金收付和发票开具情况，对按净额法核算的业务，原则上不得介入上下游资金流、发票流，避免垫付资金风险。发现“三流”不一致带来的资金垫付风险，应停止办理报账，并及时向单位负责人报告。 | M18: √ | P18: √ | Q18: √ | T18: 线上管控-待建 | U18: 智慧共享财务平台 | V18: 1.合同 2.银行回单 3.发票 | W18: 各单位-财务部-收入会计 | X18: 每季 | Y18: 抽查 | AA18: 年度 | AB18: 抽查 | AD18: “三流”一致性监督场景（待建） | AE18: 每季 | AF18: 抽查 | AH18: 是 | AI18: 是 | AJ18: 1.《国家电网有限公司关于强化“三道防线”协同管控切实防范贸易业务风险的通知》（国家电网财〔2024〕406号） 2.《国家电网有限公司2025年度财务决算审计工作指引》 | AK18: 财务部
I19: 会计核算-10.非电收入管控-控制措施05 | J19: 5.贸易业务规范性监督。对于“两头在外”购销业务，各单位会计人员严格审核业务审批、上下游关联关系、仓储物流、毛利率水平等情况，发现异常情况及时截停业务。对于业务部门提交垫付资金、大额预付、往来款项互抵等异常事项，财务部门要向本单位主要负责同志和贸易业务分管领导报告，启动业务真实性合规性调查，并暂停资金支付；经调查认定为违规贸易业务的，要逐级上报至总部财务部，并终止支付、督促业务部门停止业务。 | M19: √ | P19: √ | Q19: √ | T19: 线上管控-待建 | U19: 智慧共享财务平台 | V19: 1.业务审批记录 2.上下游关联关系核查资料 3.仓储物流单 4.毛利率分析记录 | W19: 各单位-财务部-收入会计 | X19: 每季 | Y19: 抽查 | AA19: 年度 | AB19: 抽查 | AD19: 贸易业务规范性监督场景（待建） | AE19: 每季 | AF19: 抽查 | AH19: 是 | AI19: 是 | AJ19: 1.《国家电网有限公司关于强化“三道防线”协同管控切实防范贸易业务风险的通知》（国家电网财〔2024〕406号） 2.《国家电网有限公司2025年度财务决算审计工作指引》 | AK19: 财务部
A20: 财务管理 | B20: 会计核算 | C20: 会计信息真实完整、资金资产安全 | D20: 成本费用核算管理 | E20: 成本费用列支不真实、不完整、不规范，造成利润不实、资金资产流失。 | F20: 成本费用不真实、不完整、不规范：成本结转、成本记账无依据或依据不充分，年末发生大额成本入账但与实际履约进度不符，超标准、超预算报销差旅费、会议费等，收入成本不匹配、项目毛利率异常，影响会计信息真实性、准确性。 | G20: 11.成本真实性管控 | H20: 经济业务成本费用真实发生、有据可查。 | I20: 会计核算-11.成本真实性管控-控制措施01 | J20: 成本费用真实性监督。各单位会计人员在成本费用报账审核时，通过检查采购或服务合同、发票以及入库验收、工程施工、劳务考勤等佐证资料，核查实际履约情况，对成本费用真实性进行监督。各单位会计人员在凭证过账审核时，对记账凭证依据的充分性进行监督，重点复核非系统集成记账凭证依据的充分性。 | M20: √ | O20: √ | Q20: √ | T20: 线上管控-待建 | U20: 智慧共享财务平台 | V20: 1.合同 2.发票 3.成本结算明细 | W20: 各单位-财务部-成本会计 | X20: 每月 | Y20: 全量 | AA20: 每季 | AB20: 全量 | AD20: 成本费用报账真实性监督场景（待建） | AE20: 每月 | AF20: 全量 | AH20: 是 | AI20: 是 | AJ20: 1.《国家电网有限公司会计基础管理办法》（国家电网企管〔2019〕132号）-第二章 职责分工 第八条、第四章 核算与报告-第五十四条、附则-二、成本费用业务 2.《国家电网有限公司2025年度财务决算审计工作指引》 | AK20: 财务部
G21: 12.成本合规性、完整性管控 | H21: 经济业务成本费用报账规范、完整，与公司经营相关、符合制度要求。 | I21: 会计核算-12.成本合规性、完整性管控-控制措施01 | J21: 1.成本费用合规性监督。总部会同各单位，将差旅费、“三公”经费等重点费用管控标准嵌入信息系统和业财处理流程，实施在线控制；各单位会计人员在成本报账审核时，对照公司制度要求检查成本费用超标准、超范围等情况，对成本费用合规性进行监督。 | N21: √ | Q21: √ | T21: 线上管控-待建 | U21: 智慧共享财务平台 | V21: 1.系统审核规则 2.报账附件 | W21: 各单位-财务部-成本会计 | X21: 每月 | Y21: 全量 | AA21: 每季 | AB21: 全量 | AD21: 成本费用报账合规性、完整性监督场景（待建） | AE21: 每月 | AF21: 全量 | AH21: 是 | AI21: 是 | AJ21: 《国家电网有限公司会计基础管理办法》（国家电网企管〔2019〕132号）-第二章 职责分工-第八条、第四章 核算与报告-第五十四条、附则-二、成本费用业务 | AK21: 财务部
I22: 会计核算-12.成本合规性、完整性管控-控制措施02 | J22: 2.成本费用完整性监督。各单位会计人员通过检查付款记录、结算单据、月度间成本费用规模以及业务系统中采购收货、服务进度、施工进度等记录，对成本报账的完整性进行监督。 | M22: √ | Q22: √ | T22: 线上管控-待建 | U22: 智慧共享财务平台 | V22: 1.系统审核规则 2.报账附件 | W22: 各单位-财务部-成本会计 | X22: 每月 | Y22: 全量 | AA22: 每季 | AB22: 全量 | AD22: 成本费用报账合规性、完整性监督场景（待建） | AE22: 每月 | AF22: 全量 | AH22: 是 | AI22: 是 | AJ22: 《国家电网有限公司会计基础管理办法》（国家电网企管〔2019〕132号）-第二章 职责分工-第八条、第四章 核算与报告-第五十四条、附则-二、成本费用业务 | AK22: 财务部
G23: 13.收入成本匹配性管控 | H23: 收入确认时点、规模与成本匹配，准确反映公司经营成果。 | I23: 会计核算-13.收入成本匹配性管控-控制措施01 | J23: 收入成本匹配性监督。各单位会计人员通过检查收发货记录、服务履约记录、项目毛利率以及账面合同履约成本、合同负债、往来款项等挂账情况，动态监控合同、项目等收入成本匹配性，及时向业务部门发出预警督办，确保收入成本动态匹配、反映准确。 | M23: √ | O23: √ | Q23: √ | T23: 线上管控-待建 | U23: 智慧共享财务平台 | V23: 1.合同 2.发票 3.收发货记录、服务履约记录 | W23: 各单位-财务部-成本会计 | X23: 每月 | Y23: 全量 | AA23: 每季 | AB23: 全量 | AD23: 收入成本匹配性核查场景（待建） | AE23: 每月 | AF23: 全量 | AH23: 是 | AI23: 是 | AJ23: 1.《国家电网有限公司会计核算办法》（国家电网企管〔2026〕101号）-第十九章 工程施工业务-第二节 项目建设期 2.《国家电网有限公司2025年度财务决算审计工作指引》 | AK23: 财务部
C24: 会计信息真实完整、资金资产安全 | D24: 往来会计管理 | E24: 往来客商使用不规范，通过一次性（过渡）客商无依据暂估收入成本，导致往来信息不准确，存在人为调节利润风险。 | F24: 挂账对象不规范：将可对应至具体客户或供应商的往来款项挂账至一次性（过渡）客商。 | G24: 14.往来挂账规范性管控 | H24: 规范往来客商使用，除特殊情形外不使用一次性（过渡）客商。 | I24: 会计核算-14.往来挂账规范性管控-控制措施01 | J24: 往来挂账规范性控制。各单位会计人员根据具体业务事项，将往来款项规范挂账至具体客户或供应商。除总部统一明确的特殊情形外，不得挂账至一次性（过渡）客商。 | M24: √ | Q24: √ | T24: 线上管控-待建 | U24: 智慧共享财务平台 | V24: 一次性（过渡）客商标准场景清单 | W24: 各单位-财务部-往来管理 | X24: 每季 | Y24: 抽查 | AA24: 每季 | AB24: 抽查 | AD24: 往来挂账规范性监督场景（已建） | AE24: 每季 | AF24: 全量 | AH24: 是 | AI24: 是 | AJ24: 1.《国家电网有限公司会计基础管理办法》（国家电网企管〔2019〕132号）-第四章 核算与报告-第五十六条 2.《国家电网有限公司2025年度财务决算审计工作指引》 | AK24: 财务部
E25: 往来款项清账不及时，债权债务底数不清，易形成呆账、坏账，造成资金损失风险。 | F25: 往来款项清账不及时不规范：往来款项清账不及时、账龄不准确，未及时识别收付款风险，导致坏账计提错误或资金损失。 | G25: 15.往来清账及时性管控 | H25: 及时、规范开展往来清账，确保往来款项余额和账龄准确。 | I25: 会计核算-15.往来清账及时性管控-管控措施01 | J25: 往来清账及时性控制。各单位会计人员动态监测智慧共享财务平台往来款项清账情况，对特殊情况产生的应清未清事项，及时查明原因、规范处理，确保日清日结。 | P25: √ | Q25: √ | T25: 线上管控-已建 | U25: 智慧共享财务平台 | V25: 1.应收台账 2.应付台账 | W25: 各单位-财务部-往来管理 | X25: 每月 | Y25: 全量 | AA25: 每月 | AB25: 全量 | AD25: 往来款项清账及时性监督场景（已建） | AE25: 每月 | AF25: 全量 | AH25: 是 | AI25: 是 | AJ25: 1.《国家电网有限公司会计基础管理办法》（国家电网企管〔2019〕132号）-第四章 核算与报告-第六十二条 2.《国家电网有限公司2025年度财务决算审计工作指引》 | AK25: 财务部
A26: 财务管理 | B26: 会计核算 | C26: 会计信息真实完整、资金资产安全 | D26: 往来会计管理 | E26: 往来款项对账不及时，债权债务底数不清，易造成资金损失风险。 | F26: 往来款项对账不规范：应付款项对账不准确，导致重复付款、超额付款，造成资金损失；对账流于形式，未发现往来款项错收、错付、漏记账、重复记账问题，产生资金挪用、往来舞弊风险。 | G26: 16.往来对账规范性管控 | H26: 规范开展往来对账，确保往来款项余额准确、账实相符。 | I26: 会计核算-16.往来对账规范性管控-管控措施01 | J26: 往来对账规范性控制。对账龄1年以上、逾期、债务人经营异常或单一客商挂账金额重大的往来款项，各单位要会同会计师事务所，在每年2月底前，通过询证函等书面方式，对上年末挂账余额进行对账确认。函证结果不一致的，要在决算中查明原因，规范调整账务。 | Q26: √ | S26: √ | T26: 线下管控 | V26: 询证函等书面对账材料 | W26: 各单位-财务部-往来管理 | X26: 年度 | Y26: 全量 | AA26: 年度 | AB26: 全量 | AH26: 是 | AI26: 是 | AJ26: 1.《国家电网有限公司会计基础管理办法》（国家电网企管〔2019〕132号）-第四章 核算与报告-第六十二条 2.《国家电网有限公司2025年度财务决算审计工作指引》 | AK26: 财务部
E27: 应收款项回收不及时、长期挂账，造成资金占用、坏账损失风险。应付款项支付不及时，导致合同违约、信用受损，产生舆情及合规风险。 | F27: 债权债务清理不及时：应收款项催收不及时、回款周期长，资金周转压力大，增加坏账损失风险；应付款项长期挂账未清理，容易引发合同与法律纠纷。 | G27: 17.长期挂账款项管理 | H27: 建立长期挂账款项清理机制，避免长期挂账、逾期挂账。 | I27: 会计核算-17.长期挂账款项管理-控制措施01 | J27: 1.往来款项收付及时性监督。各单位财务部门集成应用合同收付款结构化数据，在合同约定的收付款节点前，及时向业务部门经办人员发送收付款报账提醒。 | Q27: √ | S27: √ | T27: 线上管控-待建 | U27: 智慧共享财务平台、数字化法治企业建设平台 | V27: 1.系统预警规则 2.应收台账 3.应付台账 | W27: 各单位-财务部-往来管理 | X27: 每月 | Y27: 抽查 | AA27: 每季 | AB27: 抽查 | AD27: 往来款项收付及时性监督场景（待建） | AE27: 每月 | AF27: 全量 | AH27: 是 | AI27: 是 | AJ27: 《国家电网有限公司会计基础管理办法》（国家电网企管〔2019〕132号）-第四章 核算与报告-第六十二条 | AK27: 财务部
I28: 会计核算-17.长期挂账款项管理-控制措施02 | J28: 2.往来款项风险监测预警。各单位财务部门集成应用工商等大数据，对长账龄、逾期、债务人经营异常等往来款项，按月向业务部门在线发送往来状态和风险预警，并建立在线督办台账，加强过程管控。 | Q28: √ | S28: √ | T28: 线上管控-待建 | U28: 智慧共享财务平台 | V28: 1.长账龄、逾期、债务人经营异常往来款项清单 2.督办台账 | W28: 各单位-财务部-往来管理 | X28: 每月 | Y28: 抽查 | AA28: 每季 | AB28: 抽查 | AD28: 往来款项风险监测预警监督场景（待建） | AE28: 每月 | AF28: 全量 | AH28: 是 | AI28: 是 | AJ28: 1.《国家电网有限公司会计基础管理办法》（国家电网企管〔2019〕132号）-第四章 核算与报告-第六十二条 2.《国家电网有限公司2025年度财务决算审计工作指引》 | AK28: 财务部
E29: 坏账准备计提不及时、不准确，影响资产计量真实性，导致会计信息质量受损；往来款项核销不规范，导致资产流失及合规风险。 | F29: 坏账计提不准确、往来款项核销不规范：坏账计提未执行公司统一政策，高风险债务人应收款项未按单项认定计提坏账，导致坏账计提金额不准确；往来款项核销依据不充分、审批程序不合规，违规核销损害公司利益。 | G29: 18.坏账准备及往来款项处置管理 | H29: 统一坏账计提政策，确保坏账计提金额准确；严格清查核实往来款项无法收付情况，规范履行核销程序。 | I29: 会计核算-18.坏账准备及往来款项处置管理-控制措施01 | J29: 1.应收款项坏账计提准确性控制。对组合认定款项，公司总部统一在线配置各类组合计提比例；各单位会计人员动态、在线监测应收款项账龄准确性，确保自动、准确计提；对个别认定款项，各单位会计人员在线跟踪监测长账龄、逾期、债务人经营异常等款项，组织业务部门及时评估回收风险，回收风险较大的，按单项认定足额计提坏账。 | Q29: √ | T29: 线上管控-已建 | U29: 智慧共享财务平台 | V29: 1.坏账计提规则 2.长账龄、逾期、债务人经营异常等往来款项清单 | W29: 总部-财务部-总账管理 各单位-财务部-往来管理 | X29: 年度 | Y29: 抽查 | AA29: 年度 | AB29: 抽查 | AD29: 坏账准备计提准确性监督场景（已建） | AE29: 每月 | AF29: 全量 | AH29: 是 | AI29: 是 | AJ29: 1.《国家电网有限公司会计基础管理办法》（国家电网企管〔2019〕132号）-第四章 核算与报告-第六十二条、第七章 附则-三、资产业务-（三）坏账准备 2.《国家电网有限公司会计核算办法》（国家电网企管〔2026〕101号）-第二章 债权债务-第一节 债权管理 3.《国家电网有限公司2025年度财务决算审计工作指引》 | AK29: 财务部
I30: 会计核算-18.坏账准备及往来款项处置管理-控制措施02 | J30: 2.往来款项核销规范性控制。对确实无法收回的应收款项或无需支付的应付款项，各单位会计人员严格审核业务部门提供的企业吊销、法院判决裁定等佐证，会同业务部门规范履行内部决策、中介机构鉴证等程序后，进行账销案存处理。 | L30: √ | Q30: √ | T30: 线下管控 | V30: 1.应收款项核销佐证依据 2.应付款项核销佐证依据 3.内部决策文件 4.中介机构鉴证报告 | W30: 各单位-财务部-往来管理 | X30: 年度 | Y30: 抽查 | AA30: 年度 | AB30: 抽查 | AH30: 是 | AI30: 是 | AJ30: 1.《国家电网有限公司会计基础管理办法》（国家电网企管〔2019〕132号）-第四章 核算与报告-第六十二条、第七章 附则-三、资产业务-（三）坏账准备 2.《国家电网有限公司会计核算办法》（国家电网企管〔2026〕101号）-第二章 债权债务-第一节 债权管理、第二节 债务管理 3.《国家电网有限公司2025年度财务决算审计工作指引》 | AK30: 财务部
A31: 财务管理 | B31: 会计核算 | C31: 会计信息真实完整、资金资产安全 | D31: 总账会计管理 | E31: 关联交易未协同、抵销不充分，导致会计信息不准确。 | F31: 关联交易协同不充分：关联交易双方业务处理不同步、凭证未协同、存在单方挂账，导致合并抵销不充分、会计信息不准确。 | G31: 19.关联交易协同管控 | H31: 内部关联交易协同抵销充分、准确。 | I31: 会计核算-19.关联交易协同管控-控制措施01 | J31: 关联交易抵销充分性控制：各单位严格遵循公司统一的关联交易“发票码、资金码”协同抵销规则，所有内部交易事项均双方协同入账、同步生成上级单位抵销凭证。 | M31: √ | Q31: √ | T31: 线上管控-已建 | U31: 智慧共享财务平台 | V31: 系统关联交易协同抵销规则 | W31: 各单位-财务部-总账管理 | X31: 每月 | Y31: 全量 | AA31: 每月 | AB31: 全量 | AD31: 关联交易协同监督场景（已建） | AE31: 每月 | AF31: 全量 | AH31: 是 | AI31: 是 | AJ31: 1.《国家电网有限公司会计基础管理办法》（国家电网企管〔2019〕132号）-第四章 核算与报告-第三节 会计凭证 第五十六条 2.《国家电网有限公司财务管理通则》（国家电网企管〔2020〕763号）-第三章 管理内容与管理流程-第二节 会计核算-第二十六条、二十七条 | AK31: 财务部
E32: 期末结账不规范，导致账务数据不准确。 | F32: 期末结账不规范：账务处理不完整，损益类科目结转方向不规范，结账后随意调账，导致会计信息不准确。 | G32: 20.期末结账规范性管控 | H32: 规范期末结转，确保账证、账账、账实核对一致。 | I32: 会计核算-20.期末结账规范性管控-控制措施01 | J32: 期末结账规范性控制。各单位财务部门明确结账流程、相关岗位职责、账期关闭时间要求等；总账会计检查当期账务处理完整性、规范性，包括银行对账、往来清账、税费计提、资产折旧摊销、过渡科目结转、损益业务结转等，完成结账后关闭账期。 | M32: √ | Q32: √ | T32: 线上管控-已建 | U32: 智慧共享财务平台 | V32: 1.系统期末结账规则 2.期末检查记录 | W32: 各单位-财务部-总账管理 | X32: 每月 | Y32: 全量 | AA32: 每月 | AB32: 全量 | AD32: 期末结账规范性监督场景（已建） | AE32: 每月 | AF32: 全量 | AH32: 是 | AI32: 是 | AJ32: 《国家电网有限公司会计基础管理办法》（国家电网企管〔2019〕132号）-第四章 核算与报告-第六十三条 | AK32: 财务部
E33: 银行账户余额不准确，银企对账不规范，产生资金安全风险。 | F33: 银行账户余额不准确：对账数据获取不及时、不准确，银行余额调节表未经审核签字，未及时发现未达账项或差错，导致资金损失、会计信息不准确。 | G33: 21.银行账户余额准确性管控 | H33: 明确银企对账职责与流程，及时处理未达账项，确保银行账务数据完整准确。 | I33: 会计核算-21.银行账户余额准确性管控-控制措施01 | J33: 银行存款余额准确性控制。各单位财务部门安排出纳以外的人员获取银行对账单，按月编制银行存款余额调节表，并由财务部门负责人复核、签字；存在未达账项的，要及时清理，不得出现2个月以上未达账项，年末不得出现未达账项。 | K33: √ | L33: √ | M33: √ | Q33: √ | T33: 线上管控-已建 | U33: 智慧共享财务平台 | V33: 1.银行回单、对账单 2.银行余额调节表 | W33: 各单位-财务部-资金管理 各单位-财务部-财务负责人 | X33: 每月 | Y33: 全量 | AA33: 每月 | AB33: 全量 | AD33: 银企对账准确性监督场景（已建） | AE33: 每月 | AF33: 全量 | AH33: 是 | AI33: 是 | AJ33: 《国家电网有限公司司库管理办法》（国家电网企管〔2023〕88号）-第三章 银行账户（数字钱包）管理-第四十四条 | AK33: 财务部
E34: 资产盘点未核实、减值依据不充分，导致资产价值不准确、账实不一致 | F34: 资产账实不符。实物资产长期未盘点或盘点流于形式，长库龄、闲置、毁损资产未计提减值，导致资产账实不一致。 | G34: 22.资产账实一致性核查 | H34: 及时核查资产盘点结果，开展资产减值测试，确保账实相符、反映准确。 | I34: 会计核算-22.资产账实一致性核查-控制措施01 | J34: 1.资产物资账实一致性监督。每年末，各单位会计人员向相关部门获取经实物管理部门、财务部门、会计师事务所监盘人员三方签字盖章的固定资产、存货等实物资产盘点结果，核查账实一致性及实物状态，对发现的账实不符或资产减值迹象，履行审批程序后规范进行账务处理。 | M34: √ | Q34: √ | T34: 线下管控 | V34: 实物资产盘点表 | W34: 各单位-财务部-总账管理 | X34: 年度 | Y34: 抽查 | AA34: 年度 | AB34: 抽查 | AH34: 是 | AI34: 是 | AJ34: 1.《国家电网有限公司固定资产管理办法》（国家电网企管〔2023〕28号）-第四章 固定资产变动-第二十六条、第七章 固定资产日常管理-第五十二条 2.《国家电网有限公司2025年度财务决算审计工作指引》-二、 会计信息质量审计-第三条 实物资产 | AK34: 财务部
I35: 会计核算-22.资产账实一致性核查-控制措施02 | J35: 2.资产减值充分性监督。每月末，各单位会计人员在线获取在建工程停工状态、长库龄存货等信息，及时向相关业务部门发送减值风险预警，并建立督办台账、限期完成核实反馈，确保资产价值反映准确。 | M35: √ | Q35: √ | T35: 线下管控 | V35: 资产减值督办台账 | W35: 各单位-财务部-总账管理 | X35: 年度 | Y35: 抽查 | AA35: 年度 | AB35: 抽查 | AH35: 是 | AI35: 是 | AJ35: 1.《国家电网有限公司会计基础管理办法》（国家电网企管〔2019〕132号）-第四章 核算与报告-第五节 财务会计报告 第六十八条 2.《国家电网有限公司2025年度财务决算审计工作指引》-二、 会计信息质量审计-第三条 实物资产 | AK35: 财务部
E36: 期初调整不规范，通过期初调整跨年调节经营指标，导致会计信息不实、经营业绩失真。 | F36: 期初调整不规范：期初调整程序不规范、审核把关不严，滥用会计调整人为调节年度间财务状况、经营成果，导致会计信息不实、掩饰真实经营状况。 | G36: 23.期初调整规范性管控 | H36: 严格履行期初调整程序，规范期初调整行为。 | I36: 会计核算-23.期初调整规范性管控-控制措施01 | J36: 期初调整规范性控制。对重大会计差错更正等期初调整事项，各单位经内部决策审批后，纳入年度财务决算备案报告向公司总部提出调整申请，总部审核批复后方可进行期初账务处理。对重大会计差错更正，各单位应查明原因，识别跨期调节风险，严肃追究相关单位和相关人员责任。 | L36: √ | Q36: √ | T36: 线下管控 | V36: 1.重大会计差错更正等期初调整佐证材料 2.年度财务决算备案情况说明 | W36: 各单位-财务部-总账管理 | X36: 年度 | Y36: 全量 | AA36: 年度 | AB36: 全量 | AH36: 是 | AI36: 是 | AJ36: 1.《国家电网有限公司会计基础管理办法》（国家电网企管〔2019〕132号）-第四章 核算与报告-第一节 一般要求 第六十五条 2.《国家电网有限公司2025年度财务决算审计工作指引》-二、 会计信息质量审计-第十八条 期初调整 | AK36: 财务部
A37: 财务管理 | B37: 会计核算 | C37: 会计信息真实完整、资金资产安全 | D37: 总账会计管理 | E37: 财务报告编报不规范、披露不合规，会计师事务所选聘不规范、评价不到位，导致报表数据不准确、会计信息反映不实、审计意见不合规，引发监管问责及合规风险。 | F37: 财务报告编审不规范：财务报表与账务数据不一致，表内、表间数据不勾稽，报表异常波动未经审核，年度决算报告未经审议，自行选聘决算审计事务所出具审计报告，导致会计信息反映不实、决算审计的独立性与公允性受损。 | G37: 24.财务报告编报及报出 | H37: 严格按照国家财务会计制度及企业会计准则规定，规范编制、审核、披露财务报告，全面、完整、真实、准确反映企业财务状况和经营成果。 | I37: 会计核算-24.财务报告编报及报出-控制措施01 | J37: 1.财务报表编报规范性控制。公司总部在线固化财务报表出具标准流程和相关稽核规则，确保账表一致、表内和表间数据衔接。各单位结合管理实际，自行增补报表稽核规则，对异常波动数据及时分析原因，确保报表反映完整、准确。 | Q37: √ | S37: √ | T37: 线上管控-已建 | U37: 智慧共享财务平台 | V37: 1.报表取数、运算、稽核公式清单 2.异常波动事项原因分析 | W37: 各单位-财务部-报表管理 | X37: 每月 | Y37: 全量 | AA37: 每月 | AB37: 全量 | AD37: 财务报表编报规范性监督场景（已建） | AE37: 每月 | AF37: 全量 | AH37: 是 | AI37: 是 | AJ37: 《国家电网有限公司会计基础管理办法》（国家电网企管〔2019〕132号）-第四章 核算与报告-第六十八条、第六十九条 | AK37: 财务部
I38: 会计核算-24.财务报告编报及报出-控制措施02 | J38: 2.年度财务决算报告披露规范性控制。按照“三重一大”授权清单，各单位财务决算报告规范履行党委会前置研究、董事会决策程序后，报送上级监管部门或对外披露。财务报表须经单位主要负责人、总会计师（分管财务工作负责人）、会计机构负责人（会计主管人员）签章。 | L38: √ | T38: 线下管控 | V38: 1.年度决算报告 2.内部决策文件 | W38: 各单位-财务部-报表管理 | X38: 年度 | Y38: 全量 | AA38: 年度 | AB38: 全量 | AH38: 是 | AI38: 是 | AJ38: 《国家电网有限公司会计基础管理办法》（国家电网企管〔2019〕132号）-第四章 核算与报告-第七十八条 | AK38: 财务部
I39: 会计核算-24.财务报告编报及报出-控制措施03 | J39: 3.决算审计会计师事务所管理控制。公司总部统一选聘各层级单位财务决算审计会计师事务所，各单位严格执行总部选聘结果，并按年对会计师事务所决算审计工作进行评价。 | L39: √ | S39: √ | T39: 线下管控 | V39: 1.会计师事务所财务决算审计合同 2.财务决算审计会计师事务所评价表 | W39: 各单位-财务部-报表管理 | X39: 年度 | Y39: 全量 | AA39: 年度 | AB39: 全量 | AH39: 是 | AI39: 是 | AJ39: 《国家电网有限公司会计基础管理办法》（国家电网企管〔2019〕132号）-第四章 核算与报告-第七十六条 | AK39: 财务部
C40: 会计信息真实完整 | D40: 会计档案管理 | E40: 会计档案归档不准确、不完整，导致档案信息缺失，引发合规风险。 | F40: 会计档案归档不规范：会计档案归档不完整，电子会计资料不满足国家归档要求，导致档案信息不完整、不准确。 | G40: 25.会计档案归档 | H40: 明确会计档案归档范围和管理要求，规范纸质和电子会计档案归档管理，确保档案完整、准确。 | I40: 会计核算-25.会计档案归档-控制措施01 | J40: 会计资料归档规范性控制。各单位会计人员应按照归档范围和要求，定期将会计凭证、会计账簿、财务会计报告、银行对账单等归档资料整理立卷，检查电子会计档案是否符合电子化归档要求，编制会计档案保管清册，确保规范归档。 | M40: √ | S40: √ | T40: 线下管控 | V40: 1.会计档案保管清册 2.会计档案归档记录 | W40: 各单位-财务部-会计档案管理 | X40: 年度 | Y40: 全量 | AA40: 年度 | AB40: 全量 | AH40: 是 | AI40: 是 | AJ40: 《国家电网有限公司会计基础管理办法》（国家电网企管〔2019〕132号）-第六章 会计档案-第二节 会计归档和保管 第九十七条 | AK40: 财务部
E41: 无纸化资料存档不规范，导致档案信息不完整，引发合规风险。 | F41: 无纸化存档不规范：无纸化档案不完整、存档不规范，导致档案信息不可靠。 | G41: 26.无纸化存档管控 | H41: 加强无纸化存档规范化和安全防护管控，保证档案真实性、完整性、可用性和安全性。 | I41: 会计核算-26.无纸化存档管控-控制措施01 | J41: 会计资料无纸化存档规范性控制。各单位应严格管控已归档无纸化资料利用权限，通过定期备份、加密存储、操作日志留痕等安全保护措施，确保不被篡改；定期评估电子档案可读性，确保真实、完整、可用。 | Q41: √ | T41: 线上管控-待建 | U41: 智慧电子档案管理系统 | V41: 1.电子会计档案查询权限配置 2.电子会计档案操作日志 | W41: 各单位-财务部-会计档案管理 | X41: 年度 | Y41: 全量 | AA41: 年度 | AB41: 全量 | AD41: 会计资料无纸化存档规范性监督场景（待建） | AE41: 年度 | AF41: 全量 | AH41: 是 | AI41: 是 | AJ41: 1.《国家电网有限公司会计基础管理办法》（国家电网企管〔2019〕132号）-第六章 会计档案-第二节 会计归档和保管 第九十九条、第一百一十二条 2.《电子会计档案管理规范》（国家档案局DA/T 94—2022） | AK41: 财务部

Sheet 导出列表_列D
A1: 列D | B1: 计数
A2: 股权投资项目储备 | B2: 9 | C2: =VLOOKUP(A2,整体情况!K:N,4,0) -> 9 | D2: =B2-C2 -> 0
A3: 股权划转项目管理 | B3: 6 | C3: =VLOOKUP(A3,整体情况!K:N,4,0) -> 6 | D3: =B3-C3 -> 0
A4: 增资扩股项目管理 | B4: 8 | C4: =VLOOKUP(A4,整体情况!K:N,4,0) -> 8 | D4: =B4-C4 -> 0
A5: 终止清算项目管理 | B5: 6 | C5: =VLOOKUP(A5,整体情况!K:N,4,0) -> 6 | D5: =B5-C5 -> 0
A6: 参股企业运营管理 | B6: 17 | C6: =VLOOKUP(A6,整体情况!K:N,4,0) -> 17 | D6: =B6-C6 -> 0
A7: 资产评估管理 | B7: 11 | C7: =VLOOKUP(A7,整体情况!K:N,4,0) -> 11 | D7: =B7-C7 -> 0
A8: 投资项目决策管理 | B8: 3 | C8: =VLOOKUP(A8,整体情况!K:N,4,0) -> 3 | D8: =B8-C8 -> 0
A9: 股权投资项目计划预算管理 | B9: 3 | C9: =VLOOKUP(A9,整体情况!K:N,4,0) -> 3 | D9: =B9-C9 -> 0
A10: 股权投资项目实施管理 | B10: 11 | C10: =VLOOKUP(A10,整体情况!K:N,4,0) -> 11 | D10: =B10-C10 -> 0
A11: 股权投资项目后评价管理 | B11: 5 | C11: =VLOOKUP(A11,整体情况!K:N,4,0) -> 5 | D11: =B11-C11 -> 0
A12: 股东权利行使与公司治理管理 | B12: 16 | C12: =VLOOKUP(A12,整体情况!K:N,4,0) -> 16 | D12: =B12-C12 -> 0
A13: 股权优化清理管理 | B13: 6 | C13: =VLOOKUP(A13,整体情况!K:N,4,0) -> 6 | D13: =B13-C13 -> 0
... A46: 总账会计管理 | B46: 9 | C46: =VLOOKUP(A46,整体情况!K:N,4,0) -> 9 | D46: =B46-C46 -> 0

Sheet 汇总wfx
A1: 风控矩阵-财务管理
A2: 业 务 条 线 | B2: 业 务 领 域 | C2: 控 制 目 标 | D2: 业务流程步骤 | E2: 经营风险 | F2: 典型问题 | G2: 关键控制点 | H2: 控制要求 | I2: 控制措施 编号 | J2: 控制措施 | K2: 控制措施分类 | T2: 控制方式 | U2: 控制系统 | V2: 控制载体 | W2: 责任主体 | X2: 业务自评价 | AA2: 集团监督评价 | AD2: 数字化监督场景 | AH2: 现有制度及文件落实情况 | AK2: 总部审核部门 | AL2: 关联关系
K3: 不相容岗位 | L3: 分级授权 | M3: 业务真实性校验 | N3: 预算管控 | O3: 合同控制 | P3: 收付控制 | Q3: 会计监督 | R3: 财产保护 | S3: 分析与评价 | X3: 评价频率 | Y3: 评价范围 | Z3: 评价结论 | AA3: 评价频率 | AB3: 评价范围 | AC3: 评价结论 | AD3: 数字化监督场景 | AE3: 监督频率 | AF3: 监督范围 | AG3: 评价结论 | AH3: 是否已要求 | AI3: 是否满足要求 | AJ3: 对应制度及文件名称
C4: 企业经营管理合法合规、资金资产安全、会计信息真实完整 | D4: 会计岗位管理 | E4: 会计不相容权责未分离，审核审批不合规，容易引发财务舞弊，造成资金挪用、资产损失、会计信息失真。 | F4: 不相容岗位权责未分离：会计兼任出纳、业务审批、财产保管等职责，导致资金资产损失长期隐匿未被发现；凭证制单与审核、审批由同一人负责，容易造成会计舞弊。 | G4: 7.会计不相容岗位管控 | H4: 严格会计不相容岗位相分离。 | I4: 会计核算-7.会计不相容岗位管控-控制措施01 | J4: 不相容岗位相分离控制。各单位财务部门严格按照不相容岗位相分离的要求，规范设置会计岗位、匹配会计人员。 | K4: √ | L4: √ | T4: 线下管控 | V4: 1.岗位设置与岗位职责说明 2.系统角色和权限配置表 | W4: 各单位-财务部-财务负责人 | X4: 月度 | Y4: 全量 | AA4: 年度 | AB4: 全量 | AH4: 是 | AI4: 是 | AJ4: 1.《国家电网有限公司会计基础管理办法》（国家电网企管〔2019〕132号）-第三章 会计机构和会计人员-第十六条 2.《会计基础工作规范》（征求意见稿）-第二章 会计机构和会计岗位-第十一条 | AK4: 财务部
E5: 会计岗位交接不规范，影响会计工作组织和会计信息质量。 | F5: 会计岗位交接资料不完整、监交不到位：移交清册等资料不完整，资金、凭证、账簿等财务数据未核对，交接过程未经过监交人监督，交接前后财务信息不衔接、不准确。 | G5: 8.会计岗位交接管控 | H5: 规范会计工作交接，确保会计资料衔接一致。 | I5: 会计核算-8.会计岗位交接管控-控制措施03 | J5: 会计工作交接规范性控制。各单位会计人员办理移交手续前，应完成未了事项，编制移交清册，并与接管人员逐项核对确认。办理交接手续，必须有监交人负责监交；交接完毕后，交接双方和监交人员要在移交清册上签名或者盖章。 | Q5: √ | T5: 线下管控 | V5: 1.会计岗位交接清单 2.移交清册 3.本岗位相关业务流程、信息系统功能、注意事项及未了事项等的书面说明 4.交接归档留存资料 | W5: 各单位-财务部-风险内控与稽核评价管理 | X5: 年度 | Y5: 全量 | AA5: 年度 | AB5: 全量 | AH5: 是 | AI5: 是 | AJ5: 《国家电网有限公司会计基础管理办法》（国家电网企管〔2019〕132号）-第三章 会计机构和会计人员-第三节 会计工作交接 | AK5: 财务部
C6: 资金资产安全 | D6: 人员管理 | E6: 不相容岗位未严格分离、任职回避执行不到位、轮岗休假管控不足，导致资金制衡失效，引发资金挪用风险。 | G6: 42.人员管理 | H6: 严格按照不相容岗位相分离原则，执行回避制度，建立资金岗位定期轮换、交流和强制休假机制，防范资金挪用风险。 | I6: 财务管理-42.人员管理-控制措施01 | J6: 各单位严格遵循不相容岗位分离管控要求，分别配备出纳、资金收支审核和资金收支审批岗位，且不得兼任。出纳、资金收支审核等资金管理关键岗位应使用正式编制员工。 | K6: √ | T6: 线下管控 | V6: 岗位人员清单 | W6: 各单位-财务部-财务负责人 | X6: 每年 | Y6: 全量检查 | AA6: 每年 | AB6: 全量检查 | AH6: 是 | AI6: 是 | AJ6: 《国家电网有限公司司库管理办法》（国网（财/2）345-2023）第十章第二百五十五条 | AK6: 财务部
I7: 财务管理-42.人员管理-控制措施02 | J7: 各单位严格落实财务人员任职回避制度，单位负责人的直系亲属不得担任本单位财务机构负责人和会计主管，财务机构负责人和会计主管的直系亲属不得在本单位会计机构中担任出纳。 | K7: √ | T7: 线下管控 | V7: 岗位人员清单 | W7: 各单位-财务部-财务负责人 | X7: 每年 | Y7: 全量检查 | AA7: 每年 | AB7: 全量检查 | AH7: 是 | AI7: 是 | AJ7: 《国家电网有限公司司库管理办法》（国网（财/2）345-2023）第十章二百五十六条 | AK7: 财务部
I8: 财务管理-42.人员管理-控制措施03 | J8: 各单位要建立资金岗位轮岗、交流和强制休假机制。替岗人员应在替岗期间完成现金、银行账户余额、重要票据核对及未达账项核实工作，并编制核查报告、审核存档。 | K8: √ | Q8: √ | T8: 线下管控 | V8: 1.岗位交接表； 2.稽核报告 | W8: 各单位-财务部-财务负责人 | X8: 每季度 | Y8: 全量检查 | AA8: 每季度 | AB8: 全量检查 | AH8: 是 | AI8: 是 | AJ8: 《国家电网有限公司司库管理办法》（国网（财/2）345-2023）第十章二百五十七、二百五十八条 | AK8: 财务部
A9: 财务管理 | B9: 资金管理 | C9: 资金资产安全 | D9: 银行账户开立 | E9: 银行账户开立未履行审批手续，易滋生账外账及小金库，账户未纳入系统统一监管，账实不符，引发资金流失风险。 | F9: 1.银行账户未批先设：未经上级或总部批准擅自在线下开立账户。 2.银行账户开立后，未纳入中台统一管理。 3.基本账户超范围开立。 4.党费账户超范围开立 5.非经营类账户命名不规范:党费户未以党委或党委组织部门的名义单独设立银行账户；工会户未带有“工会”字样。 6.非经营类账户未纳入中台统一管理 | G9: 1.银行账户合规开立控制 | H9: 严格履行银行账户开立审批手续，规范开户渠道、开户主体，严禁未批先设；定期从人民银行或基本户开户银行获取全量账户清单，排查“应纳未纳”风险。 | I9: 财务管理-1.银行账户合规开立控制-控制措施01 | J9: 各单位财务部从严控制银行账户开立机构，基本账户应在中、农、工、建4家银行之一开立；其他账户应在开户机构白名单范围内选择，不在白名单范围内的开户事项，须履行二级单位本部审核和总部审批。 | L9: √ | M9: √ | O9: √ | T9: 线上管控-已建 | U9: 智慧共享财务平台 | V9: 1.银行账户开立申请单； 2.银行账户开立业务办理回执 | W9: 各单位-财务部-经办人员、各单位-财务部-资金审核岗 | X9: 每季度 | Y9: 抽查 | AA9: 每年 | AB9: 抽查 | AH9: 是 | AI9: 否 | AJ9: 《国家电网有限公司司库管理办法》（国网（财/2）345-2024）第三章第三十条、三十五条 | AK9: 财务部
I10: 财务管理-1.银行账户合规开立控制-控制措施02 | J10: 各单位业务部门按照“谁开立谁负责”原则，通过智慧共享财务平台办理银行账户开立申请，并履行内部审批，开立后在规定时间内完成智慧共享财务平台信息维护。开立协议应在数字化法治企业建设平台签订。 | L10: √ | O10: √ | T10: 线上管控-待建 | U10: 智慧共享财务平台 | V10: 银行账户开立业务办理回执 | W10: 各单位-业务部-经办人员、各单位-财务部-资金审核岗 | X10: 每季度 | Y10: 抽查 | AA10: 每年 | AB10: 抽查 | AH10: 否 | AK10: 财务部
I11: 财务管理-1.银行账户合规开立控制-控制措施03 | J11: 各单位财务部（经营类账户）或业务部门（非经营类账户）规范银行账户开立经办管理，须由本人或授权人员办理，经办人员应为正式编制，手续须由至少两名人员共同办理，强化岗位制衡。其中，非经营类账户指含党团工会、出资举办的事业单位以及以公司名义设立或举办的各类组织、单位等所有非并表主体账户。 | K11: √ | T11: 线下管控 | V11: 2名经办人员外出审批单 | W11: 各单位-财务部-财务负责人、各单位-业务部-部门负责人 | X11: 每季度 | Y11: 抽查 | AA11: 每年 | AB11: 抽查 | AH11: 是 | AI11: 是 | AJ11: 《国家电网有限公司司库管理办法》（国网（财/2）345-2024）第三章第三十六条 | AK11: 财务部
I12: 财务管理-1.银行账户合规开立控制-控制措施04 | J12: 各单位财务部定期从人民银行或基本户开户银行获取全量已开立银行结算账户清单，与智慧共享财务平台账户台账逐项核对，排查“应纳未纳”等异常，确保账户台账全面覆盖、信息完整。 | K12: √ | M12: √ | S12: √ | T12: 线下管控 | V12: 开立银行账户清单 | W12: 各单位-财务部-经办人员 | X12: 每季度 | Y12: 抽查 | AA12: 每年 | AB12: 抽查 | AH12: 否 | AK12: 财务部
I13: 财务管理-1.银行账户合规开立控制-控制措施05 | J13: 中国电财严格核验内部账户开立审批手续，审批流程完备合规后方可受理开户业务。 | L13: √ | T13: 线上管控-已建 | U13: 智慧共享财务平台 | V13: 银行账户开立申请单 | W13: 中国电财-直属营业部或营业部（司库服务部）-综合柜员-结算业务负责人 | X13: 每季度 | Y13: 抽查 | AA13: 每年 | AB13: 抽查 | AH13: 是 | AI13: 是 | AJ13: 《中国电力财务有限公司结算账户管理规定》（中国电财〔2024〕215号）第三章第二十三条 | AK13: 财务部
I14: 财务管理-1.银行账户合规开立控制-控制措施06 | J14: 各单位财务部严格执行“先有产权、再建核算账套、后开账户”规则，推动账户模块与产权系统、核算系统数据贯通。产权发生变更时，系统自动推送账户调整预警任务，强制同步办理变更或撤销，杜绝“工商已注销、账户未撤销”。针对系统内产权划转，建立专用账户变更流程，划转完成后原单位账户台账自动删除，新单位自动继承账户信息，无需手工操作。 | M14: √ | T14: 线上管控-待建 | U14: 智慧共享财务平台 | V14: 1.账户台账； 2.系统贯通截图 | W14: 各单位-财务部-经办人员 | X14: 每季度 | Y14: 抽查 | AA14: 每年 | AB14: 抽查 | AH14: 否 | AI14: 否 | AK14: 财务部
C15: 资金资产安全 | D15: 银行账户开立 | E15: 银行账户未及时办理监控授权，资金动向无法实时监测，异常交易识别不及时，易诱发资金违规占用及挪用风险。 | F15: 对具备监控条件的银行账户未及时办理监控授权（银企直联），造成个别账户脱离监管，造成资金损失风险。 | G15: 2.银行账户办理监控控制 | H15: 银行账户及时纳入监控，定期监控资金流水动向及频次。 | I15: 财务管理-2.银行账户办理监控控制-控制措施01 | J15: 各单位财务部（经营类账户）或业务部门（非经营类账户）对具备监控条件的银行账户在完成开立同时办理监控授权，确保纳入公司资金监控体系。 | L15: √ | M15: √ | T15: 线上管控-已建 | U15: 智慧共享财务平台 | V15: 1.《银企互联账户授权书》； 2.《资金结算系统账户服务注册（变更）申请表》 | W15: 各单位-财务部-资金管理岗、各单位-财务部-资金审核岗、各单位-业务部门-经办岗、各单位-业务部门-负责人 | X15: 每季度 | Y15: 抽查 | AA15: 每年 | AB15: 抽查 | AH15: 是 | AI15: 是 | AJ15: 《国网财务部关于规范和加强商户号管理的通知》（财金[2025]2号）第四章第10条；《国家电网有限公司司库管理办法》（国网（财/2）345-2027）第三章第三十七条 | AK15: 财务部
C16: 资金资产安全 | D16: 商户号开立 | E16: 商户号开立未履行审批手续，缺少财务监督，易形成账外资金、私设小金库，引发资金流失风险。 | F16: 商户号未按规定履行审批流程，未严格审核开户机构（服务商）资质和协议，开通了转账功能，导致资金损失风险。 | G16: 3.商户号合规开立控制 | H16: 严格履行商户号开立审批手续，规范开户渠道、开户主体，严禁未批先设，严禁超标准开设。 | I16: 财务管理-3.商户号合规开立控制-控制措施01 | J16: 各单位业务部门严格执行商户号开立白名单（微信、支付宝、银联商务、电e宝）管理，通过智慧共享财务平台办理商户号开立审批，不在白名单范围内的开户事项，须履行二级单位本部审核和总部审批。开立协议应在数字化法治企业建设平台签订。开立后在规定时间内完成智慧共享财务平台纳管，若未按规定时间纳管的视为小金库。 | L16: √ | M16: √ | T16: 线上管控-已建 | U16: 智慧共享财务平台 | V16: 1.营业执照 2.组织机构设置文件 3.商户号开立业务办理回执（若有） | W16: 各单位-业务部门-经办岗 各单位-财务部-资金管理岗、各单位-财务部-资金审核岗 | X16: 每季度 | Y16: 抽查 | AA16: 每年 | AB16: 抽查 | AH16: 是 | AI16: 是 | AJ16: 《国网财务部关于规范和加强商户号管理的通知》（财金[2025]2号）第二章第1条 | AK16: 财务部
C17: 资金资产安全 | I17: 财务管理-3.商户号合规开立控制-控制措施02 | J17: 各单位财务部对商户号开立协议进行审核，核验绑定账户为本单位或上级单位对公账户，向关联银行账户提现资金周期不得超过T+1且自动划转。 | M17: √ | O17: √ | P17: √ | T17: 线上管控-已建 | U17: 数字化法治企业建设平台 | V17: 商户号开立协议 | W17: 各单位-财务部-资金管理岗、各单位-财务部-资金审核岗 | X17: 每季度 | Y17: 抽查 | AA17: 每年 | AB17: 抽查 | AH17: 是 | AI17: 是 | AJ17: 《国网财务部关于规范和加强商户号管理的通知》（财金[2025]2号）第二章第4条，第三章第7条 | AK17: 财务部
C18: 资金资产安全 | D18: 商户号开立 | E18: 商户号未及时办理监控授权，资金动向无法实时监测，异常交易识别不及时，易诱发资金违规占用及挪用风险。 | F18: 1.商户号未办理监控授权； 2.提现周期较长，向关联银行账户提现周期超过T+1日，资金未能及时回笼，存在资金沉淀及安全风险 | G18: 4.商户号办理监控控制 | H18: 商户号及时纳入监控，定期监控资金流水动向及频次。 | I18: 财务管理-4.商户号办理监控控制-控制措施01 | J18: 各单位业务部门对具备监控条件的商户号在完成开立手续后的规定时间内向数科公司办理商户号监控授权，确保纳入公司资金监控体系。 | L18: √ | M18: √ | T18: 线上管控-已建 | U18: 智慧共享财务平台 | V18: 监控授权书 | W18: 各单位-业务部门-经办岗、各单位-财务部-资金管理岗、各单位-财务部-资金审核岗 | X18: 每季度 | Y18: 抽查 | AA18: 每年 | AB18: 抽查 | AH18: 是 | AI18: 是 | AJ18: 《国网财务部关于规范和加强商户号管理的通知》（财金[2025]2号）第四章第10条；《国家电网有限公司司库管理办法》（国网（财/2）345-2023）第三章第三十七条
I19: 财务管理-4.商户号办理监控控制-控制措施02 | J19: 各单位财务部监控商户号资金，核查是否存在除“T+1”日自动划转至上级账户外的资金沉淀。 | P19: √ | T19: 线上管控-待建 | U19: 智慧共享财务平台 | V19: 1.资金流水明细； 2.余额调节表 | W19: 各单位-财务部-资金管理岗 | X19: 每季度 | Y19: 抽查 | AA19: 每年 | AB19: 抽查 | AH19: 是 | AI19: 是 | AJ19: 《国网财务部关于规范和加强商户号管理的通知》（财金[2025]2号）第四章第12条
D20: 数字钱包开立 | E20: 数字钱包开立未履行审批手续，易滋生账外账及小金库，未纳入系统统一监管，账实不符，引发资金流失风险。 | G20: 5.数字钱包合规开立控制 | H20: 严格履行数字钱包开立审批手续，规范开户渠道、开户主体，严禁未批先设。 | I20: 财务管理-5.数字钱包合规开立控制-控制措施01 | J20: 各单位财务部通过智慧共享财务平台办理数字钱包开、变、销审批，限定工行、农行、中行、建行、交行、邮储6家银行办理，超出管控标准及开户范围的，须经各二级单位本部审核和总部审批；相关手续办结后规定时间内，须在智慧共享财务平台完成开户信息维护。 | L20: √ | M20: √ | T20: 线上管控-已建 | U20: 智慧共享财务平台 | V20: 1.数字钱包开立系统流程截图； 2.开立业务办理回执； 3.数字钱包开立申请 | W20: 各单位-财务部-经办人员、各单位-财务部-资金审核岗、各单位-财务部-资金管理岗 | X20: 每季度 | Y20: 抽查 | AA20: 每年 | AB20: 抽查 | AH20: 是 | AI20: 是 | AJ20: 《国家电网有限公司司库管理办法》（国网（财/2）345-2023）第三章第二十八条、第三十五条 | AK20: 财务部
I21: 财务管理-5.数字钱包合规开立控制-控制措施02 | J21: 各单位财务部规范数字钱包开立经办管理，须由本人或授权人员办理，经办人员应为正式编制，手续须由至少两名人员共同办理，强化岗位制衡。 | K21: √ | T21: 线下管控 | V21: 2名经办人员外出审批单 | W21: 各单位-财务部-财务负责人 | X21: 每季度 | Y21: 抽查 | AA21: 每年 | AB21: 抽查 | AH21: 是 | AI21: 是 | AJ21: 《国家电网有限公司司库管理办法》（国网（财/2）345-2023）第三章第三十六条 | AK21: 财务部
G22: 6.数字钱包监控控制 | H22: 数字钱包及时纳入监控，定期监控资金流水动向及频次。 | I22: 财务管理-6.数字钱包办理监控控制-控制措施01 | J22: 各单位财务部对具备监控条件的数字钱包在完成开立同时办理监控授权，确保纳入公司资金监控体系。 | L22: √ | M22: √ | T22: 线上管控-已建 | U22: 智慧共享财务平台 | V22: 1.《银企互联账户授权书》； 2.《资金结算系统账户服务注册（变更）申请表》 | W22: 各单位-财务部-资金管理岗、各单位-财务部-资金审核岗、各单位-业务部门-经办岗、各单位-业务部门-负责人 | X22: 每季度 | Y22: 抽查 | AA22: 每年 | AB22: 抽查 | AH22: 是 | AI22: 是 | AJ22: 《国网财务部关于规范和加强商户号管理的通知》（财金[2025]2号）第四章第10条；《国家电网有限公司司库管理办法》（国网（财/2）345-2023）第三章第三十七条 | AK22: 财务部
C23: 资金资产安全 | D23: 银行账户变更 | E23: 银行账户变更不及时，与经营信息不一致；账户信息变更后未同步更新智慧共享财务平台登记信息，可能导致台账数据失真。 | G23: 7.银行账户变更及时性、必要性控制 | H23: 银行账户信息纳入管控并及时变更 | I23: 财务管理-7.银行账户变更及时性控制-控制措施01 | J23: 各单位财务部（经营类账户）或业务部门（非经营类账户）对于银行账户经营信息、账户属性发生变动的，及时完成变更分级审批流程；对于经营类账户的特殊事项变更（包括集团账户变更为独立账户、监控账户变更为无法监控账户、其他分类变更为专用账户），须经各二级单位本部审核和公司总部审批；账户信息变更后，按规定时间在智慧共享财务平台维护登记，确保银行账户台账信息准确、账实相符。 | L23: √ | M23: √ | Q23: √ | T23: 线上管控-已建 | U23: 系统自动控制 | V23: 《资金结算系统账户服务注册（变更）申请书》、《资金结算系统数字人民币钱包服务注册（变更）申请书》 | W23: 各单位-财务部-资金管理岗、各单位-财务部-资金审核岗、各单位-业务部门-经办岗、各单位-业务部门-负责人 | X23: 每季度 | Y23: 抽查 | AA23: 每年 | AB23: 抽查 | AH23: 是 | AI23: 是 | AJ23: 《国家电网有限公司司库管理办法》（国网（财/2）345-2027）第三章第三十条、第三十五条、第三十七条、第三十八条 | AK23: 财务部
I24: 财务管理-7.银行账户变更及时性控制-控制措施02 | J24: 各单位财务部（经营类账户）或业务部门（非经营类账户）规范银行账户变更经办管理，经办人员应为正式编制，手续须由至少两名人员共同办理，强化岗位制衡。 | K24: √ | T24: 线下管控 | V24: 2名经办人员外出审批单 | W24: 各单位-财务部-财务负责人、各单位-业务部-部门负责人 | X24: 每季度 | Y24: 抽查 | AA24: 每年 | AB24: 抽查 | AH24: 是 | AI24: 是 | AJ24: 《国家电网有限公司司库管理办法》（国网（财/2）345-2024）第三章第三十六条 | AK24: 财务部
A25: 财务管理 | B25: 资金管理 | C25: 资金资产安全 | D25: 商户号变更 | E25: 商户号变更不及时，与经营信息不一致；账户信息变更后未同步更新智慧共享财务平台登记信息，可能导致台账数据失真。 | G25: 8.商户号变更及时性、必要性控制 | H25: 商户号信息纳入管控并及时变更 | I25: 资金管理业务-8.商户号信息纳入管控并及时变更-控制措施01 | J25: 各单位业务部门对商户号相关信息发生变更时，应在智慧共享平台发起商户号变更申请，其中，商户号关联银行账户变更通过各二级单位本部审核、公司总部审批，其他变更由各二级单位自行管理。完成线下信息变更及线上变更登记审批后，须在规定时间内在智慧共享财务平台维护登记，确保商户号台账信息准确、账实相符。 | L25: √ | M25: √ | Q25: √ | T25: 线上管控-已建 | U25: 系统自动控制 | V25: 《资金结算系统商户号服务注册（变更）申请书》 | W25: 各单位-财务部-资金管理岗、各单位-财务部-资金审核岗 | X25: 每季度 | Y25: 抽查 | AA25: 每年 | AB25: 抽查 | AH25: 是 | AI25: 是 | AJ25: 《国家电网有限公司司库管理办法》（国网（财/2）345-2023）第三章第三十条、第三十五条、第三十七条、第三十八条 | AK25: 财务部
C26: 资金资产安全 | D26: 数字钱包变更 | E26: 数字钱包变更不及时，与经营信息不一致；账户信息变更后未同步更新智慧共享财务平台登记信息，可能导致台账数据失真。 | G26: 9.数字钱包变更及时性、必要性控制 | H26: 数字钱包信息纳入管控并及时变更 | I26: 财务管理-9.数字钱包信息纳入管控并及时变更-控制措施01 | J26: 各单位财务部对于数字钱包经营信息、账户属性发生变动的，及时完成变更分级审批流程，对于特殊事项变更（监控账户变更为无法监控账户），须经各二级单位本部审核和公司总部审批；信息变更后，按规定时间在智慧共享财务平台维护登记，确保数字钱台账信息准确、账实相符。 | L26: √ | M26: √ | Q26: √ | T26: 线上管控-已建 | U26: 系统自动控制 | V26: 《资金结算系统数字人民币钱包服务注册（变更）申请书》 | W26: 各单位-财务部-资金管理岗、各单位-财务部-资金审核岗 | X26: 每季度 | Y26: 抽查 | AA26: 每年 | AB26: 抽查 | AH26: 是 | AI26: 是 | AJ26: 《国家电网有限公司司库管理办法》（国网（财/2）345-2023）第三章第三十条、第三十五条、第三十七条、第三十八条 | AK26: 财务部
I27: 财务管理-9.数字钱包信息纳入管控并及时变更-控制措施02 | J27: 各单位财务部规范数字钱包变更经办管理，经办人员应为正式编制，手续须由至少两名人员共同办理，强化岗位制衡。 | K27: √ | T27: 线下管控 | V27: 2名经办人员外出审批单 | W27: 各单位-财务部-财务负责人、各单位-业务部-部门负责人 | X27: 每季度 | Y27: 抽查 | AA27: 每年 | AB27: 抽查 | AH27: 是 | AI27: 是 | AJ27: 《国家电网有限公司司库管理办法》（国网（财/2）345-2023）第三章第三十六条 | AK27: 财务部
C28: 资金资产安全 | D28: 银行账户撤销 | E28: 银行账户撤销不及时，销户滞后于工商主体注销，久悬账户未及时注销，应销未销诱发“账外账”风险。 | F28: 1.银行账户注销不及时：开立主体已完成工商注销，但账户仍存续。 2.银行已销户未登记：银行账户已注销，但在中台台账登记不及时。 | G28: 34.银行账户注销及时性、规范性控制 | H28: 银行账户在工商变更或注销前、业务完结后（如工程完结农民工专户及时注销）完成账户注销，及时登记台账。 | I28: 财务管理-34.银行账户注销及时性、规范性控制-控制措施01 | J28: 各单位财务部（经营类账户）或业务部门（非经营类账户）规范银行账户撤销经办管理，须由本人或授权人员办理，经办人员应为正式编制，手续须由至少两名人员共同办理，强化岗位制衡。 | K28: √ | T28: 线下管控 | V28: 2名经办人员外出审批单 | W28: 各单位-财务部-财务负责人、各单位-业务部门-经办岗 | X28: 每季度 | Y28: 抽查 | AA28: 每年 | AB28: 抽查 | AH28: 是 | AI28: 是 | AJ28: 《国家电网有限公司司库管理办法》（国网（财/2）345-2023）第三章第三节第三十六条 | AK28: 财务部
I29: 财务管理-34.银行账户注销及时性、规范性控制-控制措施02 | J29: 各单位财务部（经营类账户）或业务部门（非经营类账户）规范办理银行账户注销，终止监控授权后按制度要求时限办理销户，严格执行先销账户、后销工商主体顺序，注销相关手续办结后在规定时间内，完成智慧共享财务平台销户登记，报二级单位备案。 | L29: √ | M29: √ | T29: 线上管控-已建 | U29: 智慧共享财务平台 | V29: 1.《终止银企互联账户授权书》； 2《资金结算系统账户服务注册（变更）申请表》； 3.银行账户撤销业务办理回执 | W29: 各单位-财务部-资金管理岗、各单位-财务部-资金审核岗、各单位-业务部门-经办岗 | X29: 每季度 | Y29: 抽查 | AA29: 每年 | AB29: 抽查 | AH29: 是 | AI29: 是 | AJ29: 《国家电网有限公司司库管理办法》（国网（财/2）345-2023）第三章第二十九条、第三十六条、第三十七条 | AK29: 财务部
I30: 财务管理-34.银行账户注销及时性、规范性控制-控制措施03 | J30: 各单位财务部加强低效、无效账户监控。销户资金应及时、全量回笼。 | Q30: √ | T30: 线上管控-待建 | U30: 智慧共享财务平台 | V30: 低效账户督办单 | W30: 各单位-财务部-资金管理岗、各单位-业务部门-经办岗 | X30: 每季度 | Y30: 抽查 | AA30: 每年 | AB30: 抽查 | AH30: 是 | AI30: 是 | AJ30: 《国家电网有限公司司库管理办法》（国网（财/2）345-2023）第十一章第二百九十八条 | AK30: 财务部
C31: 资金资产安全 | D31: 商户号撤销 | E31: 商户号撤销不及时，销户滞后于工商主体注销，应销未销诱发“账外账”风险。 | G31: 35.商户号注销及时性、规范性控制 | H31: 商户号在工商注销前完成账户注销，及时登记台账。 | I31: 财务管理-35.商户号注销及时性、规范性控制-控制措施01 | J31: 各单位业务部门提交商户号撤销资料，负责资料完整性、真实性。 | M31: √ | T31: 线下管控 | V31: 1.商户号注销申请书； 2.营业执照； 3.法人身份证 | W31: 各单位-业务部门-经办岗 | X31: 每季度 | Y31: 抽查 | AA31: 每年 | AB31: 抽查 | AH31: 否 | AK31: 财务部
I32: 财务管理-35.商户号注销及时性、规范性控制-控制措施02 | J32: 各单位业务部门规范商户号注销程序，及时完成商户号资金清算。商户号注销时，应在智慧共享平台发起商户号注销申请，注销审批流程由各二级单位审批。销户资金应及时、全量回笼。 | L32: √ | M32: √ | T32: 线上管控-已建 | U32: 智慧共享财务平台 | V32: 商户号撤销业务办理回执（若有） | W32: 各单位-财务部-资金管理岗、各单位-财务部-资金审核岗 | X32: 每季度 | Y32: 抽查 | AA32: 每年 | AB32: 抽查 | AH32: 是 | AI32: 是 | AJ32: 《国家电网有限公司司库管理办法》（国网（财/2）345-2023）第三章第二十九条、第三十六条、第三十七条 | AK32: 财务部
C33: 资金资产安全 | D33: 数字钱包撤销 | E33: 数字钱包撤销不规范，销户滞后于工商主体注销，应销未销诱发“账外账”风险。 | G33: 36.数字钱包注销及时性、规范性控制 | H33: 数字钱包在工商注销前完成账户注销，及时登记台账。 | I33: 财务管理-36.数字钱包注销及时性、规范性控制-控制措施01 | J33: 各单位财务部规范数字钱包撤销经办管理，须由本人或授权人员办理，经办人员应为正式编制，手续须由至少两名人员共同办理，强化岗位制衡。 | K33: √ | T33: 线下管控 | V33: 2名经办人员外出审批单 | W33: 各单位-财务部-财务负责人 | X33: 每季度 | Y33: 抽查 | AA33: 每年 | AB33: 抽查 | AH33: 是 | AI33: 是 | AJ33: 《国家电网有限公司司库管理办法》（国网（财/2）345-2023）第三章第三十六条 | AK33: 财务部
I34: 财务管理-36.数字钱包注销及时性、规范性控制-控制措施02 | J34: 各单位财务部规范办理数字钱包注销，终止监控授权后按制度要求时限办理销户，严格执行先销数字钱包、后销工商主体顺序，注销后在智慧财务中台完成登记。销户资金应及时、全量回笼。 | L34: √ | M34: √ | T34: 线上管控-已建 | U34: 智慧共享财务平台 | V34: 1.《终止银企互联数字人民币钱包授权书》； 2.《资金结算系统数字人民币钱包服务注册（变更）申请表》 3.数字人民币撤销业务办理回执（若有） | W34: 各单位-财务部-资金管理岗、各单位-财务部-资金审核岗、各单位-业务部门-经办岗 | X34: 每季度 | Y34: 抽查 | AA34: 每年 | AB34: 抽查 | AH34: 是 | AI34: 是 | AJ34: 《国家电网有限公司司库管理办法》（国网（财/2）345-2023）第三章第二十九条、第三十六条、第三十七条 | AK34: 财务部
C35: 会计信息真实完整 | D35: 账户核算范围管理 | E35: 银行账户核算不完整，会计信息不准确，产生资金安全风险。 | F35: 银行账户核算不完整：账内银行账户与开户清单、账内商户号与开立商户号清单不一致，存在账外资金，导致资金失管、账实不符，引发资金安全风险。 | G35: 2.账户完整性管控 | H35: 银行账户和商户号核算完整、准确。 | I35: 会计核算-2.账户完整性管控-控制措施01 | J35: 银行账户和商户号核算完整性控制。每年10月底前、次年1月初，各单位会计人员会同决算审计会计师事务所，前往人民银行或基本户开户行打印全量开户清单；登录各商户号网上平台，获取全量商户号清单。逐一与账内核算银行账户和商户号进行比对，确保以公司名义开立、可独立支配账户资金、承担资金安全管理责任的银行账户和商户号，均完整纳入账内核算。 | M35: √ | Q35: √ | T35: 线上管控-待建 | U35: 智慧共享财务平台 | V35: 1.银行账户开立清单 2.商户号清单 | W35: 各单位-财务部-总账管理 | X35: 每季 | Y35: 全量 | AA35: 年度 | AB35: 全量 | AD35: 账户完整性监督场景（待建） | AE35: 每季 | AF35: 全量 | AH35: 是 | AI35: 是 | AJ35: 1.《国家电网有限公司司库管理办法》（国家电网企管〔2023〕88号）-第三章 银行账户（数字钱包）管理-第二十五条 2.《国网财务部关于进一步加强社会保障有关账户管理和资金核算的通知》（财金〔2024〕12号） 3.《国家电网有限公司2025年度财务决算审计工作指引》 | AK35: 财务部
A36: 财务管理 | B36: 一、预算管理 | C36: 会计信息真实完整、资金资产安全、税务合规 | D36: 战略支撑 （事前） | E36: 1.财务规划与公司战略协同不足，未有效承接战略指标体系。 2.规划没有科学分解到年度预算，落地执行出现偏差。 3.预算编制未与核价规则有效衔接，导致核价结果不及预期，进而影响战略目标的实现。 | F36: 规划目标与战略脱节。未按照战略目标体系设置规划目标，各级规划目标未有效协同，目标测算未与核价规则衔接，年度决算完成后未与规划目标进行对比分析。 | G36: 1.规划目标与战略一致性审核 | H36: 规划目标测算有效衔接战略指标体系及核价规则，推动规划投资全部纳入核价、核价规则深度融入经营，经营成果有效落实规划。 | I36: 预算管理-1.规划目标与战略一致性审核-控制措施01 | J36: 1.战略指标一致性审查。国网及各二级单位财务部在规划编制环节核查经营目标与战略指标体系的一致性，对指标缺失或脱节的情形，不予通过。 | N36: √ | Q36: √ | T36: 线下管控 | U36: - | V36: 1.公司战略规划方案； 2.公司预算方案。 | W36: 各单位-财务部-预算专责 | X36: 年度 | Y36: 全量 | Z36: - | AA36: 年度 | AB36: 全量 | AC36: - | AD36: - | AE36: - | AF36: - | AG36: - | AH36: 是 | AI36: 是 | AJ36: 《国家电网有限公司全面预算管理办法》（国网（财/2）375-2026）第三条、第十四条 | AK36: 财务部
I37: 预算管理-1.规划目标与战略一致性审核-控制措施02 | J37: 2.建立“五年规划、三年核价、年度经营”相贯通的滚动预算管控机制。国网及各二级单位财务部在智慧共享财务平台部署多维联动测算模型，建立“1+N”管控场景（1个监管业务典型场景，N个非监管业务个性化场景），在进行财务规划编制时，以核价参数为约束，合理安排规划期年度经营目标、投资和成本，逐年滚动预测，对比分析规划目标、核价参数落实情况，科学编制预算。 | N37: √ | Q37: √ | S37: √ | T37: 线上管控-待建 | U37: 智慧共享财务平台 | V37: 1.公司战略规划方案； 2.公司预算方案； 3.多维联动测算模型。 | W37: 各单位-财务部-预算专责 | X37: 年度 | Y37: 全量 | Z37: - | AA37: 年度 | AB37: 全量 | AC37: - | AD37: 多维联动测算模型 | AE37: 年度 | AF37: 全量 | AG37: - | AH37: 是 | AI37: 是 | AJ37: 《国家电网有限公司全面预算管理办法》（国网（财/2）375-2026）第三条、第十四条 | AK37: 财务部
C38: 会计信息真实完整、资金资产安全、税务合规 | D38: 经营决策 （事前） | E38: 1.决策依据不充分，对经营形势研判不足，缺乏充分调研和可行性分析。 2.决策流程不规范，未严格履行决策程序，导致预算决策出现偏差。 3.预算调整不及时，预算基础或边际条件发生重大变化时，未及时履行预算调整程序。 | F38: 预算决策流程不规范。重大项目投资未按规定履行本单位“三重一大”决策程序；预算决策流程流于形式，部分事项先执行后补签、越权审批或缺少书面记录；项目已出现明显亏损或环境变化，仍继续投入，缺少主动中止或调整的机制。 | G38: 2.预算决策程序审核 | H38: 预算决策依据充分、完整，程序规范、有效，及时响应预算基础或边际条件重大变化，确保公司经营稳健。 | I38: 预算管理-2.预算决策程序审核-控制措施01 | J38: 1.强化事前可研论证。每年，各级业务部门结合实际情况，明确本本专业投入重点，并据此组织开展可研评审及项目储备。原则上所有纳入业务预算的项目均需履行项目储备程序，并向财务部提供项目清单，清单中包括以下信息：项目名称、金额、建设内容、可研评审及批复文号等。 | M38: √ | N38: √ | T38: 线下管控 | U38: - | V38: 1.项目立项相关材料； 2.储备项目明细。 | W38: 各单位-业务部门-经办人 | X38: 年度 | Y38: 抽查 | Z38: - | AA38: 年度 | AB38: 抽查 | AC38: - | AD38: - | AE38: - | AF38: - | AG38: - | AH38: 是 | AI38: 是 | AJ38: 《国家电网有限公司全面预算管理办法》（国网（财/2）375-2026）第十六条、第二十二条;财预〔2025〕27号 国网财务部关于印发《国家电网有限公司财务支出可研经济性与财务合规性评价工作指引（2025）》的通知第一章1.4 | AK38: 财务部
I39: 预算管理-2.预算决策程序审核-控制措施02 | J39: 2.规范决策程序。各级单位办公室、法律部等归口管理部门制定决策事项清单，对需纳入“三重一大”决策的预算事项进行明确；对预算方案决策程序进行合规性审核，决策会议由专人记录，会议纪要由会议主持人或公司主要负责同志签发，事后及时归档，确保决策流程完整规范。 | M39: √ | N39: √ | T39: 线下管控 | U39: - | V39: 1.决策事项清单； 2.会议纪要。 | W39: 各单位-业务部门-经办人 | X39: 年度 | Y39: 全量 | Z39: - | AA39: 年度 | AB39: 全量 | AC39: - | AD39: - | AE39: - | AF39: - | AG39: - | AH39: 是 | AI39: 是 | AJ39: 《国家电网有限公司全面预算管理办法》（国网（财/2）375-2026）第十四条、第十五条 | AK39: 财务部
I40: 预算管理-2.预算决策程序审核-控制措施03 | J40: 3.及时履行预算调整程序。在预算基础或边际条件发生重大变化时，各级单位财务部要及时组织开展经营分析，及时启动预算调整程序，在预算调整批复后，及时推进落地实施，确保公司稳健经营。 | N40: √ | Q40: √ | T40: 线上管控-已建 | U40: 智慧共享财务平台 | V40: 1.公司预算调整方案； 2.决策记录。 | W40: 各单位-业务部门-经办人；各单位-财务部-预算专责 | X40: 年度 | Y40: 全量 | Z40: - | AA40: 年度 | AB40: 全量 | AC40: - | AD40: 预算调整模块 | AE40: 年度 | AF40: 全量 | AG40: - | AH40: 是 | AI40: 是 | AJ40: 《国家电网有限公司全面预算管理办法》（国网（财/2）375-2026）第三十七条、第三十八条、三十九条 | AK40: 财务部
C41: 会计信息真实完整、资金资产安全、税务合规 | D41: 资源分配 （事前） | E41: 1.预算责任泛化。预算责任框架体系尚未健全完善，立项颗粒度不精细，预期目标不明确，导致资源错配或低效使用。 2.资源分配不精准。资源投入与公司重点任务脱节，区域、网架资源分配不均衡、布局不合理，影响电网均衡发展。 | F41: 生产性投入不足。资源分配结构不合理，生产性投入占比偏低，难以满足安全生产、设备运维等核心业务需求。 | G41: 3.资源配置精准性管控 | H41: 资源分配满足公司战略落地、监审核价、业务发展等预期目标要求，并确保预算责任主体明确。 | I41: 预算管理-3.资源配置精准性管控-控制措施01 | J41: 1.完善预算责任框架体系。各级单位财务部在智慧共享财务平台中，完善预算责任框架体系，细化成本中心、利润中心，延伸至供电所或班组（产业、金融、国际、战新等其他业务板块根据自身业务实际设置成本中心、利润中心），并将预算指标层层分解。 | N41: √ | Q41: √ | T41: 线上管控-待建 | U41: 智慧共享财务平台 | V41: 1.预算责任框架体系。 | W41: 各单位-财务部-预算专责 | X41: 年度 | Y41: 全量 | Z41: - | AA41: 年度 | AB41: 全量 | AC41: - | AD41: 预算下达模块 | AE41: 年度 | AF41: 全量 | AG41: - | AH41: 是 | AI41: 是 | AJ41: 《国家电网有限公司全面预算管理办法》（国网（财/2）375-2026）第三十二条 | AK41: 财务部
I42: 预算管理-3.资源配置精准性管控-控制措施02 | J42: 2.强化财务支出分类管理。健全财务支出四级分类体系，对于资产动因类支出，原则上应关联至三级同源目录资产（价值核算单元）；对于组织动因类支出，分解至具体业务单元或部门，原则上以供电所为最小单元进行建项和执行管控。 | N42: √ | Q42: √ | T42: 线下管控 | V42: 1.预算分解明细。 | W42: 各单位-财务部-成本专责 | X42: 年度 | Y42: 全量 | Z42: - | AA42: 年度 | AB42: 全量 | AC42: - | AD42: - | AE42: - | AF42: - | AG42: - | AH42: 是 | AI42: 是 | AJ42: 《国家电网有限公司全面预算管理办法》（国网（财/2）375-2026）第三十二条 | AK42: 财务部
I43: 预算管理-3.资源配置精准性管控-控制措施03 | J43: 3.依托作业标准成本开展资源配置。国网财务部根据业务部门、各级单位在线填报或通过系统推送变电站数量、线路长度、人员数量等业务动因参数，组织审定各业务投向、各单位标准成本，并以此为基础，编制下达检修运维费用预算。各级电网单位财务部开展本地化改造，在上级核定的成本预算范围内，开展本层级检修运维费用预算分解。产业、金融、国际、战新等其他业务板块开展其他运营标准成本本地化改造，加强费用预算管控。 | N43: √ | Q43: √ | T43: 线上管控-已建 | U43: 智慧共享财务平台 | V43: 1.标准成本体系。 | W43: 各单位-财务部-成本专责 | X43: 年度 | Y43: 全量 | Z43: - | AA43: 年度 | AB43: 全量 | AC43: - | AD43: 预算下达模块 | AE43: 年度 | AF43: 全量 | AG43: - | AH43: 是 | AI43: 是 | AJ43: 《国家电网有限公司全面预算管理办法》（国网（财/2）375-2026）第三十二条 | AK43: 财务部
C44: 会计信息真实完整、资金资产安全、税务合规 | D44: 执行控制 （事中） | E44: 1.缺乏经营目标过程管控，未及时进行预算执行情况分析，导致预算执行不均衡或年度预算目标无法完成。 | F44: 未完成预算下达指标。决算审核后，部分经营指标未完成年度预算下达目标。 | G44: 4.预算执行情况分析 | H44: 严格预算执行控制，及时发现和报告重大预算事项，顺利实现公司战略及经营目标。 | I44: 预算管理-4.预算执行情况分析-控制措施01 | J44: 定期开展预算执行情况分析。国网及各级单位财务部设定月度预算执行目标，在智慧共享财务平台部署，并设置预警阈值，每月，各级单位财务部将实际执行进度与预算进度进行对比分析，并提前制定预控措施，确保均衡规范完成年度目标，其中：对于电网监管业务，重点关注电量及增速、电价水平、成本入账进度、利润水平等执行情况及均衡性；对于产业、金融、国际、战新及原集体企业等市场化业务，重点关注利润进度、毛利率水平、关联交易情况等。 | N44: √ | Q44: √ | T44: 线上管控-待建 | U44: 智慧共享财务平台 | V44: 1.预算执行分析报告。 | W44: 各单位-财务部-预算专责 | X44: 年度 | Y44: 抽查 | Z44: - | AA44: 年度 | AB44: 抽查 | AC44: - | AD44: 预算分析模块 | AE44: 月度 | AF44: 全量 | AG44: - | AH44: 是 | AI44: 是 | AJ44: 《国家电网有限公司全面预算管理办法》（国网（财/2）375-2026）第四十条-第四十三条 | AK44: 财务部
E45: 2.成本预算执行管控不严，导致成本列支不规范、超预算列支等问题，包括： （1）无预算、超预算列支成本，导致预算管控失效，引发资金管控风险； （2）预算单控费用执行不严，“三公”经费、会议费等重点支出预算未实施单项控制，引发重点费用管控失效风险； （3）资本性支出与成本性支出未严格区分，导致会计核算混乱，引发会计信息质量失真； （4）项目支出不规范，实际列支内容与预算安排不一致，引发项目资金滥用及会计信息失真风险； （5）成本开支内容不符合输配电成本监审要求，影响输配电价格核定，引发监管合规风险。 | F45: 成本性项目及资本性项目列支超年度预算。部分成本性项目及资本性项目在列支时，未及时履行调整流程，导致实际支出超出年度预算。 | G45: 5.各会计科目、项目预算系统编制及控制 | H45: 重点费用单项列支规范，与预算下达指标保持一致。 | I45: 预算管理-5.各会计科目、项目预算系统编制及控制-控制措施01 | J45: 系统部署项目预算控制规则。国网及各二级单位财务部根据项目可研批复金额，在智慧共享财务平台中对各类成本性、资本性项目、费用科目配置预算及控制规则，通过系统预警、规则强控，确保无预算不支出、有预算不超支。 | N45: √ | Q45: √ | T45: 线上管控-已建 | U45: 智慧共享财务平台 | V45: 1.业务预算需求审批表； 2.项目可研评审批复文件。 | W45: 各单位-财务部-项目专责 | X45: 年度 | Y45: 抽查 | Z45: - | AA45: 年度 | AB45: 抽查 | AC45: - | AD45: 财务预算编审控制和预算申报服务模块 | AE45: 年度 | AF45: 全量 | AG45: - | AH45: 是 | AI45: 是 | AJ45: 《国家电网有限公司全面预算管理办法》（国网（财/2）375-2026）第三十五条 | AK45: 财务部
F46: 单项费用控制失效。对于“三公” 经费、会议费进行总额控制，未单独进行预算分解，无法进行单项控制。 | G46: 6.重点单项费用预算编制及控制 | H46: 公司可控费用纳入预算统一管理，严禁发生预算外支出。 | I46: 预算管理-6.重点单项费用预算编制及控制-控制措施01 | J46: 上级部署单控费用预算。国网及各二级单位财务部在智慧共享财务平台中根据年度预算对“三公”经费、会议费等实施单项控制，由上级单位在系统中核定，各级单位如需调整需履行预算调整程序，确保重点费用预算能控、在控。 | N46: √ | Q46: √ | T46: 线上管控-已建 | U46: 智慧共享财务平台 | V46: 1.费用支出明细； 2.单项费用预算。 | W46: 各单位-财务部-预算专责 | X46: 年度 | Y46: 抽查 | Z46: - | AA46: 年度 | AB46: 抽查 | AC46: - | AD46: 财务预算申报服务模块 | AE46: 年度 | AF46: 全量 | AG46: - | AH46: 是 | AI46: 是 | AJ46: 《国家电网有限公司全面预算管理办法》（国网（财/2）375-2026）第三十五条 | AK46: 财务部
F47: 项目立项管理不规范。项目可研审核不严格，例如，存在通过生产大修项目购买电脑、隔离开关等固定资产的情况。 | G47: 7.项目可研经济性、财务合规性检查 | H47: 项目立项规范合规，项目支出性质准确。 | I47: 预算管理-7.项目可研经济性、财务合规性检查-控制措施01 | J47: 开展项目支出性质检查。各级单位财务部协同各级经研院所组织开展项目可研经济性、财务合规性评审，检查立项依据是否充分、立项类别是否准确，重点关注：报告中应包含维修资产的设备编码、资产原值等关键信息，检查项目金额是否超过维修资产原值的50%，物料清单中是否包含固定资产目录中设备。 | N47: √ | Q47: √ | T47: 线下管控 | U47: - | V47: 1.项目可研报告或建议书； 2.储备项目明细。 | W47: 各单位-财务部-项目专责 | X47: 年度 | Y47: 抽查 | Z47: - | AA47: 年度 | AB47: 抽查 | AC47: - | AD47: - | AE47: - | AF47: - | AG47: - | AH47: 是 | AI47: 是 | AJ47: 《国家电网有限公司全面预算管理办法》（国网（财/2）375-2026）第十六条、第二十二条;财预〔2025〕27号 国网财务部关于印发《国家电网有限公司财务支出可研经济性与财务合规性评价工作指引（2025）》的通知第一章1.4 | AK47: 财务部
F48: 项目结算不准确。多结算施工费用；虚列项目，跨期结算项目费用，结算依据不充分。 | G48: 8.项目预算执行控制 | H48: 项目支出规范，实际列支内容与预算安排保持一致。 | I48: 预算管理-8.项目预算执行控制-控制措施01 | J48: 开展项目实施内容检查。各级单位业务部门在项目完工后，应组织专业机构出具项目结算报告，并对项目支出内容进行检查，重点关注：施工费结算方式是否与合同一致、是否采购可研报告之外的物料、实施内容是否变更，如有变更是否履行变更程序等。 各级单位财务部在智慧共享财务平台中对项目支出合同、发票、上传的材料，参考项目可研报告中项目实施内容，从完整性、规范性、合理性等方面进行线上审核，确保项目支出规范。 | M48: √ | N48: √ | Q48: √ | T48: 线上管控-已建 | U48: 智慧共享财务平台 | V48: 1.项目结算报告； 2.项目支出报账材料； 3.项目可研报告。 | W48: 各单位-业务部门-经办人；各单位-财务部-项目专责 | X48: 年度 | Y48: 抽查 | Z48: - | AA48: 年度 | AB48: 抽查 | AC48: - | AD48: 采购服务报账模块 | AE48: 年度 | AF48: 全量 | AG48: - | AH48: 是 | AI48: 是 | AJ48: 《国家电网有限公司全面预算管理办法》（国网（财/2）375-2026）第三十五条 | AK48: 财务部
F49: 监管单位成本预算安排规模与监审要求不符。材料修理费、其他运营费用安排严重偏离成本监审费率，与非监管单位关联交易利润率超10%，监管业务中列支广告宣传费（不含停电故障信息公告、电力安全保护宣传、电力设备安全警示等）等。 | G49: 9.预算编制与输配电成本一致性审核 | H49: 成本开支符合输配电成本监审要求。 | I49: 预算管理-9.预算编制与输配电成本一致性审核-控制措施01 | J49: 强化核价规则约束。各级单位财务部根据成本监审及核价规则，设置预警规则，监控成本执行情况，重点关注：材料修理费、其他运营费用（含管理类费用）费率是否与核价费率严重偏离，引发成本核减或费率下滑风险；对广告宣传费、研究开发费等特殊敏感会计科目严格审核，确保相关成本支出符合成本监审要求。 | N49: √ | Q49: √ | T49: 线下管控 | U49: - | V49: 1.成本支出相关资料。 | W49: 各单位-财务部-电价专责 | X49: 年度 | Y49: 抽查 | Z49: - | AA49: 年度 | AB49: 抽查 | AC49: - | AD49: - | AE49: - | AF49: - | AG49: - | AH49: 是 | AI49: 是 | AJ49: 《国家电网有限公司全面预算管理办法》（国网（财/2）375-2026）第二十二条、第三十五条 | AK49: 财务部

Sheet 汇总 (程玉策)
A1: 风控矩阵-财务管理
A2: 业 务 条 线 | B2: 业 务 领 域 | C2: 控 制 目 标 | D2: 业务流程步骤 | E2: 经营风险 | F2: 典型问题 | G2: 关键控制点 | H2: 控制要求 | I2: 控制措施 编号 | J2: 控制措施 | K2: 控制措施分类 | T2: 控制方式 | U2: 控制系统 | V2: 控制载体 | W2: 责任主体 | X2: 业务自评价 | AA2: 集团监督评价 | AD2: 数字化监督场景 | AH2: 现有制度及文件落实情况 | AK2: 总部审核部门 | AL2: 关联关系
K3: 不相容岗位 | L3: 分级授权 | M3: 业务真实性校验 | N3: 预算管控 | O3: 合同控制 | P3: 收付控制 | Q3: 会计监督 | R3: 财产保护 | S3: 分析与评价 | X3: 评价频率 | Y3: 评价范围 | Z3: 评价结论 | AA3: 评价频率 | AB3: 评价范围 | AC3: 评价结论 | AD3: 数字化监督场景 | AE3: 监督频率 | AF3: 监督范围 | AG3: 评价结论 | AH3: 是否已要求 | AI3: 是否满足要求 | AJ3: 对应制度及文件名称
A4: 股权投资及产权管理 | B4: 1.股权项目投资管理 | C4: 企业经营管理合法合规 | D4: 1.股权投资项目储备 | E4: 开展非主业、禁止类或负面清单的股权投资； 违反“压减”要求，在法人/管理层级超限的情况下新设子企业或开展并购； 对连续亏损或高负债企业安排新增股权投资，加大投资风险与资金安全风险。 | F4: 年度财务决算批复问题清单：部分单位存在房地产、文旅企业投资的问题。 | G4: 1.股权投资项目提出合规性控制 | H4: 确保股权行为全面合规，有效防范投资风险与资金安全风险。 | I4: 股权投资及产权管理－1.股权投资项目提出合规性控制－控制措施01 | J4: 各单位提出投资申请时需对应核查负面清单及禁止类清单，需列表说明核查的要点和依据，主要关注： 1.负面清单禁止类-不符合国家产业政策的投资项目、非主业、产能释放率低于70%的各类装备制造产品生产线新建及股权收购项目、名股实债投资等； 2.特别监管无关多元、多层架构、控股不控权、虚假控股、违规挂靠、靠企吃企等事项； 3.股权管理办法中严禁事项-不得对连续亏损或高负债企业新增投资、不得新增开展PPP项目投资、不得通过首次小金额新设、逐年大金额增资等方式压低投资规模或拆分项目规避监管等事项。 4.参股股权投资-不得新增财务性参股投资；不得新增无实际控制人的参股投资等。 | M4: √ | T4: 线上管控-已建 | U4: 智慧共享财务平台－资本在线运营－项目遴选管理 | V4: 1.股权投资项目基本信息表； 2.逐条审查依据； | W4: 各级单位-投资发起部门-投资管理岗 | X4: 每年 | Y4: 抽查 | AA4: 每年 | AB4: 抽查 | AH4: 否 | AI4: 是 | AJ4: 国网（财/2）198－2025《国家电网有限公司股权管理办法》第八十六条 | AK4: 总部业务管理部门；总部财务部
I5: 股权投资及产权管理－1.股权投资项目提出合规性控制－控制措施02 | J5: 二级单位审核项目意向时，依据负面清单，对清单所列事项逐条进行审查，列明审查依据，核查人需签字确认核查内容，确保逐条审查责任落实到具体人员。负面清单核查岗位与项目发起岗位为不相容岗位控制。 | K5: √ | M5: √ | S5: √ | T5: 线下管控 | V5: 1.合规审查清单； 2.二级单位审查意见。 | W5: 各级单位-投资发起部门-投资管理岗；二级单位-财务部-资产产权管理岗 | X5: 每年 | Y5: 抽查 | AA5: 每年 | AB5: 抽查 | AH5: 否 | AI5: 是 | AJ5: 《国家电网有限公司关于进一步强化参股股权管理有关事项的通知》一、二、三 | AK5: 总部业务管理部门；总部财务部
I6: 股权投资及产权管理－1.股权投资项目提出合规性控制－控制措施03 | J6: 智慧共享财务平台项目遴选模块中：“系统内置非主业、禁止类及负面清单等数据库，在投资项目遴选环节自动比对项目属性、行业分类及投资类型，命中清单内容的项目自动判定为不合规，并阻断审批流程、推送风险提示。” | K6: √ | L6: √ | M6: √ | T6: 线上管控-待建 | U6: 智慧共享财务平台－资本在线运营－项目遴选管理 | V6: 1.股权投资项目基本信息表； 2.系统风险提示； | W6: 总部-信息化部门-信息化人员 | X6: 每年 | Y6: 抽查 | AA6: 每年 | AB6: 抽查 | AD6: 投资项目合规性监督场景 | AE6: 实时 | AF6: 全量 | AH6: 是 | AI6: 是 | AJ6: 国网（财/2）198－2025《国家电网有限公司股权管理办法》第八十六条、附件1 | AK6: 总部信息化部门
C7: 企业经营管理合法合规、提高经营效率和效果 | D7: 1.股权投资项目储备 | E7: 可行性研究、尽职调查工作不规范，报告存在内容缺失、论证不充分的问题，且投资回报测算缺失、结果模糊，导致投资决策依据不实。 | F7: 公开渠道查询央企案例：投资效益不及预，尽调未发现重大风险事项，交割后形成潜在损失。 | G7: 2.项目遴选控制控制 | H7: 严格按照“逐级择优、滚动递补”原则进行项目遴选，确保尽调范围覆盖法律、财务、业务等维度。 | I7: 股权投资及产权管理－2.可研尽调控制－控制措施01 | J7: 合规性审核通过的前提下，各级单位开展可行性研究，对于新设投资，重点关注：投资回报不低于国资委投资负面清单对投资回报率的要求；从事竞争业务企业预期收益率不低于国资委业绩绩效考核经济增加值(EVA)指标；不少于5年利润情况等。 对于增资收并购情形，重点关注：标的企业过去三年的收益情况、司法诉讼、股权结构不存在代持或交叉持股、无失信被执行记录且银行授信评级不低于AA等内容。 | M7: √ | S7: √ | T7: 线下管控 | V7: 1.股权投资可行性研究报告或尽调报告。 | W7: 各级单位-投资发起部门-投资管理岗；二级单位-业务管理部门-业务审核人员；二级单位-财务部-资产产权管理岗 | X7: 每年 | Y7: 抽查 | AA7: 每年 | AB7: 抽查 | AH7: 是 | AI7: 是 | AJ7: 国网（财/2）198－2025《国家电网有限公司股权管理办法》第八十八条（一）、附件2 | AK7: 总部业务管理部门；总部财务部
I8: 股权投资及产权管理－2.可研尽调控制－控制措施02 | J8: 各级单位编制可研报告需明确可研基准日，且可研基准日与项目首次评审时间不得超过六个月，剔除建设期后，可研经济性预测时间不得少于五年。可研报告编制人、审核人、复核人执行不相容岗位控制。 | K8: √ | T8: 线下管控 | V8: 可研报告 | W8: 各级单位-投资发起部门-投资管理岗； | X8: 每年 | Y8: 抽查 | AA8: 每年 | AB8: 抽查 | AH8: 否 | AI8: 是 | AK8: 总部业务管理部门；总部财务部
I9: 股权投资及产权管理－2.可研尽调控制－控制措施03 | J9: 各级单位通过收购或增资方式取得被投资企业控制权时，需研判融合风险，制定产权及管理融合方案。 | M9: √ | S9: √ | T9: 线下管控 | V9: 管理融合方案 | W9: 各级单位-投资发起部门-投资管理岗； | X9: 每年 | Y9: 抽查 | AA9: 每年 | AB9: 抽查 | AH9: 否 | AI9: 是 | AK9: 总部业务管理部门
I10: 股权投资及产权管理－2.可研尽调控制－控制措施04 | J10: 法律部负责合规审核，重点核查： 1.标的企业股东与投资企业员工之间；2.核实股东出资实缴情况、股权质押及冻结信息，规避“明股实债”风险； 如果涉及第三方评估机构，还需核查： 1.第三方机构与标的企业之间关联关系；2.第三方机构与我方项目发起部门之间关联关系。 | M10: √ | T10: 线下管控 | V10: 1.第三方机构选择合同； 2.标的企业审查意见； 3.风险评估报告； 4.法律意见书。 | W10: 各级单位-投资发起部门-投资管理岗； 二级单位-法律部-法务人员 | X10: 每年 | Y10: 抽查 | AA10: 每年 | AB10: 抽查 | AH10: 是 | AI10: 是 | AJ10: 国网（财/2）198－2025《国家电网有限公司股权管理办法》第二十条、第八十八条、附件3 | AK10: 总部财务部；总部法律部
A11: 股权投资及产权管理 | B11: 1.股权项目投资管理 | C11: 企业经营管理合法合规、提高经营效率和效果 | D11: 1.股权投资项目储备 | E11: 可行性研究、尽职调查工作不规范，报告存在内容缺失、论证不充分的问题，且投资回报测算缺失、结果模糊，导致投资决策依据不实。 | F11: 公开渠道查询央企案例：投资效益不及预，尽调未发现重大风险事项，交割后形成潜在损失。 | G11: 2.项目遴选控制控制 | H11: 严格按照“逐级择优、滚动递补”原则进行项目遴选，确保尽调范围覆盖法律、财务、业务等维度。 | I11: 股权投资及产权管理－2.可研尽调控制－控制措施05 | J11: 二级单位每季度至少开展一次项目遴选工作，存在以下情况，需移出项目库： 1.外部股东或拟投资企业发生重大亏损； 2.行业监管政策发生重大调整，可能导致投向不合规； 3.我方或标的企业关键决策人变更，影响原有判断等。 | M11: √ | T11: 线上管控-已建 | U11: 智慧共享财务平台－资本在线运营－项目遴选管理 | V11: 1.系统中项目季度进展更新表； 2.项目移出库记录及原因。 | W11: 二级单位-财务部-资产产权管理岗 | X11: 每年 | Y11: 抽查 | AA11: 每年 | AB11: 抽查 | AD11: 投资项目合规性监督场景 | AE11: 实时 | AF11: 全量 | AH11: 是 | AI11: 是 | AJ11: 国网（财/2）198－2025《国家电网有限公司股权管理办法》第八十九条、第九十条 | AK11: 总部财务部
I12: 股权投资及产权管理－2.可研尽调控制－控制措施06 | J12: 在项目遴选过程中，需有会计核算人员参与，对子公司直接或间接合计持股比例50%以上，或持股比例不足50%但作为股比最高的股东且应该能实际控制企业，应提出并表建议，避免控股不控权。 | Q12: √ | T12: 线下管控 | V12: 投资项目审批单 | W12: 各级单位-财务部-会计人员 | X12: 每年 | Y12: 抽查 | AA12: 每年 | AB12: 抽查 | AH12: 否 | AI12: 是 | AJ12: —— | AK12: 总部财务部
C13: 企业经营管理合法合规 | D13: 2.投资项目决策管理 | E13: 二级单位违规下放股权管理决策权限，越权审批； 重大事项未履行“三重一大”决策程序。 未经总部合规决策，擅自新增参股股权投资，导致投资方向偏离目标。 | F13: 54.战新产业单位重大决策管理不到位：存在未按规定履行二级单位及总部“三重一大”程序的问题。 | G13: 3.股权投资项目分级决策 | H13: 严格执行主业管控要求和分级审批权限，“三重一大”决策事项确保按照要求进行集体决策。 | I13: 股权投资及产权管理－3.股权投资项目分级决策－控制措施01 | J13: 二级单位对照制度规定权限，逐项对比，涉及对总部管理项目，按照程序上报总部，需本单位决策事项，按照“三重一大”决策事项清单发起决策审批，同一经济行为包含多类股权事项时，决策权限从高执行。 | L13: √ | M13: √ | T13: 线上管控-已建 | U13: 智慧共享财务平台－资本在线运营－项目分级决策管理 | V13: 1.党委会、总办会、董事会决议等会议纪要； 2.项目上报备案请示文件； 3.总部批复文件。 | W13: 各二级单位-财务部-资产产权管理岗；总部-财务部-资产产权管理岗 | X13: 每年 | Y13: 抽查 | AA13: 每年 | AB13: 抽查 | AH13: 是 | AI13: 是 | AJ13: 国网（财/2）198－2025《国家电网有限公司股权管理办法》第六十六条 | AK13: 总部财务部
I14: 股权投资及产权管理－3.股权投资项目分级决策－控制措施02 | J14: 在智慧共享财务平台中将总部决策事项清单及对应审批权限固化至分级决策模块数据库中。当项目发起决策流程时，系统自动识别事项类型：若属于总部决策范围，强制执行提报、审批、驳回等操作权限，流程自动到总部对应岗位。 | L14: √ | M14: √ | T14: 线上管控-待建 | U14: 智慧共享财务平台－资本在线运营－项目分级决策管理 | V14: 信息化审批单 | W14: 总部-信息化部门-信息化人员 | X14: 每年 | Y14: 抽查 | AA14: 每年 | AB14: 抽查 | AH14: 否 | AI14: 是 | AK14: 总部信息化部门
I15: 股权投资及产权管理－3.股权投资项目分级决策－控制措施03 | J15: 总部财务部审核股权投资材料，涉及多家二级单位的，须核实相关二级单位决策资料已齐全，并按照总部分级决策要求（分管领导、董事长专题会、董事会）履行程序。 | L15: √ | T15: 线下管控 | V15: 1.投资项目基本信息表； 2.承诺函； 3.决策文件等 | W15: 总部-财务部-资产产权管理岗 | X15: 每年 | Y15: 抽查 | AA15: 每年 | AB15: 抽查 | AH15: 是 | AI15: 是 | AJ15: 国网（财/2）198－2025《国家电网有限公司股权管理办法》 | AK15: 总部财务部
C16: 企业经营管理合法合规、会计信息真实完整 | D16: 3.股权投资项目计划预算管理 | E16: 投资预算未纳入年度投资计划和预算，或挪用其他项目资金进行投资。 | G16: 4.股权投资项目计划预算审批与下达 | H16: 确保股权投资计划或重大方案经专业审核，投资预算与投资项目相匹配。 | I16: 股权投资及产权管理－4.股权投资项目计划预算审批与下达－控制措施01 | J16: 股权投资项目应纳入公司综合计划和预算安排并按本办法规定履行相应决策程序后执行，不得以计划预算方案决策代替项目决策。 | L16: √ | N16: √ | T16: 线上管控-已建 | U16: 智慧共享财务平台－资本在线运营－股权项目预算 | V16: 综合计划及预算 | W16: 各级单位-财务部-计划预算岗 | X16: 每年 | Y16: 抽查 | AA16: 每年 | AB16: 抽查 | AH16: 否 | AI16: 是 | AK16: 总部财务部
I17: 股权投资及产权管理－4.股权投资项目计划预算审批与下达－控制措施02 | J17: 总部负责统筹平衡公司股权项目计划预算，履行公司决策程序后统一下达，并督导股权项目执行。 | L17: √ | N17: √ | T17: 线上管控-已建 | U17: 智慧共享财务平台－资本在线运营－股权项目预算 | V17: 综合计划及预算 | W17: 各级单位-财务部-计划预算岗 | X17: 每年 | Y17: 抽查 | AA17: 每年 | AB17: 抽查 | AH17: 是 | AI17: 是 | AJ17: 国网（财/2）198－2025《国家电网有限公司股权管理办法》 | AK17: 总部财务部
I18: 股权投资及产权管理－4.股权投资项目计划预算审批与下达－控制措施03 | J18: 确需因市场变动、业务拓展、政策要求等急需实施但未纳入年度计划预算的项目，应先完成本单位项目决策，再根据项目类型和金额等因素，履行最终决策审批程序（二级单位内部决策或需上报总部），并按公司规定履行年度投资计划预算调整流程，经二级单位批准后方可执行。 | L18: √ | M18: √ | N18: √ | T18: 线上管控-已建 | U18: 智慧共享财务平台－资本在线运营－股权项目预算 | V18: 1.年度计划预算调整申请； 2.党委会、总办会、董事会等会议纪要。 | W18: 各级单位-财务部-预算管理岗；各二级单位-财务部-资产产权管理岗；各二级单位-财务部-预算管理岗； | X18: 每年 | Y18: 抽查 | AA18: 每年 | AB18: 抽查 | AD18: 预算控制监督场景 | AE18: 实时 | AF18: 全量 | AH18: 是 | AI18: 是 | AJ18: 国网（财/2）198－2025《国家电网有限公司股权管理办法》第九十四条 | AK18: 总部财务部
A19: 股权投资及产权管理 | B19: 1.股权项目投资管理 | C19: 企业经营管理合法合规、资金资产安全 | D19: 4.股权投资项目实施管理 | E19: 前期尽调发现的风险，未在投资协议、公司章程等法律文件中设置保护性条款（如赔偿条款、退出机制、否决权）。 | G19: 5.投资协议签署 | H19: 审慎审查合同条款，确保前期尽职调查发现的风险，已在投资协议、公司章程等法律文件中合规设置保护性条款，避免因条款缺失导致投资权益无保障。 | I19: 股权投资及产权管理－5.投资协议签署－控制措施01 | J19: 在公司章程和投资协议中不得约定损害国家权益事项，重点关注： 不得约定非国有股东对一些事项具有一票否决权；不得约定在一定条件下回购非国有股东所持股权；不得约定为非国有股东提供固定投资回报；不得与非国有股东签订一致行动、表决权委托等；不得约定非国有股东可以定向非同比例减资。 | O19: √ | T19: 线上管控-已建 | U19: 经法系统 | V19: 1.章程； 2.投资协议。 | W19: 各级单位-投资发起部门-投资管理岗；各级单位-法律部-法务人员；二级单位-法律部-法务人员 | X19: 每年 | Y19: 抽查 | AA19: 每年 | AB19: 抽查 | AH19: 否 | AI19: 是 | AK19: 总部财务部；总部法律部
C20: 企业经营管理合法合规、资金资产安全 | D20: 4.股权投资项目实施管理 | E20: 前期尽调发现的风险，未在投资协议、公司章程等法律文件中设置保护性条款（如赔偿条款、退出机制、否决权）。 | G20: 5.投资协议签署 | H20: 审慎审查合同条款，确保前期尽职调查发现的风险，已在投资协议、公司章程等法律文件中合规设置保护性条款，避免因条款缺失导致投资权益无保障。 | I20: 股权投资及产权管理－5.投资协议签署－控制措施02 | J20: 针对参股企业协议，需在协议上约定：1.国有股东有权向参股企业委派同比例数量董事；2.派出人员必须有一名财务管理人员；3.约定发生重大事项时，须经国有股东委派的董事书面同意方可实施等重要性条款；4.明确分红条款；5.保障审计监督权；6.设置优先购买权与跟随出售权；7.约定股权退出机制；8.保障信息知情权。 | O20: √ | T20: 线上管控-已建 | U20: 经法系统 | V20: 1.章程； 2.投资协议。 | W20: 各级单位-投资发起部门-投资管理岗；各级单位-法律部-法务人员；二级单位-法律部-法务人员 | X20: 每年 | Y20: 抽查 | AA20: 每年 | AB20: 抽查 | AH20: 否 | AI20: 是 | AK20: 总部财务部；总部法律部
I21: 股权投资及产权管理－5.投资协议签署－控制措施03 | J21: 法律部门审查投资协议，并出具法律意见书，在审查过程中如审查确认存在程序违规行为或协议方案不匹配情况，应立即触发风险阻断机制，暂停项目后续所有出资及推进工作，待完成合规性整改，并经原有决策机构重新审议通过后，按程序恢复项目执行。 | O21: √ | T21: 线上管控-已建 | U21: 经法系统 | V21: 1.投资协议谈判记录； 2.公司章程； 3.法律意见书。 | W21: 二级单位-法律部-法务人员；二级单位-财务部-会计岗 | X21: 每年 | Y21: 抽查 | AA21: 每年 | AB21: 抽查 | AH21: 否 | AI21: 是 | AJ21: 国网（财/2）198－2025《国家电网有限公司股权管理办法》第十一条、第八十八条 | AK21: 总部财务部；总部法律部
I22: 股权投资及产权管理－5.投资协议签署－控制措施04 | J22: 风控部门在审核投资协议时，应针对风险评估报告中识别出的风险，通过协议条款加以补充或防范；对于评估出的重大风险，需跟踪核查法律意见的采纳情况。若相关风险未被采纳，且其未经法律部确认原因，则不得进入后续流程。 | M22: √ | O22: √ | T22: 线上管控-已建 | U22: 经法系统 | V22: 投资协议 | W22: 各级单位-财务部-风控部门 | X22: 每年 | Y22: 抽查 | AA22: 每年 | AB22: 抽查 | AH22: 否 | AI22: 是 | AK22: 总部财务部
C23: 企业经营管理合法合规、资金资产安全 | E23: 在完成收购、增资或新设控股企业后，未按规定时限申请办理产权占有登记，导致产权关系不清，影响后续资产确权及股权处置。 | F23: 年度财务决算批复问题清单：存在未及时办理产权与工商登记的问题。 公开渠道查询央企案例：存在未及时办理产权变更登记或在产权变更登记时提交虚假材料的问题。 | G23: 6.产权与工商占有登记 | H23: 确保在相关经济行为发生后、办理工商登记前，及时、准确、完整地办理产权占有或变更登记，清晰界定产权归属，防范产权不清风险。 | I23: 股权投资及产权管理－6.产权与工商占有登记－控制措施01 | J23: 全资、控股企业办理产权登记，企管部须先履行机构编制程序。各单位产权管理部门在相关经济行为完成后5个工作日内，申请办理产权登记手续，并须附上新设机构的文件。对于新设、收购、产权变更、增资等情形，以相关协议签署日期为起算日；对于变更企业名称、住所等注册字段的情形，则以公司章程变更日期为起算日。 | M23: √ | O23: √ | T23: 线上管控-已建 | U23: 智慧共享财务平台－资本在线运营－产权登记管理 | V23: 1.机构编制审批文件； 2.产权登记手续 | W23: 各级单位-财务部-资产产权管理岗；各二级单位-企管部-机构管理岗 | X23: 每年 | Y23: 抽查 | AA23: 每年 | AB23: 抽查 | AH23: 是 | AI23: 是 | AJ23: 国网（财/2）198－2025《国家电网有限公司股权管理办法》第一百三十七条 | AK23: 总部企管部；总部财务部
I24: 股权投资及产权管理－6.产权与工商占有登记－控制措施02 | J24: 新增国有参股股权产权登记时，除提交申请文件及相关材料外，还需财务部门会同业务管理部门、法律部门进行承诺事项逐条核查，出具书面承诺函： 1.参股投资目标使命明确，符合公司战略规划，已纳入年度投资计划；财务性投资已对未来收益率充分研究和决策； 2.不存在股权代持、虚假出资、名股实债等问题； 3.未对其他股东出资提供垫资、担保等财务资助。列明核查依据及判断原因，由核查人签字，并加盖公章。 | M24: √ | S24: √ | T24: 线下管控 | V24: 书面承诺函 | W24: 各级单位-财务部-资产产权管理岗；各级单位-业务管理部门-业务审核人员；各级单位-法律部-法务人员 | X24: 每年 | Y24: 抽查 | AA24: 每年 | AB24: 抽查 | AH24: 否 | AI24: 是 | AJ24: 国资发产权规（2026－201）《关于进一步规范国有参股股权管理有关事项的通知》第三条 | AK24: 总部财务部；总部法律部
A25: 股权投资及产权管理 | B25: 1.股权项目投资管理 | C25: 企业经营管理合法合规、资金资产安全 | D25: 4.股权投资项目实施管理 | E25: 项目公司注册成立后未按约定实缴出资（包括我方或外部股东出资不到位），导致股权结构偏离决策、我方超比例出资或被迫垫资，以及资本金不足影响项目正常运营与后续融资。 | F25: 54.战新产业单位重大决策管理不到位：存在股权投资项目执行进度滞后、注册成立公司后未实际注资等问题。 年度财务决算批复问题清单：存在外部股东出资不到位的问题。 | G25: 7.实际出资控制 | H25: 对资金支付环节进行全过程在线监管，核实投前约定条件，确保资金安全。 | I25: 股权投资及产权管理－6.产权与工商占有登记－控制措施03 | J25: 各单位产权管理部门须核实决策文件与公司章程，确保出资人、注册资本、持股比例等信息保持一致。总部产权管理专责再次复核。 | M25: √ | T25: 线下管控 | V25: 1.决策文件；2.章程 | W25: 各级单位-财务部-资产产权管理岗；总部-财务部-资产产权管理岗 | X25: 每年 | Y25: 抽查 | AA25: 每年 | AB25: 抽查 | AH25: 否 | AI25: 是 | AK25: 总部财务部
I26: 股权投资及产权管理－6.产权与工商占有登记－控制措施04 | J26: 办公室在取得产权登记证后立即开展工商登记，且在办理工商登记前必须核查并确认产权登记证信息一致。 | M26: √ | T26: 线上管控-已建 | U26: 智慧共享财务平台－资本在线运营－产权登记管理 | V26: 1.产权登记证； 2.工商登记表 | W26: 各级单位-综合管理部-工商管理岗 | X26: 每年 | Y26: 抽查 | AA26: 每年 | AB26: 抽查 | AD26: 产权管理监督场景 | AE26: 实时 | AF26: 全量 | AH26: 否 | AI26: 是 | AJ26: 国网（财/2）198－2025《国家电网有限公司股权管理办法》第一百三十二条 | AK26: 总部财务部
I27: 股权投资及产权管理－6.产权与工商占有登记－控制措施05 | J27: 工商系统与产权系统通过接口实时同步法人机构的名称、统一社会信用代码、注册地址、登记状态等关键字段。经工商信息与产权信息比对一致后，系统方允许继续办理财务账套等后续事项。 | M27: √ | T27: 线上管控-待建 | U27: 智慧共享财务平台－资本在线运营－产权登记管理 | V27: 1.产权登记证； 2.工商登记证明。 | W27: 各级单位-信息化部门-信息化人员 | X27: 每年 | Y27: 抽查 | AA27: 每年 | AB27: 抽查 | AH27: 否 | AI27: 是 | AJ27: 国网（财/2）198－2025《国家电网有限公司股权管理办法》第一百三十六条 | AK27: 总部财务部
C28: 企业经营管理合法合规、资金资产安全 | I28: 股权投资及产权管理－7.实际出资控制－控制措施01 | J28: 在我方出资前需要进行条件验证，针对控股、参股企业，制定了如下措施： 1.我方在支付任何一笔出资款前，必须获取其他股东已按约定比例实缴出资的银行回单或验资报告； 2.若其他股东未按期出资，我方暂停出资，并及时书面通知违约方； 财务部进行补充复核，未经上述验证财务部不得支付款项。 出资申请与出资审批；会计与出纳存在不相容岗位。 | K28: √ | M28: √ | P28: √ | T28: 线下管控 | V28: 1.实缴出资的银行回单或验资报告； 2.违约通知。 | W28: 各级单位-投资发起部门-经办人员； 各级单位-财务部-会计/出纳 | X28: 每年 | Y28: 抽查 | AA28: 每年 | AB28: 抽查 | AH28: 否 | AI28: 是 | AJ28: 国网（财/2）198－2025《国家电网有限公司股权管理办法》第十五条、第七十七条 | AK28: 总部财务部
I29: 股权投资及产权管理－7.实际出资控制－控制措施02 | J29: 发现其他股东逾期出资未按照公司章程约定履行出资义务，须进行提示，如未按照提示要求出资，各级单位项目管理部门采取以下强制措施： 1.按协议约定解除合同，要求违约方返还已投入资产并支付违约金； 2.若项目无法解除，则启动股权调整：按实际出资比例重新计算股权，并办理工商变更； 3.将违约方列入合作黑名单。 我方自身出现出资逾期的，各单位法律部门进行逾期提示。 | M29: √ | P29: √ | T29: 线下管控 | V29: 1.出资记录； 2.出资发函催缴； 3.合作方黑名单。 | W29: 各级单位-投资发起部门-投资管理岗；各级单位-法律部-法务人员 | X29: 每年 | Y29: 抽查 | AA29: 每年 | AB29: 抽查 | AH29: 否 | AI29: 是 | AJ29: 国网（财/2）198－2025《国家电网有限公司股权管理办法》第一百十五条 | AK29: 总部财务部；总部法律部
C30: 资金资产安全 | D30: 8.分支机构管理 | E30: 未及时发现分支机构成立，导致违规设立分支机构引发法律及合规风险。 | G30: 14.分支机构管控 | H30: 确保建立健全分支机构设立的事前备案与事中监测机制，利用工商信息预警、定期报送等手段及时发现新设分支机构。 | I30: 股权投资及产权管理－14.分支机构管控－控制措施01 | J30: 企管部设置分支机构需同步推送给资产处分支机构设置情况，资产处对工商产权进行核查比对，防止已工商注册，没有产权。会计处对工商与账套进行比对，办理工商信息需设立独立账套。 | M30: √ | T30: 线下管控 | V30: 分支机构设置申请 | W30: 各级单位-企管部 | X30: 每年 | Y30: 抽查 | AA30: 每年 | AB30: 抽查 | AH30: 否 | AI30: 是 | AK30: 总部财务部；总部企管部
I31: 股权投资及产权管理－14.分支机构管控－控制措施02 | J31: 二级单位企管部在设置分支机构时，须履行二级单位相应的决策程序；组织部开展组织机构编制，并确保该编制已获批。 | M31: √ | Q31: √ | T31: 线下管控 | V31: 1.分支机构设置申请； 2.审批单 | W31: 各级单位-企管部 | X31: 每年 | Y31: 抽查 | AA31: 每年 | AB31: 抽查 | AH31: 否 | AI31: 是 | AK31: 总部财务部；总部企管部
C32: 提高经营效率和效果、企业经营管理合法合规、资金资产安全 | D32: 7.股权优化清理管理 | E32: “瘦身健体”政策执行不到位，导致存在大量管理层级超4级、法人层级超4级的企业，以及“无资产、无业务、无人员”的空壳企业、已吊销未注销或破产清算的僵尸企业。 参股股权瑕疵，列入参股股权调整范围内项目，未及时调整。 | F32: 80.国资国企改革政策落实不到位：存在瘦身健体工作开展不彻底的问题。 全级次股权优化整合：存在部分企业超层级、“三无”企业，已吊销未注销、破产清算等问题。 公开渠道查询央企案例：存在投资项目绩效评价结果不佳、后评价发现问题整改不到位、参股经营投资履职不规范及低效无效资产退出机制不健全的问题。 公司重点领域风险治理：部分单位存在低效无效参股投资且未能及时完成退出的问题。 | G32: 13.全级次股权优化整合 | H32: 常态化开展梳理评估，持续压减超层级、无存续价值企业，优化股权结构。 明确纳入参股股权调整、退出范围，督促及时消除参股股权问题。 | I32: 股权投资及产权管理－13.全级次股权优化整合－控制措施01 | J32: 每年1月前制定当年度“股权优化整合”计划，压减范围应至少包括管理层级及法人层级超4级的所有企业、无存续必要的企业、已吊销未注销企业、“两非”“两资”企业、空壳企业、破产清算、资不抵债等企业，确保每年压减工作完成率不低于既定目标。 | S32: √ | T32: 线下管控 | V32: 年度“压减”工作计划 | W32: 各二级单位-财务部-资产产权管理岗；总部-财务部-资产产权管理岗 | X32: 每年 | Y32: 抽查 | AA32: 每年 | AB32: 抽查 | AH32: 是 | AI32: 是 | AJ32: 国网（财/2）198－2025《国家电网有限公司股权管理办法》第一百一十八条、第一百一十九条、第一百二十条 | AK32: 总部财务部
I33: 股权投资及产权管理－13.全级次股权优化整合－控制措施02 | J33: 列入清单的低效无效投资，逐项明确退出方式（股权转让、清算注销、吸收合并、破产重整等）、退出路径、责任人和完成时限，清理任务完成期限不超过3年。 | T33: 线下管控 | V33: 年度“压减”工作计划 | W33: 各二级单位-财务部-资产产权管理岗；总部-财务部-资产产权管理岗 | X33: 每年 | Y33: 抽查 | AA33: 每年 | AB33: 抽查 | AH33: 是 | AI33: 是 | AJ33: 国网（财/2）198－2025《国家电网有限公司股权管理办法》 | AK33: 总部财务部
I34: 股权投资及产权管理－13.全级次股权优化整合－控制措施03 | J34: 各二级单位财务部应排查参股企业存在不在主业级拟培育主业范围内且参股企业净资产收益率连续两年低于国有企业年度预算数情况，并纳入参股股权调整范围。各二级单位督促投资企业在6个月内制定整改方案，采取强化股东履职、委托集中管理、调整股权比例等措施，原则上在整改方案确定后1年内解决相关问题。 | M34: √ | S34: √ | T34: 线下管控 | V34: 参股股权调整清单 | W34: 各二级单位-财务部-经办人员；总部-财务部-经办人员 | X34: 每年 | Y34: 抽查 | AA34: 每年 | AB34: 抽查 | AH34: 否 | AI34: 是 | AJ34: 国网（财/2）198－2025《国家电网有限公司股权管理办法》第一百二十四条 | AK34: 总部财务部
I35: 股权投资及产权管理－13.全级次股权优化整合－控制措施04 | J35: 各二级单位财务部将参股企业存在低效无效股权，包括连续5年及以上未分红，或连续3年及以上亏损，或连续2年及以上处于非持续经营状态情况，以及未在规定时间内完成整改的“调整”范围内国有参股股权情况纳入退出范围，制定清单式管理，每年制定清理退出计划，原则上应当在三年内全部完成清理退出，逾期未完成原则上不得新增参股股权。 | M35: √ | S35: √ | T35: 线下管控 | V35: 参股股权退出清单 | W35: 各二级单位-财务部-资产产权管理岗；总部-财务部-资产产权管理岗 | X35: 每年 | Y35: 抽查 | AA35: 每年 | AB35: 抽查 | AH35: 否 | AI35: 是 | AJ35: 国网（财/2）198－2025《国家电网有限公司股权管理办法》第一百二十四条 | AK35: 总部财务部
I36: 股权投资及产权管理－13.全级次股权优化整合－控制措施05 | J36: 每季度清查“无资产、无业务、无人员”的空壳企业、已吊销未注销企业以及长期停业、资不抵债的僵尸企业。逐户核查工商登记状态、经营许可有效期、资产债权债务状况，确保底数全面准确。 | S36: √ | T36: 线上管控-已建 | U36: 智慧共享财务平台－资本在线运营－投后评价 | V36: 年度专项检查报告 | W36: 各级单位-业务管理部门-投后管理岗；各二级单位-业务管理部门-投后管理岗；总部-业务管理部门-投后管理岗 | X36: 每年 | Y36: 抽查 | AA36: 每年 | AB36: 抽查 | AD36: 股权优化监督场景 | AE36: 实时 | AF36: 全量 | AH36: 否 | AI36: 是 | AJ36: 国网（财/2）198－2025《国家电网有限公司股权管理办法》第一百一十八条、第一百一十九条、第一百二十条 | AK36: 总部财务部
A37: 股权投资及产权管理 | B37: 2.股权项目运营管理 | I37: 股权投资及产权管理－13.全级次股权优化整合－控制措施06 | J37: 对于超层级企业确有续存必要的，通过股权划转、吸收合并或上移领导班子任免、业绩考核、薪酬分配等管理权的方式，压降管理层级； 对于空壳公司涉及不动产权变更等客观困难以及个别参股投资因涉及政府赔偿、司法诉讼或市场行情等影响，短期内不具备处置条件的，应逐项明确处置计划、措施、时间表和责任人。 | R37: √ | S37: √ | T37: 线下管控 | V37: 处置计划及方案 | W37: 各级单位-财务部-资产产权管理岗； 各二级单位-财务部-资产产权管理岗； 总部-财务部-资产产权管理岗 | X37: 每年 | Y37: 抽查 | AA37: 每年 | AB37: 抽查 | AH37: 否 | AI37: 是 | AJ37: 《国家电网有限公司关于做好全级次股权优化整合的通知》一、二、三 | AK37: 总部财务部
A38: 股权投资及产权管理 | B38: 3.股权项目变动管理 | C38: 企业经营管理合法合规 | D38: 9.股权转让项目管理 | E38: 股权协议转让事项未经合规报批、未按规定论证协议转让适用条件， | G38: 15.协议转让条件合规审查 | H38: 规范开展股权协议转让事项逐级依规报批，确保审批流程完备、定价公允合规、股权交割合法、国有资产及控制权安全稳定。 | I38: 股权投资及产权管理－15.协议转让条件合规审查－控制措施01 | J38: 依据国资委32号令，各单位发起协议转让需逐条对比转让条件：标的企业主业属于关系国家安全、国民经济命脉的重要行业和关键领域、产权仅在国有及国有控股企业之间流转等，梳理建立《协议转让条件核实清单》，涉及上市公司股份的，还须核查证券交易所合规性确认文件。 | L38: √ | M38: √ | R38: √ | T38: 线下管控 | V38: 1.协议转让条件核实清单； 2进场交易强制审查清单； 3股权转让方案； 4资产评估备案表； 5.协议转让合同 | W38: 各级单位-业务管理部门-经办人；各级单位-财务部-资产产权管理岗；各级单位-法律部-法务人员 | X38: 每年 | Y38: 抽查 | AA38: 每年 | AB38: 抽查 | AH38: 否 | AI38: 是 | AJ38: 《股权管理办法》第二十七、二十八、三十条 | AK38: 总部财务部；总部法律部
I39: 股权投资及产权管理－15.协议转让条件合规审查－控制措施02 | J39: 转让启动前逐项审查核查受让方营业执照、信用记录、最近一期经审计财务报表，外资须符合准入清单。 | M39: √ | R39: √ | T39: 线下管控 | V39: 1.营业执照； 2.信用记录； 3.审计财务报表 | W39: 各级单位-业务管理部门-经办人；各级单位-财务部-资产产权管理岗；各级单位-法律部-法务人员 | X39: 每年 | Y39: 抽查 | AA39: 每年 | AB39: 抽查 | AH39: 否 | AI39: 是 | AK39: 总部财务部；总部法律部
I40: 股权投资及产权管理－15.协议转让条件合规审查－控制措施03 | J40: 协议转让事项由业务管理部门发起，财务部、法律部依次审核，按照制度规定，逐条核实决策权限，属于总部管理项目的，由二级单位逐级上报；二级单位自主决策项目，须履行本单位“三重一大”决策程序，决策文件报总部备案。涉及非公开协议转让的，由总部报国务院国资委备案；重要子企业控股权转让、特定情形协议转让总部报国务院国资委批准。 | L40: √ | R40: √ | T40: 线下管控 | V40: 1.决策文件； 2.备案文件 | W40: 各级单位-业务管理部门-经办人；各级单位-财务部-资产产权管理岗；各级单位-法律部-法务人员 | X40: 每年 | Y40: 抽查 | AA40: 每年 | AB40: 抽查 | AH40: 是 | AI40: 是 | AJ40: 国网（财/2）198－2025《国家电网有限公司股权管理办法》第六十六、六十七六十九、七十二条 | AK40: 总部财务部；总部法律部
C41: 资金资产安全 | E41: 股权协议转让价格低于经备案的评估值/审计净资产值，导致国有资产流失风险。 | F41: 公开渠道查询央企案例：存在未履行资产评估程序、以协议方式低价转让国有股权的问题。 | G41: 16.协议转让价格控制 | H41: 确保股权协议转让价格合规确定，杜绝低价转让行为，有效防范国有资产流失风险。 | I41: 股权投资及产权管理－16.协议转让价格控制－控制措施01 | J41: 转让价格不得低于经公司总部审核备案的标的企业评估值或最近一期审计报告确认的净资产值；系统自动比对备案评估值与协议价，协议价低于备案评估值或审计净资产值的阻断支付。 | O41: √ | P41: √ | R41: √ | T41: 线上管控-待建 | U41: 智慧共享财务平台－资本在线运营-资产评估 | V41: 资产评估报告 | W41: 各级单位-业务管理部门-经办人；各级单位-财务部-资产产权管理岗；各级单位-法律部-法务人员 | X41: 每年 | Y41: 抽查 | AA41: 每年 | AB41: 抽查 | AH41: 是 | AI41: 是 | AJ41: 国网（财/2）198－2025《国家电网有限公司股权管理办法》 | AK41: 总部财务部；总部法律部
C42: 企业经营管理合法合规 | E42: 进场交易时违规设置受让方资格条件，或设置的条件具有明确指向性；进场交易项目长期未征集到受让方，未及时重新履行程序，导致资产长期低效滞留。 | F42: 公开渠道查询央企案例：存在进场交易设置排他性条款、违规将“与债权人达成一致”作为受让前置条件的问题。 | G42: 17.进场交易受让方征集与审查 | H42: 规范进场交易的信息披露和受让方征集过程，确保交易公开、公平、公正。 | I42: 股权投资及产权管理－17.进场交易受让方征集与审查－控制措施01 | J42: 风控与法律部应联合审查受让方资格条件的设置，资质条件不得存在指向性、排他性或违反公平竞争的内容，确需设置特殊资格条件的，还须在信息披露前经总部财务部审核，并报国务院国资委备案。 | L42: √ | M42: √ | R42: √ | T42: 线下管控 | V42: 1.信息披露公告文件；2.书面异议函 | W42: 各级单位-财务部-风险管控人员；各级单位-法律部-法务人员、各级单位-业务管理部门-经办人员 | X42: 每年 | Y42: 抽查 | AA42: 每年 | AB42: 抽查 | AH42: 是 | AI42: 是 | AJ42: 国网（财/2）198－2025《国家电网有限公司股权管理办法》第三十七条、第四十一条 | AK42: 总部财务部；总部法律部
I43: 股权投资及产权管理－17.进场交易受让方征集与审查－控制措施02 | J43: 财务部建立《受让方资格审查清单》，会同法律部对意向受让方审查六项内容：主体资格合法有效；财务状况与履约能力；信用合规记录；外资准入合规；关联关系与利益冲突；交易保证金。 | M43: √ | R43: √ | T43: 线下管控 | V43: 1.受让方资格条件设置；2.备案文件；3.审核报告 | W43: 各级单位-财务部-资产产权管理岗、法；各级单位-法律部-法务人员 | X43: 每年 | Y43: 抽查 | AA43: 每年 | AB43: 抽查 | AH43: 否 | AI43: 是 | AJ43: 《股权管理办法》第四十一条 | AK43: 总部财务部；法律部
A44: 股权投资及产权管理 | B44: 3.股权项目变动管理 | I44: 股权投资及产权管理－17.进场交易受让方征集与审查－控制措施03 | J44: 转让方按照遴选方案组织竞价或综合评议，确定最终受让方后，须将遴选结果报二级单位履行“三重一大”决策；涉及总部管理项目的，须报总部审批。涉及控制权变动或重要子企业的需报国资委批准。 | L44: √ | M44: √ | R44: √ | T44: 线下管控 | V44: 决策文件 | W44: 各级单位-业务管理部门-经办人员；各级单位-财务部-资产产权管理岗；各级单位-法律部-法务人员 | X44: 每年 | Y44: 抽查 | AA44: 每年 | AB44: 抽查 | AH44: 是 | AI44: 是 | AJ44: 国网（财/2）198－2025《国家电网有限公司股权管理办法》第四十一条、第六十六条 | AK44: 总部财务部；总部法律部
C45: 资金资产安全 | E45: 降价幅度（比例或金额）及后续降价梯次未在公告期满后及时形成明确方案并履行相应审批，随意降价。 | F45: 公开渠道查询央企案例：存在国有股权转让时未进行资产评估或未进行单独决策，价格低于评估价值90%转让的问题。 | G45: 18.进场交易价格监督 | H45: 严格执行进场交易定价规定，防止国有资产违规低价转让。 | I45: 股权投资及产权管理－17.进场交易价格监督－控制措施01 | J45: 首次挂牌价不得低于经备案的评估值；以审计净资产值为定价依据的，审计基准日与挂牌日间隔≤6个月。智慧财务平台自动比对备案评估值与挂牌价，低于评估值的不得发布公告。 | M45: √ | N45: √ | R45: √ | S45: √ | T45: 线上管控-待建 | U45: 智慧共享财务平台－资本在线运营-资产评估 | V45: 1.资产评估备案表；2.产权交易挂牌公告及价格信息；3.产权交易合同 | W45: 各级单位-业务管理部门-经办人员 | X45: 每年 | Y45: 抽查 | AA45: 每年 | AB45: 抽查 | AD45: 挂牌价格自动比对监督场景 | AE45: 实时 | AF45: 全量 | AH45: 是 | AI45: 是 | AJ45: 国网（财/2）198－2025《国家电网有限公司股权管理办法》第35、38条 | AK45: 总部财务部
I46: 股权投资及产权管理－14.进场交易价格监督－控制措施02 | J46: 各单位业务部门（转让方）在公告期满需降价且新底价低于评估结果90%时，单独履行二级单位决策程序；涉及总部管理或国资委审批的，还需经原批准单位批准，确保降价幅度超限时决策程序合规。 | L46: √ | M46: √ | R46: √ | T46: 线上管控-已建 | U46: 智慧共享财务平台－资本在线运营-资产评估 | V46: 1.资产评估备案表；2.产权交易挂牌公告及价格信息；3.降价决策审批文件 | W46: 各级单位-业务管理部门-经办人员 | X46: 每年 | Y46: 抽查 | AA46: 每年 | AB46: 抽查 | AD46: 降价审批流程数字化监控场景 | AE46: 实时 | AF46: 全量 | AH46: 是 | AI46: 是 | AJ46: 国网（财/2）198－2025《国家电网有限公司股权管理办法》第三十八条 | AK46: 总部财务部
C47: 企业经营管理合法合规 | E47: 转让协议未明确支付条款或对字号、资质问题未明确说明，导致交易资金回收风险、法律纠纷及字号、资质使用争议。 | G47: 19.转让协议合规性控制 | H47: 确保股权转让协议合规明确支付条款，并对字号存续、资质归属及使用条件作出清晰说明，避免导致资金损失、诉讼争议或后续经营障碍。 | I47: 股权投资及产权管理－18.转让协议合规性管理－控制措施01 | J47: 各单位财务部门在股权转让合同签署前审核支付条款，原则上一次性付清，支付时系统校验首付款到账凭证，未到账不得办理股权交割。 | O47: √ | P47: √ | Q47: √ | R47: √ | T47: 线上管控-待建 | U47: 经法系统 | V47: 1.产权交易合同；2.法律意见书 | W47: 各级单位-财务部-资金管理人员 | X47: 每年 | Y47: 抽查 | AA47: 每年 | AB47: 抽查 | AH47: 否 | AI47: 是 | AJ47: 《股权管理办法》第三十五条、《操作规则》第六十九条 | AK47: 总部法律部
I48: 股权投资及产权管理－18.转让协议合规性管理－控制措施02 | J48: 产权转让导致失去标的企业实际控制权的，交易完成后标的企业不得继续使用“国网”或“国网**”字样以及各级单位字号、经营资质和经营特许权，有关事项应在转让协议中说明，并在修订后章程中体现。 | O48: √ | T48: 线上管控-已建 | U48: 经法系统 | V48: 1.产权交易合同；2.法律意见书 | W48: 各级单位-业务管理部门-经办人员；各级单位-企管部-经办人员；各级单位-法律部-法务人员 | X48: 每年 | Y48: 抽查 | AA48: 每年 | AB48: 抽查 | AH48: 否 | AI48: 是 | AK48: 总部企管部；总部法律部
C49: 企业经营管理合法合规 | D49: 10.股权划转项目管理 | E49: 股权外部划转未满足划转条件，或审批程序缺失。 | F49: 公开渠道查询央企案例：存在项目推进不力、股权外部划转历经两年后因先决条件无法成就而终止的问题。 | G49: 20.外部划转条件审核 | H49: 严格审核划转双方主体资格（追溯至最终实际控制人），核查标的企业产权状况，形成主体资格确认书。 | I49: 股权投资及产权管理－19.外部划转条件审核－控制措施01 | J49: 启动外部划转前，调取划入方、划出方最新工商登记、章程、股权穿透图及产权登记表，追溯至最终实际控制人，确认双方均为政府、事业单位、国有独资企业/公司。核查标的企业产权登记证、工商档案，确保无质押、冻结、权属争议，形成《外部划转主体资格确认书》。 | L49: √ | M49: √ | R49: √ | T49: 线下管控 | V49: 1.股权划转申请文件；2.条件符合性说明；3.外部划转主体资格确认书 | W49: 各级单位-业务管理部门-投资管理岗；各级单位-财务部-资产产权管理岗；各级单位-法律部-法务人员 | X49: 每年 | Y49: 抽查 | AA49: 每年 | AB49: 抽查 | AH49: 否 | AI49: 是 | AJ49: 《股权管理办法》第四十五条、第四十七条、第六十八条 | AK49: 总部财务部；总部法律部
I50: 股权投资及产权管理－19.外部划转条件审核－控制措施02 | J50: 划出方出具书面承诺函，承诺标的企业股权权属清晰、不存在任何质押、冻结、权属争议或未披露的代持关系。项目发起部门对近三年主营业务收入构成、核心资质与特许经营权、与划入方业务协同效应评估。涉及重要子企业的，须说明划转后是否影响国有资本控股地位。 | O50: √ | T50: 线下管控 | V50: 书面承诺函 | W50: 各级单位-业务管理部门-投资管理岗；各级单位-财务部-资产产权管理岗；各级单位-法律部-法务人员 | X50: 每年 | Y50: 抽查 | AA50: 每年 | AB50: 抽查 | AH50: 否 | AI50: 是 | AK50: 总部财务部；总部法律部
I51: 股权投资及产权管理－19.外部划转条件审核－控制措施03 | J51: 财务部逐项核查适用条件，经划入方本单位“三重一大”决策后，报送总部，由公司总部统一报国资委批准。取得书面批复后，划转协议正式生效，方可办理产权登记及工商变更。 | L51: √ | M51: √ | R51: √ | T51: 线下管控 | V51: 1.股权划转申请文件；2.被划转企业主业匹配分析报告 | W51: 各级单位-业务管理部门；各级单位-财务部-资产产权管理岗； | X51: 每年 | Y51: 抽查 | AA51: 每年 | AB51: 抽查 | AD51: 产权管理监督场景 | AE51: 实时 | AF51: 全量 | AH51: 是 | AI51: 是 | AJ51: 国网（财/2）198－2025《国家电网有限公司股权管理办法》第六十八条、附件1 | AK51: 总部财务部；战略部
C52: 企业经营管理合法合规、资金资产安全 | E52: 股权划转协议内容不完整，未明确债权债务处置、人员安置方案等内容； 股权划转信息披露不及时，程序不合规。 | F52: 公开渠道查询央企案例：存在划转协议未按规定及时报送要约收购豁免申请、违反收购管理办法程序性规定的问题。 | G52: 21.划转协议内容完整性审核 | H52: 确保股权划转协议内容完整、合规，明确各方权利义务。 | I52: 股权投资及产权管理－17.划转协议内容完整性审核－控制措施01 | J52: 划转涉及被划转企业职工分流安置，要求划出方提供： 1.被划转企业职工代表大会关于安置方案的审议通过文件； 2.职工安置方案，并进行合规审查。 | O52: √ | R52: √ | T52: 线下管控 | V52: 1.股权划转协议；2.法律意见书；3.划出方承诺函 | W52: 各级单位-法律部-法务人员；各级单位-财务部-资产产权管理岗 | X52: 每年 | Y52: 抽查 | AA52: 每年 | AB52: 抽查 | AD52: 产权管理监督场景 | AE52: 实时 | AF52: 全量 | AH52: 是 | AI52: 是 | AJ52: 国网（财/2）198－2025《国家电网有限公司股权管理办法》第四十六条、第五十条 | AK52: 总部财务部；总部法律部
I53: 股权投资及产权管理－17.划转协议内容完整性审核－控制措施02 | J53: 划转协议签署前，要求划出方提供： 1.已向主要债权人发出书面通知的证明； 2.债务处置方案，方案须明确被划转企业现有债务的承接主体、偿还资金来源及划入方的兜底责任。 财务部进行核查，并书面提示划出方补充。 | O53: √ | T53: 线下管控 | V53: 1.债权人书面通知的证明；2.债务处置方案 | W53: 各级单位-业务管理部门-投资管理岗；各级单位-财务部-资产产权管理岗；各级单位-法律部-法务人员 | X53: 每年 | Y53: 抽查 | AA53: 每年 | AB53: 抽查 | AH53: 是 | AI53: 是 | AJ53: 国网（财/2）198－2025《国家电网有限公司股权管理办法》 | AK53: 总部财务部；总部法律部
A54: 股权投资及产权管理 | B54: 3.股权项目变动管理 | I54: 股权投资及产权管理－17.划转协议内容完整性审核－控制措施03 | J54: 法务部门在划转协议中加入“未披露债务兜底条款”，约定：划出方保证已完整披露被划转企业全部债务及或有负债；若交割后发现划转协议债务清单之外的任何负债，由划出方承担全部清偿责任，并赔偿划入方因此遭受的全部损失。 | L54: √ | Q54: √ | R54: √ | T54: 线下管控 | V54: 1.划转协议必备要素核对表；2.相关决策文件 | W54: 各级单位-法律部-法务人员； | X54: 每年 | Y54: 抽查 | AA54: 每年 | AB54: 抽查 | AD54: 产权管理监督场景 | AE54: 实时 | AF54: 全量 | AH54: 否 | AI54: 是 | AJ54: 《股权管理办法》第一百三十二条 | AK54: 总部法律部
C55: 企业经营管理合法合规 | D55: 11.增资扩股项目管理 | E55: 非公开协议增资未满足适用条件，或审批程序缺失； 增资扩股未履行审计评估程序，或应进场交易而未进场。 | F55: 公开渠道查询央企案例：存在增资引入自然人股东未履行资产评估手续、程序违规的问题。 | G55: 22.增资扩股方案报批 | H55: 严格审核非公开协议增资的适用条件，增资扩股须履行财务审计、资产评估程序，确保定价依据充分、程序合规。 | I55: 股权投资及产权管理－18.增资扩股方案报批－控制措施01 | J55: 各级单位业务部门在增资方案编制阶段，逐项审查非公开协议增资适用条件，审查结果须形成书面清单，由部门负责人签字确认，向报财务部备案。 采取非公开协议方式增资的，应说明必要性及投资方情况，同时报送与受让方草签的增资协议或初步达成的书面意向，需依据制度要求，报公司总部、国资委批准后生效。 | L55: √ | M55: √ | R55: √ | T55: 线下管控 | V55: 1.增资扩股方案；2.审查清单 | W55: 各级单位-业务管理部门-经办人；各级单位-财务部-资产产权管理岗 | X55: 每年 | Y55: 抽查 | AA55: 每年 | AB55: 抽查 | AD55: 产权管理监督场景 | AE55: 实时 | AF55: 全量 | AH55: 是 | AI55: 是 | AJ55: 国网（财/2）198－2025《国家电网有限公司股权管理办法》第五十三、五十四条 | AK55: 总部财务部
I56: 股权投资及产权管理－18.增资扩股方案报批－控制措施02 | J56: 涉及职工安置，安置方案须经职工代表大会或全体职工讨论，并在企业内部公示。 | L56: √ | R56: √ | T56: 线下管控 | V56: 增资扩股方案及职代会审议文件 | W56: 各级单位-组织部-经办人；各级单位-工会、职代会 | X56: 每年 | Y56: 抽查 | AA56: 每年 | AB56: 抽查 | AD56: 产权管理监督场景 | AE56: 实时 | AF56: 全量 | AH56: 是 | AI56: 是 | AJ56: 国网（财/2）198－2025《国家电网有限公司股权管理办法》第五十五条 | AK56: 总部组织部
I57: 股权投资及产权管理－18.增资扩股方案报批－控制措施03 | J57: 2亿元以上出资、对全资控股企业非同比例增资等情形由总部决策。重要子企业股权结构变化、特定战略合作等由总部报国资委批准。二级单位自主决策项目履行“三重一大”程序，跨二级单位事项需提供双方决策文件。 | L57: √ | R57: √ | T57: 线下管控 | V57: 决策文件 | W57: 各级单位-业务管理部门-经办人；各级单位-财务部-资产产权管理岗 | X57: 每年 | Y57: 抽查 | AA57: 每年 | AB57: 抽查 | AH57: 是 | AI57: 是 | AJ57: 国网（财/2）198－2025《国家电网有限公司股权管理办法》第五十三、五十四、六十六、六十九条 | AK57: 总部财务部
C58: 企业经营管理合法合规、资金资产安全 | E58: 进场交易投资方提供虚假资料，虚假出资、空壳主体、关联代持，实际控制人不明等情况； 投资方自有资金比例不达标，依赖高杠杆融资，无足额实缴能力； 投资方与国企主业协同不足，偏离战略方向。 | G58: 23.进场交易投资方遴选 | H58: 规范增资扩股进场交易投资方公开遴选程序，确保择优引入优质投资方，防范利益输送。 | I58: 股权投资及产权管理－19.进场交易投资方遴选－控制措施01 | J58: 各级单位业务部门在编制增资扩股方案需关注: 1.投资方的选择标准和遴选方式，不得设置具有明确指向性或违反公平竞争原则的资格条件，确保遴选标准与增资企业功能定位、发展战略相匹配； 2.增资企业基本情况、功能定位、发展战略；募集资金金额、用途； 3.如有潜在意向方的，应说明有关基本情况； 4.增资后企业的股东数量须符合国家相关法律法规的规定。 | L58: √ | M58: √ | R58: √ | T58: 线下管控 | V58: 增资扩股方案（含投资方遴选标准） | W58: 各级单位-业务管理部门-经办人 | X58: 每年 | Y58: 抽查 | AA58: 每年 | AB58: 抽查 | AD58: 产权管理监督场景 | AE58: 实时 | AF58: 全量 | AH58: 否 | AI58: 是 | AJ58: 《股权管理办法》第五十四、五十七条 | AK58: 总部财务部
H59: 规范增资扩股进场交易投资方公开遴选程序，确保择优引入优质投资方，防范利益输送。 | I59: 股权投资及产权管理－19.进场交易投资方遴选－控制措施02 | J59: 各级单位财务部门会同法律部门在收到意向投资方材料后，开展主体资格审查：股权穿透、信用核查、净资产≥投资额、自有资金，涉及外资的，还须核查外资准入相关要求，审查结果形成报告，由财务部、法律部会签。 | K59: √ | M59: √ | R59: √ | T59: 线下管控 | V59: 1.投资方资格审核报告；2法律意见书；3.营业执照；4.股权结构说明；5.资信证明等 | W59: 各级单位-财务部-资产产权管理岗；各级单位-法律部-法务人员 | X59: 每年 | Y59: 抽查 | AA59: 每年 | AB59: 抽查 | AD59: 产权管理监督场景 | AE59: 实时 | AF59: 全量 | AH59: 否 | AI59: 是 | AJ59: 《股权管理办法》第五十五条、《操作规则》第六十九条 | AK59: 总部财务部；总部法律部
A60: 股权投资及产权管理 | B60: 3.股权项目变动管理 | H60: 规范增资扩股进场交易投资方公开遴选程序，确保择优引入优质投资方，防范利益输送。 | I60: 股权投资及产权管理－19.进场交易投资方遴选－控制措施03 | J60: 选择战略投资方主要关注企业发展战略、经营目标、主营业务等方面的匹配和协同情况；选择财务投资方主要关注资金实力和财务状况等。 | L60: √ | O60: √ | R60: √ | S60: √ | T60: 线下管控 | V60: 1.遴选方案及评审记录；2.标的企业董事会/股东会决议；3.成交确认书 | W60: 各级单位-业务管理部门-经办人；各级单位-财务部-资产产权管理岗 | X60: 每年 | Y60: 抽查 | AA60: 每年 | AB60: 抽查 | AD60: 产权管理监督场景 | AE60: 实时 | AF60: 全量 | AH60: 否 | AI60: 是 | AJ60: 《股权管理办法》第五十七条、《操作规则》第六十三条 | AK60: 总部财务部
C61: 企业经营管理合法合规 | E61: 股权变动导致控制权转移或失去控股地位时，未妥善处理职工安置、债权债务使用问题；增资扩股导致国有股东失去控股地位，或对重要子企业控制权转移事项未按规定审批，导致国有权益受损。 | F61: 公开渠道查询央企案例：存在增资扩股后“控股不控权”导致国有股东无法有效行使控制权、对无法有效控制的企业进场挂牌处置，以及股权转让余款难以收回等问题。 | G61: 24.控制权转移事项专项审核 | H61: 对增资扩股导致控制权转移的事项进行重点审核，确保符合公司战略并妥善处理相关事宜。 | I61: 股权投资及产权管理－20.控制权转移事项专项审核－控制措施01 | J61: 各级单位业务部门牵头，在控制权转移方案提交决策前： 1.取得债权人书面同意； 2.职代会审议职工安置方案； 3.涉及土地使用权、探矿权采矿权的，取得自然资源部门预审或处置批复。 控制权转移须在取得总部书面意见后方可履行董事会、股东会程序。 | L61: √ | R61: √ | S61: √ | T61: 线下管控 | V61: 1.增资扩股方案（含控制权影响分析）；2.债权人意见函；3.职工安置方案；4.土地使用权处置批复 | W61: 各级单位-业务管理部门-投资管理岗；各级单位-财务部-资产产权管理岗；各级单位-组织部-用工管理岗 | X61: 每年 | Y61: 抽查 | AA61: 每年 | AB61: 抽查 | AH61: 是 | AI61: 是 | AJ61: 国网（财/2）198－2025《国家电网有限公司股权管理办法》第五十五条 | AK61: 总部财务部；总部组织部
H62: 对增资扩股导致控制权转移的事项进行重点审核，确保符合公司战略并妥善处理相关事宜。 | I62: 股权投资及产权管理－20.控制权转移事项专项审核－控制措施02 | J62: 各级单位财务部在收到控制权转移增资方案后按照决策层级决策： 1.失去控制权或重要子企业，报国资委； 2.其他总部管理项目（投资额≥5000万元或层级超限），报总部董事长专题会或董事会； 3.其余由二级单位“三重一大”决策。总部管理项目由持股比例最大的单位逐级上报，涉及多家二级单位的需附各方决策资料。 | L62: √ | M62: √ | R62: √ | S62: √ | T62: 线下管控 | V62: 总部管理项目审批文件 | W62: 各级单位-财务部-资产产权管理岗；各级单位-业务管理部门-经办人 | X62: 每年 | Y62: 抽查 | AA62: 每年 | AB62: 抽查 | AH62: 是 | AI62: 是 | AJ62: 国网（财/2）198－2025《国家电网有限公司股权管理办法》第五十五、六十九、七十二条 | AK62: 总部财务部
C63: 企业经营管理合法合规 | D63: 12.终止清算项目管理 | E63: 擅自启动终止清算，清算方案未覆盖职工安置、债权债务、资产处置等关键事项，或清算组履职不到位、资产处置不规范。 | F63: 国有产权管理问题专项治理工作进展：存在吸收合并时未成立清算组导致后续注销程序受阻及清算义务履行不规范的问题。 | G63: 25.清算组成立与清算方案审核 | H63: 规范终止清算程序，确保清算组依法成立并制定完备的清算方案。 | I63: 股权投资及产权管理－21.清算组成立与清算方案审核－控制措施01 | J63: 各级单位业务部门拟启动终止清算时，逐项核查制度要求六项要求，并说明是否符合，留有核查依据。 | L63: √ | R63: √ | S63: √ | T63: 线下管控 | V63: 企业终止申请及决策文件 | W63: 各级单位-业务管理部门-经办人 | X63: 每年 | Y63: 抽查 | AA63: 每年 | AB63: 抽查 | AD63: 产权管理监督场景 | AE63: 实时 | AF63: 全量 | AH63: 是 | AI63: 是 | AJ63: 国网（财/2）198－2025《国家电网有限公司股权管理办法》第五十九、六十、六十三、七十、七十三条 | AK63: 总部财务部
I64: 股权投资及产权管理－21.清算组成立与清算方案审核－控制措施02 | J64: 财务部需核对清算报告金额与回收资产金额一致性。 | Q64: √ | T64: 线下管控 | V64: 银行回单 | W64: 各级单位-财务部-会计人员 | X64: 每年 | Y64: 抽查 | AA64: 每年 | AB64: 抽查 | AH64: 否 | AI64: 是 | AK64: 总部财务部
C65: 企业经营管理合法合规 | E65: 终止后未及时办理注销登记，或产权注销登记缺失，导致长期存续“僵尸企业”，形成监管盲区。 | F65: 国有产权管理问题专项治理工作进展：存在部分单位经营状态为存续、吊销、未注销的问题。 | G65: 26.产权与工商变更与注销登记 | H65: 及时办理终止清算后的产权和工商注销登记，防止形成“僵尸企业”。 | I65: 股权投资及产权管理－26.产权与工商变更与注销登记－控制措施01 | J65: 各级单位财务部门在取得工商注销登记证明后，5个工作日通过平台发起产权注销申请，上传工商注销证明、清算报告、股东会决议。总部管理项目的注销须附总部批复文件。 | Q65: √ | R65: √ | T65: 线上管控-已建 | U65: 智慧共享财务平台－资本在线运营－产权登记管理 | V65: 产权注销登记凭证 | W65: 各级单位-财务部-资产产权管理岗 | X65: 每年 | Y65: 抽查 | AA65: 每年 | AB65: 抽查 | AD65: 产权管理监督场景 | AE65: 实时 | AF65: 全量 | AH65: 是 | AI65: 是 | AJ65: 《股权管理办法》第六十三、一百三十二条；《参股管理暂行办法》第二十六条 | AK65: 总部财务部
I66: 股权投资及产权管理－22.产权与工商登记注销登记－控制措施02 | J66: 公司总部财务部定期对各单位注销登记办理情况进行专项检查，重点核查： 1.注销登记完成率； 2.超期未办理户数； 3.档案移交完整率。 | Q66: √ | R66: √ | T66: 线上管控-已建 | U66: 智慧共享财务平台－资本在线运营－产权登记管理 | V66: 1.清算财务报告及审计报告；2.上级单位/股东会确认文件；3.产权注销登记凭证 | W66: 总部-财务部-资产产权管理岗 | X66: 每年 | Y66: 抽查 | AA66: 每年 | AB66: 抽查 | AD66: 产权管理监督场景 | AE66: 实时 | AF66: 全量 | AH66: 否 | AI66: 是 | AJ66: 《股权管理办法》第六十三、一百三十二条、第一百三十八条；《参股管理暂行办法》第二十六条 | AK66: 总部财务部
I67: 股权投资及产权管理－22.产权与工商登记注销登记－控制措施03 | J67: 产权变更登记时，进场转让后，若转让方与公司不存在产权关系，可不提供修订后的公司章程，但须在申请文件中予以说明。 | M67: √ | T67: 线上管控-已建 | U67: 智慧共享财务平台－资本在线运营－产权登记管理 | V67: 产权登记申请 | W67: 各级单位-财务部-资产产权管理岗 | X67: 每年 | Y67: 抽查 | AA67: 每年 | AB67: 抽查 | AH67: 否 | AI67: 是 | AK67: 总部财务部
I68: 股权投资及产权管理－22.产权与工商登记注销登记－控制措施04 | J68: 涉及瑕疵产权问题需在产权登记发起请示文件中说明解决瑕疵的处理方式、决策情况。 | M68: √ | T68: 线上管控-已建 | U68: 智慧共享财务平台－资本在线运营－产权登记管理 | V68: 决策文件 | W68: 各级单位-财务部-资产产权管理岗 | X68: 每年 | Y68: 抽查 | AA68: 每年 | AB68: 抽查 | AH68: 否 | AI68: 是 | AK68: 总部财务部
B69: 2.股权项目运营管理 | C69: 企业经营管理合法合规、资金资产安全 | D69: 6.股东权利行使与公司治理管理 | E69: 在控股企业中因治理条款设置不当（如小股东一票否决权、轮流选派关键岗位等）或行使权力不力，导致控股股东意志无法贯彻，重大事项决策权旁落，国有资产面临失控风险。 | F69: 违规挂靠专项检查：存在违规挂靠和假冒国企的问题。 公开渠道查询央企案例：存在“控股不控权”问题，部分控股企业无法实现有效控制等问题。 年度财务决算批复问题清单：部分企业存在可能损害国有权益的情形。 | G69: 9.控股企业股东权利行使保障控制 | H69: 规范股东权利的行使，严格贯彻执行国资监管及公司关于股权投资、经营管理的负面清单，建立有效的识别、监控和处置机制，严禁挂靠经营、代持股权等违规行为，确保各级单位严格按照国家法律法规、公司规章制度及公司章程的规定，维护国有股东合法权益。 | I69: 股权投资及产权管理－9.控股企业股东权利行使保障控制－控制措施01 | J69: 各单位企管部负责制定《股东权利行使规范》，明确不同事项的决策层级、职责分工和管理流程，并在规范中明确因外部股东增减资等行为导致我方股权重大变化时，派出人员须事先履行内部决策程序后方可发表意见。 | O69: √ | T69: 线下管控 | V69: 股东权利行使规范 | W69: 各级单位-企管部-经办人员；各二级单位-企管部-经办人员 总部-企管部-经办人员 | X69: 每年 | Y69: 抽查 | AA69: 每年 | AB69: 抽查 | AH69: 是 | AI69: 是 | AJ69: 国网（财/2）198－2025《国家电网有限公司股权管理办法》 | AK69: 总部企管部
I70: 股权投资及产权管理－9.控股企业股东权利行使保障控制－控制措施02 | J70: 定期排查损害国有股权权益事项，重点关注： 1.国有股东合计超50%，但为国有参股或无实际控制人企业； 2.国有股东与非国有股东同为第一大股东，但为国有参股或无实际控制人企业； 3.单一国有股东持股比例在33%-50%之间且为第一大股东，但明确为参股企业； 4.上市公司国有股东持股比例低于30%、非上市公司国有股东持股比例低于33%，其他股东持股比例较为接近，但明确为国有实际控制企业等事项。 | R70: √ | T70: 线下管控 | V70: 国有权益损害排查报告 | W70: 各二级单位-财务部-资产产权管理岗；各二级单位-企管部-经办人员；总部-财务部-资产产权管理岗； 总部-企管部-经办人员 | X70: 每年 | Y70: 抽查 | AA70: 每年 | AB70: 抽查 | AH70: 否 | AI70: 是 | AK70: 总部财务部；总部企管部
E71: 未向控股企业派出董事或派出人员履职不力，导致小股东控制资金调动、干预财务管理。 | F71: 4.公开渠道查询央企案例：存在高管履职不到位，不参与重大事项决策，不了解公司实际运行等问题。 | G71: 10.派出人员资质及履职控制 | H71: 确保依法合规向控股企业派出董事或关键管理人员，并建立履职考核与问责机制，防止小股东越权干预。 | I71: 股权投资及产权管理－10.派出人员资质及履职控制－控制措施01 | J71: 控股企业派出的董事、监事及高级管理人员，具备以下资格： 1.具有经济管理、法律、技术、财务等相关专业中级及以上专业技术职称； 2.在公司中层及以上管理岗位任职满三年； 3.过去五年内未在任何任职机构受到重大内部纪律处分，亦未受到重大行政处罚或刑事处罚； 4.与派驻企业不存在妨碍其独立履行职责的关联关系。 董事会提名委员会应对董事、高管候选人进行任职资格前置审查，并留存审查记录。 | R71: √ | T71: 线下管控 | V71: 1.董事、监事、高级管理人员派出名单； 2.资格审查记录 | W71: 各级单位-组织部-干部管理岗； | X71: 每年 | Y71: 抽查 | AA71: 每年 | AB71: 抽查 | AH71: 否 | AI71: 是 | AJ71: 国网（财/2）198－2025《国家电网有限公司股权管理办法》 | AK71: 总部财务部；总部组织部
A72: 股权投资及产权管理 | B72: 2.股权项目运营管理 | C72: 企业经营管理合法合规、资金资产安全 | D72: 6.股东权利行使与公司治理管理 | I72: 股权投资及产权管理－10.派出人员资质及履职控制－控制措施02 | J72: 控股企业派出董事、监事、高级管理层不得未经批准兼任本企业所出资企业或者其他企业的领导职务，经批准兼职的，组织部每年核查领取薪酬及其他收入。 | R72: √ | T72: 线下管控 | V72: 派出人员清单 | W72: 各级单位-派出人员； 各级单位-组织部-干部管理岗 | X72: 每年 | Y72: 抽查 | AA72: 每年 | AB72: 抽查 | AH72: 否 | AI72: 是 | AK72: 总部财务部；总部组织部
I73: 股权投资及产权管理－10.派出人员资质及履职控制－控制措施03 | J73: 派出人员按照授权清单，参加被投资企业股东会、董事会，发起议题审议流程，相关业务部门、法律部门在线出具审核意见，经授权领导批准后形成正式表决意见，并据此在会议上投票表决，确保派出人员表决意见经规范审核与授权批准，投票表决有据可依、过程可追溯。 | L73: √ | T73: 线下管控 | V73: 1.授权清单； 2.事项审批单； 3.决议文件。 | W73: 各级单位-派出人员； 各级单位-组织部-干部管理岗 | X73: 每年 | Y73: 抽查 | AA73: 每年 | AB73: 抽查 | AH73: 是 | AI73: 是 | AJ73: 国网（财/2）198－2025《国家电网有限公司股权管理办法》 | AK73: 总部财务部；总部组织部
I74: 股权投资及产权管理－10.派出人员资质及履职控制－控制措施04 | J74: 各单位组织部每季度开展派出人员履职评价，重点关注缺席率、反对票数量及独立意见发表情况。 | S74: √ | T74: 线下管控 | V74: 派出人员履职报告 | W74: 各级单位-派出人员； 各级单位-组织部-经办人员 | X74: 每年 | Y74: 抽查 | AA74: 每年 | AB74: 抽查 | AH74: 否 | AI74: 是 | AK74: 总部财务部；总部组织部
C75: 资金资产安全 | E75: 未建立控股企业运行监测机制，未能及时发现经营异常和风险隐患。 | F75: 55.战新产业单位投资管控不到位：存在未及时发现实际建设与建设方案中提出的定位功能预期相差较大问题。 55.战新产业单位投资管控不到位：存在重点任务推进不力，未有效监测重点任务完成进度等问题。 | G75: 11.重大事项监测 | H75: 确保实现对重大事项经营异常和风险隐患的及时发现、预警与处置。 | I75: 股权投资及产权管理－11.重大事项监测－控制措施01 | J75: 各单位建立股东会、董事会重大事项决策台账，动态跟踪决议执行进展，每季度更新台账并报总部备案，确保重大事项决策执行过程可追溯、可监控。 | M75: √ | T75: 线下管控 | V75: 重大事项决策台账 | W75: 各单位-综合管理部-经办人员 | X75: 每年 | Y75: 抽查 | AA75: 每年 | AB75: 抽查 | AH75: 是 | AI75: 是 | AJ75: 国网（财/2）198－2025《国家电网有限公司股权管理办法》 | AK75: 总部财务部
I76: 股权投资及产权管理－11.重大事项监测－控制措施02 | J76: 各二级单位每年根据本单位批复的功能定位，对“无关多元”“多层架构”“控股不控权”“虚假控股”“违规挂靠”“靠企吃企”情况进行核查。 | M76: √ | S76: √ | T76: 线下管控 | V76: 业务功能定位排查文件 | W76: 各二级单位-财务部-资产产权管理岗；各二级单位-业务部门-经办人 | X76: 每年 | Y76: 抽查 | AA76: 每年 | AB76: 抽查 | AH76: 否 | AI76: 是 | AK76: 总部财务部
I77: 股权投资及产权管理－11.重大事项监测－控制措施03 | J77: 对分期出资或按进度拨付资金的项目，将下一期资金拨付与本阶段业务是否符合功能定位挂钩，不符合要求的暂缓拨付，直至整改完成。 | M77: √ | R77: √ | T77: 线下管控 | V77: 出资申请 | W77: 各二级单位-财务部-会计人员； | X77: 每年 | Y77: 抽查 | AA77: 每年 | AB77: 抽查 | AH77: 否 | AI77: 是 | AK77: 总部财务部
C78: 企业经营管理合法合规、资金资产安全 | E78: 对持有上市公司股权的市值管理不当，未及时关注股价异常波动或未按规定履行信息披露义务，导致国有股权价值受损或引发监管风险。 市值管理脱离提升上市公司质量的基础，存在操纵股价、虚假披露等违规风险。 | F78: 公开渠道查询央企案例：存在经证监局调查部分上市公司收到当地证监局警示未按规定进行信息披露等问题。 | G78: 12.上市公司市值管理 | H78: 规范开展上市公司市值管理，确保公司内在价值合理反映、股价平稳运行、投资者预期稳定、合规风控全程到位。 | I78: 股权投资及产权管理－12.上市公司市值管理－控制措施01 | J78: 各上市公司的二级单位应于每年1月10日前向总部报送控股上市公司年度市值管理方案，战新产业单位相关部门同步报送国网产业部，内容包括：提质增效、并购重组、公司治理、信息披露、回购股份、现金分红、股权激励、投资者关系维护等，不含上市公司未公开披露信息的上一年总结及下一年安排。 | M78: √ | S78: √ | T78: 线上管控-已建 | U78: 智慧共享财务平台－资本在线运营－上市公司管理 | V78: 1.控股上市公司年度市值管理方案； 2.资本运作计划。 | W78: 各二级单位-财务部-经办人员；总部-财务部-经办人员；战新产业单位-相关部门-经办人员；总部-产业部-经办人员 | X78: 每年 | Y78: 抽查 | AA78: 每年 | AB78: 抽查 | AH78: 是 | AI78: 是 | AJ78: 《国家电网有限公司控股上市公司管理办法》实施细则（2026）二 | AK78: 总部财务部；总部产业部
I79: 股权投资及产权管理－12.上市公司市值管理－控制措施02 | J79: 各二级单位财务部基于自身定位和发展需要，动态梳理本单位内拟独立上市或可注入系统内存量上市公司的优质资产，有资本运作需求的，与总部财务部及时对接资本运作计划，战新产业单位同步报送国网产业部。 | M79: √ | R79: √ | T79: 线上管控-已建 | U79: 智慧共享财务平台－资本在线运营－上市公司管理 | V79: 资本运作计划 | W79: 各二级单位-财务部-经办人员； | X79: 每年 | Y79: 抽查 | AA79: 每年 | AB79: 抽查 | AH79: 是 | AI79: 是 | AJ79: 国网（财/2）198－2025《国家电网有限公司股权管理办法》 | AK79: 总部财务部
I80: 股权投资及产权管理－12.上市公司市值管理－控制措施03 | J80: 各上市公司业务管理部门结合自身情况，综合运用下列方式进行市值管理： 1.并购重组；2.股权激励、员工持股计划；3.现金分红；4.投资者关系管理；5.信息披露；6.股份回购；7.其他合法合规方式。 上市公司控股股东单位及上市公司董事、高级管理人员作为市值管理参与方，可以运用下列方式进行市值管理： 1.实施股份增持计划；2.自愿延长股份锁定期；3.自愿终止减持计划；4.承诺不减持股份；5.其他合法合规方式。 | M80: √ | T80: 线下管控 | V80: 控股上市公司年度市值管理方案 | W80: 各上市公司-业务管理部门-经办人员 | X80: 每年 | Y80: 抽查 | AA80: 每年 | AB80: 抽查 | AH80: 是 | AI80: 是 | AJ80: 国网（财/2）1147-2025《国家电网有限公司控股上市公司管理办法 》第四十八条、第四十九条 | AK80: 总部财务部
A81: 股权投资及产权管理 | B81: 2.股权项目运营管理 | C81: 企业经营管理合法合规、资金资产安全 | D81: 6.股东权利行使与公司治理管理 | E81: 对持有上市公司股权的市值管理不当，未及时关注股价异常波动或未按规定履行信息披露义务，导致国有股权价值受损或引发监管风险。 市值管理脱离提升上市公司质量的基础，存在操纵股价、虚假披露等违规风险。 | F81: 公开渠道查询央企案例：存在经证监局调查部分上市公司收到当地证监局警示未按规定进行信息披露等问题。 | G81: 12.上市公司市值管理 | H81: 规范开展上市公司市值管理，确保公司内在价值合理反映、股价平稳运行、投资者预期稳定、合规风控全程到位。 | I81: 股权投资及产权管理－12.上市公司市值管理－控制措施04 | J81: 各上市公司在发起重大事项时配合填写内幕信息知情人档案及重大事项进程备忘录；不得提前泄露信息或非法要求上市公司提供未公开信息。 上市公司业务管理部门优化年度报告结构与呈现形式，如有差错更正，各上市公司发布信息披露差错更正公告当日应向二级单位及总部财务部报告，由二级单位对上市公司予以考核。 | M81: √ | S81: √ | T81: 线上管控-已建 | U81: 智慧共享财务平台－资本在线运营－上市公司管理 | V81: 1.信息披露报告； 2.信息披露差错更正公告。 | W81: 各上市公司股东单位-相关部门-经办人员；各上市公司-业务管理部门-经办人员 | X81: 每年 | Y81: 抽查 | AA81: 每年 | AB81: 抽查 | AH81: 是 | AI81: 是 | AJ81: 《国家电网有限公司控股上市公司管理办法》实施细则（2026五 | AK81: 总部财务部
I82: 股权投资及产权管理－12.上市公司市值管理－控制措施05 | J82: 上市公司或拟上市公司业务管理部门在重大事项发生后，应立即向相关二级单位报告，二级单位财务部在收到报告1小时之内向总部财务部报告事项、原因及处置方案，当日正式报送书面材料。二级单位及时更新应对处置进展及问责整改情况，重要信息于事项完成当日报送至总部财务部。 | M82: √ | S82: √ | T82: 线上管控-已建 | U82: 智慧共享财务平台－资本在线运营－上市公司管理 | V82: 1.重大事项报告； 2.重要信息备案。 | W82: 各上市公司-业务管理部门-经办人员；各二级单位-财务部-经办人员；总部财务部-经办人员 | X82: 每年 | Y82: 抽查 | AA82: 每年 | AB82: 抽查 | AH82: 是 | AI82: 是 | AJ82: 国网（财/2）1147-2025《国家电网有限公司控股上市公司管理办法 》第七十四条、第七十五条、第七十六条、第七十七条、第七十八条 | AK82: 总部财务部
I83: 股权投资及产权管理－12.上市公司市值管理－控制措施06 | J83: 二级单位业务管理部门开展对控股上市公司市值管理的考核，与二级单位一体化管理的上市公司对相关业务部门予以考核，考核标准重点关注经营质效、合规管理、股价增长、信披质量、现金分红、机构投资者占比、投资者关系管理等，后续指标调整情况及年度考核结果，于指标及结果确定后2个工作日内报送总部财务部，战新产业单位相关部门同步报送国网产业部。 | L83: √ | S83: √ | T83: 线下管控 | V83: 控股上市公司市值管理考核文件 | W83: 各二级单位-业务管理部门-经办人员； 总部-财务部-经办人员；战新产业单位-相关部门-经办人员；总部-产业部-经办人员 | X83: 每年 | Y83: 抽查 | AA83: 每年 | AB83: 抽查 | AH83: 是 | AI83: 是 | AJ83: 《国家电网有限公司控股上市公司管理办法》实施细则（2026）一 | AK83: 总部财务部；总部产业部
I84: 股权投资及产权管理－12.上市公司市值管理－控制措施07 | J84: 上市公司业务管理部门通过系统自动获取外部股票系统数据，监测上市公司市值股票价格异常波动。 | R84: √ | S84: √ | T84: 线上管控-待建 | U84: 智慧共享财务平台－资本在线运营－上市公司管理 | V84: 系统预警记录 | W84: 各上市公司-业务管理部门-经办人员 | X84: 每年 | Y84: 抽查 | AA84: 每年 | AB84: 抽查 | AD84: 股权数据动态监督场景 | AE84: 实时 | AF84: 全量 | AH84: 否 | AI84: 是 | AJ84: 《国家电网有限公司控股上市公司管理办法》实施细则（2026）二 | AK84: 总部财务部
B85: 4.参股股权管理 | C85: 资金资产安全 | D85: 13.参股企业运营管理 | E85: 参股企业章程中未明确各治理主体权责边界，或未约定分红权、关联交易、否决权等关键事项，导致国有股东权益无法通过公司治理得到保障。 | F85: 55.战新产业单位投资管控不到位：存在对参股公司经营管理参与度不高，只投不管，固有股东权益无法保障。 | G85: 27.参股企业治理机制设置 | H85: 规范搭建参股企业治理机制设置，确保权责边界清晰、治理架构健全、重大事项可控、投资权益有效保障。 | I85: 参股企业运营管理－23.参股企业治理机制设置－控制措施01 | J85: 各级单位财务部应建立参股经营投资台账，明确具体负责部门，掌握参股企业基本情况；并将存量无实际控制人且为第一大股东的参股企业纳入重要参股企业名单报总部备案，确保每个参股投资项目可追溯、可监控。 | M85: √ | R85: √ | T85: 线上管控-已建 | U85: 智慧共享财务平台－资本在线运营 | V85: 参股经营投资台账 | W85: 各级单位-财务部-投后管理岗 | X85: 每年 | Y85: 抽查 | AA85: 每年 | AB85: 抽查 | AD85: 参股经营投资合规性监督场景 | AE85: 实时 | AF85: 全量 | AH85: 是 | AI85: 是 | AJ85: 国网（财/2）198－2025《国家电网有限公司股权管理办法》第九十七条 | AK85: 总部财务部
A86: 股权投资及产权管理 | B86: 4.参股股权管理 | I86: 参股企业运营管理－23.参股企业治理机制设置－控制措施02 | J86: 各参股企业与其他股东协商，参与公司章程制定，明确股东会、董事会的议事规则和决策权限，确保国有股东依照法律法规和公司章程规范行使股东权利、履行股东义务。 | O86: √ | T86: 线下管控 | V86: 1.公司章程； 2.议事规则。 | W86: 各参股单位-企管部-经办人员 | X86: 每年 | Y86: 抽查 | AA86: 每年 | AB86: 抽查 | AH86: 是 | AI86: 是 | AJ86: 国网（财/2）198－2025《国家电网有限公司股权管理办法》第九十七条 | AK86: 总部企管部
I87: 参股企业运营管理－23.参股企业治理机制设置－控制措施03 | J87: 各参股企业通过公司章程或股东协议明确我方提名的董事、监事及高级管理人员的席位数量，确保至少推荐1名董事和1名专职高级管理人员参与参股企业日常经营管理；对于无实控人重要参股企业，同时选派董事和高级管理人员。 | L87: √ | R87: √ | T87: 线下管控 | V87: 1.股权协议； 2.公司章程； 3.派出人员名单 | W87: 各参股单位-组织部-经办人员 | X87: 每年 | Y87: 抽查 | AA87: 每年 | AB87: 抽查 | AH87: 否 | AI87: 是 | AJ87: 国网（财/2）198－2025《国家电网有限公司股权管理办法》第一百一十六、一百一十八条 | AK87: 总部组织部
I88: 参股企业运营管理－23.参股企业治理机制设置－控制措施04 | J88: 各参股企业对派出董事/股东代表按年度办理固定授权，确保年度常规事项授权规范、权限清晰、审核合规。 | L88: √ | T88: 线上管控-已建 | U88: 经法系统 | V88: 年度授权文件 | W88: 各参股单位-组织部-经办人员 | X88: 每年 | Y88: 抽查 | AA88: 每年 | AB88: 抽查 | AD88: 参股经营投资合规性监督场景 | AE88: 实时 | AF88: 全量 | AH88: 是 | AI88: 是 | AJ88: 国网（财/2）198－2025《国家电网有限公司股权管理办法》第九十七条 | AK88: 总部组织部
C89: 资金资产安全 | E89: 未按规定向参股企业派出董事、监事或关键管理人员，或派出人员履职能力不足、缺乏考核约束，导致无法及时获取参股企业经营状况，无法有效行使股东权利。 | G89: 28.参股企业派出人员管理 | H89: 确保派出人员合规行使股东权利、参与决策，防止因人员管理缺位导致股东权益受损或风险扩大。 | I89: 参股企业运营管理－24.参股企业派出人员管理－控制措施02 | J89: 派出人员原则上应担任参股企业的董事、监事或财务总监等关键监督职位，不得仅挂虚职。禁止派出人员同时在同一参股企业担任不相容职务（如董事兼任监事）。同一人员同时担任参股企业派出岗位的数量不得超过5家，以保证履职质量 | T89: 线下管控 | V89: 派出人员清单 | W89: 各级单位-组织部-干部管理岗 | X89: 每年 | Y89: 抽查 | AA89: 每年 | AB89: 抽查 | AH89: 否 | AI89: 是 | AK89: 总部组织部
I90: 参股企业运营管理－24.参股企业派出人员管理－控制措施03 | J90: 派出前须经公司财务部、组织部联合审核任职资格，派出人员名单及拟任职位须形成书面议案，报公司分管领导审批，并抄送资产处、会计处备案。派出后每半年提交履职报告，未达到任职要求或违规者及时撤换。 | T90: 线下管控 | V90: 派出人员清单 | W90: 各二级单位-组织部-干部管理岗；各二级单位-财务部-资产产权管理岗；各二级单位-财务部-会计人员 | X90: 每年 | Y90: 抽查 | AA90: 每年 | AB90: 抽查 | AH90: 否 | AI90: 是 | AK90: 总部组织部
C91: 资金资产安全 | E91: 将公司字号、经营资质、特许经营权违规提供给参股企业使用。 | F91: 公开渠道查询央企案例：存在违规使用央企字号等问题。 | G91: 29.字号与资质使用管控 | H91: 加强无形资产管理，严禁将公司字号、经营资质和特许经营权等提供给参股企业或无产权关系企业使用，维护公司权益。 | I91: 股权投资及产权管理－25.字号与资质使用管控－控制措施01 | J91: 各级单位法律部门在参股投资协议、公司章程等法律文件中明确约定，参股企业及其再投资企业不得使用“国网”或“国网”字样、各级单位字号、经营资质和特许经营权； 失去控制权时标的企业须在工商变更后30日内完成字号及工商变更，确保参股企业及其再投资企业规范使用字号和资质，防止国有资产流失。 | O91: √ | T91: 线上管控-已建 | U91: 智慧共享财务平台－资本在线运营 | V91: 1.投资协议； 2.公司章程。 | W91: 各级单位-法律部-法务人员 | X91: 每年 | Y91: 抽查 | AA91: 每年 | AB91: 抽查 | AD91: 参股经营投资合规性监督场景 | AE91: 实时 | AF91: 全量 | AH91: 是 | AI91: 是 | AJ91: 国网（财/2）198－2025《国家电网有限公司股权管理办法》第一百二十六条 | AK91: 总部法律部
F92: 公开渠道查询央企案例：存在违规使用央企字号等问题。 | I92: 股权投资及产权管理－25.字号与资质使用管控－控制措施02 | J92: 各级单位专业部门对确需授权参股企业使用产品注册商标的情况，提出专项方案（明确授权范围、期限、使用条件及市场公允价格），履行“三重一大”决策程序后，经总部公司审批方可实施 | L92: √ | R92: √ | T92: 线下管控 | V92: 专项方案 | W92: 各级单位-专业部门-经办人员；总部-企管部-经办人员 | X92: 每年 | Y92: 抽查 | AA92: 每年 | AB92: 抽查 | AD92: 参股经营投资合规性监督场景 | AE92: 实时 | AF92: 全量 | AH92: 是 | AI92: 是 | AJ92: 国网（财/2）198－2025《国家电网有限公司股权管理办法》第一百二十六条 | AK92: 总部业务管理部门；总部企管部
F93: 公开渠道查询央企案例：存在违规使用央企字号等问题。 | I93: 股权投资及产权管理－25.字号与资质使用管控－控制措施03 | J93: 各级单位专业部门每年至少开展一次专项检查发现违规使用字号、资质情况时，立即向相关企业发出正式函告，限期整改（如变更工商登记、停止使用等），并依据协议追究违约责任；拒不整改的，采取法律措施，确保违规行为得到及时纠正与追责。 | R93: √ | S93: √ | T93: 线下管控 | V93: 专项检查报告 | W93: 各级单位-企管部-经办人员 | X93: 每年 | Y93: 抽查 | AA93: 每年 | AB93: 抽查 | AH93: 是 | AI93: 是 | AJ93: 国网（财/2）198－2025《国家电网有限公司股权管理办法》第一百二十六条 | AK93: 总部企管部
F94: 公开渠道查询央企案例：存在违规使用央企字号等问题。 | I94: 股权投资及产权管理－25.字号与资质使用管控－控制措施04 | J94: 各级单位产权转让或增资的相关责任部门在信息披露中，明确将字号变更、资质停止使用作为交易条件，并在交易合同中约定工商变更时限及违约责任。 | O94: √ | T94: 线下管控 | V94: 产权转让或增资协议 | W94: 各级单位-相关部门-经办人员 | X94: 每年 | Y94: 抽查 | AA94: 每年 | AB94: 抽查 | AH94: 是 | AI94: 是 | AJ94: 国网（财/2）198－2025《国家电网有限公司股权管理办法》第一百二十六条 | AK94: 总部企管部
C95: 企业经营管理合法合规、资金资产安全 | E95: 对参股企业“只投不管”，未有效行使股东权利，导致国有权益受损。 | F95: 55.战新产业单位投资管控不到位：存在对参股公司经营管理参与度不高，只投不管，重大事项未召开董事会、股东会进行决策等问题。 55.战新产业单位投资管控不到位：存在对参股企业经营监管不到位，对参股企业再次投建公司、重大项目投资等事项未有效管控等问题。 | G95: 30.重大事项决策 | H95: 通过派出人员充分参与参股企业重大事项决策，有效维护国有股东权益。 | I95: 股权投资及产权管理－26.重大事项决策－控制措施01 | J95: 各二级单位在投资协议、公司章程中明确约定重大事项清单（至少包括：章程修订、名称变更、股权投资、股权变动、重大融资、重大担保、对外借款、重大关联交易、重大资产处置、高管变动及薪酬激励、主营业务调整、财务预决算方案等），并规定金额达到参股企业净资产30%或3000万元及以上的事项须提交股东会审议。 | O95: √ | T95: 线下管控 | V95: 1.重大事项清单； 2.党委会、总办会、股东会、董事会会议记录 | W95: 各二级单位-法律部-法务人员；各级单位-企管部-经办人员 | X95: 每年 | Y95: 抽查 | AA95: 每年 | AB95: 抽查 | AH95: 是 | AI95: 是 | AJ95: 国网（财/2）198－2025《国家电网有限公司股权管理办法》第一百二十一条 | AK95: 总部法律部；总部企管部
A96: 股权投资及产权管理 | B96: 4.参股股权管理 | I96: 股权投资及产权管理－26.重大事项决策－控制措施02 | J96: 各级单位派出董事/监事在参股企业审议重大事项时，应通过业务归口部门征求相关职能部门意见，在履行内部决策程序后规范参与表决，并定期将会议决议等资料报业务归口部门备案。 | L96: √ | R96: √ | T96: 线下管控 | V96: 1.党委会、总办会、股东会、董事会会议纪要。 | W96: 各级单位-专业部门-经办人员；各二级单位-组织部-经办人员 | X96: 每年 | Y96: 抽查 | AA96: 每年 | AB96: 抽查 | AH96: 是 | AI96: 是 | AJ96: 国网（财/2）198－2025《国家电网有限公司股权管理办法》第一百二十一条 | AK96: 总部组织部
I97: 股权投资及产权管理－26.重大事项决策－控制措施03 | J97: 在参股企业通过增资扩股引入其他投资者时，应按国有资产监督管理规定就资产评估、进场交易等发表明确意见。 | L97: √ | M97: √ | T97: 线上管控-已建 | U97: 智慧共享财务平台－资本在线运营 | V97: 1.股东会； 2.参股经营投资台账。 | W97: 各二级单位-相关部门-经办人员 | X97: 每年 | Y97: 抽查 | AA97: 每年 | AB97: 抽查 | AH97: 是 | AI97: 是 | AJ97: 国网（财/2）198－2025《国家电网有限公司股权管理办法》第一百二十一条 | AK97: 总部财务部
I98: 股权投资及产权管理－26.重大事项决策－控制措施04 | J98: 各级单位专业部门建立参股企业再投资事项台账，对金额达净资产10%或1000万元及以上的再投资事项，督促直接参股企业每季度报送情况，并于每年12月底前报总部。 | M98: √ | R98: √ | T98: 线下管控 | V98: 参股企业再投资事项台账 | W98: 各二级单位-业务管理部门-经办人员 | X98: 每年 | Y98: 抽查 | AA98: 每年 | AB98: 抽查 | AH98: 是 | AI98: 是 | AJ98: 国网（财/2）198－2025《国家电网有限公司股权管理办法》第一百二十三条 | AK98: 总部财务部
C99: 企业经营管理合法合规、会计信息真实完整 | E99: 未定期获取参股企业财务报表，或对异常财务情况未深入分析、及时报告，信息掌握不全。 | F99: 公开渠道查询央企案例：存在对参股企业财务监管不到位、国有股东未能有效行权履职等问题。 | G99: 31.财务报表获取与分析 | H99: 定期获取并分析参股企业财务报表，全面掌握其经营和财务情况，及时发现异常。 | I99: 股权投资及产权管理－27.财务报表获取与分析－控制措施01 | J99: 各级单位财务部门对获取的报表进行分析，重点关注盈利能力、偿债能力、现金流等关键指标，与历史数据及行业水平进行对比，确保参股企业财务状况得到有效监控。 | Q99: √ | S99: √ | T99: 线上管控-已建 | U99: 智慧共享财务平台－财务管理－财务报表 | V99: 参股企业定期财务报表 | W99: 各级单位-财务部-财务分析人员 | X99: 每年 | Y99: 抽查 | AA99: 每年 | AB99: 抽查 | AD99: 参股经营投资财务准确性监督场景 | AE99: 实时 | AF99: 全量 | AH99: 是 | AI99: 是 | AJ99: 国网（财/2）198－2025《国家电网有限公司股权管理办法》第一百二十四条 | AK99: 总部财务部
I100: 股权投资及产权管理－27.财务报表获取与分析－控制措施02 | J100: 各级单位财务部门会同业务部门对投资金额大、关联交易占比高、应收账款金额大或账龄长的参股企业，建立重点风险排查清单，每半年开展专项风险排查，排查结果报总部备案。发现重大风险业务部门须在30日内提出增资、改组、退出等处置方案；财务部同步将风险提示函报送总部。 | Q100: √ | R100: √ | S100: √ | T100: 线上管控-已建 | U100: 智慧共享财务平台－财务管理－财务报表 | V100: 1.重点风险排查清单； 2.专项风险排查报告。 | W100: 各级单位-财务部-财务分析人员；各级单位-业务部门-经办人员 | X100: 每年 | Y100: 抽查 | AA100: 每年 | AB100: 抽查 | AD100: 参股经营投资财务准确性监督场景 | AE100: 实时 | AF100: 全量 | AH100: 是 | AI100: 是 | AJ100: 国网（财/2）198－2025《国家电网有限公司股权管理办法》第一百二十四条 | AK100: 总部财务部
...

Sheet 业务流程步骤
A1: 会计 | B1: 会计 | C1: 预算 | D1: 预算 | E1: 股权 | F1: 股权 | G1: 资金 | H1: 资金
A2: 会计 | B2: 核算范围管理 | C2: 预算 | D2: 战略支撑 （事前） | E2: 股权 | F2: 1.股权投资项目储备 | G2: 资金 | H2: 银行账户开立
A3: 会计 | B3: 会计政策管理 | C3: 预算 | D3: 经营决策 （事前） | E3: 股权 | F3: 2.投资项目决策管理 | G3: 资金 | H3: 商户号开立
A4: 会计 | B4: 会计岗位管理 | C4: 预算 | D4: 资源分配 （事前） | E4: 股权 | F4: 3.股权投资项目计划预算管理 | G4: 资金 | H4: 数字钱包开立
A5: 会计 | B5: 收入核算管理 | C5: 预算 | D5: 执行控制 （事中） | E5: 股权 | F5: 4.股权投资项目实施管理 | G5: 资金 | H5: 银行账户变更
A6: 会计 | B6: 成本费用核算管理 | C6: 预算 | D6: 闭环管控 （事后） | E6: 股权 | F6: 5.股权投资项目后评价管理 | G6: 资金 | H6: 商户号变更
A7: 会计 | B7: 往来会计管理 | C7: 预算 | D7: 考核评价 （事后） | E7: 股权 | F7: 6.股东权利行使与公司治理管理 | G7: 资金 | H7: 数字钱包变更
A8: 会计 | B8: 总账会计管理 | E8: 股权 | F8: 7.股权优化清理管理 | G8: 资金 | H8: 账户使用-收入
A9: 会计 | B9: 会计档案管理 | E9: 股权 | F9: 8.分支机构管理 | G9: 资金 | H9: 账户使用-支付
E10: 股权 | F10: 9.股权转让项目管理 | G10: 资金 | H10: 账户使用-对账
E11: 股权 | F11: 10.股权划转项目管理 | G11: 资金 | H11: 账户使用-前置机数据管理
E12: 股权 | F12: 11.增资扩股项目管理 | G12: 资金 | H12: 账户使用-密钥
E13: 股权 | F13: 12.终止清算项目管理 | G13: 资金 | H13: 账户使用-印鉴
E14: 股权 | F14: 13.参股企业运营管理 | G14: 资金 | H14: 银行账户撤销
E15: 股权 | F15: 14.资产评估管理 | G15: 资金 | H15: 商户号撤销
G16: 资金 | H16: 数字钱包撤销
G17: 资金 | H17: 担保管理
G18: 资金 | H18: 人员管理

Sheet 关键控制点
A1: 会计 | B1: 预算 | C1: 股权 | D1: 资金 | F1: 原分类 | G1: 融合后 | H1: 业务领域 | I1: 主线
A2: 1.会计主体完整性管控 | B2: 1.规划目标与战略一致性审核 | C2: 1.股权投资项目提出合规性控制 | D2: 1.银行账户合规开立控制 | F2: 股权 | G2: 1.股权投资项目储备 | H2: 产权管理 | I2: 产权管理
A3: 2.账户完整性管控 | B3: 2.预算决策程序审核 | C3: 2.项目遴选控制控制 | D3: 2.银行账户办理监控控制 | F3: 股权 | G3: 2.投资项目决策管理 | H3: 产权管理 | I3: 核算范围
A4: 3.业务完整性管控 | B4: 3.资源配置精准性管控 | C4: 3.股权投资项目分级决策 | D4: 3.商户号合规开立控制 | F4: 股权 | G4: 3.股权投资项目计划预算管理 | H4: 产权管理 | I4: 预算管理
A5: 4.会计政策和会计估计分类管控和分级授权管理 | B5: 4.预算执行情况分析 | C5: 4.股权投资项目计划预算审批与下达 | D5: 4.商户号办理监控控制 | F5: 股权 | G5: 4.股权投资项目实施管理 | H5: 产权管理 | I5: 会计核算
A6: 5.会计政策和会计估计执行管控 | B6: 5.各会计科目、项目预算系统编制及控制 | C6: 5.投资协议签署 | D6: 5.数字钱包合规开立控制 | F6: 股权 | G6: 8.分支机构管理 | H6: 产权管理 | I6: 资金活动
A7: 6.会计政策和会计估计变更审批 | B7: 6.重点单项费用预算编制及控制 | C7: 6.产权与工商占有登记 | D7: 6.数字钱包监控控制 | F7: 股权 | G7: 7.股权优化清理管理 | H7: 产权管理 | I7: 监测预警
A8: 7.会计不相容岗位管控 | B8: 7.项目可研经济性、财务合规性检查 | C8: 7.实际出资控制 | D8: 7.银行账户变更及时性、必要性控制 | F8: 股权 | G8: 9.股权转让项目管理 | H8: 产权管理 | I8: 会计档案
A9: 8.会计岗位交接管控 | B9: 8.项目预算执行控制 | C9: 8.股权投资后评价 | D9: 8.商户号变更及时性、必要性控制 | F9: 股权 | G9: 10.股权划转项目管理 | H9: 产权管理
A10: 9.售电收入管控 | B10: 9.预算编制与输配电成本一致性审核 | C10: 9.控股企业股东权利行使保障控制 | D10: 9.数字钱包变更及时性、必要性控制 | F10: 股权 | G10: 11.增资扩股项目管理 | H10: 产权管理
A11: 10.非电收入管控 | B11: 10.投入产出分析评价 | C11: 10.派出人员资质及履职控制 | D11: 10.现金收费解缴控制 | F11: 股权 | G11: 12.终止清算项目管理 | H11: 产权管理
A12: 11.成本真实性管控 | B12: 11.指标体系科学性审核 | C12: 11.重大事项监测 | D12: 11.账户资金到账确认控制 | F12: 股权 | G12: 6.股东权利行使与公司治理管理 | H12: 产权管理
A13: 12.成本合规性、完整性管控 | C13: 12.上市公司市值管理 | D13: 12.应收票据可靠性、合规性管控 | F13: 股权 | G13: 13.参股企业运营管理 | H13: 产权管理
A14: 13.收入成本匹配性管控 | C14: 13.全级次股权优化整合 | D14: 13.资金支付审批权限控制 | F14: 股权 | G14: 14.资产评估管理 | H14: 产权管理
A15: 14.往来挂账规范性管控 | C15: 14.分支机构管控 | D15: 14.传统结算事前审批控制 | F15: 会计 | G15: 会计主体管理（原核算范围管理） | H15: 核算范围管理
A16: 15.往来清账及时性管控 | C16: 15.协议转让条件合规审查 | D16: 15.付款结算合规性控制 | F16: 会计 | G16: 会计政策管理 | H16: 核算范围管理
A17: 16.往来对账规范性管控 | C17: 16.协议转让价格控制 | D17: 16.应付票据合规性控制 | F17: 会计 | G17: 会计岗位管理 | H17: 核算范围管理
A18: 17.长期挂账款项管理 | C18: 17.进场交易受让方征集与审查 | D18: 17.保函合规性控制 | F18: 资金 | G18: 人员管理 | H18: 核算范围管理
A19: 18.坏账准备及往来款项处置管理 | C19: 18.进场交易价格监督 | D19: 18.银企对账及时性、准确性控制 | F19: 资金 | G19: 银行账户开立 | H19: 核算范围管理
A20: 19.关联交易协同管控 | C20: 19.转让协议合规性控制 | D20: 19.数字钱包“零余额”控制 | F20: 资金 | G20: 商户号开立 | H20: 核算范围管理
A21: 20.期末结账规范性管控 | C21: 20.外部划转条件审核 | D21: 20.委贷资金池税费控制 | F21: 资金 | G21: 数字钱包开立 | H21: 核算范围管理
A22: 21.银行账户余额准确性管控 | C22: 21.划转协议内容完整性审核 | D22: 21.前置机数据安全性控制 | F22: 资金 | G22: 银行账户变更 | H22: 核算范围管理
A23: 22.资产账实一致性核查 | C23: 22.增资扩股方案报批 | D23: 22.密钥新增配置控制 | F23: 资金 | G23: 商户号变更 | H23: 核算范围管理
A24: 23.期初调整规范性管控 | C24: 23.进场交易投资方遴选 | D24: 23.网银权限配置控制 | F24: 资金 | G24: 数字钱包变更 | H24: 核算范围管理
... A27: 26.无纸化存档管控 | C27: 26.产权与工商变更与注销登记 | D27: 26.密钥授权使用控制 | F27: 资金 | G27: 数字钱包撤销 | H27: 核算范围管理
C28: 27.参股企业治理机制设置 | D28: 27.密钥账实盘点一致性控制 | F28: 预算 | G28: 战略支撑 （事前） | H28: 预算管理
C29: 28.参股企业派出人员管理 | D29: 28.密钥交接手续规范性控制 | F29: 预算 | G29: 经营决策 （事前） | H29: 预算管理
C30: 29.字号与资质使用管控 | D30: 29.印鉴新增配置 | F30: 预算 | G30: 资源分配 （事前） | H30: 预算管理
C31: 30.重大事项决策 | D31: 30.印鉴变更合规性控制 | F31: 预算 | G31: 执行控制 （事中） | H31: 预算管理
C32: 31.财务报表获取与分析 | D32: 31.印鉴注销合规性控制 | F32: 会计 | G32: 收入核算管理 | H32: 会计核算
C33: 32.资产评估组织实施 | D33: 32.印鉴授权使用控制 | F33: 会计 | G33: 成本费用核算管理 | H33: 会计核算
C34: 33.资产评估核准与备案 | D34: 33.印鉴交接手续规范性控制 | F34: 会计 | G34: 往来会计管理 | H34: 会计核算
C35: 34.资产评估机构选择 | D35: 34.银行账户注销及时性、规范性控制 | F35: 资金 | G35: 账户使用-收入 | H35: 资金活动
C36: 35.资产评估报告使用 | D36: 35.商户号注销及时性、规范性控制 | F36: 资金 | G36: 账户使用-支付 | H36: 资金活动
D37: 36.数字钱包注销及时性、规范性控制 | F37: 资金 | G37: 账户使用-对账 | H37: 资金活动
D38: 37.无股权关系担保控制 | F38: 资金 | G38: 账户使用-前置机数据管理 | H38: 资金活动
D39: 38.超股权比例担保控制 | F39: 资金 | G39: 账户使用-密钥 | H39: 资金活动
D40: 39.超净资产比例担保控制 | F40: 资金 | G40: 账户使用-印鉴 | H40: 资金活动
D41: 40.金融子企业担保控制 | F41: 资金 | G41: 担保管理 | H41: 资金活动
D42: 41.担保履约控制 | F42: 会计 | G42: 总账会计管理 | H42: 监测预警
D43: 42.人员管理 | F43: 预算 | G43: 闭环管控 （事后） | H43: 监测预警
F44: 预算 | G44: 考核评价 （事后） | H44: 监测预警
F45: 股权 | G45: 5.股权投资项目后评价管理 | H45: 监测预警
F46: 会计 | G46: 会计档案管理 | H46: 会计档案
